Workbook

Sheet Base
A1: Start Date | B1: 43646 | M1: Start Date | N1: 43646 | AW1: =+AVERAGE(AV7:AV2000) -> 7.5234393 | AX1: =+_xlfn.STDEV.S(AV7:AV2000) -> 3.2215582
A2: End Date | M2: End Date
B4: YPFD AR Equity | N4: PAMP AR Equity | Y4: COME AR Equity | AJ4: TGSU2 AR Equity
A5: Dates | B5: CURRENT_EV_TO_T12M_EBITDA | C5: RETURN_ON_INV_CAPITAL | D5: ROC_WACC_RATIO | E5: TOT_DEBT_TO_TOT_CAP | F5: NET_DEBT_TO_EBITDA | G5: TOTAL_PAYOUT_RATIO | H5: EBITDA_MARGIN | I5: TRAIL_12M_OPER_MARGIN | J5: PX_LAST | K5: CUR_MKT_CAP | M5: Dates | N5: CURRENT_EV_TO_T12M_EBITDA | O5: RETURN_ON_INV_CAPITAL | P5: ROC_WACC_RATIO | Q5: TOT_DEBT_TO_TOT_CAP | R5: NET_DEBT_TO_EBITDA | S5: TOTAL_PAYOUT_RATIO | T5: EBITDA_MARGIN | U5: TRAIL_12M_OPER_MARGIN | V5: PX_LAST | W5: CUR_MKT_CAP | Y5: CURRENT_EV_TO_T12M_EBITDA | Z5: RETURN_ON_INV_CAPITAL | AA5: ROC_WACC_RATIO | AB5: TOT_DEBT_TO_TOT_CAP | AC5: NET_DEBT_TO_EBITDA | AD5: TOTAL_PAYOUT_RATIO | AE5: EBITDA_MARGIN | AF5: TRAIL_12M_OPER_MARGIN | AG5: PX_LAST | AH5: CUR_MKT_CAP | AJ5: CURRENT_EV_TO_T12M_EBITDA | AK5: RETURN_ON_INV_CAPITAL | AL5: ROC_WACC_RATIO | AM5: TOT_DEBT_TO_TOT_CAP | AN5: NET_DEBT_TO_EBITDA | AO5: TOTAL_PAYOUT_RATIO | AP5: EBITDA_MARGIN | AQ5: TRAIL_12M_OPER_MARGIN | AR5: PX_LAST | AS5: CUR_MKT_CAP
A6: =_xll.BDH(B$4,B$5:K$5,$B1,$B2,"Dir=V","Per=CW","Days=A","Dts=S","cols=11;rows=380") -> 43651 | B6: 4.195 | C6: 2.5756 | D6: 0.9766 | E6: 51.3139 | F6: 2.2602 | G6: #N/A N/A | H6: 28.122 | I6: 7.61 | J6: 76.105 | K6: 299330.7 | M6: =_xll.BDH(N$4,N$5:W$5,$B1,$B2,"Dir=V","Per=CW","Days=A","Dts=S","cols=11;rows=380") -> 43651 | N6: 3.6787 | O6: 22.1402 | P6: 1.2657 | Q6: 44.1192 | R6: 1.379 | S6: #N/A N/A | T6: 34.2185 | U6: 24.5123 | V6: 56.95 | W6: 106749.05 | Y6: =_xll.BDH(Y$4,Y$5:AH$5,$B1,$B2,"Dir=V","Per=CW","Days=A","Dts=H","cols=10;rows=380") -> 1.9589 | Z6: 39.2209 | AA6: 2.4212 | AB6: 5.9088 | AC6: 0.0882 | AD6: #N/A N/A | AE6: 22.8938 | AF6: 17.7275 | AG6: 0.563 | AH6: 7921.5494 | AJ6: =_xll.BDH(AJ$4,AJ$5:AS$5,$B1,$B2,"Dir=V","Per=CW","Days=A","Dts=H","cols=10;rows=380") -> 3.8987 | AK6: 48.6061 | AL6: 2.1113 | AM6: 38.9348 | AN6: 0.4827 | AO6: 195.1108 | AP6: 49.3598 | AQ6: 42.2735 | AR6: 114.514 | AS6: 98795.488 | AV6: EV/EBITDA Sectorial | AW6: Z Score | AX6: Q90 | AY6: Q75 | AZ6: Q50 | BA6: Q25 | BB6: Q10
A7: 43658 | B7: 4.1974 | C7: 2.5756 | D7: 0.9766 | E7: 51.3139 | F7: 2.2602 | G7: #N/A N/A | H7: 28.122 | I7: 7.61 | J7: 76.2 | K7: 299704.35 | M7: 43658 | N7: 3.7868 | O7: 22.1402 | P7: 1.2657 | Q7: 44.1192 | R7: 1.379 | S7: #N/A N/A | T7: 34.2185 | U7: 24.5123 | V7: 59.6 | W7: 111716.3 | Y7: 1.989 | Z7: 39.2209 | AA7: 2.4212 | AB7: 5.9088 | AC7: 0.0882 | AD7: #N/A N/A | AE7: 22.8938 | AF7: 17.7275 | AG7: 0.572 | AH7: 8048.9055 | AJ7: 4.2133 | AK7: 48.6061 | AL7: 2.1113 | AM7: 38.9348 | AN7: 0.4827 | AO7: 195.1108 | AP7: 49.3598 | AQ7: 42.2735 | AR7: 125.059 | AS7: 107892.46 | AU7: =+A7 -> 43658 | AV7: =+(Y7*AH7+N7*W7+B7*K7+AJ7*AS7)/(K7+W7+AH7) -> 5.1293803 | AW7: =+(AV7-$AW$1)/$AX$1 -> -0.74313696
A8: 43665 | B8: 4.1292 | C8: 2.5756 | D8: 0.9766 | E8: 51.3139 | F8: 2.2602 | G8: #N/A N/A | H8: 28.122 | I8: 7.61 | J8: 73.48 | K8: 289006.24 | M8: 43665 | N8: 3.6114 | O8: 22.1402 | P8: 1.2657 | Q8: 44.1192 | R8: 1.379 | S8: #N/A N/A | T8: 34.2185 | U8: 24.5123 | V8: 56.6 | W8: 106093 | Y8: 1.8386 | Z8: 39.2209 | AA8: 2.4212 | AB8: 5.9088 | AC8: 0.0882 | AD8: #N/A N/A | AE8: 22.8938 | AF8: 17.7275 | AG8: 0.527 | AH8: 7412.125 | AJ8: 4.0388 | AK8: 48.6061 | AL8: 2.1113 | AM8: 38.9348 | AN8: 0.4827 | AO8: 195.1108 | AP8: 49.3598 | AQ8: 42.2735 | AR8: 119.211 | AS8: 102847.41 | AU8: =+A8 -> 43665 | AV8: =+(Y8*AH8+N8*W8+B8*K8+AJ8*AS8)/(K8+W8+AH8) -> 4.98251 | AW8: =+(AV8-$AW$1)/$AX$1 -> -0.78872681
A9: 43672 | B9: 4.1242 | C9: 2.5756 | D9: 0.9766 | E9: 51.3139 | F9: 2.2602 | G9: #N/A N/A | H9: 28.122 | I9: 7.61 | J9: 73.28 | K9: 288219.61 | M9: 43672 | N9: 3.586 | O9: 22.1402 | P9: 1.2657 | Q9: 44.1192 | R9: 1.379 | S9: #N/A N/A | T9: 34.2185 | U9: 24.5123 | V9: 58 | W9: 108717.21 | Y9: 1.8206 | Z9: 39.2209 | AA9: 2.4212 | AB9: 5.9088 | AC9: 0.0882 | AD9: #N/A N/A | AE9: 22.8938 | AF9: 17.7275 | AG9: 0.521 | AH9: 7335.7114 | AJ9: 4.146 | AK9: 48.6061 | AL9: 2.1113 | AM9: 38.9348 | AN9: 0.4827 | AO9: 195.1108 | AP9: 49.3598 | AQ9: 42.2735 | AR9: 122.802 | AS9: 105945.95 | AU9: =+A9 -> 43672 | AV9: =+(Y9*AH9+N9*W9+B9*K9+AJ9*AS9)/(K9+W9+AH9) -> 5.0241913 | AW9: =+(AV9-$AW$1)/$AX$1 -> -0.77578858
A10: 43679 | B10: 4.0745 | C10: 2.5756 | D10: 0.9766 | E10: 51.3139 | F10: 2.2602 | G10: #N/A N/A | H10: 28.122 | I10: 7.61 | J10: 71.295 | K10: 280412.36 | M10: 43679 | N10: 3.4672 | O10: 22.1402 | P10: 1.2657 | Q10: 44.1192 | R10: 1.379 | S10: #N/A N/A | T10: 34.2185 | U10: 24.5123 | V10: 57.65 | W10: 108061.15 | Y10: 1.983 | Z10: 39.2209 | AA10: 2.4212 | AB10: 5.9088 | AC10: 0.0882 | AD10: #N/A N/A | AE10: 22.8938 | AF10: 17.7275 | AG10: 0.57 | AH10: 8023.4343 | AJ10: 4.1405 | AK10: 48.6061 | AL10: 2.1113 | AM10: 38.9348 | AN10: 0.4827 | AO10: 195.1108 | AP10: 49.3598 | AQ10: 42.2735 | AR10: 122.618 | AS10: 105787.05 | AU10: =+A10 -> 43679 | AV10: =+(Y10*AH10+N10*W10+B10*K10+AJ10*AS10)/(K10+W10+AH10) -> 4.9713662 | AW10: =+(AV10-$AW$1)/$AX$1 -> -0.79218594
A11: 43686 | B11: 4.1924 | C11: 2.5756 | D11: 0.9766 | E11: 51.3139 | F11: 2.2602 | G11: #N/A N/A | H11: 28.122 | I11: 7.61 | J11: 76 | K11: 298917.72 | M11: 43686 | N11: 3.6008 | O11: 22.1402 | P11: 1.2657 | Q11: 44.1192 | R11: 1.379 | S11: #N/A N/A | T11: 34.2185 | U11: 24.5123 | V11: 63.5 | W11: 119026.6 | Y11: 1.1831 | Z11: 39.2209 | AA11: 2.4212 | AB11: 5.9088 | AC11: 0.0882 | AD11: #N/A N/A | AE11: 22.8938 | AF11: 17.7275 | AG11: 0.56 | AH11: 4635.762 | AJ11: 4.4152 | AK11: 48.6061 | AL11: 2.1113 | AM11: 38.9348 | AN11: 0.4827 | AO11: 195.1108 | AP11: 49.3598 | AQ11: 42.2735 | AR11: 131.827 | AS11: 113732 | AU11: =+A11 -> 43686 | AV11: =+(Y11*AH11+N11*W11+B11*K11+AJ11*AS11)/(K11+W11+AH11) -> 5.1810481 | AW11: =+(AV11-$AW$1)/$AX$1 -> -0.72709884
A12: 43693 | B12: 3.792 | C12: 2.5756 | D12: 0.9766 | E12: 51.3139 | F12: 2.2602 | G12: #N/A N/A | H12: 28.122 | I12: 7.61 | J12: 60.02 | K12: 236066.34 | M12: 43693 | N12: 2.281 | O12: 22.1402 | P12: 1.2657 | Q12: 44.1192 | R12: 1.379 | S12: #N/A N/A | T12: 34.2185 | U12: 24.5123 | V12: 39.55 | W12: 74133.888 | Y12: 0.9184 | Z12: 39.2209 | AA12: 2.4212 | AB12: 5.9088 | AC12: 0.0882 | AD12: #N/A N/A | AE12: 22.8938 | AF12: 17.7275 | AG12: 0.425 | AH12: 3515.0284 | AJ12: 3.4771 | AK12: 48.6061 | AL12: 2.1113 | AM12: 38.9348 | AN12: 0.4827 | AO12: 195.1108 | AP12: 49.3598 | AQ12: 42.2735 | AR12: 100.378 | AS12: 86599.985 | AU12: =+A12 -> 43693 | AV12: =+(Y12*AH12+N12*W12+B12*K12+AJ12*AS12)/(K12+W12+AH12) -> 4.3625802 | AW12: =+(AV12-$AW$1)/$AX$1 -> -0.98115847
A13: 43700 | B13: 3.629 | C13: 2.5756 | D13: 0.9766 | E13: 51.3139 | F13: 2.2602 | G13: #N/A N/A | H13: 28.122 | I13: 7.61 | J13: 53.515 | K13: 210481.34 | M13: 43700 | N13: 2.2128 | O13: 22.1402 | P13: 1.2657 | Q13: 44.1192 | R13: 1.379 | S13: #N/A N/A | T13: 34.2185 | U13: 24.5123 | V13: 35.35 | W13: 66261.262 | Y13: 0.8403 | Z13: 39.2209 | AA13: 2.4212 | AB13: 5.9088 | AC13: 0.0882 | AD13: #N/A N/A | AE13: 22.8938 | AF13: 17.7275 | AG13: 0.385 | AH13: 3183.9025 | AJ13: 3.1763 | AK13: 48.6061 | AL13: 2.1113 | AM13: 38.9348 | AN13: 0.4827 | AO13: 195.1108 | AP13: 49.3598 | AQ13: 42.2735 | AR13: 90.295 | AS13: 77900.262 | AU13: =+A13 -> 43700 | AV13: =+(Y13*AH13+N13*W13+B13*K13+AJ13*AS13)/(K13+W13+AH13) -> 4.1459802 | AW13: =+(AV13-$AW$1)/$AX$1 -> -1.048393
A14: 43707 | B14: 3.6753 | C14: 2.5756 | D14: 0.9766 | E14: 51.3139 | F14: 2.2602 | G14: #N/A N/A | H14: 28.122 | I14: 7.61 | J14: 55.365 | K14: 217757.63 | M14: 43707 | N14: 2.0099 | O14: 22.1402 | P14: 1.2657 | Q14: 44.1192 | R14: 1.379 | S14: #N/A N/A | T14: 34.2185 | U14: 24.5123 | V14: 32.6 | W14: 61106.567 | Y14: 0.7681 | Z14: 39.2209 | AA14: 2.4212 | AB14: 5.9088 | AC14: 0.0882 | AD14: #N/A N/A | AE14: 22.8938 | AF14: 17.7275 | AG14: 0.348 | AH14: 2878.2479 | AJ14: 3.0774 | AK14: 48.6061 | AL14: 2.1113 | AM14: 38.9348 | AN14: 0.4827 | AO14: 195.1108 | AP14: 49.3598 | AQ14: 42.2735 | AR14: 86.979 | AS14: 75040.079 | AU14: =+A14 -> 43707 | AV14: =+(Y14*AH14+N14*W14+B14*K14+AJ14*AS14)/(K14+W14+AH14) -> 4.1040385 | AW14: =+(AV14-$AW$1)/$AX$1 -> -1.0614121
A15: 43714 | B15: 3.8123 | C15: 2.5756 | D15: 0.9766 | E15: 51.3139 | F15: 2.2602 | G15: #N/A N/A | H15: 28.122 | I15: 7.61 | J15: 60.83 | K15: 239252.17 | M15: 43714 | N15: 2.2865 | O15: 22.1402 | P15: 1.2657 | Q15: 44.1192 | R15: 1.379 | S15: #N/A N/A | T15: 34.2185 | U15: 24.5123 | V15: 39.2 | W15: 73477.836 | Y15: 0.8523 | Z15: 39.2209 | AA15: 2.4212 | AB15: 5.9088 | AC15: 0.0882 | AD15: #N/A N/A | AE15: 22.8938 | AF15: 17.7275 | AG15: 0.391 | AH15: 3234.8449 | AJ15: 3.3274 | AK15: 48.6061 | AL15: 2.1113 | AM15: 38.9348 | AN15: 0.4827 | AO15: 195.1108 | AP15: 49.3598 | AQ15: 42.2735 | AR15: 95.36 | AS15: 82269.986 | AU15: =+A15 -> 43714 | AV15: =+(Y15*AH15+N15*W15+B15*K15+AJ15*AS15)/(K15+W15+AH15) -> 4.2935482 | AW15: =+(AV15-$AW$1)/$AX$1 -> -1.0025866
A16: 43721 | B16: 3.8625 | C16: 2.5756 | D16: 0.9766 | E16: 51.3139 | F16: 2.2602 | G16: #N/A N/A | H16: 28.122 | I16: 7.61 | J16: 62.835 | K16: 247138.09 | M16: 43721 | N16: 2.3811 | O16: 22.1402 | P16: 1.2657 | Q16: 44.1192 | R16: 1.379 | S16: #N/A N/A | T16: 34.2185 | U16: 24.5123 | V16: 43.05 | W16: 80694.409 | Y16: 1.0267 | Z16: 39.2209 | AA16: 2.4212 | AB16: 5.9088 | AC16: 0.0882 | AD16: #N/A N/A | AE16: 22.8938 | AF16: 17.7275 | AG16: 0.48 | AH16: 3973.5103 | AJ16: 3.5636 | AK16: 48.6061 | AL16: 2.1113 | AM16: 38.9348 | AN16: 0.4827 | AO16: 195.1108 | AP16: 49.3598 | AQ16: 42.2735 | AR16: 103.279 | AS16: 89102.645 | AU16: =+A16 -> 43721 | AV16: =+(Y16*AH16+N16*W16+B16*K16+AJ16*AS16)/(K16+W16+AH16) -> 4.4252306 | AW16: =+(AV16-$AW$1)/$AX$1 -> -0.96171123
A17: 43728 | B17: 3.8795 | C17: 2.5756 | D17: 0.9766 | E17: 51.3139 | F17: 2.2602 | G17: #N/A N/A | H17: 28.122 | I17: 7.61 | J17: 63.515 | K17: 249812.62 | M17: 43728 | N17: 2.3848 | O17: 22.1402 | P17: 1.2657 | Q17: 44.1192 | R17: 1.379 | S17: #N/A N/A | T17: 34.2185 | U17: 24.5123 | V17: 44.05 | W17: 82568.843 | Y17: 1.1289 | Z17: 39.2209 | AA17: 2.4212 | AB17: 5.9088 | AC17: 0.0882 | AD17: #N/A N/A | AE17: 22.8938 | AF17: 17.7275 | AG17: 0.532 | AH17: 4406.5211 | AJ17: 3.6968 | AK17: 48.6061 | AL17: 2.1113 | AM17: 38.9348 | AN17: 0.4827 | AO17: 195.1108 | AP17: 49.3598 | AQ17: 42.2735 | AR17: 107.746 | AS17: 92955.948 | AU17: =+A17 -> 43728 | AV17: =+(Y17*AH17+N17*W17+B17*K17+AJ17*AS17)/(K17+W17+AH17) -> 4.497406 | AW17: =+(AV17-$AW$1)/$AX$1 -> -0.93930736
A18: 43735 | B18: 3.7967 | C18: 2.5756 | D18: 0.9766 | E18: 51.3139 | F18: 2.2602 | G18: #N/A N/A | H18: 28.122 | I18: 7.61 | J18: 60.21 | K18: 236813.63 | M18: 43735 | N18: 2.3167 | O18: 22.1402 | P18: 1.2657 | Q18: 44.1192 | R18: 1.379 | S18: #N/A N/A | T18: 34.2185 | U18: 24.5123 | V18: 42.55 | W18: 79757.191 | Y18: 1.0508 | Z18: 39.2209 | AA18: 2.4212 | AB18: 5.9088 | AC18: 0.0882 | AD18: #N/A N/A | AE18: 22.8938 | AF18: 17.7275 | AG18: 0.492 | AH18: 4075.3952 | AJ18: 3.4729 | AK18: 48.6061 | AL18: 2.1113 | AM18: 38.9348 | AN18: 0.4827 | AO18: 195.1108 | AP18: 49.3598 | AQ18: 42.2735 | AR18: 100.24 | AS18: 86480.811 | AU18: =+A18 -> 43735 | AV18: =+(Y18*AH18+N18*W18+B18*K18+AJ18*AS18)/(K18+W18+AH18) -> 4.3303347 | AW18: =+(AV18-$AW$1)/$AX$1 -> -0.99116777
... A44: 43917 | B44: 4.7448 | C44: -1.2175 | D44: -0.3094 | E44: 51.779 | F44: 3.7315 | G44: #N/A N/A | H44: 20.3015 | I44: -3.0964 | J44: 34.08 | K44: 134041 | M44: 43917 | N44: 2.3908 | O44: 14.9734 | P44: 0.7909 | Q44: 44.6986 | R44: 1.5668 | S44: #N/A N/A | T44: 32.5224 | U44: 23.4287 | V44: 35.45 | W44: 56588.417 | Y44: 2.6568 | Z44: 4.5961 | AA44: 0.523 | AB44: 11.6861 | AC44: 0.778 | AD44: #N/A N/A | AE44: 8.2242 | AF44: 5.6235 | AG44: 0.385 | AH44: 3183.9025 | AJ44: 2.8966 | AK44: 20.1847 | AL44: 1.0202 | AM44: 41.122 | AN44: 1.0149 | AO44: 195.1108 | AP44: 48.5151 | AQ44: 40.5247 | AR44: 69.393 | AS44: 57481.734 | AU44: =+A44 -> 43917 | AV44: =+(Y44*AH44+N44*W44+B44*K44+AJ44*AS44)/(K44+W44+AH44) -> 4.8822749 | AW44: =+(AV44-$AW$1)/$AX$1 -> -0.81984067
A45: 43924 | B45: 4.4534 | C45: 0.4011 | D45: -0.253 | E45: 51.3173 | F45: 3.4632 | G45: 0 | H45: 22.2103 | I45: -2.3319 | J45: 38.835 | K45: 152743.02 | M45: 43924 | N45: 3.0239 | O45: 11.8338 | P45: 1.0633 | Q45: 42.9396 | R45: 1.7733 | S45: #N/A N/A | T45: 33.3065 | U45: 22.9975 | V45: 38.5 | W45: 61457.096 | Y45: 3.2911 | Z45: 2.4854 | AA45: 0.6857 | AB45: 12.639 | AC45: 0.805 | AD45: #N/A N/A | AE45: 6.1387 | AF45: 3.4724 | AG45: 0.428 | AH45: 3540.4996 | AJ45: 2.7648 | AK45: 27.0126 | AL45: 1.5952 | AM45: 39.0886 | AN45: 0.7317 | AO45: 195.1108 | AP45: 49.1292 | AQ45: 40.4781 | AR45: 80.375 | AS45: 66578.705 | AU45: =+A45 -> 43924 | AV45: =+(Y45*AH45+N45*W45+B45*K45+AJ45*AS45)/(K45+W45+AH45) -> 4.8764206 | AW45: =+(AV45-$AW$1)/$AX$1 -> -0.8216579
A46: 43931 | B46: 4.492 | C46: 0.4011 | D46: -0.253 | E46: 51.3173 | F46: 3.4632 | G46: 0 | H46: 22.2103 | I46: -2.3319 | J46: 40.41 | K46: 158937.7 | M46: 43931 | N46: 3.0939 | O46: 11.8338 | P46: 1.0633 | Q46: 42.9396 | R46: 1.7733 | S46: #N/A N/A | T46: 33.3065 | U46: 22.9975 | V46: 41.5 | W46: 66245.961 | Y46: 3.4504 | Z46: 2.4854 | AA46: 0.6857 | AB46: 12.639 | AC46: 0.805 | AD46: #N/A N/A | AE46: 6.1387 | AF46: 3.4724 | AG46: 0.465 | AH46: 3846.1542 | AJ46: 2.9322 | AK46: 27.0126 | AL46: 1.5952 | AM46: 39.0886 | AN46: 0.7317 | AO46: 195.1108 | AP46: 49.1292 | AQ46: 40.4781 | AR46: 86.993 | AS46: 72060.722 | AU46: =+A46 -> 43931 | AV46: =+(Y46*AH46+N46*W46+B46*K46+AJ46*AS46)/(K46+W46+AH46) -> 4.9926851 | AW46: =+(AV46-$AW$1)/$AX$1 -> -0.78556837
A47: 43938 | B47: 4.4865 | C47: 0.4011 | D47: -0.253 | E47: 51.3173 | F47: 3.4632 | G47: 0 | H47: 22.2103 | I47: -2.3319 | J47: 40.185 | K47: 158052.75 | M47: 43938 | N47: 3.0669 | O47: 11.8338 | P47: 1.0633 | Q47: 42.9396 | R47: 1.7733 | S47: #N/A N/A | T47: 33.3065 | U47: 22.9975 | V47: 41.7 | W47: 66565.219 | Y47: 3.583 | Z47: 2.4854 | AA47: 0.6857 | AB47: 12.639 | AC47: 0.805 | AD47: #N/A N/A | AE47: 6.1387 | AF47: 3.4724 | AG47: 0.495 | AH47: 4100.8664 | AJ47: 2.9213 | AK47: 27.0126 | AL47: 1.5952 | AM47: 39.0886 | AN47: 0.7317 | AO47: 195.1108 | AP47: 49.1292 | AQ47: 40.4781 | AR47: 86.561 | AS47: 71703.199 | AU47: =+A47 -> 43938 | AV47: =+(Y47*AH47+N47*W47+B47*K47+AJ47*AS47)/(K47+W47+AH47) -> 4.9729726 | AW47: =+(AV47-$AW$1)/$AX$1 -> -0.79168731
A48: 43945 | B48: 4.4091 | C48: 0.4011 | D48: -0.253 | E48: 51.3173 | F48: 3.4632 | G48: 0 | H48: 22.2103 | I48: -2.3319 | J48: 37.03 | K48: 145643.73 | M48: 43945 | N48: 3.0607 | O48: 11.8338 | P48: 1.0633 | Q48: 42.9396 | R48: 1.7733 | S48: #N/A N/A | T48: 33.3065 | U48: 22.9975 | V48: 42.45 | W48: 67762.435 | Y48: 3.8617 | Z48: 2.4854 | AA48: 0.6857 | AB48: 12.639 | AC48: 0.805 | AD48: #N/A N/A | AE48: 6.1387 | AF48: 3.4724 | AG48: 0.56 | AH48: 4635.762 | AJ48: 3.005 | AK48: 27.0126 | AL48: 1.5952 | AM48: 39.0886 | AN48: 0.7317 | AO48: 195.1108 | AP48: 49.1292 | AQ48: 40.4781 | AR48: 89.87 | AS48: 74444.208 | AU48: =+A48 -> 43945 | AV48: =+(Y48*AH48+N48*W48+B48*K48+AJ48*AS48)/(K48+W48+AH48) -> 5.0043817 | AW48: =+(AV48-$AW$1)/$AX$1 -> -0.78193765
A49: 43952 | B49: 4.5641 | C49: 0.4011 | D49: -0.253 | E49: 51.3173 | F49: 3.4632 | G49: 0 | H49: 22.2103 | I49: -2.3319 | J49: 43.35 | K49: 170501.1 | M49: 43952 | N49: 3.1374 | O49: 11.8338 | P49: 1.0633 | Q49: 42.9396 | R49: 1.7733 | S49: #N/A N/A | T49: 33.3065 | U49: 22.9975 | V49: 46.05 | W49: 73509.072 | Y49: 4.1536 | Z49: 2.4854 | AA49: 0.6857 | AB49: 12.639 | AC49: 0.805 | AD49: #N/A N/A | AE49: 6.1387 | AF49: 3.4724 | AG49: 0.628 | AH49: 5196.1289 | AJ49: 3.2015 | AK49: 27.0126 | AL49: 1.5952 | AM49: 39.0886 | AN49: 0.7317 | AO49: 195.1108 | AP49: 49.1292 | AQ49: 40.4781 | AR49: 97.639 | AS49: 80879.62 | AU49: =+A49 -> 43952 | AV49: =+(Y49*AH49+N49*W49+B49*K49+AJ49*AS49)/(K49+W49+AH49) -> 5.1737463 | AW49: =+(AV49-$AW$1)/$AX$1 -> -0.72936538
A50: 43959 | B50: 4.6727 | C50: 0.4011 | D50: -0.253 | E50: 51.3173 | F50: 3.4632 | G50: 0 | H50: 22.2103 | I50: -2.3319 | J50: 47.78 | K50: 187924.85 | M50: 43959 | N50: 3.299 | O50: 11.8338 | P50: 1.0633 | Q50: 42.9396 | R50: 1.7733 | S50: #N/A N/A | T50: 33.3065 | U50: 22.9975 | V50: 50.4 | W50: 84526.447 | Y50: 4.5516 | Z50: 2.4854 | AA50: 0.6857 | AB50: 12.639 | AC50: 0.805 | AD50: #N/A N/A | AE50: 6.1387 | AF50: 3.4724 | AG50: 0.72 | AH50: 5960.2655 | AJ50: 3.4114 | AK50: 27.0126 | AL50: 1.5952 | AM50: 39.0886 | AN50: 0.7317 | AO50: 195.1108 | AP50: 49.1292 | AQ50: 40.4781 | AR50: 105.935 | AS50: 87752.004 | AU50: =+A50 -> 43959 | AV50: =+(Y50*AH50+N50*W50+B50*K50+AJ50*AS50)/(K50+W50+AH50) -> 5.3282813 | AW50: =+(AV50-$AW$1)/$AX$1 -> -0.68139636
A51: 43966 | B51: 4.7539 | C51: 0.4011 | D51: -0.253 | E51: 51.3173 | F51: 3.4632 | G51: 0 | H51: 22.2103 | I51: -2.3319 | J51: 51.095 | K51: 200963.17 | M51: 43966 | N51: 3.3682 | O51: 11.8338 | P51: 1.0633 | Q51: 42.9396 | R51: 1.7733 | S51: #N/A N/A | T51: 33.3065 | U51: 22.9975 | V51: 53.7 | W51: 90060.917 | Y51: 4.5649 | Z51: 2.4854 | AA51: 0.6857 | AB51: 12.639 | AC51: 0.805 | AD51: #N/A N/A | AE51: 6.1387 | AF51: 3.4724 | AG51: 0.723 | AH51: 5985.7367 | AJ51: 3.8081 | AK51: 27.0126 | AL51: 1.5952 | AM51: 39.0886 | AN51: 0.7317 | AO51: 195.1108 | AP51: 49.1292 | AQ51: 40.4781 | AR51: 121.617 | AS51: 100742 | AU51: =+A51 -> 43966 | AV51: =+(Y51*AH51+N51*W51+B51*K51+AJ51*AS51)/(K51+W51+AH51) -> 5.6215713 | AW51: =+(AV51-$AW$1)/$AX$1 -> -0.59035656
A52: 43973 | B52: 4.8462 | C52: 0.4011 | D52: -0.253 | E52: 51.3173 | F52: 3.4632 | G52: 0 | H52: 22.2103 | I52: -2.3319 | J52: 54.86 | K52: 215771.4 | M52: 43973 | N52: 3.3634 | O52: 11.8338 | P52: 1.0633 | Q52: 42.9396 | R52: 1.7733 | S52: #N/A N/A | T52: 33.3065 | U52: 22.9975 | V52: 54.3 | W52: 91067.184 | Y52: 6.0541 | Z52: 2.4854 | AA52: 0.6857 | AB52: 12.639 | AC52: 0.805 | AD52: #N/A N/A | AE52: 6.1387 | AF52: 3.4724 | AG52: 0.865 | AH52: 8844.7044 | AJ52: 3.8918 | AK52: 27.0126 | AL52: 1.5952 | AM52: 39.0886 | AN52: 0.7317 | AO52: 195.1108 | AP52: 49.1292 | AQ52: 40.4781 | AR52: 124.926 | AS52: 103483.01 | AU52: =+A52 -> 43973 | AV52: =+(Y52*AH52+N52*W52+B52*K52+AJ52*AS52)/(K52+W52+AH52) -> 5.7280467 | AW52: =+(AV52-$AW$1)/$AX$1 -> -0.55730565
A53: 43980 | B53: 4.8776 | C53: 0.4011 | D53: -0.253 | E53: 51.3173 | F53: 3.4632 | G53: 0 | H53: 22.2103 | I53: -2.3319 | J53: 56.14 | K53: 220805.8 | M53: 43980 | N53: 3.162 | O53: 11.8338 | P53: 1.0633 | Q53: 42.9396 | R53: 1.7733 | S53: #N/A N/A | T53: 33.3065 | U53: 22.9975 | V53: 47.6 | W53: 79830.533 | Y53: 5.4966 | Z53: 2.4854 | AA53: 0.6857 | AB53: 12.639 | AC53: 0.805 | AD53: #N/A N/A | AE53: 6.1387 | AF53: 3.4724 | AG53: 0.76 | AH53: 7774.5267 | AJ53: 3.6795 | AK53: 27.0126 | AL53: 1.5952 | AM53: 39.0886 | AN53: 0.7317 | AO53: 195.1108 | AP53: 49.1292 | AQ53: 40.4781 | AR53: 116.534 | AS53: 96531.177 | AU53: =+A53 -> 43980 | AV53: =+(Y53*AH53+N53*W53+B53*K53+AJ53*AS53)/(K53+W53+AH53) -> 5.6007964 | AW53: =+(AV53-$AW$1)/$AX$1 -> -0.59680526
A54: 43987 | B54: 5.1576 | C54: 0.4011 | D54: -0.253 | E54: 51.3173 | F54: 3.4632 | G54: 0 | H54: 22.2103 | I54: -2.3319 | J54: 67.56 | K54: 265722.12 | M54: 43987 | N54: 3.3066 | O54: 11.8338 | P54: 1.0633 | Q54: 42.9396 | R54: 1.7733 | S54: #N/A N/A | T54: 33.3065 | U54: 22.9975 | V54: 53.7 | W54: 90060.917 | Y54: 5.6606 | Z54: 2.4854 | AA54: 0.6857 | AB54: 12.639 | AC54: 0.805 | AD54: #N/A N/A | AE54: 6.1387 | AF54: 3.4724 | AG54: 0.791 | AH54: 8089.2848 | AJ54: 4.1199 | AK54: 27.0126 | AL54: 1.5952 | AM54: 39.0886 | AN54: 0.7317 | AO54: 195.1108 | AP54: 49.1292 | AQ54: 40.4781 | AR54: 133.942 | AS54: 110951.27 | AU54: =+A54 -> 43987 | AV54: =+(Y54*AH54+N54*W54+B54*K54+AJ54*AS54)/(K54+W54+AH54) -> 5.9668791 | AW54: =+(AV54-$AW$1)/$AX$1 -> -0.48316998
A55: 43994 | B55: 5.1431 | C55: 0.4011 | D55: -0.253 | E55: 51.3173 | F55: 3.4632 | G55: 0 | H55: 22.2103 | I55: -2.3319 | J55: 66.97 | K55: 263401.58 | M55: 43994 | N55: 3.1656 | O55: 11.8338 | P55: 1.0633 | Q55: 42.9396 | R55: 1.7733 | S55: #N/A N/A | T55: 33.3065 | U55: 22.9975 | V55: 49.15 | W55: 82430.057 | Y55: 5.513 | Z55: 2.4854 | AA55: 0.6857 | AB55: 12.639 | AC55: 0.805 | AD55: #N/A N/A | AE55: 6.1387 | AF55: 3.4724 | AG55: 0.763 | AH55: 7806.0025 | AJ55: 3.8324 | AK55: 27.0126 | AL55: 1.5952 | AM55: 39.0886 | AN55: 0.7317 | AO55: 195.1108 | AP55: 49.1292 | AQ55: 40.4781 | AR55: 122.576 | AS55: 101536.5 | AU55: =+A55 -> 43994 | AV55: =+(Y55*AH55+N55*W55+B55*K55+AJ55*AS55)/(K55+W55+AH55) -> 5.7906851 | AW55: =+(AV55-$AW$1)/$AX$1 -> -0.53786214
A56: 44001 | B56: 5.0258 | C56: 0.4011 | D56: -0.253 | E56: 51.3173 | F56: 3.4632 | G56: 0 | H56: 22.2103 | I56: -2.3319 | J56: 62.185 | K56: 244581.56 | M56: 44001 | N56: 2.9801 | O56: 11.8338 | P56: 1.0633 | Q56: 42.9396 | R56: 1.7733 | S56: #N/A N/A | T56: 33.3065 | U56: 22.9975 | V56: 45.75 | W56: 71969.288 | Y56: 5.1523 | Z56: 2.4854 | AA56: 0.6857 | AB56: 12.639 | AC56: 0.805 | AD56: #N/A N/A | AE56: 6.1387 | AF56: 3.4724 | AG56: 0.695 | AH56: 7113.5345 | AJ56: 3.6346 | AK56: 27.0126 | AL56: 1.5952 | AM56: 39.0886 | AN56: 0.7317 | AO56: 195.1108 | AP56: 49.1292 | AQ56: 40.4781 | AR56: 114.759 | AS56: 95061.361 | AU56: =+A56 -> 44001 | AV56: =+(Y56*AH56+N56*W56+B56*K56+AJ56*AS56)/(K56+W56+AH56) -> 5.6411977 | AW56: =+(AV56-$AW$1)/$AX$1 -> -0.58426436
... A58: 44015 | B58: 11.8464 | C58: -7.5981 | D58: -1.0952 | E58: 54.3772 | F58: 8.2751 | G58: 0 | H58: 10.1836 | I58: -16.886 | J58: 62.79 | K58: 246961.1 | M58: 44015 | N58: 5.166 | O58: 4.0209 | P58: 0.3674 | Q58: 43.0931 | R58: 2.8022 | S58: #N/A N/A | T58: 25.2993 | U58: 13.041 | V58: 47.45 | W58: 73516.252 | Y58: 10.106 | Z58: -2.0121 | AA58: 0.2603 | AB58: 10.6599 | AC58: 0.3536 | AD58: #N/A N/A | AE58: 2.7592 | AF58: -0.0999 | AG58: 0.686 | AH58: 7019.1071 | AJ58: 3.4066 | AK58: 26.1046 | AL58: 1.1527 | AM58: 38.7698 | AN58: 0.6282 | AO58: 195.1108 | AP58: 49.4033 | AQ58: 39.5251 | AR58: 113.129 | AS58: 93710.719 | AU58: =+A58 -> 44015 | AV58: =+(Y58*AH58+N58*W58+B58*K58+AJ58*AS58)/(K58+W58+AH58) -> 11.284259 | AW58: =+(AV58-$AW$1)/$AX$1 -> 1.1673916
A59: 44022 | B59: 12.0796 | C59: -7.5981 | D59: -1.0952 | E59: 54.3772 | F59: 8.2751 | G59: 0 | H59: 10.1836 | I59: -16.886 | J59: 66.99 | K59: 263480.24 | M59: 44022 | N59: 5.2877 | O59: 4.0209 | P59: 0.3674 | Q59: 43.0931 | R59: 2.8022 | S59: #N/A N/A | T59: 25.2993 | U59: 13.041 | V59: 50.9 | W59: 78861.48 | Y59: 11.1422 | Z59: -2.0121 | AA59: 0.2603 | AB59: 10.6599 | AC59: 0.3536 | AD59: #N/A N/A | AE59: 2.7592 | AF59: -0.0999 | AG59: 0.772 | AH59: 7900.4299 | AJ59: 3.714 | AK59: 26.1046 | AL59: 1.1527 | AM59: 38.7698 | AN59: 0.6282 | AO59: 195.1108 | AP59: 49.4033 | AQ59: 39.5251 | AR59: 125.645 | AS59: 104078.88 | AU59: =+A59 -> 44022 | AV59: =+(Y59*AH59+N59*W59+B59*K59+AJ59*AS59)/(K59+W59+AH59) -> 11.632834 | AW59: =+(AV59-$AW$1)/$AX$1 -> 1.2755924 | AX59: =+_xlfn.PERCENTILE.INC(OFFSET(AW59,-52,0,52,1),0.9) -> -0.40168474 | AY59: =+_xlfn.PERCENTILE.INC(OFFSET(AW59,-52,0,52,1),0.75) -> -0.45102138 | AZ59: =+_xlfn.PERCENTILE.INC(OFFSET(AW59,-52,0,52,1),0.5) -> -0.570785 | BA59: =+_xlfn.PERCENTILE.INC(OFFSET(AW59,-52,0,52,1),0.25) -> -0.78635798 | BB59: =+_xlfn.PERCENTILE.INC(OFFSET(AW59,-52,0,52,1),0.1) -> -0.95947084
A60: 44029 | B60: 12.5002 | C60: -7.5981 | D60: -1.0952 | E60: 54.3772 | F60: 8.2751 | G60: 0 | H60: 10.1836 | I60: -16.886 | J60: 74.565 | K60: 293273.68 | M60: 44029 | N60: 5.2811 | O60: 4.0209 | P60: 0.3674 | Q60: 43.0931 | R60: 2.8022 | S60: #N/A N/A | T60: 25.2993 | U60: 13.041 | V60: 51.7 | W60: 80100.953 | Y60: 11.9564 | Z60: -2.0121 | AA60: 0.2603 | AB60: 10.6599 | AC60: 0.3536 | AD60: #N/A N/A | AE60: 2.7592 | AF60: -0.0999 | AG60: 0.84 | AH60: 8592.8979 | AJ60: 3.661 | AK60: 26.1046 | AL60: 1.1527 | AM60: 38.7698 | AN60: 0.6282 | AO60: 195.1108 | AP60: 49.4033 | AQ60: 39.5251 | AR60: 123.487 | AS60: 102291.27 | AU60: =+A60 -> 44029 | AV60: =+(Y60*AH60+N60*W60+B60*K60+AJ60*AS60)/(K60+W60+AH60) -> 11.954496 | AW60: =+(AV60-$AW$1)/$AX$1 -> 1.3754389 | AX60: =+_xlfn.PERCENTILE.INC(OFFSET(AW60,-52,0,52,1),0.9) -> -0.39821602 | AY60: =+_xlfn.PERCENTILE.INC(OFFSET(AW60,-52,0,52,1),0.75) -> -0.44741383 | AZ60: =+_xlfn.PERCENTILE.INC(OFFSET(AW60,-52,0,52,1),0.5) -> -0.55567467 | BA60: =+_xlfn.PERCENTILE.INC(OFFSET(AW60,-52,0,52,1),0.25) -> -0.78635798 | BB60: =+_xlfn.PERCENTILE.INC(OFFSET(AW60,-52,0,52,1),0.1) -> -0.95947084
A61: 44036 | B61: 12.6182 | C61: -7.5981 | D61: -1.0952 | E61: 54.3772 | F61: 8.2751 | G61: 0 | H61: 10.1836 | I61: -16.886 | J61: 76.69 | K61: 301631.58 | M61: 44036 | N61: 5.4829 | O61: 4.0209 | P61: 0.3674 | Q61: 43.0931 | R61: 2.8022 | S61: #N/A N/A | T61: 25.2993 | U61: 13.041 | V61: 57.35 | W61: 88854.732 | Y61: 11.9194 | Z61: -2.0121 | AA61: 0.2603 | AB61: 10.6599 | AC61: 0.3536 | AD61: #N/A N/A | AE61: 2.7592 | AF61: -0.0999 | AG61: 0.837 | AH61: 8561.4221 | AJ61: 4.0191 | AK61: 26.1046 | AL61: 1.1527 | AM61: 38.7698 | AN61: 0.6282 | AO61: 195.1108 | AP61: 49.4033 | AQ61: 39.5251 | AR61: 138.066 | AS61: 114367.6 | AU61: =+A61 -> 44036 | AV61: =+(Y61*AH61+N61*W61+B61*K61+AJ61*AS61)/(K61+W61+AH61) -> 12.166291 | AW61: =+(AV61-$AW$1)/$AX$1 -> 1.4411821 | AX61: =+_xlfn.PERCENTILE.INC(OFFSET(AW61,-52,0,52,1),0.9) -> -0.39182454 | AY61: =+_xlfn.PERCENTILE.INC(OFFSET(AW61,-52,0,52,1),0.75) -> -0.44340414 | AZ61: =+_xlfn.PERCENTILE.INC(OFFSET(AW61,-52,0,52,1),0.5) -> -0.54595291 | BA61: =+_xlfn.PERCENTILE.INC(OFFSET(AW61,-52,0,52,1),0.25) -> -0.78284533 | BB61: =+_xlfn.PERCENTILE.INC(OFFSET(AW61,-52,0,52,1),0.1) -> -0.95947084
A62: 44043 | B62: 12.5812 | C62: -7.5981 | D62: -1.0952 | E62: 54.3772 | F62: 8.2751 | G62: 0 | H62: 10.1836 | I62: -16.886 | J62: 76.025 | K62: 299016.05 | M62: 44043 | N62: 5.3226 | O62: 4.0209 | P62: 0.3674 | Q62: 43.0931 | R62: 2.8022 | S62: #N/A N/A | T62: 25.2993 | U62: 13.041 | V62: 54.2 | W62: 83974.307 | Y62: 13.0667 | Z62: -2.0121 | AA62: 0.2603 | AB62: 10.6599 | AC62: 0.3536 | AD62: #N/A N/A | AE62: 2.7592 | AF62: -0.0999 | AG62: 0.932 | AH62: 9537.1724 | AJ62: 3.9578 | AK62: 26.1046 | AL62: 1.1527 | AM62: 38.7698 | AN62: 0.6282 | AO62: 195.1108 | AP62: 49.4033 | AQ62: 39.5251 | AR62: 135.572 | AS62: 112301.91 | AU62: =+A62 -> 44043 | AV62: =+(Y62*AH62+N62*W62+B62*K62+AJ62*AS62)/(K62+W62+AH62) -> 12.172472 | AW62: =+(AV62-$AW$1)/$AX$1 -> 1.4431006 | AX62: =+_xlfn.PERCENTILE.INC(OFFSET(AW62,-52,0,52,1),0.9) -> -0.38426492 | AY62: =+_xlfn.PERCENTILE.INC(OFFSET(AW62,-52,0,52,1),0.75) -> -0.43633942 | AZ62: =+_xlfn.PERCENTILE.INC(OFFSET(AW62,-52,0,52,1),0.5) -> -0.53212545 | BA62: =+_xlfn.PERCENTILE.INC(OFFSET(AW62,-52,0,52,1),0.25) -> -0.78284533 | BB62: =+_xlfn.PERCENTILE.INC(OFFSET(AW62,-52,0,52,1),0.1) -> -0.95947084
A63: 44050 | B63: 12.8502 | C63: -7.5981 | D63: -1.0952 | E63: 54.3772 | F63: 8.2751 | G63: 0 | H63: 10.1836 | I63: -16.886 | J63: 80.87 | K63: 318072.06 | M63: 44050 | N63: 5.4779 | O63: 4.0209 | P63: 0.3674 | Q63: 43.0931 | R63: 2.8022 | S63: #N/A N/A | T63: 25.2993 | U63: 13.041 | V63: 58.85 | W63: 91178.745 | Y63: 14.362 | Z63: -2.0121 | AA63: 0.2603 | AB63: 10.6599 | AC63: 0.3536 | AD63: #N/A N/A | AE63: 2.7592 | AF63: -0.0999 | AG63: 1.04 | AH63: 10638.826 | AJ63: 4.2075 | AK63: 26.1046 | AL63: 1.1527 | AM63: 38.7698 | AN63: 0.6282 | AO63: 195.1108 | AP63: 49.4033 | AQ63: 39.5251 | AR63: 145.739 | AS63: 120723.56 | AU63: =+A63 -> 44050 | AV63: =+(Y63*AH63+N63*W63+B63*K63+AJ63*AS63)/(K63+W63+AH63) -> 12.497324 | AW63: =+(AV63-$AW$1)/$AX$1 -> 1.5439376 | AX63: =+_xlfn.PERCENTILE.INC(OFFSET(AW63,-52,0,52,1),0.9) -> -0.36784263 | AY63: =+_xlfn.PERCENTILE.INC(OFFSET(AW63,-52,0,52,1),0.75) -> -0.43515156 | AZ63: =+_xlfn.PERCENTILE.INC(OFFSET(AW63,-52,0,52,1),0.5) -> -0.52478749 | BA63: =+_xlfn.PERCENTILE.INC(OFFSET(AW63,-52,0,52,1),0.25) -> -0.7564079 | BB63: =+_xlfn.PERCENTILE.INC(OFFSET(AW63,-52,0,52,1),0.1) -> -0.95947084
A64: 44057 | B64: 12.3791 | C64: -7.5981 | D64: -1.0952 | E64: 54.3772 | F64: 8.2751 | G64: 0 | H64: 10.1836 | I64: -16.886 | J64: 72.385 | K64: 284699.47 | M64: 44057 | N64: 5.3785 | O64: 4.0209 | P64: 0.3674 | Q64: 43.0931 | R64: 2.8022 | S64: #N/A N/A | T64: 25.2993 | U64: 13.041 | V64: 57.1 | W64: 88467.397 | Y64: 13.2517 | Z64: -2.0121 | AA64: 0.2603 | AB64: 10.6599 | AC64: 0.3536 | AD64: #N/A N/A | AE64: 2.7592 | AF64: -0.0999 | AG64: 0.948 | AH64: 9694.5515 | AJ64: 3.8 | AK64: 26.1046 | AL64: 1.1527 | AM64: 38.7698 | AN64: 0.6282 | AO64: 195.1108 | AP64: 49.4033 | AQ64: 39.5251 | AR64: 129.146 | AS64: 106978.79 | AU64: =+A64 -> 44057 | AV64: =+(Y64*AH64+N64*W64+B64*K64+AJ64*AS64)/(K64+W64+AH64) -> 11.845366 | AW64: =+(AV64-$AW$1)/$AX$1 -> 1.3415642 | AX64: =+_xlfn.PERCENTILE.INC(OFFSET(AW64,-52,0,52,1),0.9) -> 1.0140422 | AY64: =+_xlfn.PERCENTILE.INC(OFFSET(AW64,-52,0,52,1),0.75) -> -0.42984518 | AZ64: =+_xlfn.PERCENTILE.INC(OFFSET(AW64,-52,0,52,1),0.5) -> -0.52197936 | BA64: =+_xlfn.PERCENTILE.INC(OFFSET(AW64,-52,0,52,1),0.25) -> -0.7564079 | BB64: =+_xlfn.PERCENTILE.INC(OFFSET(AW64,-52,0,52,1),0.1) -> -0.95947084
A65: 44064 | B65: 12.3311 | C65: -7.5981 | D65: -1.0952 | E65: 54.3772 | F65: 8.2751 | G65: 0 | H65: 10.1836 | I65: -16.886 | J65: 71.52 | K65: 281297.31 | M65: 44064 | N65: 5.4088 | O65: 4.0209 | P65: 0.3674 | Q65: 43.0931 | R65: 2.8022 | S65: #N/A N/A | T65: 25.2993 | U65: 13.041 | V65: 58.9 | W65: 90810.9 | Y65: 14.473 | Z65: -2.0121 | AA65: 0.2603 | AB65: 10.6599 | AC65: 0.3536 | AD65: #N/A N/A | AE65: 2.7592 | AF65: -0.0999 | AG65: 1.049 | AH65: 10733.253 | AJ65: 3.7058 | AK65: 26.1046 | AL65: 1.1527 | AM65: 38.7698 | AN65: 0.6282 | AO65: 195.1108 | AP65: 49.4033 | AQ65: 39.5251 | AR65: 125.31 | AS65: 103800.81 | AU65: =+A65 -> 44064 | AV65: =+(Y65*AH65+N65*W65+B65*K65+AJ65*AS65)/(K65+W65+AH65) -> 11.753927 | AW65: =+(AV65-$AW$1)/$AX$1 -> 1.3131806 | AX65: =+_xlfn.PERCENTILE.INC(OFFSET(AW65,-52,0,52,1),0.9) -> 1.2647723 | AY65: =+_xlfn.PERCENTILE.INC(OFFSET(AW65,-52,0,52,1),0.75) -> -0.41737456 | AZ65: =+_xlfn.PERCENTILE.INC(OFFSET(AW65,-52,0,52,1),0.5) -> -0.50610004 | BA65: =+_xlfn.PERCENTILE.INC(OFFSET(AW65,-52,0,52,1),0.25) -> -0.73399853 | BB65: =+_xlfn.PERCENTILE.INC(OFFSET(AW65,-52,0,52,1),0.1) -> -0.92999974
A66: 44071 | B66: 12.3086 | C66: -7.5981 | D66: -1.0952 | E66: 54.3772 | F66: 8.2751 | G66: 0 | H66: 10.1836 | I66: -16.886 | J66: 71.115 | K66: 279704.39 | M66: 44071 | N66: 5.4014 | O66: 4.0209 | P66: 0.3674 | Q66: 43.0931 | R66: 2.8022 | S66: #N/A N/A | T66: 25.2993 | U66: 13.041 | V66: 59.5 | W66: 91735.968 | Y66: 12.8446 | Z66: -2.0121 | AA66: 0.2603 | AB66: 10.6599 | AC66: 0.3536 | AD66: #N/A N/A | AE66: 2.7592 | AF66: -0.0999 | AG66: 1.132 | AH66: 9348.3175 | AJ66: 3.4761 | AK66: 26.1046 | AL66: 1.1527 | AM66: 38.7698 | AN66: 0.6282 | AO66: 195.1108 | AP66: 49.4033 | AQ66: 39.5251 | AR66: 115.958 | AS66: 96054.48 | AU66: =+A66 -> 44071 | AV66: =+(Y66*AH66+N66*W66+B66*K66+AJ66*AS66)/(K66+W66+AH66) -> 11.534593 | AW66: =+(AV66-$AW$1)/$AX$1 -> 1.2450975 | AX66: =+_xlfn.PERCENTILE.INC(OFFSET(AW66,-52,0,52,1),0.9) -> 1.3094218 | AY66: =+_xlfn.PERCENTILE.INC(OFFSET(AW66,-52,0,52,1),0.75) -> -0.40458557 | AZ66: =+_xlfn.PERCENTILE.INC(OFFSET(AW66,-52,0,52,1),0.5) -> -0.48995033 | BA66: =+_xlfn.PERCENTILE.INC(OFFSET(AW66,-52,0,52,1),0.25) -> -0.69338861 | BB66: =+_xlfn.PERCENTILE.INC(OFFSET(AW66,-52,0,52,1),0.1) -> -0.84377387
A67: 44078 | B67: 12.0926 | C67: -7.5981 | D67: -1.0952 | E67: 54.3772 | F67: 8.2751 | G67: 0 | H67: 10.1836 | I67: -16.886 | J67: 67.225 | K67: 264404.53 | M67: 44078 | N67: 5.3536 | O67: 4.0209 | P67: 0.3674 | Q67: 43.0931 | R67: 2.8022 | S67: #N/A N/A | T67: 25.2993 | U67: 13.041 | V67: 59.1 | W67: 91119.256 | Y67: 13.0297 | Z67: -2.0121 | AA67: 0.2603 | AB67: 10.6599 | AC67: 0.3536 | AD67: #N/A N/A | AE67: 2.7592 | AF67: -0.0999 | AG67: 1.151 | AH67: 9505.6966 | AJ67: 3.4879 | AK67: 26.1046 | AL67: 1.1527 | AM67: 38.7698 | AN67: 0.6282 | AO67: 195.1108 | AP67: 49.4033 | AQ67: 39.5251 | AR67: 116.438 | AS67: 96451.727 | AU67: =+A67 -> 44078 | AV67: =+(Y67*AH67+N67*W67+B67*K67+AJ67*AS67)/(K67+W67+AH67) -> 11.35641 | AW67: =+(AV67-$AW$1)/$AX$1 -> 1.189788 | AX67: =+_xlfn.PERCENTILE.INC(OFFSET(AW67,-52,0,52,1),0.9) -> 1.3094218 | AY67: =+_xlfn.PERCENTILE.INC(OFFSET(AW67,-52,0,52,1),0.75) -> -0.40039889 | AZ67: =+_xlfn.PERCENTILE.INC(OFFSET(AW67,-52,0,52,1),0.5) -> -0.48582152 | BA67: =+_xlfn.PERCENTILE.INC(OFFSET(AW67,-52,0,52,1),0.25) -> -0.61795304 | BB67: =+_xlfn.PERCENTILE.INC(OFFSET(AW67,-52,0,52,1),0.1) -> -0.82147618
A68: 44085 | B68: 12.0699 | C68: -7.5981 | D68: -1.0952 | E68: 54.3772 | F68: 8.2751 | G68: 0 | H68: 10.1836 | I68: -16.886 | J68: 66.815 | K68: 262791.94 | M68: 44085 | N68: 5.3928 | O68: 4.0209 | P68: 0.3674 | Q68: 43.0931 | R68: 2.8022 | S68: #N/A N/A | T68: 25.2993 | U68: 13.041 | V68: 60.95 | W68: 93971.551 | Y68: 13.2887 | Z68: -2.0121 | AA68: 0.2603 | AB68: 10.6599 | AC68: 0.3536 | AD68: #N/A N/A | AE68: 2.7592 | AF68: -0.0999 | AG68: 1.177 | AH68: 9726.0273 | AJ68: 3.4714 | AK68: 26.1046 | AL68: 1.1527 | AM68: 38.7698 | AN68: 0.6282 | AO68: 195.1108 | AP68: 49.4033 | AQ68: 39.5251 | AR68: 115.766 | AS68: 95895.581 | AU68: =+A68 -> 44085 | AV68: =+(Y68*AH68+N68*W68+B68*K68+AJ68*AS68)/(K68+W68+AH68) -> 11.298496 | AW68: =+(AV68-$AW$1)/$AX$1 -> 1.1718108 | AX68: =+_xlfn.PERCENTILE.INC(OFFSET(AW68,-52,0,52,1),0.9) -> 1.3094218 | AY68: =+_xlfn.PERCENTILE.INC(OFFSET(AW68,-52,0,52,1),0.75) -> -0.39619807 | AZ68: =+_xlfn.PERCENTILE.INC(OFFSET(AW68,-52,0,52,1),0.5) -> -0.48139847 | BA68: =+_xlfn.PERCENTILE.INC(OFFSET(AW68,-52,0,52,1),0.25) -> -0.59649447 | BB68: =+_xlfn.PERCENTILE.INC(OFFSET(AW68,-52,0,52,1),0.1) -> -0.81702533
A69: 44092 | B69: 11.6734 | C69: -7.5981 | D69: -1.0952 | E69: 54.3772 | F69: 8.2751 | G69: 0 | H69: 10.1836 | I69: -16.886 | J69: 59.675 | K69: 234709.41 | M69: 44092 | N69: 5.2754 | O69: 4.0209 | P69: 0.3674 | Q69: 43.0931 | R69: 2.8022 | S69: #N/A N/A | T69: 25.2993 | U69: 13.041 | V69: 58.8 | W69: 90656.722 | Y69: 11.6603 | Z69: -2.0121 | AA69: 0.2603 | AB69: 10.6599 | AC69: 0.3536 | AD69: #N/A N/A | AE69: 2.7592 | AF69: -0.0999 | AG69: 1.01 | AH69: 8341.0914 | AJ69: 3.2877 | AK69: 26.1046 | AL69: 1.1527 | AM69: 38.7698 | AN69: 0.6282 | AO69: 195.1108 | AP69: 49.4033 | AQ69: 39.5251 | AR69: 108.285 | AS69: 89698.518 | AU69: =+A69 -> 44092 | AV69: =+(Y69*AH69+N69*W69+B69*K69+AJ69*AS69)/(K69+W69+AH69) -> 10.818671 | AW69: =+(AV69-$AW$1)/$AX$1 -> 1.022869 | AX69: =+_xlfn.PERCENTILE.INC(OFFSET(AW69,-52,0,52,1),0.9) -> 1.3094218 | AY69: =+_xlfn.PERCENTILE.INC(OFFSET(AW69,-52,0,52,1),0.75) -> -0.3892387 | AZ69: =+_xlfn.PERCENTILE.INC(OFFSET(AW69,-52,0,52,1),0.5) -> -0.47179935 | BA69: =+_xlfn.PERCENTILE.INC(OFFSET(AW69,-52,0,52,1),0.25) -> -0.59604953 | BB69: =+_xlfn.PERCENTILE.INC(OFFSET(AW69,-52,0,52,1),0.1) -> -0.79107542
A70: 44099 | B70: 11.3644 | C70: -7.5981 | D70: -1.0952 | E70: 54.3772 | F70: 8.2751 | G70: 0 | H70: 10.1836 | I70: -16.886 | J70: 54.11 | K70: 212821.55 | M70: 44099 | N70: 5.3007 | O70: 4.0209 | P70: 0.3674 | Q70: 43.0931 | R70: 2.8022 | S70: #N/A N/A | T70: 25.2993 | U70: 13.041 | V70: 60.3 | W70: 92969.393 | Y70: 12.0304 | Z70: -2.0121 | AA70: 0.2603 | AB70: 10.6599 | AC70: 0.3536 | AD70: #N/A N/A | AE70: 2.7592 | AF70: -0.0999 | AG70: 1.048 | AH70: 8655.8495 | AJ70: 3.4243 | AK70: 26.1046 | AL70: 1.1527 | AM70: 38.7698 | AN70: 0.6282 | AO70: 195.1108 | AP70: 49.4033 | AQ70: 39.5251 | AR70: 113.848 | AS70: 94306.59 | AU70: =+A70 -> 44099 | AV70: =+(Y70*AH70+N70*W70+B70*K70+AJ70*AS70)/(K70+W70+AH70) -> 10.61693 | AW70: =+(AV70-$AW$1)/$AX$1 -> 0.96024662 | AX70: =+_xlfn.PERCENTILE.INC(OFFSET(AW70,-52,0,52,1),0.9) -> 1.3094218 | AY70: =+_xlfn.PERCENTILE.INC(OFFSET(AW70,-52,0,52,1),0.75) -> -0.37915053 | AZ70: =+_xlfn.PERCENTILE.INC(OFFSET(AW70,-52,0,52,1),0.5) -> -0.45822711 | BA70: =+_xlfn.PERCENTILE.INC(OFFSET(AW70,-52,0,52,1),0.25) -> -0.59175136 | BB70: =+_xlfn.PERCENTILE.INC(OFFSET(AW70,-52,0,52,1),0.1) -> -0.7852053
... A252: 45373 | B252: 12.4361 | C252: -20.7334 | D252: -0.2923 | E252: 49.4528 | F252: 3.5565 | G252: 0 | H252: -8.7638 | I252: -26.7893 | J252: 2217.435 | K252: 8670516 | M252: 45373 | N252: 5.1212 | O252: 3.2748 | P252: 0.2075 | Q252: 37.7356 | R252: 2.7224 | S252: #N/A N/A | T252: 36.2953 | U252: 20.8186 | V252: 1921.6 | W252: 2620140.8 | Y252: 3.3615 | Z252: -18.2438 | AA252: -0.1071 | AB252: 6.8851 | AC252: -0.1817 | AD252: #N/A N/A | AE252: -9.4786 | AF252: -13.5849 | AG252: 47.717 | AH252: 335761.72 | AJ252: 8.3063 | AK252: 5.9385 | AL252: 0.1074 | AM252: 35.5338 | AN252: 1.4941 | AO252: 195.1108 | AP252: 40.0529 | AQ252: 25.3946 | AR252: 3131.207 | AS252: 2457501.4 | AU252: =+A252 -> 45373 | AV252: =+(Y252*AH252+N252*W252+B252*K252+AJ252*AS252)/(K252+W252+AH252) -> 12.281261 | AW252: =+(AV252-$AW$1)/$AX$1 -> 1.4768696 | AX252: =+_xlfn.PERCENTILE.INC(OFFSET(AW252,-52,0,52,1),0.9) -> 1.5020789 | AY252: =+_xlfn.PERCENTILE.INC(OFFSET(AW252,-52,0,52,1),0.75) -> 1.3554596 | AZ252: =+_xlfn.PERCENTILE.INC(OFFSET(AW252,-52,0,52,1),0.5) -> 0.29824164 | BA252: =+_xlfn.PERCENTILE.INC(OFFSET(AW252,-52,0,52,1),0.25) -> -0.23503101 | BB252: =+_xlfn.PERCENTILE.INC(OFFSET(AW252,-52,0,52,1),0.1) -> -0.56279052
A253: 45380 | B253: 402.7199 | C253: -21.1153 | D253: -1.9518 | E253: 48.6608 | F253: 92.2095 | G253: 0 | H253: 0.4478 | I253: -17.0524 | J253: 2184.3 | K253: 8540953 | M253: 45380 | N253: 5.0792 | O253: 8.9935 | P253: 0.2508 | Q253: 35.6166 | R253: 2.4356 | S253: #N/A N/A | T253: 33.5954 | U253: 17.2692 | V253: 1887.35 | W253: 2573440.2 | Y253: 3.5596 | Z253: 19.0864 | AA253: 1.8772 | AB253: 4.2582 | AC253: -0.3195 | AD253: #N/A N/A | AE253: 14.4973 | AF253: 10.3589 | AG253: 46.808 | AH253: 329367.74 | AJ253: 6.0009 | AK253: 8 | AL253: 0.3357 | AM253: 20.6179 | AN253: 0.1422 | AO253: 195.1108 | AP253: 41.3498 | AQ253: 27.0848 | AR253: 3145.307 | AS253: 2468567 | AU253: =+A253 -> 45380
A254: 45387 | B254: 405.4207 | C254: -21.1153 | D254: -1.9518 | E254: 48.6608 | F254: 92.2095 | G254: 0 | H254: 0.4478 | I254: -17.0524 | J254: 2210.72 | K254: 8644259.3 | M254: 45387 | N254: 5.204 | O254: 8.9935 | P254: 0.2508 | Q254: 35.6166 | R254: 2.4356 | S254: #N/A N/A | T254: 33.5954 | U254: 17.2692 | V254: 1959.35 | W254: 2671613.7 | Y254: 3.5867 | Z254: 19.0864 | AA254: 1.8772 | AB254: 4.2582 | AC254: -0.3195 | AD254: #N/A N/A | AE254: 14.4973 | AF254: 10.3589 | AG254: 47.14 | AH254: 331707 | AJ254: 6.8086 | AK254: 8 | AL254: 0.3357 | AM254: 20.6179 | AN254: 0.1422 | AO254: 195.1108 | AP254: 41.3498 | AQ254: 27.0848 | AR254: 3578.927 | AS254: 2808890.2 | AU254: =+A254 -> 45387
A255: 45394 | B255: 406.2988 | C255: -21.1153 | D255: -1.9518 | E255: 48.6608 | F255: 92.2095 | G255: 0 | H255: 0.4478 | I255: -17.0524 | J255: 2219.31 | K255: 8677847.6 | M255: 45394 | N255: 5.0626 | O255: 8.9935 | P255: 0.2508 | Q255: 35.6166 | R255: 2.4356 | S255: #N/A N/A | T255: 33.5954 | U255: 17.2692 | V255: 1904.4 | W255: 2596688.2 | Y255: 3.8932 | Z255: 19.0864 | AA255: 1.8772 | AB255: 4.2582 | AC255: -0.3195 | AD255: #N/A N/A | AE255: 14.4973 | AF255: 10.3589 | AG255: 50.908 | AH255: 358218.61 | AJ255: 6.3877 | AK255: 8 | AL255: 0.3357 | AM255: 20.6179 | AN255: 0.1422 | AO255: 195.1108 | AP255: 41.3498 | AQ255: 27.0848 | AR255: 3353.005 | AS255: 2631577.4 | AU255: =+A255 -> 45394
A256: 45401 | B256: 388.6643 | C256: -21.1153 | D256: -1.9518 | E256: 48.6608 | F256: 92.2095 | G256: 0 | H256: 0.4478 | I256: -17.0524 | J256: 2046.805 | K256: 8003326.2 | M256: 45401 | N256: 4.8918 | O256: 8.9935 | P256: 0.2508 | Q256: 35.6166 | R256: 2.4356 | S256: #N/A N/A | T256: 33.5954 | U256: 17.2692 | V256: 1835 | W256: 2502059.9 | Y256: 3.6047 | Z256: 19.0864 | AA256: 1.8772 | AB256: 4.2582 | AC256: -0.3195 | AD256: #N/A N/A | AE256: 14.4973 | AF256: 10.3589 | AG256: 47.362 | AH256: 333266.51 | AJ256: 6.211 | AK256: 8 | AL256: 0.3357 | AM256: 20.6179 | AN256: 0.1422 | AO256: 195.1108 | AP256: 41.3498 | AQ256: 27.0848 | AR256: 3258.148 | AS256: 2557129.3 | AU256: =+A256 -> 45401
A257: 45408 | B257: 414.1043 | C257: -21.1153 | D257: -1.9518 | E257: 48.6608 | F257: 92.2095 | G257: 0 | H257: 0.4478 | I257: -17.0524 | J257: 2295.665 | K257: 8976407.5 | M257: 45408 | N257: 5.035 | O257: 8.9935 | P257: 0.2508 | Q257: 35.6166 | R257: 2.4356 | S257: #N/A N/A | T257: 33.5954 | U257: 17.2692 | V257: 1913.35 | W257: 2608891.7 | Y257: 3.6949 | Z257: 19.0864 | AA257: 1.8772 | AB257: 4.2582 | AC257: -0.3195 | AD257: #N/A N/A | AE257: 14.4973 | AF257: 10.3589 | AG257: 48.47 | AH257: 341064.04 | AJ257: 6.6228 | AK257: 8 | AL257: 0.3357 | AM257: 20.6179 | AN257: 0.1422 | AO257: 195.1108 | AP257: 41.3498 | AQ257: 27.0848 | AR257: 3479.178 | AS257: 2730603.1 | AU257: =+A257 -> 45408
A258: 45415 | B258: 446.1681 | C258: -21.1153 | D258: -1.9518 | E258: 48.6608 | F258: 92.2095 | G258: 0 | H258: 0.4478 | I258: -17.0524 | J258: 2609.32 | K258: 10202847 | M258: 45415 | N258: 5.5797 | O258: 8.9935 | P258: 0.2508 | Q258: 35.6166 | R258: 2.4356 | S258: #N/A N/A | T258: 33.5954 | U258: 17.2692 | V258: 2182.8 | W258: 2976292.3 | Y258: 3.9167 | Z258: 19.0864 | AA258: 1.8772 | AB258: 4.2582 | AC258: -0.3195 | AD258: #N/A N/A | AE258: 14.4973 | AF258: 10.3589 | AG258: 51.196 | AH258: 360245.97 | AJ258: 7.8048 | AK258: 8 | AL258: 0.3357 | AM258: 20.6179 | AN258: 0.1422 | AO258: 195.1108 | AP258: 41.3498 | AQ258: 27.0848 | AR258: 4113.783 | AS258: 3228667.5 | AU258: =+A258 -> 45415
A259: 45422 | B259: 431.4138 | C259: -21.1153 | D259: -1.9518 | E259: 48.6608 | F259: 92.2095 | G259: 0 | H259: 0.4478 | I259: -17.0524 | J259: 2464.99 | K259: 9638494.6 | M259: 45422 | N259: 5.2478 | O259: 8.9935 | P259: 0.2508 | Q259: 35.6166 | R259: 2.4356 | S259: #N/A N/A | T259: 33.5954 | U259: 17.2692 | V259: 2036.5 | W259: 2776809.3 | Y259: 4.0772 | Z259: 19.0864 | AA259: 1.8772 | AB259: 4.2582 | AC259: -0.3195 | AD259: #N/A N/A | AE259: 14.4973 | AF259: 10.3589 | AG259: 53.169 | AH259: 374125.58 | AJ259: 7.3103 | AK259: 8 | AL259: 0.3357 | AM259: 20.6179 | AN259: 0.1422 | AO259: 195.1108 | AP259: 41.3498 | AQ259: 27.0848 | AR259: 3848.297 | AS259: 3020303.2 | AU259: =+A259 -> 45422
A260: 45429 | B260: 444.4236 | C260: -21.1153 | D260: -1.9518 | E260: 48.6608 | F260: 92.2095 | G260: 0 | H260: 0.4478 | I260: -17.0524 | J260: 2592.255 | K260: 10136121 | M260: 45429 | N260: 5.4032 | O260: 8.9935 | P260: 0.2508 | Q260: 35.6166 | R260: 2.4356 | S260: #N/A N/A | T260: 33.5954 | U260: 17.2692 | V260: 2122.2 | W260: 2893663 | Y260: 4.5821 | Z260: 19.0864 | AA260: 1.8772 | AB260: 4.2582 | AC260: -0.3195 | AD260: #N/A N/A | AE260: 14.4973 | AF260: 10.3589 | AG260: 59.374 | AH260: 417791.75 | AJ260: 7.6234 | AK260: 8 | AL260: 0.3357 | AM260: 20.6179 | AN260: 0.1422 | AO260: 195.1108 | AP260: 41.3498 | AQ260: 27.0848 | AR260: 4016.384 | AS260: 3152224.6 | AU260: =+A260 -> 45429
A261: 45436 | B261: 445.7024 | C261: -21.1153 | D261: -1.9518 | E261: 48.6608 | F261: 92.2095 | G261: 0 | H261: 0.4478 | I261: -17.0524 | J261: 2604.765 | K261: 10185037 | M261: 45436 | N261: 5.6566 | O261: 8.9935 | P261: 0.2508 | Q261: 35.6166 | R261: 2.4356 | S261: #N/A N/A | T261: 33.5954 | U261: 17.2692 | V261: 2255.9 | W261: 3075965.6 | Y261: 5.1266 | Z261: 19.0864 | AA261: 1.8772 | AB261: 4.2582 | AC261: -0.3195 | AD261: #N/A N/A | AE261: 14.4973 | AF261: 10.3589 | AG261: 66.068 | AH261: 464888.85 | AJ261: 8.0953 | AK261: 8 | AL261: 0.3357 | AM261: 20.6179 | AN261: 0.1422 | AO261: 195.1108 | AP261: 41.3498 | AQ261: 27.0848 | AR261: 4269.737 | AS261: 3351066.4 | AU261: =+A261 -> 45436
A262: 45443 | B262: 476.4454 | C262: -21.1153 | D262: -1.9518 | E262: 48.6608 | F262: 92.2095 | G262: 0 | H262: 0.4478 | I262: -17.0524 | J262: 2905.5 | K262: 11360957 | M262: 45443 | N262: 6.0784 | O262: 8.9935 | P262: 0.2508 | Q262: 35.6166 | R262: 2.4356 | S262: #N/A N/A | T262: 33.5954 | U262: 17.2692 | V262: 2474 | W262: 3373349.4 | Y262: 5.6027 | Z262: 19.0864 | AA262: 1.8772 | AB262: 4.2582 | AC262: -0.3195 | AD262: #N/A N/A | AE262: 14.4973 | AF262: 10.3589 | AG262: 71.919 | AH262: 506059.81 | AJ262: 8.8962 | AK262: 8 | AL262: 0.3357 | AM262: 20.6179 | AN262: 0.1422 | AO262: 195.1108 | AP262: 41.3498 | AQ262: 27.0848 | AR262: 4699.713 | AS262: 3688529.2 | AU262: =+A262 -> 45443
A263: 45450 | B263: 448.3629 | C263: -21.1153 | D263: -1.9518 | E263: 48.6608 | F263: 92.2095 | G263: 0 | H263: 0.4478 | I263: -17.0524 | J263: 2630.79 | K263: 10286798 | M263: 45450 | N263: 5.6688 | O263: 8.9935 | P263: 0.2508 | Q263: 35.6166 | R263: 2.4356 | S263: #N/A N/A | T263: 33.5954 | U263: 17.2692 | V263: 2287.85 | W263: 3119530.1 | Y263: 5.1663 | Z263: 19.0864 | AA263: 1.8772 | AB263: 4.2582 | AC263: -0.3195 | AD263: #N/A N/A | AE263: 14.4973 | AF263: 10.3589 | AG263: 66.555 | AH263: 468319.76 | AJ263: 8.1164 | AK263: 8 | AL263: 0.3357 | AM263: 20.6179 | AN263: 0.1422 | AO263: 195.1108 | AP263: 41.3498 | AQ263: 27.0848 | AR263: 4281.054 | AS263: 3359949 | AU263: =+A263 -> 45450
A264: 45457 | B264: 451.1634 | C264: -21.1153 | D264: -1.9518 | E264: 48.6608 | F264: 92.2095 | G264: 0 | H264: 0.4478 | I264: -17.0524 | J264: 2658.185 | K264: 10393917 | M264: 45457 | N264: 5.9004 | O264: 8.9935 | P264: 0.2508 | Q264: 35.6166 | R264: 2.4356 | S264: #N/A N/A | T264: 33.5954 | U264: 17.2692 | V264: 2411.55 | W264: 3288197.6 | Y264: 5.7235 | Z264: 19.0864 | AA264: 1.8772 | AB264: 4.2582 | AC264: -0.3195 | AD264: #N/A N/A | AE264: 14.4973 | AF264: 10.3589 | AG264: 73.404 | AH264: 516508.51 | AJ264: 8.7863 | AK264: 8 | AL264: 0.3357 | AM264: 20.6179 | AN264: 0.1422 | AO264: 195.1108 | AP264: 41.3498 | AQ264: 27.0848 | AR264: 4640.726 | AS264: 3642234.4 | AU264: =+A264 -> 45457
... A279: 45562 | B279: 96.3914 | C279: -18.0782 | D279: -1.5468 | E279: 47.131 | F279: 26.4596 | G279: 0 | H279: 1.5656 | I279: -14.3655 | J279: 2675 | K279: 10459666 | M279: 45562 | N279: 5.5704 | O279: 11.5526 | P279: 0.3708 | Q279: 34.9755 | R279: 1.5548 | S279: #N/A N/A | T279: 37.6434 | U279: 20.9119 | V279: 2890 | W279: 3940573.9 | Y279: 9.255 | Z279: 15.19 | AA279: 1.4951 | AB279: 3.9281 | AC279: -0.1904 | AD279: #N/A N/A | AE279: 13.3467 | AF279: 9.1981 | AG279: 117.02 | AH279: 823419.36 | AJ279: 6.2984 | AK279: 15.3405 | AL279: 0.594 | AM279: 23.2443 | AN279: -0.0588 | AO279: 195.1108 | AP279: 46.6596 | AQ279: 33.6931 | AR279: 4450.34 | AS279: 3492811.3 | AU279: =+A279 -> 45562
A280: 45569 | B280: 16.5752 | C280: -8.3569 | D280: -0.6401 | E280: 43.3526 | F280: 5.5847 | G280: 0 | H280: 7.2625 | I280: -7.1857 | J280: 2735 | K280: 10694276 | M280: 45569 | N280: 6.2986 | O280: 11.0935 | P280: 0.2946 | Q280: 35.1331 | R280: 0.9972 | S280: #N/A N/A | T280: 36.2807 | U280: 18.4906 | V280: 3090 | W280: 4213278 | Y280: 27.3327 | Z280: -0.873 | AA280: 0.5772 | AB280: 4.2183 | AC280: -0.4904 | AD280: #N/A N/A | AE280: 4.4166 | AF280: 0.0787 | AG280: 119.236 | AH280: 839014.42 | AJ280: 5.5169 | AK280: 16.8274 | AL280: 0.4836 | AM280: 22.2797 | AN280: -0.1395 | AO280: 195.1108 | AP280: 49.9133 | AQ280: 37.493 | AR280: 4622.983 | AS280: 3628308.3 | AU280: =+A280 -> 45569 | AV280: =+(Y280*AH280+N280*W280+B280*K280+AJ280*AS280)/(K280+W280+AH280) -> 15.669894 | AW280: =+(AV280-$AW$1)/$AX$1 -> 2.5287312 | AX280: =+_xlfn.PERCENTILE.INC(OFFSET(AW280,-52,0,52,1),0.9) -> 1.6429523 | AY280: =+_xlfn.PERCENTILE.INC(OFFSET(AW280,-52,0,52,1),0.75) -> 1.4864193 | AZ280: =+_xlfn.PERCENTILE.INC(OFFSET(AW280,-52,0,52,1),0.5) -> 1.3946743 | BA280: =+_xlfn.PERCENTILE.INC(OFFSET(AW280,-52,0,52,1),0.25) -> 1.1776989 | BB280: =+_xlfn.PERCENTILE.INC(OFFSET(AW280,-52,0,52,1),0.1) -> 0.49796399
A281: 45576 | B281: 17.0074 | C281: -8.3569 | D281: -0.6401 | E281: 43.3526 | F281: 5.5847 | G281: 0 | H281: 7.2625 | I281: -7.1857 | J281: 2860 | K281: 11183045 | M281: 45576 | N281: 6.1415 | O281: 11.0935 | P281: 0.2946 | Q281: 35.1331 | R281: 0.9972 | S281: #N/A N/A | T281: 36.2807 | U281: 18.4906 | V281: 3015 | W281: 4111013.9 | Y281: 25.8987 | Z281: -0.873 | AA281: 0.5772 | AB281: 4.2183 | AC281: -0.4904 | AD281: #N/A N/A | AE281: 4.4166 | AF281: 0.0787 | AG281: 113.031 | AH281: 795348.24 | AJ281: 5.6284 | AK281: 16.8274 | AL281: 0.4836 | AM281: 22.2797 | AN281: -0.1395 | AO281: 195.1108 | AP281: 49.9133 | AQ281: 37.493 | AR281: 4714.099 | AS281: 3699820.6 | AU281: =+A281 -> 45576 | AV281: =+(Y281*AH281+N281*W281+B281*K281+AJ281*AS281)/(K281+W281+AH281) -> 15.964843 | AW281: =+(AV281-$AW$1)/$AX$1 -> 2.6202861 | AX281: =+_xlfn.PERCENTILE.INC(OFFSET(AW281,-52,0,52,1),0.9) -> 1.6632636 | AY281: =+_xlfn.PERCENTILE.INC(OFFSET(AW281,-52,0,52,1),0.75) -> 1.5038188 | AZ281: =+_xlfn.PERCENTILE.INC(OFFSET(AW281,-52,0,52,1),0.5) -> 1.4053834 | BA281: =+_xlfn.PERCENTILE.INC(OFFSET(AW281,-52,0,52,1),0.25) -> 1.2932037 | BB281: =+_xlfn.PERCENTILE.INC(OFFSET(AW281,-52,0,52,1),0.1) -> 0.49796399
A282: 45583 | B282: 17.4742 | C282: -8.3569 | D282: -0.6401 | E282: 43.3526 | F282: 5.5847 | G282: 0 | H282: 7.2625 | I282: -7.1857 | J282: 2995 | K282: 11710916 | M282: 45583 | N282: 6.5245 | O282: 11.0935 | P282: 0.2946 | Q282: 35.1331 | R282: 0.9972 | S282: #N/A N/A | T282: 36.2807 | U282: 18.4906 | V282: 3250 | W282: 4431441.2 | Y282: 24.9 | Z282: -0.873 | AA282: 0.5772 | AB282: 4.2183 | AC282: -0.4904 | AD282: #N/A N/A | AE282: 4.4166 | AF282: 0.0787 | AG282: 108.709 | AH282: 764937.87 | AJ282: 5.7751 | AK282: 16.8274 | AL282: 0.4836 | AM282: 22.2797 | AN282: -0.1395 | AO282: 195.1108 | AP282: 49.9133 | AQ282: 37.493 | AR282: 4833.99 | AS282: 3793915.7 | AU282: =+A282 -> 45583 | AV282: =+(Y282*AH282+N282*W282+B282*K282+AJ282*AS282)/(K282+W282+AH282) -> 16.236129 | AW282: =+(AV282-$AW$1)/$AX$1 -> 2.7044955 | AX282: =+_xlfn.PERCENTILE.INC(OFFSET(AW282,-52,0,52,1),0.9) -> 1.8041223 | AY282: =+_xlfn.PERCENTILE.INC(OFFSET(AW282,-52,0,52,1),0.75) -> 1.632809 | AZ282: =+_xlfn.PERCENTILE.INC(OFFSET(AW282,-52,0,52,1),0.5) -> 1.4106123 | BA282: =+_xlfn.PERCENTILE.INC(OFFSET(AW282,-52,0,52,1),0.25) -> 1.293365 | BB282: =+_xlfn.PERCENTILE.INC(OFFSET(AW282,-52,0,52,1),0.1) -> 0.49796399
A283: 45590 | B283: 17.4742 | C283: -8.3569 | D283: -0.6401 | E283: 43.3526 | F283: 5.5847 | G283: 0 | H283: 7.2625 | I283: -7.1857 | J283: 2995 | K283: 11710916 | M283: 45590 | N283: 6.409 | O283: 11.0935 | P283: 0.2946 | Q283: 35.1331 | R283: 0.9972 | S283: #N/A N/A | T283: 36.2807 | U283: 18.4906 | V283: 3200 | W283: 4363265.2 | Y283: 25.5402 | Z283: -0.873 | AA283: 0.5772 | AB283: 4.2183 | AC283: -0.4904 | AD283: #N/A N/A | AE283: 4.4166 | AF283: 0.0787 | AG283: 111.479 | AH283: 784431.7 | AJ283: 5.9512 | AK283: 16.8274 | AL283: 0.4836 | AM283: 22.2797 | AN283: -0.1395 | AO283: 195.1108 | AP283: 49.9133 | AQ283: 37.493 | AR283: 4977.859 | AS283: 3906829.9 | AU283: =+A283 -> 45590 | AV283: =+(Y283*AH283+N283*W283+B283*K283+AJ283*AS283)/(K283+W283+AH283) -> 16.364806 | AW283: =+(AV283-$AW$1)/$AX$1 -> 2.7444379 | AX283: =+_xlfn.PERCENTILE.INC(OFFSET(AW283,-52,0,52,1),0.9) -> 2.273186 | AY283: =+_xlfn.PERCENTILE.INC(OFFSET(AW283,-52,0,52,1),0.75) -> 1.640025 | AZ283: =+_xlfn.PERCENTILE.INC(OFFSET(AW283,-52,0,52,1),0.5) -> 1.4584156 | BA283: =+_xlfn.PERCENTILE.INC(OFFSET(AW283,-52,0,52,1),0.25) -> 1.3406508 | BB283: =+_xlfn.PERCENTILE.INC(OFFSET(AW283,-52,0,52,1),0.1) -> 0.49796399
A284: 45597 | B284: 17.4137 | C284: -8.3569 | D284: -0.6401 | E284: 43.3526 | F284: 5.5847 | G284: 0 | H284: 7.2625 | I284: -7.1857 | J284: 2977.5 | K284: 11642489 | M284: 45597 | N284: 6.2404 | O284: 11.0935 | P284: 0.2946 | Q284: 35.1331 | R284: 0.9972 | S284: #N/A N/A | T284: 36.2807 | U284: 18.4906 | V284: 3125 | W284: 4261001.2 | Y284: 25.1048 | Z284: -0.873 | AA284: 0.5772 | AB284: 4.2183 | AC284: -0.4904 | AD284: #N/A N/A | AE284: 4.4166 | AF284: 0.0787 | AG284: 109.596 | AH284: 771175.9 | AJ284: 6.0803 | AK284: 16.8274 | AL284: 0.4836 | AM284: 22.2797 | AN284: -0.1395 | AO284: 195.1108 | AP284: 49.9133 | AQ284: 37.493 | AR284: 5083.363 | AS284: 3989633.6 | AU284: =+A284 -> 45597 | AV284: =+(Y284*AH284+N284*W284+B284*K284+AJ284*AS284)/(K284+W284+AH284) -> 16.368996 | AW284: =+(AV284-$AW$1)/$AX$1 -> 2.7457387 | AX284: =+_xlfn.PERCENTILE.INC(OFFSET(AW284,-52,0,52,1),0.9) -> 2.5836642 | AY284: =+_xlfn.PERCENTILE.INC(OFFSET(AW284,-52,0,52,1),0.75) -> 1.6449039 | AZ284: =+_xlfn.PERCENTILE.INC(OFFSET(AW284,-52,0,52,1),0.5) -> 1.4665284 | BA284: =+_xlfn.PERCENTILE.INC(OFFSET(AW284,-52,0,52,1),0.25) -> 1.3510947 | BB284: =+_xlfn.PERCENTILE.INC(OFFSET(AW284,-52,0,52,1),0.1) -> 0.80454287
A285: 45604 | B285: 18.7622 | C285: -8.3569 | D285: -0.6401 | E285: 43.3526 | F285: 5.5847 | G285: 0 | H285: 7.2625 | I285: -7.1857 | J285: 3367.5 | K285: 13167449 | M285: 45604 | N285: 6.4304 | O285: 11.0935 | P285: 0.2946 | Q285: 35.1331 | R285: 0.9972 | S285: #N/A N/A | T285: 36.2807 | U285: 18.4906 | V285: 3245 | W285: 4424623.6 | Y285: 26.8717 | Z285: -0.873 | AA285: 0.5772 | AB285: 4.2183 | AC285: -0.4904 | AD285: #N/A N/A | AE285: 4.4166 | AF285: 0.0787 | AG285: 117.242 | AH285: 824978.86 | AJ285: 6.1976 | AK285: 16.8274 | AL285: 0.4836 | AM285: 22.2797 | AN285: -0.1395 | AO285: 195.1108 | AP285: 49.9133 | AQ285: 37.493 | AR285: 5179.275 | AS285: 4064909.7 | AU285: =+A285 -> 45604 | AV285: =+(Y285*AH285+N285*W285+B285*K285+AJ285*AS285)/(K285+W285+AH285) -> 17.530693 | AW285: =+(AV285-$AW$1)/$AX$1 -> 3.1063397 | AX285: =+_xlfn.PERCENTILE.INC(OFFSET(AW285,-52,0,52,1),0.9) -> 2.6708118 | AY285: =+_xlfn.PERCENTILE.INC(OFFSET(AW285,-52,0,52,1),0.75) -> 1.6755035 | AZ285: =+_xlfn.PERCENTILE.INC(OFFSET(AW285,-52,0,52,1),0.5) -> 1.4768696 | BA285: =+_xlfn.PERCENTILE.INC(OFFSET(AW285,-52,0,52,1),0.25) -> 1.3685543 | BB285: =+_xlfn.PERCENTILE.INC(OFFSET(AW285,-52,0,52,1),0.1) -> 1.2932682
A286: 45611 | B286: 19.7477 | C286: -8.3569 | D286: -0.6401 | E286: 43.3526 | F286: 5.5847 | G286: 0 | H286: 7.2625 | I286: -7.1857 | J286: 3652.5 | K286: 14281844 | M286: 45611 | N286: 6.6995 | O286: 11.0935 | P286: 0.2946 | Q286: 35.1331 | R286: 0.9972 | S286: #N/A N/A | T286: 36.2807 | U286: 18.4906 | V286: 3415 | W286: 4656422.1 | Y286: 25.7962 | Z286: -0.873 | AA286: 0.5772 | AB286: 4.2183 | AC286: -0.4904 | AD286: #N/A N/A | AE286: 4.4166 | AF286: 0.0787 | AG286: 112.588 | AH286: 792229.23 | AJ286: 7.0308 | AK286: 16.8274 | AL286: 0.4836 | AM286: 22.2797 | AN286: -0.1395 | AO286: 195.1108 | AP286: 49.9133 | AQ286: 37.493 | AR286: 5860.254 | AS286: 4599370.1 | AU286: =+A286 -> 45611 | AV286: =+(Y286*AH286+N286*W286+B286*K286+AJ286*AS286)/(K286+W286+AH286) -> 18.550118 | AW286: =+(AV286-$AW$1)/$AX$1 -> 3.4227782 | AX286: =+_xlfn.PERCENTILE.INC(OFFSET(AW286,-52,0,52,1),0.9) -> 2.7284609 | AY286: =+_xlfn.PERCENTILE.INC(OFFSET(AW286,-52,0,52,1),0.75) -> 1.8898682 | AZ286: =+_xlfn.PERCENTILE.INC(OFFSET(AW286,-52,0,52,1),0.5) -> 1.4864193 | BA286: =+_xlfn.PERCENTILE.INC(OFFSET(AW286,-52,0,52,1),0.25) -> 1.3946743 | BB286: =+_xlfn.PERCENTILE.INC(OFFSET(AW286,-52,0,52,1),0.1) -> 1.3122793
A287: 45618 | B287: 22.6867 | C287: -8.3569 | D287: -0.6401 | E287: 43.3526 | F287: 5.5847 | G287: 0 | H287: 7.2625 | I287: -7.1857 | J287: 4502.5 | K287: 17605476 | M287: 45618 | N287: 7.2116 | O287: 11.0935 | P287: 0.2946 | Q287: 35.1331 | R287: 0.9972 | S287: #N/A N/A | T287: 36.2807 | U287: 18.4906 | V287: 3730 | W287: 5085931 | Y287: 26.8205 | Z287: -0.873 | AA287: 0.5772 | AB287: 4.2183 | AC287: -0.4904 | AD287: #N/A N/A | AE287: 4.4166 | AF287: 0.0787 | AG287: 117.02 | AH287: 823419.36 | AJ287: 7.5824 | AK287: 16.8274 | AL287: 0.4836 | AM287: 22.2797 | AN287: -0.1395 | AO287: 195.1108 | AP287: 49.9133 | AQ287: 37.493 | AR287: 6311.043 | AS287: 4953167.8 | AU287: =+A287 -> 45618 | AV287: =+(Y287*AH287+N287*W287+B287*K287+AJ287*AS287)/(K287+W287+AH287) -> 21.081562 | AW287: =+(AV287-$AW$1)/$AX$1 -> 4.2085606 | AX287: =+_xlfn.PERCENTILE.INC(OFFSET(AW287,-52,0,52,1),0.9) -> 2.7452184 | AY287: =+_xlfn.PERCENTILE.INC(OFFSET(AW287,-52,0,52,1),0.75) -> 2.5287312 | AZ287: =+_xlfn.PERCENTILE.INC(OFFSET(AW287,-52,0,52,1),0.5) -> 1.5038188 | BA287: =+_xlfn.PERCENTILE.INC(OFFSET(AW287,-52,0,52,1),0.25) -> 1.4053834 | BB287: =+_xlfn.PERCENTILE.INC(OFFSET(AW287,-52,0,52,1),0.1) -> 1.3448284
A288: 45625 | B288: 22.7386 | C288: -8.3569 | D288: -0.6401 | E288: 43.3526 | F288: 5.5847 | G288: 0 | H288: 7.2625 | I288: -7.1857 | J288: 4517.5 | K288: 17664128 | M288: 45625 | N288: 7.3847 | O288: 11.0935 | P288: 0.2946 | Q288: 35.1331 | R288: 0.9972 | S288: #N/A N/A | T288: 36.2807 | U288: 18.4906 | V288: 3855 | W288: 5256371.1 | Y288: 24.7207 | Z288: -0.873 | AA288: 0.5772 | AB288: 4.2183 | AC288: -0.4904 | AD288: #N/A N/A | AE288: 4.4166 | AF288: 0.0787 | AG288: 107.933 | AH288: 759479.6 | AJ288: 7.6059 | AK288: 16.8274 | AL288: 0.4836 | AM288: 22.2797 | AN288: -0.1395 | AO288: 195.1108 | AP288: 49.9133 | AQ288: 37.493 | AR288: 6330.225 | AS288: 4968223 | AU288: =+A288 -> 45625 | AV288: =+(Y288*AH288+N288*W288+B288*K288+AJ288*AS288)/(K288+W288+AH288) -> 20.989755 | AW288: =+(AV288-$AW$1)/$AX$1 -> 4.1800627 | AX288: =+_xlfn.PERCENTILE.INC(OFFSET(AW288,-52,0,52,1),0.9) -> 2.9620993 | AY288: =+_xlfn.PERCENTILE.INC(OFFSET(AW288,-52,0,52,1),0.75) -> 2.6202861 | AZ288: =+_xlfn.PERCENTILE.INC(OFFSET(AW288,-52,0,52,1),0.5) -> 1.5038188 | BA288: =+_xlfn.PERCENTILE.INC(OFFSET(AW288,-52,0,52,1),0.25) -> 1.4053834 | BB288: =+_xlfn.PERCENTILE.INC(OFFSET(AW288,-52,0,52,1),0.1) -> 1.3448284
A289: 45632 | B289: 21.6926 | C289: -8.3569 | D289: -0.6401 | E289: 43.3526 | F289: 5.5847 | G289: 0 | H289: 7.2625 | I289: -7.1857 | J289: 4215 | K289: 16481306 | M289: 45632 | N289: 7.1507 | O289: 11.0935 | P289: 0.2946 | Q289: 35.1331 | R289: 0.9972 | S289: #N/A N/A | T289: 36.2807 | U289: 18.4906 | V289: 3730 | W289: 5085931 | Y289: 22.9538 | Z289: -0.873 | AA289: 0.5772 | AB289: 4.2183 | AC289: -0.4904 | AD289: #N/A N/A | AE289: 4.4166 | AF289: 0.0787 | AG289: 100.287 | AH289: 705676.63 | AJ289: 7.0074 | AK289: 16.8274 | AL289: 0.4836 | AM289: 22.2797 | AN289: -0.1395 | AO289: 195.1108 | AP289: 49.9133 | AQ289: 37.493 | AR289: 5841.071 | AS289: 4584314.8 | AU289: =+A289 -> 45632 | AV289: =+(Y289*AH289+N289*W289+B289*K289+AJ289*AS289)/(K289+W289+AH289) -> 19.85427 | AW289: =+(AV289-$AW$1)/$AX$1 -> 3.8275982 | AX289: =+_xlfn.PERCENTILE.INC(OFFSET(AW289,-52,0,52,1),0.9) -> 3.2962028 | AY289: =+_xlfn.PERCENTILE.INC(OFFSET(AW289,-52,0,52,1),0.75) -> 2.7044955 | AZ289: =+_xlfn.PERCENTILE.INC(OFFSET(AW289,-52,0,52,1),0.5) -> 1.632809 | BA289: =+_xlfn.PERCENTILE.INC(OFFSET(AW289,-52,0,52,1),0.25) -> 1.4106123 | BB289: =+_xlfn.PERCENTILE.INC(OFFSET(AW289,-52,0,52,1),0.1) -> 1.3448284
A290: 45639 | B290: 23.8969 | C290: -8.3569 | D290: -0.6401 | E290: 43.3526 | F290: 5.5847 | G290: 0 | H290: 7.2625 | I290: -7.1857 | J290: 4852.5 | K290: 18974030 | M290: 45639 | N290: 7.3897 | O290: 11.0935 | P290: 0.2946 | Q290: 35.1331 | R290: 0.9972 | S290: #N/A N/A | T290: 36.2807 | U290: 18.4906 | V290: 3890 | W290: 5304094.3 | Y290: 24.9256 | Z290: -0.873 | AA290: 0.5772 | AB290: 4.2183 | AC290: -0.4904 | AD290: #N/A N/A | AE290: 4.4166 | AF290: 0.0787 | AG290: 108.82 | AH290: 765717.62 | AJ290: 7.4768 | AK290: 16.8274 | AL290: 0.4836 | AM290: 22.2797 | AN290: -0.1395 | AO290: 195.1108 | AP290: 49.9133 | AQ290: 37.493 | AR290: 6224.721 | AS290: 4885419.3 | AU290: =+A290 -> 45639 | AV290: =+(Y290*AH290+N290*W290+B290*K290+AJ290*AS290)/(K290+W290+AH290) -> 21.890788 | AW290: =+(AV290-$AW$1)/$AX$1 -> 4.4597515 | AX290: =+_xlfn.PERCENTILE.INC(OFFSET(AW290,-52,0,52,1),0.9) -> 3.6656702 | AY290: =+_xlfn.PERCENTILE.INC(OFFSET(AW290,-52,0,52,1),0.75) -> 2.7444379 | AZ290: =+_xlfn.PERCENTILE.INC(OFFSET(AW290,-52,0,52,1),0.5) -> 1.640025 | BA290: =+_xlfn.PERCENTILE.INC(OFFSET(AW290,-52,0,52,1),0.25) -> 1.4106123 | BB290: =+_xlfn.PERCENTILE.INC(OFFSET(AW290,-52,0,52,1),0.1) -> 1.3448284
A291: 45646 | B291: 24.1995 | C291: -8.3569 | D291: -0.6401 | E291: 43.3526 | F291: 5.5847 | G291: 0 | H291: 7.2625 | I291: -7.1857 | J291: 4940 | K291: 19316169 | M291: 45646 | N291: 7.6169 | O291: 11.0935 | P291: 0.2946 | Q291: 35.1331 | R291: 0.9972 | S291: #N/A N/A | T291: 36.2807 | U291: 18.4906 | V291: 4040 | W291: 5508622.3 | Y291: 24.9 | Z291: -0.873 | AA291: 0.5772 | AB291: 4.2183 | AC291: -0.4904 | AD291: #N/A N/A | AE291: 4.4166 | AF291: 0.0787 | AG291: 108.709 | AH291: 764937.87 | AJ291: 7.6059 | AK291: 16.8274 | AL291: 0.4836 | AM291: 22.2797 | AN291: -0.1395 | AO291: 195.1108 | AP291: 49.9133 | AQ291: 37.493 | AR291: 6330.225 | AS291: 4968223 | AU291: =+A291 -> 45646 | AV291: =+(Y291*AH291+N291*W291+B291*K291+AJ291*AS291)/(K291+W291+AH291) -> 22.127433 | AW291: =+(AV291-$AW$1)/$AX$1 -> 4.5332081 | AX291: =+_xlfn.PERCENTILE.INC(OFFSET(AW291,-52,0,52,1),0.9) -> 4.0390769 | AY291: =+_xlfn.PERCENTILE.INC(OFFSET(AW291,-52,0,52,1),0.75) -> 2.7457387 | AZ291: =+_xlfn.PERCENTILE.INC(OFFSET(AW291,-52,0,52,1),0.5) -> 1.6449039 | BA291: =+_xlfn.PERCENTILE.INC(OFFSET(AW291,-52,0,52,1),0.25) -> 1.4584156 | BB291: =+_xlfn.PERCENTILE.INC(OFFSET(AW291,-52,0,52,1),0.1) -> 1.3518122
... A305: 45744 | B305: 6.9552 | C305: 13.3738 | D305: 0.2826 | E305: 45.0157 | F305: 1.9368 | G305: 0 | H305: 21.9717 | I305: 7.6712 | J305: 4687.5 | K305: 18328855 | M305: 45744 | N305: 9.3503 | O305: 7.9386 | P305: 0.3527 | Q305: 38.8515 | R305: 0.7899 | S305: #N/A N/A | T305: 32.0651 | U305: 13.8709 | V305: 4145 | W305: 5651792 | Y305: 7.2697 | Z305: 9.5021 | AA305: 0.4015 | AB305: 4.7557 | AC305: -0.5985 | AD305: #N/A N/A | AE305: 10.5613 | AF305: 5.8359 | AG305: 81.67 | AH305: 574678.09 | AJ305: 5.7451 | AK305: 12.8408 | AL305: 0.7162 | AM305: 20.6179 | AN305: -0.3223 | AO305: 195.1108 | AP305: 57.1096 | AQ305: 46.0819 | AR305: 6828.97 | AS305: 5359658.7 | AU305: =+A305 -> 45744 | AV305: =+(Y305*AH305+N305*W305+B305*K305+AJ305*AS305)/(K305+W305+AH305) -> 8.7678056 | AW305: =+(AV305-$AW$1)/$AX$1 -> 0.38626224 | AX305: =+_xlfn.PERCENTILE.INC(OFFSET(AW305,-52,0,52,1),0.9) -> 4.3592751 | AY305: =+_xlfn.PERCENTILE.INC(OFFSET(AW305,-52,0,52,1),0.75) -> 3.4227782 | AZ305: =+_xlfn.PERCENTILE.INC(OFFSET(AW305,-52,0,52,1),0.5) -> 2.5287312 | BA305: =+_xlfn.PERCENTILE.INC(OFFSET(AW305,-52,0,52,1),0.25) -> 0.37844665 | BB305: =+_xlfn.PERCENTILE.INC(OFFSET(AW305,-52,0,52,1),0.1) -> 0.26789851
A306: 45751 | B306: 6.7468 | C306: 8.5348 | D306: 0.0947 | E306: 46.2805 | F306: 2.3039 | G306: 0 | H306: 20.0041 | I306: 5.135 | J306: 4015 | K306: 15699275 | M306: 45751 | N306: 8.1134 | O306: 5.9086 | P306: -0.1166 | Q306: 32.8706 | R306: 0.9118 | S306: #N/A N/A | T306: 34.0536 | U306: 15.2033 | V306: 3660 | W306: 4990484.6 | Y306: 7.2697 | Z306: -14.9096 | AA306: -0.6637 | AB306: 5.0711 | AC306: -0.5985 | AD306: 15.9076 | AE306: -9.8629 | AF306: -14.5936 | AG306: 68.04 | AH306: 478768.45 | AJ306: 4.6801 | AK306: 14.7561 | AL306: 0.7611 | AM306: 18.9114 | AN306: -0.081 | AO306: 195.1108 | AP306: 58.839 | AQ306: 47.5963 | AR306: 5984.94 | AS306: 4697229 | AU306: =+A306 -> 45751 | AV306: =+(Y306*AH306+N306*W306+B306*K306+AJ306*AS306)/(K306+W306+AH306) -> 8.1193019 | AW306: =+(AV306-$AW$1)/$AX$1 -> 0.184961 | AX306: =+_xlfn.PERCENTILE.INC(OFFSET(AW306,-52,0,52,1),0.9) -> 4.334156 | AY306: =+_xlfn.PERCENTILE.INC(OFFSET(AW306,-52,0,52,1),0.75) -> 3.3436686 | AZ306: =+_xlfn.PERCENTILE.INC(OFFSET(AW306,-52,0,52,1),0.5) -> 1.6025152 | BA306: =+_xlfn.PERCENTILE.INC(OFFSET(AW306,-52,0,52,1),0.25) -> 0.38040054 | BB306: =+_xlfn.PERCENTILE.INC(OFFSET(AW306,-52,0,52,1),0.1) -> 0.27033026
A307: 45758 | B307: 6.7493 | C307: 8.5348 | D307: 0.0947 | E307: 46.2805 | F307: 2.3039 | G307: 0 | H307: 20.0041 | I307: 5.135 | J307: 4017.5 | K307: 15709050 | M307: 45758 | N307: 8.2382 | O307: 5.9086 | P307: -0.1166 | Q307: 32.8706 | R307: 0.9118 | S307: #N/A N/A | T307: 34.0536 | U307: 15.2033 | V307: 3730 | W307: 5085931 | Y307: 7.2697 | Z307: -14.9096 | AA307: -0.6637 | AB307: 5.0711 | AC307: -0.5985 | AD307: 15.9076 | AE307: -9.8629 | AF307: -14.5936 | AG307: 69.148 | AH307: 486565.98 | AJ307: 5.0158 | AK307: 14.7561 | AL307: 0.7611 | AM307: 18.9114 | AN307: -0.081 | AO307: 195.1108 | AP307: 58.839 | AQ307: 47.5963 | AR307: 6406.955 | AS307: 5028443.9 | AU307: =+A307 -> 45758 | AV307: =+(Y307*AH307+N307*W307+B307*K307+AJ307*AS307)/(K307+W307+AH307) -> 8.3021627 | AW307: =+(AV307-$AW$1)/$AX$1 -> 0.24172258 | AX307: =+_xlfn.PERCENTILE.INC(OFFSET(AW307,-52,0,52,1),0.9) -> 4.3090369 | AY307: =+_xlfn.PERCENTILE.INC(OFFSET(AW307,-52,0,52,1),0.75) -> 3.2645589 | AZ307: =+_xlfn.PERCENTILE.INC(OFFSET(AW307,-52,0,52,1),0.5) -> 0.67629919 | BA307: =+_xlfn.PERCENTILE.INC(OFFSET(AW307,-52,0,52,1),0.25) -> 0.33945021 | BB307: =+_xlfn.PERCENTILE.INC(OFFSET(AW307,-52,0,52,1),0.1) -> 0.22888731
A308: 45765 | B308: 6.6104 | C308: 8.5348 | D308: 0.0947 | E308: 46.2805 | F308: 2.3039 | G308: 0 | H308: 20.0041 | I308: 5.135 | J308: 3882.5 | K308: 15181179 | M308: 45765 | N308: 7.4471 | O308: 5.9086 | P308: -0.1166 | Q308: 32.8706 | R308: 0.9118 | S308: #N/A N/A | T308: 34.0536 | U308: 15.2033 | V308: 3615 | W308: 4929126.2 | Y308: 7.2697 | Z308: -14.9096 | AA308: -0.6637 | AB308: 5.0711 | AC308: -0.5985 | AD308: 15.9076 | AE308: -9.8629 | AF308: -14.5936 | AG308: 63.718 | AH308: 448358.08 | AJ308: 4.7717 | AK308: 14.7561 | AL308: 0.7611 | AM308: 18.9114 | AN308: -0.081 | AO308: 195.1108 | AP308: 58.839 | AQ308: 47.5963 | AR308: 6100.035 | AS308: 4787560.3 | AU308: =+A308 -> 45765 | AV308: =+(Y308*AH308+N308*W308+B308*K308+AJ308*AS308)/(K308+W308+AH308) -> 7.9365856 | AW308: =+(AV308-$AW$1)/$AX$1 -> 0.12824425 | AX308: =+_xlfn.PERCENTILE.INC(OFFSET(AW308,-52,0,52,1),0.9) -> 4.2839178 | AY308: =+_xlfn.PERCENTILE.INC(OFFSET(AW308,-52,0,52,1),0.75) -> 3.1854493 | AZ308: =+_xlfn.PERCENTILE.INC(OFFSET(AW308,-52,0,52,1),0.5) -> 0.65915762 | BA308: =+_xlfn.PERCENTILE.INC(OFFSET(AW308,-52,0,52,1),0.25) -> 0.29801643 | BB308: =+_xlfn.PERCENTILE.INC(OFFSET(AW308,-52,0,52,1),0.1) -> 0.22469411
A309: 45772 | B309: 6.5641 | C309: 8.5348 | D309: 0.0947 | E309: 46.2805 | F309: 2.3039 | G309: 0 | H309: 20.0041 | I309: 5.135 | J309: 3837.5 | K309: 15005222 | M309: 45772 | N309: 7.4401 | O309: 5.9086 | P309: -0.1166 | Q309: 32.8706 | R309: 0.9118 | S309: #N/A N/A | T309: 34.0536 | U309: 15.2033 | V309: 3650 | W309: 4976849.4 | Y309: 7.2697 | Z309: -14.9096 | AA309: -0.6637 | AB309: 5.0711 | AC309: -0.5985 | AD309: 15.9076 | AE309: -9.8629 | AF309: -14.5936 | AG309: 61.945 | AH309: 435882.03 | AJ309: 4.6877 | AK309: 14.7561 | AL309: 0.7611 | AM309: 18.9114 | AN309: -0.081 | AO309: 195.1108 | AP309: 58.839 | AQ309: 47.5963 | AR309: 5994.531 | AS309: 4704756.6 | AU309: =+A309 -> 45772 | AV309: =+(Y309*AH309+N309*W309+B309*K309+AJ309*AS309)/(K309+W309+AH309) -> 7.8728387 | AW309: =+(AV309-$AW$1)/$AX$1 -> 0.10845664 | AX309: =+_xlfn.PERCENTILE.INC(OFFSET(AW309,-52,0,52,1),0.9) -> 4.2587988 | AY309: =+_xlfn.PERCENTILE.INC(OFFSET(AW309,-52,0,52,1),0.75) -> 3.1063397 | AZ309: =+_xlfn.PERCENTILE.INC(OFFSET(AW309,-52,0,52,1),0.5) -> 0.64201605 | BA309: =+_xlfn.PERCENTILE.INC(OFFSET(AW309,-52,0,52,1),0.25) -> 0.29070441 | BB309: =+_xlfn.PERCENTILE.INC(OFFSET(AW309,-52,0,52,1),0.1) -> 0.17776065
A310: 45779 | B310: 6.2786 | C310: 8.5348 | D310: 0.0947 | E310: 46.2805 | F310: 2.3039 | G310: 0 | H310: 20.0041 | I310: 5.135 | J310: 3560 | K310: 13920154 | M310: 45779 | N310: 6.9613 | O310: 5.9086 | P310: -0.1166 | Q310: 32.8706 | R310: 0.9118 | S310: #N/A N/A | T310: 34.0536 | U310: 15.2033 | V310: 3385 | W310: 4615516.5 | Y310: 7.2697 | Z310: -14.9096 | AA310: -0.6637 | AB310: 5.0711 | AC310: -0.5985 | AD310: 15.9076 | AE310: -9.8629 | AF310: -14.5936 | AG310: 57.956 | AH310: 407810.91 | AJ310: 4.5275 | AK310: 14.7561 | AL310: 0.7611 | AM310: 18.9114 | AN310: -0.081 | AO310: 195.1108 | AP310: 58.839 | AQ310: 47.5963 | AR310: 5793.115 | AS310: 4546676.8 | AU310: =+A310 -> 45779 | AV310: =+(Y310*AH310+N310*W310+B310*K310+AJ310*AS310)/(K310+W310+AH310) -> 7.5529314 | AW310: =+(AV310-$AW$1)/$AX$1 -> 0.0091546098 | AX310: =+_xlfn.PERCENTILE.INC(OFFSET(AW310,-52,0,52,1),0.9) -> 4.2336797 | AY310: =+_xlfn.PERCENTILE.INC(OFFSET(AW310,-52,0,52,1),0.75) -> 3.0161894 | AZ310: =+_xlfn.PERCENTILE.INC(OFFSET(AW310,-52,0,52,1),0.5) -> 0.53104977 | BA310: =+_xlfn.PERCENTILE.INC(OFFSET(AW310,-52,0,52,1),0.25) -> 0.28454285 | BB310: =+_xlfn.PERCENTILE.INC(OFFSET(AW310,-52,0,52,1),0.1) -> 0.14777669
A311: 45786 | B311: 6.5024 | C311: 8.5348 | D311: 0.0947 | E311: 46.2805 | F311: 2.3039 | G311: 0 | H311: 20.0041 | I311: 5.135 | J311: 3777.5 | K311: 14770613 | M311: 45786 | N311: 7.4942 | O311: 5.9086 | P311: -0.1166 | Q311: 32.8706 | R311: 0.9118 | S311: #N/A N/A | T311: 34.0536 | U311: 15.2033 | V311: 3495 | W311: 4765503.7 | Y311: 7.2697 | Z311: -14.9096 | AA311: -0.6637 | AB311: 5.0711 | AC311: -0.5985 | AD311: 15.9076 | AE311: -9.8629 | AF311: -14.5936 | AG311: 60.172 | AH311: 423405.98 | AJ311: 4.848 | AK311: 14.7561 | AL311: 0.7611 | AM311: 18.9114 | AN311: -0.081 | AO311: 195.1108 | AP311: 58.839 | AQ311: 47.5963 | AR311: 6195.948 | AS311: 4862836.4 | AU311: =+A311 -> 45786 | AV311: =+(Y311*AH311+N311*W311+B311*K311+AJ311*AS311)/(K311+W311+AH311) -> 7.9366195 | AW311: =+(AV311-$AW$1)/$AX$1 -> 0.12825477 | AX311: =+_xlfn.PERCENTILE.INC(OFFSET(AW311,-52,0,52,1),0.9) -> 4.2085606 | AY311: =+_xlfn.PERCENTILE.INC(OFFSET(AW311,-52,0,52,1),0.75) -> 2.9260392 | AZ311: =+_xlfn.PERCENTILE.INC(OFFSET(AW311,-52,0,52,1),0.5) -> 0.42008349 | BA311: =+_xlfn.PERCENTILE.INC(OFFSET(AW311,-52,0,52,1),0.25) -> 0.27033026 | BB311: =+_xlfn.PERCENTILE.INC(OFFSET(AW311,-52,0,52,1),0.1) -> 0.13713372
A312: 45793 | B312: 6.95 | C312: 8.5348 | D312: 0.0947 | E312: 46.2805 | F312: 2.3039 | G312: 0 | H312: 20.0041 | I312: 5.135 | J312: 4212.5 | K312: 16471531 | M312: 45793 | N312: 7.9604 | O312: 5.9086 | P312: -0.1166 | Q312: 32.8706 | R312: 0.9118 | S312: #N/A N/A | T312: 34.0536 | U312: 15.2033 | V312: 3860 | W312: 5263188.7 | Y312: 7.2697 | Z312: -14.9096 | AA312: -0.6637 | AB312: 5.0711 | AC312: -0.5985 | AD312: 15.9076 | AE312: -9.8629 | AF312: -14.5936 | AG312: 75.747 | AH312: 530232.16 | AJ312: 5.4202 | AK312: 14.7561 | AL312: 0.7611 | AM312: 18.9114 | AN312: -0.081 | AO312: 195.1108 | AP312: 58.839 | AQ312: 47.5963 | AR312: 6915.291 | AS312: 5427407.2 | AU312: =+A312 -> 45793 | AV312: =+(Y312*AH312+N312*W312+B312*K312+AJ312*AS312)/(K312+W312+AH312) -> 8.5177139 | AW312: =+(AV312-$AW$1)/$AX$1 -> 0.30863158 | AX312: =+_xlfn.PERCENTILE.INC(OFFSET(AW312,-52,0,52,1),0.9) -> 4.2057108 | AY312: =+_xlfn.PERCENTILE.INC(OFFSET(AW312,-52,0,52,1),0.75) -> 2.835889 | AZ312: =+_xlfn.PERCENTILE.INC(OFFSET(AW312,-52,0,52,1),0.5) -> 0.41443545 | BA312: =+_xlfn.PERCENTILE.INC(OFFSET(AW312,-52,0,52,1),0.25) -> 0.25405929 | BB312: =+_xlfn.PERCENTILE.INC(OFFSET(AW312,-52,0,52,1),0.1) -> 0.12914267
A313: 45800 | B313: 6.9937 | C313: 8.5348 | D313: 0.0947 | E313: 46.2805 | F313: 2.3039 | G313: 0 | H313: 20.0041 | I313: 5.135 | J313: 4255 | K313: 16637712 | M313: 45800 | N313: 7.9423 | O313: 5.9086 | P313: -0.1166 | Q313: 32.8706 | R313: 0.9118 | S313: #N/A N/A | T313: 34.0536 | U313: 15.2033 | V313: 3805 | W313: 5188195 | Y313: 7.2697 | Z313: -14.9096 | AA313: -0.6637 | AB313: 5.0711 | AC313: -0.5985 | AD313: 15.9076 | AE313: -9.8629 | AF313: -14.5936 | AG313: 73.52 | AH313: 514637.1 | AJ313: 5.4202 | AK313: 14.7561 | AL313: 0.7611 | AM313: 18.9114 | AN313: -0.081 | AO313: 195.1108 | AP313: 58.839 | AQ313: 47.5963 | AR313: 6915.291 | AS313: 5427407.2 | AU313: =+A313 -> 45800 | AV313: =+(Y313*AH313+N313*W313+B313*K313+AJ313*AS313)/(K313+W313+AH313) -> 8.5371357 | AW313: =+(AV313-$AW$1)/$AX$1 -> 0.31466028 | AX313: =+_xlfn.PERCENTILE.INC(OFFSET(AW313,-52,0,52,1),0.9) -> 4.202861 | AY313: =+_xlfn.PERCENTILE.INC(OFFSET(AW313,-52,0,52,1),0.75) -> 2.7457387 | AZ313: =+_xlfn.PERCENTILE.INC(OFFSET(AW313,-52,0,52,1),0.5) -> 0.40878741 | BA313: =+_xlfn.PERCENTILE.INC(OFFSET(AW313,-52,0,52,1),0.25) -> 0.25817152 | BB313: =+_xlfn.PERCENTILE.INC(OFFSET(AW313,-52,0,52,1),0.1) -> 0.13003056
A314: 45807 | B314: 7.0092 | C314: 8.5348 | D314: 0.0947 | E314: 46.2805 | F314: 2.3039 | G314: 0 | H314: 20.0041 | I314: 5.135 | J314: 4270 | K314: 16696365 | M314: 45807 | N314: 7.3375 | O314: 5.9086 | P314: -0.1166 | Q314: 32.8706 | R314: 0.9118 | S314: #N/A N/A | T314: 34.0536 | U314: 15.2033 | V314: 3700 | W314: 5045025.4 | Y314: 7.2697 | Z314: -14.9096 | AA314: -0.6637 | AB314: 5.0711 | AC314: -0.5985 | AD314: 15.9076 | AE314: -9.8629 | AF314: -14.5936 | AG314: 69.064 | AH314: 483446.97 | AJ314: 5.0692 | AK314: 14.7561 | AL314: 0.7611 | AM314: 18.9114 | AN314: -0.081 | AO314: 195.1108 | AP314: 58.839 | AQ314: 47.5963 | AR314: 6474.094 | AS314: 5081137.1 | AU314: =+A314 -> 45807 | AV314: =+(Y314*AH314+N314*W314+B314*K314+AJ314*AS314)/(K314+W314+AH314) -> 8.2483326 | AW314: =+(AV314-$AW$1)/$AX$1 -> 0.22501326 | AX314: =+_xlfn.PERCENTILE.INC(OFFSET(AW314,-52,0,52,1),0.9) -> 4.2000112 | AY314: =+_xlfn.PERCENTILE.INC(OFFSET(AW314,-52,0,52,1),0.75) -> 2.7454135 | AZ314: =+_xlfn.PERCENTILE.INC(OFFSET(AW314,-52,0,52,1),0.5) -> 0.40197939 | BA314: =+_xlfn.PERCENTILE.INC(OFFSET(AW314,-52,0,52,1),0.25) -> 0.26425089 | BB314: =+_xlfn.PERCENTILE.INC(OFFSET(AW314,-52,0,52,1),0.1) -> 0.13091846
A315: 45814 | B315: 6.7579 | C315: 8.5348 | D315: 0.0947 | E315: 46.2805 | F315: 2.3039 | G315: 0 | H315: 20.0041 | I315: 5.135 | J315: 4117.5 | K315: 15741729 | M315: 45814 | N315: 7.1095 | O315: 5.9086 | P315: -0.1166 | Q315: 32.8706 | R315: 0.9118 | S315: #N/A N/A | T315: 34.0536 | U315: 15.2033 | V315: 3550 | W315: 4826727.1 | Y315: 7.2697 | Z315: -14.9096 | AA315: -0.6637 | AB315: 5.0711 | AC315: -0.5985 | AD315: 15.9076 | AE315: -9.8629 | AF315: -14.5936 | AG315: 66.056 | AH315: 462393.64 | AJ315: 4.7945 | AK315: 14.7561 | AL315: 0.7611 | AM315: 18.9114 | AN315: -0.081 | AO315: 195.1108 | AP315: 58.839 | AQ315: 47.5963 | AR315: 6390 | AS315: 4810143.2 | AU315: =+A315 -> 45814 | AV315: =+(Y315*AH315+N315*W315+B315*K315+AJ315*AS315)/(K315+W315+AH315) -> 7.9464379 | AW315: =+(AV315-$AW$1)/$AX$1 -> 0.13130248 | AX315: =+_xlfn.PERCENTILE.INC(OFFSET(AW315,-52,0,52,1),0.9) -> 4.1971614 | AY315: =+_xlfn.PERCENTILE.INC(OFFSET(AW315,-52,0,52,1),0.75) -> 2.7450883 | AZ315: =+_xlfn.PERCENTILE.INC(OFFSET(AW315,-52,0,52,1),0.5) -> 0.39517137 | BA315: =+_xlfn.PERCENTILE.INC(OFFSET(AW315,-52,0,52,1),0.25) -> 0.24994705 | BB315: =+_xlfn.PERCENTILE.INC(OFFSET(AW315,-52,0,52,1),0.1) -> 0.13180635
A316: 45821 | B316: 6.9667 | C316: 8.5348 | D316: 0.0947 | E316: 46.2805 | F316: 2.3039 | G316: 0 | H316: 20.0041 | I316: 5.135 | J316: 4325 | K316: 16535028 | M316: 45821 | N316: 7.1777 | O316: 5.9086 | P316: -0.1166 | Q316: 32.8706 | R316: 0.9118 | S316: #N/A N/A | T316: 34.0536 | U316: 15.2033 | V316: 3565 | W316: 4847121.7 | Y316: 7.2697 | Z316: -14.9096 | AA316: -0.6637 | AB316: 5.0711 | AC316: -0.5985 | AD316: 15.9076 | AE316: -9.8629 | AF316: -14.5936 | AG316: 61.6 | AH316: 431203.51 | AJ316: 4.8022 | AK316: 14.7561 | AL316: 0.7611 | AM316: 18.9114 | AN316: -0.081 | AO316: 195.1108 | AP316: 58.839 | AQ316: 47.5963 | AR316: 6400 | AS316: 4817670.8 | AU316: =+A316 -> 45821 | AV316: =+(Y316*AH316+N316*W316+B316*K316+AJ316*AS316)/(K316+W316+AH316) -> 8.0801838 | AW316: =+(AV316-$AW$1)/$AX$1 -> 0.17281839 | AX316: =+_xlfn.PERCENTILE.INC(OFFSET(AW316,-52,0,52,1),0.9) -> 4.1943116 | AY316: =+_xlfn.PERCENTILE.INC(OFFSET(AW316,-52,0,52,1),0.75) -> 2.7447631 | AZ316: =+_xlfn.PERCENTILE.INC(OFFSET(AW316,-52,0,52,1),0.5) -> 0.3907168 | BA316: =+_xlfn.PERCENTILE.INC(OFFSET(AW316,-52,0,52,1),0.25) -> 0.23754525 | BB316: =+_xlfn.PERCENTILE.INC(OFFSET(AW316,-52,0,52,1),0.1) -> 0.12977862
A317: 45828 | B317: 6.7982 | C317: 8.5348 | D317: 0.0947 | E317: 46.2805 | F317: 2.3039 | G317: 0 | H317: 20.0041 | I317: 5.135 | J317: 4157.5 | K317: 15894654 | M317: 45828 | N317: 7.0581 | O317: 5.9086 | P317: -0.1166 | Q317: 32.8706 | R317: 0.9118 | S317: #N/A N/A | T317: 34.0536 | U317: 15.2033 | V317: 3430 | W317: 4663570.1 | Y317: 7.2697 | Z317: -14.9096 | AA317: -0.6637 | AB317: 5.0711 | AC317: -0.5985 | AD317: 15.9076 | AE317: -9.8629 | AF317: -14.5936 | AG317: 57.925 | AH317: 405471.65 | AJ317: 4.97 | AK317: 14.7561 | AL317: 0.7611 | AM317: 18.9114 | AN317: -0.081 | AO317: 195.1108 | AP317: 58.839 | AQ317: 47.5963 | AR317: 6620 | AS317: 4983278.2 | AU317: =+A317 -> 45828 | AV317: =+(Y317*AH317+N317*W317+B317*K317+AJ317*AS317)/(K317+W317+AH317) -> 8.046555 | AW317: =+(AV317-$AW$1)/$AX$1 -> 0.16237971 | AX317: =+_xlfn.PERCENTILE.INC(OFFSET(AW317,-52,0,52,1),0.9) -> 4.1914619 | AY317: =+_xlfn.PERCENTILE.INC(OFFSET(AW317,-52,0,52,1),0.75) -> 2.7444379 | AZ317: =+_xlfn.PERCENTILE.INC(OFFSET(AW317,-52,0,52,1),0.5) -> 0.38626224 | BA317: =+_xlfn.PERCENTILE.INC(OFFSET(AW317,-52,0,52,1),0.25) -> 0.22501326 | BB317: =+_xlfn.PERCENTILE.INC(OFFSET(AW317,-52,0,52,1),0.1) -> 0.13008339
... A385: 46304 | B385: 4.5143 | C385: 2.2759 | D385: 0.6913 | E385: 45.8688 | F385: 1.1856 | G385: 0 | H385: 34.0654 | I385: 18.471 | J385: 8065 | K385: 31724855 | M385: 46304 | N385: 6.0066 | O385: 7.662 | P385: 0.9978 | Q385: 39.403 | R385: 1.3473 | S385: #N/A N/A | T385: 41.3322 | U385: 20.7695 | V385: 5190 | W385: 7076670.8 | Y385: 11.9161 | Z385: -0.4615 | AA385: -0.0052 | AB385: 8.528 | AC385: -0.3422 | AD385: 15.9076 | AE385: 3.2685 | AF385: -0.7937 | AG385: 39.01 | AH385: 273070 | AJ385: 5.4762 | AK385: 11.7906 | AL385: 0.4427 | AM385: 30.1042 | AN385: -0.4446 | AO385: 0 | AP385: 55.6591 | AQ385: 43.8201 | AR385: 8340 | AS385: 6626090.7 | AU385: =+A385 -> 46304 | AV385: =+(Y385*AH385+N385*W385+B385*K385+AJ385*AS385)/(K385+W385+AH385) -> 5.7649213 | AW385: =+(AV385-$AW$1)/$AX$1 -> -0.54585945 | AX385: =+_xlfn.PERCENTILE.INC(OFFSET(AW385,-52,0,52,1),0.9) -> 0.69169996 | AY385: =+_xlfn.PERCENTILE.INC(OFFSET(AW385,-52,0,52,1),0.75) -> 0.1665913 | AZ385: =+_xlfn.PERCENTILE.INC(OFFSET(AW385,-52,0,52,1),0.5) -> 0.0018769895 | BA385: =+_xlfn.PERCENTILE.INC(OFFSET(AW385,-52,0,52,1),0.25) -> -0.37450025 | BB385: =+_xlfn.PERCENTILE.INC(OFFSET(AW385,-52,0,52,1),0.1) -> -0.49417852

Sheet Indice
B2: Start Date | C2: 38718
B3: End Date
I4: Retornos | O4: Ret EW | Q4: Indice EW | T4: Oil / Merval | V4: Mkt Cap | AC4: Ret MktCap W | AE4: Indice MktCap W | AH4: Ratio y percentiles
B5: Dates | C5: YPFD AR Equity | D5: PAMP AR Equity | E5: COME AR Equity | F5: TGSU2 AR EQUITY | G5: MERVAL Index | I5: =+C5 -> YPFD AR Equity | J5: =+D5 -> PAMP AR Equity | K5: =+E5 -> COME AR Equity | L5: =+F5 -> TGSU2 AR EQUITY | M5: =+G5 -> MERVAL Index | Q5: Indice | R5: Merval | V5: Dates | W5: =+I5 -> YPFD AR Equity | X5: =+J5 -> PAMP AR Equity | Y5: =+K5 -> COME AR Equity | Z5: =+L5 -> TGSU2 AR EQUITY | AE5: Indice | AF5: Merval | AH5: Fecha | AI5: Ratio | AJ5: Q10 | AK5: Q25 | AL5: Q50 | AM5: Q75 | AN5: Q90
B6: =_xll.BDH(C$5,"PX_LAST",$C2,$C3,"Dir=V","Per=W","Days=A","Dts=S","cols=2;rows=1084") -> 38723 | C6: 10.118 | D6: =_xll.BDH(D$5,"PX_LAST",$C2,$C3,"Dir=V","Per=W","Days=A","Dts=H","cols=1;rows=1084") -> 3.222 | E6: =_xll.BDH(E$5,"PX_LAST",$C2,$C3,"Dir=V","Per=W","Days=A","Dts=H","cols=1;rows=1084") -> 0.097 | F6: =_xll.BDH(F$5,"PX_LAST",$C2,$C3,"Dir=V","Per=W","Days=A","Dts=H","cols=1;rows=1084") -> 1.667 | G6: =_xll.BDH(G$5,"PX_LAST",$C2,$C3,"Dir=V","Per=W","Days=A","Dts=H","cols=1;rows=1084") -> 1616.29 | Q6: 100 | R6: 100 | T6: =+Q6/R6 -> 1 | V6: =_xll.BDH(W$5,"CUR_MKT_CAP",$C2,$C3,"Dir=V","Per=W","Days=A","Dts=S","cols=2;rows=1084") -> 38723 | W6: 68829.747 | X6: =_xll.BDH(X$5,"CUR_MKT_CAP",$C2,$C3,"Dir=V","Per=W","Days=A","Dts=H","cols=1;rows=1084") -> 20.4 | Y6: =_xll.BDH(Y$5,"CUR_MKT_CAP",$C2,$C3,"Dir=V","Per=W","Days=A","Dts=H","cols=1;rows=1084") -> 15.7349 | Z6: =_xll.BDH(Z$5,"CUR_MKT_CAP",$C2,$C3,"Dir=V","Per=W","Days=A","Dts=H","cols=1;rows=1084") -> 2860.1831 | AE6: 100 | AF6: 100 | AH6: =+B6 -> 38723 | AI6: =+(AE6/$AE$6)/(AF6/$AF$6) -> 1
B7: 38730 | C7: 9.627 | D7: 2.606 | E7: 0.097 | F7: 1.56 | G7: 1645.24 | I7: =+C7/C6-1 -> -0.048527377 | J7: =+D7/D6-1 -> -0.1911856 | K7: =+E7/E6-1 -> 0 | L7: =+F7/F6-1 -> -0.064187163 | M7: =+G7/G6-1 -> 0.01791139 | O7: =+AVERAGE(I7:L7) -> -0.075975035 | Q7: =+Q6*(1+O7) -> 92.402497 | R7: =+R6*(1+M7) -> 101.79114 | T7: =+Q7/R7 -> 0.90776562 | V7: 38730 | W7: 65486.588 | X7: 16.5 | Y7: 15.6828 | Z7: 2677.4492 | AC7: =+SUMPRODUCT(I7:L7,W6:Z6)/SUM(W6:AA6) -> -0.049181763 | AE7: =+AE6*(1+AC7) -> 95.081824 | AF7: =+AF6*(1+M7) -> 101.79114 | AH7: =+B7 -> 38730 | AI7: =+(AE7/$AE$6)/(AF7/$AF$6) -> 0.93408743
B8: 38737 | C8: 9.974 | D8: 2.795 | E8: 0.103 | F8: 1.574 | G8: 1701.88 | I8: =+C8/C7-1 -> 0.036044458 | J8: =+D8/D7-1 -> 0.072524942 | K8: =+E8/E7-1 -> 0.06185567 | L8: =+F8/F7-1 -> 0.008974359 | M8: =+G8/G7-1 -> 0.034426588 | O8: =+AVERAGE(I8:L8) -> 0.044849857 | Q8: =+Q7*(1+O8) -> 96.546735 | R8: =+R7*(1+M8) -> 105.29546 | T8: =+Q8/R8 -> 0.91691261 | V8: 38737 | W8: 67846.465 | X8: 17.7 | Y8: 16.7249 | Z8: 2701.284 | AC8: =+SUMPRODUCT(I8:L8,W7:Z7)/SUM(W7:AA7) -> 0.034996422 | AE8: =+AE7*(1+AC8) -> 98.409347 | AF8: =+AF7*(1+M8) -> 105.29546 | AH8: =+B8 -> 38737 | AI8: =+(AE8/$AE$6)/(AF8/$AF$6) -> 0.93460199
B9: 38744 | C9: 9.818 | D9: 2.843 | E9: 0.103 | F9: 1.505 | G9: 1739.83 | I9: =+C9/C8-1 -> -0.015640666 | J9: =+D9/D8-1 -> 0.017173524 | K9: =+E9/E8-1 -> 0 | L9: =+F9/F8-1 -> -0.043837357 | M9: =+G9/G8-1 -> 0.022298869 | O9: =+AVERAGE(I9:L9) -> -0.010576125 | Q9: =+Q8*(1+O9) -> 95.525645 | R9: =+R8*(1+M9) -> 107.64343 | T9: =+Q9/R9 -> 0.88742662 | V9: 38744 | W9: 66784.521 | X9: 18 | Y9: 16.6467 | Z9: 2582.1097 | AC9: =+SUMPRODUCT(I9:L9,W8:Z8)/SUM(W8:AA8) -> -0.01670786 | AE9: =+AE8*(1+AC9) -> 96.765138 | AF9: =+AF8*(1+M9) -> 107.64343 | AH9: =+B9 -> 38744 | AI9: =+(AE9/$AE$6)/(AF9/$AF$6) -> 0.89894142
B10: 38751 | C10: 9.309 | D10: 2.843 | E10: 0.109 | F10: 1.486 | G10: 1703.33 | I10: =+C10/C9-1 -> -0.051843553 | J10: =+D10/D9-1 -> 0 | K10: =+E10/E9-1 -> 0.058252427 | L10: =+F10/F9-1 -> -0.012624585 | M10: =+G10/G9-1 -> -0.020979061 | O10: =+AVERAGE(I10:L10) -> -0.0015539275 | Q10: =+Q9*(1+O10) -> 95.377205 | R10: =+R9*(1+M10) -> 105.38517 | T10: =+Q10/R10 -> 0.90503439 | V10: 38751 | W10: 63323.368 | X10: 18 | Y10: 17.6367 | Z10: 2550.3299 | AC10: =+SUMPRODUCT(I10:L10,W9:Z9)/SUM(W9:AA9) -> -0.050344537 | AE10: =+AE9*(1+AC10) -> 91.893542 | AF10: =+AF9*(1+M10) -> 105.38517 | AH10: =+B10 -> 38751 | AI10: =+(AE10/$AE$6)/(AF10/$AF$6) -> 0.87197791
B11: 38758 | C11: 9.338 | D11: 2.843 | E11: 0.11 | F11: 1.505 | G11: 1695.48 | I11: =+C11/C10-1 -> 0.0031152648 | J11: =+D11/D10-1 -> 0 | K11: =+E11/E10-1 -> 0.0091743119 | L11: =+F11/F10-1 -> 0.012786003 | M11: =+G11/G10-1 -> -0.0046086196 | O11: =+AVERAGE(I11:L11) -> 0.0062688949 | Q11: =+Q10*(1+O11) -> 95.975115 | R11: =+R10*(1+M11) -> 104.89949 | T11: =+Q11/R11 -> 0.91492449 | V11: 38758 | W11: 63520.024 | X11: 18 | Y11: 17.8451 | Z11: 2582.1097 | AC11: =+SUMPRODUCT(I11:L11,W10:Z10)/SUM(W10:AA10) -> 0.0034902399 | AE11: =+AE10*(1+AC11) -> 92.214272 | AF11: =+AF10*(1+M11) -> 104.89949 | AH11: =+B11 -> 38758 | AI11: =+(AE11/$AE$6)/(AF11/$AF$6) -> 0.87907263
B12: 38765 | C12: 9.309 | D12: 2.653 | E12: 0.107 | F12: 1.444 | G12: 1699.49 | I12: =+C12/C11-1 -> -0.0031055901 | J12: =+D12/D11-1 -> -0.066830813 | K12: =+E12/E11-1 -> -0.027272727 | L12: =+F12/F11-1 -> -0.040531561 | M12: =+G12/G11-1 -> 0.0023651119 | O12: =+AVERAGE(I12:L12) -> -0.034435173 | Q12: =+Q11*(1+O12) -> 92.670195 | R12: =+R11*(1+M12) -> 105.14759 | T12: =+Q12/R12 -> 0.88133446 | V12: 38765 | W12: 63323.368 | X12: 16.8 | Y12: 17.298 | Z12: 2478.8253 | AC12: =+SUMPRODUCT(I12:L12,W11:Z11)/SUM(W11:AA11) -> -0.004590611 | AE12: =+AE11*(1+AC12) -> 91.790952 | AF12: =+AF11*(1+M12) -> 105.14759 | AH12: =+B12 -> 38765 | AI12: =+(AE12/$AE$6)/(AF12/$AF$6) -> 0.87297247
B13: 38772 | C13: 9.517 | D13: 2.653 | E13: 0.11 | F13: 1.482 | G13: 1726.65 | I13: =+C13/C12-1 -> 0.022343968 | J13: =+D13/D12-1 -> 0 | K13: =+E13/E12-1 -> 0.028037383 | L13: =+F13/F12-1 -> 0.026315789 | M13: =+G13/G12-1 -> 0.015981265 | O13: =+AVERAGE(I13:L13) -> 0.019174285 | Q13: =+Q12*(1+O13) -> 94.44708 | R13: =+R12*(1+M13) -> 106.82798 | T13: =+Q13/R13 -> 0.88410431 | V13: 38772 | W13: 64739.294 | X13: 16.8 | Y13: 17.7669 | Z13: 2542.385 | AC13: =+SUMPRODUCT(I13:L13,W12:Z12)/SUM(W12:AA12) -> 0.022489307 | AE13: =+AE12*(1+AC13) -> 93.855267 | AF13: =+AF12*(1+M13) -> 106.82798 | AH13: =+B13 -> 38772 | AI13: =+(AE13/$AE$6)/(AF13/$AF$6) -> 0.87856445
B14: 38779 | C14: 9.829 | D14: 1.706 | E14: 0.106 | F14: 1.468 | G14: 1823.56 | I14: =+C14/C13-1 -> 0.03278344 | J14: =+D14/D13-1 -> -0.35695439 | K14: =+E14/E13-1 -> -0.036363636 | L14: =+F14/F13-1 -> -0.0094466937 | M14: =+G14/G13-1 -> 0.056126024 | O14: =+AVERAGE(I14:L14) -> -0.09249532 | Q14: =+Q13*(1+O14) -> 85.711167 | R14: =+R13*(1+M14) -> 112.82381 | T14: =+Q14/R14 -> 0.7596904 | V14: 38779 | W14: 66863.183 | X14: 10.8 | Y14: 17.1938 | Z14: 2518.5501 | AC14: =+SUMPRODUCT(I14:L14,W13:Z13)/SUM(W13:AA13) -> 0.031072986 | AE14: =+AE13*(1+AC14) -> 96.771631 | AF14: =+AF13*(1+M14) -> 112.82381 | AH14: =+B14 -> 38779 | AI14: =+(AE14/$AE$6)/(AF14/$AF$6) -> 0.85772346
B15: 38786 | C15: 9.829 | D15: 1.421 | E15: 0.101 | F15: 1.407 | G15: 1762.56 | I15: =+C15/C14-1 -> 0 | J15: =+D15/D14-1 -> -0.16705744 | K15: =+E15/E14-1 -> -0.047169811 | L15: =+F15/F14-1 -> -0.041553134 | M15: =+G15/G14-1 -> -0.033451052 | O15: =+AVERAGE(I15:L15) -> -0.063945097 | Q15: =+Q14*(1+O15) -> 80.230358 | R15: =+R14*(1+M15) -> 109.04974 | T15: =+Q15/R15 -> 0.73572262 | V15: 38786 | W15: 66863.183 | X15: 9 | Y15: 16.3341 | Z15: 2415.2657 | AC15: =+SUMPRODUCT(I15:L15,W14:Z14)/SUM(W14:AA14) -> -0.0015454447 | AE15: =+AE14*(1+AC15) -> 96.622075 | AF15: =+AF14*(1+M15) -> 109.04974 | AH15: =+B15 -> 38786 | AI15: =+(AE15/$AE$6)/(AF15/$AF$6) -> 0.88603676
B16: 38793 | C16: 9.743 | D16: 1.374 | E16: 0.1 | F16: 1.421 | G16: 1810.63 | I16: =+C16/C15-1 -> -0.0087496185 | J16: =+D16/D15-1 -> -0.033075299 | K16: =+E16/E15-1 -> -0.0099009901 | L16: =+F16/F15-1 -> 0.0099502488 | M16: =+G16/G15-1 -> 0.02727283 | O16: =+AVERAGE(I16:L16) -> -0.010443915 | Q16: =+Q15*(1+O16) -> 79.392439 | R16: =+R15*(1+M16) -> 112.02383 | T16: =+Q16/R16 -> 0.70871026 | V16: 38793 | W16: 66273.214 | X16: 8.7 | Y16: 16.282 | Z16: 2439.1006 | AC16: =+SUMPRODUCT(I16:L16,W15:Z15)/SUM(W15:AA15) -> -0.0081013507 | AE16: =+AE15*(1+AC16) -> 95.839306 | AF16: =+AF15*(1+M16) -> 112.02383 | AH16: =+B16 -> 38793 | AI16: =+(AE16/$AE$6)/(AF16/$AF$6) -> 0.85552604
B17: 38800 | C17: 9.251 | D17: 1.327 | E17: 0.1 | F17: 1.375 | G17: 1794.12 | I17: =+C17/C16-1 -> -0.050497793 | J17: =+D17/D16-1 -> -0.034206696 | K17: =+E17/E16-1 -> 0 | L17: =+F17/F16-1 -> -0.032371569 | M17: =+G17/G16-1 -> -0.0091183732 | O17: =+AVERAGE(I17:L17) -> -0.029269015 | Q17: =+Q16*(1+O17) -> 77.068701 | R17: =+R16*(1+M17) -> 111.00236 | T17: =+Q17/R17 -> 0.69429787 | V17: 38800 | W17: 62930.055 | X17: 8.4 | Y17: 16.2038 | Z17: 2359.651 | AC17: =+SUMPRODUCT(I17:L17,W16:Z16)/SUM(W16:AA16) -> -0.049840572 | AE17: =+AE16*(1+AC17) -> 91.06262 | AF17: =+AF16*(1+M17) -> 111.00236 | AH17: =+B17 -> 38800 | AI17: =+(AE17/$AE$6)/(AF17/$AF$6) -> 0.82036655
B18: 38807 | C18: 9.251 | D18: 1.308 | E18: 0.098 | F18: 1.477 | G18: 1800.58 | I18: =+C18/C17-1 -> 0 | J18: =+D18/D17-1 -> -0.014318011 | K18: =+E18/E17-1 -> -0.02 | L18: =+F18/F17-1 -> 0.074181818 | M18: =+G18/G17-1 -> 0.003600651 | O18: =+AVERAGE(I18:L18) -> 0.0099659519 | Q18: =+Q17*(1+O18) -> 77.836764 | R18: =+R17*(1+M18) -> 111.40204 | T18: =+Q18/R18 -> 0.69870143 | V18: 38807 | W18: 62930.055 | X18: 8.28 | Y18: 15.8912 | Z18: 2534.44 | AC18: =+SUMPRODUCT(I18:L18,W17:Z17)/SUM(W17:AA17) -> 0.0026732098 | AE18: =+AE17*(1+AC18) -> 91.30605 | AF18: =+AF17*(1+M18) -> 111.40204 | AH18: =+B18 -> 38807 | AI18: =+(AE18/$AE$6)/(AF18/$AF$6) -> 0.81960843
... B57: 39080 | C57: 8.726 | D57: 2.179 | E57: 0.085 | F57: 1.94 | G57: 2090.46 | I57: =+C57/C56-1 -> 0.0069236095 | J57: =+D57/D56-1 -> 0.084619214 | K57: =+E57/E56-1 -> 0.1038961 | L57: =+F57/F56-1 -> 0.047516199 | M57: =+G57/G56-1 -> 0.016014503 | O57: =+AVERAGE(I57:L57) -> 0.060738781 | Q57: =+Q56*(1+O57) -> 102.11911 | R57: =+R56*(1+M57) -> 129.33694 | T57: =+Q57/R57 -> 0.78955876 | V57: 39080 | W57: 57030.362 | X57: 1025.8 | Y57: 13.8071 | Z57: 3328.9353 | AC57: =+SUMPRODUCT(I57:L57,W56:Z56)/SUM(W56:AA56) -> 0.010274979 | AE57: =+AE56*(1+AC57) -> 88.02287 | AF57: =+AF56*(1+M57) -> 129.33694 | AH57: =+B57 -> 39080 | AI57: =+(AE57/$AE$6)/(AF57/$AF$6) -> 0.68057023
B58: 39087 | C58: 8.425 | D58: 2.208 | E58: 0.085 | F58: 1.935 | G58: 2063.88 | I58: =+C58/C57-1 -> -0.034494614 | J58: =+D58/D57-1 -> 0.013308857 | K58: =+E58/E57-1 -> 0 | L58: =+F58/F57-1 -> -0.0025773196 | M58: =+G58/G57-1 -> -0.012714905 | O58: =+AVERAGE(I58:L58) -> -0.005940769 | Q58: =+Q57*(1+O58) -> 101.51245 | R58: =+R57*(1+M58) -> 127.69243 | T58: =+Q58/R58 -> 0.79497622 | V58: 39087 | W58: 55063.798 | X58: 1039.18 | Y58: 13.755 | Z58: 3320.9904 | AC58: =+SUMPRODUCT(I58:L58,W57:Z57)/SUM(W57:AA57) -> -0.031957701 | AE58: =+AE57*(1+AC58) -> 85.209861 | AF58: =+AF57*(1+M58) -> 127.69243 | AH58: =+B58 -> 39087 | AI58: =+(AE58/$AE$6)/(AF58/$AF$6) -> 0.6673055 | AJ58: =+_xlfn.PERCENTILE.INC(OFFSET(AI58,-52,0,52,1),0.1) -> 0.71001223 | AK58: =+_xlfn.PERCENTILE.INC(OFFSET(AI58,-52,0,52,1),0.25) -> 0.74192072 | AL58: =+_xlfn.PERCENTILE.INC(OFFSET(AI58,-52,0,52,1),0.5) -> 0.78237478 | AM58: =+_xlfn.PERCENTILE.INC(OFFSET(AI58,-52,0,52,1),0.75) -> 0.83320049 | AN58: =+_xlfn.PERCENTILE.INC(OFFSET(AI58,-52,0,52,1),0.9) -> 0.87902181
B59: 39094 | C59: 8.245 | D59: 2.189 | E59: 0.083 | F59: 1.972 | G59: 2072.62 | I59: =+C59/C58-1 -> -0.021364985 | J59: =+D59/D58-1 -> -0.0086050725 | K59: =+E59/E58-1 -> -0.023529412 | L59: =+F59/F58-1 -> 0.019121447 | M59: =+G59/G58-1 -> 0.0042347423 | O59: =+AVERAGE(I59:L59) -> -0.0085945056 | Q59: =+Q58*(1+O59) -> 100.64 | R59: =+R58*(1+M59) -> 128.23318 | T59: =+Q59/R59 -> 0.78482028 | V59: 39094 | W59: 53883.859 | X59: 1030.26 | Y59: 13.4164 | Z59: 3384.55 | AC59: =+SUMPRODUCT(I59:L59,W58:Z58)/SUM(W58:AA58) -> -0.018880282 | AE59: =+AE58*(1+AC59) -> 83.601075 | AF59: =+AF58*(1+M59) -> 128.23318 | AH59: =+B59 -> 39094 | AI59: =+(AE59/$AE$6)/(AF59/$AF$6) -> 0.65194576 | AJ59: =+_xlfn.PERCENTILE.INC(OFFSET(AI59,-52,0,52,1),0.1) -> 0.70576683 | AK59: =+_xlfn.PERCENTILE.INC(OFFSET(AI59,-52,0,52,1),0.25) -> 0.73891562 | AL59: =+_xlfn.PERCENTILE.INC(OFFSET(AI59,-52,0,52,1),0.5) -> 0.7775169 | AM59: =+_xlfn.PERCENTILE.INC(OFFSET(AI59,-52,0,52,1),0.75) -> 0.82309572 | AN59: =+_xlfn.PERCENTILE.INC(OFFSET(AI59,-52,0,52,1),0.9) -> 0.87800525
B60: 39101 | C60: 7.583 | D60: 2.113 | E60: 0.083 | F60: 1.944 | G60: 2037.32 | I60: =+C60/C59-1 -> -0.080291086 | J60: =+D60/D59-1 -> -0.03471905 | K60: =+E60/E59-1 -> 0 | L60: =+F60/F59-1 -> -0.014198783 | M60: =+G60/G59-1 -> -0.017031583 | O60: =+AVERAGE(I60:L60) -> -0.03230223 | Q60: =+Q59*(1+O60) -> 97.389101 | R60: =+R59*(1+M60) -> 126.04916 | T60: =+Q60/R60 -> 0.77262792 | V60: 39101 | W60: 49557.418 | X60: 994.58 | Y60: 13.4424 | Z60: 3336.8803 | AC60: =+SUMPRODUCT(I60:L60,W59:Z59)/SUM(W59:AA59) -> -0.075631315 | AE60: =+AE59*(1+AC60) -> 77.278216 | AF60: =+AF59*(1+M60) -> 126.04916 | AH60: =+B60 -> 39101 | AI60: =+(AE60/$AE$6)/(AF60/$AF$6) -> 0.61307997 | AJ60: =+_xlfn.PERCENTILE.INC(OFFSET(AI60,-52,0,52,1),0.1) -> 0.69982751 | AK60: =+_xlfn.PERCENTILE.INC(OFFSET(AI60,-52,0,52,1),0.25) -> 0.7307288 | AL60: =+_xlfn.PERCENTILE.INC(OFFSET(AI60,-52,0,52,1),0.5) -> 0.77320636 | AM60: =+_xlfn.PERCENTILE.INC(OFFSET(AI60,-52,0,52,1),0.75) -> 0.81979796 | AN60: =+_xlfn.PERCENTILE.INC(OFFSET(AI60,-52,0,52,1),0.9) -> 0.87287301
B61: 39108 | C61: 8.546 | D61: 2.244 | E61: 0.083 | F61: 1.898 | G61: 2039.46 | I61: =+C61/C60-1 -> 0.12699459 | J61: =+D61/D60-1 -> 0.06199716 | K61: =+E61/E60-1 -> 0 | L61: =+F61/F60-1 -> -0.023662551 | M61: =+G61/G60-1 -> 0.0010503995 | O61: =+AVERAGE(I61:L61) -> 0.041332301 | Q61: =+Q60*(1+O61) -> 101.41442 | R61: =+R60*(1+M61) -> 126.18156 | T61: =+Q61/R61 -> 0.80371818 | V61: 39108 | W61: 55850.424 | X61: 1030.26 | Y61: 13.4685 | Z61: 3257.4307 | AC61: =+SUMPRODUCT(I61:L61,W60:Z60)/SUM(W60:AA60) -> 0.11643703 | AE61: =+AE60*(1+AC61) -> 86.276262 | AF61: =+AF60*(1+M61) -> 126.18156 | AH61: =+B61 -> 39108 | AI61: =+(AE61/$AE$6)/(AF61/$AF$6) -> 0.68374697 | AJ61: =+_xlfn.PERCENTILE.INC(OFFSET(AI61,-52,0,52,1),0.1) -> 0.68591414 | AK61: =+_xlfn.PERCENTILE.INC(OFFSET(AI61,-52,0,52,1),0.25) -> 0.72895601 | AL61: =+_xlfn.PERCENTILE.INC(OFFSET(AI61,-52,0,52,1),0.5) -> 0.77269357 | AM61: =+_xlfn.PERCENTILE.INC(OFFSET(AI61,-52,0,52,1),0.75) -> 0.81382712 | AN61: =+_xlfn.PERCENTILE.INC(OFFSET(AI61,-52,0,52,1),0.9) -> 0.87055246
B62: 39115 | C62: 8.877 | D62: 2.254 | E62: 0.09 | F62: 1.88 | G62: 2081.27 | I62: =+C62/C61-1 -> 0.03873157 | J62: =+D62/D61-1 -> 0.004456328 | K62: =+E62/E61-1 -> 0.084337349 | L62: =+F62/F61-1 -> -0.009483667 | M62: =+G62/G61-1 -> 0.020500525 | O62: =+AVERAGE(I62:L62) -> 0.029510395 | Q62: =+Q61*(1+O62) -> 104.4072 | R62: =+R61*(1+M62) -> 128.76835 | T62: =+Q62/R62 -> 0.81081411 | V62: 39115 | W62: 58013.644 | X62: 1034.72 | Y62: 14.5887 | Z62: 3225.6509 | AC62: =+SUMPRODUCT(I62:L62,W61:Z61)/SUM(W61:AA61) -> 0.035543691 | AE62: =+AE61*(1+AC62) -> 89.342839 | AF62: =+AF61*(1+M62) -> 128.76835 | AH62: =+B62 -> 39115 | AI62: =+(AE62/$AE$6)/(AF62/$AF$6) -> 0.69382606 | AJ62: =+_xlfn.PERCENTILE.INC(OFFSET(AI62,-52,0,52,1),0.1) -> 0.68381594 | AK62: =+_xlfn.PERCENTILE.INC(OFFSET(AI62,-52,0,52,1),0.25) -> 0.72680631 | AL62: =+_xlfn.PERCENTILE.INC(OFFSET(AI62,-52,0,52,1),0.5) -> 0.76986176 | AM62: =+_xlfn.PERCENTILE.INC(OFFSET(AI62,-52,0,52,1),0.75) -> 0.80938704 | AN62: =+_xlfn.PERCENTILE.INC(OFFSET(AI62,-52,0,52,1),0.9) -> 0.85750372
B63: 39122 | C63: 8.413 | D63: 2.283 | E63: 0.085 | F63: 1.833 | G63: 2100.24 | I63: =+C63/C62-1 -> -0.052269911 | J63: =+D63/D62-1 -> 0.012866016 | K63: =+E63/E62-1 -> -0.055555556 | L63: =+F63/F62-1 -> -0.025 | M63: =+G63/G62-1 -> 0.0091146271 | O63: =+AVERAGE(I63:L63) -> -0.029989863 | Q63: =+Q62*(1+O63) -> 101.27604 | R63: =+R62*(1+M63) -> 129.94203 | T63: =+Q63/R63 -> 0.77939402 | V63: 39122 | W63: 54985.135 | X63: 1048.1 | Y63: 13.8592 | Z63: 3146.2014 | AC63: =+SUMPRODUCT(I63:L63,W62:Z62)/SUM(W62:AA62) -> -0.049776474 | AE63: =+AE62*(1+AC63) -> 84.895667 | AF63: =+AF62*(1+M63) -> 129.94203 | AH63: =+B63 -> 39122 | AI63: =+(AE63/$AE$6)/(AF63/$AF$6) -> 0.65333494 | AJ63: =+_xlfn.PERCENTILE.INC(OFFSET(AI63,-52,0,52,1),0.1) -> 0.68381594 | AK63: =+_xlfn.PERCENTILE.INC(OFFSET(AI63,-52,0,52,1),0.25) -> 0.72409201 | AL63: =+_xlfn.PERCENTILE.INC(OFFSET(AI63,-52,0,52,1),0.5) -> 0.76706529 | AM63: =+_xlfn.PERCENTILE.INC(OFFSET(AI63,-52,0,52,1),0.75) -> 0.80535672 | AN63: =+_xlfn.PERCENTILE.INC(OFFSET(AI63,-52,0,52,1),0.9) -> 0.85448317
B64: 39129 | C64: 8.154 | D64: 2.273 | E64: 0.089 | F64: 1.921 | G64: 2145.49 | I64: =+C64/C63-1 -> -0.030785689 | J64: =+D64/D63-1 -> -0.0043802015 | K64: =+E64/E63-1 -> 0.047058824 | L64: =+F64/F63-1 -> 0.048008729 | M64: =+G64/G63-1 -> 0.021545157 | O64: =+AVERAGE(I64:L64) -> 0.014975416 | Q64: =+Q63*(1+O64) -> 102.79269 | R64: =+R63*(1+M64) -> 132.74165 | T64: =+Q64/R64 -> 0.77438159 | V64: 39129 | W64: 53293.89 | X64: 2447.64 | Y64: 14.4584 | Z64: 3297.1555 | AC64: =+SUMPRODUCT(I64:L64,W63:Z63)/SUM(W63:AA63) -> -0.02611189 | AE64: =+AE63*(1+AC64) -> 82.678881 | AF64: =+AF63*(1+M64) -> 132.74165 | AH64: =+B64 -> 39129 | AI64: =+(AE64/$AE$6)/(AF64/$AF$6) -> 0.62285561 | AJ64: =+_xlfn.PERCENTILE.INC(OFFSET(AI64,-52,0,52,1),0.1) -> 0.6808879 | AK64: =+_xlfn.PERCENTILE.INC(OFFSET(AI64,-52,0,52,1),0.25) -> 0.72098353 | AL64: =+_xlfn.PERCENTILE.INC(OFFSET(AI64,-52,0,52,1),0.5) -> 0.7657852 | AM64: =+_xlfn.PERCENTILE.INC(OFFSET(AI64,-52,0,52,1),0.75) -> 0.80359265 | AN64: =+_xlfn.PERCENTILE.INC(OFFSET(AI64,-52,0,52,1),0.9) -> 0.84448277
B65: 39136 | C65: 8.124 | D65: 2.497 | E65: 0.092 | F65: 1.907 | G65: 2202.45 | I65: =+C65/C64-1 -> -0.0036791759 | J65: =+D65/D64-1 -> 0.098548174 | K65: =+E65/E64-1 -> 0.033707865 | L65: =+F65/F64-1 -> -0.0072878709 | M65: =+G65/G64-1 -> 0.026548714 | O65: =+AVERAGE(I65:L65) -> 0.030322248 | Q65: =+Q64*(1+O65) -> 105.9096 | R65: =+R64*(1+M65) -> 136.26577 | T65: =+Q65/R65 -> 0.77722818 | V65: 39136 | W65: 53097.234 | X65: 2688.22 | Y65: 14.9273 | Z65: 3273.3206 | AC65: =+SUMPRODUCT(I65:L65,W64:Z64)/SUM(W64:AA64) -> 0.00036561943 | AE65: =+AE64*(1+AC65) -> 82.70911 | AF65: =+AF64*(1+M65) -> 136.26577 | AH65: =+B65 -> 39136 | AI65: =+(AE65/$AE$6)/(AF65/$AF$6) -> 0.60696909 | AJ65: =+_xlfn.PERCENTILE.INC(OFFSET(AI65,-52,0,52,1),0.1) -> 0.68034907 | AK65: =+_xlfn.PERCENTILE.INC(OFFSET(AI65,-52,0,52,1),0.25) -> 0.71448068 | AL65: =+_xlfn.PERCENTILE.INC(OFFSET(AI65,-52,0,52,1),0.5) -> 0.76142799 | AM65: =+_xlfn.PERCENTILE.INC(OFFSET(AI65,-52,0,52,1),0.75) -> 0.80252106 | AN65: =+_xlfn.PERCENTILE.INC(OFFSET(AI65,-52,0,52,1),0.9) -> 0.83818537
B66: 39143 | C66: 7.974 | D66: 2.264 | E66: 0.081 | F66: 1.829 | G66: 1997.64 | I66: =+C66/C65-1 -> -0.018463811 | J66: =+D66/D65-1 -> -0.093311974 | K66: =+E66/E65-1 -> -0.11956522 | L66: =+F66/F65-1 -> -0.04090194 | M66: =+G66/G65-1 -> -0.092991895 | O66: =+AVERAGE(I66:L66) -> -0.068060736 | Q66: =+Q65*(1+O66) -> 98.70131 | R66: =+R65*(1+M66) -> 123.59416 | T66: =+Q66/R66 -> 0.79859204 | V66: 39143 | W66: 52113.952 | X66: 2437.18 | Y66: 13.208 | Z66: 3138.2564 | AC66: =+SUMPRODUCT(I66:L66,W65:Z65)/SUM(W65:AA65) -> -0.023138729 | AE66: =+AE65*(1+AC66) -> 80.795326 | AF66: =+AF65*(1+M66) -> 123.59416 | AH66: =+B66 -> 39143 | AI66: =+(AE66/$AE$6)/(AF66/$AF$6) -> 0.65371477 | AJ66: =+_xlfn.PERCENTILE.INC(OFFSET(AI66,-52,0,52,1),0.1) -> 0.6686074 | AK66: =+_xlfn.PERCENTILE.INC(OFFSET(AI66,-52,0,52,1),0.25) -> 0.70833646 | AL66: =+_xlfn.PERCENTILE.INC(OFFSET(AI66,-52,0,52,1),0.5) -> 0.75821839 | AM66: =+_xlfn.PERCENTILE.INC(OFFSET(AI66,-52,0,52,1),0.75) -> 0.80062194 | AN66: =+_xlfn.PERCENTILE.INC(OFFSET(AI66,-52,0,52,1),0.9) -> 0.83019156
B67: 39150 | C67: 8.365 | D67: 2.312 | E67: 0.08 | F67: 1.829 | G67: 2036.46 | I67: =+C67/C66-1 -> 0.049034362 | J67: =+D67/D66-1 -> 0.021201413 | K67: =+E67/E66-1 -> -0.012345679 | L67: =+F67/F66-1 -> 0 | M67: =+G67/G66-1 -> 0.019432931 | O67: =+AVERAGE(I67:L67) -> 0.014472524 | Q67: =+Q66*(1+O67) -> 100.12977 | R67: =+R66*(1+M67) -> 125.99595 | T67: =+Q67/R67 -> 0.79470621 | V67: 39150 | W67: 54670.485 | X67: 2489.48 | Y67: 12.9214 | Z67: 3138.2564 | AC67: =+SUMPRODUCT(I67:L67,W66:Z66)/SUM(W66:AA66) -> 0.045177915 | AE67: =+AE66*(1+AC67) -> 84.445491 | AF67: =+AF66*(1+M67) -> 125.99595 | AH67: =+B67 -> 39150 | AI67: =+(AE67/$AE$6)/(AF67/$AF$6) -> 0.67022383 | AJ67: =+_xlfn.PERCENTILE.INC(OFFSET(AI67,-52,0,52,1),0.1) -> 0.65507385 | AK67: =+_xlfn.PERCENTILE.INC(OFFSET(AI67,-52,0,52,1),0.25) -> 0.70383151 | AL67: =+_xlfn.PERCENTILE.INC(OFFSET(AI67,-52,0,52,1),0.5) -> 0.75789882 | AM67: =+_xlfn.PERCENTILE.INC(OFFSET(AI67,-52,0,52,1),0.75) -> 0.79831046 | AN67: =+_xlfn.PERCENTILE.INC(OFFSET(AI67,-52,0,52,1),0.9) -> 0.82029073
B68: 39157 | C68: 7.991 | D68: 2.234 | E68: 0.085 | F68: 1.759 | G68: 1985.79 | I68: =+C68/C67-1 -> -0.044710102 | J68: =+D68/D67-1 -> -0.033737024 | K68: =+E68/E67-1 -> 0.0625 | L68: =+F68/F67-1 -> -0.03827228 | M68: =+G68/G67-1 -> -0.024881412 | O68: =+AVERAGE(I68:L68) -> -0.013554851 | Q68: =+Q67*(1+O68) -> 98.772523 | R68: =+R67*(1+M68) -> 122.861 | T68: =+Q68/R68 -> 0.80393718 | V68: 39157 | W68: 49872.068 | X68: 2405.8 | Y68: 13.7811 | Z68: 3019.0821 | AC68: =+SUMPRODUCT(I68:L68,W67:Z67)/SUM(W67:AA67) -> -0.043899205 | AE68: =+AE67*(1+AC68) -> 80.738401 | AF68: =+AF67*(1+M68) -> 122.861 | AH68: =+B68 -> 39157 | AI68: =+(AE68/$AE$6)/(AF68/$AF$6) -> 0.65715242 | AJ68: =+_xlfn.PERCENTILE.INC(OFFSET(AI68,-52,0,52,1),0.1) -> 0.65507385 | AK68: =+_xlfn.PERCENTILE.INC(OFFSET(AI68,-52,0,52,1),0.25) -> 0.69786515 | AL68: =+_xlfn.PERCENTILE.INC(OFFSET(AI68,-52,0,52,1),0.5) -> 0.75444109 | AM68: =+_xlfn.PERCENTILE.INC(OFFSET(AI68,-52,0,52,1),0.75) -> 0.78864389 | AN68: =+_xlfn.PERCENTILE.INC(OFFSET(AI68,-52,0,52,1),0.9) -> 0.81883759
B69: 39164 | C69: 8.035 | D69: 2.312 | E69: 0.088 | F69: 1.81 | G69: 2085.51 | I69: =+C69/C68-1 -> 0.0055061945 | J69: =+D69/D68-1 -> 0.034914951 | K69: =+E69/E68-1 -> 0.035294118 | L69: =+F69/F68-1 -> 0.028993746 | M69: =+G69/G68-1 -> 0.05021679 | O69: =+AVERAGE(I69:L69) -> 0.026177252 | Q69: =+Q68*(1+O69) -> 101.35812 | R69: =+R68*(1+M69) -> 129.03068 | T69: =+Q69/R69 -> 0.785535 | V69: 39164 | W69: 50147.387 | X69: 2489.48 | Y69: 14.3542 | Z69: 3106.4766 | AC69: =+SUMPRODUCT(I69:L69,W68:Z68)/SUM(W68:AA68) -> 0.008074827 | AE69: =+AE68*(1+AC69) -> 81.390349 | AF69: =+AF68*(1+M69) -> 129.03068 | AH69: =+B69 -> 39164 | AI69: =+(AE69/$AE$6)/(AF69/$AF$6) -> 0.63078292 | AJ69: =+_xlfn.PERCENTILE.INC(OFFSET(AI69,-52,0,52,1),0.1) -> 0.65405854 | AK69: =+_xlfn.PERCENTILE.INC(OFFSET(AI69,-52,0,52,1),0.25) -> 0.69147871 | AL69: =+_xlfn.PERCENTILE.INC(OFFSET(AI69,-52,0,52,1),0.5) -> 0.74725333 | AM69: =+_xlfn.PERCENTILE.INC(OFFSET(AI69,-52,0,52,1),0.75) -> 0.78396091 | AN69: =+_xlfn.PERCENTILE.INC(OFFSET(AI69,-52,0,52,1),0.9) -> 0.81156495
... B1089: 46304 | C1089: 8065 | D1089: 5190 | E1089: 39.01 | F1089: 8340 | G1089: 2828027 | I1089: =+C1089/C1088-1 -> 0.001863354 | J1089: =+D1089/D1088-1 -> 0.043740573 | K1089: =+E1089/E1088-1 -> 0.0012833676 | L1089: =+F1089/F1088-1 -> 0.028994448 | M1089: =+G1089/G1088-1 -> 0.021810459 | O1089: =+AVERAGE(I1089:L1089) -> 0.018970436 | Q1089: =+Q1088*(1+O1089) -> 369640.9 | R1089: =+R1088*(1+M1089) -> 174970.27 | T1089: =+Q1089/R1089 -> 2.1125926 | V1089: 46304 | W1089: 31724855 | X1089: 7076670.8 | Y1089: 273070 | Z1089: 6626090.7 | AC1089: =+SUMPRODUCT(I1089:L1089,W1088:Z1088)/SUM(W1088:AA1088) -> 0.012016166 | AE1089: =+AE1088*(1+AC1089) -> 106021.84 | AF1089: =+AF1088*(1+M1089) -> 174970.27 | AH1089: =+B1089 -> 46304 | AI1089: =+(AE1089/$AE$6)/(AF1089/$AF$6) -> 0.60594202 | AJ1089: =+_xlfn.PERCENTILE.INC(OFFSET(AI1089,-52,0,52,1),0.1) -> 0.45138735 | AK1089: =+_xlfn.PERCENTILE.INC(OFFSET(AI1089,-52,0,52,1),0.25) -> 0.46524869 | AL1089: =+_xlfn.PERCENTILE.INC(OFFSET(AI1089,-52,0,52,1),0.5) -> 0.50603741 | AM1089: =+_xlfn.PERCENTILE.INC(OFFSET(AI1089,-52,0,52,1),0.75) -> 0.54684479 | AN1089: =+_xlfn.PERCENTILE.INC(OFFSET(AI1089,-52,0,52,1),0.9) -> 0.58664796

Sheet crack spread y Brent_WTI
A1: =+AVERAGE(B4:B5000) -> 12.990308 | B1: =+_xlfn.STDEV.S(B4:B5000) -> 10.959003
J2: Brent | K2: WTI
A3: Dates | B3: Crack Spread | C3: ZSPREAD | D3: YoY | I3: Dates | J3: CO1 Comdty | K3: CL1 COMB Comdty | L3: BRENT/WTI
A4: =_xll.BDH("CRK321M1 Index", "PX_LAST","1987-01-01", "", "Per=M","cols=2;rows=477") -> 31807 | B4: 3.002 | C4: =+(B4-$A$1)/$B$1 -> -0.91142492 | I4: =_xll.BDH(J$3,"PX_LAST","1990-12-28","","Dir=V","Per=M","Days=A","Dts=S","cols=2;rows=430") -> 33238 | J4: 28.27 | K4: =_xll.BDH(K$3,"PX_LAST","1990-12-28","","Dir=V","Per=M","Days=A","Dts=H","cols=1;rows=430") -> 28.44 | L4: =+J4/K4 -> 0.9940225
A5: 31835 | B5: 2.738 | C5: =+(B5-$A$1)/$B$1 -> -0.9355147 | I5: 33269 | J5: 20.06 | K5: 21.54 | L5: =+J5/K5 -> 0.93129062
A6: 31867 | B6: 3.126 | C6: =+(B6-$A$1)/$B$1 -> -0.90011002 | I6: 33297 | J6: 18.68 | K6: 19.16 | L6: =+J6/K6 -> 0.97494781
A7: 31897 | B7: 2.747 | C7: =+(B7-$A$1)/$B$1 -> -0.93469346 | I7: 33326 | J7: 18.17 | K7: 19.63 | L7: =+J7/K7 -> 0.92562404
A8: 31926 | B8: 2.978 | C8: =+(B8-$A$1)/$B$1 -> -0.9136149 | I8: 33358 | J8: 19.42 | K8: 20.96 | L8: =+J8/K8 -> 0.92652672
A9: 31958 | B9: 2.676 | C9: =+(B9-$A$1)/$B$1 -> -0.94117215 | I9: 33389 | J9: 19.21 | K9: 21.13 | L9: =+J9/K9 -> 0.90913393
A10: 31989 | B10: 1.743 | C10: =+(B10-$A$1)/$B$1 -> -1.0263076 | I10: 33417 | J10: 18.72 | K10: 20.56 | L10: =+J10/K10 -> 0.91050584
A11: 32020 | B11: 1.673 | C11: =+(B11-$A$1)/$B$1 -> -1.0326951 | I11: 33450 | J11: 19.74 | K11: 21.68 | L11: =+J11/K11 -> 0.91051661
A12: 32050 | B12: 2.242 | C12: =+(B12-$A$1)/$B$1 -> -0.9807743 | I12: 33480 | J12: 20.7 | K12: 22.26 | L12: =+J12/K12 -> 0.92991914
A13: 32080 | B13: 2.756 | C13: =+(B13-$A$1)/$B$1 -> -0.93387222 | I13: 33511 | J13: 21.05 | K13: 22.23 | L13: =+J13/K13 -> 0.94691858
A14: 32111 | B14: 2.766 | C14: =+(B14-$A$1)/$B$1 -> -0.93295973 | I14: 33542 | J14: 22.1 | K14: 23.37 | L14: =+J14/K14 -> 0.94565682
A15: 32142 | B15: 2.568 | C15: =+(B15-$A$1)/$B$1 -> -0.95102706 | I15: 33571 | J15: 20.13 | K15: 21.48 | L15: =+J15/K15 -> 0.93715084
A16: 32171 | B16: 2.527 | C16: =+(B16-$A$1)/$B$1 -> -0.95476828 | D16: =+B16/B4-1 -> -0.15822785 | I16: 33603 | J16: 17.61 | K16: 19.12 | L16: =+J16/K16 -> 0.9210251
A17: 32202 | B17: 3.163 | C17: =+(B17-$A$1)/$B$1 -> -0.8967338 | D17: =+B17/B5-1 -> 0.15522279 | I17: 33634 | J17: 18.15 | K17: 18.9 | L17: =+J17/K17 -> 0.96031746
A18: 32233 | B18: 3.207 | C18: =+(B18-$A$1)/$B$1 -> -0.89271884 | D18: =+B18/B6-1 -> 0.025911708 | I18: 33662 | J18: 17.55 | K18: 18.68 | L18: =+J18/K18 -> 0.93950749
A19: 32262 | B19: 3.233 | C19: =+(B19-$A$1)/$B$1 -> -0.89034636 | D19: =+B19/B7-1 -> 0.17692028 | I19: 33694 | J19: 18.14 | K19: 19.44 | L19: =+J19/K19 -> 0.93312757
A20: 32294 | B20: 3.504 | C20: =+(B20-$A$1)/$B$1 -> -0.86561783 | D20: =+B20/B8-1 -> 0.17662861 | I20: 33724 | J20: 19.66 | K20: 20.85 | L20: =+J20/K20 -> 0.94292566
A21: 32324 | B21: 4.048 | C21: =+(B21-$A$1)/$B$1 -> -0.81597828 | D21: =+B21/B9-1 -> 0.51270553 | I21: 33753 | J21: 20.79 | K21: 22.11 | L21: =+J21/K21 -> 0.94029851
A22: 32353 | B22: 3.48 | C22: =+(B22-$A$1)/$B$1 -> -0.86780781 | D22: =+B22/B10-1 -> 0.99655766 | I22: 33785 | J22: 20.41 | K22: 21.6 | L22: =+J22/K22 -> 0.94490741
A23: 32386 | B23: 3.303 | C23: =+(B23-$A$1)/$B$1 -> -0.88395892 | D23: =+B23/B11-1 -> 0.97429767 | I23: 33816 | J23: 20.47 | K23: 21.87 | L23: =+J23/K23 -> 0.93598537
A24: 32416 | B24: 3.877 | C24: =+(B24-$A$1)/$B$1 -> -0.83158189 | D24: =+B24/B12-1 -> 0.72925959 | I24: 33847 | J24: 19.87 | K24: 21.48 | L24: =+J24/K24 -> 0.92504655
A25: 32447 | B25: 4.817 | C25: =+(B25-$A$1)/$B$1 -> -0.74580766 | D25: =+B25/B13-1 -> 0.74782293 | I25: 33877 | J25: 20.34 | K25: 21.71 | L25: =+J25/K25 -> 0.93689544
A26: 32477 | B26: 4.112 | C26: =+(B26-$A$1)/$B$1 -> -0.81013833 | D26: =+B26/B14-1 -> 0.48662328 | I26: 33907 | J26: 19.45 | K26: 20.62 | L26: =+J26/K26 -> 0.94325897
A27: 32507 | B27: 3.277 | C27: =+(B27-$A$1)/$B$1 -> -0.8863314 | D27: =+B27/B15-1 -> 0.27609034 | I27: 33938 | J27: 18.84 | K27: 19.89 | L27: =+J27/K27 -> 0.94720965
... A432: 44834 | B432: 31.96 | C432: =+(B432-$A$1)/$B$1 -> 1.7309688 | D432: =+B432/B420-1 -> 0.67725007 | I432: 46265 | J432: 90.49 | K432: 85.76 | L432: =+J432/K432 -> 1.0551539
A433: 44865 | B433: 35.78 | C433: =+(B433-$A$1)/$B$1 -> 2.0795407 | D433: =+B433/B421-1 -> 1.0408396 | I433: 46295 | J433: 103.53 | K433: 90.42
A434: 44895 | B434: 33.046 | C434: =+(B434-$A$1)/$B$1 -> 1.8300654 | D434: =+B434/B422-1 -> 0.91426751
A435: 44925 | B435: 35.565 | C435: =+(B435-$A$1)/$B$1 -> 2.0599221 | D435: =+B435/B423-1 -> 0.84983876
A436: 44957 | B436: 36.711 | C436: =+(B436-$A$1)/$B$1 -> 2.1644937 | D436: =+B436/B424-1 -> 0.707012
A437: 44985 | B437: 36.219 | C437: =+(B437-$A$1)/$B$1 -> 2.1195991 | D437: =+B437/B425-1 -> 0.3129486
A438: 45016 | B438: 35.871 | C438: =+(B438-$A$1)/$B$1 -> 2.0878443 | D438: =+B438/B426-1 -> 0.040644038
A439: 45044 | B439: 27.314 | C439: =+(B439-$A$1)/$B$1 -> 1.3070251 | D439: =+B439/B427-1 -> -0.43049561
A440: 45077 | B440: 31.921 | C440: =+(B440-$A$1)/$B$1 -> 1.7274101 | D440: =+B440/B428-1 -> -0.3765795
A441: 45107 | B441: 34.809 | C441: =+(B441-$A$1)/$B$1 -> 1.9909377 | D441: =+B441/B429-1 -> -0.2735412
A442: 45138 | B442: 41.425 | C442: =+(B442-$A$1)/$B$1 -> 2.5946423 | D442: =+B442/B430-1 -> 0.096102453
A443: 45169 | B443: 31.791 | C443: =+(B443-$A$1)/$B$1 -> 1.7155477 | D443: =+B443/B431-1 -> 0.072860421
A444: 45198 | B444: 22.35 | C444: =+(B444-$A$1)/$B$1 -> 0.85406419 | D444: =+B444/B432-1 -> -0.30068836
A445: 45230 | B445: 21.984 | C445: =+(B445-$A$1)/$B$1 -> 0.82066699 | D445: =+B445/B433-1 -> -0.38557854
... A479: 46265 | B479: 61.968 | C479: =+(B479-$A$1)/$B$1 -> 4.4691742 | D479: =+B479/B467-1 -> 1.7066172
A480: 46295 | B480: 66.577

Sheet Macro
B1: Start Date | C1: 38016 | D1: 43099 | Y1: Transformaciones | AK1: Normalización | AL1: =+(_xlfn.QUARTILE.INC(AL76:AL275,1))-(1.5*((_xlfn.QUARTILE.INC(AL76:AL275,3))-(_xlfn.QUARTILE.INC(AL76:AL275,1)))) -> -2.6834467 | AM1: =+(_xlfn.QUARTILE.INC(AM76:AM275,1))-(1.5*((_xlfn.QUARTILE.INC(AM76:AM275,3))-(_xlfn.QUARTILE.INC(AM76:AM275,1)))) -> -1.9428258 | AN1: =+(_xlfn.QUARTILE.INC(AN76:AN275,1))-(1.5*((_xlfn.QUARTILE.INC(AN76:AN275,3))-(_xlfn.QUARTILE.INC(AN76:AN275,1)))) -> -1.7743432 | AO1: =+(_xlfn.QUARTILE.INC(AO76:AO275,1))-(1.5*((_xlfn.QUARTILE.INC(AO76:AO275,3))-(_xlfn.QUARTILE.INC(AO76:AO275,1)))) -> -4.3521929 | AP1: =+(_xlfn.QUARTILE.INC(AP76:AP275,1))-(1.5*((_xlfn.QUARTILE.INC(AP76:AP275,3))-(_xlfn.QUARTILE.INC(AP76:AP275,1)))) -> -3.1589195 | AQ1: =+(_xlfn.QUARTILE.INC(AQ76:AQ275,1))-(1.5*((_xlfn.QUARTILE.INC(AQ76:AQ275,3))-(_xlfn.QUARTILE.INC(AQ76:AQ275,1)))) -> -2.9749989 | AR1: =+(_xlfn.QUARTILE.INC(AR76:AR275,1))-(1.5*((_xlfn.QUARTILE.INC(AR76:AR275,3))-(_xlfn.QUARTILE.INC(AR76:AR275,1)))) -> -1.8998286 | AS1: =+(_xlfn.QUARTILE.INC(AS76:AS275,1))-(1.5*((_xlfn.QUARTILE.INC(AS76:AS275,3))-(_xlfn.QUARTILE.INC(AS76:AS275,1)))) -> -2.7144925 | ... AU1: =+(_xlfn.QUARTILE.INC(AU76:AU275,1))-(1.5*((_xlfn.QUARTILE.INC(AU76:AU275,3))-(_xlfn.QUARTILE.INC(AU76:AU275,1)))) -> -2.4095924 | AW1: Filtro Tukey
B2: End Date | AL2: =+(_xlfn.QUARTILE.INC(AL76:AL275,3))+(1.5*(+(_xlfn.QUARTILE.INC(AL76:AL275,3))-(+_xlfn.QUARTILE.INC(AL76:AL275,1)))) -> 2.5365314 | AM2: =+(_xlfn.QUARTILE.INC(AM76:AM275,3))+(1.5*(+(_xlfn.QUARTILE.INC(AM76:AM275,3))-(+_xlfn.QUARTILE.INC(AM76:AM275,1)))) -> 2.4812117 | AN2: =+(_xlfn.QUARTILE.INC(AN76:AN275,3))+(1.5*(+(_xlfn.QUARTILE.INC(AN76:AN275,3))-(+_xlfn.QUARTILE.INC(AN76:AN275,1)))) -> 1.987541 | AO2: =+(_xlfn.QUARTILE.INC(AO76:AO275,3))+(1.5*(+(_xlfn.QUARTILE.INC(AO76:AO275,3))-(+_xlfn.QUARTILE.INC(AO76:AO275,1)))) -> 5.8146337 | AP2: =+(_xlfn.QUARTILE.INC(AP76:AP275,3))+(1.5*(+(_xlfn.QUARTILE.INC(AP76:AP275,3))-(+_xlfn.QUARTILE.INC(AP76:AP275,1)))) -> 4.3351565 | AQ2: =+(_xlfn.QUARTILE.INC(AQ76:AQ275,3))+(1.5*(+(_xlfn.QUARTILE.INC(AQ76:AQ275,3))-(+_xlfn.QUARTILE.INC(AQ76:AQ275,1)))) -> 3.2111085 | AR2: =+(_xlfn.QUARTILE.INC(AR76:AR275,3))+(1.5*(+(_xlfn.QUARTILE.INC(AR76:AR275,3))-(+_xlfn.QUARTILE.INC(AR76:AR275,1)))) -> 1.94021 | AS2: =+(_xlfn.QUARTILE.INC(AS76:AS275,3))+(1.5*(+(_xlfn.QUARTILE.INC(AS76:AS275,3))-(+_xlfn.QUARTILE.INC(AS76:AS275,1)))) -> 2.6971619 | ... AU2: =+(_xlfn.QUARTILE.INC(AU76:AU275,3))+(1.5*(+(_xlfn.QUARTILE.INC(AU76:AU275,3))-(+_xlfn.QUARTILE.INC(AU76:AU275,1)))) -> 2.2332954
A3: Year | B3: Dates | C3: Exp nivel | D3: Exp | E3: Impo | F3: Nominal GDP (ars mill) | G3: (Exp+Imp)/GDP | H3: EMAE | I3: EMAE Transporte | J3: IPC Transporte | K3: Producción Petroleo Arg | L3: Producción Petroleo Arg YoY | M3: ITCRM | N3: ITCRM YoY | O3: Inventarios comer. De crudo | P3: Inventarios comer. De crudo YoY | Q3: Crack Spread YoY | R3: GDP | S3: GDP avg 5Y | T3: Gas | U3: Gas YoY% | V3: Brent | W3: Brent YoY% | X3: REM 12M (expect) | Z3: =+_xlfn.CONCAT("Exc. ",D3) -> Exc. Exp | AA3: =+_xlfn.CONCAT("Exc. ",H3) -> Exc. EMAE | AB3: =+_xlfn.CONCAT("Exc. ",I3) -> Exc. EMAE Transporte | AC3: =+_xlfn.CONCAT("Exc. ",J3) -> Exc. IPC Transporte | AD3: =+_xlfn.CONCAT("Exc. ",K3) -> Exc. Producción Petroleo Arg | AE3: =+_xlfn.CONCAT("Exc. ",M3) -> Exc. ITCRM | AF3: =+_xlfn.CONCAT("Exc. ",O3) -> Exc. Inventarios comer. De crudo | AG3: =+_xlfn.CONCAT("Exc. ",Q3) -> Exc. Crack Spread YoY | AH3: =+_xlfn.CONCAT("Exc. ",T3) -> Exc. Gas | AI3: =+_xlfn.CONCAT("Exc. ",V3) -> Exc. Brent | AL3: =+Z3 -> Exc. Exp | AM3: =+AA3 -> Exc. EMAE | AN3: =+AB3 -> Exc. EMAE Transporte | AO3: =+AC3 -> Exc. IPC Transporte | AP3: =+AD3 -> Exc. Producción Petroleo Arg | AQ3: =+AE3 -> Exc. ITCRM | AR3: =+AF3 -> Exc. Inventarios comer. De crudo | AS3: =+AG3 -> Exc. Crack Spread YoY | ... AU3: =+AI3 -> Exc. Brent | AW3: =+AL3 -> Exc. Exp | AX3: =+AM3 -> Exc. EMAE | AY3: =+AN3 -> Exc. EMAE Transporte | AZ3: =+AO3 -> Exc. IPC Transporte | BA3: =+AP3 -> Exc. Producción Petroleo Arg | BB3: =+AQ3 -> Exc. ITCRM | BC3: =+AR3 -> Exc. Inventarios comer. De crudo | BD3: =+AS3 -> Exc. Crack Spread YoY | ... BF3: =+AU3 -> Exc. Brent | BH3: Score ( Median ) | BI3: |score| | BJ3: Umbral | BK3: Señal | BL3: Posición | BM3: Posición (12M avg) | BN3: Signo | BO3: OIL&GAS vs Merval | BP3: ln(OIL&GAS vs Merval) | BQ3: r relat | BR3: Estrategía | BS3: Buy&Hold | BT3: Estrategía -base100- | BU3: B&h -base100-
A4: =+YEAR(B4) -> 2004 | B4: =_xll.BDH("ARBABEXP Index","PX_LAST",$C1,$C2,"Dir=V","Per=M","Days=A","Dts=S","cols=2;rows=273") -> 38017 | C4: 2322 | E4: =_xll.BDH("ARBABIMP Index","PX_LAST",$C1,$C2,"Dir=V","Per=M","Days=A","Dts=H","cols=1;rows=273") -> 1609 | F4: =_xll.BDH("ECOXARN Index","PX_LAST",$C1,$C2,"Dir=V","Per=M","Days=A","Dts=H","cols=1;rows=273") -> #N/A N/A | H4: =_xll.BDH("AREMORMO Index","PX_LAST",$C1,$C2,"Dir=V","Per=M","Days=A","Dts=H","cols=1;rows=273") -> 10.2 | I4: =_xll.BDH("AREMCOMY Index","PX_LAST",$C1,$C2,"Dir=V","Per=M","Days=A","Dts=H","cols=1;rows=273") -> #N/A N/A | J4: -0.40792348 | K4: =_xll.BDH("DWOPARGE Index","PX_LAST",$C1,$C2,"Dir=V","Per=M","Days=A","Dts=H","cols=1;rows=273") -> 701.755 | M4: =_xll.BDH("ARITCR Index","PX_LAST",$C1,$C2,"Dir=V","Per=M","Days=A","Dts=H","cols=1;rows=273") -> 159.536 | O4: =_xll.BDH("DOESCRUD Index","PX_LAST",$C1,$C2,"Dir=V","Per=M","Days=A","Dts=H","cols=1;rows=273") -> 255245 | Q4: =+'crack spread y Brent_WTI'!D208*100 -> 3.7609948 | R4: =_xll.BDH("ARGQPYOX Index","PX_LAST",$C1,$C2,"Dir=V","Per=M","Days=A","Dts=H","cols=1;rows=273") -> #N/A N/A | T4: =_xll.BDH("NG1 COMB Comdty","PX_LAST",$C1,$C2,"Dir=V","Per=M","Days=A","Dts=H","cols=1;rows=273") -> 5.397 | V4: =_xll.BDH("CO1 Comdty","PX_LAST",$C1,$C2,"Dir=V","Per=M","Days=A","Dts=H","cols=1;rows=273") -> 29.18 | X4: =_xll.BDH("ARFCCP12 Index","PX_LAST",$C1,$C2,"Dir=V","Per=M","Days=A","Dts=H","cols=1;rows=273") -> #N/A N/A
A5: =+YEAR(B5) -> 2004 | B5: 38046 | C5: 2395 | E5: 1364 | F5: #N/A N/A | H5: 10.2 | I5: #N/A N/A | J5: -0.92311906 | K5: 706.096 | M5: 159.629 | O5: 259092 | Q5: =+'crack spread y Brent_WTI'!D209*100 -> -8.5377611 | R5: #N/A N/A | T5: 5.416 | V5: 32.23 | X5: #N/A N/A
A6: =+YEAR(B6) -> 2004 | B6: 38077 | C6: 2658 | E6: 1690 | F6: 151.11 | H6: 13.2 | I6: #N/A N/A | J6: -0.90675726 | K6: 683.964 | M6: 155.118 | O6: 277539 | Q6: =+'crack spread y Brent_WTI'!D210*100 -> 30.716359 | R6: #N/A N/A | T6: 5.933 | V6: 31.51 | X6: #N/A N/A
A7: =+YEAR(B7) -> 2004 | B7: 38107 | C7: 3040 | E7: 1651 | F7: 151.11 | H7: 6.8 | I7: #N/A N/A | J7: -0.031656771 | K7: 679.854 | M7: 151.165 | O7: 282748 | Q7: =+'crack spread y Brent_WTI'!D211*100 -> 72.362556 | R7: #N/A N/A | T7: 5.862 | V7: 34.48 | X7: #N/A N/A
A8: =+YEAR(B8) -> 2004 | B8: 38138 | C8: 3394 | E8: 1792 | F8: 151.11 | H8: 5.9 | I8: #N/A N/A | J8: 1.0678588 | K8: 712.11 | M8: 155.047 | O8: 285384 | Q8: =+'crack spread y Brent_WTI'!D212*100 -> 112.77349 | R8: #N/A N/A | T8: 6.442 | V8: 36.58 | X8: #N/A N/A
A9: =+YEAR(B9) -> 2004 | B9: 38168 | C9: 2951 | E9: 2039 | F9: 175.44 | H9: 8.8 | I9: #N/A N/A | J9: 1.9446521 | K9: 707.394 | M9: 154.076 | O9: 288862 | Q9: =+'crack spread y Brent_WTI'!D213*100 -> 89.060415 | R9: #N/A N/A | T9: 6.155 | V9: 34.5 | X9: #N/A N/A
A10: =+YEAR(B10) -> 2004 | B10: 38199 | C10: 3034 | E10: 1970 | F10: 175.44 | H10: 7.3 | I10: #N/A N/A | J10: 1.9590982 | K10: 696.371 | M10: 156.135 | O10: 282564 | Q10: =+'crack spread y Brent_WTI'!D214*100 -> 65.281307 | R10: #N/A N/A | T10: 6.112 | V10: 40.03 | X10: #N/A N/A
A11: =+YEAR(B11) -> 2004 | B11: 38230 | C11: 2945 | E11: 2032 | F11: 175.44 | H11: 10.1 | I11: #N/A N/A | J11: 2.3238328 | K11: 688.71 | M11: 159.947 | O11: 271284 | Q11: =+'crack spread y Brent_WTI'!D215*100 -> -8.4836339 | R11: #N/A N/A | T11: 5.074 | V11: 39.61 | X11: #N/A N/A
A12: =+YEAR(B12) -> 2004 | B12: 38260 | C12: 3002 | E12: 2025 | F12: 163.49 | H12: 8.9 | I12: #N/A N/A | J12: 2.9918852 | K12: 706.017 | M12: 160.499 | O12: 257031 | Q12: =+'crack spread y Brent_WTI'!D216*100 -> 60.26796 | R12: #N/A N/A | T12: 6.795 | V12: 46.38 | X12: #N/A N/A
A13: =+YEAR(B13) -> 2004 | B13: 38291 | C13: 2831 | E13: 1973 | F13: 163.49 | H13: 7.3 | I13: #N/A N/A | J13: 2.7729906 | K13: 698.292 | M13: 161.079 | O13: 273529 | Q13: =+'crack spread y Brent_WTI'!D217*100 -> 35.999083 | R13: #N/A N/A | T13: 8.725 | V13: 48.98 | X13: #N/A N/A
A14: =+YEAR(B14) -> 2004 | B14: 38321 | C14: 3042 | E14: 2193 | F14: 163.49 | H14: 10.9 | I14: #N/A N/A | J14: 2.4934673 | K14: 675.486 | M14: 165.003 | O14: 276981 | Q14: =+'crack spread y Brent_WTI'!D218*100 -> 40.917702 | R14: #N/A N/A | T14: 7.62 | V14: 45.51 | X14: #N/A N/A
A15: =+YEAR(B15) -> 2004 | B15: 38352 | C15: 2962 | E15: 2109 | F15: 169.79 | G15: =+(SUM(C4:C15)+SUM(E4:E15))/(F15*1000) -> 0.33584428 | H15: 9.6 | I15: #N/A N/A | J15: 3.2049911 | K15: 682.534 | M15: 169.353 | O15: 275442 | Q15: =+'crack spread y Brent_WTI'!D219*100 -> -9.3349984 | R15: #N/A N/A | T15: 6.149 | V15: 40.46 | X15: #N/A N/A
A16: =+YEAR(B16) -> 2005 | B16: 38383 | C16: 2781 | D16: =+(C16/C4-1)*100 -> 19.767442 | E16: 1901 | F16: 169.79 | G16: =+(SUM(C5:C16)+SUM(E5:E16))/(F16*1000) -> 0.34026739 | H16: 6.3 | I16: 12.3 | J16: 4.4088634 | K16: 678.684 | L16: =(K16/K4-1)*100 -> -3.2876146 | M16: 163.055 | N16: =(M16/M4-1)*100 -> 2.2057717 | O16: 279566 | P16: =(O16/O4-1)*100 -> 9.5284922 | Q16: =+'crack spread y Brent_WTI'!D220*100 -> 22.858813 | R16: #N/A N/A | T16: 6.321 | U16: =(T16/T4-1)*100 -> 17.120623 | V16: 45.92 | W16: =(V16/V4-1)*100 -> 57.36806 | X16: #N/A N/A
A17: =+YEAR(B17) -> 2005 | B17: 38411 | C17: 2606 | D17: =+(C17/C5-1)*100 -> 8.8100209 | E17: 1867 | F17: 169.79 | G17: =+(SUM(C6:C17)+SUM(E6:E17))/(F17*1000) -> 0.34447258 | H17: 6.6 | I17: 12.4 | J17: 5.391405 | K17: 678.364 | L17: =(K17/K5-1)*100 -> -3.9275113 | M17: 164.581 | N17: =(M17/M5-1)*100 -> 3.1021932 | O17: 283301 | P17: =(O17/O5-1)*100 -> 9.3437852 | Q17: =+'crack spread y Brent_WTI'!D221*100 -> -4.6732256 | R17: #N/A N/A | T17: 6.73 | U17: =(T17/T5-1)*100 -> 24.261448 | V17: 50.06 | W17: =(V17/V5-1)*100 -> 55.321129 | X17: #N/A N/A
A18: =+YEAR(B18) -> 2005 | B18: 38442 | C18: 3054 | D18: =+(C18/C6-1)*100 -> 14.89842 | E18: 2198 | F18: 174.34 | G18: =+(SUM(C7:C18)+SUM(E7:E18))/(F18*1000) -> 0.34066766 | H18: 8.6 | I18: 14.4 | J18: 6.4800433 | K18: 676.981 | L18: =(K18/K6-1)*100 -> -1.0209602 | M18: 158.604 | N18: =(M18/M6-1)*100 -> 2.2473214 | O18: 298349 | P18: =(O18/O6-1)*100 -> 7.4980453 | Q18: =+'crack spread y Brent_WTI'!D222*100 -> 61.159149 | R18: 7.2 | T18: 7.653 | U18: =(T18/T6-1)*100 -> 28.990393 | V18: 54.29 | W18: =(V18/V6-1)*100 -> 72.29451 | X18: #N/A N/A
A19: =+YEAR(B19) -> 2005 | B19: 38472 | C19: 3561 | D19: =+(C19/C7-1)*100 -> 17.138158 | E19: 2380 | F19: 174.34 | G19: =+(SUM(C8:C19)+SUM(E8:E19))/(F19*1000) -> 0.34783756 | H19: 13.6 | I19: 15.6 | J19: 6.0567796 | K19: 677.515 | L19: =(K19/K7-1)*100 -> -0.34404446 | M19: 161.298 | N19: =(M19/M7-1)*100 -> 6.7032713 | O19: 311127 | P19: =(O19/O7-1)*100 -> 10.036853 | Q19: =+'crack spread y Brent_WTI'!D223*100 -> 16.216475 | R19: 7.2 | T19: 6.585 | U19: =(T19/T7-1)*100 -> 12.333675 | V19: 51.09 | W19: =(V19/V7-1)*100 -> 48.172854 | X19: #N/A N/A
A20: =+YEAR(B20) -> 2005 | B20: 38503 | C20: 3695 | D20: =+(C20/C8-1)*100 -> 8.8685916 | E20: 2476 | F20: 174.34 | G20: =+(SUM(C9:C20)+SUM(E9:E20))/(F20*1000) -> 0.35348744 | H20: 15.3 | I20: 17.8 | J20: 6.059606 | K20: 682.57 | L20: =(K20/K8-1)*100 -> -4.1482355 | M20: 160.255 | N20: =(M20/M8-1)*100 -> 3.3589815 | O20: 317706 | P20: =(O20/O8-1)*100 -> 11.325793 | Q20: =+'crack spread y Brent_WTI'!D224*100 -> -7.9522084 | R20: 7.2 | T20: 6.379 | U20: =(T20/T8-1)*100 -> -0.97795716 | V20: 50.73 | W20: =(V20/V8-1)*100 -> 38.68234 | X20: #N/A N/A
A21: =+YEAR(B21) -> 2005 | B21: 38533 | C21: 3450 | D21: =+(C21/C9-1)*100 -> 16.909522 | E21: 2724 | F21: 209.55 | G21: =+(SUM(C10:C21)+SUM(E10:E21))/(F21*1000) -> 0.2997423 | H21: 10.3 | I21: 16.5 | J21: 6.3155492 | K21: 671.959 | L21: =(K21/K9-1)*100 -> -5.0092311 | M21: 159.909 | N21: =(M21/M9-1)*100 -> 3.785794 | O21: 312453 | P21: =(O21/O9-1)*100 -> 8.1668755 | Q21: =+'crack spread y Brent_WTI'!D225*100 -> 3.3064516 | R21: 13.1 | T21: 6.981 | U21: =(T21/T9-1)*100 -> 13.419984 | V21: 55.58 | W21: =(V21/V9-1)*100 -> 61.101449 | X21: #N/A N/A
A22: =+YEAR(B22) -> 2005 | B22: 38564 | C22: 3601 | D22: =+(C22/C10-1)*100 -> 18.6882 | E22: 2349 | F22: 209.55 | G22: =+(SUM(C11:C22)+SUM(E11:E22))/(F22*1000) -> 0.30425674 | H22: 6.4 | I22: 16.6 | J22: 6.9467413 | K22: 671.923 | L22: =(K22/K10-1)*100 -> -3.5107723 | M22: 157.442 | N22: =(M22/M10-1)*100 -> 0.8370961 | O22: 302036 | P22: =(O22/O10-1)*100 -> 6.8911822 | Q22: =+'crack spread y Brent_WTI'!D226*100 -> 23.289777 | R22: 13.1 | T22: 7.885 | U22: =(T22/T10-1)*100 -> 29.008508 | V22: 59.37 | W22: =(V22/V10-1)*100 -> 48.313765 | X22: #N/A N/A
A23: =+YEAR(B23) -> 2005 | B23: 38595 | C23: 3837 | D23: =+(C23/C11-1)*100 -> 30.288625 | E23: 2626 | F23: 209.55 | G23: =+(SUM(C12:C23)+SUM(E12:E23))/(F23*1000) -> 0.31134813 | H23: 7.6 | I23: 16.3 | J23: 7.0561613 | K23: 666.511 | L23: =(K23/K11-1)*100 -> -3.2232725 | M23: 161.454 | N23: =(M23/M11-1)*100 -> 0.9421871 | O23: 305363 | P23: =(O23/O11-1)*100 -> 12.562112 | Q23: =+'crack spread y Brent_WTI'!D227*100 -> 324.79927 | R23: 13.1 | T23: 11.472 | U23: =(T23/T11-1)*100 -> 126.09381 | V23: 67.02 | W23: =(V23/V11-1)*100 -> 69.199697 | X23: #N/A N/A
A24: =+YEAR(B24) -> 2005 | B24: 38625 | C24: 3483 | D24: =+(C24/C12-1)*100 -> 16.022652 | E24: 2468 | F24: 204.28 | G24: =+(SUM(C13:C24)+SUM(E13:E24))/(F24*1000) -> 0.32390347 | H24: 6.9 | I24: 15.9 | J24: 7.6813306 | K24: 645.615 | L24: =(K24/K12-1)*100 -> -8.5553181 | M24: 162.7 | N24: =(M24/M12-1)*100 -> 1.3713481 | O24: 289398 | P24: =(O24/O12-1)*100 -> 12.592644 | Q24: =+'crack spread y Brent_WTI'!D228*100 -> 221.20208 | R24: 7 | T24: 13.921 | U24: =(T24/T12-1)*100 -> 104.87123 | V24: 63.48 | W24: =(V24/V12-1)*100 -> 36.86934 | X24: #N/A N/A
A25: =+YEAR(B25) -> 2005 | B25: 38656 | C25: 3399 | D25: =+(C25/C13-1)*100 -> 20.063582 | E25: 2503 | F25: 204.28 | G25: =+(SUM(C14:C25)+SUM(E14:E25))/(F25*1000) -> 0.32927844 | H25: 6.8 | I25: 14.7 | J25: 8.132387 | K25: 623.582 | L25: =(K25/K13-1)*100 -> -10.698963 | M25: 166.021 | N25: =(M25/M13-1)*100 -> 3.0680598 | O25: 303027 | P25: =(O25/O13-1)*100 -> 10.784231 | Q25: =+'crack spread y Brent_WTI'!D229*100 -> 73.496209 | R25: 7 | T25: 12.205 | U25: =(T25/T13-1)*100 -> 39.885387 | V25: 58.1 | W25: =(V25/V13-1)*100 -> 18.619845 | X25: #N/A N/A
A26: =+YEAR(B26) -> 2005 | B26: 38686 | C26: 3274 | D26: =+(C26/C14-1)*100 -> 7.6265615 | E26: 2701 | F26: 204.28 | G26: =+(SUM(C15:C26)+SUM(E15:E26))/(F26*1000) -> 0.33290092 | H26: 7.9 | I26: 12.4 | J26: 9.5727506 | K26: 650.316 | L26: =(K26/K14-1)*100 -> -3.726206 | M26: 163.367 | N26: =(M26/M14-1)*100 -> -0.99149712 | O26: 301443 | P26: =(O26/O14-1)*100 -> 8.8316527 | Q26: =+'crack spread y Brent_WTI'!D230*100 -> 23.300971 | R26: 7 | T26: 12.587 | U26: =(T26/T14-1)*100 -> 65.183727 | V26: 55.05 | W26: =(V26/V14-1)*100 -> 20.962426 | X26: #N/A N/A
A27: =+YEAR(B27) -> 2005 | B27: 38717 | C27: 3645 | D27: =+(C27/C15-1)*100 -> 23.058744 | E27: 2495 | F27: 209.23 | G27: =+(SUM(C16:C27)+SUM(E16:E27))/(F27*1000) -> 0.3301343 | H27: 8.7 | I27: 14 | J27: 9.8985781 | K27: 653.195 | L27: =(K27/K15-1)*100 -> -4.2985404 | M27: 162.511 | N27: =(M27/M15-1)*100 -> -4.040082 | O27: 305527 | P27: =(O27/O15-1)*100 -> 10.922445 | Q27: =+'crack spread y Brent_WTI'!D231*100 -> 108.4022 | R27: 7.8 | T27: 11.225 | U27: =(T27/T15-1)*100 -> 82.550008 | V27: 58.98 | W27: =(V27/V15-1)*100 -> 45.773604 | X27: #N/A N/A
A28: =+YEAR(B28) -> 2006 | B28: 38748 | C28: 3188 | D28: =+(C28/C16-1)*100 -> 14.635023 | E28: 2324 | F28: 209.23 | G28: =+(SUM(C17:C28)+SUM(E17:E28))/(F28*1000) -> 0.33410123 | H28: 8.2 | I28: 12.4 | J28: 9.6562073 | K28: 648.863 | L28: =(K28/K16-1)*100 -> -4.3939448 | M28: 167.111 | N28: =(M28/M16-1)*100 -> 2.4875042 | O28: 304935 | P28: =(O28/O16-1)*100 -> 9.0744225 | Q28: =+'crack spread y Brent_WTI'!D232*100 -> 1.034975 | R28: 7.8 | T28: 9.316 | U28: =(T28/T16-1)*100 -> 47.381743 | V28: 65.99 | W28: =(V28/V16-1)*100 -> 43.706446 | X28: #N/A N/A
A29: =+YEAR(B29) -> 2006 | B29: 38776 | C29: 3090 | D29: =+(C29/C17-1)*100 -> 18.572525 | E29: 2326 | F29: 209.23 | G29: =+(SUM(C18:C29)+SUM(E18:E29))/(F29*1000) -> 0.33860823 | H29: 8.3 | I29: 13.9 | J29: 8.9925922 | K29: 629.005 | L29: =(K29/K17-1)*100 -> -7.2761821 | M29: 169.294 | N29: =(M29/M17-1)*100 -> 2.8636355 | O29: 312135 | P29: =(O29/O17-1)*100 -> 10.177867 | Q29: =+'crack spread y Brent_WTI'!D233*100 -> -11.008723 | R29: 7.8 | T29: 6.714 | U29: =(T29/T17-1)*100 -> -0.23774146 | V29: 61.76 | W29: =(V29/V17-1)*100 -> 23.371954 | X29: #N/A N/A
... A40: =+YEAR(B40) -> 2007 | B40: 39113 | C40: 3390 | D40: =+(C40/C28-1)*100 -> 6.336261 | E40: 2951 | F40: 247.8 | G40: =+(SUM(C29:C40)+SUM(E29:E40))/(F40*1000) -> 0.32900323 | H40: 7.7 | I40: 13.3 | J40: 5.1336095 | K40: 652.861 | L40: =(K40/K28-1)*100 -> 0.61615472 | M40: 163.081 | N40: =(M40/M28-1)*100 -> -2.4115708 | O40: 307711 | P40: =(O40/O28-1)*100 -> 0.91035795 | Q40: =+'crack spread y Brent_WTI'!D244*100 -> 4.7921818 | R40: 9.7 | T40: 7.667 | U40: =(T40/T28-1)*100 -> -17.70073 | V40: 57.4 | W40: =(V40/V28-1)*100 -> -13.017124 | X40: #N/A N/A
A41: =+YEAR(B41) -> 2007 | B41: 39141 | C41: 3587 | D41: =+(C41/C29-1)*100 -> 16.084142 | E41: 2791 | F41: 247.8 | G41: =+(SUM(C30:C41)+SUM(E30:E41))/(F41*1000) -> 0.33288539 | H41: 8.3 | I41: 12.6 | J41: 5.6748822 | K41: 654.151 | L41: =(K41/K29-1)*100 -> 3.9977425 | M41: 163.327 | N41: =(M41/M29-1)*100 -> -3.5246376 | O41: 311719 | P41: =(O41/O29-1)*100 -> -0.13327567 | Q41: =+'crack spread y Brent_WTI'!D245*100 -> 114.96617 | R41: 9.7 | S41: =+AVERAGE($R$18:R41) -> 8.45 | T41: 7.3 | U41: =(T41/T29-1)*100 -> 8.728031 | V41: 61.89 | W41: =(V41/V29-1)*100 -> 0.21049223 | X41: #N/A N/A | Z41: =+AVERAGE(D39:D41)-$S41 -> 4.4738565 | AA41: =+AVERAGE(H39:H41)-$S41 -> -0.38333333 | AB41: =+AVERAGE(I39:I41)-$S41 -> 4.35 | AC41: -7.6415495 | AD41: =AVERAGE(L39:L41) -> 1.9909698 | AE41: =+AVERAGE(N39:N41)*AVERAGE($G$15:G41) -> -0.63539272 | AF41: =-AVERAGE(P39:P41) -> -0.0072220758 | AG41: =AVERAGE(Q39:Q41) -> 26.637341 | AH41: =AVERAGE(U39:U41) -> -17.618962 | AI41: =AVERAGE(W39:W41) -> -3.2063701
A42: =+YEAR(B42) -> 2007 | B42: 39172 | C42: 4173 | D42: =+(C42/C30-1)*100 -> 14.391447 | E42: 3422 | F42: 250.14 | G42: =+(SUM(C31:C42)+SUM(E31:E42))/(F42*1000) -> 0.33466859 | H42: 9 | I42: 13.3 | J42: 5.9315225 | K42: 658.454 | L42: =(K42/K30-1)*100 -> -0.18206487 | M42: 164.445 | N42: =(M42/M30-1)*100 -> -1.4053685 | O42: 315387 | P42: =(O42/O30-1)*100 -> -3.3865128 | Q42: =+'crack spread y Brent_WTI'!D246*100 -> 47.589425 | R42: 8.4 | S42: =+AVERAGE($R$18:R42) -> 8.448 | T42: 7.73 | U42: =(T42/T30-1)*100 -> 7.2122053 | V42: 68.1 | W42: =(V42/V30-1)*100 -> 3.3227128 | X42: #N/A N/A | Z42: =+AVERAGE(D40:D42)-$S42 -> 3.8226169 | AA42: =+AVERAGE(H40:H42)-$S42 -> -0.11466667 | AB42: =+AVERAGE(I40:I42)-$S42 -> 4.6186667 | AC42: -7.4665241 | AD42: =AVERAGE(L40:L42) -> 1.4772774 | AE42: =+AVERAGE(N40:N42)*AVERAGE($G$15:G42) -> -0.80982144 | AF42: =-AVERAGE(P40:P42) -> 0.86981016 | AG42: =AVERAGE(Q40:Q42) -> 55.782594 | AH42: =AVERAGE(U40:U42) -> -0.58683123 | AI42: =AVERAGE(W40:W42) -> -3.1613063
A43: =+YEAR(B43) -> 2007 | B43: 39202 | C43: 4299 | D43: =+(C43/C31-1)*100 -> 9.5286624 | E43: 3061 | F43: 250.14 | G43: =+(SUM(C32:C43)+SUM(E32:E43))/(F43*1000) -> 0.33822659 | H43: 9.3 | I43: 13.5 | J43: 7.9107545 | K43: 666.882 | L43: =(K43/K31-1)*100 -> 1.090209 | M43: 162.919 | N43: =(M43/M31-1)*100 -> -3.2196936 | O43: 318468 | P43: =(O43/O31-1)*100 -> -3.5789869 | Q43: =+'crack spread y Brent_WTI'!D247*100 -> 62.724693 | R43: 8.4 | S43: =+AVERAGE($R$18:R43) -> 8.4461538 | T43: 7.863 | U43: =(T43/T31-1)*100 -> 19.954233 | V43: 67.65 | W43: =(V43/V31-1)*100 -> -6.6896552 | X43: #N/A N/A | Z43: =+AVERAGE(D41:D43)-$S43 -> 4.8885969 | AA43: =+AVERAGE(H41:H43)-$S43 -> 0.42051282 | AB43: =+AVERAGE(I41:I43)-$S43 -> 4.6871795 | AC43: -6.8069323 | AD43: =AVERAGE(L41:L43) -> 1.6352955 | AE43: =+AVERAGE(N41:N43)*AVERAGE($G$15:G43) -> -0.89964698 | AF43: =-AVERAGE(P41:P43) -> 2.3662584 | AG43: =AVERAGE(Q41:Q43) -> 75.09343 | AH43: =AVERAGE(U41:U43) -> 11.964823 | AI43: =AVERAGE(W41:W43) -> -1.0521501
A44: =+YEAR(B44) -> 2007 | B44: 39233 | C44: 4856 | D44: =+(C44/C32-1)*100 -> 16.144463 | E44: 3542 | F44: 250.14 | G44: =+(SUM(C33:C44)+SUM(E33:E44))/(F44*1000) -> 0.34378748 | H44: 10.7 | I44: 14.4 | J44: 9.9768223 | K44: 663.095 | L44: =(K44/K32-1)*100 -> -0.9531335 | M44: 162.155 | N44: =(M44/M32-1)*100 -> -1.1707989 | O44: 325014 | P44: =(O44/O32-1)*100 -> -1.2568699 | Q44: =+'crack spread y Brent_WTI'!D248*100 -> 56.897677 | R44: 8.4 | S44: =+AVERAGE($R$18:R44) -> 8.4444444 | T44: 7.935 | U44: =(T44/T32-1)*100 -> 24.295113 | V44: 68.04 | W44: =(V44/V32-1)*100 -> -3.3659991 | X44: #N/A N/A | Z44: =+AVERAGE(D42:D44)-$S44 -> 4.9104132 | AA44: =+AVERAGE(H42:H44)-$S44 -> 1.2222222 | AB44: =+AVERAGE(I42:I44)-$S44 -> 5.2888889 | AC44: -5.9382206 | AD44: =AVERAGE(L42:L44) -> -0.014996442 | AE44: =+AVERAGE(N42:N44)*AVERAGE($G$15:G44) -> -0.64061876 | AF44: =-AVERAGE(P42:P44) -> 2.7407899 | AG44: =AVERAGE(Q42:Q44) -> 55.737265 | AH44: =AVERAGE(U42:U44) -> 17.15385 | AI44: =AVERAGE(W42:W44) -> -2.2443138
A45: =+YEAR(B45) -> 2007 | B45: 39263 | C45: 4521 | D45: =+(C45/C33-1)*100 -> 17.489605 | E45: 3579 | F45: 293.29 | G45: =+(SUM(C34:C45)+SUM(E34:E45))/(F45*1000) -> 0.29795765 | H45: 9.5 | I45: 14.3 | J45: 12.546611 | K45: 655.071 | L45: =(K45/K33-1)*100 -> -2.9728561 | M45: 159.444 | N45: =(M45/M33-1)*100 -> -4.5308393 | O45: 336924 | P45: =(O45/O33-1)*100 -> 3.6405415 | Q45: =+'crack spread y Brent_WTI'!D249*100 -> 24.793637 | R45: 9.9 | S45: =+AVERAGE($R$18:R45) -> 8.4964286 | T45: 6.773 | U45: =(T45/T33-1)*100 -> 10.960026 | V45: 71.41 | W45: =(V45/V33-1)*100 -> -2.8567542 | X45: #N/A N/A | Z45: =+AVERAGE(D43:D45)-$S45 -> 5.8911482 | AA45: =+AVERAGE(H43:H45)-$S45 -> 1.3369048 | AB45: =+AVERAGE(I43:I45)-$S45 -> 5.5702381 | AC45: -4.1903499 | AD45: =AVERAGE(L43:L45) -> -0.94526018 | AE45: =+AVERAGE(N43:N45)*AVERAGE($G$15:G45) -> -0.98285185 | AF45: =-AVERAGE(P43:P45) -> 0.39843844 | AG45: =AVERAGE(Q43:Q45) -> 48.138669 | AH45: =AVERAGE(U43:U45) -> 18.403124 | AI45: =AVERAGE(W43:W45) -> -4.3041362
A46: =+YEAR(B46) -> 2007 | B46: 39294 | C46: 4614 | D46: =+(C46/C34-1)*100 -> 20.880272 | E46: 4126 | F46: 293.29 | G46: =+(SUM(C35:C46)+SUM(E35:E46))/(F46*1000) -> 0.30501892 | H46: 8.8 | I46: 13.6 | J46: 15.313295 | K46: 632.482 | L46: =(K46/K34-1)*100 -> -5.8949386 | M46: 159.679 | N46: =(M46/M34-1)*100 -> -3.5382032 | O46: 327287 | P46: =(O46/O34-1)*100 -> 3.061096 | Q46: =+'crack spread y Brent_WTI'!D250*100 -> -34.732515 | R46: 9.9 | S46: =+AVERAGE($R$18:R46) -> 8.5448276 | T46: 6.191 | U46: =(T46/T34-1)*100 -> -24.601145 | V46: 77.05 | W46: =(V46/V34-1)*100 -> 2.5282768 | X46: #N/A N/A | Z46: =+AVERAGE(D44:D46)-$S46 -> 9.6266192 | AA46: =+AVERAGE(H44:H46)-$S46 -> 1.1218391 | AB46: =+AVERAGE(I44:I46)-$S46 -> 5.5551724 | AC46: -2.2697628 | AD46: =AVERAGE(L44:L46) -> -3.2736427 | AE46: =+AVERAGE(N44:N46)*AVERAGE($G$15:G46) -> -1.0154885 | AF46: =-AVERAGE(P44:P46) -> -1.8149225 | AG46: =AVERAGE(Q44:Q46) -> 15.652933 | AH46: =AVERAGE(U44:U46) -> 3.5513314 | AI46: =AVERAGE(W44:W46) -> -1.2314922
A47: =+YEAR(B47) -> 2007 | B47: 39325 | C47: 4922 | D47: =+(C47/C35-1)*100 -> 15.920867 | E47: 4606 | F47: 293.29 | G47: =+(SUM(C36:C47)+SUM(E36:E47))/(F47*1000) -> 0.31184152 | H47: 8.8 | I47: 12.1 | J47: 19.249919 | K47: 655.962 | L47: =(K47/K35-1)*100 -> -1.4700736 | M47: 154.497 | N47: =(M47/M35-1)*100 -> -7.6797591 | O47: 312591 | P47: =(O47/O35-1)*100 -> -1.2696969 | Q47: =+'crack spread y Brent_WTI'!D251*100 -> 24.031992 | R47: 9.9 | S47: =+AVERAGE($R$18:R47) -> 8.59 | T47: 5.468 | U47: =(T47/T35-1)*100 -> -9.5899471 | V47: 72.69 | W47: =(V47/V35-1)*100 -> 3.4733096 | X47: #N/A N/A | Z47: =+AVERAGE(D45:D47)-$S47 -> 9.5069147 | AA47: =+AVERAGE(H45:H47)-$S47 -> 0.44333333 | AB47: =+AVERAGE(I45:I47)-$S47 -> 4.7433333 | AC47: 0.21557915 | AD47: =AVERAGE(L45:L47) -> -3.4459561 | AE47: =+AVERAGE(N45:N47)*AVERAGE($G$15:G47) -> -1.7280019 | AF47: =-AVERAGE(P45:P47) -> -1.8106469 | AG47: =AVERAGE(Q45:Q47) -> 4.6977046 | AH47: =AVERAGE(U45:U47) -> -7.7436886 | AI47: =AVERAGE(W45:W47) -> 1.0482774
A48: =+YEAR(B48) -> 2007 | B48: 39355 | C48: 4828 | D48: =+(C48/C36-1)*100 -> 19.268775 | E48: 3963 | F48: 291.46 | G48: =+(SUM(C37:C48)+SUM(E37:E48))/(F48*1000) -> 0.31919989 | H48: 7.6 | I48: 10.5 | J48: 21.298396 | K48: 663.274 | L48: =(K48/K36-1)*100 -> -2.4152187 | M48: 157.525 | N48: =(M48/M36-1)*100 -> -4.6372249 | O48: 304684 | P48: =(O48/O36-1)*100 -> -2.3451848 | Q48: =+'crack spread y Brent_WTI'!D252*100 -> 29.156954 | R48: 8.4 | S48: =+AVERAGE($R$18:R48) -> 8.583871 | T48: 6.87 | U48: =(T48/T36-1)*100 -> 22.241993 | V48: 79.17 | W48: =(V48/V36-1)*100 -> 26.712548 | X48: #N/A N/A | Z48: =+AVERAGE(D46:D48)-$S48 -> 10.1061 | AA48: =+AVERAGE(H46:H48)-$S48 -> -0.18387097 | AB48: =+AVERAGE(I46:I48)-$S48 -> 3.4827957 | AC48: 2.5993052 | AD48: =AVERAGE(L46:L48) -> -3.2600769 | AE48: =+AVERAGE(N46:N48)*AVERAGE($G$15:G48) -> -1.7381253 | AF48: =-AVERAGE(P46:P48) -> 0.18459524 | AG48: =AVERAGE(Q46:Q48) -> 6.1521435 | AH48: =AVERAGE(U46:U48) -> -3.983033 | AI48: =AVERAGE(W46:W48) -> 10.904711
A49: =+YEAR(B49) -> 2007 | B49: 39386 | C49: 5581 | D49: =+(C49/C37-1)*100 -> 32.75452 | E49: 4400 | F49: 291.46 | G49: =+(SUM(C38:C49)+SUM(E38:E49))/(F49*1000) -> 0.32785288 | H49: 10.2 | I49: 12.7 | J49: 22.52987 | K49: 658.56 | L49: =(K49/K37-1)*100 -> -2.8189528 | M49: 159.438 | N49: =(M49/M37-1)*100 -> -3.136676 | O49: 295477 | P49: =(O49/O37-1)*100 -> -7.040902 | Q49: =+'crack spread y Brent_WTI'!D253*100 -> 38.145232 | R49: 8.4 | S49: =+AVERAGE($R$18:R49) -> 8.578125 | T49: 8.33 | U49: =(T49/T37-1)*100 -> 10.565437 | V49: 90.63 | W49: =(V49/V37-1)*100 -> 53.532102 | X49: #N/A N/A | Z49: =+AVERAGE(D47:D49)-$S49 -> 14.069929 | AA49: =+AVERAGE(H47:H49)-$S49 -> 0.28854167 | AB49: =+AVERAGE(I47:I49)-$S49 -> 3.1885417 | AC49: 4.3912161 | AD49: =AVERAGE(L47:L49) -> -2.2347483 | AE49: =+AVERAGE(N47:N49)*AVERAGE($G$15:G49) -> -1.6939575 | AF49: =-AVERAGE(P47:P49) -> 3.5519279 | AG49: =AVERAGE(Q47:Q49) -> 30.444726 | AH49: =AVERAGE(U47:U49) -> 7.7391608 | AI49: =AVERAGE(W47:W49) -> 27.905987
A50: =+YEAR(B50) -> 2007 | B50: 39416 | C50: 5424 | D50: =+(C50/C38-1)*100 -> 31.970803 | E50: 4384 | F50: 291.46 | G50: =+(SUM(C39:C50)+SUM(E39:E50))/(F50*1000) -> 0.33629658 | H50: 9.8 | I50: 11 | J50: 20.624128 | K50: 622.965 | L50: =(K50/K38-1)*100 -> -0.69628092 | M50: 159.413 | N50: =(M50/M38-1)*100 -> -2.4406215 | O50: 287895 | P50: =(O50/O38-1)*100 -> -11.268947 | Q50: =+'crack spread y Brent_WTI'!D254*100 -> -5.596543 | R50: 8.4 | S50: =+AVERAGE($R$18:R50) -> 8.5727273 | T50: 7.302 | U50: =(T50/T38-1)*100 -> -17.43555 | V50: 88.26 | W50: =(V50/V38-1)*100 -> 37.348273 | X50: #N/A N/A | Z50: =+AVERAGE(D48:D50)-$S50 -> 19.425305 | AA50: =+AVERAGE(H48:H50)-$S50 -> 0.62727273 | AB50: =+AVERAGE(I48:I50)-$S50 -> 2.8272727 | AC50: 4.4906806 | AD50: =AVERAGE(L48:L50) -> -1.9768175 | AE50: =+AVERAGE(N48:N50)*AVERAGE($G$15:G50) -> -1.1203725 | AF50: =-AVERAGE(P48:P50) -> 6.8850113 | AG50: =AVERAGE(Q48:Q50) -> 20.568548 | AH50: =AVERAGE(U48:U50) -> 5.12396 | AI50: =AVERAGE(W48:W50) -> 39.197641
A51: =+YEAR(B51) -> 2007 | B51: 39447 | C51: 5787 | D51: =+(C51/C39-1)*100 -> 36.453667 | E51: 3881 | F51: 316.38 | G51: =+(SUM(C40:C51)+SUM(E40:E51))/(F51*1000) -> 0.31825021 | H51: 7.8 | I51: 11 | J51: 19.783908 | K51: 654.397 | L51: =(K51/K39-1)*100 -> -1.1592395 | M51: 159.57 | N51: =(M51/M39-1)*100 -> -1.9798149 | O51: 271865 | P51: =(O51/O39-1)*100 -> -10.340381 | Q51: =+'crack spread y Brent_WTI'!D255*100 -> 49.07293 | R51: 9.3 | S51: =+AVERAGE($R$18:R51) -> 8.5941176 | T51: 7.483 | U51: =(T51/T39-1)*100 -> 18.796634 | V51: 93.85 | W51: =(V51/V39-1)*100 -> 54.206375 | X51: #N/A N/A | Z51: =+AVERAGE(D49:D51)-$S51 -> 25.132212 | AA51: =+AVERAGE(H49:H51)-$S51 -> 0.67254902 | AB51: =+AVERAGE(I49:I51)-$S51 -> 2.972549 | AC51: 3.6169283 | AD51: =AVERAGE(L49:L51) -> -1.5581577 | AE51: =+AVERAGE(N49:N51)*AVERAGE($G$15:G51) -> -0.82816097 | AF51: =-AVERAGE(P49:P51) -> 9.5500767 | AG51: =AVERAGE(Q49:Q51) -> 27.207206 | AH51: =AVERAGE(U49:U51) -> 3.9755072 | AI51: =AVERAGE(W49:W51) -> 48.36225
A52: =+YEAR(B52) -> 2008 | B52: 39478 | C52: 5818 | D52: =+(C52/C40-1)*100 -> 71.622419 | E52: 4479 | F52: 316.38 | G52: =+(SUM(C41:C52)+SUM(E41:E52))/(F52*1000) -> 0.33075416 | H52: 10 | I52: 11.4 | J52: 20.956813 | K52: 665.363 | L52: =(K52/K40-1)*100 -> 1.9149559 | M52: 159.852 | N52: =(M52/M40-1)*100 -> -1.9799977 | O52: 275472 | P52: =(O52/O40-1)*100 -> -10.477039 | Q52: =+'crack spread y Brent_WTI'!D256*100 -> 8.5280899 | R52: 9.3 | S52: =+AVERAGE($R$18:R52) -> 8.6142857 | T52: 8.074 | U52: =(T52/T40-1)*100 -> 5.3084648 | V52: 92.21 | W52: =(V52/V40-1)*100 -> 60.644599 | X52: #N/A N/A | Z52: =+AVERAGE(D50:D52)-$S52 -> 38.06801 | AA52: =+AVERAGE(H50:H52)-$S52 -> 0.58571429 | AB52: =+AVERAGE(I50:I52)-$S52 -> 2.5190476 | AC52: 2.8068754 | AD52: =AVERAGE(L50:L52) -> 0.019811821 | AE52: =+AVERAGE(N50:N52)*AVERAGE($G$15:G52) -> -0.70151602 | AF52: =-AVERAGE(P50:P52) -> 10.695456 | AG52: =AVERAGE(Q50:Q52) -> 17.334825 | AH52: =AVERAGE(U50:U52) -> 2.2231832 | AI52: =AVERAGE(W50:W52) -> 50.733082
... A75: =+YEAR(B75) -> 2009 | B75: 40178 | C75: 4794 | D75: =+(C75/C63-1)*100 -> 13.306547 | E75: 3602 | F75: 356.1 | G75: =+(SUM(C64:C75)+SUM(E64:E75))/(F75*1000) -> 0.26525695 | H75: 2.3 | I75: 4.2 | J75: 16.507906 | K75: 616.566 | L75: =(K75/K63-1)*100 -> -6.5470678 | M75: 143.615 | N75: =(M75/M63-1)*100 -> 8.3461585 | O75: 307969 | P75: =(O75/O63-1)*100 -> 2.2670368 | Q75: =+'crack spread y Brent_WTI'!D279*100 -> 45.352113 | R75: 0.3 | S75: =+AVERAGE($R$18:R75) -> 5.012069 | T75: 5.572 | U75: =(T75/T63-1)*100 -> -0.88936322 | V75: 77.93 | W75: =(V75/V63-1)*100 -> 70.936609 | X75: #N/A N/A | Z75: =+AVERAGE(D73:D75)-$S75 -> -7.6783607 | AA75: =+AVERAGE(H73:H75)-$S75 -> -4.6787356 | AB75: =+AVERAGE(I73:I75)-$S75 -> -2.0787356 | AC75: -11.108161 | AD75: =AVERAGE(L73:L75) -> -7.4524444 | AE75: =+AVERAGE(N73:N75)*AVERAGE($G$15:G75) -> 4.2271336 | AF75: =-AVERAGE(P73:P75) -> -5.4952591 | AG75: =AVERAGE(Q73:Q75) -> 80.350007 | AH75: =AVERAGE(U73:U75) -> -17.347399 | AI75: =AVERAGE(W73:W75) -> 44.254154
A76: =+YEAR(B76) -> 2010 | B76: 40209 | C76: 4408 | D76: =+(C76/C64-1)*100 -> 18.654105 | E76: 3209 | F76: 356.1 | G76: =+(SUM(C65:C76)+SUM(E65:E76))/(F76*1000) -> 0.26846391 | H76: 4.1 | I76: 6.3 | J76: 17.841403 | K76: 625.542 | L76: =(K76/K64-1)*100 -> -2.2179635 | M76: 137.363 | N76: =(M76/M64-1)*100 -> 5.3421474 | O76: 308283 | P76: =(O76/O64-1)*100 -> -5.9734405 | Q76: =+'crack spread y Brent_WTI'!D280*100 -> -46.357759 | R76: 0.3 | S76: =+AVERAGE($R$18:R76) -> 4.9322034 | T76: 5.131 | U76: =(T76/T64-1)*100 -> 16.164818 | V76: 71.46 | W76: =(V76/V64-1)*100 -> 55.754141 | X76: #N/A N/A | Z76: =+AVERAGE(D74:D76)-$S76 -> 5.5105919 | AA76: =+AVERAGE(H74:H76)-$S76 -> -2.3988701 | AB76: =+AVERAGE(I74:I76)-$S76 -> -0.16553672 | AC76: -9.4548049 | AD76: =AVERAGE(L74:L76) -> -6.1190577 | AE76: =+AVERAGE(N74:N76)*AVERAGE($G$15:G76) -> 3.4123465 | AF76: =-AVERAGE(P74:P76) -> -0.85765544 | AG76: =AVERAGE(Q74:Q76) -> 37.392811 | AH76: =AVERAGE(U74:U76) -> -3.4181665 | AI76: =AVERAGE(W74:W76) -> 57.797023 | AL76: =(Z76- AVERAGE(Z$41:Z76))/_xlfn.STDEV.S(Z$41:Z76) -> 0.12776213 | AM76: =(AA76- AVERAGE(AA$41:AA76))/_xlfn.STDEV.S(AA$41:AA76) -> 0.44708068 | AN76: =(AB76- AVERAGE(AB$41:AB76))/_xlfn.STDEV.S(AB$41:AB76) -> 0.30254342 | AO76: =(AC76- AVERAGE(AC$41:AC76))/_xlfn.STDEV.S(AC$41:AC76) -> -0.80858734 | AP76: =(AD76- AVERAGE(AD$41:AD76))/_xlfn.STDEV.S(AD$41:AD76) -> -1.0406195 | AQ76: =(AE76- AVERAGE(AE$41:AE76))/_xlfn.STDEV.S(AE$41:AE76) -> 1.7412184 | AR76: =(AF76- AVERAGE(AF$41:AF76))/_xlfn.STDEV.S(AF$41:AF76) -> 0.077778053 | AS76: =(AG76- AVERAGE(AG$41:AG76))/_xlfn.STDEV.S(AG$41:AG76) -> 0.98128025 | ... AU76: =(AI76- AVERAGE(AI$41:AI76))/_xlfn.STDEV.S(AI$41:AI76) -> 1.1083521 | AW76: =+IF(AL76>AL$2,AL$2,IF(AL76<AL$1,AL$1,AL76)) -> 0.12776213 | AX76: =+IF(AM76>AM$2,AM$2,IF(AM76<AM$1,AM$1,AM76)) -> 0.44708068 | AY76: =+IF(AN76>AN$2,AN$2,IF(AN76<AN$1,AN$1,AN76)) -> 0.30254342 | AZ76: =+IF(AO76>AO$2,AO$2,IF(AO76<AO$1,AO$1,AO76)) -> -0.80858734 | BA76: =+IF(AP76>AP$2,AP$2,IF(AP76<AP$1,AP$1,AP76)) -> -1.0406195 | BB76: =+IF(AQ76>AQ$2,AQ$2,IF(AQ76<AQ$1,AQ$1,AQ76)) -> 1.7412184 | BC76: =+IF(AR76>AR$2,AR$2,IF(AR76<AR$1,AR$1,AR76)) -> 0.077778053 | BD76: =+IF(AS76>AS$2,AS$2,IF(AS76<AS$1,AS$1,AS76)) -> 0.98128025 | ... BF76: =+IF(AU76>AU$2,AU$2,IF(AU76<AU$1,AU$1,AU76)) -> 1.1083521 | BH76: =+MEDIAN(AW76:BF76) -> 0.21515277 | BI76: =+ABS(BH76) -> 0.21515277 | BJ76: =IF(COUNT(BI75:BI$76)<60,"",MEDIAN(BI75:BI$76)) | BK76: =IF(BH76="","",IF(BJ76="",0,IF(BI76>=BJ76,BH76,0))) -> 0 | BL76: =IF(BK76="","",MEDIAN(-1,BK76,1)) -> 0 | BO76: =+_xlfn.XLOOKUP(B76,Indice!B:B,Indice!AI:AI,"NOOOOOO",-1) -> 0.88197381 | BP76: =IF(BO76="","",LN(BO76)) -> -0.12559292
A77: =+YEAR(B77) -> 2010 | B77: 40237 | C77: 3959 | D77: =+(C77/C65-1)*100 -> 0.35487959 | E77: 3455 | F77: 356.1 | G77: =+(SUM(C66:C77)+SUM(E66:E77))/(F77*1000) -> 0.27072732 | H77: 4.3 | I77: 5.5 | J77: 23.47793 | K77: 626.65 | L77: =(K77/K65-1)*100 -> -4.0856028 | M77: 134.975 | N77: =(M77/M65-1)*100 -> 2.3685648 | O77: 320730 | P77: =(O77/O65-1)*100 -> -3.4844076 | Q77: =+'crack spread y Brent_WTI'!D281*100 -> -11.563732 | R77: 0.3 | S77: =+AVERAGE(R18:R77) -> 4.855 | T77: 4.813 | U77: =(T77/T65-1)*100 -> 14.649833 | V77: 77.59 | W77: =(V77/V65-1)*100 -> 67.400216 | X77: #N/A N/A | Z77: =+AVERAGE(D75:D77)-$S77 -> 5.9168438 | AA77: =+AVERAGE(H75:H77)-$S77 -> -1.2883333 | AB77: =+AVERAGE(I75:I77)-$S77 -> 0.47833333 | AC77: -6.1326151 | AD77: =AVERAGE(L75:L77) -> -4.2835447 | AE77: =+AVERAGE(N75:N77)*AVERAGE($G$15:G77) -> 1.7487267 | AF77: =-AVERAGE(P75:P77) -> 2.3969371 | AG77: =AVERAGE(Q75:Q77) -> -4.1897926 | AH77: =AVERAGE(U75:U77) -> 9.9750959 | AI77: =AVERAGE(W75:W77) -> 64.696989 | AL77: =(Z77- AVERAGE(Z$41:Z77))/_xlfn.STDEV.S(Z$41:Z77) -> 0.14215922 | AM77: =(AA77- AVERAGE(AA$41:AA77))/_xlfn.STDEV.S(AA$41:AA77) -> 0.61817763 | AN77: =(AB77- AVERAGE(AB$41:AB77))/_xlfn.STDEV.S(AB$41:AB77) -> 0.42039626 | AO77: =(AC77- AVERAGE(AC$41:AC77))/_xlfn.STDEV.S(AC$41:AC77) -> -0.32302304 | AP77: =(AD77- AVERAGE(AD$41:AD77))/_xlfn.STDEV.S(AD$41:AD77) -> -0.62638274 | AQ77: =(AE77- AVERAGE(AE$41:AE77))/_xlfn.STDEV.S(AE$41:AE77) -> 1.1043792 | AR77: =(AF77- AVERAGE(AF$41:AF77))/_xlfn.STDEV.S(AF$41:AF77) -> 0.3860933 | AS77: =(AG77- AVERAGE(AG$41:AG77))/_xlfn.STDEV.S(AG$41:AG77) -> -0.24801986 | ... AU77: =(AI77- AVERAGE(AI$41:AI77))/_xlfn.STDEV.S(AI$41:AI77) -> 1.2203479 | AW77: =+IF(AL77>AL$2,AL$2,IF(AL77<AL$1,AL$1,AL77)) -> 0.14215922 | AX77: =+IF(AM77>AM$2,AM$2,IF(AM77<AM$1,AM$1,AM77)) -> 0.61817763 | AY77: =+IF(AN77>AN$2,AN$2,IF(AN77<AN$1,AN$1,AN77)) -> 0.42039626 | AZ77: =+IF(AO77>AO$2,AO$2,IF(AO77<AO$1,AO$1,AO77)) -> -0.32302304 | BA77: =+IF(AP77>AP$2,AP$2,IF(AP77<AP$1,AP$1,AP77)) -> -0.62638274 | BB77: =+IF(AQ77>AQ$2,AQ$2,IF(AQ77<AQ$1,AQ$1,AQ77)) -> 1.1043792 | BC77: =+IF(AR77>AR$2,AR$2,IF(AR77<AR$1,AR$1,AR77)) -> 0.3860933 | BD77: =+IF(AS77>AS$2,AS$2,IF(AS77<AS$1,AS$1,AS77)) -> -0.24801986 | ... BF77: =+IF(AU77>AU$2,AU$2,IF(AU77<AU$1,AU$1,AU77)) -> 1.2203479 | BH77: =+MEDIAN(AW77:BF77) -> 0.40324478 | BI77: =+ABS(BH77) -> 0.40324478 | BJ77: =IF(COUNT(BI76:BI$76)<60,"",MEDIAN(BI76:BI$76)) | BK77: =IF(BH77="","",IF(BJ77="",0,IF(BI77>=BJ77,BH77,0))) -> 0 | BL77: =IF(BK77="","",MEDIAN(-1,BK77,1)) -> 0 | BO77: =+_xlfn.XLOOKUP(B77,Indice!B:B,Indice!AI:AI,"NOOOOOO",-1) -> 0.88507782 | BP77: =IF(BO77="","",LN(BO77)) -> -0.1220797 | BQ77: =+BP77-BP76 -> 0.0035132186
A78: =+YEAR(B78) -> 2010 | B78: 40268 | C78: 4687 | D78: =+(C78/C66-1)*100 -> 9.9202627 | E78: 4403 | F78: 369.47 | G78: =+(SUM(C67:C78)+SUM(E67:E78))/(F78*1000) -> 0.26617587 | H78: 8.5 | I78: 7.6 | J78: 23.845025 | K78: 627.027 | L78: =(K78/K66-1)*100 -> -3.5193161 | M78: 132.964 | N78: =(M78/M66-1)*100 -> -3.4316467 | O78: 333386 | P78: =(O78/O66-1)*100 -> -2.2076078 | Q78: =+'crack spread y Brent_WTI'!D282*100 -> 22.192312 | R78: 5.7 | S78: =+AVERAGE(R19:R78) -> 4.83 | T78: 3.869 | U78: =(T78/T66-1)*100 -> 2.4629237 | V78: 82.7 | W78: =(V78/V66-1)*100 -> 67.987 | X78: #N/A N/A | Z78: =+AVERAGE(D76:D78)-$S78 -> 4.8130824 | AA78: =+AVERAGE(H76:H78)-$S78 -> 0.80333333 | AB78: =+AVERAGE(I76:I78)-$S78 -> 1.6366667 | AC78: -3.832958 | AD78: =AVERAGE(L76:L78) -> -3.2742941 | AE78: =+AVERAGE(N76:N78)*AVERAGE($G$15:G78) -> 0.46467636 | AF78: =-AVERAGE(P76:P78) -> 3.8884853 | AG78: =AVERAGE(Q76:Q78) -> -11.909726 | AH78: =AVERAGE(U76:U78) -> 11.092525 | AI78: =AVERAGE(W76:W78) -> 63.713786 | AL78: =(Z78- AVERAGE(Z$41:Z78))/_xlfn.STDEV.S(Z$41:Z78) -> 0.095872919 | AM78: =(AA78- AVERAGE(AA$41:AA78))/_xlfn.STDEV.S(AA$41:AA78) -> 0.94127035 | AN78: =(AB78- AVERAGE(AB$41:AB78))/_xlfn.STDEV.S(AB$41:AB78) -> 0.63517301 | AO78: =(AC78- AVERAGE(AC$41:AC78))/_xlfn.STDEV.S(AC$41:AC78) -> 0.013792284 | AP78: =(AD78- AVERAGE(AD$41:AD78))/_xlfn.STDEV.S(AD$41:AD78) -> -0.39725613 | AQ78: =(AE78- AVERAGE(AE$41:AE78))/_xlfn.STDEV.S(AE$41:AE78) -> 0.62963729 | AR78: =(AF78- AVERAGE(AF$41:AF78))/_xlfn.STDEV.S(AF$41:AF78) -> 0.52302727 | AS78: =(AG78- AVERAGE(AG$41:AG78))/_xlfn.STDEV.S(AG$41:AG78) -> -0.47229098 | ... AU78: =(AI78- AVERAGE(AI$41:AI78))/_xlfn.STDEV.S(AI$41:AI78) -> 1.1605918 | AW78: =+IF(AL78>AL$2,AL$2,IF(AL78<AL$1,AL$1,AL78)) -> 0.095872919 | AX78: =+IF(AM78>AM$2,AM$2,IF(AM78<AM$1,AM$1,AM78)) -> 0.94127035 | AY78: =+IF(AN78>AN$2,AN$2,IF(AN78<AN$1,AN$1,AN78)) -> 0.63517301 | AZ78: =+IF(AO78>AO$2,AO$2,IF(AO78<AO$1,AO$1,AO78)) -> 0.013792284 | BA78: =+IF(AP78>AP$2,AP$2,IF(AP78<AP$1,AP$1,AP78)) -> -0.39725613 | BB78: =+IF(AQ78>AQ$2,AQ$2,IF(AQ78<AQ$1,AQ$1,AQ78)) -> 0.62963729 | BC78: =+IF(AR78>AR$2,AR$2,IF(AR78<AR$1,AR$1,AR78)) -> 0.52302727 | BD78: =+IF(AS78>AS$2,AS$2,IF(AS78<AS$1,AS$1,AS78)) -> -0.47229098 | ... BF78: =+IF(AU78>AU$2,AU$2,IF(AU78<AU$1,AU$1,AU78)) -> 1.1605918 | BH78: =+MEDIAN(AW78:BF78) -> 0.49026423 | BI78: =+ABS(BH78) -> 0.49026423 | BJ78: =IF(COUNT(BI$76:BI77)<60,"",MEDIAN(BI$76:BI77)) | BK78: =IF(BH78="","",IF(BJ78="",0,IF(BI78>=BJ78,BH78,0))) -> 0 | BL78: =IF(BK78="","",MEDIAN(-1,BK78,1)) -> 0 | BO78: =+_xlfn.XLOOKUP(B78,Indice!B:B,Indice!AI:AI,"NOOOOOO",-1) -> 0.82452387 | BP78: =IF(BO78="","",LN(BO78)) -> -0.19294919 | BQ78: =+BP78-BP77 -> -0.070869484
A79: =+YEAR(B79) -> 2010 | B79: 40298 | C79: 6208 | D79: =+(C79/C67-1)*100 -> 22.882027 | E79: 4101 | F79: 369.47 | G79: =+(SUM(C68:C79)+SUM(E68:E79))/(F79*1000) -> 0.27288819 | H79: 13.9 | I79: 9.6 | J79: 23.243368 | K79: 626.594 | L79: =(K79/K67-1)*100 -> -3.1835698 | M79: 132.848 | N79: =(M79/M67-1)*100 -> -3.8469055 | O79: 339942 | P79: =(O79/O67-1)*100 -> -4.4862591 | Q79: =+'crack spread y Brent_WTI'!D283*100 -> 55.74207 | R79: 5.7 | S79: =+AVERAGE(R20:R79) -> 4.805 | T79: 3.92 | U79: =(T79/T67-1)*100 -> 16.217017 | V79: 87.44 | W79: =(V79/V67-1)*100 -> 72.125984 | X79: #N/A N/A | Z79: =+AVERAGE(D77:D79)-$S79 -> 6.2473897 | AA79: =+AVERAGE(H77:H79)-$S79 -> 4.095 | AB79: =+AVERAGE(I77:I79)-$S79 -> 2.7616667 | AC79: -2.1841147 | AD79: =AVERAGE(L77:L79) -> -3.5961629 | AE79: =+AVERAGE(N77:N79)*AVERAGE($G$15:G79) -> -0.53185827 | AF79: =-AVERAGE(P77:P79) -> 3.3927582 | AG79: =AVERAGE(Q77:Q79) -> 22.12355 | AH79: =AVERAGE(U77:U79) -> 11.109925 | AI79: =AVERAGE(W77:W79) -> 69.171067 | AL79: =(Z79- AVERAGE(Z$41:Z79))/_xlfn.STDEV.S(Z$41:Z79) -> 0.15317993 | AM79: =(AA79- AVERAGE(AA$41:AA79))/_xlfn.STDEV.S(AA$41:AA79) -> 1.4287501 | AN79: =(AB79- AVERAGE(AB$41:AB79))/_xlfn.STDEV.S(AB$41:AB79) -> 0.83829666 | AO79: =(AC79- AVERAGE(AC$41:AC79))/_xlfn.STDEV.S(AC$41:AC79) -> 0.25527337 | AP79: =(AD79- AVERAGE(AD$41:AD79))/_xlfn.STDEV.S(AD$41:AD79) -> -0.46198469 | AQ79: =(AE79- AVERAGE(AE$41:AE79))/_xlfn.STDEV.S(AE$41:AE79) -> 0.26376784 | AR79: =(AF79- AVERAGE(AF$41:AF79))/_xlfn.STDEV.S(AF$41:AF79) -> 0.46675848 | AS79: =(AG79- AVERAGE(AG$41:AG79))/_xlfn.STDEV.S(AG$41:AG79) -> 0.55170507 | ... AU79: =(AI79- AVERAGE(AI$41:AI79))/_xlfn.STDEV.S(AI$41:AI79) -> 1.23936 | AW79: =+IF(AL79>AL$2,AL$2,IF(AL79<AL$1,AL$1,AL79)) -> 0.15317993 | AX79: =+IF(AM79>AM$2,AM$2,IF(AM79<AM$1,AM$1,AM79)) -> 1.4287501 | AY79: =+IF(AN79>AN$2,AN$2,IF(AN79<AN$1,AN$1,AN79)) -> 0.83829666 | AZ79: =+IF(AO79>AO$2,AO$2,IF(AO79<AO$1,AO$1,AO79)) -> 0.25527337 | BA79: =+IF(AP79>AP$2,AP$2,IF(AP79<AP$1,AP$1,AP79)) -> -0.46198469 | BB79: =+IF(AQ79>AQ$2,AQ$2,IF(AQ79<AQ$1,AQ$1,AQ79)) -> 0.26376784 | BC79: =+IF(AR79>AR$2,AR$2,IF(AR79<AR$1,AR$1,AR79)) -> 0.46675848 | BD79: =+IF(AS79>AS$2,AS$2,IF(AS79<AS$1,AS$1,AS79)) -> 0.55170507 | ... BF79: =+IF(AU79>AU$2,AU$2,IF(AU79<AU$1,AU$1,AU79)) -> 1.23936 | BH79: =+MEDIAN(AW79:BF79) -> 0.45886904 | BI79: =+ABS(BH79) -> 0.45886904 | BJ79: =IF(COUNT(BI$76:BI78)<60,"",MEDIAN(BI$76:BI78)) | BK79: =IF(BH79="","",IF(BJ79="",0,IF(BI79>=BJ79,BH79,0))) -> 0 | BL79: =IF(BK79="","",MEDIAN(-1,BK79,1)) -> 0 | BO79: =+_xlfn.XLOOKUP(B79,Indice!B:B,Indice!AI:AI,"NOOOOOO",-1) -> 0.9065987 | BP79: =IF(BO79="","",LN(BO79)) -> -0.098055371 | BQ79: =+BP79-BP78 -> 0.094893815
A80: =+YEAR(B80) -> 2010 | B80: 40329 | C80: 6503 | D80: =+(C80/C68-1)*100 -> 24.985585 | E80: 4575 | F80: 369.47 | G80: =+(SUM(C69:C80)+SUM(E69:E80))/(F80*1000) -> 0.28158984 | H80: 18.8 | I80: 13.5 | J80: 24.197056 | K80: 625.2 | L80: =(K80/K68-1)*100 -> -2.8515223 | M80: 127.344 | N80: =(M80/M68-1)*100 -> -13.302424 | O80: 342581 | P80: =(O80/O68-1)*100 -> -1.4387972 | Q80: =+'crack spread y Brent_WTI'!D284*100 -> 5.7881894 | R80: 5.7 | S80: =+AVERAGE(R21:R80) -> 4.78 | T80: 4.341 | U80: =(T80/T68-1)*100 -> 13.194263 | V80: 74.65 | W80: =(V80/V68-1)*100 -> 13.934676 | X80: #N/A N/A | Z80: =+AVERAGE(D78:D80)-$S80 -> 14.482625 | AA80: =+AVERAGE(H78:H80)-$S80 -> 8.9533333 | AB80: =+AVERAGE(I78:I80)-$S80 -> 5.4533333 | AC80: -2.0431559 | AD80: =AVERAGE(L78:L80) -> -3.1848027 | AE80: =+AVERAGE(N78:N80)*AVERAGE($G$15:G80) -> -2.2248581 | AF80: =-AVERAGE(P78:P80) -> 2.710888 | AG80: =AVERAGE(Q78:Q80) -> 27.907524 | AH80: =AVERAGE(U78:U80) -> 10.624735 | AI80: =AVERAGE(W78:W80) -> 51.34922 | AL80: =(Z80- AVERAGE(Z$41:Z80))/_xlfn.STDEV.S(Z$41:Z80) -> 0.49048346 | AM80: =(AA80- AVERAGE(AA$41:AA80))/_xlfn.STDEV.S(AA$41:AA80) -> 2.0697309 | AN80: =(AB80- AVERAGE(AB$41:AB80))/_xlfn.STDEV.S(AB$41:AB80) -> 1.3230079 | AO80: =(AC80- AVERAGE(AC$41:AC80))/_xlfn.STDEV.S(AC$41:AC80) -> 0.27282152 | AP80: =(AD80- AVERAGE(AD$41:AD80))/_xlfn.STDEV.S(AD$41:AD80) -> -0.36389379 | AQ80: =(AE80- AVERAGE(AE$41:AE80))/_xlfn.STDEV.S(AE$41:AE80) -> -0.3543603 | AR80: =(AF80- AVERAGE(AF$41:AF80))/_xlfn.STDEV.S(AF$41:AF80) -> 0.39306014 | AS80: =(AG80- AVERAGE(AG$41:AG80))/_xlfn.STDEV.S(AG$41:AG80) -> 0.71515232 | ... AU80: =(AI80- AVERAGE(AI$41:AI80))/_xlfn.STDEV.S(AI$41:AI80) -> 0.82804179 | AW80: =+IF(AL80>AL$2,AL$2,IF(AL80<AL$1,AL$1,AL80)) -> 0.49048346 | AX80: =+IF(AM80>AM$2,AM$2,IF(AM80<AM$1,AM$1,AM80)) -> 2.0697309 | AY80: =+IF(AN80>AN$2,AN$2,IF(AN80<AN$1,AN$1,AN80)) -> 1.3230079 | AZ80: =+IF(AO80>AO$2,AO$2,IF(AO80<AO$1,AO$1,AO80)) -> 0.27282152 | BA80: =+IF(AP80>AP$2,AP$2,IF(AP80<AP$1,AP$1,AP80)) -> -0.36389379 | BB80: =+IF(AQ80>AQ$2,AQ$2,IF(AQ80<AQ$1,AQ$1,AQ80)) -> -0.3543603 | BC80: =+IF(AR80>AR$2,AR$2,IF(AR80<AR$1,AR$1,AR80)) -> 0.39306014 | BD80: =+IF(AS80>AS$2,AS$2,IF(AS80<AS$1,AS$1,AS80)) -> 0.71515232 | ... BF80: =+IF(AU80>AU$2,AU$2,IF(AU80<AU$1,AU$1,AU80)) -> 0.82804179 | BH80: =+MEDIAN(AW80:BF80) -> 0.46082607 | BI80: =+ABS(BH80) -> 0.46082607 | BJ80: =IF(COUNT(BI$76:BI79)<60,"",MEDIAN(BI$76:BI79)) | BK80: =IF(BH80="","",IF(BJ80="",0,IF(BI80>=BJ80,BH80,0))) -> 0 | BL80: =IF(BK80="","",MEDIAN(-1,BK80,1)) -> 0 | BO80: =+_xlfn.XLOOKUP(B80,Indice!B:B,Indice!AI:AI,"NOOOOOO",-1) -> 0.83891291 | BP80: =IF(BO80="","",LN(BO80)) -> -0.17564838 | BQ80: =+BP80-BP79 -> -0.077593005
A81: =+YEAR(B81) -> 2010 | B81: 40359 | C81: 6369 | D81: =+(C81/C69-1)*100 -> 22.222222 | E81: 5151 | F81: 432.2 | G81: =+(SUM(C70:C81)+SUM(E70:E81))/(F81*1000) -> 0.24694354 | H81: 15.9 | I81: 11.1 | J81: 24.947025 | K81: 627.703 | L81: =(K81/K69-1)*100 -> -0.07593365 | M81: 126.58 | N81: =(M81/M69-1)*100 -> -14.927078 | O81: 342606 | P81: =(O81/O69-1)*100 -> 3.2617607 | Q81: =+'crack spread y Brent_WTI'!D285*100 -> 25.327615 | R81: 16.2 | S81: =+AVERAGE(R22:R81) -> 4.8316667 | T81: 4.616 | U81: =(T81/T69-1)*100 -> 20.365059 | V81: 75.01 | W81: =(V81/V69-1)*100 -> 8.2395382 | X81: #N/A N/A | Z81: =+AVERAGE(D79:D81)-$S81 -> 18.531611 | AA81: =+AVERAGE(H79:H81)-$S81 -> 11.368333 | AB81: =+AVERAGE(I79:I81)-$S81 -> 6.5683333 | AC81: -1.818857 | AD81: =AVERAGE(L79:L81) -> -2.0370086 | AE81: =+AVERAGE(N79:N81)*AVERAGE($G$15:G81) -> -3.4551987 | AF81: =-AVERAGE(P79:P81) -> 0.88776521 | AG81: =AVERAGE(Q79:Q81) -> 28.952625 | AH81: =AVERAGE(U79:U81) -> 16.592113 | AI81: =AVERAGE(W79:W81) -> 31.4334 | AL81: =(Z81- AVERAGE(Z$41:Z81))/_xlfn.STDEV.S(Z$41:Z81) -> 0.65029673 | AM81: =(AA81- AVERAGE(AA$41:AA81))/_xlfn.STDEV.S(AA$41:AA81) -> 2.2549017 | AN81: =(AB81- AVERAGE(AB$41:AB81))/_xlfn.STDEV.S(AB$41:AB81) -> 1.4797173 | AO81: =(AC81- AVERAGE(AC$41:AC81))/_xlfn.STDEV.S(AC$41:AC81) -> 0.30294043 | AP81: =(AD81- AVERAGE(AD$41:AD81))/_xlfn.STDEV.S(AD$41:AD81) -> -0.10042702 | AQ81: =(AE81- AVERAGE(AE$41:AE81))/_xlfn.STDEV.S(AE$41:AE81) -> -0.79609446 | AR81: =(AF81- AVERAGE(AF$41:AF81))/_xlfn.STDEV.S(AF$41:AF81) -> 0.20660033 | AS81: =(AG81- AVERAGE(AG$41:AG81))/_xlfn.STDEV.S(AG$41:AG81) -> 0.73333163 | ... AU81: =(AI81- AVERAGE(AI$41:AI81))/_xlfn.STDEV.S(AI$41:AI81) -> 0.38138611 | AW81: =+IF(AL81>AL$2,AL$2,IF(AL81<AL$1,AL$1,AL81)) -> 0.65029673 | AX81: =+IF(AM81>AM$2,AM$2,IF(AM81<AM$1,AM$1,AM81)) -> 2.2549017 | AY81: =+IF(AN81>AN$2,AN$2,IF(AN81<AN$1,AN$1,AN81)) -> 1.4797173 | AZ81: =+IF(AO81>AO$2,AO$2,IF(AO81<AO$1,AO$1,AO81)) -> 0.30294043 | BA81: =+IF(AP81>AP$2,AP$2,IF(AP81<AP$1,AP$1,AP81)) -> -0.10042702 | BB81: =+IF(AQ81>AQ$2,AQ$2,IF(AQ81<AQ$1,AQ$1,AQ81)) -> -0.79609446 | BC81: =+IF(AR81>AR$2,AR$2,IF(AR81<AR$1,AR$1,AR81)) -> 0.20660033 | BD81: =+IF(AS81>AS$2,AS$2,IF(AS81<AS$1,AS$1,AS81)) -> 0.73333163 | ... BF81: =+IF(AU81>AU$2,AU$2,IF(AU81<AU$1,AU$1,AU81)) -> 0.38138611 | BH81: =+MEDIAN(AW81:BF81) -> 0.48461178 | BI81: =+ABS(BH81) -> 0.48461178 | BJ81: =IF(COUNT(BI$76:BI80)<60,"",MEDIAN(BI$76:BI80)) | BK81: =IF(BH81="","",IF(BJ81="",0,IF(BI81>=BJ81,BH81,0))) -> 0 | BL81: =IF(BK81="","",MEDIAN(-1,BK81,1)) -> 0 | BO81: =+_xlfn.XLOOKUP(B81,Indice!B:B,Indice!AI:AI,"NOOOOOO",-1) -> 0.85404288 | BP81: =IF(BO81="","",LN(BO81)) -> -0.15777387 | BQ81: =+BP81-BP80 -> 0.017874501
A82: =+YEAR(B82) -> 2010 | B82: 40390 | C82: 5984 | D82: =+(C82/C70-1)*100 -> 21.502538 | E82: 5291 | F82: 432.2 | G82: =+(SUM(C71:C82)+SUM(E71:E82))/(F82*1000) -> 0.25333179 | H82: 9.5 | I82: 10.4 | J82: 25.56816 | K82: 624.752 | L82: =(K82/K70-1)*100 -> -0.60630358 | M82: 128.581 | N82: =(M82/M70-1)*100 -> -15.411132 | O82: 337388 | P82: =(O82/O70-1)*100 -> 1.838839 | Q82: =+'crack spread y Brent_WTI'!D286*100 -> -22.670807 | R82: 16.2 | S82: =+AVERAGE(R23:R82) -> 4.8833333 | T82: 4.923 | U82: =(T82/T70-1)*100 -> 34.765946 | V82: 78.18 | W82: =(V82/V70-1)*100 -> 9.0376569 | X82: #N/A N/A | Z82: =+AVERAGE(D80:D82)-$S82 -> 18.020115 | AA82: =+AVERAGE(H80:H82)-$S82 -> 9.85 | AB82: =+AVERAGE(I80:I82)-$S82 -> 6.7833333 | AC82: -1.1808022 | AD82: =AVERAGE(L80:L82) -> -1.1779198 | AE82: =+AVERAGE(N80:N82)*AVERAGE($G$15:G82) -> -4.6859347 | AF82: =-AVERAGE(P80:P82) -> -1.2206008 | AG82: =AVERAGE(Q80:Q82) -> 2.814999 | AH82: =AVERAGE(U80:U82) -> 22.775089 | AI82: =AVERAGE(W80:W82) -> 10.403957 | AL82: =(Z82- AVERAGE(Z$41:Z82))/_xlfn.STDEV.S(Z$41:Z82) -> 0.61818762 | AM82: =(AA82- AVERAGE(AA$41:AA82))/_xlfn.STDEV.S(AA$41:AA82) -> 1.9130825 | AN82: =(AB82- AVERAGE(AB$41:AB82))/_xlfn.STDEV.S(AB$41:AB82) -> 1.4626672 | AO82: =(AC82- AVERAGE(AC$41:AC82))/_xlfn.STDEV.S(AC$41:AC82) -> 0.39573701 | AP82: =(AD82- AVERAGE(AD$41:AD82))/_xlfn.STDEV.S(AD$41:AD82) -> 0.097164576 | AQ82: =(AE82- AVERAGE(AE$41:AE82))/_xlfn.STDEV.S(AE$41:AE82) -> -1.2183716 | AR82: =(AF82- AVERAGE(AF$41:AF82))/_xlfn.STDEV.S(AF$41:AF82) -> -0.0084980961 | AS82: =(AG82- AVERAGE(AG$41:AG82))/_xlfn.STDEV.S(AG$41:AG82) -> -0.076315586 | ... AU82: =(AI82- AVERAGE(AI$41:AI82))/_xlfn.STDEV.S(AI$41:AI82) -> -0.088607799 | AW82: =+IF(AL82>AL$2,AL$2,IF(AL82<AL$1,AL$1,AL82)) -> 0.61818762 | AX82: =+IF(AM82>AM$2,AM$2,IF(AM82<AM$1,AM$1,AM82)) -> 1.9130825 | AY82: =+IF(AN82>AN$2,AN$2,IF(AN82<AN$1,AN$1,AN82)) -> 1.4626672 | AZ82: =+IF(AO82>AO$2,AO$2,IF(AO82<AO$1,AO$1,AO82)) -> 0.39573701 | BA82: =+IF(AP82>AP$2,AP$2,IF(AP82<AP$1,AP$1,AP82)) -> 0.097164576 | BB82: =+IF(AQ82>AQ$2,AQ$2,IF(AQ82<AQ$1,AQ$1,AQ82)) -> -1.2183716 | BC82: =+IF(AR82>AR$2,AR$2,IF(AR82<AR$1,AR$1,AR82)) -> -0.0084980961 | BD82: =+IF(AS82>AS$2,AS$2,IF(AS82<AS$1,AS$1,AS82)) -> -0.076315586 | ... BF82: =+IF(AU82>AU$2,AU$2,IF(AU82<AU$1,AU$1,AU82)) -> -0.088607799 | BH82: =+MEDIAN(AW82:BF82) -> 0.24645079 | BI82: =+ABS(BH82) -> 0.24645079 | BJ82: =IF(COUNT(BI$76:BI81)<60,"",MEDIAN(BI$76:BI81)) | BK82: =IF(BH82="","",IF(BJ82="",0,IF(BI82>=BJ82,BH82,0))) -> 0 | BL82: =IF(BK82="","",MEDIAN(-1,BK82,1)) -> 0 | BO82: =+_xlfn.XLOOKUP(B82,Indice!B:B,Indice!AI:AI,"NOOOOOO",-1) -> 0.83530665 | BP82: =IF(BO82="","",LN(BO82)) -> -0.17995638 | BQ82: =+BP82-BP81 -> -0.022182507
A83: =+YEAR(B83) -> 2010 | B83: 40421 | C83: 6383 | D83: =+(C83/C71-1)*100 -> 46.668199 | E83: 5355 | F83: 432.2 | G83: =+(SUM(C72:C83)+SUM(E72:E83))/(F83*1000) -> 0.26288987 | H83: 10.7 | I83: 10.8 | J83: 24.50106 | K83: 625.585 | L83: =(K83/K71-1)*100 -> 12.554965 | M83: 127.302 | N83: =(M83/M71-1)*100 -> -15.23767 | O83: 341105 | P83: =(O83/O71-1)*100 -> 4.8421551 | Q83: =+'crack spread y Brent_WTI'!D287*100 -> 32.14049 | R83: 16.2 | S83: =+AVERAGE(R24:R83) -> 4.935 | T83: 3.816 | U83: =(T83/T71-1)*100 -> 28.182734 | V83: 74.64 | W83: =(V83/V71-1)*100 -> 7.1643934 | X83: #N/A N/A | Z83: =+AVERAGE(D81:D83)-$S83 -> 25.195986 | AA83: =+AVERAGE(H81:H83)-$S83 -> 7.0983333 | AB83: =+AVERAGE(I81:I83)-$S83 -> 5.8316667 | AC83: -1.2169554 | AD83: =AVERAGE(L81:L83) -> 3.9575761 | AE83: =+AVERAGE(N81:N83)*AVERAGE($G$15:G83) -> -4.8806903 | AF83: =-AVERAGE(P81:P83) -> -3.3142516 | AG83: =AVERAGE(Q81:Q83) -> 11.599099 | AH83: =AVERAGE(U81:U83) -> 27.771246 | AI83: =AVERAGE(W81:W83) -> 8.1471962 | AL83: =(Z83- AVERAGE(Z$41:Z83))/_xlfn.STDEV.S(Z$41:Z83) -> 0.9064662 | AM83: =(AA83- AVERAGE(AA$41:AA83))/_xlfn.STDEV.S(AA$41:AA83) -> 1.4639292 | AN83: =(AB83- AVERAGE(AB$41:AB83))/_xlfn.STDEV.S(AB$41:AB83) -> 1.2431972 | AO83: =(AC83- AVERAGE(AC$41:AC83))/_xlfn.STDEV.S(AC$41:AC83) -> 0.38496056 | AP83: =(AD83- AVERAGE(AD$41:AD83))/_xlfn.STDEV.S(AD$41:AD83) -> 1.2599404 | AQ83: =(AE83- AVERAGE(AE$41:AE83))/_xlfn.STDEV.S(AE$41:AE83) -> -1.251393 | AR83: =(AF83- AVERAGE(AF$41:AF83))/_xlfn.STDEV.S(AF$41:AF83) -> -0.22214889 | AS83: =(AG83- AVERAGE(AG$41:AG83))/_xlfn.STDEV.S(AG$41:AG83) -> 0.19708213 | ... AU83: =(AI83- AVERAGE(AI$41:AI83))/_xlfn.STDEV.S(AI$41:AI83) -> -0.1381533 | AW83: =+IF(AL83>AL$2,AL$2,IF(AL83<AL$1,AL$1,AL83)) -> 0.9064662 | AX83: =+IF(AM83>AM$2,AM$2,IF(AM83<AM$1,AM$1,AM83)) -> 1.4639292 | AY83: =+IF(AN83>AN$2,AN$2,IF(AN83<AN$1,AN$1,AN83)) -> 1.2431972 | AZ83: =+IF(AO83>AO$2,AO$2,IF(AO83<AO$1,AO$1,AO83)) -> 0.38496056 | BA83: =+IF(AP83>AP$2,AP$2,IF(AP83<AP$1,AP$1,AP83)) -> 1.2599404 | BB83: =+IF(AQ83>AQ$2,AQ$2,IF(AQ83<AQ$1,AQ$1,AQ83)) -> -1.251393 | BC83: =+IF(AR83>AR$2,AR$2,IF(AR83<AR$1,AR$1,AR83)) -> -0.22214889 | BD83: =+IF(AS83>AS$2,AS$2,IF(AS83<AS$1,AS$1,AS83)) -> 0.19708213 | ... BF83: =+IF(AU83>AU$2,AU$2,IF(AU83<AU$1,AU$1,AU83)) -> -0.1381533 | BH83: =+MEDIAN(AW83:BF83) -> 0.62772272 | BI83: =+ABS(BH83) -> 0.62772272 | BJ83: =IF(COUNT(BI$76:BI82)<60,"",MEDIAN(BI$76:BI82)) | BK83: =IF(BH83="","",IF(BJ83="",0,IF(BI83>=BJ83,BH83,0))) -> 0 | BL83: =IF(BK83="","",MEDIAN(-1,BK83,1)) -> 0 | BO83: =+_xlfn.XLOOKUP(B83,Indice!B:B,Indice!AI:AI,"NOOOOOO",-1) -> 0.85400202 | BP83: =IF(BO83="","",LN(BO83)) -> -0.15782172 | BQ83: =+BP83-BP82 -> 0.022134661
A84: =+YEAR(B84) -> 2010 | B84: 40451 | C84: 6375 | D84: =+(C84/C72-1)*100 -> 40.697418 | E84: 5337 | F84: 434.56 | G84: =+(SUM(C73:C84)+SUM(E73:E84))/(F84*1000) -> 0.26955081 | H84: 8.3 | I84: 9.2 | J84: 24.563675 | K84: 615.741 | L84: =(K84/K72-1)*100 -> -2.1581922 | M84: 130.347 | N84: =(M84/M72-1)*100 -> -14.081471 | O84: 337343 | P84: =(O84/O72-1)*100 -> 5.2660648 | Q84: =+'crack spread y Brent_WTI'!D288*100 -> 115.01957 | R84: 9.5 | S84: =+AVERAGE(R25:R84) -> 4.9766667 | T84: 3.872 | U84: =(T84/T72-1)*100 -> -20.016526 | V84: 82.31 | W84: =(V84/V72-1)*100 -> 19.168959 | X84: #N/A N/A | Z84: =+AVERAGE(D82:D84)-$S84 -> 31.312718 | AA84: =+AVERAGE(H82:H84)-$S84 -> 4.5233333 | AB84: =+AVERAGE(I82:I84)-$S84 -> 5.1566667 | AC84: -1.4477479 | AD84: =AVERAGE(L82:L84) -> 3.2634899 | AE84: =+AVERAGE(N82:N84)*AVERAGE($G$15:G84) -> -4.779119 | AF84: =-AVERAGE(P82:P84) -> -3.982353 | AG84: =AVERAGE(Q82:Q84) -> 41.496417 | AH84: =AVERAGE(U82:U84) -> 14.310718 | AI84: =AVERAGE(W82:W84) -> 11.790336 | AL84: =(Z84- AVERAGE(Z$41:Z84))/_xlfn.STDEV.S(Z$41:Z84) -> 1.1385419 | AM84: =(AA84- AVERAGE(AA$41:AA84))/_xlfn.STDEV.S(AA$41:AA84) -> 1.0750912 | AN84: =(AB84- AVERAGE(AB$41:AB84))/_xlfn.STDEV.S(AB$41:AB84) -> 1.0878169 | AO84: =(AC84- AVERAGE(AC$41:AC84))/_xlfn.STDEV.S(AC$41:AC84) -> 0.34429953 | AP84: =(AD84- AVERAGE(AD$41:AD84))/_xlfn.STDEV.S(AD$41:AD84) -> 1.0714273 | AQ84: =(AE84- AVERAGE(AE$41:AE84))/_xlfn.STDEV.S(AE$41:AE84) -> -1.1803249 | AR84: =(AF84- AVERAGE(AF$41:AF84))/_xlfn.STDEV.S(AF$41:AF84) -> -0.28843834 | AS84: =(AG84- AVERAGE(AG$41:AG84))/_xlfn.STDEV.S(AG$41:AG84) -> 1.116854 | ... AU84: =(AI84- AVERAGE(AI$41:AI84))/_xlfn.STDEV.S(AI$41:AI84) -> -0.053950153 | AW84: =+IF(AL84>AL$2,AL$2,IF(AL84<AL$1,AL$1,AL84)) -> 1.1385419 | AX84: =+IF(AM84>AM$2,AM$2,IF(AM84<AM$1,AM$1,AM84)) -> 1.0750912 | AY84: =+IF(AN84>AN$2,AN$2,IF(AN84<AN$1,AN$1,AN84)) -> 1.0878169 | AZ84: =+IF(AO84>AO$2,AO$2,IF(AO84<AO$1,AO$1,AO84)) -> 0.34429953 | BA84: =+IF(AP84>AP$2,AP$2,IF(AP84<AP$1,AP$1,AP84)) -> 1.0714273 | BB84: =+IF(AQ84>AQ$2,AQ$2,IF(AQ84<AQ$1,AQ$1,AQ84)) -> -1.1803249 | BC84: =+IF(AR84>AR$2,AR$2,IF(AR84<AR$1,AR$1,AR84)) -> -0.28843834 | BD84: =+IF(AS84>AS$2,AS$2,IF(AS84<AS$1,AS$1,AS84)) -> 1.116854 | ... BF84: =+IF(AU84>AU$2,AU$2,IF(AU84<AU$1,AU$1,AU84)) -> -0.053950153 | BH84: =+MEDIAN(AW84:BF84) -> 0.77676715 | BI84: =+ABS(BH84) -> 0.77676715 | BJ84: =IF(COUNT(BI$76:BI83)<60,"",MEDIAN(BI$76:BI83)) | BK84: =IF(BH84="","",IF(BJ84="",0,IF(BI84>=BJ84,BH84,0))) -> 0 | BL84: =IF(BK84="","",MEDIAN(-1,BK84,1)) -> 0 | BO84: =+_xlfn.XLOOKUP(B84,Indice!B:B,Indice!AI:AI,"NOOOOOO",-1) -> 0.76531225 | BP84: =IF(BO84="","",LN(BO84)) -> -0.26747136 | BQ84: =+BP84-BP83 -> -0.10964964
A85: =+YEAR(B85) -> 2010 | B85: 40482 | C85: 5899 | D85: =+(C85/C73-1)*100 -> 22.691348 | E85: 4951 | F85: 434.56 | G85: =+(SUM(C74:C85)+SUM(E74:E85))/(F85*1000) -> 0.27504142 | H85: 6.3 | I85: 7.7 | J85: 26.701947 | K85: 608.529 | L85: =(K85/K73-1)*100 -> -4.7655639 | M85: 127.506 | N85: =(M85/M73-1)*100 -> -14.860344 | O85: 347394 | P85: =(O85/O73-1)*100 -> 9.3049232 | Q85: =+'crack spread y Brent_WTI'!D289*100 -> 27.310995 | R85: 9.5 | S85: =+AVERAGE(R26:R85) -> 5.0183333 | T85: 4.038 | U85: =(T85/T73-1)*100 -> -19.960357 | V85: 83.15 | W85: =(V85/V73-1)*100 -> 10.571809 | X85: #N/A N/A | Z85: =+AVERAGE(D83:D85)-$S85 -> 31.667321 | AA85: =+AVERAGE(H83:H85)-$S85 -> 3.415 | AB85: =+AVERAGE(I83:I85)-$S85 -> 4.215 | AC85: -1.2144052 | AD85: =AVERAGE(L83:L85) -> 1.8770698 | AE85: =+AVERAGE(N83:N85)*AVERAGE($G$15:G85) -> -4.7108362 | AF85: =-AVERAGE(P83:P85) -> -6.4710477 | AG85: =AVERAGE(Q83:Q85) -> 58.157018 | AH85: =AVERAGE(U83:U85) -> -3.9313827 | AI85: =AVERAGE(W83:W85) -> 12.30172 | AL85: =(Z85- AVERAGE(Z$41:Z85))/_xlfn.STDEV.S(Z$41:Z85) -> 1.1242514 | AM85: =(AA85- AVERAGE(AA$41:AA85))/_xlfn.STDEV.S(AA$41:AA85) -> 0.90118918 | AN85: =(AB85- AVERAGE(AB$41:AB85))/_xlfn.STDEV.S(AB$41:AB85) -> 0.89238465 | AO85: =(AC85- AVERAGE(AC$41:AC85))/_xlfn.STDEV.S(AC$41:AC85) -> 0.37657886 | AP85: =(AD85- AVERAGE(AD$41:AD85))/_xlfn.STDEV.S(AD$41:AD85) -> 0.7370018 | AQ85: =(AE85- AVERAGE(AE$41:AE85))/_xlfn.STDEV.S(AE$41:AE85) -> -1.1257069 | AR85: =(AF85- AVERAGE(AF$41:AF85))/_xlfn.STDEV.S(AF$41:AF85) -> -0.54349553 | AS85: =(AG85- AVERAGE(AG$41:AG85))/_xlfn.STDEV.S(AG$41:AG85) -> 1.5784947 | ... AU85: =(AI85- AVERAGE(AI$41:AI85))/_xlfn.STDEV.S(AI$41:AI85) -> -0.041617687 | AW85: =+IF(AL85>AL$2,AL$2,IF(AL85<AL$1,AL$1,AL85)) -> 1.1242514 | AX85: =+IF(AM85>AM$2,AM$2,IF(AM85<AM$1,AM$1,AM85)) -> 0.90118918 | AY85: =+IF(AN85>AN$2,AN$2,IF(AN85<AN$1,AN$1,AN85)) -> 0.89238465 | AZ85: =+IF(AO85>AO$2,AO$2,IF(AO85<AO$1,AO$1,AO85)) -> 0.37657886 | BA85: =+IF(AP85>AP$2,AP$2,IF(AP85<AP$1,AP$1,AP85)) -> 0.7370018 | BB85: =+IF(AQ85>AQ$2,AQ$2,IF(AQ85<AQ$1,AQ$1,AQ85)) -> -1.1257069 | BC85: =+IF(AR85>AR$2,AR$2,IF(AR85<AR$1,AR$1,AR85)) -> -0.54349553 | BD85: =+IF(AS85>AS$2,AS$2,IF(AS85<AS$1,AS$1,AS85)) -> 1.5784947 | ... BF85: =+IF(AU85>AU$2,AU$2,IF(AU85<AU$1,AU$1,AU85)) -> -0.041617687 | BH85: =+MEDIAN(AW85:BF85) -> 0.55679033 | BI85: =+ABS(BH85) -> 0.55679033 | BJ85: =IF(COUNT(BI$76:BI84)<60,"",MEDIAN(BI$76:BI84)) | BK85: =IF(BH85="","",IF(BJ85="",0,IF(BI85>=BJ85,BH85,0))) -> 0 | BL85: =IF(BK85="","",MEDIAN(-1,BK85,1)) -> 0 | BO85: =+_xlfn.XLOOKUP(B85,Indice!B:B,Indice!AI:AI,"NOOOOOO",-1) -> 0.6744494 | BP85: =IF(BO85="","",LN(BO85)) -> -0.39385862 | BQ85: =+BP85-BP84 -> -0.12638726
A86: =+YEAR(B86) -> 2010 | B86: 40512 | C86: 5915 | D86: =+(C86/C74-1)*100 -> 21.408046 | E86: 5576 | F86: 434.56 | G86: =+(SUM(C75:C86)+SUM(E75:E86))/(F86*1000) -> 0.28187132 | H86: 9.8 | I86: 8 | J86: 27.721263 | K86: 608.272 | L86: =(K86/K74-1)*100 -> -1.4329582 | M86: 124.236 | N86: =(M86/M74-1)*100 -> -16.946218 | O86: 338658 | P86: =(O86/O74-1)*100 -> 5.2281936 | Q86: =+'crack spread y Brent_WTI'!D290*100 -> 25.269026 | R86: 9.5 | S86: =+AVERAGE(R27:R86) -> 5.06 | T86: 4.18 | U86: =(T86/T74-1)*100 -> -13.778878 | V86: 85.92 | W86: =(V86/V74-1)*100 -> 9.4940742 | X86: #N/A N/A | Z86: =+AVERAGE(D84:D86)-$S86 -> 23.205604 | AA86: =+AVERAGE(H84:H86)-$S86 -> 3.0733333 | AB86: =+AVERAGE(I84:I86)-$S86 -> 3.24 | AC86: -0.28612843 | AD86: =AVERAGE(L84:L86) -> -2.7855714 | AE86: =+AVERAGE(N84:N86)*AVERAGE($G$15:G86) -> -4.8849413 | AF86: =-AVERAGE(P84:P86) -> -6.5997272 | AG86: =AVERAGE(Q84:Q86) -> 55.86653 | AH86: =AVERAGE(U84:U86) -> -17.918587 | AI86: =AVERAGE(W84:W86) -> 13.078281 | AL86: =(Z86- AVERAGE(Z$41:Z86))/_xlfn.STDEV.S(Z$41:Z86) -> 0.7499404 | AM86: =(AA86- AVERAGE(AA$41:AA86))/_xlfn.STDEV.S(AA$41:AA86) -> 0.83737533 | AN86: =(AB86- AVERAGE(AB$41:AB86))/_xlfn.STDEV.S(AB$41:AB86) -> 0.69715422 | AO86: =(AC86- AVERAGE(AC$41:AC86))/_xlfn.STDEV.S(AC$41:AC86) -> 0.51828601 | AP86: =(AD86- AVERAGE(AD$41:AD86))/_xlfn.STDEV.S(AD$41:AD86) -> -0.34573191 | AQ86: =(AE86- AVERAGE(AE$41:AE86))/_xlfn.STDEV.S(AE$41:AE86) -> -1.1585731 | AR86: =(AF86- AVERAGE(AF$41:AF86))/_xlfn.STDEV.S(AF$41:AF86) -> -0.54935508 | AS86: =(AG86- AVERAGE(AG$41:AG86))/_xlfn.STDEV.S(AG$41:AG86) -> 1.454908 | ... AU86: =(AI86- AVERAGE(AI$41:AI86))/_xlfn.STDEV.S(AI$41:AI86) -> -0.023131139 | AW86: =+IF(AL86>AL$2,AL$2,IF(AL86<AL$1,AL$1,AL86)) -> 0.7499404 | AX86: =+IF(AM86>AM$2,AM$2,IF(AM86<AM$1,AM$1,AM86)) -> 0.83737533 | AY86: =+IF(AN86>AN$2,AN$2,IF(AN86<AN$1,AN$1,AN86)) -> 0.69715422 | AZ86: =+IF(AO86>AO$2,AO$2,IF(AO86<AO$1,AO$1,AO86)) -> 0.51828601 | BA86: =+IF(AP86>AP$2,AP$2,IF(AP86<AP$1,AP$1,AP86)) -> -0.34573191 | BB86: =+IF(AQ86>AQ$2,AQ$2,IF(AQ86<AQ$1,AQ$1,AQ86)) -> -1.1585731 | BC86: =+IF(AR86>AR$2,AR$2,IF(AR86<AR$1,AR$1,AR86)) -> -0.54935508 | BD86: =+IF(AS86>AS$2,AS$2,IF(AS86<AS$1,AS$1,AS86)) -> 1.454908 | ... BF86: =+IF(AU86>AU$2,AU$2,IF(AU86<AU$1,AU$1,AU86)) -> -0.023131139 | BH86: =+MEDIAN(AW86:BF86) -> 0.24757743 | BI86: =+ABS(BH86) -> 0.24757743 | BJ86: =IF(COUNT(BI$76:BI85)<60,"",MEDIAN(BI$76:BI85)) | BK86: =IF(BH86="","",IF(BJ86="",0,IF(BI86>=BJ86,BH86,0))) -> 0 | BL86: =IF(BK86="","",MEDIAN(-1,BK86,1)) -> 0 | BO86: =+_xlfn.XLOOKUP(B86,Indice!B:B,Indice!AI:AI,"NOOOOOO",-1) -> 0.68453884 | BP86: =IF(BO86="","",LN(BO86)) -> -0.3790099 | BQ86: =+BP86-BP85 -> 0.014848728
A87: =+YEAR(B87) -> 2010 | B87: 40543 | C87: 5484 | D87: =+(C87/C75-1)*100 -> 14.392991 | E87: 5389 | F87: 461.07 | G87: =+(SUM(C76:C87)+SUM(E76:E87))/(F87*1000) -> 0.27103694 | H87: 9.7 | I87: 6.5 | J87: 25.70633 | K87: 520.601 | L87: =(K87/K75-1)*100 -> -15.564433 | M87: 125.461 | N87: =(M87/M75-1)*100 -> -12.640741 | O87: 313918 | P87: =(O87/O75-1)*100 -> 1.9316879 | Q87: =+'crack spread y Brent_WTI'!D291*100 -> 58.423773 | R87: 8.6 | S87: =+AVERAGE(R28:R87) -> 5.0733333 | T87: 4.405 | U87: =(T87/T75-1)*100 -> -20.944006 | V87: 94.75 | W87: =(V87/V75-1)*100 -> 21.583472 | X87: #N/A N/A | Z87: =+AVERAGE(D85:D87)-$S87 -> 14.424128 | AA87: =+AVERAGE(H85:H87)-$S87 -> 3.5266667 | AB87: =+AVERAGE(I85:I87)-$S87 -> 2.3266667 | AC87: -0.066118415 | AD87: =AVERAGE(L85:L87) -> -7.2543182 | AE87: =+AVERAGE(N85:N87)*AVERAGE($G$15:G87) -> -4.721763 | AF87: =-AVERAGE(P85:P87) -> -5.4882682 | AG87: =AVERAGE(Q85:Q87) -> 37.001265 | AH87: =AVERAGE(U85:U87) -> -18.227747 | AI87: =AVERAGE(W85:W87) -> 13.883118 | AL87: =(Z87- AVERAGE(Z$41:Z87))/_xlfn.STDEV.S(Z$41:Z87) -> 0.36869557 | AM87: =(AA87- AVERAGE(AA$41:AA87))/_xlfn.STDEV.S(AA$41:AA87) -> 0.88399623 | AN87: =(AB87- AVERAGE(AB$41:AB87))/_xlfn.STDEV.S(AB$41:AB87) -> 0.5169943 | AO87: =(AC87- AVERAGE(AC$41:AC87))/_xlfn.STDEV.S(AC$41:AC87) -> 0.54625523 | AP87: =(AD87- AVERAGE(AD$41:AD87))/_xlfn.STDEV.S(AD$41:AD87) -> -1.3547064 | AQ87: =(AE87- AVERAGE(AE$41:AE87))/_xlfn.STDEV.S(AE$41:AE87) -> -1.0736545 | AR87: =(AF87- AVERAGE(AF$41:AF87))/_xlfn.STDEV.S(AF$41:AF87) -> -0.42469151 | AS87: =(AG87- AVERAGE(AG$41:AG87))/_xlfn.STDEV.S(AG$41:AG87) -> 0.86006463 | ... AU87: =(AI87- AVERAGE(AI$41:AI87))/_xlfn.STDEV.S(AI$41:AI87) -> -0.0039750132 | AW87: =+IF(AL87>AL$2,AL$2,IF(AL87<AL$1,AL$1,AL87)) -> 0.36869557 | AX87: =+IF(AM87>AM$2,AM$2,IF(AM87<AM$1,AM$1,AM87)) -> 0.88399623 | AY87: =+IF(AN87>AN$2,AN$2,IF(AN87<AN$1,AN$1,AN87)) -> 0.5169943 | AZ87: =+IF(AO87>AO$2,AO$2,IF(AO87<AO$1,AO$1,AO87)) -> 0.54625523 | BA87: =+IF(AP87>AP$2,AP$2,IF(AP87<AP$1,AP$1,AP87)) -> -1.3547064 | BB87: =+IF(AQ87>AQ$2,AQ$2,IF(AQ87<AQ$1,AQ$1,AQ87)) -> -1.0736545 | BC87: =+IF(AR87>AR$2,AR$2,IF(AR87<AR$1,AR$1,AR87)) -> -0.42469151 | BD87: =+IF(AS87>AS$2,AS$2,IF(AS87<AS$1,AS$1,AS87)) -> 0.86006463 | ... BF87: =+IF(AU87>AU$2,AU$2,IF(AU87<AU$1,AU$1,AU87)) -> -0.0039750132 | BH87: =+MEDIAN(AW87:BF87) -> 0.18236028 | BI87: =+ABS(BH87) -> 0.18236028 | BJ87: =IF(COUNT(BI$76:BI86)<60,"",MEDIAN(BI$76:BI86)) | BK87: =IF(BH87="","",IF(BJ87="",0,IF(BI87>=BJ87,BH87,0))) -> 0 | BL87: =IF(BK87="","",MEDIAN(-1,BK87,1)) -> 0 | BM87: =+AVERAGE(BL76:BL87) -> 0 | BO87: =+_xlfn.XLOOKUP(B87,Indice!B:B,Indice!AI:AI,"NOOOOOO",-1) -> 0.7706617 | BP87: =IF(BO87="","",LN(BO87)) -> -0.26050579 | BQ87: =+BP87-BP86 -> 0.11850411
A88: =+YEAR(B88) -> 2011 | B88: 40574 | C88: 5185 | D88: =+(C88/C76-1)*100 -> 17.627042 | E88: 4889 | F88: 461.07 | G88: =+(SUM(C77:C88)+SUM(E77:E88))/(F88*1000) -> 0.27636584 | H88: 9.5 | I88: 8.4 | J88: 24.214883 | K88: 600.395 | L88: =(K88/K76-1)*100 -> -4.0200338 | M88: 125.875 | N88: =(M88/M76-1)*100 -> -8.3632419 | O88: 321573 | P88: =(O88/O76-1)*100 -> 4.310974 | Q88: =+'crack spread y Brent_WTI'!D292*100 -> 116.64658 | R88: 8.6 | S88: =+AVERAGE(R29:R88) -> 5.0866667 | T88: 4.42 | U88: =(T88/T76-1)*100 -> -13.856948 | V88: 101.01 | W88: =(V88/V76-1)*100 -> 41.351805 | X88: #N/A N/A | Z88: =+AVERAGE(D86:D88)-$S88 -> 12.722693 | AA88: =+AVERAGE(H86:H88)-$S88 -> 4.58 | AB88: =+AVERAGE(I86:I88)-$S88 -> 2.5466667 | AC88: -0.96839458 | AD88: =AVERAGE(L86:L88) -> -7.0058082 | AE88: =+AVERAGE(N86:N88)*AVERAGE($G$15:G88) -> -4.0243207 | AF88: =-AVERAGE(P86:P88) -> -3.8236185 | AG88: =AVERAGE(Q86:Q88) -> 66.779792 | AH88: =AVERAGE(U86:U88) -> -16.193277 | AI88: =AVERAGE(W86:W88) -> 24.143117 | AL88: =(Z88- AVERAGE(Z$41:Z88))/_xlfn.STDEV.S(Z$41:Z88) -> 0.2917046 | AM88: =(AA88- AVERAGE(AA$41:AA88))/_xlfn.STDEV.S(AA$41:AA88) -> 1.0106338 | AN88: =(AB88- AVERAGE(AB$41:AB88))/_xlfn.STDEV.S(AB$41:AB88) -> 0.55147423 | AO88: =(AC88- AVERAGE(AC$41:AC88))/_xlfn.STDEV.S(AC$41:AC88) -> 0.39444527 | AP88: =(AD88- AVERAGE(AD$41:AD88))/_xlfn.STDEV.S(AD$41:AD88) -> -1.2611101 | AQ88: =(AE88- AVERAGE(AE$41:AE88))/_xlfn.STDEV.S(AE$41:AE88) -> -0.80609688 | AR88: =(AF88- AVERAGE(AF$41:AF88))/_xlfn.STDEV.S(AF$41:AF88) -> -0.24172676 | AS88: =(AG88- AVERAGE(AG$41:AG88))/_xlfn.STDEV.S(AG$41:AG88) -> 1.7013589 | ... AU88: =(AI88- AVERAGE(AI$41:AI88))/_xlfn.STDEV.S(AI$41:AI88) -> 0.23974862 | AW88: =+IF(AL88>AL$2,AL$2,IF(AL88<AL$1,AL$1,AL88)) -> 0.2917046 | AX88: =+IF(AM88>AM$2,AM$2,IF(AM88<AM$1,AM$1,AM88)) -> 1.0106338 | AY88: =+IF(AN88>AN$2,AN$2,IF(AN88<AN$1,AN$1,AN88)) -> 0.55147423 | AZ88: =+IF(AO88>AO$2,AO$2,IF(AO88<AO$1,AO$1,AO88)) -> 0.39444527 | BA88: =+IF(AP88>AP$2,AP$2,IF(AP88<AP$1,AP$1,AP88)) -> -1.2611101 | BB88: =+IF(AQ88>AQ$2,AQ$2,IF(AQ88<AQ$1,AQ$1,AQ88)) -> -0.80609688 | BC88: =+IF(AR88>AR$2,AR$2,IF(AR88<AR$1,AR$1,AR88)) -> -0.24172676 | BD88: =+IF(AS88>AS$2,AS$2,IF(AS88<AS$1,AS$1,AS88)) -> 1.7013589 | ... BF88: =+IF(AU88>AU$2,AU$2,IF(AU88<AU$1,AU$1,AU88)) -> 0.23974862 | BH88: =+MEDIAN(AW88:BF88) -> 0.26572661 | BI88: =+ABS(BH88) -> 0.26572661 | BJ88: =IF(COUNT(BI$76:BI87)<60,"",MEDIAN(BI$76:BI87)) | BK88: =IF(BH88="","",IF(BJ88="",0,IF(BI88>=BJ88,BH88,0))) -> 0 | BL88: =IF(BK88="","",MEDIAN(-1,BK88,1)) -> 0 | BM88: =+AVERAGE(BL77:BL88) -> 0 | BO88: =+_xlfn.XLOOKUP(B88,Indice!B:B,Indice!AI:AI,"NOOOOOO",-1) -> 0.75913897 | BP88: =IF(BO88="","",LN(BO88)) -> -0.27557042 | BQ88: =+BP88-BP87 -> -0.015064638
A89: =+YEAR(B89) -> 2011 | B89: 40602 | C89: 5398 | D89: =+(C89/C77-1)*100 -> 36.347563 | E89: 4764 | F89: 461.07 | G89: =+(SUM(C78:C89)+SUM(E78:E89))/(F89*1000) -> 0.28232589 | H89: 8.1 | I89: 7.5 | J89: 19.956253 | K89: 604.323 | L89: =(K89/K77-1)*100 -> -3.5629139 | M89: 127.089 | N89: =(M89/M77-1)*100 -> -5.8425634 | O89: 324722 | P89: =(O89/O77-1)*100 -> 1.2446606 | Q89: =+'crack spread y Brent_WTI'!D293*100 -> 149.33135 | R89: 8.6 | S89: =+AVERAGE(R30:R89) -> 5.1 | T89: 4.037 | U89: =(T89/T77-1)*100 -> -16.123 | V89: 111.8 | W89: =(V89/V77-1)*100 -> 44.090733 | X89: #N/A N/A | Z89: =+AVERAGE(D87:D89)-$S89 -> 17.689198 | AA89: =+AVERAGE(H87:H89)-$S89 -> 4 | AB89: =+AVERAGE(I87:I89)-$S89 -> 2.3666667 | AC89: -3.6738734 | AD89: =AVERAGE(L87:L89) -> -7.7157935 | AE89: =+AVERAGE(N87:N89)*AVERAGE($G$15:G89) -> -2.8425937 | AF89: =-AVERAGE(P87:P89) -> -2.4957742 | AG89: =AVERAGE(Q87:Q89) -> 108.1339 | AH89: =AVERAGE(U87:U89) -> -16.974651 | AI89: =AVERAGE(W87:W89) -> 35.675337 | AL89: =(Z89- AVERAGE(Z$41:Z89))/_xlfn.STDEV.S(Z$41:Z89) -> 0.50248876 | AM89: =(AA89- AVERAGE(AA$41:AA89))/_xlfn.STDEV.S(AA$41:AA89) -> 0.91135027 | AN89: =(AB89- AVERAGE(AB$41:AB89))/_xlfn.STDEV.S(AB$41:AB89) -> 0.51021314 | AO89: =(AC89- AVERAGE(AC$41:AC89))/_xlfn.STDEV.S(AC$41:AC89) -> -0.049991237 | AP89: =(AD89- AVERAGE(AD$41:AD89))/_xlfn.STDEV.S(AD$41:AD89) -> -1.382221 | AQ89: =(AE89- AVERAGE(AE$41:AE89))/_xlfn.STDEV.S(AE$41:AE89) -> -0.37086432 | AR89: =(AF89- AVERAGE(AF$41:AF89))/_xlfn.STDEV.S(AF$41:AF89) -> -0.095460811 | AS89: =(AG89- AVERAGE(AG$41:AG89))/_xlfn.STDEV.S(AG$41:AG89) -> 2.6834797 | ... AU89: =(AI89- AVERAGE(AI$41:AI89))/_xlfn.STDEV.S(AI$41:AI89) -> 0.512816 | AW89: =+IF(AL89>AL$2,AL$2,IF(AL89<AL$1,AL$1,AL89)) -> 0.50248876 | AX89: =+IF(AM89>AM$2,AM$2,IF(AM89<AM$1,AM$1,AM89)) -> 0.91135027 | AY89: =+IF(AN89>AN$2,AN$2,IF(AN89<AN$1,AN$1,AN89)) -> 0.51021314 | AZ89: =+IF(AO89>AO$2,AO$2,IF(AO89<AO$1,AO$1,AO89)) -> -0.049991237 | BA89: =+IF(AP89>AP$2,AP$2,IF(AP89<AP$1,AP$1,AP89)) -> -1.382221 | BB89: =+IF(AQ89>AQ$2,AQ$2,IF(AQ89<AQ$1,AQ$1,AQ89)) -> -0.37086432 | BC89: =+IF(AR89>AR$2,AR$2,IF(AR89<AR$1,AR$1,AR89)) -> -0.095460811 | BD89: =+IF(AS89>AS$2,AS$2,IF(AS89<AS$1,AS$1,AS89)) -> 2.6834797 | ... BF89: =+IF(AU89>AU$2,AU$2,IF(AU89<AU$1,AU$1,AU89)) -> 0.512816 | BH89: =+MEDIAN(AW89:BF89) -> 0.22624876 | BI89: =+ABS(BH89) -> 0.22624876 | BJ89: =IF(COUNT(BI$76:BI88)<60,"",MEDIAN(BI$76:BI88)) | BK89: =IF(BH89="","",IF(BJ89="",0,IF(BI89>=BJ89,BH89,0))) -> 0 | BL89: =IF(BK89="","",MEDIAN(-1,BK89,1)) -> 0 | BM89: =+AVERAGE(BL78:BL89) -> 0 | BO89: =+_xlfn.XLOOKUP(B89,Indice!B:B,Indice!AI:AI,"NOOOOOO",-1) -> 0.83858808 | BP89: =IF(BO89="","",LN(BO89)) -> -0.17603565 | BQ89: =+BP89-BP88 -> 0.09953477
A90: =+YEAR(B90) -> 2011 | B90: 40633 | C90: 6098 | D90: =+(C90/C78-1)*100 -> 30.104544 | E90: 5642 | F90: 470.77 | G90: =+(SUM(C79:C90)+SUM(E79:E90))/(F90*1000) -> 0.28213777 | H90: 7.4 | I90: 7.3 | J90: 20.010586 | K90: 599.16 | L90: =(K90/K78-1)*100 -> -4.4443062 | M90: 127.141 | N90: =(M90/M78-1)*100 -> -4.3793809 | O90: 333920 | P90: =(O90/O78-1)*100 -> 0.16017469 | Q90: =+'crack spread y Brent_WTI'!D294*100 -> 110.35425 | R90: 8.3 | S90: =+AVERAGE(R31:R90) -> 5.1083333 | T90: 4.389 | U90: =(T90/T78-1)*100 -> 13.440165 | V90: 117.36 | W90: =(V90/V78-1)*100 -> 41.91052 | X90: #N/A N/A | Z90: =+AVERAGE(D88:D90)-$S90 -> 22.91805 | AA90: =+AVERAGE(H88:H90)-$S90 -> 3.225 | AB90: =+AVERAGE(I88:I90)-$S90 -> 2.625 | AC90: -5.6761859 | AD90: =AVERAGE(L88:L90) -> -4.0090847 | AE90: =+AVERAGE(N88:N90)*AVERAGE($G$15:G90) -> -1.9649612 | AF90: =-AVERAGE(P88:P90) -> -1.9052698 | AG90: =AVERAGE(Q88:Q90) -> 125.44406 | AH90: =AVERAGE(U88:U90) -> -5.5132609 | AI90: =AVERAGE(W88:W90) -> 42.451019 | AL90: =(Z90- AVERAGE(Z$41:Z90))/_xlfn.STDEV.S(Z$41:Z90) -> 0.72184859 | AM90: =(AA90- AVERAGE(AA$41:AA90))/_xlfn.STDEV.S(AA$41:AA90) -> 0.78881819 | AN90: =(AB90- AVERAGE(AB$41:AB90))/_xlfn.STDEV.S(AB$41:AB90) -> 0.55304778 | AO90: =(AC90- AVERAGE(AC$41:AC90))/_xlfn.STDEV.S(AC$41:AC90) -> -0.37843521 | AP90: =(AD90- AVERAGE(AD$41:AD90))/_xlfn.STDEV.S(AD$41:AD90) -> -0.52591245 | AQ90: =(AE90- AVERAGE(AE$41:AE90))/_xlfn.STDEV.S(AE$41:AE90) -> -0.047445937 | AR90: =(AF90- AVERAGE(AF$41:AF90))/_xlfn.STDEV.S(AF$41:AF90) -> -0.029875086 | AS90: =(AG90- AVERAGE(AG$41:AG90))/_xlfn.STDEV.S(AG$41:AG90) -> 2.8575525 | ... AU90: =(AI90- AVERAGE(AI$41:AI90))/_xlfn.STDEV.S(AI$41:AI90) -> 0.66862703 | AW90: =+IF(AL90>AL$2,AL$2,IF(AL90<AL$1,AL$1,AL90)) -> 0.72184859 | AX90: =+IF(AM90>AM$2,AM$2,IF(AM90<AM$1,AM$1,AM90)) -> 0.78881819 | AY90: =+IF(AN90>AN$2,AN$2,IF(AN90<AN$1,AN$1,AN90)) -> 0.55304778 | AZ90: =+IF(AO90>AO$2,AO$2,IF(AO90<AO$1,AO$1,AO90)) -> -0.37843521 | BA90: =+IF(AP90>AP$2,AP$2,IF(AP90<AP$1,AP$1,AP90)) -> -0.52591245 | BB90: =+IF(AQ90>AQ$2,AQ$2,IF(AQ90<AQ$1,AQ$1,AQ90)) -> -0.047445937 | BC90: =+IF(AR90>AR$2,AR$2,IF(AR90<AR$1,AR$1,AR90)) -> -0.029875086 | BD90: =+IF(AS90>AS$2,AS$2,IF(AS90<AS$1,AS$1,AS90)) -> 2.6971619 | ... BF90: =+IF(AU90>AU$2,AU$2,IF(AU90<AU$1,AU$1,AU90)) -> 0.66862703 | BH90: =+MEDIAN(AW90:BF90) -> 0.26158635 | BI90: =+ABS(BH90) -> 0.26158635 | BJ90: =IF(COUNT(BI$76:BI89)<60,"",MEDIAN(BI$76:BI89)) | BK90: =IF(BH90="","",IF(BJ90="",0,IF(BI90>=BJ90,BH90,0))) -> 0 | BL90: =IF(BK90="","",MEDIAN(-1,BK90,1)) -> 0 | BM90: =+AVERAGE(BL79:BL90) -> 0 | BO90: =+_xlfn.XLOOKUP(B90,Indice!B:B,Indice!AI:AI,"NOOOOOO",-1) -> 0.71331935 | BP90: =IF(BO90="","",LN(BO90)) -> -0.33782606 | BQ90: =+BP90-BP89 -> -0.1617904
A91: =+YEAR(B91) -> 2011 | B91: 40663 | C91: 7043 | D91: =+(C91/C79-1)*100 -> 13.450387 | E91: 5533 | F91: 470.77 | G91: =+(SUM(C80:C91)+SUM(E80:E91))/(F91*1000) -> 0.28695329 | H91: 3.6 | I91: 5.2 | J91: 21.597521 | K91: 504.641 | L91: =(K91/K79-1)*100 -> -19.462842 | M91: 129.135 | N91: =(M91/M79-1)*100 -> -2.7949235 | O91: 344418 | P91: =(O91/O79-1)*100 -> 1.3166952 | Q91: =+'crack spread y Brent_WTI'!D295*100 -> 101.33799 | R91: 8.3 | S91: =+AVERAGE(R32:R91) -> 5.1166667 | T91: 4.698 | U91: =(T91/T79-1)*100 -> 19.846939 | V91: 125.89 | W91: =(V91/V79-1)*100 -> 43.97301 | X91: #N/A N/A | Z91: =+AVERAGE(D89:D91)-$S91 -> 21.517498 | AA91: =+AVERAGE(H89:H91)-$S91 -> 1.25 | AB91: =+AVERAGE(I89:I91)-$S91 -> 1.55 | AC91: -6.6048694 | AD91: =AVERAGE(L89:L91) -> -9.1566874 | AE91: =+AVERAGE(N89:N91)*AVERAGE($G$15:G91) -> -1.3745347 | AF91: =-AVERAGE(P89:P91) -> -0.90717684 | AG91: =AVERAGE(Q89:Q91) -> 120.3412 | AH91: =AVERAGE(U89:U91) -> 5.721368 | AI91: =AVERAGE(W89:W91) -> 43.324754 | AL91: =(Z91- AVERAGE(Z$41:Z91))/_xlfn.STDEV.S(Z$41:Z91) -> 0.65060469 | AM91: =(AA91- AVERAGE(AA$41:AA91))/_xlfn.STDEV.S(AA$41:AA91) -> 0.50255715 | AN91: =(AB91- AVERAGE(AB$41:AB91))/_xlfn.STDEV.S(AB$41:AB91) -> 0.33928221 | AO91: =(AC91- AVERAGE(AC$41:AC91))/_xlfn.STDEV.S(AC$41:AC91) -> -0.52748578 | AP91: =(AD91- AVERAGE(AD$41:AD91))/_xlfn.STDEV.S(AD$41:AD91) -> -1.6501014 | AQ91: =(AE91- AVERAGE(AE$41:AE91))/_xlfn.STDEV.S(AE$41:AE91) -> 0.17035015 | AR91: =(AF91- AVERAGE(AF$41:AF91))/_xlfn.STDEV.S(AF$41:AF91) -> 0.080827048 | AS91: =(AG91- AVERAGE(AG$41:AG91))/_xlfn.STDEV.S(AG$41:AG91) -> 2.5190115 | ... AU91: =(AI91- AVERAGE(AI$41:AI91))/_xlfn.STDEV.S(AI$41:AI91) -> 0.68020956 | AW91: =+IF(AL91>AL$2,AL$2,IF(AL91<AL$1,AL$1,AL91)) -> 0.65060469 | AX91: =+IF(AM91>AM$2,AM$2,IF(AM91<AM$1,AM$1,AM91)) -> 0.50255715 | AY91: =+IF(AN91>AN$2,AN$2,IF(AN91<AN$1,AN$1,AN91)) -> 0.33928221 | AZ91: =+IF(AO91>AO$2,AO$2,IF(AO91<AO$1,AO$1,AO91)) -> -0.52748578 | BA91: =+IF(AP91>AP$2,AP$2,IF(AP91<AP$1,AP$1,AP91)) -> -1.6501014 | BB91: =+IF(AQ91>AQ$2,AQ$2,IF(AQ91<AQ$1,AQ$1,AQ91)) -> 0.17035015 | BC91: =+IF(AR91>AR$2,AR$2,IF(AR91<AR$1,AR$1,AR91)) -> 0.080827048 | BD91: =+IF(AS91>AS$2,AS$2,IF(AS91<AS$1,AS$1,AS91)) -> 2.5190115 | ... BF91: =+IF(AU91>AU$2,AU$2,IF(AU91<AU$1,AU$1,AU91)) -> 0.68020956 | BH91: =+MEDIAN(AW91:BF91) -> 0.31259585 | BI91: =+ABS(BH91) -> 0.31259585 | BJ91: =IF(COUNT(BI$76:BI90)<60,"",MEDIAN(BI$76:BI90)) | BK91: =IF(BH91="","",IF(BJ91="",0,IF(BI91>=BJ91,BH91,0))) -> 0 | BL91: =IF(BK91="","",MEDIAN(-1,BK91,1)) -> 0 | BM91: =+AVERAGE(BL80:BL91) -> 0 | BO91: =+_xlfn.XLOOKUP(B91,Indice!B:B,Indice!AI:AI,"NOOOOOO",-1) -> 0.75636413 | BP91: =IF(BO91="","",LN(BO91)) -> -0.27923236 | BQ91: =+BP91-BP90 -> 0.058593698
A92: =+YEAR(B92) -> 2011 | B92: 40694 | C92: 7933 | D92: =+(C92/C80-1)*100 -> 21.989851 | E92: 6490 | F92: 470.77 | G92: =+(SUM(C81:C92)+SUM(E81:E92))/(F92*1000) -> 0.29405867 | H92: 5.1 | I92: 4.3 | J92: 21.804435 | K92: 528.395 | L92: =(K92/K80-1)*100 -> -15.483845 | M92: 126.298 | N92: =(M92/M80-1)*100 -> -0.82139716 | O92: 351529 | P92: =(O92/O80-1)*100 -> 2.611937 | Q92: =+'crack spread y Brent_WTI'!D296*100 -> 134.82192 | R92: 8.3 | S92: =+AVERAGE(R33:R92) -> 5.125 | T92: 4.666 | U92: =(T92/T80-1)*100 -> 7.4867542 | V92: 116.73 | W92: =(V92/V80-1)*100 -> 56.369725 | X92: #N/A N/A | Z92: =+AVERAGE(D90:D92)-$S92 -> 16.723261 | AA92: =+AVERAGE(H90:H92)-$S92 -> 0.24166667 | AB92: =+AVERAGE(I90:I92)-$S92 -> 0.475 | AC92: -6.0296303 | AD92: =AVERAGE(L90:L92) -> -13.130331 | AE92: =+AVERAGE(N90:N92)*AVERAGE($G$15:G92) -> -0.84354078 | AF92: =-AVERAGE(P90:P92) -> -1.3629356 | AG92: =AVERAGE(Q90:Q92) -> 115.50472 | AH92: =AVERAGE(U90:U92) -> 13.591286 | AI92: =AVERAGE(W90:W92) -> 47.417752 | AL92: =(Z92- AVERAGE(Z$41:Z92))/_xlfn.STDEV.S(Z$41:Z92) -> 0.43203726 | AM92: =(AA92- AVERAGE(AA$41:AA92))/_xlfn.STDEV.S(AA$41:AA92) -> 0.3546569 | AN92: =(AB92- AVERAGE(AB$41:AB92))/_xlfn.STDEV.S(AB$41:AB92) -> 0.12611757 | AO92: =(AC92- AVERAGE(AC$41:AC92))/_xlfn.STDEV.S(AC$41:AC92) -> -0.42548602 | AP92: =(AD92- AVERAGE(AD$41:AD92))/_xlfn.STDEV.S(AD$41:AD92) -> -2.3793724 | AQ92: =(AE92- AVERAGE(AE$41:AE92))/_xlfn.STDEV.S(AE$41:AE92) -> 0.36571559 | AR92: =(AF92- AVERAGE(AF$41:AF92))/_xlfn.STDEV.S(AF$41:AF92) -> 0.029122706 | AS92: =(AG92- AVERAGE(AG$41:AG92))/_xlfn.STDEV.S(AG$41:AG92) -> 2.2547302 | ... AU92: =(AI92- AVERAGE(AI$41:AI92))/_xlfn.STDEV.S(AI$41:AI92) -> 0.76937024 | AW92: =+IF(AL92>AL$2,AL$2,IF(AL92<AL$1,AL$1,AL92)) -> 0.43203726 | AX92: =+IF(AM92>AM$2,AM$2,IF(AM92<AM$1,AM$1,AM92)) -> 0.3546569 | AY92: =+IF(AN92>AN$2,AN$2,IF(AN92<AN$1,AN$1,AN92)) -> 0.12611757 | AZ92: =+IF(AO92>AO$2,AO$2,IF(AO92<AO$1,AO$1,AO92)) -> -0.42548602 | BA92: =+IF(AP92>AP$2,AP$2,IF(AP92<AP$1,AP$1,AP92)) -> -2.3793724 | BB92: =+IF(AQ92>AQ$2,AQ$2,IF(AQ92<AQ$1,AQ$1,AQ92)) -> 0.36571559 | BC92: =+IF(AR92>AR$2,AR$2,IF(AR92<AR$1,AR$1,AR92)) -> 0.029122706 | BD92: =+IF(AS92>AS$2,AS$2,IF(AS92<AS$1,AS$1,AS92)) -> 2.2547302 | ... BF92: =+IF(AU92>AU$2,AU$2,IF(AU92<AU$1,AU$1,AU92)) -> 0.76937024 | BH92: =+MEDIAN(AW92:BF92) -> 0.36018625 | BI92: =+ABS(BH92) -> 0.36018625 | BJ92: =IF(COUNT(BI$76:BI91)<60,"",MEDIAN(BI$76:BI91)) | BK92: =IF(BH92="","",IF(BJ92="",0,IF(BI92>=BJ92,BH92,0))) -> 0 | BL92: =IF(BK92="","",MEDIAN(-1,BK92,1)) -> 0 | BM92: =+AVERAGE(BL81:BL92) -> 0 | BO92: =+_xlfn.XLOOKUP(B92,Indice!B:B,Indice!AI:AI,"NOOOOOO",-1) -> 0.859468 | BP92: =IF(BO92="","",LN(BO92)) -> -0.15144168 | BQ92: =+BP92-BP91 -> 0.12779068
A93: =+YEAR(B93) -> 2011 | B93: 40724 | C93: 7817 | D93: =+(C93/C81-1)*100 -> 22.735123 | E93: 6705 | F93: 548.13 | G93: =+(SUM(C82:C93)+SUM(E82:E93))/(F93*1000) -> 0.25803368 | H93: 4.6 | I93: 4 | J93: 22.353281 | K93: 536.417 | L93: =(K93/K81-1)*100 -> -14.542865 | M93: 126.136 | N93: =(M93/M81-1)*100 -> -0.35076631 | O93: 337405 | P93: =(O93/O81-1)*100 -> -1.5180703 | Q93: =+'crack spread y Brent_WTI'!D297*100 -> 175.34221 | R93: 4.4 | S93: =+AVERAGE(R34:R93) -> 5.105 | T93: 4.374 | U93: =(T93/T81-1)*100 -> -5.2426343 | V93: 112.48 | W93: =(V93/V81-1)*100 -> 49.95334 | X93: #N/A N/A | Z93: =+AVERAGE(D91:D93)-$S93 -> 14.286787 | AA93: =+AVERAGE(H91:H93)-$S93 -> -0.67166667 | AB93: =+AVERAGE(I91:I93)-$S93 -> -0.605 | AC93: -5.339126 | AD93: =AVERAGE(L91:L93) -> -16.496517 | AE93: =+AVERAGE(N91:N93)*AVERAGE($G$15:G93) -> -0.41754621 | AF93: =-AVERAGE(P91:P93) -> -0.80352064 | AG93: =AVERAGE(Q91:Q93) -> 137.16737 | AH93: =AVERAGE(U91:U93) -> 7.3636862 | AI93: =AVERAGE(W91:W93) -> 50.098692 | AL93: =(Z93- AVERAGE(Z$41:Z93))/_xlfn.STDEV.S(Z$41:Z93) -> 0.31927992 | AM93: =(AA93- AVERAGE(AA$41:AA93))/_xlfn.STDEV.S(AA$41:AA93) -> 0.22085984 | AN93: =(AB93- AVERAGE(AB$41:AB93))/_xlfn.STDEV.S(AB$41:AB93) -> -0.088058132 | AO93: =(AC93- AVERAGE(AC$41:AC93))/_xlfn.STDEV.S(AC$41:AC93) -> -0.30478001 | AP93: =(AD93- AVERAGE(AD$41:AD93))/_xlfn.STDEV.S(AD$41:AD93) -> -2.8253189 | AQ93: =(AE93- AVERAGE(AE$41:AE93))/_xlfn.STDEV.S(AE$41:AE93) -> 0.52073845 | AR93: =(AF93- AVERAGE(AF$41:AF93))/_xlfn.STDEV.S(AF$41:AF93) -> 0.092000997 | AS93: =(AG93- AVERAGE(AG$41:AG93))/_xlfn.STDEV.S(AG$41:AG93) -> 2.5521021 | ... AU93: =(AI93- AVERAGE(AI$41:AI93))/_xlfn.STDEV.S(AI$41:AI93) -> 0.82260903 | AW93: =+IF(AL93>AL$2,AL$2,IF(AL93<AL$1,AL$1,AL93)) -> 0.31927992 | AX93: =+IF(AM93>AM$2,AM$2,IF(AM93<AM$1,AM$1,AM93)) -> 0.22085984 | AY93: =+IF(AN93>AN$2,AN$2,IF(AN93<AN$1,AN$1,AN93)) -> -0.088058132 | AZ93: =+IF(AO93>AO$2,AO$2,IF(AO93<AO$1,AO$1,AO93)) -> -0.30478001 | BA93: =+IF(AP93>AP$2,AP$2,IF(AP93<AP$1,AP$1,AP93)) -> -2.8253189 | BB93: =+IF(AQ93>AQ$2,AQ$2,IF(AQ93<AQ$1,AQ$1,AQ93)) -> 0.52073845 | BC93: =+IF(AR93>AR$2,AR$2,IF(AR93<AR$1,AR$1,AR93)) -> 0.092000997 | BD93: =+IF(AS93>AS$2,AS$2,IF(AS93<AS$1,AS$1,AS93)) -> 2.5521021 | ... BF93: =+IF(AU93>AU$2,AU$2,IF(AU93<AU$1,AU$1,AU93)) -> 0.82260903 | BH93: =+MEDIAN(AW93:BF93) -> 0.27006988 | BI93: =+ABS(BH93) -> 0.27006988 | BJ93: =IF(COUNT(BI$76:BI92)<60,"",MEDIAN(BI$76:BI92)) | BK93: =IF(BH93="","",IF(BJ93="",0,IF(BI93>=BJ93,BH93,0))) -> 0 | BL93: =IF(BK93="","",MEDIAN(-1,BK93,1)) -> 0 | BM93: =+AVERAGE(BL82:BL93) -> 0 | BO93: =+_xlfn.XLOOKUP(B93,Indice!B:B,Indice!AI:AI,"NOOOOOO",-1) -> 0.77073527 | BP93: =IF(BO93="","",LN(BO93)) -> -0.26041032 | BQ93: =+BP93-BP92 -> -0.10896863
A94: =+YEAR(B94) -> 2011 | B94: 40755 | C94: 7226 | D94: =+(C94/C82-1)*100 -> 20.755348 | E94: 6859 | F94: 548.13 | G94: =+(SUM(C83:C94)+SUM(E83:E94))/(F94*1000) -> 0.2631602 | H94: 4.9 | I94: 4.1 | J94: 22.714093 | K94: 562.13 | L94: =(K94/K82-1)*100 -> -10.023497 | M94: 126.039 | N94: =(M94/M82-1)*100 -> -1.9769639 | O94: 332927 | P94: =(O94/O82-1)*100 -> -1.3222166 | Q94: =+'crack spread y Brent_WTI'!D298*100 -> 243.04397 | R94: 4.4 | S94: =+AVERAGE(R35:R94) -> 5.085 | T94: 4.145 | U94: =(T94/T82-1)*100 -> -15.803372 | V94: 116.74 | W94: =(V94/V82-1)*100 -> 49.322077 | X94: #N/A N/A | Z94: =+AVERAGE(D92:D94)-$S94 -> 16.741774 | AA94: =+AVERAGE(H92:H94)-$S94 -> -0.21833333 | AB94: =+AVERAGE(I92:I94)-$S94 -> -0.95166667 | AC94: -4.9859156 | AD94: =AVERAGE(L92:L94) -> -13.350069 | AE94: =+AVERAGE(N92:N94)*AVERAGE($G$15:G94) -> -0.33076369 | AF94: =-AVERAGE(P92:P94) -> 0.076116616 | AG94: =AVERAGE(Q92:Q94) -> 184.4027 | AH94: =AVERAGE(U92:U94) -> -4.5197507 | AI94: =AVERAGE(W92:W94) -> 51.881714 | AL94: =(Z94- AVERAGE(Z$41:Z94))/_xlfn.STDEV.S(Z$41:Z94) -> 0.42584199 | AM94: =(AA94- AVERAGE(AA$41:AA94))/_xlfn.STDEV.S(AA$41:AA94) -> 0.28395671 | AN94: =(AB94- AVERAGE(AB$41:AB94))/_xlfn.STDEV.S(AB$41:AB94) -> -0.15626505 | AO94: =(AC94- AVERAGE(AC$41:AC94))/_xlfn.STDEV.S(AC$41:AC94) -> -0.24174699 | AP94: =(AD94- AVERAGE(AD$41:AD94))/_xlfn.STDEV.S(AD$41:AD94) -> -2.0834247 | AQ94: =(AE94- AVERAGE(AE$41:AE94))/_xlfn.STDEV.S(AE$41:AE94) -> 0.54719666 | AR94: =(AF94- AVERAGE(AF$41:AF94))/_xlfn.STDEV.S(AF$41:AF94) -> 0.19138068 | AS94: =(AG94- AVERAGE(AG$41:AG94))/_xlfn.STDEV.S(AG$41:AG94) -> 3.1883535 | ... AU94: =(AI94- AVERAGE(AI$41:AI94))/_xlfn.STDEV.S(AI$41:AI94) -> 0.85304145 | AW94: =+IF(AL94>AL$2,AL$2,IF(AL94<AL$1,AL$1,AL94)) -> 0.42584199 | AX94: =+IF(AM94>AM$2,AM$2,IF(AM94<AM$1,AM$1,AM94)) -> 0.28395671 | AY94: =+IF(AN94>AN$2,AN$2,IF(AN94<AN$1,AN$1,AN94)) -> -0.15626505 | AZ94: =+IF(AO94>AO$2,AO$2,IF(AO94<AO$1,AO$1,AO94)) -> -0.24174699 | BA94: =+IF(AP94>AP$2,AP$2,IF(AP94<AP$1,AP$1,AP94)) -> -2.0834247 | BB94: =+IF(AQ94>AQ$2,AQ$2,IF(AQ94<AQ$1,AQ$1,AQ94)) -> 0.54719666 | BC94: =+IF(AR94>AR$2,AR$2,IF(AR94<AR$1,AR$1,AR94)) -> 0.19138068 | BD94: =+IF(AS94>AS$2,AS$2,IF(AS94<AS$1,AS$1,AS94)) -> 2.6971619 | ... BF94: =+IF(AU94>AU$2,AU$2,IF(AU94<AU$1,AU$1,AU94)) -> 0.85304145 | BH94: =+MEDIAN(AW94:BF94) -> 0.23766869 | BI94: =+ABS(BH94) -> 0.23766869 | BJ94: =IF(COUNT(BI$76:BI93)<60,"",MEDIAN(BI$76:BI93)) | BK94: =IF(BH94="","",IF(BJ94="",0,IF(BI94>=BJ94,BH94,0))) -> 0 | BL94: =IF(BK94="","",MEDIAN(-1,BK94,1)) -> 0 | BM94: =+AVERAGE(BL83:BL94) -> 0 | BO94: =+_xlfn.XLOOKUP(B94,Indice!B:B,Indice!AI:AI,"NOOOOOO",-1) -> 0.76214162 | BP94: =IF(BO94="","",LN(BO94)) -> -0.27162289 | BQ94: =+BP94-BP93 -> -0.01121257
A95: =+YEAR(B95) -> 2011 | B95: 40786 | C95: 8328 | D95: =+(C95/C83-1)*100 -> 30.471565 | E95: 7671 | F95: 548.13 | G95: =+(SUM(C84:C95)+SUM(E84:E95))/(F95*1000) -> 0.2709339 | H95: 6.7 | I95: 5.4 | J95: 24.526021 | K95: 592.374 | L95: =(K95/K83-1)*100 -> -5.308791 | M95: 123.523 | N95: =(M95/M83-1)*100 -> -2.9685315 | O95: 335107 | P95: =(O95/O83-1)*100 -> -1.7584028 | Q95: =+'crack spread y Brent_WTI'!D299*100 -> 337.58776 | R95: 4.4 | S95: =+AVERAGE(R36:R95) -> 5.065 | T95: 4.054 | U95: =(T95/T83-1)*100 -> 6.2368973 | V95: 114.85 | W95: =(V95/V83-1)*100 -> 53.871919 | X95: #N/A N/A | Z95: =+AVERAGE(D93:D95)-$S95 -> 19.589012 | AA95: =+AVERAGE(H93:H95)-$S95 -> 0.335 | AB95: =+AVERAGE(I93:I95)-$S95 -> -0.565 | AC95: -4.3360669 | AD95: =AVERAGE(L93:L95) -> -9.9583844 | AE95: =+AVERAGE(N93:N95)*AVERAGE($G$15:G95) -> -0.55532198 | AF95: =-AVERAGE(P93:P95) -> 1.5328966 | AG95: =AVERAGE(Q93:Q95) -> 251.99131 | AH95: =AVERAGE(U93:U95) -> -4.9363697 | AI95: =AVERAGE(W93:W95) -> 51.049112 | AL95: =(Z95- AVERAGE(Z$41:Z95))/_xlfn.STDEV.S(Z$41:Z95) -> 0.54930563 | AM95: =(AA95- AVERAGE(AA$41:AA95))/_xlfn.STDEV.S(AA$41:AA95) -> 0.36142404 | AN95: =(AB95- AVERAGE(AB$41:AB95))/_xlfn.STDEV.S(AB$41:AB95) -> -0.077114377 | AO95: =(AC95- AVERAGE(AC$41:AC95))/_xlfn.STDEV.S(AC$41:AC95) -> -0.12794362 | AP95: =(AD95- AVERAGE(AD$41:AD95))/_xlfn.STDEV.S(AD$41:AD95) -> -1.3892167 | AQ95: =(AE95- AVERAGE(AE$41:AE95))/_xlfn.STDEV.S(AE$41:AE95) -> 0.45596339 | AR95: =(AF95- AVERAGE(AF$41:AF95))/_xlfn.STDEV.S(AF$41:AF95) -> 0.35688022 | AS95: =(AG95- AVERAGE(AG$41:AG95))/_xlfn.STDEV.S(AG$41:AG95) -> 3.8212378 | ... AU95: =(AI95- AVERAGE(AI$41:AI95))/_xlfn.STDEV.S(AI$41:AI95) -> 0.81956803 | AW95: =+IF(AL95>AL$2,AL$2,IF(AL95<AL$1,AL$1,AL95)) -> 0.54930563 | AX95: =+IF(AM95>AM$2,AM$2,IF(AM95<AM$1,AM$1,AM95)) -> 0.36142404 | AY95: =+IF(AN95>AN$2,AN$2,IF(AN95<AN$1,AN$1,AN95)) -> -0.077114377 | AZ95: =+IF(AO95>AO$2,AO$2,IF(AO95<AO$1,AO$1,AO95)) -> -0.12794362 | BA95: =+IF(AP95>AP$2,AP$2,IF(AP95<AP$1,AP$1,AP95)) -> -1.3892167 | BB95: =+IF(AQ95>AQ$2,AQ$2,IF(AQ95<AQ$1,AQ$1,AQ95)) -> 0.45596339 | BC95: =+IF(AR95>AR$2,AR$2,IF(AR95<AR$1,AR$1,AR95)) -> 0.35688022 | BD95: =+IF(AS95>AS$2,AS$2,IF(AS95<AS$1,AS$1,AS95)) -> 2.6971619 | ... BF95: =+IF(AU95>AU$2,AU$2,IF(AU95<AU$1,AU$1,AU95)) -> 0.81956803 | BH95: =+MEDIAN(AW95:BF95) -> 0.35915213 | BI95: =+ABS(BH95) -> 0.35915213 | BJ95: =IF(COUNT(BI$76:BI94)<60,"",MEDIAN(BI$76:BI94)) | BK95: =IF(BH95="","",IF(BJ95="",0,IF(BI95>=BJ95,BH95,0))) -> 0 | BL95: =IF(BK95="","",MEDIAN(-1,BK95,1)) -> 0 | BM95: =+AVERAGE(BL84:BL95) -> 0 | BO95: =+_xlfn.XLOOKUP(B95,Indice!B:B,Indice!AI:AI,"NOOOOOO",-1) -> 0.80728599 | BP95: =IF(BO95="","",LN(BO95)) -> -0.21407729 | BQ95: =+BP95-BP94 -> 0.057545598
A96: =+YEAR(B96) -> 2011 | B96: 40816 | C96: 7718 | D96: =+(C96/C84-1)*100 -> 21.066667 | E96: 6889 | F96: 540.17 | G96: =+(SUM(C85:C96)+SUM(E85:E96))/(F96*1000) -> 0.28028584 | H96: 7.7 | I96: 6 | J96: 24.967251 | K96: 596.773 | L96: =(K96/K84-1)*100 -> -3.080516 | M96: 111.065 | N96: =(M96/M84-1)*100 -> -14.792822 | O96: 314342 | P96: =(O96/O84-1)*100 -> -6.8182829 | Q96: =+'crack spread y Brent_WTI'!D300*100 -> 250.13652 | R96: 6.4 | S96: =+AVERAGE(R37:R96) -> 5.015 | T96: 3.666 | U96: =(T96/T84-1)*100 -> -5.3202479 | V96: 102.76 | W96: =(V96/V84-1)*100 -> 24.845098 | X96: #N/A N/A | Z96: =+AVERAGE(D94:D96)-$S96 -> 19.08286 | AA96: =+AVERAGE(H94:H96)-$S96 -> 1.4183333 | AB96: =+AVERAGE(I94:I96)-$S96 -> 0.15166667 | AC96: -3.7513312 | AD96: =AVERAGE(L94:L96) -> -6.1376014 | AE96: =+AVERAGE(N94:N96)*AVERAGE($G$15:G96) -> -2.0668462 | AF96: =-AVERAGE(P94:P96) -> 3.2996341 | AG96: =AVERAGE(Q94:Q96) -> 276.92275 | AH96: =AVERAGE(U94:U96) -> -4.9622409 | AI96: =AVERAGE(W94:W96) -> 42.679698 | AL96: =(Z96- AVERAGE(Z$41:Z96))/_xlfn.STDEV.S(Z$41:Z96) -> 0.52010335 | AM96: =(AA96- AVERAGE(AA$41:AA96))/_xlfn.STDEV.S(AA$41:AA96) -> 0.51579922 | AN96: =(AB96- AVERAGE(AB$41:AB96))/_xlfn.STDEV.S(AB$41:AB96) -> 0.069027425 | AO96: =(AC96- AVERAGE(AC$41:AC96))/_xlfn.STDEV.S(AC$41:AC96) -> -0.025440166 | AP96: =(AD96- AVERAGE(AD$41:AD96))/_xlfn.STDEV.S(AD$41:AD96) -> -0.64930261 | AQ96: =(AE96- AVERAGE(AE$41:AE96))/_xlfn.STDEV.S(AE$41:AE96) -> -0.12743816 | AR96: =(AF96- AVERAGE(AF$41:AF96))/_xlfn.STDEV.S(AF$41:AF96) -> 0.55713905 | AS96: =(AG96- AVERAGE(AG$41:AG96))/_xlfn.STDEV.S(AG$41:AG96) -> 3.6524511 | ... AU96: =(AI96- AVERAGE(AI$41:AI96))/_xlfn.STDEV.S(AI$41:AI96) -> 0.60272861 | AW96: =+IF(AL96>AL$2,AL$2,IF(AL96<AL$1,AL$1,AL96)) -> 0.52010335 | AX96: =+IF(AM96>AM$2,AM$2,IF(AM96<AM$1,AM$1,AM96)) -> 0.51579922 | AY96: =+IF(AN96>AN$2,AN$2,IF(AN96<AN$1,AN$1,AN96)) -> 0.069027425 | AZ96: =+IF(AO96>AO$2,AO$2,IF(AO96<AO$1,AO$1,AO96)) -> -0.025440166 | BA96: =+IF(AP96>AP$2,AP$2,IF(AP96<AP$1,AP$1,AP96)) -> -0.64930261 | BB96: =+IF(AQ96>AQ$2,AQ$2,IF(AQ96<AQ$1,AQ$1,AQ96)) -> -0.12743816 | BC96: =+IF(AR96>AR$2,AR$2,IF(AR96<AR$1,AR$1,AR96)) -> 0.55713905 | BD96: =+IF(AS96>AS$2,AS$2,IF(AS96<AS$1,AS$1,AS96)) -> 2.6971619 | ... BF96: =+IF(AU96>AU$2,AU$2,IF(AU96<AU$1,AU$1,AU96)) -> 0.60272861 | BH96: =+MEDIAN(AW96:BF96) -> 0.29241332 | BI96: =+ABS(BH96) -> 0.29241332 | BJ96: =IF(COUNT(BI$76:BI95)<60,"",MEDIAN(BI$76:BI95)) | BK96: =IF(BH96="","",IF(BJ96="",0,IF(BI96>=BJ96,BH96,0))) -> 0 | BL96: =IF(BK96="","",MEDIAN(-1,BK96,1)) -> 0 | BM96: =+AVERAGE(BL85:BL96) -> 0 | BO96: =+_xlfn.XLOOKUP(B96,Indice!B:B,Indice!AI:AI,"NOOOOOO",-1) -> 0.98393477 | BP96: =IF(BO96="","",LN(BO96)) -> -0.016195674 | BQ96: =+BP96-BP95 -> 0.19788162
A97: =+YEAR(B97) -> 2011 | B97: 40847 | C97: 7435 | D97: =+(C97/C85-1)*100 -> 26.038312 | E97: 6303 | F97: 540.17 | G97: =+(SUM(C86:C97)+SUM(E86:E97))/(F97*1000) -> 0.2856323 | H97: 7.3 | I97: 4.7 | J97: 22.119297 | K97: 600.061 | L97: =(K97/K85-1)*100 -> -1.3915524 | M97: 116.799 | N97: =(M97/M85-1)*100 -> -8.3972519 | O97: 317407 | P97: =(O97/O85-1)*100 -> -8.6319856 | Q97: =+'crack spread y Brent_WTI'!D301*100 -> 198.7171 | R97: 6.4 | S97: =+AVERAGE(R38:R97) -> 4.965 | T97: 3.934 | U97: =(T97/T85-1)*100 -> -2.5755324 | V97: 109.56 | W97: =(V97/V85-1)*100 -> 31.761876 | X97: #N/A N/A | Z97: =+AVERAGE(D95:D97)-$S97 -> 20.893848 | AA97: =+AVERAGE(H95:H97)-$S97 -> 2.2683333 | AB97: =+AVERAGE(I95:I97)-$S97 -> 0.40166667 | AC97: -4.2511926 | AD97: =AVERAGE(L95:L97) -> -3.2602865 | AE97: =+AVERAGE(N95:N97)*AVERAGE($G$15:G97) -> -2.7361353 | AF97: =-AVERAGE(P95:P97) -> 5.7362238 | AG97: =AVERAGE(Q95:Q97) -> 262.14713 | AH97: =AVERAGE(U95:U97) -> -0.55296103 | AI97: =AVERAGE(W95:W97) -> 36.826297 | AL97: =(Z97- AVERAGE(Z$41:Z97))/_xlfn.STDEV.S(Z$41:Z97) -> 0.59672915 | AM97: =(AA97- AVERAGE(AA$41:AA97))/_xlfn.STDEV.S(AA$41:AA97) -> 0.63448222 | AN97: =(AB97- AVERAGE(AB$41:AB97))/_xlfn.STDEV.S(AB$41:AB97) -> 0.1196318 | AO97: =(AC97- AVERAGE(AC$41:AC97))/_xlfn.STDEV.S(AC$41:AC97) -> -0.11268064 | AP97: =(AD97- AVERAGE(AD$41:AD97))/_xlfn.STDEV.S(AD$41:AD97) -> -0.094638314 | AQ97: =(AE97- AVERAGE(AE$41:AE97))/_xlfn.STDEV.S(AE$41:AE97) -> -0.38473799 | AR97: =(AF97- AVERAGE(AF$41:AF97))/_xlfn.STDEV.S(AF$41:AF97) -> 0.83160764 | AS97: =(AG97- AVERAGE(AG$41:AG97))/_xlfn.STDEV.S(AG$41:AG97) -> 3.0923436 | ... AU97: =(AI97- AVERAGE(AI$41:AI97))/_xlfn.STDEV.S(AI$41:AI97) -> 0.45063084 | AW97: =+IF(AL97>AL$2,AL$2,IF(AL97<AL$1,AL$1,AL97)) -> 0.59672915 | AX97: =+IF(AM97>AM$2,AM$2,IF(AM97<AM$1,AM$1,AM97)) -> 0.63448222 | AY97: =+IF(AN97>AN$2,AN$2,IF(AN97<AN$1,AN$1,AN97)) -> 0.1196318 | AZ97: =+IF(AO97>AO$2,AO$2,IF(AO97<AO$1,AO$1,AO97)) -> -0.11268064 | BA97: =+IF(AP97>AP$2,AP$2,IF(AP97<AP$1,AP$1,AP97)) -> -0.094638314 | BB97: =+IF(AQ97>AQ$2,AQ$2,IF(AQ97<AQ$1,AQ$1,AQ97)) -> -0.38473799 | BC97: =+IF(AR97>AR$2,AR$2,IF(AR97<AR$1,AR$1,AR97)) -> 0.83160764 | BD97: =+IF(AS97>AS$2,AS$2,IF(AS97<AS$1,AS$1,AS97)) -> 2.6971619 | ... BF97: =+IF(AU97>AU$2,AU$2,IF(AU97<AU$1,AU$1,AU97)) -> 0.45063084 | BH97: =+MEDIAN(AW97:BF97) -> 0.28513132 | BI97: =+ABS(BH97) -> 0.28513132 | BJ97: =IF(COUNT(BI$76:BI96)<60,"",MEDIAN(BI$76:BI96)) | BK97: =IF(BH97="","",IF(BJ97="",0,IF(BI97>=BJ97,BH97,0))) -> 0 | BL97: =IF(BK97="","",MEDIAN(-1,BK97,1)) -> 0 | BM97: =+AVERAGE(BL86:BL97) -> 0 | BO97: =+_xlfn.XLOOKUP(B97,Indice!B:B,Indice!AI:AI,"NOOOOOO",-1) -> 0.79206396 | BP97: =IF(BO97="","",LN(BO97)) -> -0.23311314 | BQ97: =+BP97-BP96 -> -0.21691746
