Workbook

Sheet Indice Bancos
B2: Start Date | C2: 42736
B3: End Date
I4: Retornos | O4: Ret EW | Q4: Indice EW | T4: Bancos / Merval | V4: Mkt Cap | AB4: Ret MktCap W | AD4: Indice MktCap W | AG4: Ratio Bancos y percentiles | AO4: Ratio Bancos/Utilities | AX4: =+MEDIAN(AX6:AX505) -> 0.74455845 | AY4: =+MEDIAN(AY6:AY505) -> 0.93037466 | AZ4: =+MEDIAN(AZ6:AZ505) -> 1.2733384 | BA4: =+MEDIAN(BA6:BA505) -> 0.58231214
B5: Dates | C5: BBAR AR Equity | D5: BMA AR Equity | E5: GGAL AR Equity | F5: SUPV AR Equity | G5: MERVAL Index | I5: =+C5 -> BBAR AR Equity | J5: =+D5 -> BMA AR Equity | K5: =+E5 -> GGAL AR Equity | L5: =+F5 -> SUPV AR Equity | M5: =+G5 -> MERVAL Index | Q5: Indice | R5: Merval | V5: Dates | W5: BBAR AR Equity | X5: BMA AR Equity | Y5: GGAL AR Equity | Z5: SUPV AR Equity | AD5: Indice | AE5: Merval | AG5: Fecha | AH5: Ratio | AI5: Q10 | AJ5: Q25 | AK5: Q50 | AL5: Q75 | AM5: Q90 | AO5: Fecha | AP5: Ratio | AQ5: Q10 | AR5: Q25 | AS5: Q50 | AT5: Q75 | AU5: Q90 | AX5: =+C5 -> BBAR AR Equity | AY5: =+D5 -> BMA AR Equity | AZ5: =+E5 -> GGAL AR Equity | BA5: =+F5 -> SUPV AR Equity
B6: =_xll.BDH(C$5,"PX_LAST",$C2,$C3,"Dir=V","Per=W","Days=A","Dts=S","cols=2;rows=510") -> 42741 | C6: 63.307 | D6: =_xll.BDH(D$5,"PX_LAST",$C2,$C3,"Dir=V","Per=W","Days=A","Dts=H","cols=1;rows=510") -> 77.584 | E6: =_xll.BDH(E$5,"PX_LAST",$C2,$C3,"Dir=V","Per=W","Days=A","Dts=H","cols=1;rows=510") -> 33.21 | F6: =_xll.BDH(F$5,"PX_LAST",$C2,$C3,"Dir=V","Per=W","Days=A","Dts=H","cols=1;rows=510") -> 39.188 | G6: =_xll.BDH(G$5,"PX_LAST",$C2,$C3,"Dir=V","Per=W","Days=A","Dts=H","cols=1;rows=510") -> 18284.28 | Q6: 100 | R6: 100 | T6: =+Q6/R6 -> 1 | V6: =_xll.BDH(W$5,"CUR_MKT_CAP",$C2,$C3,"Dir=V","Per=W","Days=A","Dts=S","cols=2;rows=510") -> 42741 | W6: 53016.69 | X6: =_xll.BDH(X$5,"CUR_MKT_CAP",$C2,$C3,"Dir=V","Per=W","Days=A","Dts=H","cols=1;rows=510") -> 66464.813 | Y6: =_xll.BDH(Y$5,"CUR_MKT_CAP",$C2,$C3,"Dir=V","Per=W","Days=A","Dts=H","cols=1;rows=510") -> 60787.371 | Z6: =_xll.BDH(Z$5,"PX_LAST",$C2,$C3,"Dir=V","Per=W","Days=A","Dts=H","cols=1;rows=510") -> 39.188 | AD6: 100 | AE6: 100 | AG6: =+B6 -> 42741 | AH6: =+(AD6/$AD$6)/(AE6/$AE$6) -> 1 | AO6: =+AG6 -> 42741 | AP6: =AD6/VLOOKUP(AO6,'[1]Indice Utilities'!$Z:$AJ,11,0) -> 1 | AX6: =+(C6/$C$6)/(AD6/$AD$6) -> 1 | AY6: =+(D6/$D$6)/(AD6/$AD$6) -> 1 | AZ6: =+(E6/$E$6)/(AD6/$AD$6) -> 1 | BA6: =+(F6/$F$6)/(AD6/$AD$6) -> 1
B7: 42748 | C7: 61.416 | D7: 78.471 | E7: 35.234 | F7: 40.295 | G7: 18885.09 | I7: =+C7/C6-1 -> -0.029870314 | J7: =+D7/D6-1 -> 0.01143277 | K7: =+E7/E6-1 -> 0.060945498 | L7: =+F7/F6-1 -> 0.028248443 | M7: =+G7/G6-1 -> 0.032859374 | O7: =+AVERAGE(I7:L7) -> 0.017689099 | Q7: =+Q6*(1+O7) -> 101.76891 | R7: =+R6*(1+M7) -> 103.28594 | T7: =+Q7/R7 -> 0.98531235 | V7: 42748 | W7: 51432.9 | X7: 67224.745 | Y7: 64493.125 | Z7: 40.295 | AB7: =+SUMPRODUCT(I7:L7,W6:Z6)/SUM(W6:Z6) -> 0.015984173 | AD7: =+AD6*(1+AB7) -> 101.59842 | AE7: =+AE6*(1+M7) -> 103.28594 | AG7: =+B7 -> 42748 | AH7: =+(AD7/$AD$6)/(AE7/$AE$6) -> 0.98366167 | AO7: =+AG7 -> 42748 | AP7: =AD7/VLOOKUP(AO7,'[1]Indice Utilities'!$Z:$AJ,11,0) -> 0.99789024 | AX7: =+(C7/$C$6)/(AD7/$AD$6) -> 0.95486693 | AY7: =+(D7/$D$6)/(AD7/$AD$6) -> 0.9955202 | AZ7: =+(E7/$E$6)/(AD7/$AD$6) -> 1.044254 | BA7: =+(F7/$F$6)/(AD7/$AD$6) -> 1.0120713
B8: 42755 | C8: 60.903 | D8: 80.996 | E8: 36.655 | F8: 39.852 | G8: 19039.49 | I8: =+C8/C7-1 -> -0.0083528722 | J8: =+D8/D7-1 -> 0.032177492 | K8: =+E8/E7-1 -> 0.040330363 | L8: =+F8/F7-1 -> -0.01099392 | M8: =+G8/G7-1 -> 0.0081757619 | O8: =+AVERAGE(I8:L8) -> 0.013290266 | Q8: =+Q7*(1+O8) -> 103.12145 | R8: =+R7*(1+M8) -> 104.13038 | T8: =+Q8/R8 -> 0.99031087 | V8: 42755 | W8: 51003.397 | X8: 69387.628 | Y8: 67093.654 | Z8: 39.852 | AB8: =+SUMPRODUCT(I8:L8,W7:Z7)/SUM(W7:Z7) -> 0.023658902 | AD8: =+AD7*(1+AB8) -> 104.00212 | AE8: =+AE7*(1+M8) -> 104.13038 | AG8: =+B8 -> 42755 | AH8: =+(AD8/$AD$6)/(AE8/$AE$6) -> 0.99876833 | AO8: =+AG8 -> 42755 | AP8: =AD8/VLOOKUP(AO8,'[1]Indice Utilities'!$Z:$AJ,11,0) -> 1.0278182 | AX8: =+(C8/$C$6)/(AD8/$AD$6) -> 0.92500641 | AY8: =+(D8/$D$6)/(AD8/$AD$6) -> 1.0038046 | AZ8: =+(E8/$E$6)/(AD8/$AD$6) -> 1.0612608 | BA8: =+(F8/$F$6)/(AD8/$AD$6) -> 0.97781076
B9: 42762 | C9: 64.044 | D9: 83.214 | E9: 35.234 | F9: 39.941 | G9: 19215.78 | I9: =+C9/C8-1 -> 0.051573814 | J9: =+D9/D8-1 -> 0.027384068 | K9: =+E9/E8-1 -> -0.03876688 | L9: =+F9/F8-1 -> 0.0022332631 | M9: =+G9/G8-1 -> 0.0092591766 | O9: =+AVERAGE(I9:L9) -> 0.010606066 | Q9: =+Q8*(1+O9) -> 104.21516 | R9: =+R8*(1+M9) -> 105.09454 | T9: =+Q9/R9 -> 0.99163247 | V9: 42762 | W9: 53634.099 | X9: 71287.458 | Y9: 64493.125 | Z9: 39.941 | AB9: =+SUMPRODUCT(I9:L9,W8:Z8)/SUM(W8:Z8) -> 0.010290028 | AD9: =+AD8*(1+AB9) -> 105.07231 | AE9: =+AE8*(1+M9) -> 105.09454 | AG9: =+B9 -> 42762 | AH9: =+(AD9/$AD$6)/(AE9/$AE$6) -> 0.99978846 | AO9: =+AG9 -> 42762 | AP9: =AD9/VLOOKUP(AO9,'[1]Indice Utilities'!$Z:$AJ,11,0) -> 1.033909 | AX9: =+(C9/$C$6)/(AD9/$AD$6) -> 0.96280523 | AY9: =+(D9/$D$6)/(AD9/$AD$6) -> 1.0207889 | AZ9: =+(E9/$E$6)/(AD9/$AD$6) -> 1.0097289 | BA9: =+(F9/$F$6)/(AD9/$AD$6) -> 0.97001301
B10: 42769 | C10: 64.076 | D10: 81.951 | E10: 35.909 | F10: 39.764 | G10: 19200.5 | I10: =+C10/C9-1 -> 0.00049965649 | J10: =+D10/D9-1 -> -0.015177735 | K10: =+E10/E9-1 -> 0.019157632 | L10: =+F10/F9-1 -> -0.0044315365 | M10: =+G10/G9-1 -> -0.00079517979 | O10: =+AVERAGE(I10:L10) -> 1.2004322e-05 | Q10: =+Q9*(1+O10) -> 104.21641 | R10: =+R9*(1+M10) -> 105.01097 | T10: =+Q10/R10 -> 0.99243354 | V10: 42769 | W10: 53660.943 | X10: 70206.016 | Y10: 65728.376 | Z10: 39.764 | AB10: =+SUMPRODUCT(I10:L10,W9:Z9)/SUM(W9:Z9) -> 0.00095101959 | AD10: =+AD9*(1+AB10) -> 105.17223 | AE10: =+AE9*(1+M10) -> 105.01097 | AG10: =+B10 -> 42769 | AH10: =+(AD10/$AD$6)/(AE10/$AE$6) -> 1.0015357 | AO10: =+AG10 -> 42769 | AP10: =AD10/VLOOKUP(AO10,'[1]Indice Utilities'!$Z:$AJ,11,0) -> 0.95731998 | AX10: =+(C10/$C$6)/(AD10/$AD$6) -> 0.96237106 | AY10: =+(D10/$D$6)/(AD10/$AD$6) -> 1.0043405 | AZ10: =+(E10/$E$6)/(AD10/$AD$6) -> 1.0280952 | BA10: =+(F10/$F$6)/(AD10/$AD$6) -> 0.96479682
B11: 42776 | C11: 65.326 | D11: 89.389 | E11: 39.035 | F11: 40.295 | G11: 19502.93 | I11: =+C11/C10-1 -> 0.019508084 | J11: =+D11/D10-1 -> 0.090761553 | K11: =+E11/E10-1 -> 0.087053385 | L11: =+F11/F10-1 -> 0.013353787 | M11: =+G11/G10-1 -> 0.015751152 | O11: =+AVERAGE(I11:L11) -> 0.052669202 | Q11: =+Q10*(1+O11) -> 109.7054 | R11: =+R10*(1+M11) -> 106.66501 | T11: =+Q11/R11 -> 1.0285041 | V11: 42776 | W11: 54707.855 | X11: 76577.753 | Y11: 71449.541 | Z11: 40.295 | AB11: =+SUMPRODUCT(I11:L11,W10:Z10)/SUM(W10:Z10) -> 0.069297498 | AD11: =+AD10*(1+AB11) -> 112.46041 | AE11: =+AE10*(1+M11) -> 106.66501 | AG11: =+B11 -> 42776 | AH11: =+(AD11/$AD$6)/(AE11/$AE$6) -> 1.0543326 | AO11: =+AG11 -> 42776 | AP11: =AD11/VLOOKUP(AO11,'[1]Indice Utilities'!$Z:$AJ,11,0) -> 1.0232508 | AX11: =+(C11/$C$6)/(AD11/$AD$6) -> 0.91756044 | AY11: =+(D11/$D$6)/(AD11/$AD$6) -> 1.0245007 | AZ11: =+(E11/$E$6)/(AD11/$AD$6) -> 1.0451669 | BA11: =+(F11/$F$6)/(AD11/$AD$6) -> 0.9143204
B12: 42783 | C12: 62.826 | D12: 85.977 | E12: 38.502 | F12: 43.395 | G12: 19681.34 | I12: =+C12/C11-1 -> -0.038269602 | J12: =+D12/D11-1 -> -0.038170245 | K12: =+E12/E11-1 -> -0.013654413 | L12: =+F12/F11-1 -> 0.076932622 | M12: =+G12/G11-1 -> 0.0091478562 | O12: =+AVERAGE(I12:L12) -> -0.0032904093 | Q12: =+Q11*(1+O12) -> 109.34443 | R12: =+R11*(1+M12) -> 107.64077 | T12: =+Q12/R12 -> 1.0158273 | V12: 42783 | W12: 52614.031 | X12: 73654.938 | Y12: 70474.342 | Z12: 43.395 | AB12: =+SUMPRODUCT(I12:L12,W11:Z11)/SUM(W11:Z11) -> -0.029535829 | AD12: =+AD11*(1+AB12) -> 109.1388 | AE12: =+AE11*(1+M12) -> 107.64077 | AG12: =+B12 -> 42783 | AH12: =+(AD12/$AD$6)/(AE12/$AE$6) -> 1.0139169 | AO12: =+AG12 -> 42783 | AP12: =AD12/VLOOKUP(AO12,'[1]Indice Utilities'!$Z:$AJ,11,0) -> 0.98507567 | AX12: =+(C12/$C$6)/(AD12/$AD$6) -> 0.90930278 | AY12: =+(D12/$D$6)/(AD12/$AD$6) -> 1.0153855 | AZ12: =+(E12/$E$6)/(AD12/$AD$6) -> 1.0622708 | BA12: =+(F12/$F$6)/(AD12/$AD$6) -> 1.0146294
B13: 42790 | C13: 59.3 | D13: 84.783 | E13: 36.016 | F13: 42.509 | G13: 19117.45 | I13: =+C13/C12-1 -> -0.056123261 | J13: =+D13/D12-1 -> -0.013887435 | K13: =+E13/E12-1 -> -0.064568074 | L13: =+F13/F12-1 -> -0.020417099 | M13: =+G13/G12-1 -> -0.028650996 | O13: =+AVERAGE(I13:L13) -> -0.038748967 | Q13: =+Q12*(1+O13) -> 105.10745 | R13: =+R12*(1+M13) -> 104.55676 | T13: =+Q13/R13 -> 1.0052669 | V13: 42790 | W13: 49661.203 | X13: 72631.953 | Y13: 65923.416 | Z13: 42.509 | AB13: =+SUMPRODUCT(I13:L13,W12:Z12)/SUM(W12:Z12) -> -0.04333132 | AD13: =+AD12*(1+AB13) -> 104.40967 | AE13: =+AE12*(1+M13) -> 104.55676 | AG13: =+B13 -> 42790 | AH13: =+(AD13/$AD$6)/(AE13/$AE$6) -> 0.99859323 | AO13: =+AG13 -> 42790 | AP13: =AD13/VLOOKUP(AO13,'[1]Indice Utilities'!$Z:$AJ,11,0) -> 0.92740467 | AX13: =+(C13/$C$6)/(AD13/$AD$6) -> 0.89714418 | AY13: =+(D13/$D$6)/(AD13/$AD$6) -> 1.0466366 | AZ13: =+(E13/$E$6)/(AD13/$AD$6) -> 1.0386898 | BA13: =+(F13/$F$6)/(AD13/$AD$6) -> 1.0389319
B14: 42797 | C14: 58.339 | D14: 87.547 | E14: 37.152 | F14: 42.066 | G14: 19265.45 | I14: =+C14/C13-1 -> -0.016205734 | J14: =+D14/D13-1 -> 0.032600875 | K14: =+E14/E13-1 -> 0.031541537 | L14: =+F14/F13-1 -> -0.010421323 | M14: =+G14/G13-1 -> 0.0077416183 | O14: =+AVERAGE(I14:L14) -> 0.009378839 | Q14: =+Q13*(1+O14) -> 106.09323 | R14: =+R13*(1+M14) -> 105.36619 | T14: =+Q14/R14 -> 1.0069001 | V14: 42797 | W14: 48855.886 | X14: 74999.433 | Y14: 68003.84 | Z14: 42.066 | AB14: =+SUMPRODUCT(I14:L14,W13:Z13)/SUM(W13:Z13) -> 0.019345425 | AD14: =+AD13*(1+AB14) -> 106.42952 | AE14: =+AE13*(1+M14) -> 105.36619 | AG14: =+B14 -> 42797 | AH14: =+(AD14/$AD$6)/(AE14/$AE$6) -> 1.0100917 | AO14: =+AG14 -> 42797 | AP14: =AD14/VLOOKUP(AO14,'[1]Indice Utilities'!$Z:$AJ,11,0) -> 0.93948899 | AX14: =+(C14/$C$6)/(AD14/$AD$6) -> 0.86585497 | AY14: =+(D14/$D$6)/(AD14/$AD$6) -> 1.0602469 | AZ14: =+(E14/$E$6)/(AD14/$AD$6) -> 1.0511174 | BA14: =+(F14/$F$6)/(AD14/$AD$6) -> 1.0085932
B15: 42804 | C15: 57.377 | D15: 86.523 | E15: 37.01 | F15: 41.181 | G15: 18895.91 | I15: =+C15/C14-1 -> -0.016489827 | J15: =+D15/D14-1 -> -0.011696574 | K15: =+E15/E14-1 -> -0.0038221361 | L15: =+F15/F14-1 -> -0.021038368 | M15: =+G15/G14-1 -> -0.019181488 | O15: =+AVERAGE(I15:L15) -> -0.013261726 | Q15: =+Q14*(1+O15) -> 104.68625 | R15: =+R14*(1+M15) -> 103.34511 | T15: =+Q15/R15 -> 1.0129773 | V15: 42804 | W15: 48050.569 | X15: 74122.589 | Y15: 67743.787 | Z15: 41.181 | AB15: =+SUMPRODUCT(I15:L15,W14:Z14)/SUM(W14:Z14) -> -0.010128474 | AD15: =+AD14*(1+AB15) -> 105.35155 | AE15: =+AE14*(1+M15) -> 103.34511 | AG15: =+B15 -> 42804 | AH15: =+(AD15/$AD$6)/(AE15/$AE$6) -> 1.0194149 | AO15: =+AG15 -> 42804 | AP15: =AD15/VLOOKUP(AO15,'[1]Indice Utilities'!$Z:$AJ,11,0) -> 0.92561915 | AX15: =+(C15/$C$6)/(AD15/$AD$6) -> 0.8602906 | AY15: =+(D15/$D$6)/(AD15/$AD$6) -> 1.0585673 | AZ15: =+(E15/$E$6)/(AD15/$AD$6) -> 1.0578139 | BA15: =+(F15/$F$6)/(AD15/$AD$6) -> 0.99747694
B16: 42811 | C16: 60.23 | D16: 88.024 | E16: 38.644 | F16: 43.218 | G16: 19434 | I16: =+C16/C15-1 -> 0.049723757 | J16: =+D16/D15-1 -> 0.017347988 | K16: =+E16/E15-1 -> 0.04415023 | L16: =+F16/F15-1 -> 0.049464559 | M16: =+G16/G15-1 -> 0.028476533 | O16: =+AVERAGE(I16:L16) -> 0.040171633 | Q16: =+Q15*(1+O16) -> 108.89167 | R16: =+R15*(1+M16) -> 106.28802 | T16: =+Q16/R16 -> 1.0244961 | V16: 42811 | W16: 50439.676 | X16: 75408.627 | Y16: 70734.395 | Z16: 43.218 | AB16: =+SUMPRODUCT(I16:L16,W15:Z15)/SUM(W15:Z15) -> 0.035102859 | AD16: =+AD15*(1+AB16) -> 109.04969 | AE16: =+AE15*(1+M16) -> 106.28802 | AG16: =+B16 -> 42811 | AH16: =+(AD16/$AD$6)/(AE16/$AE$6) -> 1.0259828 | AO16: =+AG16 -> 42811 | AP16: =AD16/VLOOKUP(AO16,'[1]Indice Utilities'!$Z:$AJ,11,0) -> 0.92575773 | AX16: =+(C16/$C$6)/(AD16/$AD$6) -> 0.87244226 | AY16: =+(D16/$D$6)/(AD16/$AD$6) -> 1.04041 | AZ16: =+(E16/$E$6)/(AD16/$AD$6) -> 1.0670598 | BA16: =+(F16/$F$6)/(AD16/$AD$6) -> 1.0113166
B17: 42818 | C17: 61.063 | D17: 90.651 | E17: 41.521 | F17: 43.04 | G17: 19705.1 | I17: =+C17/C16-1 -> 0.013830317 | J17: =+D17/D16-1 -> 0.029844133 | K17: =+E17/E16-1 -> 0.074448815 | L17: =+F17/F16-1 -> -0.0041186543 | M17: =+G17/G16-1 -> 0.013949779 | O17: =+AVERAGE(I17:L17) -> 0.028501153 | Q17: =+Q16*(1+O17) -> 111.99521 | R17: =+R16*(1+M17) -> 107.77072 | T17: =+Q17/R17 -> 1.0391989 | V17: 42818 | W17: 51137.617 | X17: 77659.195 | Y17: 76000.467 | Z17: 43.04 | AB17: =+SUMPRODUCT(I17:L17,W16:Z16)/SUM(W16:Z16) -> 0.041774838 | AD17: =+AD16*(1+AB17) -> 113.60522 | AE17: =+AE16*(1+M17) -> 107.77072 | AG17: =+B17 -> 42818 | AH17: =+(AD17/$AD$6)/(AE17/$AE$6) -> 1.0541381 | AO17: =+AG17 -> 42818 | AP17: =AD17/VLOOKUP(AO17,'[1]Indice Utilities'!$Z:$AJ,11,0) -> 0.97207165 | AX17: =+(C17/$C$6)/(AD17/$AD$6) -> 0.84903991 | AY17: =+(D17/$D$6)/(AD17/$AD$6) -> 1.0284949 | AZ17: =+(E17/$E$6)/(AD17/$AD$6) -> 1.1005268 | BA17: =+(F17/$F$6)/(AD17/$AD$6) -> 0.96676488
B18: 42825 | C18: 60.967 | D18: 91.095 | E18: 41.841 | F18: 47.026 | G18: 20265.32 | I18: =+C18/C17-1 -> -0.0015721468 | J18: =+D18/D17-1 -> 0.0048979052 | K18: =+E18/E17-1 -> 0.0077069435 | L18: =+F18/F17-1 -> 0.092611524 | M18: =+G18/G17-1 -> 0.028430203 | O18: =+AVERAGE(I18:L18) -> 0.025911056 | Q18: =+Q17*(1+O18) -> 114.89712 | R18: =+R17*(1+M18) -> 110.83466 | T18: =+Q18/R18 -> 1.0366533 | V18: 42825 | W18: 51057.085 | X18: 78039.161 | Y18: 76585.586 | Z18: 47.026 | AB18: =+SUMPRODUCT(I18:L18,W17:Z17)/SUM(W17:Z17) -> 0.0043433287 | AD18: =+AD17*(1+AB18) -> 114.09865 | AE18: =+AE17*(1+M18) -> 110.83466 | AG18: =+B18 -> 42825 | AH18: =+(AD18/$AD$6)/(AE18/$AE$6) -> 1.0294491 | AO18: =+AG18 -> 42825 | AP18: =AD18/VLOOKUP(AO18,'[1]Indice Utilities'!$Z:$AJ,11,0) -> 0.93631431 | AX18: =+(C18/$C$6)/(AD18/$AD$6) -> 0.84403916 | AY18: =+(D18/$D$6)/(AD18/$AD$6) -> 1.0290628 | AZ18: =+(E18/$E$6)/(AD18/$AD$6) -> 1.1042126 | BA18: =+(F18/$F$6)/(AD18/$AD$6) -> 1.0517304
... B57: 43098 | C57: 100.329 | D57: 149.264 | E57: 88.128 | F57: 100.162 | G57: 30065.61 | I57: =+C57/C56-1 -> 0.019531131 | J57: =+D57/D56-1 -> 0.028676182 | K57: =+E57/E56-1 -> 0.055905682 | L57: =+F57/F56-1 -> 0.029774022 | M57: =+G57/G56-1 -> 0.039198397 | O57: =+AVERAGE(I57:L57) -> 0.033471754 | Q57: =+Q56*(1+O57) -> 217.01162 | R57: =+R56*(1+M57) -> 164.4342 | T57: =+Q57/R57 -> 1.3197474 | V57: 43098 | W57: 94349.584 | X57: 145316.88 | Y57: 176490.78 | Z57: 100.162 | AB57: =+SUMPRODUCT(I57:L57,W56:Z56)/SUM(W56:Z56) -> 0.037914649 | AD57: =+AD56*(1+AB57) -> 207.52842 | AE57: =+AE56*(1+M57) -> 164.4342 | AG57: =+B57 -> 43098 | AH57: =+(AD57/$AD$6)/(AE57/$AE$6) -> 1.2620758 | AO57: =+AG57 -> 43098 | AP57: =AD57/VLOOKUP(AO57,'[1]Indice Utilities'!$Z:$AJ,11,0) -> 0.95902155 | AX57: =+(C57/$C$6)/(AD57/$AD$6) -> 0.76365494 | AY57: =+(D57/$D$6)/(AD57/$AD$6) -> 0.92705462 | AZ57: =+(E57/$E$6)/(AD57/$AD$6) -> 1.2786964 | BA57: =+(F57/$F$6)/(AD57/$AD$6) -> 1.2316074
B58: 43105 | C58: 105.509 | D58: 151.156 | E58: 92.438 | F58: 102.479 | G58: 32190.3 | I58: =+C58/C57-1 -> 0.051630137 | J58: =+D58/D57-1 -> 0.012675528 | K58: =+E58/E57-1 -> 0.048906137 | L58: =+F58/F57-1 -> 0.023132525 | M58: =+G58/G57-1 -> 0.070668448 | O58: =+AVERAGE(I58:L58) -> 0.034086082 | Q58: =+Q57*(1+O58) -> 224.40869 | R58: =+R57*(1+M58) -> 176.05451 | T58: =+Q58/R58 -> 1.2746546 | V58: 43105 | W58: 99220.228 | X58: 147158.45 | Y58: 185122.71 | Z58: 102.479 | AB58: =+SUMPRODUCT(I58:L58,W57:Z57)/SUM(W57:Z57) -> 0.036869132 | AD58: =+AD57*(1+AB58) -> 215.17982 | AE58: =+AE57*(1+M58) -> 176.05451 | AG58: =+B58 -> 43105 | AH58: =+(AD58/$AD$6)/(AE58/$AE$6) -> 1.222234 | AI58: =+_xlfn.PERCENTILE.INC(OFFSET(AH58,-52,0,52,1),0.1) -> 1.0001536 | AJ58: =+_xlfn.PERCENTILE.INC(OFFSET(AH58,-52,0,52,1),0.25) -> 1.0198766 | AK58: =+_xlfn.PERCENTILE.INC(OFFSET(AH58,-52,0,52,1),0.5) -> 1.0785454 | AL58: =+_xlfn.PERCENTILE.INC(OFFSET(AH58,-52,0,52,1),0.75) -> 1.1409934 | AM58: =+_xlfn.PERCENTILE.INC(OFFSET(AH58,-52,0,52,1),0.9) -> 1.2075559 | AO58: =+AG58 -> 43105 | AP58: =AD58/VLOOKUP(AO58,'[1]Indice Utilities'!$Z:$AJ,11,0) -> 0.90630434 | AQ58: =+_xlfn.PERCENTILE.INC(OFFSET(AP58,-52,0,52,1),0.1) -> 0.90949958 | AR58: =+_xlfn.PERCENTILE.INC(OFFSET(AP58,-52,0,52,1),0.25) -> 0.93347828 | AS58: =+_xlfn.PERCENTILE.INC(OFFSET(AP58,-52,0,52,1),0.5) -> 0.95009979 | AT58: =+_xlfn.PERCENTILE.INC(OFFSET(AP58,-52,0,52,1),0.75) -> 0.98027432 | AU58: =+_xlfn.PERCENTILE.INC(OFFSET(AP58,-52,0,52,1),0.9) -> 1.005755 | AX58: =+(C58/$C$6)/(AD58/$AD$6) -> 0.77452643 | AY58: =+(D58/$D$6)/(AD58/$AD$6) -> 0.90542335 | AZ58: =+(E58/$E$6)/(AD58/$AD$6) -> 1.2935408 | BA58: =+(F58/$F$6)/(AD58/$AD$6) -> 1.2152909
B59: 43112 | C59: 106.779 | D59: 148.955 | E59: 94.754 | F59: 106.222 | G59: 32719.7 | I59: =+C59/C58-1 -> 0.012036888 | J59: =+D59/D58-1 -> -0.014561116 | K59: =+E59/E58-1 -> 0.025054631 | L59: =+F59/F58-1 -> 0.036524556 | M59: =+G59/G58-1 -> 0.016445948 | O59: =+AVERAGE(I59:L59) -> 0.01476374 | Q59: =+Q58*(1+O59) -> 227.7218 | R59: =+R58*(1+M59) -> 178.9499 | T59: =+Q59/R59 -> 1.2725451 | V59: 43112 | W59: 100414.91 | X59: 145015.53 | Y59: 189759.69 | Z59: 106.222 | AB59: =+SUMPRODUCT(I59:L59,W58:Z58)/SUM(W58:Z58) -> 0.0085574668 | AD59: =+AD58*(1+AB59) -> 217.02121 | AE59: =+AE58*(1+M59) -> 178.9499 | AG59: =+B59 -> 43112 | AH59: =+(AD59/$AD$6)/(AE59/$AE$6) -> 1.2127485 | AI59: =+_xlfn.PERCENTILE.INC(OFFSET(AH59,-52,0,52,1),0.1) -> 1.0019457 | AJ59: =+_xlfn.PERCENTILE.INC(OFFSET(AH59,-52,0,52,1),0.25) -> 1.0244947 | AK59: =+_xlfn.PERCENTILE.INC(OFFSET(AH59,-52,0,52,1),0.5) -> 1.0809374 | AL59: =+_xlfn.PERCENTILE.INC(OFFSET(AH59,-52,0,52,1),0.75) -> 1.1475712 | AM59: =+_xlfn.PERCENTILE.INC(OFFSET(AH59,-52,0,52,1),0.9) -> 1.2207786 | AO59: =+AG59 -> 43112 | AP59: =AD59/VLOOKUP(AO59,'[1]Indice Utilities'!$Z:$AJ,11,0) -> 0.88281227 | AQ59: =+_xlfn.PERCENTILE.INC(OFFSET(AP59,-52,0,52,1),0.1) -> 0.90655203 | AR59: =+_xlfn.PERCENTILE.INC(OFFSET(AP59,-52,0,52,1),0.25) -> 0.92699294 | AS59: =+_xlfn.PERCENTILE.INC(OFFSET(AP59,-52,0,52,1),0.5) -> 0.94950498 | AT59: =+_xlfn.PERCENTILE.INC(OFFSET(AP59,-52,0,52,1),0.75) -> 0.97399172 | AU59: =+_xlfn.PERCENTILE.INC(OFFSET(AP59,-52,0,52,1),0.9) -> 1.005749 | AX59: =+(C59/$C$6)/(AD59/$AD$6) -> 0.77719847 | AY59: =+(D59/$D$6)/(AD59/$AD$6) -> 0.88466886 | AZ59: =+(E59/$E$6)/(AD59/$AD$6) -> 1.3146995 | BA59: =+(F59/$F$6)/(AD59/$AD$6) -> 1.2489907
B60: 43119 | C60: 107.137 | D60: 149.574 | E60: 97.532 | F60: 111.212 | G60: 33591.7 | I60: =+C60/C59-1 -> 0.0033527192 | J60: =+D60/D59-1 -> 0.0041556175 | K60: =+E60/E59-1 -> 0.029318024 | L60: =+F60/F59-1 -> 0.046977086 | M60: =+G60/G59-1 -> 0.026650611 | O60: =+AVERAGE(I60:L60) -> 0.020950861 | Q60: =+Q59*(1+O60) -> 232.49277 | R60: =+R59*(1+M60) -> 183.71902 | T60: =+Q60/R60 -> 1.2654801 | V60: 43119 | W60: 100751.88 | X60: 145618.22 | Y60: 195324.07 | Z60: 111.212 | AB60: =+SUMPRODUCT(I60:L60,W59:Z59)/SUM(W59:Z59) -> 0.014949956 | AD60: =+AD59*(1+AB60) -> 220.26567 | AE60: =+AE59*(1+M60) -> 183.71902 | AG60: =+B60 -> 43119 | AH60: =+(AD60/$AD$6)/(AE60/$AE$6) -> 1.1989269 | AI60: =+_xlfn.PERCENTILE.INC(OFFSET(AH60,-52,0,52,1),0.1) -> 1.0058345 | AJ60: =+_xlfn.PERCENTILE.INC(OFFSET(AH60,-52,0,52,1),0.25) -> 1.0285826 | AK60: =+_xlfn.PERCENTILE.INC(OFFSET(AH60,-52,0,52,1),0.5) -> 1.0823752 | AL60: =+_xlfn.PERCENTILE.INC(OFFSET(AH60,-52,0,52,1),0.75) -> 1.1543511 | AM60: =+_xlfn.PERCENTILE.INC(OFFSET(AH60,-52,0,52,1),0.9) -> 1.2212855 | AO60: =+AG60 -> 43119 | AP60: =AD60/VLOOKUP(AO60,'[1]Indice Utilities'!$Z:$AJ,11,0) -> 0.8679463 | AQ60: =+_xlfn.PERCENTILE.INC(OFFSET(AP60,-52,0,52,1),0.1) -> 0.90052455 | AR60: =+_xlfn.PERCENTILE.INC(OFFSET(AP60,-52,0,52,1),0.25) -> 0.92572308 | AS60: =+_xlfn.PERCENTILE.INC(OFFSET(AP60,-52,0,52,1),0.5) -> 0.94875673 | AT60: =+_xlfn.PERCENTILE.INC(OFFSET(AP60,-52,0,52,1),0.75) -> 0.96965132 | AU60: =+_xlfn.PERCENTILE.INC(OFFSET(AP60,-52,0,52,1),0.9) -> 1.005749 | AX60: =+(C60/$C$6)/(AD60/$AD$6) -> 0.76831788 | AY60: =+(D60/$D$6)/(AD60/$AD$6) -> 0.8752601 | AZ60: =+(E60/$E$6)/(AD60/$AD$6) -> 1.3333109 | BA60: =+(F60/$F$6)/(AD60/$AD$6) -> 1.288403
B61: 43126 | C61: 108.017 | D61: 147.441 | E61: 93.008 | F61: 112.37 | G61: 35126.22 | I61: =+C61/C60-1 -> 0.0082137824 | J61: =+D61/D60-1 -> -0.0142605 | K61: =+E61/E60-1 -> -0.046384776 | L61: =+F61/F60-1 -> 0.010412545 | M61: =+G61/G60-1 -> 0.045681523 | O61: =+AVERAGE(I61:L61) -> -0.010504737 | Q61: =+Q60*(1+O61) -> 230.0505 | R61: =+R60*(1+M61) -> 192.11158 | T61: =+Q61/R61 -> 1.1974837 | V61: 43126 | W61: 101578.97 | X61: 143542.27 | Y61: 186264.12 | Z61: 112.37 | AB61: =+SUMPRODUCT(I61:L61,W60:Z60)/SUM(W60:Z60) -> -0.023331404 | AD61: =+AD60*(1+AB61) -> 215.12656 | AE61: =+AE60*(1+M61) -> 192.11158 | AG61: =+B61 -> 43126 | AH61: =+(AD61/$AD$6)/(AE61/$AE$6) -> 1.1198 | AI61: =+_xlfn.PERCENTILE.INC(OFFSET(AH61,-52,0,52,1),0.1) -> 1.0078721 | AJ61: =+_xlfn.PERCENTILE.INC(OFFSET(AH61,-52,0,52,1),0.25) -> 1.0313277 | AK61: =+_xlfn.PERCENTILE.INC(OFFSET(AH61,-52,0,52,1),0.5) -> 1.0875387 | AL61: =+_xlfn.PERCENTILE.INC(OFFSET(AH61,-52,0,52,1),0.75) -> 1.1654639 | AM61: =+_xlfn.PERCENTILE.INC(OFFSET(AH61,-52,0,52,1),0.9) -> 1.2212855 | AO61: =+AG61 -> 43126 | AP61: =AD61/VLOOKUP(AO61,'[1]Indice Utilities'!$Z:$AJ,11,0) -> 0.79729521 | AQ61: =+_xlfn.PERCENTILE.INC(OFFSET(AP61,-52,0,52,1),0.1) -> 0.88451928 | AR61: =+_xlfn.PERCENTILE.INC(OFFSET(AP61,-52,0,52,1),0.25) -> 0.92509594 | AS61: =+_xlfn.PERCENTILE.INC(OFFSET(AP61,-52,0,52,1),0.5) -> 0.94779097 | AT61: =+_xlfn.PERCENTILE.INC(OFFSET(AP61,-52,0,52,1),0.75) -> 0.96612757 | AU61: =+_xlfn.PERCENTILE.INC(OFFSET(AP61,-52,0,52,1),0.9) -> 0.99984462 | AX61: =+(C61/$C$6)/(AD61/$AD$6) -> 0.79313359 | AY61: =+(D61/$D$6)/(AD61/$AD$6) -> 0.88338916 | AZ61: =+(E61/$E$6)/(AD61/$AD$6) -> 1.3018394 | BA61: =+(F61/$F$6)/(AD61/$AD$6) -> 1.3329174
B62: 43133 | C62: 97.756 | D62: 136.367 | E62: 88.556 | F62: 105.197 | G62: 32614.77 | I62: =+C62/C61-1 -> -0.094994306 | J62: =+D62/D61-1 -> -0.075108009 | K62: =+E62/E61-1 -> -0.04786685 | L62: =+F62/F61-1 -> -0.063833763 | M62: =+G62/G61-1 -> -0.071497873 | O62: =+AVERAGE(I62:L62) -> -0.070450732 | Q62: =+Q61*(1+O62) -> 213.84327 | R62: =+R61*(1+M62) -> 178.37601 | T62: =+Q62/R62 -> 1.1988342 | V62: 43133 | W62: 91929.579 | X62: 132760.69 | Y62: 177346.84 | Z62: 105.197 | AB62: =+SUMPRODUCT(I62:L62,W61:Z61)/SUM(W61:Z61) -> -0.068027351 | AD62: =+AD61*(1+AB62) -> 200.49207 | AE62: =+AE61*(1+M62) -> 178.37601 | AG62: =+B62 -> 43133 | AH62: =+(AD62/$AD$6)/(AE62/$AE$6) -> 1.1239856 | AI62: =+_xlfn.PERCENTILE.INC(OFFSET(AH62,-52,0,52,1),0.1) -> 1.0103069 | AJ62: =+_xlfn.PERCENTILE.INC(OFFSET(AH62,-52,0,52,1),0.25) -> 1.0324471 | AK62: =+_xlfn.PERCENTILE.INC(OFFSET(AH62,-52,0,52,1),0.5) -> 1.0935931 | AL62: =+_xlfn.PERCENTILE.INC(OFFSET(AH62,-52,0,52,1),0.75) -> 1.1654639 | AM62: =+_xlfn.PERCENTILE.INC(OFFSET(AH62,-52,0,52,1),0.9) -> 1.2212855 | AO62: =+AG62 -> 43133 | AP62: =AD62/VLOOKUP(AO62,'[1]Indice Utilities'!$Z:$AJ,11,0) -> 0.84955812 | AQ62: =+_xlfn.PERCENTILE.INC(OFFSET(AP62,-52,0,52,1),0.1) -> 0.88175841 | AR62: =+_xlfn.PERCENTILE.INC(OFFSET(AP62,-52,0,52,1),0.25) -> 0.92302469 | AS62: =+_xlfn.PERCENTILE.INC(OFFSET(AP62,-52,0,52,1),0.5) -> 0.94457781 | AT62: =+_xlfn.PERCENTILE.INC(OFFSET(AP62,-52,0,52,1),0.75) -> 0.96456338 | AU62: =+_xlfn.PERCENTILE.INC(OFFSET(AP62,-52,0,52,1),0.9) -> 0.99769514 | AX62: =+(C62/$C$6)/(AD62/$AD$6) -> 0.77018399 | AY62: =+(D62/$D$6)/(AD62/$AD$6) -> 0.87667762 | AZ62: =+(E62/$E$6)/(AD62/$AD$6) -> 1.3300008 | BA62: =+(F62/$F$6)/(AD62/$AD$6) -> 1.3389151
B63: 43140 | C63: 93.684 | D63: 131.38 | E63: 84.103 | F63: 100.028 | G63: 30143.44 | I63: =+C63/C62-1 -> -0.041654732 | J63: =+D63/D62-1 -> -0.036570431 | K63: =+E63/E62-1 -> -0.050284566 | L63: =+F63/F62-1 -> -0.049136382 | M63: =+G63/G62-1 -> -0.075773338 | O63: =+AVERAGE(I63:L63) -> -0.044411528 | Q63: =+Q62*(1+O63) -> 204.34616 | R63: =+R62*(1+M63) -> 164.85987 | T63: =+Q63/R63 -> 1.2395143 | V63: 43140 | W63: 88100.456 | X63: 127905.64 | Y63: 168429.56 | Z63: 100.028 | AB63: =+SUMPRODUCT(I63:L63,W62:Z62)/SUM(W62:Z62) -> -0.043783992 | AD63: =+AD62*(1+AB63) -> 191.71373 | AE63: =+AE62*(1+M63) -> 164.85987 | AG63: =+B63 -> 43140 | AH63: =+(AD63/$AD$6)/(AE63/$AE$6) -> 1.162889 | AI63: =+_xlfn.PERCENTILE.INC(OFFSET(AH63,-52,0,52,1),0.1) -> 1.0124109 | AJ63: =+_xlfn.PERCENTILE.INC(OFFSET(AH63,-52,0,52,1),0.25) -> 1.0487565 | AK63: =+_xlfn.PERCENTILE.INC(OFFSET(AH63,-52,0,52,1),0.5) -> 1.0957032 | AL63: =+_xlfn.PERCENTILE.INC(OFFSET(AH63,-52,0,52,1),0.75) -> 1.1654639 | AM63: =+_xlfn.PERCENTILE.INC(OFFSET(AH63,-52,0,52,1),0.9) -> 1.2212855 | AO63: =+AG63 -> 43140 | AP63: =AD63/VLOOKUP(AO63,'[1]Indice Utilities'!$Z:$AJ,11,0) -> 0.8613918 | AQ63: =+_xlfn.PERCENTILE.INC(OFFSET(AP63,-52,0,52,1),0.1) -> 0.87312988 | AR63: =+_xlfn.PERCENTILE.INC(OFFSET(AP63,-52,0,52,1),0.25) -> 0.92102847 | AS63: =+_xlfn.PERCENTILE.INC(OFFSET(AP63,-52,0,52,1),0.5) -> 0.94115137 | AT63: =+_xlfn.PERCENTILE.INC(OFFSET(AP63,-52,0,52,1),0.75) -> 0.96456338 | AU63: =+_xlfn.PERCENTILE.INC(OFFSET(AP63,-52,0,52,1),0.9) -> 0.99769514 | AX63: =+(C63/$C$6)/(AD63/$AD$6) -> 0.77189901 | AY63: =+(D63/$D$6)/(AD63/$AD$6) -> 0.88329115 | AZ63: =+(E63/$E$6)/(AD63/$AD$6) -> 1.3209592 | BA63: =+(F63/$F$6)/(AD63/$AD$6) -> 1.3314206
B64: 43147 | C64: 108.017 | D64: 150.537 | E64: 95.894 | F64: 114.375 | G64: 32677.25 | I64: =+C64/C63-1 -> 0.15299304 | J64: =+D64/D63-1 -> 0.14581367 | K64: =+E64/E63-1 -> 0.14019714 | L64: =+F64/F63-1 -> 0.14342984 | M64: =+G64/G63-1 -> 0.084058422 | O64: =+AVERAGE(I64:L64) -> 0.14560842 | Q64: =+Q63*(1+O64) -> 234.10069 | R64: =+R63*(1+M64) -> 178.71773 | T64: =+Q64/R64 -> 1.3098907 | V64: 43147 | W64: 101578.97 | X64: 146555.75 | Y64: 192042.51 | Z64: 114.375 | AB64: =+SUMPRODUCT(I64:L64,W63:Z63)/SUM(W63:Z63) -> 0.14499782 | AD64: =+AD63*(1+AB64) -> 219.5118 | AE64: =+AE63*(1+M64) -> 178.71773 | AG64: =+B64 -> 43147 | AH64: =+(AD64/$AD$6)/(AE64/$AE$6) -> 1.2282598 | AI64: =+_xlfn.PERCENTILE.INC(OFFSET(AH64,-52,0,52,1),0.1) -> 1.0124109 | AJ64: =+_xlfn.PERCENTILE.INC(OFFSET(AH64,-52,0,52,1),0.25) -> 1.0487565 | AK64: =+_xlfn.PERCENTILE.INC(OFFSET(AH64,-52,0,52,1),0.5) -> 1.1023511 | AL64: =+_xlfn.PERCENTILE.INC(OFFSET(AH64,-52,0,52,1),0.75) -> 1.1657314 | AM64: =+_xlfn.PERCENTILE.INC(OFFSET(AH64,-52,0,52,1),0.9) -> 1.2212855 | AO64: =+AG64 -> 43147 | AP64: =AD64/VLOOKUP(AO64,'[1]Indice Utilities'!$Z:$AJ,11,0) -> 0.91606987 | AQ64: =+_xlfn.PERCENTILE.INC(OFFSET(AP64,-52,0,52,1),0.1) -> 0.87095436 | AR64: =+_xlfn.PERCENTILE.INC(OFFSET(AP64,-52,0,52,1),0.25) -> 0.91865705 | AS64: =+_xlfn.PERCENTILE.INC(OFFSET(AP64,-52,0,52,1),0.5) -> 0.9399418 | AT64: =+_xlfn.PERCENTILE.INC(OFFSET(AP64,-52,0,52,1),0.75) -> 0.96403469 | AU64: =+_xlfn.PERCENTILE.INC(OFFSET(AP64,-52,0,52,1),0.9) -> 0.98598722 | AX64: =+(C64/$C$6)/(AD64/$AD$6) -> 0.77728897 | AY64: =+(D64/$D$6)/(AD64/$AD$6) -> 0.88392053 | AZ64: =+(E64/$E$6)/(AD64/$AD$6) -> 1.3154207 | BA64: =+(F64/$F$6)/(AD64/$AD$6) -> 1.3295973
B65: 43154 | C65: 106.421 | D65: 155.833 | E65: 93.151 | F65: 113.93 | G65: 32742.39 | I65: =+C65/C64-1 -> -0.014775452 | J65: =+D65/D64-1 -> 0.03518072 | K65: =+E65/E64-1 -> -0.028604501 | L65: =+F65/F64-1 -> -0.0038907104 | M65: =+G65/G64-1 -> 0.0019934358 | O65: =+AVERAGE(I65:L65) -> -0.0030224859 | Q65: =+Q64*(1+O65) -> 233.39312 | R65: =+R64*(1+M65) -> 179.07399 | T65: =+Q65/R65 -> 1.3033334 | V65: 43154 | W65: 100077.95 | X65: 151712.16 | Y65: 186549.47 | Z65: 113.93 | AB65: =+SUMPRODUCT(I65:L65,W64:Z64)/SUM(W64:Z64) -> -0.0041760133 | AD65: =+AD64*(1+AB65) -> 218.59512 | AE65: =+AE64*(1+M65) -> 179.07399 | AG65: =+B65 -> 43154 | AH65: =+(AD65/$AD$6)/(AE65/$AE$6) -> 1.2206972 | AI65: =+_xlfn.PERCENTILE.INC(OFFSET(AH65,-52,0,52,1),0.1) -> 1.0129607 | AJ65: =+_xlfn.PERCENTILE.INC(OFFSET(AH65,-52,0,52,1),0.25) -> 1.0596128 | AK65: =+_xlfn.PERCENTILE.INC(OFFSET(AH65,-52,0,52,1),0.5) -> 1.1138832 | AL65: =+_xlfn.PERCENTILE.INC(OFFSET(AH65,-52,0,52,1),0.75) -> 1.1754499 | AM65: =+_xlfn.PERCENTILE.INC(OFFSET(AH65,-52,0,52,1),0.9) -> 1.2276572 | AO65: =+AG65 -> 43154 | AP65: =AD65/VLOOKUP(AO65,'[1]Indice Utilities'!$Z:$AJ,11,0) -> 0.9365008 | AQ65: =+_xlfn.PERCENTILE.INC(OFFSET(AP65,-52,0,52,1),0.1) -> 0.87095436 | AR65: =+_xlfn.PERCENTILE.INC(OFFSET(AP65,-52,0,52,1),0.25) -> 0.9160437 | AS65: =+_xlfn.PERCENTILE.INC(OFFSET(AP65,-52,0,52,1),0.5) -> 0.93949372 | AT65: =+_xlfn.PERCENTILE.INC(OFFSET(AP65,-52,0,52,1),0.75) -> 0.96024907 | AU65: =+_xlfn.PERCENTILE.INC(OFFSET(AP65,-52,0,52,1),0.9) -> 0.9856638 | AX65: =+(C65/$C$6)/(AD65/$AD$6) -> 0.7690156 | AY65: =+(D65/$D$6)/(AD65/$AD$6) -> 0.91885464 | AZ65: =+(E65/$E$6)/(AD65/$AD$6) -> 1.2831523 | BA65: =+(F65/$F$6)/(AD65/$AD$6) -> 1.3299783
B66: 43161 | C66: 98.7 | D66: 149.47 | E66: 87.594 | F66: 105.197 | G66: 31900.7 | I66: =+C66/C65-1 -> -0.07255147 | J66: =+D66/D65-1 -> -0.040832173 | K66: =+E66/E65-1 -> -0.059655828 | L66: =+F66/F65-1 -> -0.07665233 | M66: =+G66/G65-1 -> -0.025706431 | O66: =+AVERAGE(I66:L66) -> -0.06242295 | Q66: =+Q65*(1+O66) -> 218.82403 | R66: =+R65*(1+M66) -> 174.47064 | T66: =+Q66/R66 -> 1.254217 | V66: 43161 | W66: 92817.935 | X66: 145517.77 | Y66: 175420.71 | Z66: 105.197 | AB66: =+SUMPRODUCT(I66:L66,W65:Z65)/SUM(W65:Z65) -> -0.056090407 | AD66: =+AD65*(1+AB66) -> 206.33403 | AE66: =+AE65*(1+M66) -> 174.47064 | AG66: =+B66 -> 43161 | AH66: =+(AD66/$AD$6)/(AE66/$AE$6) -> 1.1826289 | AI66: =+_xlfn.PERCENTILE.INC(OFFSET(AH66,-52,0,52,1),0.1) -> 1.0194765 | AJ66: =+_xlfn.PERCENTILE.INC(OFFSET(AH66,-52,0,52,1),0.25) -> 1.0665439 | AK66: =+_xlfn.PERCENTILE.INC(OFFSET(AH66,-52,0,52,1),0.5) -> 1.1206206 | AL66: =+_xlfn.PERCENTILE.INC(OFFSET(AH66,-52,0,52,1),0.75) -> 1.1834339 | AM66: =+_xlfn.PERCENTILE.INC(OFFSET(AH66,-52,0,52,1),0.9) -> 1.2276572 | AO66: =+AG66 -> 43161 | AP66: =AD66/VLOOKUP(AO66,'[1]Indice Utilities'!$Z:$AJ,11,0) -> 0.91227043 | AQ66: =+_xlfn.PERCENTILE.INC(OFFSET(AP66,-52,0,52,1),0.1) -> 0.87095436 | AR66: =+_xlfn.PERCENTILE.INC(OFFSET(AP66,-52,0,52,1),0.25) -> 0.9160437 | AS66: =+_xlfn.PERCENTILE.INC(OFFSET(AP66,-52,0,52,1),0.5) -> 0.93949372 | AT66: =+_xlfn.PERCENTILE.INC(OFFSET(AP66,-52,0,52,1),0.75) -> 0.96024907 | AU66: =+_xlfn.PERCENTILE.INC(OFFSET(AP66,-52,0,52,1),0.9) -> 0.9856638 | AX66: =+(C66/$C$6)/(AD66/$AD$6) -> 0.75560455 | AY66: =+(D66/$D$6)/(AD66/$AD$6) -> 0.93370786 | AZ66: =+(E66/$E$6)/(AD66/$AD$6) -> 1.2783054 | BA66: =+(F66/$F$6)/(AD66/$AD$6) -> 1.3010063
B67: 43168 | C67: 99.678 | D67: 153.529 | E67: 92.403 | F67: 106.845 | G67: 33182.6 | I67: =+C67/C66-1 -> 0.0099088146 | J67: =+D67/D66-1 -> 0.027155951 | K67: =+E67/E66-1 -> 0.054901021 | L67: =+F67/F66-1 -> 0.015665846 | M67: =+G67/G66-1 -> 0.040184071 | O67: =+AVERAGE(I67:L67) -> 0.026907908 | Q67: =+Q66*(1+O67) -> 224.71213 | R67: =+R66*(1+M67) -> 181.48158 | T67: =+Q67/R67 -> 1.238209 | V67: 43168 | W67: 93736.925 | X67: 149468.79 | Y67: 185051.37 | Z67: 106.845 | AB67: =+SUMPRODUCT(I67:L67,W66:Z66)/SUM(W66:Z66) -> 0.035045079 | AD67: =+AD66*(1+AB67) -> 213.56502 | AE67: =+AE66*(1+M67) -> 181.48158 | AG67: =+B67 -> 43168 | AH67: =+(AD67/$AD$6)/(AE67/$AE$6) -> 1.1767862 | AI67: =+_xlfn.PERCENTILE.INC(OFFSET(AH67,-52,0,52,1),0.1) -> 1.0206257 | AJ67: =+_xlfn.PERCENTILE.INC(OFFSET(AH67,-52,0,52,1),0.25) -> 1.0691437 | AK67: =+_xlfn.PERCENTILE.INC(OFFSET(AH67,-52,0,52,1),0.5) -> 1.1226444 | AL67: =+_xlfn.PERCENTILE.INC(OFFSET(AH67,-52,0,52,1),0.75) -> 1.1861377 | AM67: =+_xlfn.PERCENTILE.INC(OFFSET(AH67,-52,0,52,1),0.9) -> 1.2276572 | AO67: =+AG67 -> 43168 | AP67: =AD67/VLOOKUP(AO67,'[1]Indice Utilities'!$Z:$AJ,11,0) -> 0.88812158 | AQ67: =+_xlfn.PERCENTILE.INC(OFFSET(AP67,-52,0,52,1),0.1) -> 0.87095436 | AR67: =+_xlfn.PERCENTILE.INC(OFFSET(AP67,-52,0,52,1),0.25) -> 0.91504149 | AS67: =+_xlfn.PERCENTILE.INC(OFFSET(AP67,-52,0,52,1),0.5) -> 0.93900899 | AT67: =+_xlfn.PERCENTILE.INC(OFFSET(AP67,-52,0,52,1),0.75) -> 0.96024907 | AU67: =+_xlfn.PERCENTILE.INC(OFFSET(AP67,-52,0,52,1),0.9) -> 0.9856638 | AX67: =+(C67/$C$6)/(AD67/$AD$6) -> 0.73725455 | AY67: =+(D67/$D$6)/(AD67/$AD$6) -> 0.92659112 | AZ67: =+(E67/$E$6)/(AD67/$AD$6) -> 1.302828 | BA67: =+(F67/$F$6)/(AD67/$AD$6) -> 1.2766475
B68: 43175 | C68: 103.815 | D68: 151.844 | E68: 94.22 | F68: 110.544 | G68: 32555.08 | I68: =+C68/C67-1 -> 0.041503642 | J68: =+D68/D67-1 -> -0.010975125 | K68: =+E68/E67-1 -> 0.019663864 | L68: =+F68/F67-1 -> 0.034620244 | M68: =+G68/G67-1 -> -0.018911116 | O68: =+AVERAGE(I68:L68) -> 0.021203156 | Q68: =+Q67*(1+O68) -> 229.47674 | R68: =+R67*(1+M68) -> 178.04956 | T68: =+Q68/R68 -> 1.2888363 | V68: 43175 | W68: 97627.314 | X68: 147828.11 | Y68: 188689.62 | Z68: 110.544 | AB68: =+SUMPRODUCT(I68:L68,W67:Z67)/SUM(W67:Z67) -> 0.013755848 | AD68: =+AD67*(1+AB68) -> 216.50279 | AE68: =+AE67*(1+M68) -> 178.04956 | AG68: =+B68 -> 43175 | AH68: =+(AD68/$AD$6)/(AE68/$AE$6) -> 1.2159692 | AI68: =+_xlfn.PERCENTILE.INC(OFFSET(AH68,-52,0,52,1),0.1) -> 1.0263295 | AJ68: =+_xlfn.PERCENTILE.INC(OFFSET(AH68,-52,0,52,1),0.25) -> 1.0731168 | AK68: =+_xlfn.PERCENTILE.INC(OFFSET(AH68,-52,0,52,1),0.5) -> 1.1239166 | AL68: =+_xlfn.PERCENTILE.INC(OFFSET(AH68,-52,0,52,1),0.75) -> 1.1861377 | AM68: =+_xlfn.PERCENTILE.INC(OFFSET(AH68,-52,0,52,1),0.9) -> 1.2276572 | AO68: =+AG68 -> 43175 | AP68: =AD68/VLOOKUP(AO68,'[1]Indice Utilities'!$Z:$AJ,11,0) -> 0.90464279 | AQ68: =+_xlfn.PERCENTILE.INC(OFFSET(AP68,-52,0,52,1),0.1) -> 0.87095436 | AR68: =+_xlfn.PERCENTILE.INC(OFFSET(AP68,-52,0,52,1),0.25) -> 0.91139811 | AS68: =+_xlfn.PERCENTILE.INC(OFFSET(AP68,-52,0,52,1),0.5) -> 0.93900899 | AT68: =+_xlfn.PERCENTILE.INC(OFFSET(AP68,-52,0,52,1),0.75) -> 0.96024907 | AU68: =+_xlfn.PERCENTILE.INC(OFFSET(AP68,-52,0,52,1),0.9) -> 0.9856638 | AX68: =+(C68/$C$6)/(AD68/$AD$6) -> 0.75743415 | AY68: =+(D68/$D$6)/(AD68/$AD$6) -> 0.90398657 | AZ68: =+(E68/$E$6)/(AD68/$AD$6) -> 1.3104207 | BA68: =+(F68/$F$6)/(AD68/$AD$6) -> 1.3029225
B69: 43182 | C69: 98.472 | D69: 149.195 | E69: 91.299 | F69: 107.826 | G69: 31461.26 | I69: =+C69/C68-1 -> -0.051466551 | J69: =+D69/D68-1 -> -0.017445536 | K69: =+E69/E68-1 -> -0.03100191 | L69: =+F69/F68-1 -> -0.024587495 | M69: =+G69/G68-1 -> -0.033599057 | O69: =+AVERAGE(I69:L69) -> -0.031125373 | Q69: =+Q68*(1+O69) -> 222.33419 | R69: =+R68*(1+M69) -> 172.06726 | T69: =+Q69/R69 -> 1.2921353 | V69: 43182 | W69: 92603.504 | X69: 145249.91 | Y69: 182839.88 | Z69: 107.826 | AB69: =+SUMPRODUCT(I69:L69,W68:Z68)/SUM(W68:Z68) -> -0.030986218 | AD69: =+AD68*(1+AB69) -> 209.79418 | AE69: =+AE68*(1+M69) -> 172.06726 | AG69: =+B69 -> 43182 | AH69: =+(AD69/$AD$6)/(AE69/$AE$6) -> 1.2192568 | AI69: =+_xlfn.PERCENTILE.INC(OFFSET(AH69,-52,0,52,1),0.1) -> 1.0296996 | AJ69: =+_xlfn.PERCENTILE.INC(OFFSET(AH69,-52,0,52,1),0.25) -> 1.0754721 | AK69: =+_xlfn.PERCENTILE.INC(OFFSET(AH69,-52,0,52,1),0.5) -> 1.1251071 | AL69: =+_xlfn.PERCENTILE.INC(OFFSET(AH69,-52,0,52,1),0.75) -> 1.1972297 | AM69: =+_xlfn.PERCENTILE.INC(OFFSET(AH69,-52,0,52,1),0.9) -> 1.2276572 | AO69: =+AG69 -> 43182 | AP69: =AD69/VLOOKUP(AO69,'[1]Indice Utilities'!$Z:$AJ,11,0) -> 0.92321445 | AQ69: =+_xlfn.PERCENTILE.INC(OFFSET(AP69,-52,0,52,1),0.1) -> 0.87095436 | AR69: =+_xlfn.PERCENTILE.INC(OFFSET(AP69,-52,0,52,1),0.25) -> 0.90816197 | AS69: =+_xlfn.PERCENTILE.INC(OFFSET(AP69,-52,0,52,1),0.5) -> 0.93900899 | AT69: =+_xlfn.PERCENTILE.INC(OFFSET(AP69,-52,0,52,1),0.75) -> 0.96024907 | AU69: =+_xlfn.PERCENTILE.INC(OFFSET(AP69,-52,0,52,1),0.9) -> 0.9856638 | AX69: =+(C69/$C$6)/(AD69/$AD$6) -> 0.7414256 | AY69: =+(D69/$D$6)/(AD69/$AD$6) -> 0.91661858 | AZ69: =+(E69/$E$6)/(AD69/$AD$6) -> 1.3103994 | BA69: =+(F69/$F$6)/(AD69/$AD$6) -> 1.3115261
... B515: 46304 | C515: 6800 | D515: 10440 | E515: 5940 | F515: 2314 | G515: 2828027 | I515: =+C515/C514-1 -> 0.0074074074 | J515: =+D515/D514-1 -> -0.0057142857 | K515: =+E515/E514-1 -> 0.017994859 | L515: =+F515/F514-1 -> 0.028901734 | M515: =+G515/G514-1 -> 0.021810459 | O515: =+AVERAGE(I515:L515) -> 0.012147429 | Q515: =+Q514*(1+O515) -> 13428.87 | R515: =+R514*(1+M515) -> 15466.986 | T515: =+Q515/R515 -> 0.868228 | V515: 46304 | W515: 4166428.5 | X515: 6675476 | Y515: 9541147.2 | Z515: 2314 | AB515: =+SUMPRODUCT(I515:L515,W514:Z514)/SUM(W514:Z514) -> 0.007960313 | AD515: =+AD514*(1+AB515) -> 14199.562 | AE515: =+AE514*(1+M515) -> 15466.986 | AG515: =+B515 -> 46304 | AH515: =+(AD515/$AD$6)/(AE515/$AE$6) -> 0.91805616 | AI515: =+_xlfn.PERCENTILE.INC(OFFSET(AH515,-52,0,52,1),0.1) -> 0.95117447 | AJ515: =+_xlfn.PERCENTILE.INC(OFFSET(AH515,-52,0,52,1),0.25) -> 0.98742377 | AK515: =+_xlfn.PERCENTILE.INC(OFFSET(AH515,-52,0,52,1),0.5) -> 1.0456541 | AL515: =+_xlfn.PERCENTILE.INC(OFFSET(AH515,-52,0,52,1),0.75) -> 1.1041949 | AM515: =+_xlfn.PERCENTILE.INC(OFFSET(AH515,-52,0,52,1),0.9) -> 1.1286625 | AO515: =+AG515 -> 46304 | AP515: =AD515/VLOOKUP(AO515,'[1]Indice Utilities'!$Z:$AJ,11,0) -> #N/A | AQ515: =+_xlfn.PERCENTILE.INC(OFFSET(AP515,-52,0,52,1),0.1) -> 0.73843861 | AR515: =+_xlfn.PERCENTILE.INC(OFFSET(AP515,-52,0,52,1),0.25) -> 0.782608 | AS515: =+_xlfn.PERCENTILE.INC(OFFSET(AP515,-52,0,52,1),0.5) -> 0.8359267 | AT515: =+_xlfn.PERCENTILE.INC(OFFSET(AP515,-52,0,52,1),0.75) -> 0.90528121 | AU515: =+_xlfn.PERCENTILE.INC(OFFSET(AP515,-52,0,52,1),0.9) -> 0.93468884 | AX515: =+(C515/$C$6)/(AD515/$AD$6) -> 0.75645351 | AY515: =+(D515/$D$6)/(AD515/$AD$6) -> 0.94766184 | AZ515: =+(E515/$E$6)/(AD515/$AD$6) -> 1.2596289 | BA515: =+(F515/$F$6)/(AD515/$AD$6) -> 0.41584867

Sheet Relativos

Sheet Beta Rolling
A1: =+'Indice Bancos'!B5 -> Dates | B1: =+'Indice Bancos'!I5 -> BBAR AR Equity | C1: =+'Indice Bancos'!J5 -> BMA AR Equity | D1: =+'Indice Bancos'!K5 -> GGAL AR Equity | E1: =+'Indice Bancos'!L5 -> SUPV AR Equity | G1: =+'Indice Bancos'!M5 -> MERVAL Index
A2: =+'Indice Bancos'!B6 -> 42741
A3: =+'Indice Bancos'!B7 -> 42748 | B3: =+'Indice Bancos'!I7 -> -0.029870314 | C3: =+'Indice Bancos'!J7 -> 0.01143277 | D3: =+'Indice Bancos'!K7 -> 0.060945498 | E3: =+'Indice Bancos'!L7 -> 0.028248443 | G3: =+'Indice Bancos'!M7 -> 0.032859374
A4: =+'Indice Bancos'!B8 -> 42755 | B4: =+'Indice Bancos'!I8 -> -0.0083528722 | C4: =+'Indice Bancos'!J8 -> 0.032177492 | D4: =+'Indice Bancos'!K8 -> 0.040330363 | E4: =+'Indice Bancos'!L8 -> -0.01099392 | G4: =+'Indice Bancos'!M8 -> 0.0081757619
A5: =+'Indice Bancos'!B9 -> 42762 | B5: =+'Indice Bancos'!I9 -> 0.051573814 | C5: =+'Indice Bancos'!J9 -> 0.027384068 | D5: =+'Indice Bancos'!K9 -> -0.03876688 | E5: =+'Indice Bancos'!L9 -> 0.0022332631 | G5: =+'Indice Bancos'!M9 -> 0.0092591766
A6: =+'Indice Bancos'!B10 -> 42769 | B6: =+'Indice Bancos'!I10 -> 0.00049965649 | C6: =+'Indice Bancos'!J10 -> -0.015177735 | D6: =+'Indice Bancos'!K10 -> 0.019157632 | E6: =+'Indice Bancos'!L10 -> -0.0044315365 | G6: =+'Indice Bancos'!M10 -> -0.00079517979
A7: =+'Indice Bancos'!B11 -> 42776 | B7: =+'Indice Bancos'!I11 -> 0.019508084 | C7: =+'Indice Bancos'!J11 -> 0.090761553 | D7: =+'Indice Bancos'!K11 -> 0.087053385 | E7: =+'Indice Bancos'!L11 -> 0.013353787 | G7: =+'Indice Bancos'!M11 -> 0.015751152
A8: =+'Indice Bancos'!B12 -> 42783 | B8: =+'Indice Bancos'!I12 -> -0.038269602 | C8: =+'Indice Bancos'!J12 -> -0.038170245 | D8: =+'Indice Bancos'!K12 -> -0.013654413 | E8: =+'Indice Bancos'!L12 -> 0.076932622 | G8: =+'Indice Bancos'!M12 -> 0.0091478562
A9: =+'Indice Bancos'!B13 -> 42790 | B9: =+'Indice Bancos'!I13 -> -0.056123261 | C9: =+'Indice Bancos'!J13 -> -0.013887435 | D9: =+'Indice Bancos'!K13 -> -0.064568074 | E9: =+'Indice Bancos'!L13 -> -0.020417099 | G9: =+'Indice Bancos'!M13 -> -0.028650996
A10: =+'Indice Bancos'!B14 -> 42797 | B10: =+'Indice Bancos'!I14 -> -0.016205734 | C10: =+'Indice Bancos'!J14 -> 0.032600875 | D10: =+'Indice Bancos'!K14 -> 0.031541537 | E10: =+'Indice Bancos'!L14 -> -0.010421323 | G10: =+'Indice Bancos'!M14 -> 0.0077416183
A11: =+'Indice Bancos'!B15 -> 42804 | B11: =+'Indice Bancos'!I15 -> -0.016489827 | C11: =+'Indice Bancos'!J15 -> -0.011696574 | D11: =+'Indice Bancos'!K15 -> -0.0038221361 | E11: =+'Indice Bancos'!L15 -> -0.021038368 | G11: =+'Indice Bancos'!M15 -> -0.019181488
A12: =+'Indice Bancos'!B16 -> 42811 | B12: =+'Indice Bancos'!I16 -> 0.049723757 | C12: =+'Indice Bancos'!J16 -> 0.017347988 | D12: =+'Indice Bancos'!K16 -> 0.04415023 | E12: =+'Indice Bancos'!L16 -> 0.049464559 | G12: =+'Indice Bancos'!M16 -> 0.028476533
A13: =+'Indice Bancos'!B17 -> 42818 | B13: =+'Indice Bancos'!I17 -> 0.013830317 | C13: =+'Indice Bancos'!J17 -> 0.029844133 | D13: =+'Indice Bancos'!K17 -> 0.074448815 | E13: =+'Indice Bancos'!L17 -> -0.0041186543 | G13: =+'Indice Bancos'!M17 -> 0.013949779
A14: =+'Indice Bancos'!B18 -> 42825 | B14: =+'Indice Bancos'!I18 -> -0.0015721468 | C14: =+'Indice Bancos'!J18 -> 0.0048979052 | D14: =+'Indice Bancos'!K18 -> 0.0077069435 | E14: =+'Indice Bancos'!L18 -> 0.092611524 | G14: =+'Indice Bancos'!M18 -> 0.028430203
... A90: =+'Indice Bancos'!B94 -> 43357 | B90: =+'Indice Bancos'!I94 -> 0.0087729808 | C90: =+'Indice Bancos'!J94 -> -0.0031597551 | D90: =+'Indice Bancos'!K94 -> -0.01992133 | E90: =+'Indice Bancos'!L94 -> -0.051913503 | G90: =+'Indice Bancos'!M94 -> 0.012284301
A91: =+'Indice Bancos'!B95 -> 43364 | B91: =+'Indice Bancos'!I95 -> 0.30608636 | C91: =+'Indice Bancos'!J95 -> 0.14787787 | D91: =+'Indice Bancos'!K95 -> 0.2886296 | E91: =+'Indice Bancos'!L95 -> 0.25584239 | G91: =+'Indice Bancos'!M95 -> 0.13750972 | I91: =+A1 -> Dates | J91: =+B1 -> BBAR AR Equity | K91: =+C1 -> BMA AR Equity | L91: =+D1 -> GGAL AR Equity | M91: =+E1 -> SUPV AR Equity
A92: =+'Indice Bancos'!B96 -> 43371 | B92: =+'Indice Bancos'!I96 -> 0.065241993 | C92: =+'Indice Bancos'!J96 -> -0.05075861 | D92: =+'Indice Bancos'!K96 -> -0.04777274 | E92: =+'Indice Bancos'!L96 -> -0.086483985 | G92: =+'Indice Bancos'!M96 -> -0.025208931 | I92: =+A92 -> 43371 | J92: =+SLOPE(B3:B92,$G3:$G92) -> 1.1661612 | K92: =+SLOPE(C3:C92,$G3:$G92) -> 1.040295 | L92: =+SLOPE(D3:D92,$G3:$G92) -> 1.0863557 | M92: =+SLOPE(E3:E92,$G3:$G92) -> 1.590764
A93: =+'Indice Bancos'!B97 -> 43378 | B93: =+'Indice Bancos'!I97 -> -0.12249234 | C93: =+'Indice Bancos'!J97 -> -0.098514233 | D93: =+'Indice Bancos'!K97 -> -0.13487992 | E93: =+'Indice Bancos'!L97 -> -0.11893781 | G93: =+'Indice Bancos'!M97 -> -0.098412308 | I93: =+A93 -> 43378 | J93: =+SLOPE(B4:B93,$G4:$G93) -> 1.1797826 | K93: =+SLOPE(C4:C93,$G4:$G93) -> 1.0405589 | L93: =+SLOPE(D4:D93,$G4:$G93) -> 1.1007745 | M93: =+SLOPE(E4:E93,$G4:$G93) -> 1.569407
A94: =+'Indice Bancos'!B98 -> 43385 | B94: =+'Indice Bancos'!I98 -> -0.081199399 | C94: =+'Indice Bancos'!J98 -> -0.045132179 | D94: =+'Indice Bancos'!K98 -> 0 | E94: =+'Indice Bancos'!L98 -> -0.028414499 | G94: =+'Indice Bancos'!M98 -> -0.018911641 | I94: =+A94 -> 43385 | J94: =+SLOPE(B5:B94,$G5:$G94) -> 1.1879782 | K94: =+SLOPE(C5:C94,$G5:$G94) -> 1.0436206 | L94: =+SLOPE(D5:D94,$G5:$G94) -> 1.097823 | M94: =+SLOPE(E5:E94,$G5:$G94) -> 1.5690176
A95: =+'Indice Bancos'!B99 -> 43392 | B95: =+'Indice Bancos'!I99 -> -0.039152481 | C95: =+'Indice Bancos'!J99 -> -0.070225014 | D95: =+'Indice Bancos'!K99 -> -0.079318861 | E95: =+'Indice Bancos'!L99 -> -0.060327762 | G95: =+'Indice Bancos'!M99 -> -0.031248543 | I95: =+A95 -> 43392 | J95: =+SLOPE(B6:B95,$G6:$G95) -> 1.1872763 | K95: =+SLOPE(C6:C95,$G6:$G95) -> 1.0505007 | L95: =+SLOPE(D6:D95,$G6:$G95) -> 1.1083172 | M95: =+SLOPE(E6:E95,$G6:$G95) -> 1.5708471
A96: =+'Indice Bancos'!B100 -> 43399 | B96: =+'Indice Bancos'!I100 -> 0.077859268 | C96: =+'Indice Bancos'!J100 -> 0.14270019 | D96: =+'Indice Bancos'!K100 -> 0.0095044128 | E96: =+'Indice Bancos'!L100 -> 0.13228938 | G96: =+'Indice Bancos'!M100 -> 0.024294047 | I96: =+A96 -> 43399 | J96: =+SLOPE(B7:B96,$G7:$G96) -> 1.1925344 | K96: =+SLOPE(C7:C96,$G7:$G96) -> 1.0621762 | L96: =+SLOPE(D7:D96,$G7:$G96) -> 1.1070097 | M96: =+SLOPE(E7:E96,$G7:$G96) -> 1.5807255
A97: =+'Indice Bancos'!B101 -> 43406 | B97: =+'Indice Bancos'!I101 -> 0.10179253 | C97: =+'Indice Bancos'!J101 -> 0.091831325 | D97: =+'Indice Bancos'!K101 -> 0.12831532 | E97: =+'Indice Bancos'!L101 -> 0.10910346 | G97: =+'Indice Bancos'!M101 -> 0.069778654 | I97: =+A97 -> 43406 | J97: =+SLOPE(B8:B97,$G8:$G97) -> 1.1991495 | K97: =+SLOPE(C8:C97,$G8:$G97) -> 1.0646676 | L97: =+SLOPE(D8:D97,$G8:$G97) -> 1.1204364 | M97: =+SLOPE(E8:E97,$G8:$G97) -> 1.5815166
A98: =+'Indice Bancos'!B102 -> 43413 | B98: =+'Indice Bancos'!I102 -> -0.080160424 | C98: =+'Indice Bancos'!J102 -> -0.095456378 | D98: =+'Indice Bancos'!K102 -> -0.05842419 | E98: =+'Indice Bancos'!L102 -> -0.082114074 | G98: =+'Indice Bancos'!M102 -> -0.04795689 | I98: =+A98 -> 43413 | J98: =+SLOPE(B9:B98,$G9:$G98) -> 1.2061517 | K98: =+SLOPE(C9:C98,$G9:$G98) -> 1.0777 | L98: =+SLOPE(D9:D98,$G9:$G98) -> 1.1225471 | M98: =+SLOPE(E9:E98,$G9:$G98) -> 1.5815489
A99: =+'Indice Bancos'!B103 -> 43420 | B99: =+'Indice Bancos'!I103 -> 0.11521218 | C99: =+'Indice Bancos'!J103 -> 0.099424995 | D99: =+'Indice Bancos'!K103 -> 0.064812956 | E99: =+'Indice Bancos'!L103 -> 0.064984738 | G99: =+'Indice Bancos'!M103 -> 0.040008705 | I99: =+A99 -> 43420 | J99: =+SLOPE(B10:B99,$G10:$G99) -> 1.2142784 | K99: =+SLOPE(C10:C99,$G10:$G99) -> 1.0913139 | L99: =+SLOPE(D10:D99,$G10:$G99) -> 1.1195718 | M99: =+SLOPE(E10:E99,$G10:$G99) -> 1.5874727
A100: =+'Indice Bancos'!B104 -> 43427 | B100: =+'Indice Bancos'!I104 -> -0.013909967 | C100: =+'Indice Bancos'!J104 -> 0.0049735187 | D100: =+'Indice Bancos'!K104 -> 0.01248387 | E100: =+'Indice Bancos'!L104 -> 0.057852556 | G100: =+'Indice Bancos'!M104 -> -0.012400492 | I100: =+A100 -> 43427 | J100: =+SLOPE(B11:B100,$G11:$G100) -> 1.2143864 | K100: =+SLOPE(C11:C100,$G11:$G100) -> 1.0891966 | L100: =+SLOPE(D11:D100,$G11:$G100) -> 1.1170101 | M100: =+SLOPE(E11:E100,$G11:$G100) -> 1.5797111
A101: =+'Indice Bancos'!B105 -> 43434 | B101: =+'Indice Bancos'!I105 -> 0.006716745 | C101: =+'Indice Bancos'!J105 -> -0.010778897 | D101: =+'Indice Bancos'!K105 -> 0.047286267 | E101: =+'Indice Bancos'!L105 -> -0.0037462579 | G101: =+'Indice Bancos'!M105 -> 0.024707488 | I101: =+A101 -> 43434 | J101: =+SLOPE(B12:B101,$G12:$G101) -> 1.2129985 | K101: =+SLOPE(C12:C101,$G12:$G101) -> 1.0871299 | L101: =+SLOPE(D12:D101,$G12:$G101) -> 1.1208176 | M101: =+SLOPE(E12:E101,$G12:$G101) -> 1.5773643
A102: =+'Indice Bancos'!B106 -> 43441 | B102: =+'Indice Bancos'!I106 -> -0.0023285951 | C102: =+'Indice Bancos'!J106 -> -0.046215829 | D102: =+'Indice Bancos'!K106 -> 0.016682164 | E102: =+'Indice Bancos'!L106 -> 0.0052544109 | G102: =+'Indice Bancos'!M106 -> 0.0021542072 | I102: =+A102 -> 43441 | J102: =+SLOPE(B13:B102,$G13:$G102) -> 1.2113617 | K102: =+SLOPE(C13:C102,$G13:$G102) -> 1.0895954 | L102: =+SLOPE(D13:D102,$G13:$G102) -> 1.1193485 | M102: =+SLOPE(E13:E102,$G13:$G102) -> 1.5764473
A103: =+'Indice Bancos'!B107 -> 43448 | B103: =+'Indice Bancos'!I107 -> -0.034442167 | C103: =+'Indice Bancos'!J107 -> -0.0098795601 | D103: =+'Indice Bancos'!K107 -> 0.021236819 | E103: =+'Indice Bancos'!L107 -> -0.014211282 | G103: =+'Indice Bancos'!M107 -> -0.013976051 | I103: =+A103 -> 43448 | J103: =+SLOPE(B14:B103,$G14:$G103) -> 1.2133374 | K103: =+SLOPE(C14:C103,$G14:$G103) -> 1.0881294 | L103: =+SLOPE(D14:D103,$G14:$G103) -> 1.1133065 | M103: =+SLOPE(E14:E103,$G14:$G103) -> 1.5763262
... A511: =+'Indice Bancos'!B515 -> 46304 | B511: =+'Indice Bancos'!I515 -> 0.0074074074 | C511: =+'Indice Bancos'!J515 -> -0.0057142857 | D511: =+'Indice Bancos'!K515 -> 0.017994859 | E511: =+'Indice Bancos'!L515 -> 0.028901734 | G511: =+'Indice Bancos'!M515 -> 0.021810459 | I511: =+A511 -> 46304 | J511: =+SLOPE(B422:B511,$G422:$G511) -> 1.3808373 | K511: =+SLOPE(C422:C511,$G422:$G511) -> 1.2639558 | L511: =+SLOPE(D422:D511,$G422:$G511) -> 1.3253954 | M511: =+SLOPE(E422:E511,$G422:$G511) -> 1.6760156

Sheet BASE
A1: BMA AR Equity | F1: GGAL AR Equity | K1: BBAR AR Equity | P1: VALO AR Equity | AC1: =+AVERAGE(AB3:AB2000) -> 1.2128981 | AD1: =+_xlfn.STDEV.S(AB3:AB2000) -> 0.64294819
A2: Date | B2: RETURN_COM_EQY | C2: PX_TO_BOOK_RATIO | D2: PE_RATIO | E2: CUR_MKT_CAP | F2: Date | G2: RETURN_COM_EQY | H2: PX_TO_BOOK_RATIO | I2: PE_RATIO | J2: CUR_MKT_CAP | K2: Date | L2: RETURN_COM_EQY | M2: PX_TO_BOOK_RATIO | N2: PE_RATIO | O2: CUR_MKT_CAP | P2: Date | Q2: RETURN_COM_EQY | R2: PX_TO_BOOK_RATIO | S2: PE_RATIO | AA2: =+A2 -> Date | AB2: PBV Sector | AC2: Z Score | AD2: Relativo | AE2: Q90 | AF2: Q75 | AG2: Q50 | AH2: Q25 | AI2: Q10
A3: =_xll.BDH($A$1,$B$2:$E$2,"02/10/2001","","FX=ARS","Dir=V","Dts=S","Sort=A","Quote=C","QtTyp=Y","Days=T","Per=cw","DtFmt=D","UseDPDF=Y","cols=5;rows=1304") -> 37169 | B3: -80.7193 | C3: 0.1066 | D3: #N/A N/A | E3: 21.0622 | F3: =_xll.BDH($F$1,$G$2:$J$2,"02/10/2001","","FX=ARS","Dir=V","Dts=S","Sort=A","Quote=C","QtTyp=Y","Days=T","Per=cw","DtFmt=D","UseDPDF=Y","cols=5;rows=1304") -> 37169 | G3: 13.5991 | H3: 0.2712 | I3: 1.9387 | J3: 551.6654 | K3: =_xll.BDH($K$1,$L$2:$O$2,"02/10/2001","","FX=ARS","Dir=V","Dts=S","Sort=A","Quote=C","QtTyp=Y","Days=T","Per=cw","DtFmt=D","UseDPDF=Y","cols=5;rows=1304") -> 37169 | L3: 17.8185 | M3: 0.2236 | N3: 1.2198 | O3: 545.0406 | AA3: =+A3 -> 37169 | AB3: =+(C3*E3+H3*J3+M3*O3)/(E3+J3+O3) -> 0.24488795 | AC3: =+(AB3-$AC$1)/$AD$1 -> -1.5055804
A4: 37176 | B4: -80.7193 | C4: 0.1076 | D4: #N/A N/A | E4: 21.2554 | F4: 37176 | G4: 13.5991 | H4: 0.3136 | I4: 2.242 | J4: 637.9655 | K4: 37176 | L4: 17.8185 | M4: 0.2408 | N4: 1.3136 | O4: 586.9668 | AA4: =+A4 -> 37176 | AB4: =+(C4*E4+H4*J4+M4*O4)/(E4+J4+O4) -> 0.27579687 | AC4: =+(AB4-$AC$1)/$AD$1 -> -1.4575067
A5: 37183 | B5: -80.7193 | C5: 0.15 | D5: #N/A N/A | E5: 29.6288 | F5: 37183 | G5: 13.5991 | H5: 0.3598 | I5: 2.5722 | J5: 731.9125 | K5: 37183 | L5: 17.8185 | M5: 0.2735 | N5: 1.4919 | O5: 666.6266 | AA5: =+A5 -> 37183 | AB5: =+(C5*E5+H5*J5+M5*O5)/(E5+J5+O5) -> 0.31516519 | AC5: =+(AB5-$AC$1)/$AD$1 -> -1.3962757
A6: 37190 | B6: -80.7193 | C6: 0.1565 | D6: #N/A N/A | E6: 30.917 | F6: 37190 | G6: 13.5991 | H6: 0.3377 | I6: 2.4148 | J6: 687.1238 | K6: 37190 | L6: 17.8185 | M6: 0.2554 | N6: 1.3934 | O6: 622.6041 | AA6: =+A6 -> 37190 | AB6: =+(C6*E6+H6*J6+M6*O6)/(E6+J6+O6) -> 0.29530065 | AC6: =+(AB6-$AC$1)/$AD$1 -> -1.4271717
A7: 37197 | B7: -80.7193 | C7: 0.1483 | D7: #N/A N/A | E7: 29.3067 | F7: 37197 | G7: 13.5991 | H7: 0.2631 | I7: 1.8811 | J7: 535.2793 | K7: 37197 | L7: 17.8185 | M7: 0.2305 | N7: 1.2573 | O7: 561.8111 | AA7: =+A7 -> 37197 | AB7: =+(C7*E7+H7*J7+M7*O7)/(E7+J7+O7) -> 0.24385328 | AC7: =+(AB7-$AC$1)/$AD$1 -> -1.5071896
A8: 37204 | B8: -80.7193 | C8: 0.1298 | D8: #N/A N/A | E8: 25.6353 | F8: 37204 | G8: 13.5991 | H8: 0.2733 | I8: 1.9541 | J8: 556.035 | K8: 37204 | L8: 17.8185 | M8: 0.2528 | N8: 1.3793 | O8: 616.3151 | AA8: =+A8 -> 37204 | AB8: =+(C8*E8+H8*J8+M8*O8)/(E8+J8+O8) -> 0.25968287 | AC8: =+(AB8-$AC$1)/$AD$1 -> -1.4825693
A9: 37211 | B9: -80.7193 | C9: 0.1252 | D9: #N/A N/A | E9: 24.7336 | F9: 37211 | G9: 13.5991 | H9: 0.2658 | I9: 1.9003 | J9: 540.7413 | K9: 37211 | L9: 17.8185 | M9: 0.2193 | N9: 1.1963 | O9: 534.559 | AA9: =+A9 -> 37211 | AB9: =+(C9*E9+H9*J9+M9*O9)/(E9+J9+O9) -> 0.24004212 | AC9: =+(AB9-$AC$1)/$AD$1 -> -1.5131173
A10: 37218 | B10: -80.7193 | C10: #N/A N/A | D10: #N/A N/A | E10: 24.7336 | F10: 37218 | G10: 13.5991 | H10: 0.255 | I10: 1.8235 | J10: 518.8932 | K10: 37218 | L10: 17.8185 | M10: 0.2176 | N10: 1.187 | O10: 530.3664 | AA10: =+A10 -> 37218 | AB10: =+(C9*E10+H10*J10+M10*O10)/(E10+J10+O10) -> 0.23354165 | AC10: =+(AB10-$AC$1)/$AD$1 -> -1.5232277
A11: 37225 | B11: -80.7193 | C11: #N/A N/A | D11: #N/A N/A | E11: 24.7336 | F11: 37225 | G11: 13.5991 | H11: 0.2164 | I11: 1.5471 | J11: 440.2399 | K11: 37225 | L11: 17.8185 | M11: 0.2193 | N11: 1.1963 | O11: 534.559 | AA11: =+A11 -> 37225 | AB11: =+(C9*E11+H11*J11+M11*O11)/(E11+J11+O11) -> 0.21569419 | AC11: =+(AB11-$AC$1)/$AD$1 -> -1.5509865
A12: 37232 | B12: -80.7193 | C12: 0.1174 | D12: #N/A N/A | E12: 23.1877 | F12: 37232 | G12: 13.5991 | H12: 0.247 | I12: 1.766 | J12: 502.5071 | K12: 37232 | L12: 17.8185 | M12: 0.2494 | N12: 1.3605 | O12: 607.9299 | AA12: =+A12 -> 37232 | AB12: =+(C12*E12+H12*J12+M12*O12)/(E12+J12+O12) -> 0.24563615 | AC12: =+(AB12-$AC$1)/$AD$1 -> -1.5044167
A13: 37239 | B13: -80.7193 | C13: 0.1206 | D13: #N/A N/A | E13: 23.8318 | F13: 37239 | G13: 13.5991 | H13: 0.2228 | I13: 1.5932 | J13: 453.3488 | K13: 37239 | L13: 17.8185 | M13: 0.2365 | N13: 1.2902 | O13: 576.4852 | AA13: =+A13 -> 37239 | AB13: =+(C13*E13+H13*J13+M13*O13)/(E13+J13+O13) -> 0.22798403 | AC13: =+(AB13-$AC$1)/$AD$1 -> -1.5318716
A14: 37246 | B14: -80.7193 | C14: 0.1206 | D14: #N/A N/A | E14: 23.8318 | F14: 37246 | G14: 13.5991 | H14: 0.2524 | I14: 1.8043 | J14: 513.4311 | K14: 37246 | L14: 17.8185 | M14: 0.258 | N14: 1.4075 | O14: 628.893 | AA14: =+A14 -> 37246 | AB14: =+(C14*E14+H14*J14+M14*O14)/(E14+J14+O14) -> 0.25272652 | AC14: =+(AB14-$AC$1)/$AD$1 -> -1.4933888
A15: 37253 | B15: -92.054 | C15: 0.1936 | D15: #N/A N/A | E15: 23.1877 | F15: 37253 | G15: 8.7976 | H15: 0.2503 | I15: 2.6034 | J15: 504.6919 | K15: 37253 | L15: 1.3953 | M15: 0.3075 | N15: 6.0472 | O15: 618.4114 | AA15: =+A15 -> 37253 | AB15: =+(C15*E15+H15*J15+M15*O15)/(E15+J15+O15) -> 0.28001182 | AC15: =+(AB15-$AC$1)/$AD$1 -> -1.450951
A16: 37260 | B16: -92.054 | C16: 0.2043 | D16: #N/A N/A | E16: 24.4759 | F16: 37260 | G16: 8.7976 | H16: 0.2704 | I16: 2.8119 | J16: 545.1109 | K16: 37260 | L16: 1.3953 | M16: 0.3575 | N16: 7.0311 | O16: 719.0343 | AA16: =+A16 -> 37260 | AB16: =+(C16*E16+H16*J16+M16*O16)/(E16+J16+O16) -> 0.31774521 | AC16: =+(AB16-$AC$1)/$AD$1 -> -1.3922629
A17: 37274 | B17: -92.054 | C17: 0.2097 | D17: #N/A N/A | E17: 25.12 | F17: 37274 | G17: 8.7976 | H17: 0.2655 | I17: 2.7612 | J17: 535.2793 | K17: 37274 | L17: 1.3953 | M17: 0.2866 | N17: 5.6372 | O17: 576.4852 | AA17: =+A17 -> 37274 | AB17: =+(C17*E17+H17*J17+M17*O17)/(E17+J17+O17) -> 0.27496635 | AC17: =+(AB17-$AC$1)/$AD$1 -> -1.4587984
A18: 37281 | B18: -92.054 | C18: 0.2689 | D18: #N/A N/A | E18: 32.2052 | F18: 37281 | G18: 8.7976 | H18: 0.3088 | I18: 3.212 | J18: 622.6718 | K18: 37281 | L18: 1.3953 | M18: 0.3179 | N18: 6.2522 | O18: 639.3745 | AA18: =+A18 -> 37281 | AB18: =+(C18*E18+H18*J18+M18*O18)/(E18+J18+O18) -> 0.31230266 | AC18: =+(AB18-$AC$1)/$AD$1 -> -1.4007279
A19: 37288 | B19: -92.054 | C19: 0.2662 | D19: #N/A N/A | E19: 31.8831 | F19: 37288 | G19: 8.7976 | H19: 0.2763 | I19: 2.8739 | J19: 557.1274 | K19: 37288 | L19: 1.3953 | M19: 0.37 | N19: 7.2771 | O19: 744.19 | AA19: =+A19 -> 37288 | AB19: =+(C19*E19+H19*J19+M19*O19)/(E19+J19+O19) -> 0.32836162 | AC19: =+(AB19-$AC$1)/$AD$1 -> -1.3757508
A20: 37295 | B20: -92.054 | C20: 0.2097 | D20: #N/A N/A | E20: 25.12 | F20: 37295 | G20: 8.7976 | H20: 0.2357 | I20: 2.4513 | J20: 475.1969 | K20: 37295 | L20: 1.3953 | M20: 0.2971 | N20: 5.8422 | O20: 597.4483 | AA20: =+A20 -> 37295 | AB20: =+(C20*E20+H20*J20+M20*O20)/(E20+J20+O20) -> 0.26852141 | AC20: =+(AB20-$AC$1)/$AD$1 -> -1.4688224
A21: 37302 | B21: -92.054 | C21: 0.2151 | D21: #N/A N/A | E21: 25.7641 | F21: 37302 | G21: 8.7976 | H21: 0.1869 | I21: 1.9441 | J21: 376.8803 | K21: 37302 | L21: 1.3953 | M21: 0.2366 | N21: 4.6533 | O21: 475.8624 | AA21: =+A21 -> 37302 | AB21: =+(C21*E21+H21*J21+M21*O21)/(E21+J21+O21) -> 0.21464812 | AC21: =+(AB21-$AC$1)/$AD$1 -> -1.5526135
A22: 37309 | B22: -92.054 | C22: 0.2259 | D22: #N/A N/A | E22: 27.0523 | F22: 37309 | G22: 8.7976 | H22: 0.1409 | I22: 1.4651 | J22: 284.0257 | K22: 37309 | L22: 1.3953 | M22: 0.1928 | N22: 3.7923 | O22: 387.8173 | AA22: =+A22 -> 37309 | AB22: =+(C22*E22+H22*J22+M22*O22)/(E22+J22+O22) -> 0.17298945 | AC22: =+(AB22-$AC$1)/$AD$1 -> -1.6174067
A23: 37316 | B23: -92.054 | C23: 0.2285 | D23: #N/A N/A | E23: 27.3744 | F23: 37316 | G23: 8.7976 | H23: 0.2438 | I23: 2.5358 | J23: 491.583 | K23: 37316 | L23: 1.3953 | M23: 0.2408 | N23: 4.7352 | O23: 484.2476 | AA23: =+A23 -> 37316 | AB23: =+(C23*E23+H23*J23+M23*O23)/(E23+J23+O23) -> 0.24193441 | AC23: =+(AB23-$AC$1)/$AD$1 -> -1.5101741
... A26: 37337 | B26: -92.054 | C26: 0.1995 | D26: #N/A N/A | E26: 23.8962 | F26: 37337 | G26: 8.7976 | H26: 0.2319 | I26: 2.4118 | J26: 467.55 | K26: 37337 | L26: 1.3953 | M26: 0.2866 | N26: 5.6372 | O26: 576.4852 | AA26: =+A26 -> 37337 | AB26: =+(C26*E26+H26*J26+M26*O26)/(E26+J26+O26) -> 0.26070288 | AC26: =+(AB26-$AC$1)/$AD$1 -> -1.4809829
A27: 37344 | B27: 35.7337 | C27: 0.0163 | D27: 0.079 | E27: 24.1539 | F27: 37344 | G27: 8.7976 | H27: 0.227 | I27: 2.3611 | J27: 457.7184 | K27: 37344 | L27: -5.2097 | M27: 0.169 | N27: 5.4117 | O27: 549.2332 | AA27: =+A27 -> 37344 | AB27: =+(C27*E27+H27*J27+M27*O27)/(E27+J27+O27) -> 0.19116977 | AC27: =+(AB27-$AC$1)/$AD$1 -> -1.5891302
A28: 37351 | B28: 35.7337 | C28: 0.0148 | D28: 0.0716 | E28: 21.8995 | F28: 37351 | G28: 8.7976 | H28: 0.2048 | I28: 2.1301 | J28: 412.9297 | K28: 37351 | L28: -5.2097 | M28: 0.1722 | N28: #N/A N/A | O28: 559.7148 | AA28: =+A28 -> 37351 | AB28: =+(C28*E28+H28*J28+M28*O28)/(E28+J28+O28) -> 0.18226947 | AC28: =+(AB28-$AC$1)/$AD$1 -> -1.6029731
A29: 37358 | B29: 35.7337 | C29: 0.0146 | D29: 0.0703 | E29: 21.5131 | F29: 37358 | G29: 8.7976 | H29: 0.1923 | I29: 2.0005 | J29: 387.8044 | K29: 37358 | L29: -5.2097 | M29: 0.138 | N29: #N/A N/A | O29: 448.6103 | AA29: =+A29 -> 37358 | AB29: =+(C29*E29+H29*J29+M29*O29)/(E29+J29+O29) -> 0.1594506 | AC29: =+(AB29-$AC$1)/$AD$1 -> -1.6384641
A30: 37365 | B30: 35.7337 | C30: 0.0174 | D30: 0.084 | E30: 25.6997 | F30: 37365 | G30: 8.7976 | H30: 0.233 | I30: 2.4231 | J30: 469.7349 | K30: 37365 | L30: -5.2097 | M30: 0.1838 | N30: #N/A N/A | O30: 597.4483 | AA30: =+A30 -> 37365 | AB30: =+(C30*E30+H30*J30+M30*O30)/(E30+J30+O30) -> 0.2010338 | AC30: =+(AB30-$AC$1)/$AD$1 -> -1.5737883
A31: 37379 | B31: 35.7337 | C31: 0.0161 | D31: 0.0779 | E31: 23.8318 | F31: 37379 | G31: 8.7976 | H31: 0.2227 | I31: 2.316 | J31: 448.9791 | K31: 37379 | L31: -5.2097 | M31: 0.1729 | N31: #N/A N/A | O31: 561.8111 | AA31: =+A31 -> 37379 | AB31: =+(C31*E31+H31*J31+M31*O31)/(E31+J31+O31) -> 0.19089917 | AC31: =+(AB31-$AC$1)/$AD$1 -> -1.589551
A32: 37386 | B32: 35.7337 | C32: 0.0157 | D32: 0.0758 | E32: 23.1877 | F32: 37386 | G32: 8.7976 | H32: 0.2059 | I32: 2.1413 | J32: 415.1145 | K32: 37386 | L32: -5.2097 | M32: 0.1471 | N32: #N/A N/A | O32: 477.9587 | AA32: =+A32 -> 37386 | AB32: =+(C32*E32+H32*J32+M32*O32)/(E32+J32+O32) -> 0.17041418 | AC32: =+(AB32-$AC$1)/$AD$1 -> -1.6214121
A33: 37393 | B33: 35.7337 | C33: 0.0156 | D33: 0.0756 | E33: 23.1233 | F33: 37393 | G33: 8.7976 | H33: 0.1891 | I33: 1.9667 | J33: 381.2499 | K33: 37393 | L33: -5.2097 | M33: 0.1419 | N33: #N/A N/A | O33: 461.1882 | AA33: =+A33 -> 37393 | AB33: =+(C33*E33+H33*J33+M33*O33)/(E33+J33+O33) -> 0.15931589 | AC33: =+(AB33-$AC$1)/$AD$1 -> -1.6386736
A34: 37400 | B34: 35.7337 | C34: 0.0156 | D34: 0.0756 | E34: 23.1233 | F34: 37400 | G34: 8.7976 | H34: 0.1533 | I34: 1.5947 | J34: 309.1511 | K34: 37400 | L34: -5.2097 | M34: 0.1213 | N34: #N/A N/A | O34: 394.1063 | AA34: =+A34 -> 37400 | AB34: =+(C34*E34+H34*J34+M34*O34)/(E34+J34+O34) -> 0.13155454 | AC34: =+(AB34-$AC$1)/$AD$1 -> -1.6818518
A35: 37407 | B35: 35.7337 | C35: 0.0183 | D35: 0.0885 | E35: 27.0523 | F35: 37407 | G35: 8.7976 | H35: 0.1571 | I35: 1.6342 | J35: 316.7979 | K35: 37407 | L35: -5.2097 | M35: 0.1258 | N35: #N/A N/A | O35: 408.7804 | AA35: =+A35 -> 37407 | AB35: =+(C35*E35+H35*J35+M35*O35)/(E35+J35+O35) -> 0.13511088 | AC35: =+(AB35-$AC$1)/$AD$1 -> -1.6763205
A36: 37414 | B36: 35.7337 | C36: 0.0233 | D36: 0.1127 | E36: 34.4595 | F36: 37414 | G36: 8.7976 | H36: 0.1246 | I36: 1.2961 | J36: 251.2535 | K36: 37414 | L36: -5.2097 | M36: 0.1464 | N36: #N/A N/A | O36: 475.8624 | AA36: =+A36 -> 37414 | AB36: =+(C36*E36+H36*J36+M36*O36)/(E36+J36+O36) -> 0.13363791 | AC36: =+(AB36-$AC$1)/$AD$1 -> -1.6786115
A37: 37421 | B37: 35.7337 | C37: 0.0205 | D37: 0.099 | E37: 30.2729 | F37: 37421 | G37: 8.7976 | H37: 0.0786 | I37: 0.8171 | J37: 158.399 | K37: 37421 | L37: -5.2097 | M37: 0.1032 | N37: #N/A N/A | O37: 335.4096 | AA37: =+A37 -> 37421 | AB37: =+(C37*E37+H37*J37+M37*O37)/(E37+J37+O37) -> 0.090987807 | AC37: =+(AB37-$AC$1)/$AD$1 -> -1.7449467
A38: 37428 | B38: 35.7337 | C38: 0.0196 | D38: 0.0948 | E38: 28.9847 | F38: 37428 | G38: 8.7976 | H38: 0.1029 | I38: 1.0707 | J38: 207.5573 | K38: 37428 | L38: -5.2097 | M38: 0.1097 | N38: #N/A N/A | O38: 356.3727 | AA38: =+A38 -> 37428 | AB38: =+(C38*E38+H38*J38+M38*O38)/(E38+J38+O38) -> 0.10291503 | AC38: =+(AB38-$AC$1)/$AD$1 -> -1.7263959
A39: 37435 | B39: 16.1172 | C39: 0.0164 | D39: 0.1815 | E39: 29.6288 | F39: 37435 | G39: 8.7976 | H39: 0.1073 | I39: 1.1158 | J39: 216.2965 | K39: 37435 | L39: -27.7697 | M39: 0.0907 | N39: #N/A N/A | O39: 379.4321 | AA39: =+A39 -> 37435 | AB39: =+(C39*E39+H39*J39+M39*O39)/(E39+J39+O39) -> 0.092921293 | AC39: =+(AB39-$AC$1)/$AD$1 -> -1.7419395
... A66: 37624 | B66: 17.699 | C66: 0.0457 | D66: 0.4694 | E66: 94.6832 | F66: 37624 | G66: 8.7976 | H66: 0.3955 | I66: 4.1136 | J66: 797.4569 | K66: 37624 | L66: -84.1223 | M66: 0.3488 | N66: #N/A N/A | O66: 853.1982 | AA66: =+A66 -> 37624 | AB66: =+(C66*E66+H66*J66+M66*O66)/(E66+J66+O66) -> 0.35369462 | AC66: =+(AB66-$AC$1)/$AD$1 -> -1.3363495
A67: 37631 | B67: 17.699 | C67: #N/A N/A | D67: #N/A N/A | E67: 84.3776 | F67: 37631 | G67: 8.7976 | H67: 0.4335 | I67: 4.5081 | J67: 873.9253 | K67: 37631 | L67: -84.1223 | M67: 0.4328 | N67: #N/A N/A | O67: 1859.0464 | AA67: =+A67 -> 37631 | AB67: =+($C$66*E67+H67*J67+M67*O67)/(E67+J67+O67) -> 0.42142377 | AC67: =+(AB67-$AC$1)/$AD$1 -> -1.231008
A68: 37638 | B68: 17.699 | C68: #N/A N/A | D68: #N/A N/A | E68: 657.6589 | F68: 37638 | G68: 8.7976 | H68: 0.4226 | I68: 4.3954 | J68: 852.0772 | K68: 37638 | L68: -84.1223 | M68: 0.4114 | N68: #N/A N/A | O68: 1767.0144 | AA68: =+A68 -> 37638 | AB68: =+($C$66*E68+H68*J68+M68*O68)/(E68+J68+O68) -> 0.34091474 | AC68: =+(AB68-$AC$1)/$AD$1 -> -1.3562265
A69: 37645 | B69: 17.699 | C69: #N/A N/A | D69: #N/A N/A | E69: 645.48 | F69: 37645 | G69: 8.7976 | H69: 0.4009 | I69: 4.17 | J69: 808.3809 | K69: 37645 | L69: -84.1223 | M69: 0.4045 | N69: #N/A N/A | O69: 1737.5641 | AA69: =+A69 -> 37645 | AB69: =+($C$66*E69+H69*J69+M69*O69)/(E69+J69+O69) -> 0.33101922 | AC69: =+(AB69-$AC$1)/$AD$1 -> -1.3716174
A70: 37652 | B70: 17.699 | C70: #N/A N/A | D70: #N/A N/A | E70: 712.4638 | F70: 37652 | G70: 8.7976 | H70: 0.4058 | I70: 4.2207 | J70: 818.2126 | K70: 37652 | L70: -84.1223 | M70: 0.4037 | N70: #N/A N/A | O70: 1733.8828 | AA70: =+A70 -> 37652 | AB70: =+($C$66*E70+H70*J70+M70*O70)/(E70+J70+O70) -> 0.32609571 | AC70: =+(AB70-$AC$1)/$AD$1 -> -1.3792751
A71: 37659 | B71: 17.699 | C71: #N/A N/A | D71: #N/A N/A | E71: 742.911 | F71: 37659 | G71: 8.7976 | H71: 0.4009 | I71: 4.17 | J71: 808.3809 | K71: 37659 | L71: -84.1223 | M71: 0.42 | N71: #N/A N/A | O71: 1803.8272 | AA71: =+A71 -> 37659 | AB71: =+($C$66*E71+H71*J71+M71*O71)/(E71+J71+O71) -> 0.33251826 | AC71: =+(AB71-$AC$1)/$AD$1 -> -1.3692859
A72: 37666 | B72: 17.699 | C72: #N/A N/A | D72: #N/A N/A | E72: 730.7321 | F72: 37666 | G72: 8.7976 | H72: 0.4253 | I72: 4.4236 | J72: 857.5392 | K72: 37666 | L72: -84.1223 | M72: 0.4285 | N72: #N/A N/A | O72: 1840.64 | AA72: =+A72 -> 37666 | AB72: =+($C$66*E72+H72*J72+M72*O72)/(E72+J72+O72) -> 0.34612156 | AC72: =+(AB72-$AC$1)/$AD$1 -> -1.3481282
A73: 37673 | B73: 17.699 | C73: #N/A N/A | D73: #N/A N/A | E73: 785.537 | F73: 37673 | G73: 8.7976 | H73: 0.4226 | I73: 4.3954 | J73: 852.0772 | K73: 37673 | L73: -84.1223 | M73: 0.4543 | N73: #N/A N/A | O73: 1951.0784 | AA73: =+A73 -> 37673 | AB73: =+($C$66*E73+H73*J73+M73*O73)/(E73+J73+O73) -> 0.35733397 | AC73: =+(AB73-$AC$1)/$AD$1 -> -1.3306891
A74: 37680 | B74: 17.699 | C74: #N/A N/A | D74: #N/A N/A | E74: 840.3419 | F74: 37680 | G74: 8.7976 | H74: 0.4362 | I74: 4.5363 | J74: 879.3874 | K74: 37680 | L74: -84.1223 | M74: 0.4345 | N74: #N/A N/A | O74: 1866.4089 | AA74: =+A74 -> 37680 | AB74: =+($C$66*E74+H74*J74+M74*O74)/(E74+J74+O74) -> 0.34380914 | AC74: =+(AB74-$AC$1)/$AD$1 -> -1.3517248
A75: 37687 | B75: 17.699 | C75: #N/A N/A | D75: #N/A N/A | E75: 852.5208 | F75: 37687 | G75: 8.7976 | H75: 0.4064 | I75: 4.2263 | J75: 819.305 | K75: 37687 | L75: -84.1223 | M75: 0.396 | N75: #N/A N/A | O75: 1700.7513 | AA75: =+A75 -> 37687 | AB75: =+($C$66*E75+H75*J75+M75*O75)/(E75+J75+O75) -> 0.30997757 | AC75: =+(AB75-$AC$1)/$AD$1 -> -1.4043442
A76: 37694 | B76: 17.699 | C76: #N/A N/A | D76: #N/A N/A | E76: 822.0736 | F76: 37694 | G76: 8.7976 | H76: 0.3901 | I76: 4.0573 | J76: 786.5328 | K76: 37694 | L76: -84.1223 | M76: 0.3857 | N76: #N/A N/A | O76: 1656.576 | AA76: =+A76 -> 37694 | AB76: =+($C$66*E76+H76*J76+M76*O76)/(E76+J76+O76) -> 0.30115824 | AC76: =+(AB76-$AC$1)/$AD$1 -> -1.4180612
A77: 37701 | B77: 17.699 | C77: #N/A N/A | D77: #N/A N/A | E77: 870.7891 | F77: 37701 | G77: 8.7976 | H77: 0.4443 | I77: 4.6208 | J77: 895.7735 | K77: 37701 | L77: -84.1223 | M77: 0.42 | N77: #N/A N/A | O77: 1803.8272 | AA77: =+A77 -> 37701 | AB77: =+($C$66*E77+H77*J77+M77*O77)/(E77+J77+O77) -> 0.33480788 | AC77: =+(AB77-$AC$1)/$AD$1 -> -1.3657247
A78: 37708 | B78: 17.699 | C78: 0.3159 | D78: #N/A N/A | E78: 907.3257 | F78: 37708 | G78: 8.7976 | H78: 0.382 | I78: 4.5926 | J78: 873.9253 | K78: 37708 | L78: -80.7512 | M78: 0.442 | N78: #N/A N/A | O78: 1767.0144 | AA78: =+A78 -> 37708 | AB78: =+(C78*E78+H78*J78+M78*O78)/(E78+J78+O78) -> 0.39497722 | AC78: =+(AB78-$AC$1)/$AD$1 -> -1.2721412
A79: 37715 | B79: 17.699 | C79: 0.3117 | D79: #N/A N/A | E79: 895.1468 | F79: 37715 | G79: 8.7976 | H79: 0.3701 | I79: #N/A N/A | J79: 846.6152 | K79: 37715 | L79: -80.7512 | M79: 0.442 | N79: #N/A N/A | O79: 1767.0144 | AA79: =+A79 -> 37715 | AB79: =+(C79*E79+H79*J79+M79*O79)/(E79+J79+O79) -> 0.39140993 | AC79: =+(AB79-$AC$1)/$AD$1 -> -1.2776896
A80: 37722 | B80: 17.699 | C80: 0.3329 | D80: #N/A N/A | E80: 956.0412 | F80: 37722 | G80: 8.7976 | H80: 0.3653 | I80: #N/A N/A | J80: 835.6911 | K80: 37722 | L80: -80.7512 | M80: 0.4327 | N80: #N/A N/A | O80: 1730.2016 | AA80: =+A80 -> 37722 | AB80: =+(C80*E80+H80*J80+M80*O80)/(E80+J80+O80) -> 0.38961614 | AC80: =+(AB80-$AC$1)/$AD$1 -> -1.2804795
A81: 37729 | B81: 17.699 | C81: 0.3519 | D81: #N/A N/A | E81: 1010.8461 | F81: 37729 | G81: 8.7976 | H81: 0.3901 | I81: #N/A N/A | J81: 892.4962 | K81: 37729 | L81: -80.7512 | M81: 0.441 | N81: #N/A N/A | O81: 1763.3331 | AA81: =+A81 -> 37729 | AB81: =+(C81*E81+H81*J81+M81*O81)/(E81+J81+O81) -> 0.40404706 | AC81: =+(AB81-$AC$1)/$AD$1 -> -1.2580346
A82: 37736 | B82: 17.699 | C82: 0.3774 | D82: #N/A N/A | E82: 1083.9193 | F82: 37736 | G82: 8.7976 | H82: 0.4622 | I82: #N/A N/A | J82: 1057.4496 | K82: 37736 | L82: -80.7512 | M82: 0.5202 | N82: #N/A N/A | O82: 2079.9231 | AA82: =+A82 -> 37736 | AB82: =+(C82*E82+H82*J82+M82*O82)/(E82+J82+O82) -> 0.46900341 | AC82: =+(AB82-$AC$1)/$AD$1 -> -1.1570057
A83: 37743 | B83: 17.699 | C83: 0.3774 | D83: #N/A N/A | E83: 1083.9193 | F83: 37743 | G83: 8.7976 | H83: 0.4202 | I83: #N/A N/A | J83: 961.3178 | K83: 37743 | L83: -80.7512 | M83: 0.4926 | N83: #N/A N/A | O83: 1969.4848 | AA83: =+A83 -> 37743 | AB83: =+(C83*E83+H83*J83+M83*O83)/(E83+J83+O83) -> 0.44416155 | AC83: =+(AB83-$AC$1)/$AD$1 -> -1.1956431
A84: 37750 | B84: 17.699 | C84: 0.371 | D84: #N/A N/A | E84: 1065.651 | F84: 37750 | G84: 8.7976 | H84: 0.3916 | I84: #N/A N/A | J84: 895.7735 | K84: 37750 | L84: -80.7512 | M84: 0.4687 | N84: #N/A N/A | O84: 1873.7715 | AA84: =+A84 -> 37750 | AB84: =+(C84*E84+H84*J84+M84*O84)/(E84+J84+O84) -> 0.42354501 | AC84: =+(AB84-$AC$1)/$AD$1 -> -1.2277088
A85: 37757 | B85: 17.699 | C85: 0.3731 | D85: #N/A N/A | E85: 1071.7404 | F85: 37757 | G85: 8.7976 | H85: 0.4049 | I85: #N/A N/A | J85: 926.3608 | K85: 37757 | L85: -80.7512 | M85: 0.4696 | N85: #N/A N/A | O85: 1877.4528 | AA85: =+A85 -> 37757 | AB85: =+(C85*E85+H85*J85+M85*O85)/(E85+J85+O85) -> 0.427449 | AC85: =+(AB85-$AC$1)/$AD$1 -> -1.2216368
A86: 37764 | B86: 17.699 | C86: 0.3562 | D86: #N/A N/A | E86: 1023.025 | F86: 37764 | G86: 8.7976 | H86: 0.4274 | I86: #N/A N/A | J86: 977.7039 | K86: 37764 | L86: -80.7512 | M86: 0.4696 | N86: #N/A N/A | O86: 1877.4528 | AA86: =+A86 -> 37764 | AB86: =+(C86*E86+H86*J86+M86*O86)/(E86+J86+O86) -> 0.42904745 | AC86: =+(AB86-$AC$1)/$AD$1 -> -1.2191506
A87: 37771 | B87: 17.699 | C87: 0.3498 | D87: #N/A N/A | E87: 1004.7567 | F87: 37771 | G87: 8.7976 | H87: 0.4288 | I87: #N/A N/A | J87: 980.9812 | K87: 37771 | L87: -80.7512 | M87: 0.4604 | N87: #N/A N/A | O87: 1840.64 | AA87: =+A87 -> 37771 | AB87: =+(C87*E87+H87*J87+M87*O87)/(E87+J87+O87) -> 0.42325649 | AC87: =+(AB87-$AC$1)/$AD$1 -> -1.2281575
A88: 37778 | B88: 17.699 | C88: 0.3986 | D88: #N/A N/A | E88: 1144.8137 | F88: 37778 | G88: 8.7976 | H88: 0.5109 | I88: #N/A N/A | J88: 1168.8751 | K88: 37778 | L88: -80.7512 | M88: 0.5018 | N88: #N/A N/A | O88: 2006.2975 | AA88: =+A88 -> 37778 | AB88: =+(C88*E88+H88*J88+M88*O88)/(E88+J88+O88) -> 0.47691381 | AC88: =+(AB88-$AC$1)/$AD$1 -> -1.1447024
A89: 37785 | B89: 17.699 | C89: 0.424 | D89: #N/A N/A | E89: 1217.8869 | F89: 37785 | G89: 8.7976 | H89: 0.6064 | I89: #N/A N/A | J89: 1387.3564 | K89: 37785 | L89: -80.7512 | M89: 0.5985 | N89: #N/A N/A | O89: 2392.8319 | AA89: =+A89 -> 37785 | AB89: =+(C89*E89+H89*J89+M89*O89)/(E89+J89+O89) -> 0.55817225 | AC89: =+(AB89-$AC$1)/$AD$1 -> -1.0183183
A90: 37792 | B90: 17.699 | C90: 0.4452 | D90: #N/A N/A | E90: 1278.7812 | F90: 37792 | G90: 8.7976 | H90: 0.6399 | I90: #N/A N/A | J90: 1463.8249 | K90: 37792 | L90: -80.7512 | M90: 0.6077 | N90: #N/A N/A | O90: 2429.6447 | AA90: =+A90 -> 37792 | AB90: =+(C90*E90+H90*J90+M90*O90)/(E90+J90+O90) -> 0.57663678 | AC90: =+(AB90-$AC$1)/$AD$1 -> -0.98959973
... A117: 37981 | B117: 17.699 | C117: 0.5994 | D117: #N/A N/A | E117: 1747.6677 | F117: 37981 | G117: 8.7976 | H117: 0.9725 | I117: #N/A N/A | J117: 2064.6486 | K117: 37981 | L117: -26.1297 | M117: 0.8468 | N117: #N/A N/A | O117: 3309.4706 | AA117: =+A117 -> 37981 | AB117: =+(C117*E117+H117*J117+M117*O117)/(E117+J117+O117) -> 0.82252987 | AC117: =+(AB117-$AC$1)/$AD$1 -> -0.60715352
A118: 37988 | B118: 17.699 | C118: 0.8242 | D118: 4.6119 | E118: 1814.3144 | F118: 37988 | G118: 8.7976 | H118: 1.0959 | I118: #N/A N/A | J118: 2294.054 | K118: 37988 | L118: -14.6599 | M118: 0.8912 | N118: #N/A N/A | O118: 3331.5583 | AA118: =+A118 -> 37988 | AB118: =+(C118*E118+H118*J118+M118*O118)/(E118+J118+O118) -> 0.9379792 | AC118: =+(AB118-$AC$1)/$AD$1 -> -0.42759112
A119: 37995 | B119: 17.699 | C119: 0.8878 | D119: 4.9678 | E119: 1951.7871 | F119: 37995 | G119: 8.7976 | H119: 1.1533 | I119: #N/A N/A | J119: 2414.2187 | K119: 37995 | L119: -14.6599 | M119: 0.9129 | N119: #N/A N/A | O119: 3412.5465 | AA119: =+A119 -> 37995 | AB119: =+(C119*E119+H119*J119+M119*O119)/(E119+J119+O119) -> 0.98121455 | AC119: =+(AB119-$AC$1)/$AD$1 -> -0.36034564
A120: 38002 | B120: 17.699 | C120: 0.9072 | D120: 5.0761 | E120: 1993.6267 | F120: 38002 | G120: 8.7976 | H120: 1.2734 | I120: #N/A N/A | J120: 2665.4722 | K120: 38002 | L120: -14.6599 | M120: 0.9159 | N120: #N/A N/A | O120: 3423.5903 | AA120: =+A120 -> 38002 | AB120: =+(C120*E120+H120*J120+M120*O120)/(E120+J120+O120) -> 1.0316488 | AC120: =+(AB120-$AC$1)/$AD$1 -> -0.28190344
A121: 38009 | B121: 17.699 | C121: 0.8629 | D121: 4.8285 | E121: 1897.9934 | F121: 38009 | G121: 8.7976 | H121: 1.2212 | I121: #N/A N/A | J121: 2556.2316 | K121: 38009 | L121: -14.6599 | M121: 0.906 | N121: #N/A N/A | O121: 3386.7775 | AA121: =+A121 -> 38009 | AB121: =+(C121*E121+H121*J121+M121*O121)/(E121+J121+O121) -> 0.99832502 | AC121: =+(AB121-$AC$1)/$AD$1 -> -0.33373313
A122: 38016 | B122: 17.699 | C122: 0.8464 | D122: 4.7357 | E122: 1862.131 | F122: 38016 | G122: 8.7976 | H122: 1.1377 | I122: #N/A N/A | J122: 2381.4465 | K122: 38016 | L122: -14.6599 | M122: 0.8607 | N122: #N/A N/A | O122: 3217.4386 | AA122: =+A122 -> 38016 | AB122: =+(C122*E122+H122*J122+M122*O122)/(E122+J122+O122) -> 0.94554531 | AC122: =+(AB122-$AC$1)/$AD$1 -> -0.41582328
A123: 38023 | B123: 17.699 | C123: 0.7385 | D123: 4.1321 | E123: 1629.025 | F123: 38023 | G123: 8.7976 | H123: 1.0751 | I123: #N/A N/A | J123: 2250.3577 | K123: 38023 | L123: -14.6599 | M123: 0.7238 | N123: #N/A N/A | O123: 2705.7407 | AA123: =+A123 -> 38023 | AB123: =+(C123*E123+H123*J123+M123*O123)/(E123+J123+O123) -> 0.84748748 | AC123: =+(AB123-$AC$1)/$AD$1 -> -0.56833607
A124: 38030 | B124: 17.699 | C124: 0.7689 | D124: 4.3023 | E124: 1694.7728 | F124: 38030 | G124: 8.7976 | H124: 1.1533 | I124: #N/A N/A | J124: 2414.2187 | K124: 38030 | L124: -14.6599 | M124: 0.7888 | N124: #N/A N/A | O124: 2948.7052 | AA124: =+A124 -> 38030 | AB124: =+(C124*E124+H124*J124+M124*O124)/(E124+J124+O124) -> 0.90870551 | AC124: =+(AB124-$AC$1)/$AD$1 -> -0.47312151
A125: 38037 | B125: 17.699 | C125: 0.8436 | D125: 4.7202 | E125: 1856.1539 | F125: 38037 | G125: 8.7976 | H125: 1.2264 | I125: #N/A N/A | J125: 2567.1556 | K125: 38037 | L125: -14.6599 | M125: 0.8243 | N125: #N/A N/A | O125: 3081.2313 | AA125: =+A125 -> 38037 | AB125: =+(C125*E125+H125*J125+M125*O125)/(E125+J125+O125) -> 0.9666241 | AC125: =+(AB125-$AC$1)/$AD$1 -> -0.38303868
A126: 38044 | B126: 17.699 | C126: 0.9044 | D126: 5.0607 | E126: 1991.245 | F126: 38044 | G126: 8.7976 | H126: 1.2734 | I126: #N/A N/A | J126: 2665.4722 | K126: 38044 | L126: -14.6599 | M126: 0.8528 | N126: #N/A N/A | O126: 3187.9884 | AA126: =+A126 -> 38044 | AB126: =+(C126*E126+H126*J126+M126*O126)/(E126+J126+O126) -> 1.0088091 | AC126: =+(AB126-$AC$1)/$AD$1 -> -0.31742679
A127: 38051 | B127: 17.699 | C127: 0.8519 | D127: 4.7666 | E127: 1875.5458 | F127: 38051 | G127: 8.7976 | H127: 1.216 | I127: #N/A N/A | J127: 2545.3075 | K127: 38051 | L127: -14.6599 | M127: 0.8125 | N127: #N/A N/A | O127: 3037.0559 | AA127: =+A127 -> 38051 | AB127: =+(C127*E127+H127*J127+M127*O127)/(E127+J127+O127) -> 0.96011886 | AC127: =+(AB127-$AC$1)/$AD$1 -> -0.39315651
A128: 38058 | B128: 17.699 | C128: 0.9736 | D128: 5.4476 | E128: 2137.0766 | F128: 38058 | G128: 8.7976 | H128: 1.3308 | I128: #N/A N/A | J128: 2785.6369 | K128: 38058 | L128: -14.6599 | M128: 0.8578 | N128: #N/A N/A | O128: 3206.3948 | AA128: =+A128 -> 38058 | AB128: =+(C128*E128+H128*J128+M128*O128)/(E128+J128+O128) -> 1.0503278 | AC128: =+(AB128-$AC$1)/$AD$1 -> -0.2528513
A129: 38065 | B129: 17.699 | C129: 1.004 | D129: 5.6178 | E129: 2202.7121 | F129: 38065 | G129: 8.7976 | H129: 1.3308 | I129: #N/A N/A | J129: 2785.6369 | K129: 38065 | L129: -14.6599 | M129: 0.9001 | N129: #N/A N/A | O129: 3364.6898 | AA129: =+A129 -> 38065 | AB129: =+(C129*E129+H129*J129+M129*O129)/(E129+J129+O129) -> 1.0711318 | AC129: =+(AB129-$AC$1)/$AD$1 -> -0.22049411
... A182: 38436 | B182: 25.4544 | C182: 1.0756 | D182: 7.0058 | E182: 2368.79 | F182: 38436 | G182: -9.6993 | H182: 1.2271 | I182: #N/A N/A | J182: 2654.5445 | K182: 38436 | L182: -5.0268 | M182: 0.7842 | N182: #N/A N/A | O182: 2710.3257 | AA182: =+A182 -> 38436 | AB182: =+(C182*E182+H182*J182+M182*O182)/(E182+J182+O182) -> 1.0254781 | AC182: =+(AB182-$AC$1)/$AD$1 -> -0.29150092
A183: 38443 | B183: 26.2921 | C183: 1.0578 | D183: 6.5038 | E183: 2441.8632 | F183: 38443 | G183: 1.5268 | H183: 1.135 | I183: 49.6456 | J183: 2828.3414 | K183: 38443 | L183: -1.5888 | M183: 0.8529 | N183: #N/A N/A | O183: 3002.5695 | AA183: =+A183 -> 38443 | AB183: =+(C183*E183+H183*J183+M183*O183)/(E183+J183+O183) -> 1.0098259 | AC183: =+(AB183-$AC$1)/$AD$1 -> -0.31584534
A184: 38450 | B184: 26.2921 | C184: 1.0473 | D184: 6.439 | E184: 2417.5054 | F184: 38450 | G184: 1.5268 | H184: 1.1301 | I184: 49.4288 | J184: 2821.7196 | K184: 38450 | L184: -1.5888 | M184: 0.806 | N184: #N/A N/A | O184: 2837.5932 | AA184: =+A184 -> 38450 | AB184: =+(C184*E184+H184*J184+M184*O184)/(E184+J184+O184) -> 0.99145216 | AC184: =+(AB184-$AC$1)/$AD$1 -> -0.34442273
A185: 38457 | B185: 26.2921 | C185: 0.947 | D185: 5.8226 | E185: 2186.1069 | F185: 38457 | G185: 1.5268 | H185: 1.021 | I185: 44.6594 | J185: 2548.6101 | K185: 38457 | L185: -1.5888 | M185: 0.7565 | N185: #N/A N/A | O185: 2663.1896 | AA185: =+A185 -> 38457 | AB185: =+(C185*E185+H185*J185+M185*O185)/(E185+J185+O185) -> 0.90391477 | AC185: =+(AB185-$AC$1)/$AD$1 -> -0.48057271
A186: 38464 | B186: 26.2921 | C186: 0.9892 | D186: 6.0821 | E186: 2283.5379 | F186: 38464 | G186: 1.5268 | H186: 1.0656 | I186: 46.6105 | J186: 2671.9211 | K186: 38464 | L186: -1.5888 | M186: 0.8207 | N186: #N/A N/A | O186: 2889.4429 | AA186: =+A186 -> 38464 | AB186: =+(C186*E186+H186*J186+M186*O186)/(E186+J186+O186) -> 0.95315922 | AC186: =+(AB186-$AC$1)/$AD$1 -> -0.40398109
A187: 38471 | B187: 26.2921 | C187: 1.0103 | D187: 6.2119 | E187: 2332.2534 | F187: 38471 | G187: 1.5268 | H187: 1.0656 | I187: 46.6105 | J187: 2669.025 | K187: 38471 | L187: -1.5888 | M187: 0.8087 | N187: #N/A N/A | O187: 2847.0204 | AA187: =+A187 -> 38471 | AB187: =+(C187*E187+H187*J187+M187*O187)/(E187+J187+O187) -> 0.95597457 | AC187: =+(AB187-$AC$1)/$AD$1 -> -0.39960228
A188: 38478 | B188: 26.2921 | C188: 1.0421 | D188: 6.4074 | E188: 2374.8794 | F188: 38478 | G188: 1.5268 | H188: 1.14 | I188: 49.8624 | J188: 2846.5477 | K188: 38478 | L188: -1.5888 | M188: 0.8475 | N188: #N/A N/A | O188: 2983.7151 | AA188: =+A188 -> 38478 | AB188: =+(C188*E188+H188*J188+M188*O188)/(E188+J188+O188) -> 1.0052994 | AC188: =+(AB188-$AC$1)/$AD$1 -> -0.32288559
A189: 38485 | B189: 26.2921 | C189: 1.0475 | D189: 6.4402 | E189: 2387.0583 | F189: 38485 | G189: 1.5268 | H189: 1.1499 | I189: 50.296 | J189: 2534.3842 | K189: 38485 | L189: -1.5888 | M189: 0.8689 | N189: #N/A N/A | O189: 3059.1328 | AA189: =+A189 -> 38485 | AB189: =+(C189*E189+H189*J189+M189*O189)/(E189+J189+O189) -> 1.0115577 | AC189: =+(AB189-$AC$1)/$AD$1 -> -0.31315186
A190: 38492 | B190: 26.2921 | C190: 1.0582 | D190: 6.5059 | E190: 2410.9666 | F190: 38492 | G190: 1.5268 | H190: 1.1499 | I190: 50.296 | J190: 2534.3842 | K190: 38492 | L190: -1.5888 | M190: 0.8569 | N190: #N/A N/A | O190: 3016.7104 | AA190: =+A190 -> 38492 | AB190: =+(C190*E190+H190*J190+M190*O190)/(E190+J190+O190) -> 1.0111191 | AC190: =+(AB190-$AC$1)/$AD$1 -> -0.313834
A191: 38499 | B191: 26.2921 | C191: 1.0662 | D191: 6.5552 | E191: 2429.2349 | F191: 38499 | G191: 1.5268 | H191: 1.2044 | I191: 52.6807 | J191: 2654.549 | K191: 38499 | L191: -1.5888 | M191: 0.8877 | N191: #N/A N/A | O191: 3125.1234 | AA191: =+A191 -> 38499 | AB191: =+(C191*E191+H191*J191+M191*O191)/(E191+J191+O191) -> 1.0429355 | AC191: =+(AB191-$AC$1)/$AD$1 -> -0.26434882
A192: 38506 | B192: 26.2921 | C192: 1.1196 | D192: 6.8838 | E192: 2549.7876 | F192: 38506 | G192: 1.5268 | H192: 1.254 | I192: 54.8486 | J192: 2763.7897 | K192: 38506 | L192: -1.5888 | M192: 0.881 | N192: #N/A N/A | O192: 3101.5553 | AA192: =+A192 -> 38506 | AB192: =+(C192*E192+H192*J192+M192*O192)/(E192+J192+O192) -> 1.0758006 | AC192: =+(AB192-$AC$1)/$AD$1 -> -0.21323263
A193: 38513 | B193: 26.2921 | C193: 1.0689 | D193: 6.5717 | E193: 2436.2232 | F193: 38513 | G193: 1.5268 | H193: 1.1796 | I193: 51.5967 | J193: 2599.9286 | K193: 38513 | L193: -1.5888 | M193: 0.8207 | N193: #N/A N/A | O193: 2889.4429 | AA193: =+A193 -> 38513 | AB193: =+(C193*E193+H193*J193+M193*O193)/(E193+J193+O193) -> 1.0147277 | AC193: =+(AB193-$AC$1)/$AD$1 -> -0.30822145
A194: 38520 | B194: 26.2921 | C194: 1.0475 | D194: 6.4402 | E194: 2388.4065 | F194: 38520 | G194: 1.5268 | H194: 1.1895 | I194: 52.0303 | J194: 2621.7768 | K194: 38520 | L194: -1.5888 | M194: 0.8475 | N194: #N/A N/A | O194: 2983.7151 | AA194: =+A194 -> 38520 | AB194: =+(C194*E194+H194*J194+M194*O194)/(E194+J194+O194) -> 1.0194222 | AC194: =+(AB194-$AC$1)/$AD$1 -> -0.30091987
A195: 38527 | B195: 26.2921 | C195: 1.0635 | D195: 6.5388 | E195: 2424.269 | F195: 38527 | G195: 1.5268 | H195: 1.1796 | I195: 51.5967 | J195: 2599.9286 | K195: 38527 | L195: -1.5888 | M195: 0.8435 | N195: #N/A N/A | O195: 2969.5743 | AA195: =+A195 -> 38527 | AB195: =+(C195*E195+H195*J195+M195*O195)/(E195+J195+O195) -> 1.0195339 | AC195: =+(AB195-$AC$1)/$AD$1 -> -0.30074614
A196: 38534 | B196: 25.246 | C196: 0.9687 | D196: 6.3536 | E196: 2262.8879 | F196: 38534 | G196: 3.7228 | H196: 1.2241 | I196: 28.3633 | J196: 2425.1435 | K196: 38534 | L196: 1.3158 | M196: 0.7352 | N196: 67.8091 | O196: 2781.0299 | AA196: =+A196 -> 38534 | AB196: =+(C196*E196+H196*J196+M196*O196)/(E196+J196+O196) -> 0.96468493 | AC196: =+(AB196-$AC$1)/$AD$1 -> -0.38605475
A197: 38541 | B197: 25.246 | C197: 0.9739 | D197: 6.3878 | E197: 2274.8421 | F197: 38541 | G197: 3.7228 | H197: 1.2517 | I197: 29.0021 | J197: 2479.7639 | K197: 38541 | L197: 1.3158 | M197: 0.7576 | N197: 69.8779 | O197: 2865.8748 | AA197: =+A197 -> 38541 | AB197: =+(C197*E197+H197*J197+M197*O197)/(E197+J197+O197) -> 0.98295319 | AC197: =+(AB197-$AC$1)/$AD$1 -> -0.35764147
A198: 38548 | B198: 25.246 | C198: 1.0522 | D198: 6.9016 | E198: 2454.1544 | F198: 38548 | G198: 3.7228 | H198: 1.351 | I198: 31.3018 | J198: 2676.3971 | K198: 38548 | L198: 1.3158 | M198: 0.8075 | N198: 74.4751 | O198: 3054.4192 | AA198: =+A198 -> 38548 | AB198: =+(C198*E198+H198*J198+M198*O198)/(E198+J198+O198) -> 1.0585887 | AC198: =+(AB198-$AC$1)/$AD$1 -> -0.24000295
A199: 38555 | B199: 25.246 | C199: 1.081 | D199: 7.09 | E199: 2521.0258 | F199: 38555 | G199: 3.7228 | H199: 1.3565 | I199: 31.4296 | J199: 2687.3212 | K199: 38555 | L199: 1.3158 | M199: 0.8037 | N199: 74.1303 | O199: 3040.2784 | AA199: =+A199 -> 38555 | AB199: =+(C199*E199+H199*J199+M199*O199)/(E199+J199+O199) -> 1.068548 | AC199: =+(AB199-$AC$1)/$AD$1 -> -0.22451291
A200: 38562 | B200: 25.246 | C200: 1.094 | D200: 7.1756 | E200: 2551.473 | F200: 38562 | G200: 3.7228 | H200: 1.3785 | I200: 31.9406 | J200: 2731.0175 | K200: 38562 | L200: 1.3158 | M200: 0.8199 | N200: 75.6244 | O200: 3101.5553 | AA200: =+A200 -> 38562 | AB200: =+(C200*E200+H200*J200+M200*O200)/(E200+J200+O200) -> 1.0852737 | AC200: =+(AB200-$AC$1)/$AD$1 -> -0.1984988
A201: 38569 | B201: 25.246 | C201: 1.0992 | D201: 7.2099 | E201: 2563.6519 | F201: 38569 | G201: 3.7228 | H201: 1.362 | I201: 31.5573 | J201: 2698.2452 | K201: 38569 | L201: 1.3158 | M201: 0.8199 | N201: 75.6244 | O201: 3101.5553 | AA201: =+A201 -> 38569 | AB201: =+(C201*E201+H201*J201+M201*O201)/(E201+J201+O201) -> 1.0804081 | AC201: =+(AB201-$AC$1)/$AD$1 -> -0.20606649
A202: 38576 | B202: 25.246 | C202: 1.0705 | D202: 7.0215 | E202: 2498.3534 | F202: 38576 | G202: 3.7228 | H202: 1.3013 | I202: 30.152 | J202: 2578.0805 | K202: 38576 | L202: 1.3158 | M202: 0.7826 | N202: 72.1765 | O202: 2960.147 | AA202: =+A202 -> 38576 | AB202: =+(C202*E202+H202*J202+M202*O202)/(E202+J202+O202) -> 1.0384957 | AC202: =+(AB202-$AC$1)/$AD$1 -> -0.27125429
A203: 38583 | B203: 25.246 | C203: 1.0653 | D203: 6.9872 | E203: 2486.3993 | F203: 38583 | G203: 3.7228 | H203: 1.2903 | I203: 29.8964 | J203: 2904.8923 | K203: 38583 | L203: 1.3158 | M203: 0.7863 | N203: 72.5213 | O203: 2974.2879 | AA203: =+A203 -> 38583 | AB203: =+(C203*E203+H203*J203+M203*O203)/(E203+J203+O203) -> 1.0442344 | AC203: =+(AB203-$AC$1)/$AD$1 -> -0.26232858
A204: 38590 | B204: 25.246 | C204: 1.1488 | D204: 7.5352 | E204: 2677.6658 | F204: 38590 | G204: 3.7228 | H204: 1.3399 | I204: 31.0463 | J204: 3016.619 | K204: 38590 | L204: 1.3158 | M204: 0.8287 | N204: 76.4289 | O204: 3134.5506 | AA204: =+A204 -> 38590 | AB204: =+(C204*E204+H204*J204+M204*O204)/(E204+J204+O204) -> 1.1004478 | AC204: =+(AB204-$AC$1)/$AD$1 -> -0.17489799
A205: 38597 | B205: 25.246 | C205: 1.2037 | D205: 7.8949 | E205: 2805.4315 | F205: 38597 | G205: 3.7228 | H205: 1.3399 | I205: 31.0463 | J205: 3016.619 | K205: 38597 | L205: 1.3158 | M205: 0.8511 | N205: 78.4977 | O205: 3219.3956 | AA205: =+A205 -> 38597 | AB205: =+(C205*E205+H205*J205+M205*O205)/(E205+J205+O205) -> 1.1235916 | AC205: =+(AB205-$AC$1)/$AD$1 -> -0.13890153
A206: 38604 | B206: 25.246 | C206: 1.235 | D206: 8.1004 | E206: 2877.1565 | F206: 38604 | G206: 3.7228 | H206: 1.3289 | I206: 30.7908 | J206: 2991.7908 | K206: 38604 | L206: 1.3158 | M206: 0.8885 | N206: 81.9456 | O206: 3360.8039 | AA206: =+A206 -> 38604 | AB206: =+(C206*E206+H206*J206+M206*O206)/(E206+J206+O206) -> 1.1392673 | AC206: =+(AB206-$AC$1)/$AD$1 -> -0.11452069
...

Sheet PBV
B1: px book relativo
B2: FRAN/GGAL | C2: BMA/GGAL | D2: BPAT/GGAL | E2: SUPV/GGAL | F2: BMA/BBAR | G2: VALO/GGAL | H2: VALO/BMA | I2: VALO/BBAR
A3: =+BASE!A3 -> 37169 | B3: =+IFERROR(BASE!M3/BASE!H3,B2) -> 0.82448378 | C3: =+IFERROR(BASE!C3/BASE!H3,C2) -> 0.39306785 | F3: =+IFERROR(BASE!C3/BASE!M3,F2) -> 0.47674419
A4: =+BASE!A4 -> 37176 | B4: =+IFERROR(BASE!M4/BASE!H4,B3) -> 0.76785714 | C4: =+IFERROR(BASE!C4/BASE!H4,C3) -> 0.34311224 | F4: =+IFERROR(BASE!C4/BASE!M4,F3) -> 0.44684385
A5: =+BASE!A5 -> 37183 | B5: =+IFERROR(BASE!M5/BASE!H5,B4) -> 0.76014452 | C5: =+IFERROR(BASE!C5/BASE!H5,C4) -> 0.41689828 | F5: =+IFERROR(BASE!C5/BASE!M5,F4) -> 0.54844607
A6: =+BASE!A6 -> 37190 | B6: =+IFERROR(BASE!M6/BASE!H6,B5) -> 0.75629257 | C6: =+IFERROR(BASE!C6/BASE!H6,C5) -> 0.46342908 | F6: =+IFERROR(BASE!C6/BASE!M6,F5) -> 0.61276429
A7: =+BASE!A7 -> 37197 | B7: =+IFERROR(BASE!M7/BASE!H7,B6) -> 0.87609274 | C7: =+IFERROR(BASE!C7/BASE!H7,C6) -> 0.56366401 | F7: =+IFERROR(BASE!C7/BASE!M7,F6) -> 0.64338395
A8: =+BASE!A8 -> 37204 | B8: =+IFERROR(BASE!M8/BASE!H8,B7) -> 0.92499085 | C8: =+IFERROR(BASE!C8/BASE!H8,C7) -> 0.47493597 | F8: =+IFERROR(BASE!C8/BASE!M8,F7) -> 0.51344937
A9: =+BASE!A9 -> 37211 | B9: =+IFERROR(BASE!M9/BASE!H9,B8) -> 0.82505643 | C9: =+IFERROR(BASE!C9/BASE!H9,C8) -> 0.47103085 | F9: =+IFERROR(BASE!C9/BASE!M9,F8) -> 0.57090743
A10: =+BASE!A10 -> 37218 | B10: =+IFERROR(BASE!M10/BASE!H10,B9) -> 0.85333333 | C10: =+IFERROR(BASE!C10/BASE!H10,C9) -> 0.47103085 | F10: =+IFERROR(BASE!C10/BASE!M10,F9) -> 0.57090743
A11: =+BASE!A11 -> 37225 | B11: =+IFERROR(BASE!M11/BASE!H11,B10) -> 1.0134011 | C11: =+IFERROR(BASE!C11/BASE!H11,C10) -> 0.47103085 | F11: =+IFERROR(BASE!C11/BASE!M11,F10) -> 0.57090743
A12: =+BASE!A12 -> 37232 | B12: =+IFERROR(BASE!M12/BASE!H12,B11) -> 1.0097166 | C12: =+IFERROR(BASE!C12/BASE!H12,C11) -> 0.47530364 | F12: =+IFERROR(BASE!C12/BASE!M12,F11) -> 0.47072975
A13: =+BASE!A13 -> 37239 | B13: =+IFERROR(BASE!M13/BASE!H13,B12) -> 1.0614901 | C13: =+IFERROR(BASE!C13/BASE!H13,C12) -> 0.54129264 | F13: =+IFERROR(BASE!C13/BASE!M13,F12) -> 0.50993658
A14: =+BASE!A14 -> 37246 | B14: =+IFERROR(BASE!M14/BASE!H14,B13) -> 1.022187 | C14: =+IFERROR(BASE!C14/BASE!H14,C13) -> 0.477813 | F14: =+IFERROR(BASE!C14/BASE!M14,F13) -> 0.46744186
... A70: =+BASE!A70 -> 37652 | B70: =+IFERROR(BASE!M70/BASE!H70,B69) -> 0.99482504 | C70: =+IFERROR(BASE!C70/BASE!H70,C69) -> 0.11554994 | F70: =+IFERROR(BASE!C70/BASE!M70,F69) -> 0.13102064
A71: =+BASE!A71 -> 37659 | B71: =+IFERROR(BASE!M71/BASE!H71,B70) -> 1.0476428 | C71: =+IFERROR(BASE!C71/BASE!H71,C70) -> 0.11554994 | D71: =+IFERROR(BASE!R303/BASE!H71,D70) -> 0 | F71: =+IFERROR(BASE!C71/BASE!M71,F70) -> 0.13102064
A72: =+BASE!A72 -> 37666 | B72: =+IFERROR(BASE!M72/BASE!H72,B71) -> 1.0075241 | C72: =+IFERROR(BASE!C72/BASE!H72,C71) -> 0.11554994 | D72: =+IFERROR(BASE!R304/BASE!H72,D71) -> 0 | F72: =+IFERROR(BASE!C72/BASE!M72,F71) -> 0.13102064
A73: =+BASE!A73 -> 37673 | B73: =+IFERROR(BASE!M73/BASE!H73,B72) -> 1.0750118 | C73: =+IFERROR(BASE!C73/BASE!H73,C72) -> 0.11554994 | D73: =+IFERROR(BASE!R305/BASE!H73,D72) -> 0 | F73: =+IFERROR(BASE!C73/BASE!M73,F72) -> 0.13102064
A74: =+BASE!A74 -> 37680 | B74: =+IFERROR(BASE!M74/BASE!H74,B73) -> 0.99610271 | C74: =+IFERROR(BASE!C74/BASE!H74,C73) -> 0.11554994 | D74: =+IFERROR(BASE!R306/BASE!H74,D73) -> 0 | F74: =+IFERROR(BASE!C74/BASE!M74,F73) -> 0.13102064
A75: =+BASE!A75 -> 37687 | B75: =+IFERROR(BASE!M75/BASE!H75,B74) -> 0.97440945 | C75: =+IFERROR(BASE!C75/BASE!H75,C74) -> 0.11554994 | D75: =+IFERROR(BASE!R307/BASE!H75,D74) -> 0 | F75: =+IFERROR(BASE!C75/BASE!M75,F74) -> 0.13102064
A76: =+BASE!A76 -> 37694 | B76: =+IFERROR(BASE!M76/BASE!H76,B75) -> 0.98872084 | C76: =+IFERROR(BASE!C76/BASE!H76,C75) -> 0.11554994 | D76: =+IFERROR(BASE!R308/BASE!H76,D75) -> 0 | F76: =+IFERROR(BASE!C76/BASE!M76,F75) -> 0.13102064
A77: =+BASE!A77 -> 37701 | B77: =+IFERROR(BASE!M77/BASE!H77,B76) -> 0.94530722 | C77: =+IFERROR(BASE!C77/BASE!H77,C76) -> 0.11554994 | D77: =+IFERROR(BASE!R309/BASE!H77,D76) -> 0 | F77: =+IFERROR(BASE!C77/BASE!M77,F76) -> 0.13102064
A78: =+BASE!A78 -> 37708 | B78: =+IFERROR(BASE!M78/BASE!H78,B77) -> 1.1570681 | C78: =+IFERROR(BASE!C78/BASE!H78,C77) -> 0.82696335 | D78: =+IFERROR(BASE!R310/BASE!H78,D77) -> 0 | F78: =+IFERROR(BASE!C78/BASE!M78,F77) -> 0.71470588 | L78: =+(AVERAGE(B26:B78)) -> 0.86635385
A79: =+BASE!A79 -> 37715 | B79: =+IFERROR(BASE!M79/BASE!H79,B78) -> 1.1942718 | C79: =+IFERROR(BASE!C79/BASE!H79,C78) -> 0.84220481 | D79: =+IFERROR(BASE!R311/BASE!H79,D78) -> 0 | F79: =+IFERROR(BASE!C79/BASE!M79,F78) -> 0.70520362 | L79: =+(AVERAGE(B27:B79)) -> 0.86556884 | M79: =+STDEV($L$78:L79)*2+L79 -> 0.86667902 | N79: =L79-STDEV($L$78:L79)*2 -> 0.86445866
A80: =+BASE!A80 -> 37722 | B80: =+IFERROR(BASE!M80/BASE!H80,B79) -> 1.1845059 | C80: =+IFERROR(BASE!C80/BASE!H80,C79) -> 0.91130578 | D80: =+IFERROR(BASE!R312/BASE!H80,D79) -> 0 | F80: =+IFERROR(BASE!C80/BASE!M80,F79) -> 0.76935521 | L80: =+(AVERAGE(B28:B80)) -> 0.87387096 | M80: =+STDEV($L$78:L80)*2+L80 -> 0.88303787 | N80: =L80-STDEV($L$78:L80)*2 -> 0.86470405
A81: =+BASE!A81 -> 37729 | B81: =+IFERROR(BASE!M81/BASE!H81,B80) -> 1.1304794 | C81: =+IFERROR(BASE!C81/BASE!H81,C80) -> 0.90207639 | D81: =+IFERROR(BASE!R313/BASE!H81,D80) -> 0 | F81: =+IFERROR(BASE!C81/BASE!M81,F80) -> 0.79795918 | L81: =+(AVERAGE(B29:B81)) -> 0.87933623 | M81: =+STDEV($L$78:L81)*2+L81 -> 0.89242567 | N81: =L81-STDEV($L$78:L81)*2 -> 0.86624678
A82: =+BASE!A82 -> 37736 | B82: =+IFERROR(BASE!M82/BASE!H82,B81) -> 1.1254868 | C82: =+IFERROR(BASE!C82/BASE!H82,C81) -> 0.81652964 | D82: =+IFERROR(BASE!R314/BASE!H82,D81) -> 0 | F82: =+IFERROR(BASE!C82/BASE!M82,F81) -> 0.7254902 | L82: =+(AVERAGE(B30:B82)) -> 0.88703166 | M82: =+STDEV($L$78:L82)*2+L82 -> 0.90511286 | N82: =L82-STDEV($L$78:L82)*2 -> 0.86895046
A83: =+BASE!A83 -> 37743 | B83: =+IFERROR(BASE!M83/BASE!H83,B82) -> 1.1722989 | C83: =+IFERROR(BASE!C83/BASE!H83,C82) -> 0.89814374 | D83: =+IFERROR(BASE!R315/BASE!H83,D82) -> 0 | F83: =+IFERROR(BASE!C83/BASE!M83,F82) -> 0.76613886 | L83: =+(AVERAGE(B31:B83)) -> 0.89426671 | M83: =+STDEV($L$78:L83)*2+L83 -> 0.91715367 | N83: =L83-STDEV($L$78:L83)*2 -> 0.87137975
A84: =+BASE!A84 -> 37750 | B84: =+IFERROR(BASE!M84/BASE!H84,B83) -> 1.1968846 | C84: =+IFERROR(BASE!C84/BASE!H84,C83) -> 0.9473953 | D84: =+IFERROR(BASE!R316/BASE!H84,D83) -> 0 | F84: =+IFERROR(BASE!C84/BASE!M84,F83) -> 0.7915511 | L84: =+(AVERAGE(B32:B84)) -> 0.90220075 | M84: =+STDEV($L$78:L84)*2+L84 -> 0.93010177 | N84: =L84-STDEV($L$78:L84)*2 -> 0.87429972
A85: =+BASE!A85 -> 37757 | B85: =+IFERROR(BASE!M85/BASE!H85,B84) -> 1.1597925 | C85: =+IFERROR(BASE!C85/BASE!H85,C84) -> 0.92146209 | D85: =+IFERROR(BASE!R317/BASE!H85,D84) -> 0 | F85: =+IFERROR(BASE!C85/BASE!M85,F84) -> 0.79450596 | L85: =+(AVERAGE(B33:B85)) -> 0.91060392 | M85: =+STDEV($L$78:L85)*2+L85 -> 0.94374893 | N85: =L85-STDEV($L$78:L85)*2 -> 0.87745891
A86: =+BASE!A86 -> 37764 | B86: =+IFERROR(BASE!M86/BASE!H86,B85) -> 1.0987365 | C86: =+IFERROR(BASE!C86/BASE!H86,C85) -> 0.83341132 | D86: =+IFERROR(BASE!R318/BASE!H86,D85) -> 0 | F86: =+IFERROR(BASE!C86/BASE!M86,F85) -> 0.75851789 | L86: =+(AVERAGE(B34:B86)) -> 0.91717637 | M86: =+STDEV($L$78:L86)*2+L86 -> 0.95491436 | N86: =L86-STDEV($L$78:L86)*2 -> 0.87943838
A87: =+BASE!A87 -> 37771 | B87: =+IFERROR(BASE!M87/BASE!H87,B86) -> 1.073694 | C87: =+IFERROR(BASE!C87/BASE!H87,C86) -> 0.81576493 | D87: =+IFERROR(BASE!R319/BASE!H87,D86) -> 0 | F87: =+IFERROR(BASE!C87/BASE!M87,F86) -> 0.75977411 | L87: =+(AVERAGE(B35:B87)) -> 0.92250533 | M87: =+STDEV($L$78:L87)*2+L87 -> 0.9640834 | N87: =L87-STDEV($L$78:L87)*2 -> 0.88092727
A88: =+BASE!A88 -> 37778 | B88: =+IFERROR(BASE!M88/BASE!H88,B87) -> 0.9821883 | C88: =+IFERROR(BASE!C88/BASE!H88,C87) -> 0.78019182 | D88: =+IFERROR(BASE!R320/BASE!H88,D87) -> 0 | F88: =+IFERROR(BASE!C88/BASE!M88,F87) -> 0.79434037 | L88: =+(AVERAGE(B36:B88)) -> 0.92592844 | M88: =+STDEV($L$78:L88)*2+L88 -> 0.97039348 | N88: =L88-STDEV($L$78:L88)*2 -> 0.88146339
A89: =+BASE!A89 -> 37785 | B89: =+IFERROR(BASE!M89/BASE!H89,B88) -> 0.9869723 | C89: =+IFERROR(BASE!C89/BASE!H89,C88) -> 0.69920844 | D89: =+IFERROR(BASE!R321/BASE!H89,D88) -> 0 | F89: =+IFERROR(BASE!C89/BASE!M89,F88) -> 0.70843776 | L89: =+(AVERAGE(B37:B89)) -> 0.9223815 | M89: =+STDEV($L$78:L89)*2+L89 -> 0.96763165 | N89: =L89-STDEV($L$78:L89)*2 -> 0.87713135
A90: =+BASE!A90 -> 37792 | B90: =+IFERROR(BASE!M90/BASE!H90,B89) -> 0.94967964 | C90: =+IFERROR(BASE!C90/BASE!H90,C89) -> 0.69573371 | D90: =+IFERROR(BASE!R322/BASE!H90,D89) -> 0 | F90: =+IFERROR(BASE!C90/BASE!M90,F89) -> 0.73259832 | L90: =+(AVERAGE(B38:B90)) -> 0.91552683 | M90: =+STDEV($L$78:L90)*2+L90 -> 0.96001859 | N90: =L90-STDEV($L$78:L90)*2 -> 0.87103507
... A763: =+BASE!A763 -> 42503 | B763: =+IFERROR(BASE!M763/BASE!H763,B762) -> 0.84302395 | C763: =+IFERROR(BASE!C763/BASE!H763,C762) -> 0.77192843 | D763: =+IFERROR(BASE!R995/BASE!H763,D762) -> 2.2249631 | F763: =+IFERROR(BASE!C763/BASE!M763,F762) -> 0.91566607 | L763: =+(AVERAGE(B711:B763)) -> 0.94036837 | M763: =+STDEV($L$78:L763)*2+L763 -> 1.1393843 | N763: =L763-STDEV($L$78:L763)*2 -> 0.7413525
A764: =+BASE!A764 -> 42510 | B764: =+IFERROR(BASE!M764/BASE!H764,B763) -> 0.83452905 | C764: =+IFERROR(BASE!C764/BASE!H764,C763) -> 0.78409901 | D764: =+IFERROR(BASE!R996/BASE!H764,D763) -> 2.196266 | E764: =+BASE!W764/BASE!H764 -> 1.1685756 | F764: =+IFERROR(BASE!C764/BASE!M764,F763) -> 0.93957066 | L764: =+(AVERAGE(B712:B764)) -> 0.93833641 | M764: =+STDEV($L$78:L764)*2+L764 -> 1.1374301 | N764: =L764-STDEV($L$78:L764)*2 -> 0.7392427
A765: =+BASE!A765 -> 42517 | B765: =+IFERROR(BASE!M765/BASE!H765,B764) -> 0.81926838 | C765: =+IFERROR(BASE!C765/BASE!H765,C764) -> 0.75830013 | D765: =+IFERROR(BASE!R997/BASE!H765,D764) -> 2.3045595 | E765: =+IFERROR(BASE!W765/BASE!H765,E764) -> 1.1243913 | F765: =+IFERROR(BASE!C765/BASE!M765,F764) -> 0.92558208 | L765: =+(AVERAGE(B713:B765)) -> 0.93643772 | M765: =+STDEV($L$78:L765)*2+L765 -> 1.1356016 | N765: =L765-STDEV($L$78:L765)*2 -> 0.73727385
A766: =+BASE!A766 -> 42524 | B766: =+IFERROR(BASE!M766/BASE!H766,B765) -> 0.8129522 | C766: =+IFERROR(BASE!C766/BASE!H766,C765) -> 0.79974697 | D766: =+IFERROR(BASE!R998/BASE!H766,D765) -> 2.349148 | E766: =+IFERROR(BASE!W766/BASE!H766,E765) -> 1.1252125 | F766: =+IFERROR(BASE!C766/BASE!M766,F765) -> 0.98375644 | L766: =+(AVERAGE(B714:B766)) -> 0.93466469 | M766: =+STDEV($L$78:L766)*2+L766 -> 1.1338916 | N766: =L766-STDEV($L$78:L766)*2 -> 0.73543773
A767: =+BASE!A767 -> 42531 | B767: =+IFERROR(BASE!M767/BASE!H767,B766) -> 0.81252133 | C767: =+IFERROR(BASE!C767/BASE!H767,C766) -> 0.80455804 | D767: =+IFERROR(BASE!R999/BASE!H767,D766) -> 2.1948352 | E767: =+IFERROR(BASE!W767/BASE!H767,E766) -> 1.0923742 | F767: =+IFERROR(BASE!C767/BASE!M767,F766) -> 0.99019928 | L767: =+(AVERAGE(B715:B767)) -> 0.93321102 | M767: =+STDEV($L$78:L767)*2+L767 -> 1.1324952 | N767: =L767-STDEV($L$78:L767)*2 -> 0.73392679
A768: =+BASE!A768 -> 42538 | B768: =+IFERROR(BASE!M768/BASE!H768,B767) -> 0.8129491 | C768: =+IFERROR(BASE!C768/BASE!H768,C767) -> 0.80351796 | D768: =+IFERROR(BASE!R1000/BASE!H768,D767) -> 2.1968563 | E768: =+IFERROR(BASE!W768/BASE!H768,E767) -> 1.1040793 | F768: =+IFERROR(BASE!C768/BASE!M768,F767) -> 0.98839886 | L768: =+(AVERAGE(B716:B768)) -> 0.9311263 | M768: =+STDEV($L$78:L768)*2+L768 -> 1.13046 | N768: =L768-STDEV($L$78:L768)*2 -> 0.73179262
A769: =+BASE!A769 -> 42545 | B769: =+IFERROR(BASE!M769/BASE!H769,B768) -> 0.79909755 | C769: =+IFERROR(BASE!C769/BASE!H769,C768) -> 0.80468414 | D769: =+IFERROR(BASE!R1001/BASE!H769,D768) -> 2.0691162 | E769: =+IFERROR(BASE!W769/BASE!H769,E768) -> 1.1466122 | F769: =+IFERROR(BASE!C769/BASE!M769,F768) -> 1.0069911 | L769: =+(AVERAGE(B717:B769)) -> 0.92847546 | M769: =+STDEV($L$78:L769)*2+L769 -> 1.1278491 | N769: =L769-STDEV($L$78:L769)*2 -> 0.72910181
A770: =+BASE!A770 -> 42552 | B770: =+IFERROR(BASE!M770/BASE!H770,B769) -> 0.87160648 | C770: =+IFERROR(BASE!C770/BASE!H770,C769) -> 0.85764667 | D770: =+IFERROR(BASE!R1002/BASE!H770,D769) -> 2.1074905 | E770: =+IFERROR(BASE!W770/BASE!H770,E769) -> 0.76988355 | F770: =+IFERROR(BASE!C770/BASE!M770,F769) -> 0.98398382 | L770: =+(AVERAGE(B718:B770)) -> 0.92690941 | M770: =+STDEV($L$78:L770)*2+L770 -> 1.1263173 | N770: =L770-STDEV($L$78:L770)*2 -> 0.72750151
A771: =+BASE!A771 -> 42559 | B771: =+IFERROR(BASE!M771/BASE!H771,B770) -> 0.86228647 | C771: =+IFERROR(BASE!C771/BASE!H771,C770) -> 0.86941994 | D771: =+IFERROR(BASE!R1003/BASE!H771,D770) -> 1.9961705 | E771: =+IFERROR(BASE!W771/BASE!H771,E770) -> 0.75749953 | F771: =+IFERROR(BASE!C771/BASE!M771,F770) -> 1.0082727 | L771: =+(AVERAGE(B719:B771)) -> 0.92430647 | M771: =+STDEV($L$78:L771)*2+L771 -> 1.1237398 | N771: =L771-STDEV($L$78:L771)*2 -> 0.72487318
A772: =+BASE!A772 -> 42566 | B772: =+IFERROR(BASE!M772/BASE!H772,B771) -> 0.86774934 | C772: =+IFERROR(BASE!C772/BASE!H772,C771) -> 0.88972539 | D772: =+IFERROR(BASE!R1004/BASE!H772,D771) -> 2.0419445 | E772: =+IFERROR(BASE!W772/BASE!H772,E771) -> 0.76482398 | F772: =+IFERROR(BASE!C772/BASE!M772,F771) -> 1.0253253 | L772: =+(AVERAGE(B720:B772)) -> 0.92232389 | M772: =+STDEV($L$78:L772)*2+L772 -> 1.1217759 | N772: =L772-STDEV($L$78:L772)*2 -> 0.72287189
A773: =+BASE!A773 -> 42573 | B773: =+IFERROR(BASE!M773/BASE!H773,B772) -> 0.90076704 | C773: =+IFERROR(BASE!C773/BASE!H773,C772) -> 0.90484307 | D773: =+IFERROR(BASE!R1005/BASE!H773,D772) -> 0.83629155 | E773: =+IFERROR(BASE!W773/BASE!H773,E772) -> 0.80850039 | F773: =+IFERROR(BASE!C773/BASE!M773,F772) -> 1.0045251 | L773: =+(AVERAGE(B721:B773)) -> 0.92050965 | M773: =+STDEV($L$78:L773)*2+L773 -> 1.1199743 | N773: =L773-STDEV($L$78:L773)*2 -> 0.72104496
A774: =+BASE!A774 -> 42580 | B774: =+IFERROR(BASE!M774/BASE!H774,B773) -> 0.87716625 | C774: =+IFERROR(BASE!C774/BASE!H774,C773) -> 0.9052371 | D774: =+IFERROR(BASE!R1006/BASE!H774,D773) -> 0.83298419 | E774: =+IFERROR(BASE!W774/BASE!H774,E773) -> 0.83923062 | F774: =+IFERROR(BASE!C774/BASE!M774,F773) -> 1.0320017 | L774: =+(AVERAGE(B722:B774)) -> 0.91864777 | M774: =+STDEV($L$78:L774)*2+L774 -> 1.1181191 | N774: =L774-STDEV($L$78:L774)*2 -> 0.71917639
A775: =+BASE!A775 -> 42587 | B775: =+IFERROR(BASE!M775/BASE!H775,B774) -> 0.90567587 | C775: =+IFERROR(BASE!C775/BASE!H775,C774) -> 0.89985146 | D775: =+IFERROR(BASE!R1007/BASE!H775,D774) -> 0.86553045 | E775: =+IFERROR(BASE!W775/BASE!H775,E774) -> 0.8255414 | F775: =+IFERROR(BASE!C775/BASE!M775,F774) -> 0.99356899 | L775: =+(AVERAGE(B723:B775)) -> 0.91800652 | M775: =+STDEV($L$78:L775)*2+L775 -> 1.1174823 | N775: =L775-STDEV($L$78:L775)*2 -> 0.71853077
A776: =+BASE!A776 -> 42594 | B776: =+IFERROR(BASE!M776/BASE!H776,B775) -> 0.90838403 | C776: =+IFERROR(BASE!C776/BASE!H776,C775) -> 0.95805971 | D776: =+IFERROR(BASE!R1008/BASE!H776,D775) -> 0.87639499 | E776: =+IFERROR(BASE!W776/BASE!H776,E775) -> 0.85516297 | F776: =+IFERROR(BASE!C776/BASE!M776,F775) -> 1.0546858 | L776: =+(AVERAGE(B724:B776)) -> 0.91698775 | M776: =+STDEV($L$78:L776)*2+L776 -> 1.1164645 | N776: =L776-STDEV($L$78:L776)*2 -> 0.71751101
... A899: =+BASE!A899 -> 43455 | B899: =+IFERROR(BASE!M899/BASE!H899,B898) -> 0.92533971 | C899: =+IFERROR(BASE!C899/BASE!H899,C898) -> 0.64919334 | D899: =+IFERROR(BASE!R1131/BASE!H899,D898) -> 0.63540129 | E899: =+IFERROR(BASE!W899/BASE!H899,E898) -> 0.72914652 | F899: =+IFERROR(BASE!C899/BASE!M899,F898) -> 0.70157298 | L899: =+(AVERAGE(B847:B899)) -> 0.83749645 | M899: =+STDEV($L$78:L899)*2+L899 -> 1.0287099 | N899: =L899-STDEV($L$78:L899)*2 -> 0.646283
A900: =+BASE!A900 -> 43462 | B900: =+IFERROR(BASE!M900/BASE!H900,B899) -> 0.92332747 | C900: =+IFERROR(BASE!C900/BASE!H900,C899) -> 0.70308138 | D900: =+IFERROR(BASE!R1132/BASE!H900,D899) -> 0.66559818 | E900: =+IFERROR(BASE!W900/BASE!H900,E899) -> 0.78042602 | F900: =+IFERROR(BASE!C900/BASE!M900,F899) -> 0.76146481 | G900: =+IFERROR(BASE!$R900/BASE!H900,G899) -> 0.84008893 | H900: =+IFERROR(BASE!$R900/BASE!C900,H899) -> 1.1948673 | I900: =+IFERROR(BASE!$R900/BASE!M900,I899) -> 0.90984938 | L900: =+(AVERAGE(B848:B900)) -> 0.84200201 | M900: =+STDEV($L$78:L900)*2+L900 -> 1.0331096 | N900: =L900-STDEV($L$78:L900)*2 -> 0.65089441
A901: =+BASE!A901 -> 43469 | B901: =+IFERROR(BASE!M901/BASE!H901,B900) -> 0.87954631 | C901: =+IFERROR(BASE!C901/BASE!H901,C900) -> 0.67721222 | D901: =+IFERROR(BASE!R1133/BASE!H901,D900) -> 0.62593738 | E901: =+IFERROR(BASE!W901/BASE!H901,E900) -> 0.74104799 | F901: =+IFERROR(BASE!C901/BASE!M901,F900) -> 0.7699563 | G901: =+IFERROR(BASE!$R901/BASE!H901,G900) -> 0.76157668 | H901: =+IFERROR(BASE!$R901/BASE!C901,H900) -> 1.1245761 | I901: =+IFERROR(BASE!$R901/BASE!M901,I900) -> 0.86587445 | L901: =+(AVERAGE(B849:B901)) -> 0.84226084 | M901: =+STDEV($L$78:L901)*2+L901 -> 1.033263 | N901: =L901-STDEV($L$78:L901)*2 -> 0.65125874
A902: =+BASE!A902 -> 43476 | B902: =+IFERROR(BASE!M902/BASE!H902,B901) -> 0.88705736 | C902: =+IFERROR(BASE!C902/BASE!H902,C901) -> 0.71528858 | D902: =+IFERROR(BASE!R1134/BASE!H902,D901) -> 0.57866442 | E902: =+IFERROR(BASE!W902/BASE!H902,E901) -> 0.75545386 | F902: =+IFERROR(BASE!C902/BASE!M902,F901) -> 0.80636113 | G902: =+IFERROR(BASE!$R902/BASE!H902,G901) -> 0.75349891 | H902: =+IFERROR(BASE!$R902/BASE!C902,H901) -> 1.0534195 | I902: =+IFERROR(BASE!$R902/BASE!M902,I901) -> 0.84943651 | L902: =+(AVERAGE(B850:B902)) -> 0.84261968 | M902: =+STDEV($L$78:L902)*2+L902 -> 1.0335167 | N902: =L902-STDEV($L$78:L902)*2 -> 0.65172263
A903: =+BASE!A903 -> 43483 | B903: =+IFERROR(BASE!M903/BASE!H903,B902) -> 0.88632221 | C903: =+IFERROR(BASE!C903/BASE!H903,C902) -> 0.71491544 | D903: =+IFERROR(BASE!R1135/BASE!H903,D902) -> 0.54435638 | E903: =+IFERROR(BASE!W903/BASE!H903,E902) -> 0.72271436 | F903: =+IFERROR(BASE!C903/BASE!M903,F902) -> 0.80660896 | G903: =+IFERROR(BASE!$R903/BASE!H903,G902) -> 0.78023142 | H903: =+IFERROR(BASE!$R903/BASE!C903,H902) -> 1.0913618 | I903: =+IFERROR(BASE!$R903/BASE!M903,I902) -> 0.88030223 | L903: =+(AVERAGE(B851:B903)) -> 0.84317269 | M903: =+STDEV($L$78:L903)*2+L903 -> 1.0339653 | N903: =L903-STDEV($L$78:L903)*2 -> 0.65238011
A904: =+BASE!A904 -> 43490 | B904: =+IFERROR(BASE!M904/BASE!H904,B903) -> 0.8429359 | C904: =+IFERROR(BASE!C904/BASE!H904,C903) -> 0.71701528 | D904: =+IFERROR(BASE!R1136/BASE!H904,D903) -> 0.55317537 | E904: =+IFERROR(BASE!W904/BASE!H904,E903) -> 0.69803459 | F904: =+IFERROR(BASE!C904/BASE!M904,F903) -> 0.85061661 | G904: =+IFERROR(BASE!$R904/BASE!H904,G903) -> 0.79807247 | H904: =+IFERROR(BASE!$R904/BASE!C904,H903) -> 1.1130481 | I904: =+IFERROR(BASE!$R904/BASE!M904,I903) -> 0.94677717 | L904: =+(AVERAGE(B852:B904)) -> 0.84331479 | M904: =+STDEV($L$78:L904)*2+L904 -> 1.0340032 | N904: =L904-STDEV($L$78:L904)*2 -> 0.6526264
A905: =+BASE!A905 -> 43497 | B905: =+IFERROR(BASE!M905/BASE!H905,B904) -> 0.84091633 | C905: =+IFERROR(BASE!C905/BASE!H905,C904) -> 0.71378486 | D905: =+IFERROR(BASE!R1137/BASE!H905,D904) -> 0.52007968 | E905: =+IFERROR(BASE!W905/BASE!H905,E904) -> 0.75629482 | F905: =+IFERROR(BASE!C905/BASE!M905,F904) -> 0.84881793 | G905: =+IFERROR(BASE!$R905/BASE!H905,G904) -> 0.75549801 | H905: =+IFERROR(BASE!$R905/BASE!C905,H904) -> 1.0584394 | I905: =+IFERROR(BASE!$R905/BASE!M905,I904) -> 0.89842232 | L905: =+(AVERAGE(B853:B905)) -> 0.84251679 | M905: =+STDEV($L$78:L905)*2+L905 -> 1.0331006 | N905: =L905-STDEV($L$78:L905)*2 -> 0.65193302
A906: =+BASE!A906 -> 43504 | B906: =+IFERROR(BASE!M906/BASE!H906,B905) -> 0.83280992 | C906: =+IFERROR(BASE!C906/BASE!H906,C905) -> 0.70640653 | D906: =+IFERROR(BASE!R1138/BASE!H906,D905) -> 0.51244406 | E906: =+IFERROR(BASE!W906/BASE!H906,E905) -> 0.77090367 | F906: =+IFERROR(BASE!C906/BASE!M906,F905) -> 0.8482206 | G906: =+IFERROR(BASE!$R906/BASE!H906,G905) -> 0.73109837 | H906: =+IFERROR(BASE!$R906/BASE!C906,H905) -> 1.0349542 | I906: =+IFERROR(BASE!$R906/BASE!M906,I905) -> 0.87786943 | L906: =+(AVERAGE(B854:B906)) -> 0.84239006 | M906: =+STDEV($L$78:L906)*2+L906 -> 1.0328693 | N906: =L906-STDEV($L$78:L906)*2 -> 0.65191083
A907: =+BASE!A907 -> 43511 | B907: =+IFERROR(BASE!M907/BASE!H907,B906) -> 0.82472266 | C907: =+IFERROR(BASE!C907/BASE!H907,C906) -> 0.72492076 | D907: =+IFERROR(BASE!R1139/BASE!H907,D906) -> 0.52080032 | E907: =+IFERROR(BASE!W907/BASE!H907,E906) -> 0.77004754 | F907: =+IFERROR(BASE!C907/BASE!M907,F906) -> 0.87898732 | G907: =+IFERROR(BASE!$R907/BASE!H907,G906) -> 0.81604596 | H907: =+IFERROR(BASE!$R907/BASE!C907,H906) -> 1.1257037 | I907: =+IFERROR(BASE!$R907/BASE!M907,I906) -> 0.98947925 | L907: =+(AVERAGE(B855:B907)) -> 0.84196686 | M907: =+STDEV($L$78:L907)*2+L907 -> 1.0323414 | N907: =L907-STDEV($L$78:L907)*2 -> 0.65159232
A908: =+BASE!A908 -> 43518 | B908: =+IFERROR(BASE!M908/BASE!H908,B907) -> 0.81051523 | C908: =+IFERROR(BASE!C908/BASE!H908,C907) -> 0.71075016 | D908: =+IFERROR(BASE!R1140/BASE!H908,D907) -> 0.52997408 | E908: =+IFERROR(BASE!W908/BASE!H908,E907) -> 0.75056708 | F908: =+IFERROR(BASE!C908/BASE!M908,F907) -> 0.87691154 | G908: =+IFERROR(BASE!$R908/BASE!H908,G907) -> 0.88549093 | H908: =+IFERROR(BASE!$R908/BASE!C908,H907) -> 1.245854 | I908: =+IFERROR(BASE!$R908/BASE!M908,I907) -> 1.0925037 | L908: =+(AVERAGE(B856:B908)) -> 0.84109657 | M908: =+STDEV($L$78:L908)*2+L908 -> 1.031366 | N908: =L908-STDEV($L$78:L908)*2 -> 0.65082715
A909: =+BASE!A909 -> 43525 | B909: =+IFERROR(BASE!M909/BASE!H909,B908) -> 0.81243745 | C909: =+IFERROR(BASE!C909/BASE!H909,C908) -> 0.70712401 | D909: =+IFERROR(BASE!R1141/BASE!H909,D908) -> 0.58279501 | E909: =+IFERROR(BASE!W909/BASE!H909,E908) -> 0.72686744 | F909: =+IFERROR(BASE!C909/BASE!M909,F908) -> 0.87037348 | G909: =+IFERROR(BASE!$R909/BASE!H909,G908) -> 0.94823037 | H909: =+IFERROR(BASE!$R909/BASE!C909,H908) -> 1.3409676 | I909: =+IFERROR(BASE!$R909/BASE!M909,I908) -> 1.1671426 | L909: =+(AVERAGE(B857:B909)) -> 0.84003197 | M909: =+STDEV($L$78:L909)*2+L909 -> 1.0301957 | N909: =L909-STDEV($L$78:L909)*2 -> 0.64986824
A910: =+BASE!A910 -> 43532 | B910: =+IFERROR(BASE!M910/BASE!H910,B909) -> 0.89589691 | C910: =+IFERROR(BASE!C910/BASE!H910,C909) -> 0.73811946 | D910: =+IFERROR(BASE!R1142/BASE!H910,D909) -> 0.71830645 | E910: =+IFERROR(BASE!W910/BASE!H910,E909) -> 0.73356586 | F910: =+IFERROR(BASE!C910/BASE!M910,F909) -> 0.82388883 | G910: =+IFERROR(BASE!$R910/BASE!H910,G909) -> 0.95146054 | H910: =+IFERROR(BASE!$R910/BASE!C910,H909) -> 1.2890333 | I910: =+IFERROR(BASE!$R910/BASE!M910,I909) -> 1.0620201 | L910: =+(AVERAGE(B858:B910)) -> 0.84076725 | M910: =+STDEV($L$78:L910)*2+L910 -> 1.030826 | N910: =L910-STDEV($L$78:L910)*2 -> 0.65070853
A911: =+BASE!A911 -> 43539 | B911: =+IFERROR(BASE!M911/BASE!H911,B910) -> 0.85943908 | C911: =+IFERROR(BASE!C911/BASE!H911,C910) -> 0.77860005 | D911: =+IFERROR(BASE!R1143/BASE!H911,D910) -> 0.77963705 | E911: =+IFERROR(BASE!W911/BASE!H911,E910) -> 0.68682536 | F911: =+IFERROR(BASE!C911/BASE!M911,F910) -> 0.90593978 | G911: =+IFERROR(BASE!$R911/BASE!H911,G910) -> 0.97958991 | H911: =+IFERROR(BASE!$R911/BASE!C911,H910) -> 1.2581426 | I911: =+IFERROR(BASE!$R911/BASE!M911,I910) -> 1.1398015 | L911: =+(AVERAGE(B859:B911)) -> 0.84150369 | M911: =+STDEV($L$78:L911)*2+L911 -> 1.0314581 | N911: =L911-STDEV($L$78:L911)*2 -> 0.65154929
... A1003: =+BASE!A1003 -> 44183 | B1003: =+IFERROR(BASE!M1003/BASE!H1003,B1002) -> 0.70022939 | C1003: =+IFERROR(BASE!C1003/BASE!H1003,C1002) -> 0.9735603 | D1003: =+IFERROR(BASE!R1235/BASE!H1003,D1002) -> 2.0054328 | E1003: =+IFERROR(BASE!W1003/BASE!H1003,E1002) -> 0.93130508 | F1003: =+IFERROR(BASE!C1003/BASE!M1003,F1002) -> 1.3903448 | G1003: =+IFERROR(BASE!$R1003/BASE!H1003,G1002) -> 6.4189303 | H1003: =+IFERROR(BASE!$R1003/BASE!C1003,H1002) -> 6.593254 | I1003: =+IFERROR(BASE!$R1003/BASE!M1003,I1002) -> 9.1668966 | L1003: =+(AVERAGE(B951:B1003)) -> 0.65186396 | M1003: =+STDEV($L$78:L1003)*2+L1003 -> 0.85108877 | N1003: =L1003-STDEV($L$78:L1003)*2 -> 0.45263914
A1004: =+BASE!A1004 -> 44190 | B1004: =+IFERROR(BASE!M1004/BASE!H1004,B1003) -> 0.71924068 | C1004: =+IFERROR(BASE!C1004/BASE!H1004,C1003) -> 0.93824701 | D1004: =+IFERROR(BASE!#REF!/BASE!H1004,D1003) -> 2.0054328 | E1004: =+IFERROR(BASE!W1004/BASE!H1004,E1003) -> 0.93648934 | F1004: =+IFERROR(BASE!C1004/BASE!M1004,F1003) -> 1.3044966 | G1004: =+IFERROR(BASE!$R1004/BASE!H1004,G1003) -> 6.6742442 | H1004: =+IFERROR(BASE!$R1004/BASE!C1004,H1003) -> 7.1135257 | I1004: =+IFERROR(BASE!$R1004/BASE!M1004,I1003) -> 9.2795699 | L1004: =+(AVERAGE(B952:B1004)) -> 0.65258675 | M1004: =+STDEV($L$78:L1004)*2+L1004 -> 0.85194846 | N1004: =L1004-STDEV($L$78:L1004)*2 -> 0.45322503
A1005: =+BASE!A1005 -> 44197 | B1005: =+IFERROR(BASE!M1005/BASE!H1005,B1004) -> 0.83928571 | C1005: =+IFERROR(BASE!C1005/BASE!H1005,C1004) -> 0.95674603 | D1005: =+IFERROR(BASE!#REF!/BASE!H1005,D1004) -> 2.0054328 | E1005: =+IFERROR(BASE!W1005/BASE!H1005,E1004) -> 0.95357143 | F1005: =+IFERROR(BASE!C1005/BASE!M1005,F1004) -> 1.1399527 | G1005: =+IFERROR(BASE!$R1005/BASE!H1005,G1004) -> 4.4779762 | H1005: =+IFERROR(BASE!$R1005/BASE!C1005,H1004) -> 4.6804231 | I1005: =+IFERROR(BASE!$R1005/BASE!M1005,I1004) -> 5.335461 | L1005: =+(AVERAGE(B953:B1005)) -> 0.65513436 | M1005: =+STDEV($L$78:L1005)*2+L1005 -> 0.85462387 | N1005: =L1005-STDEV($L$78:L1005)*2 -> 0.45564486
A1006: =+BASE!A1006 -> 44204 | B1006: =+IFERROR(BASE!M1006/BASE!H1006,B1005) -> 0.8049227 | C1006: =+IFERROR(BASE!C1006/BASE!H1006,C1005) -> 0.95606184 | D1006: =+IFERROR(BASE!#REF!/BASE!H1006,D1005) -> 2.0054328 | E1006: =+IFERROR(BASE!W1006/BASE!H1006,E1005) -> 0.93144833 | F1006: =+IFERROR(BASE!C1006/BASE!M1006,F1005) -> 1.1877685 | G1006: =+IFERROR(BASE!$R1006/BASE!H1006,G1005) -> 4.4487388 | H1006: =+IFERROR(BASE!$R1006/BASE!C1006,H1005) -> 4.6531915 | I1006: =+IFERROR(BASE!$R1006/BASE!M1006,I1005) -> 5.5269143 | L1006: =+(AVERAGE(B954:B1006)) -> 0.6624461 | M1006: =+STDEV($L$78:L1006)*2+L1006 -> 0.86203987 | N1006: =L1006-STDEV($L$78:L1006)*2 -> 0.46285234
A1007: =+BASE!A1007 -> 44211 | B1007: =+IFERROR(BASE!M1007/BASE!H1007,B1006) -> 0.82564422 | C1007: =+IFERROR(BASE!C1007/BASE!H1007,C1006) -> 0.94201995 | D1007: =+IFERROR(BASE!#REF!/BASE!H1007,D1006) -> 2.0054328 | E1007: =+IFERROR(BASE!W1007/BASE!H1007,E1006) -> 0.92040732 | F1007: =+IFERROR(BASE!C1007/BASE!M1007,F1006) -> 1.1409514 | G1007: =+IFERROR(BASE!$R1007/BASE!H1007,G1006) -> 4.6014131 | H1007: =+IFERROR(BASE!$R1007/BASE!C1007,H1006) -> 4.8846239 | I1007: =+IFERROR(BASE!$R1007/BASE!M1007,I1006) -> 5.5731186 | L1007: =+(AVERAGE(B955:B1007)) -> 0.66976334 | M1007: =+STDEV($L$78:L1007)*2+L1007 -> 0.86943915 | N1007: =L1007-STDEV($L$78:L1007)*2 -> 0.47008752
A1008: =+BASE!A1008 -> 44218 | B1008: =+IFERROR(BASE!M1008/BASE!H1008,B1007) -> 0.83917935 | C1008: =+IFERROR(BASE!C1008/BASE!H1008,C1007) -> 0.95477609 | D1008: =+IFERROR(BASE!#REF!/BASE!H1008,D1007) -> 2.0054328 | E1008: =+IFERROR(BASE!W1008/BASE!H1008,E1007) -> 0.94661372 | F1008: =+IFERROR(BASE!C1008/BASE!M1008,F1007) -> 1.1377497 | G1008: =+IFERROR(BASE!$R1008/BASE!H1008,G1007) -> 4.7988087 | H1008: =+IFERROR(BASE!$R1008/BASE!C1008,H1007) -> 5.0261091 | I1008: =+IFERROR(BASE!$R1008/BASE!M1008,I1007) -> 5.7184543 | L1008: =+(AVERAGE(B956:B1008)) -> 0.67733753 | M1008: =+STDEV($L$78:L1008)*2+L1008 -> 0.87707381 | N1008: =L1008-STDEV($L$78:L1008)*2 -> 0.47760125
A1009: =+BASE!A1009 -> 44225 | B1009: =+IFERROR(BASE!M1009/BASE!H1009,B1008) -> 0.83178779 | C1009: =+IFERROR(BASE!C1009/BASE!H1009,C1008) -> 0.93185249 | D1009: =+IFERROR(BASE!#REF!/BASE!H1009,D1008) -> 2.0054328 | E1009: =+IFERROR(BASE!W1009/BASE!H1009,E1008) -> 0.88979944 | F1009: =+IFERROR(BASE!C1009/BASE!M1009,F1008) -> 1.1203008 | G1009: =+IFERROR(BASE!$R1009/BASE!H1009,G1008) -> 4.5488462 | H1009: =+IFERROR(BASE!$R1009/BASE!C1009,H1008) -> 4.8815089 | I1009: =+IFERROR(BASE!$R1009/BASE!M1009,I1008) -> 5.4687581 | L1009: =+(AVERAGE(B957:B1009)) -> 0.68515939 | M1009: =+STDEV($L$78:L1009)*2+L1009 -> 0.88493532 | N1009: =L1009-STDEV($L$78:L1009)*2 -> 0.48538347
A1010: =+BASE!A1010 -> 44232 | B1010: =+IFERROR(BASE!M1010/BASE!H1010,B1009) -> 0.81079478 | C1010: =+IFERROR(BASE!C1010/BASE!H1010,C1009) -> 0.92941874 | D1010: =+IFERROR(BASE!#REF!/BASE!H1010,D1009) -> 2.0054328 | E1010: =+IFERROR(BASE!W1010/BASE!H1010,E1009) -> 0.8742586 | F1010: =+IFERROR(BASE!C1010/BASE!M1010,F1009) -> 1.1463058 | G1010: =+IFERROR(BASE!$R1010/BASE!H1010,G1009) -> 4.3621985 | H1010: =+IFERROR(BASE!$R1010/BASE!C1010,H1009) -> 4.6934695 | I1010: =+IFERROR(BASE!$R1010/BASE!M1010,I1009) -> 5.3801512 | L1010: =+(AVERAGE(B958:B1010)) -> 0.69280833 | M1010: =+STDEV($L$78:L1010)*2+L1010 -> 0.89260496 | N1010: =L1010-STDEV($L$78:L1010)*2 -> 0.4930117
A1011: =+BASE!A1011 -> 44239 | B1011: =+IFERROR(BASE!M1011/BASE!H1011,B1010) -> 0.81426269 | C1011: =+IFERROR(BASE!C1011/BASE!H1011,C1010) -> 0.9540693 | D1011: =+IFERROR(BASE!#REF!/BASE!H1011,D1010) -> 2.0054328 | E1011: =+IFERROR(BASE!W1011/BASE!H1011,E1010) -> 0.88839645 | F1011: =+IFERROR(BASE!C1011/BASE!M1011,F1010) -> 1.1716972 | G1011: =+IFERROR(BASE!$R1011/BASE!H1011,G1010) -> 4.2101128 | H1011: =+IFERROR(BASE!$R1011/BASE!C1011,H1010) -> 4.4127956 | I1011: =+IFERROR(BASE!$R1011/BASE!M1011,I1010) -> 5.1704602 | L1011: =+(AVERAGE(B959:B1011)) -> 0.70041051 | M1011: =+STDEV($L$78:L1011)*2+L1011 -> 0.90021037 | N1011: =L1011-STDEV($L$78:L1011)*2 -> 0.50061065
A1012: =+BASE!A1012 -> 44246 | B1012: =+IFERROR(BASE!M1012/BASE!H1012,B1011) -> 0.79546351 | C1012: =+IFERROR(BASE!C1012/BASE!H1012,C1011) -> 0.92721893 | D1012: =+IFERROR(BASE!#REF!/BASE!H1012,D1011) -> 2.0054328 | E1012: =+IFERROR(BASE!W1012/BASE!H1012,E1011) -> 1.0185404 | F1012: =+IFERROR(BASE!C1012/BASE!M1012,F1011) -> 1.1656335 | G1012: =+IFERROR(BASE!$R1012/BASE!H1012,G1011) -> 3.930572 | H1012: =+IFERROR(BASE!$R1012/BASE!C1012,H1011) -> 4.2390981 | I1012: =+IFERROR(BASE!$R1012/BASE!M1012,I1011) -> 4.9412348 | L1012: =+(AVERAGE(B960:B1012)) -> 0.70793 | M1012: =+STDEV($L$78:L1012)*2+L1012 -> 0.90771713 | N1012: =L1012-STDEV($L$78:L1012)*2 -> 0.50814287
A1013: =+BASE!A1013 -> 44253 | B1013: =+IFERROR(BASE!M1013/BASE!H1013,B1012) -> 0.82392027 | C1013: =+IFERROR(BASE!C1013/BASE!H1013,C1012) -> 0.9517165 | D1013: =+IFERROR(BASE!#REF!/BASE!H1013,D1012) -> 2.0054328 | E1013: =+IFERROR(BASE!W1013/BASE!H1013,E1012) -> 0.9683278 | F1013: =+IFERROR(BASE!C1013/BASE!M1013,F1012) -> 1.1551075 | G1013: =+IFERROR(BASE!$R1013/BASE!H1013,G1012) -> 4.413732 | H1013: =+IFERROR(BASE!$R1013/BASE!C1013,H1012) -> 4.6376542 | I1013: =+IFERROR(BASE!$R1013/BASE!M1013,I1012) -> 5.3569892 | L1013: =+(AVERAGE(B961:B1013)) -> 0.7158632 | M1013: =+STDEV($L$78:L1013)*2+L1013 -> 0.91562221 | N1013: =L1013-STDEV($L$78:L1013)*2 -> 0.5161042
A1014: =+BASE!A1014 -> 44260 | B1014: =+IFERROR(BASE!M1014/BASE!H1014,B1013) -> 0.81679909 | C1014: =+IFERROR(BASE!C1014/BASE!H1014,C1013) -> 0.96345062 | D1014: =+IFERROR(BASE!#REF!/BASE!H1014,D1013) -> 2.0054328 | E1014: =+IFERROR(BASE!W1014/BASE!H1014,E1013) -> 0.95482406 | F1014: =+IFERROR(BASE!C1014/BASE!M1014,F1013) -> 1.1795442 | G1014: =+IFERROR(BASE!$R1014/BASE!H1014,G1013) -> 4.3650397 | H1014: =+IFERROR(BASE!$R1014/BASE!C1014,H1013) -> 4.5306315 | I1014: =+IFERROR(BASE!$R1014/BASE!M1014,I1013) -> 5.34408 | L1014: =+(AVERAGE(B962:B1014)) -> 0.72359438 | M1014: =+STDEV($L$78:L1014)*2+L1014 -> 0.92331162 | N1014: =L1014-STDEV($L$78:L1014)*2 -> 0.52387714
A1015: =+BASE!A1015 -> 44267 | B1015: =+IFERROR(BASE!M1015/BASE!H1015,B1014) -> 0.81827687 | C1015: =+IFERROR(BASE!C1015/BASE!H1015,C1014) -> 0.95838561 | D1015: =+IFERROR(BASE!#REF!/BASE!H1015,D1014) -> 2.0054328 | E1015: =+IFERROR(BASE!W1015/BASE!H1015,E1014) -> 0.90046006 | F1015: =+IFERROR(BASE!C1015/BASE!M1015,F1014) -> 1.1712241 | G1015: =+IFERROR(BASE!$R1015/BASE!H1015,G1014) -> 3.9642409 | H1015: =+IFERROR(BASE!$R1015/BASE!C1015,H1014) -> 4.1363736 | I1015: =+IFERROR(BASE!$R1015/BASE!M1015,I1014) -> 4.8446205 | L1015: =+(AVERAGE(B963:B1015)) -> 0.73108069 | M1015: =+STDEV($L$78:L1015)*2+L1015 -> 0.93074425 | N1015: =L1015-STDEV($L$78:L1015)*2 -> 0.53141713
... A1306: =+BASE!A1306 -> 46304 | B1306: =+IFERROR(BASE!M1306/BASE!H1306,B1305) -> 0.95931746 | C1306: =+IFERROR(BASE!C1306/BASE!H1306,C1305) -> 1.0228478 | D1306: =+IFERROR(BASE!#REF!/BASE!H1306,D1305) -> 2.0054328 | E1306: =+IFERROR(BASE!W1306/BASE!H1306,E1305) -> 0.83659501 | F1306: =+IFERROR(BASE!C1306/BASE!M1306,F1305) -> 1.0662245 | G1306: =+IFERROR(BASE!$R1306/BASE!H1306,G1305) -> 1.4080787 | H1306: =+IFERROR(BASE!$R1306/BASE!C1306,H1305) -> 1.3766258 | I1306: =+IFERROR(BASE!$R1306/BASE!M1306,I1305) -> 1.4677922 | L1306: =+(AVERAGE(B1254:B1306)) -> 0.9758691 | M1306: =+STDEV($L$78:L1306)*2+L1306 -> 1.173869 | N1306: =L1306-STDEV($L$78:L1306)*2 -> 0.77786924

Sheet ROE
B1: ROE
B2: FRAN/GGAL | C2: BMA/GGAL | D2: BPAT/GGAL | E2: SUPV/GGAL | F2: BMA/BBAR
A3: =+BASE!A3 -> 37169 | B3: =+IFERROR(VLOOKUP(A3,BASE!K:M,3,0)/VLOOKUP(ROE!A3,BASE!F:H,3,0),B2) -> 0.82448378 | C3: =+IFERROR(VLOOKUP(A3,BASE!A:C,3,0)/VLOOKUP(ROE!A3,BASE!F:H,3,0),C2) -> 0.39306785 | F3: =+IFERROR(VLOOKUP(A3,BASE!A:C,3,0)/VLOOKUP(A3,BASE!K:M,3,0),F2) -> 0.47674419
A4: =+BASE!A4 -> 37176 | B4: =+IFERROR(VLOOKUP(A4,BASE!K:M,3,0)/VLOOKUP(ROE!A4,BASE!F:H,3,0),B3) -> 0.76785714 | C4: =+IFERROR(VLOOKUP(A4,BASE!A:C,3,0)/VLOOKUP(ROE!A4,BASE!F:H,3,0),C3) -> 0.34311224 | F4: =+IFERROR(VLOOKUP(A4,BASE!A:C,3,0)/VLOOKUP(A4,BASE!K:M,3,0),F3) -> 0.44684385
A5: =+BASE!A5 -> 37183 | B5: =+IFERROR(VLOOKUP(A5,BASE!K:M,3,0)/VLOOKUP(ROE!A5,BASE!F:H,3,0),B4) -> 0.76014452 | C5: =+IFERROR(VLOOKUP(A5,BASE!A:C,3,0)/VLOOKUP(ROE!A5,BASE!F:H,3,0),C4) -> 0.41689828 | F5: =+IFERROR(VLOOKUP(A5,BASE!A:C,3,0)/VLOOKUP(A5,BASE!K:M,3,0),F4) -> 0.54844607
A6: =+BASE!A6 -> 37190 | B6: =+IFERROR(VLOOKUP(A6,BASE!K:M,3,0)/VLOOKUP(ROE!A6,BASE!F:H,3,0),B5) -> 0.75629257 | C6: =+IFERROR(VLOOKUP(A6,BASE!A:C,3,0)/VLOOKUP(ROE!A6,BASE!F:H,3,0),C5) -> 0.46342908 | F6: =+IFERROR(VLOOKUP(A6,BASE!A:C,3,0)/VLOOKUP(A6,BASE!K:M,3,0),F5) -> 0.61276429
A7: =+BASE!A7 -> 37197 | B7: =+IFERROR(VLOOKUP(A7,BASE!K:M,3,0)/VLOOKUP(ROE!A7,BASE!F:H,3,0),B6) -> 0.87609274 | C7: =+IFERROR(VLOOKUP(A7,BASE!A:C,3,0)/VLOOKUP(ROE!A7,BASE!F:H,3,0),C6) -> 0.56366401 | F7: =+IFERROR(VLOOKUP(A7,BASE!A:C,3,0)/VLOOKUP(A7,BASE!K:M,3,0),F6) -> 0.64338395
A8: =+BASE!A8 -> 37204 | B8: =+IFERROR(VLOOKUP(A8,BASE!K:M,3,0)/VLOOKUP(ROE!A8,BASE!F:H,3,0),B7) -> 0.92499085 | C8: =+IFERROR(VLOOKUP(A8,BASE!A:C,3,0)/VLOOKUP(ROE!A8,BASE!F:H,3,0),C7) -> 0.47493597 | F8: =+IFERROR(VLOOKUP(A8,BASE!A:C,3,0)/VLOOKUP(A8,BASE!K:M,3,0),F7) -> 0.51344937
A9: =+BASE!A9 -> 37211 | B9: =+IFERROR(VLOOKUP(A9,BASE!K:M,3,0)/VLOOKUP(ROE!A9,BASE!F:H,3,0),B8) -> 0.82505643 | C9: =+IFERROR(VLOOKUP(A9,BASE!A:C,3,0)/VLOOKUP(ROE!A9,BASE!F:H,3,0),C8) -> 0.47103085 | F9: =+IFERROR(VLOOKUP(A9,BASE!A:C,3,0)/VLOOKUP(A9,BASE!K:M,3,0),F8) -> 0.57090743
A10: =+BASE!A10 -> 37218 | B10: =+IFERROR(VLOOKUP(A10,BASE!K:M,3,0)/VLOOKUP(ROE!A10,BASE!F:H,3,0),B9) -> 0.85333333 | C10: =+IFERROR(VLOOKUP(A10,BASE!A:C,3,0)/VLOOKUP(ROE!A10,BASE!F:H,3,0),C9) -> 0.47103085 | F10: =+IFERROR(VLOOKUP(A10,BASE!A:C,3,0)/VLOOKUP(A10,BASE!K:M,3,0),F9) -> 0.57090743
A11: =+BASE!A11 -> 37225 | B11: =+IFERROR(VLOOKUP(A11,BASE!K:M,3,0)/VLOOKUP(ROE!A11,BASE!F:H,3,0),B10) -> 1.0134011 | C11: =+IFERROR(VLOOKUP(A11,BASE!A:C,3,0)/VLOOKUP(ROE!A11,BASE!F:H,3,0),C10) -> 0.47103085 | F11: =+IFERROR(VLOOKUP(A11,BASE!A:C,3,0)/VLOOKUP(A11,BASE!K:M,3,0),F10) -> 0.57090743
A12: =+BASE!A12 -> 37232 | B12: =+IFERROR(VLOOKUP(A12,BASE!K:M,3,0)/VLOOKUP(ROE!A12,BASE!F:H,3,0),B11) -> 1.0097166 | C12: =+IFERROR(VLOOKUP(A12,BASE!A:C,3,0)/VLOOKUP(ROE!A12,BASE!F:H,3,0),C11) -> 0.47530364 | F12: =+IFERROR(VLOOKUP(A12,BASE!A:C,3,0)/VLOOKUP(A12,BASE!K:M,3,0),F11) -> 0.47072975
A13: =+BASE!A13 -> 37239 | B13: =+IFERROR(VLOOKUP(A13,BASE!K:M,3,0)/VLOOKUP(ROE!A13,BASE!F:H,3,0),B12) -> 1.0614901 | C13: =+IFERROR(VLOOKUP(A13,BASE!A:C,3,0)/VLOOKUP(ROE!A13,BASE!F:H,3,0),C12) -> 0.54129264 | F13: =+IFERROR(VLOOKUP(A13,BASE!A:C,3,0)/VLOOKUP(A13,BASE!K:M,3,0),F12) -> 0.50993658
A14: =+BASE!A14 -> 37246 | B14: =+IFERROR(VLOOKUP(A14,BASE!K:M,3,0)/VLOOKUP(ROE!A14,BASE!F:H,3,0),B13) -> 1.022187 | C14: =+IFERROR(VLOOKUP(A14,BASE!A:C,3,0)/VLOOKUP(ROE!A14,BASE!F:H,3,0),C13) -> 0.477813 | F14: =+IFERROR(VLOOKUP(A14,BASE!A:C,3,0)/VLOOKUP(A14,BASE!K:M,3,0),F13) -> 0.46744186
... A77: =+BASE!A77 -> 37701 | B77: =+IFERROR(VLOOKUP(A77,BASE!K:M,3,0)/VLOOKUP(ROE!A77,BASE!F:H,3,0),B76) -> 0.94530722 | C77: =+IFERROR(VLOOKUP(A77,BASE!A:C,3,0)/VLOOKUP(ROE!A77,BASE!F:H,3,0),C76) -> 0.11554994 | F77: =+IFERROR(VLOOKUP(A77,BASE!A:C,3,0)/VLOOKUP(A77,BASE!K:M,3,0),F76) -> 0.13102064
A78: =+BASE!A78 -> 37708 | B78: =+IFERROR(VLOOKUP(A78,BASE!K:M,3,0)/VLOOKUP(ROE!A78,BASE!F:H,3,0),B77) -> 1.1570681 | C78: =+IFERROR(VLOOKUP(A78,BASE!A:C,3,0)/VLOOKUP(ROE!A78,BASE!F:H,3,0),C77) -> 0.82696335 | F78: =+IFERROR(VLOOKUP(A78,BASE!A:C,3,0)/VLOOKUP(A78,BASE!K:M,3,0),F77) -> 0.71470588 | L78: =+STDEVA(B26:B78)*2+B78 -> 1.4586185 | M78: =-STDEVA(B26:B78)*2+B78 -> 0.8555176
A79: =+BASE!A79 -> 37715 | B79: =+IFERROR(VLOOKUP(A79,BASE!K:M,3,0)/VLOOKUP(ROE!A79,BASE!F:H,3,0),B78) -> 1.1942718 | C79: =+IFERROR(VLOOKUP(A79,BASE!A:C,3,0)/VLOOKUP(ROE!A79,BASE!F:H,3,0),C78) -> 0.84220481 | F79: =+IFERROR(VLOOKUP(A79,BASE!A:C,3,0)/VLOOKUP(A79,BASE!K:M,3,0),F78) -> 0.70520362 | L79: =+STDEVA(B27:B79)*2+B79 -> 1.492094 | M79: =-STDEVA(B27:B79)*2+B79 -> 0.89644964
A80: =+BASE!A80 -> 37722 | B80: =+IFERROR(VLOOKUP(A80,BASE!K:M,3,0)/VLOOKUP(ROE!A80,BASE!F:H,3,0),B79) -> 1.1845059 | C80: =+IFERROR(VLOOKUP(A80,BASE!A:C,3,0)/VLOOKUP(ROE!A80,BASE!F:H,3,0),C79) -> 0.91130578 | F80: =+IFERROR(VLOOKUP(A80,BASE!A:C,3,0)/VLOOKUP(A80,BASE!K:M,3,0),F79) -> 0.76935521 | L80: =+STDEVA(B28:B80)*2+B80 -> 1.4929116 | M80: =-STDEVA(B28:B80)*2+B80 -> 0.87610016
A81: =+BASE!A81 -> 37729 | B81: =+IFERROR(VLOOKUP(A81,BASE!K:M,3,0)/VLOOKUP(ROE!A81,BASE!F:H,3,0),B80) -> 1.1304794 | C81: =+IFERROR(VLOOKUP(A81,BASE!A:C,3,0)/VLOOKUP(ROE!A81,BASE!F:H,3,0),C80) -> 0.90207639 | F81: =+IFERROR(VLOOKUP(A81,BASE!A:C,3,0)/VLOOKUP(A81,BASE!K:M,3,0),F80) -> 0.79795918 | L81: =+STDEVA(B29:B81)*2+B81 -> 1.4466652 | M81: =-STDEVA(B29:B81)*2+B81 -> 0.81429348
A82: =+BASE!A82 -> 37736 | B82: =+IFERROR(VLOOKUP(A82,BASE!K:M,3,0)/VLOOKUP(ROE!A82,BASE!F:H,3,0),B81) -> 1.1254868 | C82: =+IFERROR(VLOOKUP(A82,BASE!A:C,3,0)/VLOOKUP(ROE!A82,BASE!F:H,3,0),C81) -> 0.81652964 | F82: =+IFERROR(VLOOKUP(A82,BASE!A:C,3,0)/VLOOKUP(A82,BASE!K:M,3,0),F81) -> 0.7254902 | L82: =+STDEVA(B30:B82)*2+B82 -> 1.4454577 | M82: =-STDEVA(B30:B82)*2+B82 -> 0.80551592
A83: =+BASE!A83 -> 37743 | B83: =+IFERROR(VLOOKUP(A83,BASE!K:M,3,0)/VLOOKUP(ROE!A83,BASE!F:H,3,0),B82) -> 1.1722989 | C83: =+IFERROR(VLOOKUP(A83,BASE!A:C,3,0)/VLOOKUP(ROE!A83,BASE!F:H,3,0),C82) -> 0.89814374 | F83: =+IFERROR(VLOOKUP(A83,BASE!A:C,3,0)/VLOOKUP(A83,BASE!K:M,3,0),F82) -> 0.76613886 | L83: =+STDEVA(B31:B83)*2+B83 -> 1.5004545 | M83: =-STDEVA(B31:B83)*2+B83 -> 0.84414328
A84: =+BASE!A84 -> 37750 | B84: =+IFERROR(VLOOKUP(A84,BASE!K:M,3,0)/VLOOKUP(ROE!A84,BASE!F:H,3,0),B83) -> 1.1968846 | C84: =+IFERROR(VLOOKUP(A84,BASE!A:C,3,0)/VLOOKUP(ROE!A84,BASE!F:H,3,0),C83) -> 0.9473953 | F84: =+IFERROR(VLOOKUP(A84,BASE!A:C,3,0)/VLOOKUP(A84,BASE!K:M,3,0),F83) -> 0.7915511 | L84: =+STDEVA(B32:B84)*2+B84 -> 1.533641 | M84: =-STDEVA(B32:B84)*2+B84 -> 0.86012814
A85: =+BASE!A85 -> 37757 | B85: =+IFERROR(VLOOKUP(A85,BASE!K:M,3,0)/VLOOKUP(ROE!A85,BASE!F:H,3,0),B84) -> 1.1597925 | C85: =+IFERROR(VLOOKUP(A85,BASE!A:C,3,0)/VLOOKUP(ROE!A85,BASE!F:H,3,0),C84) -> 0.92146209 | F85: =+IFERROR(VLOOKUP(A85,BASE!A:C,3,0)/VLOOKUP(A85,BASE!K:M,3,0),F84) -> 0.79450596 | L85: =+STDEVA(B33:B85)*2+B85 -> 1.4996584 | M85: =-STDEVA(B33:B85)*2+B85 -> 0.81992665
A86: =+BASE!A86 -> 37764 | B86: =+IFERROR(VLOOKUP(A86,BASE!K:M,3,0)/VLOOKUP(ROE!A86,BASE!F:H,3,0),B85) -> 1.0987365 | C86: =+IFERROR(VLOOKUP(A86,BASE!A:C,3,0)/VLOOKUP(ROE!A86,BASE!F:H,3,0),C85) -> 0.83341132 | F86: =+IFERROR(VLOOKUP(A86,BASE!A:C,3,0)/VLOOKUP(A86,BASE!K:M,3,0),F85) -> 0.75851789 | L86: =+STDEVA(B34:B86)*2+B86 -> 1.4394431 | M86: =-STDEVA(B34:B86)*2+B86 -> 0.75802995
A87: =+BASE!A87 -> 37771 | B87: =+IFERROR(VLOOKUP(A87,BASE!K:M,3,0)/VLOOKUP(ROE!A87,BASE!F:H,3,0),B86) -> 1.073694 | C87: =+IFERROR(VLOOKUP(A87,BASE!A:C,3,0)/VLOOKUP(ROE!A87,BASE!F:H,3,0),C86) -> 0.81576493 | F87: =+IFERROR(VLOOKUP(A87,BASE!A:C,3,0)/VLOOKUP(A87,BASE!K:M,3,0),F86) -> 0.75977411 | L87: =+STDEVA(B35:B87)*2+B87 -> 1.4152054 | M87: =-STDEVA(B35:B87)*2+B87 -> 0.73218265
A88: =+BASE!A88 -> 37778 | B88: =+IFERROR(VLOOKUP(A88,BASE!K:M,3,0)/VLOOKUP(ROE!A88,BASE!F:H,3,0),B87) -> 0.9821883 | C88: =+IFERROR(VLOOKUP(A88,BASE!A:C,3,0)/VLOOKUP(ROE!A88,BASE!F:H,3,0),C87) -> 0.78019182 | F88: =+IFERROR(VLOOKUP(A88,BASE!A:C,3,0)/VLOOKUP(A88,BASE!K:M,3,0),F87) -> 0.79434037 | L88: =+STDEVA(B36:B88)*2+B88 -> 1.3223591 | M88: =-STDEVA(B36:B88)*2+B88 -> 0.64201748
A89: =+BASE!A89 -> 37785 | B89: =+IFERROR(VLOOKUP(A89,BASE!K:M,3,0)/VLOOKUP(ROE!A89,BASE!F:H,3,0),B88) -> 0.9869723 | C89: =+IFERROR(VLOOKUP(A89,BASE!A:C,3,0)/VLOOKUP(ROE!A89,BASE!F:H,3,0),C88) -> 0.69920844 | F89: =+IFERROR(VLOOKUP(A89,BASE!A:C,3,0)/VLOOKUP(A89,BASE!K:M,3,0),F88) -> 0.70843776 | L89: =+STDEVA(B37:B89)*2+B89 -> 1.3204105 | M89: =-STDEVA(B37:B89)*2+B89 -> 0.65353412
... A302: =+BASE!A302 -> 39276 | B302: =+IFERROR(VLOOKUP(A302,BASE!K:M,3,0)/VLOOKUP(ROE!A302,BASE!F:H,3,0),B301) -> 0.7437125 | C302: =+IFERROR(VLOOKUP(A302,BASE!A:C,3,0)/VLOOKUP(ROE!A302,BASE!F:H,3,0),C301) -> 1.0469062 | F302: =+IFERROR(VLOOKUP(A302,BASE!A:C,3,0)/VLOOKUP(A302,BASE!K:M,3,0),F301) -> 1.407676 | L302: =+STDEVA(B250:B302)*2+B302 -> 0.88936995 | M302: =-STDEVA(B250:B302)*2+B302 -> 0.59805506
A303: =+BASE!A303 -> 39283 | B303: =+IFERROR(VLOOKUP(A303,BASE!K:M,3,0)/VLOOKUP(ROE!A303,BASE!F:H,3,0),B302) -> 0.75636894 | C303: =+IFERROR(VLOOKUP(A303,BASE!A:C,3,0)/VLOOKUP(ROE!A303,BASE!F:H,3,0),C302) -> 1.0089378 | D303: =+IFERROR(+VLOOKUP(A303,BASE!P:R,3,0)/VLOOKUP(ROE!A303,BASE!F:H,3,0),D302) -> 0 | F303: =+IFERROR(VLOOKUP(A303,BASE!A:C,3,0)/VLOOKUP(A303,BASE!K:M,3,0),F302) -> 1.3339228 | L303: =+STDEVA(B251:B303)*2+B303 -> 0.9012853 | M303: =-STDEVA(B251:B303)*2+B303 -> 0.61145258
A304: =+BASE!A304 -> 39290 | B304: =+IFERROR(VLOOKUP(A304,BASE!K:M,3,0)/VLOOKUP(ROE!A304,BASE!F:H,3,0),B303) -> 0.76128274 | C304: =+IFERROR(VLOOKUP(A304,BASE!A:C,3,0)/VLOOKUP(ROE!A304,BASE!F:H,3,0),C303) -> 0.96989093 | D304: =+IFERROR(+VLOOKUP(A304,BASE!P:R,3,0)/VLOOKUP(ROE!A304,BASE!F:H,3,0),D303) -> 0 | F304: =+IFERROR(VLOOKUP(A304,BASE!A:C,3,0)/VLOOKUP(A304,BASE!K:M,3,0),F303) -> 1.274022 | L304: =+STDEVA(B252:B304)*2+B304 -> 0.90316353 | M304: =-STDEVA(B252:B304)*2+B304 -> 0.61940195
A305: =+BASE!A305 -> 39297 | B305: =+IFERROR(VLOOKUP(A305,BASE!K:M,3,0)/VLOOKUP(ROE!A305,BASE!F:H,3,0),B304) -> 0.75131793 | C305: =+IFERROR(VLOOKUP(A305,BASE!A:C,3,0)/VLOOKUP(ROE!A305,BASE!F:H,3,0),C304) -> 0.98919623 | D305: =+IFERROR(+VLOOKUP(A305,BASE!P:R,3,0)/VLOOKUP(ROE!A305,BASE!F:H,3,0),D304) -> 0 | F305: =+IFERROR(VLOOKUP(A305,BASE!A:C,3,0)/VLOOKUP(A305,BASE!K:M,3,0),F304) -> 1.3166147 | L305: =+STDEVA(B253:B305)*2+B305 -> 0.88717347 | M305: =-STDEVA(B253:B305)*2+B305 -> 0.61546239
A306: =+BASE!A306 -> 39304 | B306: =+IFERROR(VLOOKUP(A306,BASE!K:M,3,0)/VLOOKUP(ROE!A306,BASE!F:H,3,0),B305) -> 0.77070295 | C306: =+IFERROR(VLOOKUP(A306,BASE!A:C,3,0)/VLOOKUP(ROE!A306,BASE!F:H,3,0),C305) -> 1.0879057 | D306: =+IFERROR(+VLOOKUP(A306,BASE!P:R,3,0)/VLOOKUP(ROE!A306,BASE!F:H,3,0),D305) -> 0 | F306: =+IFERROR(VLOOKUP(A306,BASE!A:C,3,0)/VLOOKUP(A306,BASE!K:M,3,0),F305) -> 1.4115759 | L306: =+STDEVA(B254:B306)*2+B306 -> 0.89760957 | M306: =-STDEVA(B254:B306)*2+B306 -> 0.64379634
A307: =+BASE!A307 -> 39311 | B307: =+IFERROR(VLOOKUP(A307,BASE!K:M,3,0)/VLOOKUP(ROE!A307,BASE!F:H,3,0),B306) -> 0.81994609 | C307: =+IFERROR(VLOOKUP(A307,BASE!A:C,3,0)/VLOOKUP(ROE!A307,BASE!F:H,3,0),C306) -> 1.038737 | D307: =+IFERROR(+VLOOKUP(A307,BASE!P:R,3,0)/VLOOKUP(ROE!A307,BASE!F:H,3,0),D306) -> 0 | F307: =+IFERROR(VLOOKUP(A307,BASE!A:C,3,0)/VLOOKUP(A307,BASE!K:M,3,0),F306) -> 1.2668357 | L307: =+STDEVA(B255:B307)*2+B307 -> 0.93659166 | M307: =-STDEVA(B255:B307)*2+B307 -> 0.70330052
A308: =+BASE!A308 -> 39318 | B308: =+IFERROR(VLOOKUP(A308,BASE!K:M,3,0)/VLOOKUP(ROE!A308,BASE!F:H,3,0),B307) -> 0.79049406 | C308: =+IFERROR(VLOOKUP(A308,BASE!A:C,3,0)/VLOOKUP(ROE!A308,BASE!F:H,3,0),C307) -> 1.0446112 | D308: =+IFERROR(+VLOOKUP(A308,BASE!P:R,3,0)/VLOOKUP(ROE!A308,BASE!F:H,3,0),D307) -> 0 | F308: =+IFERROR(VLOOKUP(A308,BASE!A:C,3,0)/VLOOKUP(A308,BASE!K:M,3,0),F307) -> 1.3214662 | L308: =+STDEVA(B256:B308)*2+B308 -> 0.89563786 | M308: =-STDEVA(B256:B308)*2+B308 -> 0.68535026
A309: =+BASE!A309 -> 39325 | B309: =+IFERROR(VLOOKUP(A309,BASE!K:M,3,0)/VLOOKUP(ROE!A309,BASE!F:H,3,0),B308) -> 0.78180511 | C309: =+IFERROR(VLOOKUP(A309,BASE!A:C,3,0)/VLOOKUP(ROE!A309,BASE!F:H,3,0),C308) -> 1.0368932 | D309: =+IFERROR(+VLOOKUP(A309,BASE!P:R,3,0)/VLOOKUP(ROE!A309,BASE!F:H,3,0),D308) -> 0 | F309: =+IFERROR(VLOOKUP(A309,BASE!A:C,3,0)/VLOOKUP(A309,BASE!K:M,3,0),F308) -> 1.3262809 | L309: =+STDEVA(B257:B309)*2+B309 -> 0.88205055 | M309: =-STDEVA(B257:B309)*2+B309 -> 0.68155966
A310: =+BASE!A310 -> 39332 | B310: =+IFERROR(VLOOKUP(A310,BASE!K:M,3,0)/VLOOKUP(ROE!A310,BASE!F:H,3,0),B309) -> 0.78096587 | C310: =+IFERROR(VLOOKUP(A310,BASE!A:C,3,0)/VLOOKUP(ROE!A310,BASE!F:H,3,0),C309) -> 1.0497839 | D310: =+IFERROR(+VLOOKUP(A310,BASE!P:R,3,0)/VLOOKUP(ROE!A310,BASE!F:H,3,0),D309) -> 0 | F310: =+IFERROR(VLOOKUP(A310,BASE!A:C,3,0)/VLOOKUP(A310,BASE!K:M,3,0),F309) -> 1.3442122 | L310: =+STDEVA(B258:B310)*2+B310 -> 0.87443866 | M310: =-STDEVA(B258:B310)*2+B310 -> 0.68749307
A311: =+BASE!A311 -> 39339 | B311: =+IFERROR(VLOOKUP(A311,BASE!K:M,3,0)/VLOOKUP(ROE!A311,BASE!F:H,3,0),B310) -> 0.76255776 | C311: =+IFERROR(VLOOKUP(A311,BASE!A:C,3,0)/VLOOKUP(ROE!A311,BASE!F:H,3,0),C310) -> 1.0993442 | D311: =+IFERROR(+VLOOKUP(A311,BASE!P:R,3,0)/VLOOKUP(ROE!A311,BASE!F:H,3,0),D310) -> 0 | F311: =+IFERROR(VLOOKUP(A311,BASE!A:C,3,0)/VLOOKUP(A311,BASE!K:M,3,0),F310) -> 1.4416536 | L311: =+STDEVA(B259:B311)*2+B311 -> 0.85420087 | M311: =-STDEVA(B259:B311)*2+B311 -> 0.67091464
A312: =+BASE!A312 -> 39346 | B312: =+IFERROR(VLOOKUP(A312,BASE!K:M,3,0)/VLOOKUP(ROE!A312,BASE!F:H,3,0),B311) -> 0.7755434 | C312: =+IFERROR(VLOOKUP(A312,BASE!A:C,3,0)/VLOOKUP(ROE!A312,BASE!F:H,3,0),C311) -> 1.1114151 | D312: =+IFERROR(+VLOOKUP(A312,BASE!P:R,3,0)/VLOOKUP(ROE!A312,BASE!F:H,3,0),D311) -> 0 | F312: =+IFERROR(VLOOKUP(A312,BASE!A:C,3,0)/VLOOKUP(A312,BASE!K:M,3,0),F311) -> 1.4330791 | L312: =+STDEVA(B260:B312)*2+B312 -> 0.86662661 | M312: =-STDEVA(B260:B312)*2+B312 -> 0.68446019
A313: =+BASE!A313 -> 39353 | B313: =+IFERROR(VLOOKUP(A313,BASE!K:M,3,0)/VLOOKUP(ROE!A313,BASE!F:H,3,0),B312) -> 0.74918325 | C313: =+IFERROR(VLOOKUP(A313,BASE!A:C,3,0)/VLOOKUP(ROE!A313,BASE!F:H,3,0),C312) -> 1.0953371 | D313: =+IFERROR(+VLOOKUP(A313,BASE!P:R,3,0)/VLOOKUP(ROE!A313,BASE!F:H,3,0),D312) -> 0 | F313: =+IFERROR(VLOOKUP(A313,BASE!A:C,3,0)/VLOOKUP(A313,BASE!K:M,3,0),F312) -> 1.4620416 | L313: =+STDEVA(B261:B313)*2+B313 -> 0.84010106 | M313: =-STDEVA(B261:B313)*2+B313 -> 0.65826543
A314: =+BASE!A314 -> 39360 | B314: =+IFERROR(VLOOKUP(A314,BASE!K:M,3,0)/VLOOKUP(ROE!A314,BASE!F:H,3,0),B313) -> 0.77617354 | C314: =+IFERROR(VLOOKUP(A314,BASE!A:C,3,0)/VLOOKUP(ROE!A314,BASE!F:H,3,0),C313) -> 1.1290896 | D314: =+IFERROR(+VLOOKUP(A314,BASE!P:R,3,0)/VLOOKUP(ROE!A314,BASE!F:H,3,0),D313) -> 0 | F314: =+IFERROR(VLOOKUP(A314,BASE!A:C,3,0)/VLOOKUP(A314,BASE!K:M,3,0),F313) -> 1.4546871 | L314: =+STDEVA(B262:B314)*2+B314 -> 0.86460373 | M314: =-STDEVA(B262:B314)*2+B314 -> 0.68774335
... A763: =+BASE!A763 -> 42503 | B763: =+IFERROR(VLOOKUP(A763,BASE!K:M,3,0)/VLOOKUP(ROE!A763,BASE!F:H,3,0),B762) -> 0.84302395 | C763: =+IFERROR(VLOOKUP(A763,BASE!A:C,3,0)/VLOOKUP(ROE!A763,BASE!F:H,3,0),C762) -> 0.77192843 | D763: =+IFERROR(+VLOOKUP(A763,BASE!P:R,3,0)/VLOOKUP(ROE!A763,BASE!F:H,3,0),D762) -> 0 | F763: =+IFERROR(VLOOKUP(A763,BASE!A:C,3,0)/VLOOKUP(A763,BASE!K:M,3,0),F762) -> 0.91566607 | L763: =+STDEVA(B711:B763)*2+B763 -> 0.9743705 | M763: =-STDEVA(B711:B763)*2+B763 -> 0.7116774
A764: =+BASE!A764 -> 42510 | B764: =+IFERROR(VLOOKUP(A764,BASE!K:M,3,0)/VLOOKUP(ROE!A764,BASE!F:H,3,0),B763) -> 0.83452905 | C764: =+IFERROR(VLOOKUP(A764,BASE!A:C,3,0)/VLOOKUP(ROE!A764,BASE!F:H,3,0),C763) -> 0.78409901 | D764: =+IFERROR(+VLOOKUP(A764,BASE!P:R,3,0)/VLOOKUP(ROE!A764,BASE!F:H,3,0),D763) -> 0 | E764: =+IFERROR(BASE!V764/BASE!G764,E763) -> 0.92975467 | F764: =+IFERROR(VLOOKUP(A764,BASE!A:C,3,0)/VLOOKUP(A764,BASE!K:M,3,0),F763) -> 0.93957066 | L764: =+STDEVA(B712:B764)*2+B764 -> 0.96905232 | M764: =-STDEVA(B712:B764)*2+B764 -> 0.70000579
A765: =+BASE!A765 -> 42517 | B765: =+IFERROR(VLOOKUP(A765,BASE!K:M,3,0)/VLOOKUP(ROE!A765,BASE!F:H,3,0),B764) -> 0.81926838 | C765: =+IFERROR(VLOOKUP(A765,BASE!A:C,3,0)/VLOOKUP(ROE!A765,BASE!F:H,3,0),C764) -> 0.75830013 | D765: =+IFERROR(+VLOOKUP(A765,BASE!P:R,3,0)/VLOOKUP(ROE!A765,BASE!F:H,3,0),D764) -> 0 | E765: =+IFERROR(BASE!V765/BASE!G765,E764) -> 0.92975467 | F765: =+IFERROR(VLOOKUP(A765,BASE!A:C,3,0)/VLOOKUP(A765,BASE!K:M,3,0),F764) -> 0.92558208 | L765: =+STDEVA(B713:B765)*2+B765 -> 0.95763823 | M765: =-STDEVA(B713:B765)*2+B765 -> 0.68089853
A766: =+BASE!A766 -> 42524 | B766: =+IFERROR(VLOOKUP(A766,BASE!K:M,3,0)/VLOOKUP(ROE!A766,BASE!F:H,3,0),B765) -> 0.8129522 | C766: =+IFERROR(VLOOKUP(A766,BASE!A:C,3,0)/VLOOKUP(ROE!A766,BASE!F:H,3,0),C765) -> 0.79974697 | D766: =+IFERROR(+VLOOKUP(A766,BASE!P:R,3,0)/VLOOKUP(ROE!A766,BASE!F:H,3,0),D765) -> 0 | E766: =+IFERROR(BASE!V766/BASE!G766,E765) -> 0.92975467 | F766: =+IFERROR(VLOOKUP(A766,BASE!A:C,3,0)/VLOOKUP(A766,BASE!K:M,3,0),F765) -> 0.98375644 | L766: =+STDEVA(B714:B766)*2+B766 -> 0.95521732 | M766: =-STDEVA(B714:B766)*2+B766 -> 0.67068708
A767: =+BASE!A767 -> 42531 | B767: =+IFERROR(VLOOKUP(A767,BASE!K:M,3,0)/VLOOKUP(ROE!A767,BASE!F:H,3,0),B766) -> 0.81252133 | C767: =+IFERROR(VLOOKUP(A767,BASE!A:C,3,0)/VLOOKUP(ROE!A767,BASE!F:H,3,0),C766) -> 0.80455804 | D767: =+IFERROR(+VLOOKUP(A767,BASE!P:R,3,0)/VLOOKUP(ROE!A767,BASE!F:H,3,0),D766) -> 0 | E767: =+IFERROR(BASE!V767/BASE!G767,E766) -> 0.92975467 | F767: =+IFERROR(VLOOKUP(A767,BASE!A:C,3,0)/VLOOKUP(A767,BASE!K:M,3,0),F766) -> 0.99019928 | L767: =+STDEVA(B715:B767)*2+B767 -> 0.95819875 | M767: =-STDEVA(B715:B767)*2+B767 -> 0.66684392
A768: =+BASE!A768 -> 42538 | B768: =+IFERROR(VLOOKUP(A768,BASE!K:M,3,0)/VLOOKUP(ROE!A768,BASE!F:H,3,0),B767) -> 0.8129491 | C768: =+IFERROR(VLOOKUP(A768,BASE!A:C,3,0)/VLOOKUP(ROE!A768,BASE!F:H,3,0),C767) -> 0.80351796 | D768: =+IFERROR(+VLOOKUP(A768,BASE!P:R,3,0)/VLOOKUP(ROE!A768,BASE!F:H,3,0),D767) -> 0 | E768: =+IFERROR(BASE!V768/BASE!G768,E767) -> 0.92975467 | F768: =+IFERROR(VLOOKUP(A768,BASE!A:C,3,0)/VLOOKUP(A768,BASE!K:M,3,0),F767) -> 0.98839886 | L768: =+STDEVA(B716:B768)*2+B768 -> 0.96231235 | M768: =-STDEVA(B716:B768)*2+B768 -> 0.66358586
A769: =+BASE!A769 -> 42545 | B769: =+IFERROR(VLOOKUP(A769,BASE!K:M,3,0)/VLOOKUP(ROE!A769,BASE!F:H,3,0),B768) -> 0.79909755 | C769: =+IFERROR(VLOOKUP(A769,BASE!A:C,3,0)/VLOOKUP(ROE!A769,BASE!F:H,3,0),C768) -> 0.80468414 | D769: =+IFERROR(+VLOOKUP(A769,BASE!P:R,3,0)/VLOOKUP(ROE!A769,BASE!F:H,3,0),D768) -> 0 | E769: =+IFERROR(BASE!V769/BASE!G769,E768) -> 0.92975467 | F769: =+IFERROR(VLOOKUP(A769,BASE!A:C,3,0)/VLOOKUP(A769,BASE!K:M,3,0),F768) -> 1.0069911 | L769: =+STDEVA(B717:B769)*2+B769 -> 0.95277289 | M769: =-STDEVA(B717:B769)*2+B769 -> 0.64542222
A770: =+BASE!A770 -> 42552 | B770: =+IFERROR(VLOOKUP(A770,BASE!K:M,3,0)/VLOOKUP(ROE!A770,BASE!F:H,3,0),B769) -> 0.87160648 | C770: =+IFERROR(VLOOKUP(A770,BASE!A:C,3,0)/VLOOKUP(ROE!A770,BASE!F:H,3,0),C769) -> 0.85764667 | D770: =+IFERROR(+VLOOKUP(A770,BASE!P:R,3,0)/VLOOKUP(ROE!A770,BASE!F:H,3,0),D769) -> 0 | E770: =+IFERROR(BASE!V770/BASE!G770,E769) -> 0.60009374 | F770: =+IFERROR(VLOOKUP(A770,BASE!A:C,3,0)/VLOOKUP(A770,BASE!K:M,3,0),F769) -> 0.98398382 | L770: =+STDEVA(B718:B770)*2+B770 -> 1.0258866 | M770: =-STDEVA(B718:B770)*2+B770 -> 0.71732635
A771: =+BASE!A771 -> 42559 | B771: =+IFERROR(VLOOKUP(A771,BASE!K:M,3,0)/VLOOKUP(ROE!A771,BASE!F:H,3,0),B770) -> 0.86228647 | C771: =+IFERROR(VLOOKUP(A771,BASE!A:C,3,0)/VLOOKUP(ROE!A771,BASE!F:H,3,0),C770) -> 0.86941994 | D771: =+IFERROR(+VLOOKUP(A771,BASE!P:R,3,0)/VLOOKUP(ROE!A771,BASE!F:H,3,0),D770) -> 0 | E771: =+IFERROR(BASE!V771/BASE!G771,E770) -> 0.60009374 | F771: =+IFERROR(VLOOKUP(A771,BASE!A:C,3,0)/VLOOKUP(A771,BASE!K:M,3,0),F770) -> 1.0082727 | L771: =+STDEVA(B719:B771)*2+B771 -> 1.016177 | M771: =-STDEVA(B719:B771)*2+B771 -> 0.70839591
A772: =+BASE!A772 -> 42566 | B772: =+IFERROR(VLOOKUP(A772,BASE!K:M,3,0)/VLOOKUP(ROE!A772,BASE!F:H,3,0),B771) -> 0.86774934 | C772: =+IFERROR(VLOOKUP(A772,BASE!A:C,3,0)/VLOOKUP(ROE!A772,BASE!F:H,3,0),C771) -> 0.88972539 | D772: =+IFERROR(+VLOOKUP(A772,BASE!P:R,3,0)/VLOOKUP(ROE!A772,BASE!F:H,3,0),D771) -> 0 | E772: =+IFERROR(BASE!V772/BASE!G772,E771) -> 0.60009374 | F772: =+IFERROR(VLOOKUP(A772,BASE!A:C,3,0)/VLOOKUP(A772,BASE!K:M,3,0),F771) -> 1.0253253 | L772: =+STDEVA(B720:B772)*2+B772 -> 1.0217988 | M772: =-STDEVA(B720:B772)*2+B772 -> 0.71369985
A773: =+BASE!A773 -> 42573 | B773: =+IFERROR(VLOOKUP(A773,BASE!K:M,3,0)/VLOOKUP(ROE!A773,BASE!F:H,3,0),B772) -> 0.90076704 | C773: =+IFERROR(VLOOKUP(A773,BASE!A:C,3,0)/VLOOKUP(ROE!A773,BASE!F:H,3,0),C772) -> 0.90484307 | D773: =+IFERROR(+VLOOKUP(A773,BASE!P:R,3,0)/VLOOKUP(ROE!A773,BASE!F:H,3,0),D772) -> 0 | E773: =+IFERROR(BASE!V773/BASE!G773,E772) -> 0.60009374 | F773: =+IFERROR(VLOOKUP(A773,BASE!A:C,3,0)/VLOOKUP(A773,BASE!K:M,3,0),F772) -> 1.0045251 | L773: =+STDEVA(B721:B773)*2+B773 -> 1.0534939 | M773: =-STDEVA(B721:B773)*2+B773 -> 0.74804014
A774: =+BASE!A774 -> 42580 | B774: =+IFERROR(VLOOKUP(A774,BASE!K:M,3,0)/VLOOKUP(ROE!A774,BASE!F:H,3,0),B773) -> 0.87716625 | C774: =+IFERROR(VLOOKUP(A774,BASE!A:C,3,0)/VLOOKUP(ROE!A774,BASE!F:H,3,0),C773) -> 0.9052371 | D774: =+IFERROR(+VLOOKUP(A774,BASE!P:R,3,0)/VLOOKUP(ROE!A774,BASE!F:H,3,0),D773) -> 0 | E774: =+IFERROR(BASE!V774/BASE!G774,E773) -> 0.60009374 | F774: =+IFERROR(VLOOKUP(A774,BASE!A:C,3,0)/VLOOKUP(A774,BASE!K:M,3,0),F773) -> 1.0320017 | L774: =+STDEVA(B722:B774)*2+B774 -> 1.0295485 | M774: =-STDEVA(B722:B774)*2+B774 -> 0.72478404
A775: =+BASE!A775 -> 42587 | B775: =+IFERROR(VLOOKUP(A775,BASE!K:M,3,0)/VLOOKUP(ROE!A775,BASE!F:H,3,0),B774) -> 0.90567587 | C775: =+IFERROR(VLOOKUP(A775,BASE!A:C,3,0)/VLOOKUP(ROE!A775,BASE!F:H,3,0),C774) -> 0.89985146 | D775: =+IFERROR(+VLOOKUP(A775,BASE!P:R,3,0)/VLOOKUP(ROE!A775,BASE!F:H,3,0),D774) -> 0 | E775: =+IFERROR(BASE!V775/BASE!G775,E774) -> 0.60009374 | F775: =+IFERROR(VLOOKUP(A775,BASE!A:C,3,0)/VLOOKUP(A775,BASE!K:M,3,0),F774) -> 0.99356899 | L775: =+STDEVA(B723:B775)*2+B775 -> 1.0579836 | M775: =-STDEVA(B723:B775)*2+B775 -> 0.75336816
... A1269: =+BASE!A1269 -> 46045 | B1269: =+IFERROR(VLOOKUP(A1269,BASE!K:M,3,0)/VLOOKUP(ROE!A1269,BASE!F:H,3,0),B1268) -> 0.98597692 | C1269: =+IFERROR(VLOOKUP(A1269,BASE!A:C,3,0)/VLOOKUP(ROE!A1269,BASE!F:H,3,0),C1268) -> 0.99845679 | D1269: =+IFERROR(+VLOOKUP(A1269,BASE!P:R,3,0)/VLOOKUP(ROE!A1269,BASE!F:H,3,0),D1268) -> 1.0890365 | E1269: =+IFERROR(BASE!V1269/BASE!G1269,E1268) -> -1.152977 | F1269: =+IFERROR(VLOOKUP(A1269,BASE!A:C,3,0)/VLOOKUP(A1269,BASE!K:M,3,0),F1268) -> 1.0126574 | L1269: =+STDEVA(B1217:B1269)*2+B1269 -> 1.0997956 | M1269: =-STDEVA(B1217:B1269)*2+B1269 -> 0.87215822

Sheet Ratios
A1: BMA AR Equity | F1: GGAL AR Equity | K1: BBAR AR Equity | P1: BPAT AR Equity | U1: SUPV AR Equity
A2: Date | B2: RETURN_COM_EQY | C2: PX_TO_BOOK_RATIO | D2: PE_RATIO | F2: Date | G2: RETURN_COM_EQY | H2: PX_TO_BOOK_RATIO | I2: PE_RATIO | K2: Date | L2: RETURN_COM_EQY | M2: PX_TO_BOOK_RATIO | N2: PE_RATIO | P2: Date | Q2: RETURN_COM_EQY | R2: PX_TO_BOOK_RATIO | S2: PE_RATIO | U2: Date | V2: RETURN_COM_EQY | W2: PX_TO_BOOK_RATIO | X2: PE_RATIO
A3: =_xll.BDH($A$1,$B$2:$D$2,"02/10/2001","","FX=ARS","Dir=V","Dts=S","Sort=A","Quote=C","QtTyp=Y","Days=T","Per=cq","DtFmt=D","UseDPDF=Y","cols=4;rows=100") -> 37253 | B3: -92.054 | C3: 0.1936 | D3: #N/A N/A | F3: =_xll.BDH($F$1,$G$2:$I$2,"02/10/2001","","FX=ARS","Dir=V","Dts=S","Sort=A","Quote=C","QtTyp=Y","Days=T","Per=cq","DtFmt=D","UseDPDF=Y","cols=4;rows=100") -> 37253 | G3: 8.7976 | H3: 0.2503 | I3: 2.6034 | K3: =_xll.BDH($K$1,$L$2:$N$2,"02/10/2001","","FX=ARS","Dir=V","Dts=S","Sort=A","Quote=C","QtTyp=Y","Days=T","Per=cq","DtFmt=D","UseDPDF=Y","cols=4;rows=100") -> 37253 | L3: 1.3953 | M3: 0.3075 | N3: 6.0472
A4: 37342 | B4: 35.7337 | C4: 0.0163 | D4: 0.079 | F4: 37342 | G4: #N/A N/A | H4: 0.227 | I4: 2.3611 | K4: 37342 | L4: -5.2097 | M4: 0.169 | N4: 5.4117
A5: 37435 | B5: 16.1172 | C5: 0.0164 | D5: 0.1815 | F5: 37435 | G5: #N/A N/A | H5: 0.1073 | I5: 1.1158 | K5: 37435 | L5: -27.7697 | M5: 0.0907 | N5: #N/A N/A
A6: 37529 | B6: 17.699 | C6: 0.0283 | D6: 0.2909 | F6: 37529 | G6: #N/A N/A | H6: 0.1571 | I6: 1.6342 | K6: 37529 | L6: -81.7954 | M6: 0.1465 | N6: #N/A N/A
A7: 37621 | B7: #N/A N/A | C7: 0.0457 | D7: 0.4694 | F7: 37621 | G7: #N/A N/A | H7: 0.3793 | I7: 3.9446 | K7: 37621 | L7: -84.1223 | M7: 0.3343 | N7: #N/A N/A
A8: 37708 | B8: #N/A N/A | C8: 0.3159 | D8: #N/A N/A | F8: 37708 | G8: #N/A N/A | H8: 0.382 | I8: 4.5926 | K8: 37708 | L8: -80.7512 | M8: 0.442 | N8: #N/A N/A
A9: 37802 | B9: #N/A N/A | C9: 0.4406 | D9: #N/A N/A | F9: 37802 | G9: #N/A N/A | H9: 0.6353 | I9: #N/A N/A | K9: 37802 | L9: -56.2599 | M9: 0.5361 | N9: #N/A N/A
A10: 37894 | B10: #N/A N/A | C10: 0.4365 | D10: #N/A N/A | F10: 37894 | G10: #N/A N/A | H10: 0.7667 | I10: #N/A N/A | K10: 37894 | L10: -26.1297 | M10: 0.5774 | N10: #N/A N/A
A11: 37986 | B11: #N/A N/A | C11: 0.8076 | D11: 4.519 | F11: 37986 | G11: #N/A N/A | H11: 1.0542 | I11: #N/A N/A | K11: 37986 | L11: -14.6599 | M11: 0.8371 | N11: #N/A N/A
A12: 38077 | B12: 17.9949 | C12: 0.9105 | D12: 4.6643 | F12: 38077 | G12: -24.4343 | H12: 1.3058 | I12: #N/A N/A | K12: 38077 | L12: -9.2761 | M12: 1.0347 | N12: #N/A N/A
A13: 38168 | B13: 23.6091 | C13: 0.7257 | D13: 2.9141 | F13: 38168 | G13: -19.8866 | H13: 0.976 | I13: #N/A N/A | K13: 38168 | L13: -10.0597 | M13: 0.6772 | N13: #N/A N/A
A14: 38260 | B14: 25.4678 | C14: 0.9259 | D14: 3.47 | F14: 38260 | G14: -8.6008 | H14: 1.093 | I14: #N/A N/A | K14: 38260 | L14: -8.8037 | M14: 0.8759 | N14: #N/A N/A
A15: 38352 | B15: 25.4544 | C15: 1.0203 | D15: 6.6456 | F15: 38352 | G15: -9.6993 | H15: 1.4382 | I15: #N/A N/A | K15: 38352 | L15: -5.0268 | M15: 0.9587 | N15: #N/A N/A
A16: 38442 | B16: 26.2921 | C16: 1.0341 | D16: 6.3579 | F16: 38442 | G16: 1.5268 | H16: 1.1201 | I16: 48.9952 | K16: 38442 | L16: -1.5888 | M16: 0.8502 | N16: #N/A N/A
A17: 38533 | B17: 25.246 | C17: 0.9608 | D17: 6.3022 | F17: 38533 | G17: 3.7228 | H17: 1.2352 | I17: 28.6188 | K17: 38533 | L17: 1.3158 | M17: 0.724 | N17: 66.7748
A18: 38625 | B18: 26.8011 | C18: 1.2576 | D18: 7.6715 | F18: 38625 | G18: 2.7884 | H18: 1.3286 | I18: 43.7727 | K18: 38625 | L18: 3.8408 | M18: 0.9068 | N18: 29.4567
A19: 38715 | B19: 19.1286 | C19: 1.2672 | D19: 7.2139 | F19: 38715 | G19: 6.8167 | H19: 1.1248 | I19: 16.3236 | K19: 38715 | L19: 6.854 | M19: 0.8919 | N19: 13.9341
A20: 38807 | B20: 16.4207 | C20: 1.3392 | D20: 8.8282 | F20: 38807 | G20: 4.616 | H20: 1.2209 | I20: 26.2973 | K20: 38807 | L20: 7.316 | M20: 0.9454 | N20: 13.8552
A21: 38898 | B21: 18.3153 | C21: 1.2076 | D21: 7.2448 | F21: 38898 | G21: 5.8139 | H21: 0.9729 | I21: 17.2204 | K21: 38898 | L21: 7.8603 | M21: 0.882 | N21: 11.4963
A22: 38989 | B22: 19.6898 | C22: 1.2284 | D22: 7.0775 | F22: 38989 | G22: 6.116 | H22: 1.0253 | I22: 17.277 | K22: 38989 | L22: 8.8194 | M22: 0.9026 | N22: 10.553
A23: 39079 | B23: 22.3048 | C23: 1.5702 | D23: 8.2765 | F23: 39079 | G23: -1.1692 | H23: 1.542 | I23: 24.2394 | K23: 39079 | L23: 9.5884 | M23: 1.092 | N23: 11.9117
A24: 39171 | B24: 21.2333 | C24: 1.7298 | D24: 8.782 | F24: 39171 | G24: -1.4212 | H24: 1.7668 | I24: #N/A N/A | K24: 39171 | L24: 10.7617 | M24: 1.4013 | N24: 13.6951
A25: 39262 | B25: 21.7698 | C25: 1.6694 | D25: 8.3288 | F25: 39262 | G25: -3.9507 | H25: 1.6123 | I25: #N/A N/A | K25: 39262 | L25: 12.6715 | M25: 1.2328 | N25: 10.156
A26: 39353 | B26: 20.1233 | C26: 1.4752 | D26: 7.9087 | F26: 39353 | G26: -5.4898 | H26: 1.3468 | I26: #N/A N/A | K26: 39353 | L26: 13.746 | M26: 1.009 | N26: 7.6525
A27: 39444 | B27: 19.7185 | C27: 1.1578 | D27: 6.3306 | F27: 39444 | G27: 2.8218 | H27: 1.2056 | I27: 43.3266 | K27: 39444 | L27: 11.719 | M27: 0.9282 | N27: 8.1225
A28: 39538 | B28: 19.805 | C28: 1.1631 | D28: 6.3288 | F28: 39538 | G28: 6.1158 | H28: 1.067 | I28: 17.9794 | K28: 39538 | L28: 12.0446 | M28: 0.8912 | N28: 7.3122
A29: 39629 | B29: 21.8243 | C29: 0.8296 | D29: 4.0314 | F29: 39629 | G29: 7.7878 | H29: 0.7857 | I29: 10.4823 | K29: 39629 | L29: 13.2482 | M29: 0.6524 | N29: 5.0119
A30: 39721 | B30: 24.4183 | C30: 0.9333 | D30: 3.9678 | F30: 39721 | G30: 11.1023 | H30: 0.7327 | I30: 6.9659 | K30: 39721 | L30: 14.9185 | M30: 0.5707 | N30: 3.934
A31: 39812 | B31: 23.8962 | C31: 0.6003 | D31: 2.5615 | F31: 39812 | G31: 10.1032 | H31: 0.3947 | I31: 4.1199 | K31: 39812 | L31: 15.5587 | M31: 0.4338 | N31: 2.8012
A32: 39903 | B32: 23.0337 | C32: 0.5573 | D32: 2.4491 | F32: 39903 | G32: 13.854 | H32: 0.3637 | I32: 2.607 | K32: 39903 | L32: 16.2682 | M32: 0.4241 | N32: 2.4459
A33: 39994 | B33: 23.4502 | C33: 0.819 | D33: 3.7363 | F33: 39994 | G33: 13.243 | H33: 0.6535 | I33: 4.8864 | K33: 39994 | L33: 12.9655 | M33: 0.6786 | N33: 5.0899
A34: 40086 | B34: 23.7305 | C34: 1.1129 | D34: 5.095 | F34: 40086 | G34: 12.0193 | H34: 0.9064 | I34: 7.3989 | K34: 40086 | L34: 19.6874 | M34: 0.7178 | N34: 4.1403
A35: 40177 | B35: 24.3524 | C35: 1.2086 | D35: 5.3318 | F35: 40177 | G35: 12.7032 | H35: 1.057 | I35: 8.1337 | K35: 40177 | L35: 28.7241 | M35: 0.7536 | N35: 3.1482
A36: 40268 | B36: 25.8095 | C36: 1.1838 | D36: 4.8943 | F36: 40268 | G36: 10.9016 | H36: 1.1069 | I36: 10.5495 | K36: 40268 | L36: 30.4956 | M36: 0.8402 | N36: 3.2961
A37: 40359 | B37: 27.591 | C37: 1.2505 | D37: 4.8979 | F37: 40359 | G37: 11.2506 | H37: 1.0836 | I37: 9.9976 | K37: 40359 | L37: 37.1507 | M37: 0.9226 | N37: 2.7482
A38: 40451 | B38: 27.9775 | C38: 1.8064 | D38: 7.1649 | F38: 40451 | G38: 14.6831 | H38: 1.7822 | I38: 12.7857 | K38: 40451 | L38: 35.8636 | M38: 1.2074 | N38: 3.7478
... A101: 46203 | B101: 7.9114 | C101: 1.4567 | D101: 21.4384 | F101: 46203 | G101: 2.1572 | H101: 1.356 | I101: 71.8458 | K101: 46203 | L101: 8.7252 | M101: 1.4772 | N101: 20.0635
A102: 46295 | B102: #N/A N/A | C102: 1.1006 | D102: 16.1978 | F102: 46295 | G102: #N/A N/A | H102: 1.0566 | I102: 55.9815 | K102: 46295 | L102: #N/A N/A | M102: 1.0156 | N102: 13.794
P235: =_xll.BDH($P$1,$Q$2:$S$2,"02/10/2001","","FX=ARS","Dir=V","Dts=S","Sort=A","Quote=C","QtTyp=Y","Days=T","Per=cw","DtFmt=D","UseDPDF=Y","cols=4;rows=1072") -> 38807 | Q235: 37.4756 | R235: #N/A N/A | S235: #N/A N/A
P236: 38814 | Q236: 37.4756 | R236: #N/A N/A | S236: #N/A N/A
P237: 38821 | Q237: 37.4756 | R237: #N/A N/A | S237: #N/A N/A
P238: 38828 | Q238: 37.4756 | R238: #N/A N/A | S238: #N/A N/A
P239: 38835 | Q239: 37.4756 | R239: #N/A N/A | S239: #N/A N/A
P240: 38842 | Q240: 37.4756 | R240: #N/A N/A | S240: #N/A N/A
P241: 38849 | Q241: 37.4756 | R241: #N/A N/A | S241: #N/A N/A
P242: 38856 | Q242: 37.4756 | R242: #N/A N/A | S242: #N/A N/A
P243: 38863 | Q243: 37.4756 | R243: #N/A N/A | S243: #N/A N/A
P244: 38870 | Q244: 37.4756 | R244: #N/A N/A | S244: #N/A N/A
P245: 38877 | Q245: 37.4756 | R245: #N/A N/A | S245: #N/A N/A
P246: 38884 | Q246: 37.4756 | R246: #N/A N/A | S246: #N/A N/A
P247: 38891 | Q247: 37.4756 | R247: #N/A N/A | S247: #N/A N/A
... P302: 39276 | Q302: 23.7482 | R302: #N/A N/A | S302: #N/A N/A
P303: 39283 | Q303: 23.7482 | R303: 1.1121 | S303: 4.2362
P304: 39290 | Q304: 23.7482 | R304: 1.0444 | S304: 3.9786
P305: 39297 | Q305: 23.7482 | R305: 1.0369 | S305: 3.95
P306: 39304 | Q306: 23.7482 | R306: 0.9442 | S306: 3.597
P307: 39311 | Q307: 23.7482 | R307: 0.8666 | S307: 3.3012
P308: 39318 | Q308: 23.7482 | R308: 0.9167 | S308: 3.492
P309: 39325 | Q309: 23.7482 | R309: 0.8891 | S309: 3.3871
P310: 39332 | Q310: 23.7482 | R310: 0.8691 | S310: 3.3108
P311: 39339 | Q311: 23.7482 | R311: 0.8566 | S311: 3.2631
P312: 39346 | Q312: 23.7482 | R312: 0.8616 | S312: 3.2821
P313: 39353 | Q313: 13.4893 | R313: 0.7279 | S313: 5.5955
P314: 39360 | Q314: 13.4893 | R314: 0.7972 | S314: 6.1284
... P482: 40536 | Q482: 24.912 | R482: 0.9924 | S482: 4.2367
P483: 40543 | Q483: 24.2827 | R483: 0.9171 | S483: 4.0217 | U483: =_xll.BDH($U$1,$Q$2:$S$2,"02/10/2001","","FX=ARS","Dir=V","Dts=S","Sort=A","Quote=C","QtTyp=Y","Days=T","Per=cw","DtFmt=D","UseDPDF=Y","cols=4;rows=772") -> 40907 | V483: 24.8638 | W483: #N/A N/A | X483: #N/A N/A
P484: 40550 | Q484: 24.2827 | R484: 0.9844 | S484: 4.3167 | U484: 40914 | V484: 24.8638 | W484: #N/A N/A | X484: #N/A N/A
P485: 40557 | Q485: 24.2827 | R485: 0.9352 | S485: 4.1008 | U485: 40921 | V485: 24.8638 | W485: #N/A N/A | X485: #N/A N/A
P486: 40564 | Q486: 24.2827 | R486: 0.968 | S486: 4.2447 | U486: 40928 | V486: 24.8638 | W486: #N/A N/A | X486: #N/A N/A
P487: 40571 | Q487: 24.2827 | R487: 0.9024 | S487: 3.9569 | U487: 40935 | V487: 24.8638 | W487: #N/A N/A | X487: #N/A N/A
P488: 40578 | Q488: 24.2827 | R488: 0.9352 | S488: 4.1008 | U488: 40942 | V488: 24.8638 | W488: #N/A N/A | X488: #N/A N/A
P489: 40585 | Q489: 24.2827 | R489: 0.927 | S489: 4.0648 | U489: 40949 | V489: 24.8638 | W489: #N/A N/A | X489: #N/A N/A
P490: 40592 | Q490: 24.2827 | R490: 0.9073 | S490: 3.9785 | U490: 40956 | V490: 24.8638 | W490: #N/A N/A | X490: #N/A N/A
P491: 40599 | Q491: 24.2827 | R491: 0.8892 | S491: 3.8994 | U491: 40963 | V491: 24.8638 | W491: #N/A N/A | X491: #N/A N/A
P492: 40606 | Q492: 24.2827 | R492: 0.8991 | S492: 3.9425 | U492: 40970 | V492: 24.8638 | W492: #N/A N/A | X492: #N/A N/A
P493: 40613 | Q493: 24.2827 | R493: 0.8778 | S493: 3.849 | U493: 40977 | V493: 24.8638 | W493: #N/A N/A | X493: #N/A N/A
P494: 40620 | Q494: 24.2827 | R494: 0.84 | S494: 3.6835 | U494: 40984 | V494: 24.8638 | W494: #N/A N/A | X494: #N/A N/A
P495: 40627 | Q495: 24.2827 | R495: 0.8531 | S495: 3.7411 | U495: 40991 | V495: 24.8638 | W495: #N/A N/A | X495: #N/A N/A
... P711: 42139 | Q711: 29.9995 | R711: 1.3445 | S711: 5.003 | U711: 42503 | V711: 35.2192 | W711: #N/A N/A | X711: #N/A N/A
P712: 42146 | Q712: 29.9995 | R712: 1.2643 | S712: 4.7044 | U712: 42510 | V712: 35.2192 | W712: 2.7853 | X712: 6.9914
P713: 42153 | Q713: 29.9995 | R713: 1.1951 | S713: 4.4471 | U713: 42517 | V713: 35.2192 | W713: 2.794 | X713: 7.0131
P714: 42160 | Q714: 29.9995 | R714: 1.1951 | S714: 4.4471 | U714: 42524 | V714: 35.2192 | W714: 2.846 | X714: 7.1438
P715: 42167 | Q715: 29.9995 | R715: 1.2422 | S715: 4.6221 | U715: 42531 | V715: 35.2192 | W715: 2.8807 | X715: 7.2309
P716: 42174 | Q716: 29.9995 | R716: 1.1453 | S716: 4.2618 | U716: 42538 | V716: 35.2192 | W716: 2.9501 | X716: 7.4052
P717: 42181 | Q717: 29.9995 | R717: 1.2228 | S717: 4.55 | U717: 42545 | V717: 35.2192 | W717: 3.2018 | X717: 8.0368
P718: 42188 | Q718: 29.9995 | R718: 1.1619 | S718: 4.3236 | U718: 42552 | V718: 22.9174 | W718: 2.0957 | X718: 7.9643
P719: 42195 | Q719: 29.9995 | R719: #N/A N/A | S719: #N/A N/A | U719: 42559 | V719: 22.9174 | W719: 2.0176 | X719: 7.6675
P720: 42202 | Q720: 29.9995 | R720: #N/A N/A | S720: #N/A N/A | U720: 42566 | V720: 22.9174 | W720: 2.1334 | X720: 8.1076
P721: 42209 | Q721: 29.9995 | R721: #N/A N/A | S721: #N/A N/A | U721: 42573 | V721: 22.9174 | W721: 2.1819 | X721: 8.2919
P722: 42216 | Q722: 29.9995 | R722: #N/A N/A | S722: #N/A N/A | U722: 42580 | V722: 22.9174 | W722: 2.2034 | X722: 8.3738
P723: 42223 | Q723: 29.9995 | R723: #N/A N/A | S723: #N/A N/A | U723: 42587 | V723: 22.9174 | W723: 2.1119 | X723: 8.0258
P724: 42230 | Q724: 29.9995 | R724: #N/A N/A | S724: #N/A N/A | U724: 42594 | V724: 22.9174 | W724: 2.1226 | X724: 8.0667
P725: 42237 | Q725: 29.9995 | R725: #N/A N/A | S725: #N/A N/A | U725: 42601 | V725: 22.9174 | W725: 2.155 | X725: 8.1895
P726: 42244 | Q726: 29.9995 | R726: #N/A N/A | S726: #N/A N/A | U726: 42608 | V726: 22.9174 | W726: 2.1684 | X726: 8.2407
P727: 42251 | Q727: 29.9995 | R727: #N/A N/A | S727: #N/A N/A | U727: 42615 | V727: 22.9174 | W727: 2.2358 | X727: 8.4967
P728: 42258 | Q728: 29.9995 | R728: #N/A N/A | S728: #N/A N/A | U728: 42622 | V728: 22.9174 | W728: 2.3274 | X728: 8.8447
P729: 42265 | Q729: 29.9995 | R729: #N/A N/A | S729: #N/A N/A | U729: 42629 | V729: 22.9174 | W729: 2.4028 | X729: 9.1313
P730: 42272 | Q730: 29.9995 | R730: #N/A N/A | S730: #N/A N/A | U730: 42636 | V730: 22.9174 | W730: 2.4782 | X730: 9.418
...

Sheet rel ROE PBV
A1: EQY_FUND_CRNCY | B1: REL_INDEX | C1: FA_ADJUSTED
A2: ARS | C2: ADJUSTED
A3: Ticker | B3: Name | C3: Mkt Cap (ARS) | D3: Last Px (ARS) | E3: Chg Pct 1D | F3: Chg Pct 1M | G3: Rev - 1 Yr Gr:Y | H3: EPS - 1 Yr Gr:Y | I3: P/E | J3: ROE | K3: Dvd 12M Yld | L3: P/B
A4: None (6 securities)
A5: Average | B5: Average | C5: =IFERROR(AVERAGE($C6:$C10),0) -> 4506254.8 | D5: =IFERROR(AVERAGE($D6:$D10),0) -> 5333.4 | E5: =IFERROR(AVERAGE($E6:$E10),0) -> 2.0412834 | F5: =IFERROR(AVERAGE($F6:$F10),0) -> -10.082648 | G5: =IFERROR(AVERAGE($G6:$G10),0) -> -14.640596 | H5: =IFERROR(AVERAGE($H6:$H10),0) -> -16.298879 | I5: =IFERROR(AVERAGE($I6:$I10),0) -> 24.032804 | J5: =IFERROR(AVERAGE($J6:$J9),0) -> 2.8247348 | K5: =IFERROR(AVERAGE($K6:$K10),0) -> 4.3091581 | L5: =IFERROR(AVERAGE($L6:$L10),0) -> 1.1047071
A6: BMA AR Equity | B6: BANCO MACRO SA-B | C6: {=_xll.BDP($A6,"CRNCY_ADJ_MKT_CAP",$A$1:$C$1,$A$2:$C$2)} -> 6816146.9 | D6: {=_xll.BDP($A6,"CRNCY_ADJ_PX_LAST",$A$1:$C$1,$A$2:$C$2)} -> 10660 | E6: {=_xll.BDP($A6,"CHG_PCT_1D",$A$1:$C$1,$A$2:$C$2)} -> 2.10728 | F6: {=_xll.BDP($A6,"CHG_PCT_1M",$A$1:$C$1,$A$2:$C$2)} -> -14.17069 | G6: {=_xll.BDP($A6,"SALES_GROWTH","FUND_PER","Y",$A$1:$C$1,$A$2:$C$2)} -> -24.445119 | H6: {=_xll.BDP($A6,"DILUTED_EPS_AFT_XO_ITEMS_GROWTH","FUND_PER","Y",$A$1:$C$1,$A$2:$C$2)} -> -31.949346 | I6: {=_xll.BDP($A6,"PE_RATIO",$A$1:$C$1,$A$2:$C$2)} -> 15.943538 | J6: {=_xll.BDP($A6,"RETURN_COM_EQY",$A$1:$C$1,$A$2:$C$2)} -> 8.1844019 | K6: {=_xll.BDP($A6,"DIVIDEND_12_MONTH_YIELD",$A$1:$C$1,$A$2:$C$2)} -> 6.1209736 | L6: {=_xll.BDP($A6,"PX_TO_BOOK_RATIO",$A$1:$C$1,$A$2:$C$2)} -> 1.0833649
A7: BBAR AR Equity | B7: BANCO BBVA ARGENTINA SA | C7: {=_xll.BDP($A7,"CRNCY_ADJ_MKT_CAP",$A$1:$C$1,$A$2:$C$2)} -> 4331860.3 | D7: {=_xll.BDP($A7,"CRNCY_ADJ_PX_LAST",$A$1:$C$1,$A$2:$C$2)} -> 7070 | E7: {=_xll.BDP($A7,"CHG_PCT_1D",$A$1:$C$1,$A$2:$C$2)} -> 3.970588 | F7: {=_xll.BDP($A7,"CHG_PCT_1M",$A$1:$C$1,$A$2:$C$2)} -> -10.90107 | G7: {=_xll.BDP($A7,"SALES_GROWTH","FUND_PER","Y",$A$1:$C$1,$A$2:$C$2)} -> -10.376148 | H7: {=_xll.BDP($A7,"DILUTED_EPS_AFT_XO_ITEMS_GROWTH","FUND_PER","Y",$A$1:$C$1,$A$2:$C$2)} -> -48.947144 | I7: {=_xll.BDP($A7,"PE_RATIO",$A$1:$C$1,$A$2:$C$2)} -> 14.052408 | J7: {=_xll.BDP($A7,"RETURN_COM_EQY",$A$1:$C$1,$A$2:$C$2)} -> 8.8903003 | K7: {=_xll.BDP($A7,"DIVIDEND_12_MONTH_YIELD",$A$1:$C$1,$A$2:$C$2)} -> 3.4514552 | L7: {=_xll.BDP($A7,"PX_TO_BOOK_RATIO",$A$1:$C$1,$A$2:$C$2)} -> 1.0346004
A8: GGAL AR Equity | B8: GRUPO FINANCIERO GALICIA-B | C8: {=_xll.BDP($A8,"CRNCY_ADJ_MKT_CAP",$A$1:$C$1,$A$2:$C$2)} -> 9677678.7 | D8: {=_xll.BDP($A8,"CRNCY_ADJ_PX_LAST",$A$1:$C$1,$A$2:$C$2)} -> 6025 | E8: {=_xll.BDP($A8,"CHG_PCT_1D",$A$1:$C$1,$A$2:$C$2)} -> 1.430976 | F8: {=_xll.BDP($A8,"CHG_PCT_1M",$A$1:$C$1,$A$2:$C$2)} -> -13.92857 | G8: {=_xll.BDP($A8,"SALES_GROWTH","FUND_PER","Y",$A$1:$C$1,$A$2:$C$2)} -> -8.8973042 | H8: {=_xll.BDP($A8,"DILUTED_EPS_AFT_XO_ITEMS_GROWTH","FUND_PER","Y",$A$1:$C$1,$A$2:$C$2)} -> -91.3279 | I8: {=_xll.BDP($A8,"PE_RATIO",$A$1:$C$1,$A$2:$C$2)} -> 55.750138 | J8: {=_xll.BDP($A8,"RETURN_COM_EQY",$A$1:$C$1,$A$2:$C$2)} -> 2.157227 | K8: {=_xll.BDP($A8,"DIVIDEND_12_MONTH_YIELD",$A$1:$C$1,$A$2:$C$2)} -> 5.1177533 | L8: {=_xll.BDP($A8,"PX_TO_BOOK_RATIO",$A$1:$C$1,$A$2:$C$2)} -> 1.0521917
A9: SUPV AR Equity | B9: GRUPO SUPERVIELLE SA CL-B | C9: {=_xll.BDP($A9,"CRNCY_ADJ_MKT_CAP",$A$1:$C$1,$A$2:$C$2)} -> 1082431.9 | D9: {=_xll.BDP($A9,"CRNCY_ADJ_PX_LAST",$A$1:$C$1,$A$2:$C$2)} -> 2370 | E9: {=_xll.BDP($A9,"CHG_PCT_1D",$A$1:$C$1,$A$2:$C$2)} -> 2.420052 | F9: {=_xll.BDP($A9,"CHG_PCT_1M",$A$1:$C$1,$A$2:$C$2)} -> -12.62673 | G9: {=_xll.BDP($A9,"SALES_GROWTH","FUND_PER","Y",$A$1:$C$1,$A$2:$C$2)} -> -15.543922 | H9: {=_xll.BDP($A9,"DILUTED_EPS_AFT_XO_ITEMS_GROWTH","FUND_PER","Y",$A$1:$C$1,$A$2:$C$2)} -> #N/A N/A | I9: {=_xll.BDP($A9,"PE_RATIO",$A$1:$C$1,$A$2:$C$2)} -> #N/A N/A | J9: {=_xll.BDP($A9,"RETURN_COM_EQY",$A$1:$C$1,$A$2:$C$2)} -> -7.93299 | K9: {=_xll.BDP($A9,"DIVIDEND_12_MONTH_YIELD",$A$1:$C$1,$A$2:$C$2)} -> #N/A N/A | L9: {=_xll.BDP($A9,"PX_TO_BOOK_RATIO",$A$1:$C$1,$A$2:$C$2)} -> 0.88875586
A10: VALO AR Equity | B10: BANCO DE VALORES | C10: {=_xll.BDP($A10,"CRNCY_ADJ_MKT_CAP",$A$1:$C$1,$A$2:$C$2)} -> 623156.31 | D10: {=_xll.BDP($A10,"CRNCY_ADJ_PX_LAST",$A$1:$C$1,$A$2:$C$2)} -> 542 | E10: {=_xll.BDP($A10,"CHG_PCT_1D",$A$1:$C$1,$A$2:$C$2)} -> 0.2775208 | F10: {=_xll.BDP($A10,"CHG_PCT_1M",$A$1:$C$1,$A$2:$C$2)} -> 1.213819 | G10: {=_xll.BDP($A10,"SALES_GROWTH","FUND_PER","Y",$A$1:$C$1,$A$2:$C$2)} -> -13.940484 | H10: {=_xll.BDP($A10,"DILUTED_EPS_AFT_XO_ITEMS_GROWTH","FUND_PER","Y",$A$1:$C$1,$A$2:$C$2)} -> 107.02887 | I10: {=_xll.BDP($A10,"PE_RATIO",$A$1:$C$1,$A$2:$C$2)} -> 10.385131 | J10: {=_xll.BDP($A10,"RETURN_COM_EQY",$A$1:$C$1,$A$2:$C$2)} -> 17.598423 | K10: {=_xll.BDP($A10,"DIVIDEND_12_MONTH_YIELD",$A$1:$C$1,$A$2:$C$2)} -> 2.5464501 | L10: {=_xll.BDP($A10,"PX_TO_BOOK_RATIO",$A$1:$C$1,$A$2:$C$2)} -> 1.4646228
A11: BHIP AR Equity | B11: HIPOTECARIO | C11: {=_xll.BDP($A11,"CRNCY_ADJ_MKT_CAP",$A$1:$C$1,$A$2:$C$2)} -> 393923.35 | D11: {=_xll.BDP($A11,"CRNCY_ADJ_PX_LAST",$A$1:$C$1,$A$2:$C$2)} -> 253 | E11: {=_xll.BDP($A11,"CHG_PCT_1D",$A$1:$C$1,$A$2:$C$2)} -> -0.7843137 | F11: {=_xll.BDP($A11,"CHG_PCT_1M",$A$1:$C$1,$A$2:$C$2)} -> -16.22517 | G11: {=_xll.BDP($A11,"SALES_GROWTH","FUND_PER","Y",$A$1:$C$1,$A$2:$C$2)} -> -44.149224 | H11: {=_xll.BDP($A11,"DILUTED_EPS_AFT_XO_ITEMS_GROWTH","FUND_PER","Y",$A$1:$C$1,$A$2:$C$2)} -> -85.824922 | I11: {=_xll.BDP($A11,"PE_RATIO",$A$1:$C$1,$A$2:$C$2)} -> 75.159 | J11: {=_xll.BDP($A11,"RETURN_COM_EQY",$A$1:$C$1,$A$2:$C$2)} -> 0.75529065 | K11: {=_xll.BDP($A11,"DIVIDEND_12_MONTH_YIELD",$A$1:$C$1,$A$2:$C$2)} -> 18.056372 | L11: {=_xll.BDP($A11,"PX_TO_BOOK_RATIO",$A$1:$C$1,$A$2:$C$2)} -> 0.56786196
A13: The BLOOMBERG PROFESSIONAL service, BLOOMBERG Data and BLOOMBERG Order Management Systems (the "Services") are owned and distributed locally by Bloomberg Finance L.P. ("BFLP") and its subsidiaries in all jurisdictions other than Argentina, Bermuda, China, India, Japan and Korea (the "BLP Countries"). BFLP is a wholly-owned subsidiary of Bloomberg L.P. ("BLP"). BLP provides BFLP with all global marketing and operational support and service for the Services and distributes the Services either directly or through a non-BFLP subsidiary in the BLP Countries. The Services include electronic trading and order-routing services, which are available only to sophisticated institutional investors and only where necessary legal clearances have been obtained. BFLP, BLP and their affiliates do not provide investment advice or guarantee the accuracy of prices or information in the Services. Nothing on the Services shall constitute an offering of financial instruments by BFLP, BLP or their affiliates. BLOOMBERG, BLOOMBERG PROFESSIONAL, BLOOMBERG MARKET, BLOOMBERG NEWS, BLOOMBERG ANYWHERE, BLOOMBERG TRADEBOOK, BLOOMBERG BONDTRADER, BLOOMBERG TELEVISION, BLOOMBERG RADIO, BLOOMBERG PRESS and BLOOMBERG.COM are trademarks and service marks of BFLP, a Delaware limited partnership, or its subsidiaries.
G16: g | H16: 0.04
G17: Ke | H17: {=+_xll.BDP("ZO283201@IBVL Corp","YAS_BOND_YLD")/100} -> 0.11184204
H18: ROE
H19: 0.07 | I19: =+H19+2% -> 0.09 | J19: =+I19+2% -> 0.11 | K19: =+J19+2% -> 0.13 | L19: =+K19+2% -> 0.15 | M19: =+L19+2% -> 0.17 | N19: =+M19+2% -> 0.19 | O19: =+N19+2% -> 0.21
F20: g(%) | G20: 0.06 | H20: =+(H$19-$G20)/($H$17-$H$16) -> 0.13919427 | I20: =+(I$19-$G20)/($H$17-$H$16) -> 0.4175828 | J20: =+(J$19-$G20)/($H$17-$H$16) -> 0.69597133 | K20: =+(K$19-$G20)/($H$17-$H$16) -> 0.97435986 | L20: =+(L$19-$G20)/($H$17-$H$16) -> 1.2527484 | M20: =+(M$19-$G20)/($H$17-$H$16) -> 1.5311369 | N20: =+(N$19-$G20)/($H$17-$H$16) -> 1.8095255 | O20: =+(O$19-$G20)/($H$17-$H$16) -> 2.087914
G21: =+G20-1% -> 0.05 | H21: =+(H$19-$G21)/($H$17-$H$16) -> 0.27838853 | I21: =+(I$19-$G21)/($H$17-$H$16) -> 0.55677706 | J21: =+(J$19-$G21)/($H$17-$H$16) -> 0.83516559 | K21: =+(K$19-$G21)/($H$17-$H$16) -> 1.1135541 | L21: =+(L$19-$G21)/($H$17-$H$16) -> 1.3919427 | M21: =+(M$19-$G21)/($H$17-$H$16) -> 1.6703312 | N21: =+(N$19-$G21)/($H$17-$H$16) -> 1.9487197 | O21: =+(O$19-$G21)/($H$17-$H$16) -> 2.2271083
G22: =+G21-1% -> 0.04 | H22: =+(H$19-$G22)/($H$17-$H$16) -> 0.4175828 | I22: =+(I$19-$G22)/($H$17-$H$16) -> 0.69597133 | J22: =+(J$19-$G22)/($H$17-$H$16) -> 0.97435986 | K22: =+(K$19-$G22)/($H$17-$H$16) -> 1.2527484 | L22: =+(L$19-$G22)/($H$17-$H$16) -> 1.5311369 | M22: =+(M$19-$G22)/($H$17-$H$16) -> 1.8095255 | N22: =+(N$19-$G22)/($H$17-$H$16) -> 2.087914 | O22: =+(O$19-$G22)/($H$17-$H$16) -> 2.3663025
G23: =+G22-1% -> 0.03 | H23: =+(H$19-$G23)/($H$17-$H$16) -> 0.55677706 | I23: =+(I$19-$G23)/($H$17-$H$16) -> 0.83516559 | J23: =+(J$19-$G23)/($H$17-$H$16) -> 1.1135541 | K23: =+(K$19-$G23)/($H$17-$H$16) -> 1.3919427 | L23: =+(L$19-$G23)/($H$17-$H$16) -> 1.6703312 | M23: =+(M$19-$G23)/($H$17-$H$16) -> 1.9487197 | N23: =+(N$19-$G23)/($H$17-$H$16) -> 2.2271083 | O23: =+(O$19-$G23)/($H$17-$H$16) -> 2.5054968
G24: =+G23-1% -> 0.02 | H24: =+(H$19-$G24)/($H$17-$H$16) -> 0.69597133 | I24: =+(I$19-$G24)/($H$17-$H$16) -> 0.97435986 | J24: =+(J$19-$G24)/($H$17-$H$16) -> 1.2527484 | K24: =+(K$19-$G24)/($H$17-$H$16) -> 1.5311369 | L24: =+(L$19-$G24)/($H$17-$H$16) -> 1.8095255 | M24: =+(M$19-$G24)/($H$17-$H$16) -> 2.087914 | N24: =+(N$19-$G24)/($H$17-$H$16) -> 2.3663025 | O24: =+(O$19-$G24)/($H$17-$H$16) -> 2.644691
G25: =+G24-1% -> 0.01 | H25: =+(H$19-$G25)/($H$17-$H$16) -> 0.83516559 | I25: =+(I$19-$G25)/($H$17-$H$16) -> 1.1135541 | J25: =+(J$19-$G25)/($H$17-$H$16) -> 1.3919427 | K25: =+(K$19-$G25)/($H$17-$H$16) -> 1.6703312 | L25: =+(L$19-$G25)/($H$17-$H$16) -> 1.9487197 | M25: =+(M$19-$G25)/($H$17-$H$16) -> 2.2271083 | N25: =+(N$19-$G25)/($H$17-$H$16) -> 2.5054968 | O25: =+(O$19-$G25)/($H$17-$H$16) -> 2.7838853

Sheet ROE_WACC
A1: Start Date | B1: 42495
A2: End Date
B4: GGAL AR Equity | D4: BMA AR Equity | F4: SUPV AR Equity | H4: BBAR AR Equity
A5: Dates | B5: RETURN_COM_EQY | C5: WACC | D5: RETURN_COM_EQY | E5: WACC | F5: RETURN_COM_EQY | G5: WACC | H5: RETURN_COM_EQY | I5: WACC | K5: =+A5 -> Dates | L5: GGAL_ROE_WACC | M5: BMA_ROE_WACC | N5: SUPV_ROE_WACC | O5: BBAR_ROE_WACC
A6: =_xll.BDH(B$4,B$5:C$5,$B1,$B2,"Dir=V","Per=W","Days=A","Dts=S","cols=3;rows=42") -> 42551 | B6: 38.1897 | C6: 9.5328 | D6: =_xll.BDH(D$4,D$5:E$5,$B1,$B2,"Dir=V","Per=W","Days=A","Dts=H","cols=2;rows=42") -> 39.7966 | E6: 12.5888 | F6: =_xll.BDH(F$4,F$5:G$5,$B1,$B2,"Dir=V","Per=W","Days=A","Dts=H","cols=2;rows=42") -> 22.9174 | G6: 7.9343 | H6: =_xll.BDH(H$4,H$5:I$5,$B1,$B2,"Dir=V","Per=W","Days=A","Dts=H","cols=2;rows=42") -> 32.5946 | I6: 12.9777 | K6: =+A6 -> 42551 | L6: =+B6/C6 -> 4.0061367 | M6: =+D6/E6 -> 3.1612703 | N6: =+F6/G6 -> 2.888396 | O6: =+H6/I6 -> 2.5115853
A7: 42643 | B7: 37.2248 | C7: 12.673 | D7: 39.6279 | E7: 17.0426 | F7: 27.0358 | G7: 11.4193 | H7: 29.9202 | I7: 17.1627 | K7: =+A7 -> 42643 | L7: =+B7/C7 -> 2.9373313 | M7: =+D7/E7 -> 2.3252262 | N7: =+F7/G7 -> 2.3675532 | O7: =+H7/I7 -> 1.7433271
A8: 42735 | B8: 37.2993 | C8: 7.6644 | D8: 34.4404 | E8: 9.8148 | F8: 28.1841 | G8: 6.4439 | H8: 24.1492 | I8: 10.4537 | K8: =+A8 -> 42735 | L8: =+B8/C8 -> 4.8665649 | M8: =+D8/E8 -> 3.5090272 | N8: =+F8/G8 -> 4.3737643 | O8: =+H8/I8 -> 2.3101103
A9: 42825 | B9: 34.8254 | C9: 12.0289 | D9: 34.3838 | E9: 15.1276 | F9: 28.969 | G9: 8.2239 | H9: 18.9396 | I9: 15.4163 | K9: =+A9 -> 42825 | L9: =+B9/C9 -> 2.8951442 | M9: =+D9/E9 -> 2.2729184 | N9: =+F9/G9 -> 3.522538 | O9: =+H9/I9 -> 1.2285438
A10: 42916 | B10: 36.7779 | C10: 17.1759 | D10: 27.6774 | E10: 20.3619 | F10: 25.531 | G10: 12.2257 | H10: 19.2002 | I10: 20.561 | K10: =+A10 -> 42916 | L10: =+B10/C10 -> 2.1412502 | M10: =+D10/E10 -> 1.3592739 | N10: =+F10/G10 -> 2.0883058 | O10: =+H10/I10 -> 0.93381645
A11: 43008 | B11: 30.6679 | C11: 14.9892 | D11: 28.8001 | E11: 17.4276 | F11: 18.1957 | G11: 12.4492 | H11: 18.148 | I11: 17.2251 | K11: =+A11 -> 43008 | L11: =+B11/C11 -> 2.0459998 | M11: =+D11/E11 -> 1.6525569 | N11: =+F11/G11 -> 1.4615959 | O11: =+H11/I11 -> 1.0535788
A12: 43100 | B12: 29.867 | C12: 12.9852 | D12: 29.3276 | E12: 12.9247 | F12: 17.0868 | G12: 11.1938 | H12: 22.5949 | I12: 12.1924 | K12: =+A12 -> 43100 | L12: =+B12/C12 -> 2.3000801 | M12: =+D12/E12 -> 2.2691126 | N12: =+F12/G12 -> 1.5264521 | O12: =+H12/I12 -> 1.8531954
A13: 43190 | B13: 28.042 | C13: 12.758 | D13: 31.3764 | E13: 15.0709 | F13: 20.0705 | G13: 11.7102 | H13: 22.4177 | I13: 14.0047 | K13: =+A13 -> 43190 | L13: =+B13/C13 -> 2.1979934 | M13: =+D13/E13 -> 2.0819195 | N13: =+F13/G13 -> 1.7139332 | O13: =+H13/I13 -> 1.6007269
A14: 43281 | B14: 32.5252 | C14: 13.9464 | D14: 29.0658 | E14: 15.2662 | F14: 17.4091 | G14: 11.3748 | H14: 26.5814 | I14: 14.3289 | K14: =+A14 -> 43281 | L14: =+B14/C14 -> 2.3321574 | M14: =+D14/E14 -> 1.9039316 | N14: =+F14/G14 -> 1.5304972 | O14: =+H14/I14 -> 1.8550901
A15: 43373 | B15: 30.9458 | C15: 13.8 | D15: 29.8863 | E15: 14.2207 | F15: 15.2578 | G15: 13.1144 | H15: 30.084 | I15: 14.6546 | K15: =+A15 -> 43373 | L15: =+B15/C15 -> 2.2424493 | M15: =+D15/E15 -> 2.1016054 | N15: =+F15/G15 -> 1.1634387 | O15: =+H15/I15 -> 2.0528708
A16: 43465 | B16: 30.0252 | C16: 16.3694 | D16: 31.0943 | E16: 16.547 | F16: 16.289 | G16: 16.401 | H16: 34.9533 | I16: 16.0334 | K16: =+A16 -> 43465 | L16: =+B16/C16 -> 1.8342273 | M16: =+D16/E16 -> 1.8791503 | N16: =+F16/G16 -> 0.99317115 | O16: =+H16/I16 -> 2.1800304
A17: 43555 | B17: 37.2724 | C17: 21.2106 | D17: 28.7331 | E17: 21.9358 | F17: 2.9889 | G17: 17.4804 | H17: 34.0392 | I17: 20.9453 | K17: =+A17 -> 43555 | L17: =+B17/C17 -> 1.7572534 | M17: =+D17/E17 -> 1.3098724 | N17: =+F17/G17 -> 0.17098579 | O17: =+H17/I17 -> 1.6251474
A18: 43646 | B18: 48.8803 | C18: 14.7887 | D18: 28.3938 | E18: 16.0753 | F18: 6.1919 | G18: 13.2366 | H18: 47.471 | I18: 15.092 | K18: =+A18 -> 43646 | L18: =+B18/C18 -> 3.3052466 | M18: =+D18/E18 -> 1.7662999 | N18: =+F18/G18 -> 0.46778629 | O18: =+H18/I18 -> 3.1454413
... A46: 46203 | B46: 2.1572 | C46: 26.3064 | D46: 7.9114 | E46: 22.9581 | F46: -7.2049 | G46: 23.2206 | H46: 8.7252 | I46: 26.9111 | K46: =+A46 -> 46203 | L46: =+B46/C46 -> 0.082002859 | M46: =+D46/E46 -> 0.34460169 | N46: =+F46/G46 -> -0.31028053 | O46: =+H46/I46 -> 0.32422309
A47: 46308 | B47: 2.1572 | C47: 32.5193 | D47: 7.9114 | E47: 28.4549 | F47: -7.2049 | G47: 28.8624 | H47: 8.7252 | I47: 33.6485

Sheet NIM
A1: Start Date | B1: 43956
A2: End Date
B4: GGAL AR Equity | C4: SUPV AR Equity | D4: BMA AR Equity | E4: BBAR AR Equity | F4: GGAL AR Equity | G4: SUPV AR Equity | H4: BMA AR Equity | I4: BBAR AR Equity
A5: Dates | B5: T12_NET_INT_MARGIN | C5: T12_NET_INT_MARGIN | D5: T12_NET_INT_MARGIN | E5: T12_NET_INT_MARGIN | F5: RETURN_COM_EQY | G5: RETURN_COM_EQY | H5: RETURN_COM_EQY | I5: RETURN_COM_EQY
A6: Dates | B6: =+B4 -> GGAL AR Equity | C6: =+C4 -> SUPV AR Equity | D6: =+D4 -> BMA AR Equity | E6: =+E4 -> BBAR AR Equity | F6: =+F4 -> GGAL AR Equity | G6: =+G4 -> SUPV AR Equity | H6: =+H4 -> BMA AR Equity | I6: =+I4 -> BBAR AR Equity
A7: =_xll.BDH(B$4,B$5,$B1,$B2,"Dir=V","Per=W","Days=A","Dts=S","cols=2;rows=25") -> 44012 | B7: 15.0816 | C7: =_xll.BDH(C$4,C$5,$B1,$B2,"Dir=V","Per=W","Days=A","Dts=H","cols=1;rows=25") -> #N/A N/A | D7: =_xll.BDH(D$4,D$5,$B1,$B2,"Dir=V","Per=W","Days=A","Dts=H","cols=1;rows=25") -> 34.9281 | E7: =_xll.BDH(E$4,E$5,$B1,$B2,"Dir=V","Per=W","Days=A","Dts=H","cols=1;rows=25") -> 32.4297 | F7: =_xll.BDH(F$4,F$5,$B1,$B2,"Dir=V","Per=W","Days=A","Dts=H","cols=1;rows=25") -> 25.2085 | G7: =_xll.BDH(G$4,G$5,$B1,$B2,"Dir=V","Per=W","Days=A","Dts=H","cols=1;rows=25") -> 4.9406 | H7: =_xll.BDH(H$4,H$5,$B1,$B2,"Dir=V","Per=W","Days=A","Dts=H","cols=1;rows=25") -> 41.2537 | I7: =_xll.BDH(I$4,I$5,$B1,$B2,"Dir=V","Per=W","Days=A","Dts=H","cols=1;rows=25") -> 18.5288
A8: 44104 | B8: 15.7372 | C8: #N/A N/A | D8: 32.7887 | E8: 31.1243 | F8: 26.5622 | G8: 18.1474 | H8: 34.0339 | I8: 13.4611
A9: 44196 | B9: 12.781 | C9: 30.5887 | D9: 23.1391 | E9: 21.5983 | F9: 19.4176 | G9: 10.3446 | H9: 18.5058 | I9: 12.3206
A10: 44286 | B10: 15.6918 | C10: 30.5887 | D10: 32.8276 | E10: 30.5818 | F10: 16.6104 | G10: 12.4595 | H10: 19.1478 | I10: 18.006
A11: 44377 | B11: 13.2622 | C11: 30.5887 | D11: 29.2459 | E11: 34.2507 | F11: 17.7525 | G11: 6.1238 | H11: 17.2951 | I11: 21.5008
A12: 44469 | B12: 15.2386 | C12: 37.3741 | D12: 29.9336 | E12: 38.0578 | F12: 20.46 | G12: 1.8726 | H12: 18.8864 | I12: 19.799
A13: 44561 | B13: 10.7026 | C13: 24.7203 | D13: 21.8976 | E13: 26.6712 | F13: 13.825 | G13: -4.0589 | H13: 14.445 | I13: 15.8018
A14: 44651 | B14: 19.6768 | C14: 24.7203 | D14: 40.48 | E14: 53.5386 | F14: 23.7751 | G14: -6.9196 | H14: 25.914 | I14: 26.3156
A15: 44742 | B15: 20.5504 | C15: 24.7203 | D15: 45.5469 | E15: 49.7327 | F15: 19.8855 | G15: -11.9022 | H15: 22.9901 | I15: 24.8316
A16: 44834 | B16: 20.4177 | C16: 62.8411 | D16: 47.0542 | E16: 67.0883 | F16: 18.9713 | G16: -11.9877 | H16: 21.4174 | I16: 27.9988
A17: 44926 | B17: 11.7836 | C17: 39.5561 | D17: 40.0093 | E17: 45.1096 | F17: 14.7738 | G17: -6.5327 | H17: 14.9341 | I17: 20.5018
A18: 45016 | B18: 44.9996 | C18: 39.5561 | D18: 119.446 | E18: 154.7127 | F18: 43.6048 | G18: -10.6349 | H18: 39.2165 | I18: 61.091
A19: 45107 | B19: 60.9211 | C19: 39.5561 | D19: 120.9978 | E19: 190.7811 | F19: 69.1684 | G19: 16.4499 | H19: 61.8095 | I19: 74.1454
A20: 45199 | B20: 79.59 | C20: 145.663 | D20: 91.3726 | E20: 214.0037 | F20: 66.9163 | G20: 33.6212 | H20: 46.9759 | I20: 56.8704
... A31: 46203 | B31: 17.799 | C31: 23.4355 | D31: 23.9882 | E31: 18.6707 | F31: 2.1572 | G31: -7.2049 | H31: 7.9114 | I31: 8.7252
B34: NIM | C34: ROE
A35: GGAL AR Equity | B35: =+B29 -> 18.074 | C35: =+F29 -> 3.3188
A36: SUPV AR Equity | B36: =+C29 -> 23.4355 | C36: =+G29 -> -3.8265
A37: BMA AR Equity | B37: =+D29 -> 22.4341 | C37: =+H29 -> 5.9387
A38: BBAR AR Equity | B38: =+E29 -> 17.8148 | C38: =+I29 -> 7.5952

Sheet Cost of Income
A1: Start Date | B1: 43956
A2: End Date
B4: GGAL AR Equity | I4: SUPV AR Equity | O4: BBAR AR Equity | U4: BMA AR Equity
A5: Dates | B5: IS_OPERATING_EXPN | C5: NET_INT_INC | D5: NON_INT_INC | E5: RETURN_COM_EQY | F5: COST_INCOME | I5: IS_OPERATING_EXPN | J5: NET_INT_INC | K5: NON_INT_INC | L5: RETURN_COM_EQY | M5: COST_INCOME | O5: IS_OPERATING_EXPN | P5: NET_INT_INC | Q5: NON_INT_INC | R5: RETURN_COM_EQY | S5: COST_INCOME | U5: IS_OPERATING_EXPN | V5: NET_INT_INC | W5: NON_INT_INC | X5: RETURN_COM_EQY | Y5: COST_INCOME
A6: =_xll.BDH(B$4,B$5:E$5,$B1,$B2,"Dir=V","Per=W","Days=A","Dts=S","cols=5;rows=25") -> 44012 | B6: 43905.859 | C6: 29630.555 | D6: 46805.801 | E6: 25.2085 | F6: =+B6/(C6+D6) -> 0.57441068 | I6: =_xll.BDH(I$4,I$5:L$5,$B1,$B2,"Dir=V","Per=W","Days=A","Dts=H","cols=4;rows=25") -> 11910.673 | J6: 12169.869 | K6: 5797.142 | L6: 4.9406 | M6: =+I6/(J6+K6) -> 0.662919 | O6: =_xll.BDH(O$4,O$5:R$5,$B1,$B2,"Dir=V","Per=W","Days=A","Dts=H","cols=4;rows=25") -> 17229.908 | P6: 23846.043 | Q6: 14732.44 | R6: 18.5288 | S6: =+O6/(P6+Q6) -> 0.44661964 | U6: =_xll.BDH(U$4,U$5:X$5,$B1,$B2,"Dir=V","Per=W","Days=A","Dts=H","cols=4;rows=25") -> 20515.875 | V6: 30101.652 | W6: 13746.932 | X6: 41.2537 | Y6: =+U6/(V6+W6) -> 0.46787999
A7: 44104 | B7: 35864.604 | C7: 20378.778 | D7: 54515.226 | E7: 26.5622 | F7: =+B7/(C7+D7) -> 0.4788715 | I7: 12418.516 | J7: 12791.445 | K7: 6217.318 | L7: 18.1474 | M7: =+I7/(J7+K7) -> 0.65330479 | O7: 19039.024 | P7: 25388.914 | Q7: 14305.31 | R7: 13.4611 | S7: =+O7/(P7+Q7) -> 0.47964218 | U7: 23177.208 | V7: 32261.108 | W7: 16599.904 | X7: 34.0339 | Y7: =+U7/(V7+W7) -> 0.47434973
A8: 44196 | B8: 41504.161 | C8: 34765.416 | D8: 70153.259 | E8: 19.4176 | F8: =+B8/(C8+D8) -> 0.39558411 | I8: 17901.369 | J8: 16202.794 | K8: 7711.785 | L8: 10.3446 | M8: =+I8/(J8+K8) -> 0.74855464 | O8: 31438.215 | P8: 37632.146 | Q8: 26450.333 | R8: 12.3206 | S8: =+O8/(P8+Q8) -> 0.49058987 | U8: 32315.208 | V8: 43274.629 | W8: 23337.811 | X8: 18.5058 | Y8: =+U8/(V8+W8) -> 0.48512272
A9: 44286 | B9: 45809.318 | C9: 27527.248 | D9: 57003.037 | E9: 16.6104 | F9: =+B9/(C9+D9) -> 0.54192788 | I9: 16052.826 | J9: 12579.613 | K9: 7299.5 | L9: 12.4595 | M9: =+I9/(J9+K9) -> 0.80752225 | O9: 26195.113 | P9: 33422.315 | Q9: 18128.467 | R9: 18.006 | S9: =+O9/(P9+Q9) -> 0.50814191 | U9: 28411.516 | V9: 36960.488 | W9: 21738.027 | X9: 19.1478 | Y9: =+U9/(V9+W9) -> 0.48402444
A10: 44377 | B10: 55895.81 | C10: 28842.395 | D10: 83538.62 | E10: 17.7525 | F10: =+B10/(C10+D10) -> 0.49737769 | I10: 19391.048 | J10: 14512.166 | K10: 8962.732 | L10: 6.1238 | M10: =+I10/(J10+K10) -> 0.82603332 | O10: 31138.767 | P10: 39857.524 | Q10: 22573.66 | R10: 21.5008 | S10: =+O10/(P10+Q10) -> 0.49876945 | U10: 32769.895 | V10: 41786.532 | W10: 24324.995 | X10: 17.2951 | Y10: =+U10/(V10+W10) -> 0.49567597
A11: 44469 | B11: 70396.432 | C11: 48282.275 | D11: 87372.552 | E11: 20.46 | F11: =+B11/(C11+D11) -> 0.51893791 | I11: 23177.469 | J11: 17663.599 | K11: 11081.31 | L11: 1.8726 | M11: =+I11/(J11+K11) -> 0.80631562 | O11: 42536.217 | P11: 53460.431 | Q11: 25451.95 | R11: 19.799 | S11: =+O11/(P11+Q11) -> 0.53903097 | U11: 41576.031 | V11: 54446.277 | W11: 26500.383 | X11: 18.8864 | Y11: =+U11/(V11+W11) -> 0.51362256
A12: 44561 | B12: 109539.05 | C12: 90014.737 | D12: 146161.29 | E12: 13.825 | F12: =+B12/(C12+D12) -> 0.46380259 | I12: 31398.275 | J12: 30033.38 | K12: 9603.175 | L12: -4.0589 | M12: =+I12/(J12+K12) -> 0.79215449 | O12: 69050.995 | P12: 91339.172 | Q12: 42972.905 | R12: 15.8018 | S12: =+O12/(P12+Q12) -> 0.51410861 | U12: 74417.862 | V12: 96954.68 | W12: 48133.793 | X12: 14.445 | Y12: =+U12/(V12+W12) -> 0.51291368
A13: 44651 | B13: 95213.602 | C13: 60045.712 | D13: 148142.52 | E13: 23.7751 | F13: =+B13/(C13+D13) -> 0.45734382 | I13: 33827.437 | J13: 24943.465 | K13: 16357.725 | L13: -6.9196 | M13: =+I13/(J13+K13) -> 0.81904267 | O13: 57137.898 | P13: 80142.999 | Q13: 45132.763 | R13: 26.3156 | S13: =+O13/(P13+Q13) -> 0.45609699 | U13: 56467.335 | V13: 85658.412 | W13: 49134.253 | X13: 25.914 | Y13: =+U13/(V13+W13) -> 0.41891994
A14: 44742 | B14: 120798.07 | C14: 88038.969 | D14: 175429.3 | E14: 19.8855 | F14: =+B14/(C14+D14) -> 0.45849192 | I14: 44200.76 | J14: 32806.921 | K14: 16878.043 | L14: -11.9022 | M14: =+I14/(J14+K14) -> 0.88962045 | O14: 36943.054 | P14: 54310.305 | Q14: 21177.298 | R14: 24.8316 | S14: =+O14/(P14+Q14) -> 0.48939233 | U14: 79831.451 | V14: 115858.47 | W14: 64280.45 | X14: 22.9901 | Y14: =+U14/(V14+W14) -> 0.44316604
A15: 44834 | B15: 171196.82 | C15: 59515.695 | D15: 344843.01 | E15: 18.9713 | F15: =+B15/(C15+D15) -> 0.42337859 | I15: 58895.103 | J15: 47852.79 | K15: 23068.222 | L15: -11.9877 | M15: =+I15/(J15+K15) -> 0.83043235 | O15: 104268 | P15: 182491.06 | Q15: 64555.658 | R15: 27.9988 | S15: =+O15/(P15+Q15) -> 0.42205782 | U15: 110836.45 | V15: 179213.59 | W15: 145703.97 | X15: 21.4174 | Y15: =+U15/(V15+W15) -> 0.34112175
A16: 44926 | B16: 852842.56 | C16: 354146.68 | D16: 1562136.1 | E16: 14.7738 | F16: =+B16/(C16+D16) -> 0.44505047 | I16: 194675.89 | J16: 138462.3 | K16: 75804.845 | L16: -6.5327 | M16: =+I16/(J16+K16) -> 0.90856622 | O16: 342530.76 | P16: 582949.32 | Q16: 200865.67 | R16: 20.5018 | S16: =+O16/(P16+Q16) -> 0.4370046 | U16: 513495.38 | V16: 761772.82 | W16: 512276.3 | X16: 14.9341 | Y16: =+U16/(V16+W16) -> 0.40304206
A17: 45016 | B17: 422404.57 | C17: 484977.17 | D17: 546296.61 | E17: 43.6048 | F17: =+B17/(C17+D17) -> 0.40959499 | I17: 97657.089 | J17: 94869.257 | K17: 60073.12 | L17: -10.6349 | M17: =+I17/(J17+K17) -> 0.63028005 | O17: 268187.07 | P17: 508840.1 | Q17: 137852.17 | R17: 61.091 | S17: =+O17/(P17+Q17) -> 0.41470584 | U17: 247649.44 | V17: 378800.89 | W17: 294300.93 | X17: 39.2165 | Y17: =+U17/(V17+W17) -> 0.3679227
A18: 45107 | B18: 525219.86 | C18: 812068.02 | D18: 599570.68 | E18: 69.1684 | F18: =+B18/(C18+D18) -> 0.37206394 | I18: 151450.6 | J18: 145044.37 | K18: 63906.43 | L18: 16.4499 | M18: =+I18/(J18+K18) -> 0.72481462 | O18: 344596 | P18: 689204.01 | Q18: 198046.55 | R18: 74.1454 | S18: =+O18/(P18+Q18) -> 0.38838634 | U18: 328439.54 | V18: 401194.84 | W18: 586239.22 | X18: 61.8095 | Y18: =+U18/(V18+W18) -> 0.33261921
... A28: 46022 | B28: 1455586.9 | C28: 1860601.5 | D28: 1239319.1 | E28: 3.3188 | F28: =+B28/(C28+D28) -> 0.46955619 | I28: 259111.97 | J28: 285101.06 | K28: 69766.185 | L28: -3.8265 | M28: =+I28/(J28+K28) -> 0.73016594 | O28: 653979.78 | P28: 901982.93 | Q28: 512142.65 | R28: 7.5952 | S28: =+O28/(P28+Q28) -> 0.46246231 | U28: 842405.75 | V28: 999600.01 | W28: 601677.08 | X28: 5.9387 | Y28: =+U28/(V28+W28) -> 0.52608368
A29: 46112 | B29: 1065566.6 | C29: 1595336.4 | D29: 1026850.9 | E29: 1.9048 | I29: 246474.2 | J29: 212623.28 | K29: 94033.77 | L29: -7.1273 | O29: 587925.43 | P29: 879880.04 | Q29: 385179.99 | R29: 7.6706 | U29: 661577.37 | V29: 975193.54 | W29: 514297.12 | X29: 8.1685
A30: 46203 | B30: 1127493.1 | C30: 1669092.2 | D30: 1161259.2 | E30: 2.1572 | I30: 248976.22 | J30: 256650.97 | K30: 94955.934 | L30: -7.2049 | O30: 596197.21 | P30: 912204.29 | Q30: 437690.26 | R30: 8.7252 | U30: 687785.06 | V30: 1033691.8 | W30: 471830.96 | X30: 7.9114
B32: =+F5 -> COST_INCOME | C32: =+E5 -> RETURN_COM_EQY
A33: =+B4 -> GGAL AR Equity | B33: =+F28 -> 0.46955619 | C33: =+E28 -> 3.3188
A34: =+I4 -> SUPV AR Equity | B34: =+M28 -> 0.73016594 | C34: =+L28 -> -3.8265
A35: =+O4 -> BBAR AR Equity | B35: =+S28 -> 0.46246231 | C35: =+R28 -> 7.5952
A36: =+U4 -> BMA AR Equity | B36: =+Y28 -> 0.52608368 | C36: =+X28 -> 5.9387

Sheet PE
A1: Start Date | B1: 45782
A2: End Date
B4: GGAL AR Equity | C4: BMA AR EQUITY | D4: BBAR AR Equity | E4: SUPV AR Equity
A5: Dates | B5: BEST_PE_RATIO | C5: BEST_PE_RATIO | D5: BEST_PE_RATIO | E5: BEST_PE_RATIO
A6: =+A5 -> Dates | B6: =+B4 -> GGAL AR Equity | C6: =+C4 -> BMA AR EQUITY | D6: =+D4 -> BBAR AR Equity | E6: =+E4 -> SUPV AR Equity
A7: =_xll.BDH(B$4,B$5,$B1,$B2,"Dir=V","CDR=5D","Days=A","Dts=S","cols=2;rows=377") -> 45782 | B7: 7.054 | C7: =_xll.BDH(C$4,C$5,$B1,$B2,"Dir=V","CDR=5D","Days=A","Dts=H","cols=1;rows=377") -> 4.322 | D7: =_xll.BDH(D$4,D$5,$B1,$B2,"Dir=V","CDR=5D","Days=A","Dts=H","cols=1;rows=377") -> 3.588 | E7: =_xll.BDH(E$4,E$5,$B1,$B2,"Dir=V","CDR=5D","Days=A","Dts=H","cols=1;rows=377") -> #N/A N/A
A8: 45783 | B8: 7.054 | C8: 4.461 | D8: 3.694 | E8: #N/A N/A
A9: 45784 | B9: 7.054 | C9: 4.311 | D9: 3.551 | E9: #N/A N/A
A10: 45785 | B10: 7.054 | C10: 4.343 | D10: 3.57 | E10: #N/A N/A
A11: 45786 | B11: 7.054 | C11: 4.375 | D11: 3.625 | E11: #N/A N/A
A12: 45789 | B12: 7.054 | C12: 4.601 | D12: 3.791 | E12: #N/A N/A
A13: 45790 | B13: 7.054 | C13: 4.622 | D13: 3.911 | E13: #N/A N/A
A14: 45791 | B14: 7.054 | C14: 4.654 | D14: 3.944 | E14: #N/A N/A
A15: 45792 | B15: 7.054 | C15: 4.59 | D15: 3.828 | E15: #N/A N/A
A16: 45793 | B16: 7.054 | C16: 4.665 | D16: 3.851 | E16: #N/A N/A
A17: 45796 | B17: 7.054 | C17: 4.804 | D17: 4.004 | E17: #N/A N/A
A18: 45797 | B18: 7.054 | C18: 4.772 | D18: 3.967 | E18: #N/A N/A
A19: 45798 | B19: 7.054 | C19: 4.643 | D19: 3.911 | E19: #N/A N/A
... A148: 45979 | B148: 7.054 | C148: 7.298 | D148: 2.426 | E148: #N/A N/A
A149: 45980 | B149: 7.054 | C149: 6.704 | D149: 2.426 | E149: 5.591
A150: 45981 | B150: 7.054 | C150: 6.821 | D150: 2.67 | E150: 5.502
A151: 45982 | B151: 7.054 | C151: 1.585 | D151: 2.549 | E151: 5.081
A152: 45985 | B152: 7.054 | C152: 1.585 | D152: 2.549 | E152: 5.081
A153: 45986 | B153: 7.054 | C153: 6.858 | D153: 2.701 | E153: 5.507
A154: 45987 | B154: 7.054 | C154: 7.412 | D154: 2.701 | E154: 6.126
A155: 45988 | B155: 7.054 | C155: 7.64 | D155: 2.701 | E155: 6.19
A156: 45989 | B156: 7.054 | C156: 7.588 | D156: 2.701 | E156: 6.167
A157: 45992 | B157: 7.054 | C157: 7.562 | D157: 2.701 | E157: 6.276
A158: 45993 | B158: 7.054 | C158: 7.433 | D158: 2.701 | E158: 6.135
A159: 45994 | B159: 11.166 | C159: 7.738 | D159: 2.701 | E159: 6.525
A160: 45995 | B160: 10.855 | C160: 7.913 | D160: 2.701 | E160: 6.425
... A383: 46308 | B383: 8.725 | C383: 6.913 | D383: 7.219 | E383: 6.509

Sheet Valuación
C2: PE_RATIO | D2: PX_TO_BOOK_RATIO | E2: RETURN_COM_EQY | F2: EPS_GROWTH | G2: OPER_MARGIN
B3: GGAL AR Equity | C3: {=+_xll.BDP($B3,C$2)} -> 55.750138 | D3: {=+_xll.BDP($B3,D$2)} -> 1.0521917 | E3: {=+_xll.BDP($B3,E$2)} -> 2.157227 | F3: {=+_xll.BDP($B3,F$2)} -> -91.3279 | G3: {=+_xll.BDP($B3,G$2)} -> 18.767426
B4: BMA AR Equity | C4: {=+_xll.BDP($B4,C$2)} -> 15.943538 | D4: {=+_xll.BDP($B4,D$2)} -> 1.0833649 | E4: {=+_xll.BDP($B4,E$2)} -> 7.9114481 | F4: {=+_xll.BDP($B4,F$2)} -> -32.108294 | G4: {=+_xll.BDP($B4,G$2)} -> 33.165812
B5: SUPV AR Equity | D5: {=+_xll.BDP($B5,D$2)} -> 0.88875586 | E5: {=+_xll.BDP($B5,E$2)} -> -7.2048889 | G5: {=+_xll.BDP($B5,G$2)} -> -9.2712195
B6: BBAR AR Equity | C6: {=+_xll.BDP($B6,C$2)} -> 14.052408 | D6: {=+_xll.BDP($B6,D$2)} -> 1.0346004 | E6: {=+_xll.BDP($B6,E$2)} -> 8.7252379 | F6: {=+_xll.BDP($B6,F$2)} -> -46.201808 | G6: {=+_xll.BDP($B6,G$2)} -> 23.281895
B9: min | C9: =+MIN(C3:C6) -> 14.052408 | D9: =+MIN(D3:D6) -> 0.88875586 | E9: =+MIN(E3:E6) -> -7.2048889 | F9: =+MIN(F3:F6) -> -91.3279 | G9: =+MIN(G3:G6) -> -9.2712195
B10: max | C10: =+MAX(C3:C6) -> 55.750138 | D10: =+MAX(D3:D6) -> 1.0833649 | E10: =+MAX(E3:E6) -> 8.7252379 | F10: =+MAX(F3:F6) -> -32.108294 | G10: =+MAX(G3:G6) -> 33.165812
C13: PE | D13: PBV | E13: ROE | F13: EPS Growth | G13: Oper Margin
B14: =+B3 -> GGAL AR Equity | C14: =+(C3-C$9)/(C$10-C$9) -> 1 | D14: =+(D3-D$9)/(D$10-D$9) -> 0.83981655 | E14: =+(E3-E$9)/(E$10-E$9) -> 0.58769877 | F14: =+(F3-F$9)/(F$10-F$9) -> 0 | G14: =+(G3-G$9)/(G$10-G$9) -> 0.66071176
B15: =+B4 -> BMA AR Equity | C15: =+(C4-C$9)/(C$10-C$9) -> 0.045353296 | D15: =+(D4-D$9)/(D$10-D$9) -> 1 | E15: =+(E4-E$9)/(E$10-E$9) -> 0.94891504 | F15: =+(F4-F$9)/(F$10-F$9) -> 1 | G15: =+(G4-G$9)/(G$10-G$9) -> 1
B16: =+B5 -> SUPV AR Equity | D16: =+(D5-D$9)/(D$10-D$9) -> 0 | E16: =+(E5-E$9)/(E$10-E$9) -> 0 | G16: =+(G5-G$9)/(G$10-G$9) -> 0
B17: =+B6 -> BBAR AR Equity | C17: =+(C6-C$9)/(C$10-C$9) -> 0 | D17: =+(D6-D$9)/(D$10-D$9) -> 0.74942352 | E17: =+(E6-E$9)/(E$10-E$9) -> 1 | F17: =+(F6-F$9)/(F$10-F$9) -> 0.76201271 | G17: =+(G6-G$9)/(G$10-G$9) -> 0.76709217

Sheet Correl EMBI
A3: Start Date | B3: 42582
A4: End Date
B6: GGAL us Equity | C6: JPSSGARG Index
B7: =_xll.BFieldInfo(B$8) -> Last Price | C7: =_xll.BFieldInfo(C$8) -> Last Price
A8: Dates | B8: PX_LAST | C8: PX_LAST
A9: =_xll.BDH(B$6,B$8,$B3,$B4,"Dir=V","Per=W","Days=A","Dts=S","cols=2;rows=532") -> 42587 | B9: 21.857 | C9: =_xll.BDH(C$6,C$8,$B3,$B4,"Dir=V","Per=W","Days=A","Dts=H") -> #N/A Invalid Security
A10: 42594 | B10: 21.4477 | D10: =+B10/B9-1 -> -0.018726266 | E10: =+C10/C9-1 -> #VALUE!
A11: 42601 | B11: 21.6858 | D11: =+B11/B10-1 -> 0.011101423 | E11: =+C11/C10-1 -> #DIV/0!
A12: 42608 | B12: 22.4747 | D12: =+B12/B11-1 -> 0.036378644 | E12: =+C12/C11-1 -> #DIV/0!
A13: 42615 | B13: 22.7351 | D13: =+B13/B12-1 -> 0.011586362 | E13: =+C13/C12-1 -> #DIV/0!
A14: 42622 | B14: 21.6114 | D14: =+B14/B13-1 -> -0.049425778 | E14: =+C14/C13-1 -> #DIV/0!
A15: 42629 | B15: 21.1798 | D15: =+B15/B14-1 -> -0.019970941 | E15: =+C15/C14-1 -> #DIV/0!
A16: 42636 | B16: 22.5565 | D16: =+B16/B15-1 -> 0.065000614 | E16: =+C16/C15-1 -> #DIV/0!
A17: 42643 | B17: 23.1519 | D17: =+B17/B16-1 -> 0.026395939 | E17: =+C17/C16-1 -> #DIV/0!
A18: 42650 | B18: 23.457 | D18: =+B18/B17-1 -> 0.013178184 | E18: =+C18/C17-1 -> #DIV/0!
A19: 42657 | B19: 23.5314 | D19: =+B19/B18-1 -> 0.0031717611 | E19: =+C19/C18-1 -> #DIV/0!
A20: 42664 | B20: 23.5314 | D20: =+B20/B19-1 -> 0 | E20: =+C20/C19-1 -> #DIV/0!
A21: 42671 | B21: 23.2859 | D21: =+B21/B20-1 -> -0.010432868 | E21: =+C21/C20-1 -> #DIV/0!
... A534: 46262 | B534: 42.1878 | D534: =+B534/B533-1 -> 0.020243914 | E534: =+C534/C533-1 -> #DIV/0!
A535: 46269 | B535: 44.3052
A536: 46276 | B536: 43.8058
A537: 46283 | B537: 41.7084
A538: 46290 | B538: 38.6922
A539: 46297 | B539: 35.89
A540: 46304 | B540: 36.81

Sheet Sheet1
