Workbook
Name MIN_BANCOS: Parametros!$B$5
Name MIN_OBS_ROLL: Parametros!$B$6
Name MIN_OBS_Z: Parametros!$B$7
Name Z_CLIP: Parametros!$B$8
Name AMPLITUD: Parametros!$B$9
Name W_BANCOS: Parametros!$B$10
Name COSTO: Parametros!$B$11
Name FECHA_ERA: Parametros!$B$12
Name INICIO_VIVO: Parametros!$B$13
Name MESES_EVAL: Parametros!$B$14

Sheet LEEME
A1: Seguimiento en vivo de la regla H_OVR3
A2: Reversión tras sobrerreacciones de los bancos al riesgo país (EMBI). Sobre/sub-ponderación de bancos vs Merval.
A4: Qué hace la regla
A5: 1. Mide el spread de los bancos contra el Merval ajustado por β (T2), sobre retornos en exceso de la Badlar.
A6: 2. Estima con los 36 meses previos cuánto se mueve ese spread por cada variación del EMBI (β_E).
A7: 3. El residuo de cada mes es lo que los bancos se movieron de más (o de menos) respecto de lo que explica el EMBI. El gap suma los últimos 3 meses.
A8: 4. El gap se estandariza con toda su historia disponible (z expansivo, recortado a ±3). Score = −z: si los bancos cayeron de más, el score es positivo.
A9: 5. m = 1 + 0.2·tanh(score) va de 0.8 a 1.2. Se aplica el promedio de los últimos 3 meses (cada señal se mantiene 3 meses).
A10: 6. Peso de bancos en la cartera = m × peso de bancos en el benchmark, durante el mes siguiente.
A12: Fórmulas (iguales al código Python)
A13: rf_t = ln(1 + Badlar_{t−1}/1200) · XB_t = ln(1 + r_bancos,t) − rf_t · XM_t = ln(1 + r_Merval,t) − rf_t
A14: β_t = cov(XB, XM) / var(XM), ventana de 36 meses hasta t−1 (mínimo 24) · T2_t = XB_t − β_t·XM_t
... A36: Origen: proyecto bancos_model_prod, xs_model/build_excel_hovr3.py (METHODOLOGY §14).

Sheet Tablero
A1: H_OVR3 — Reversión tras sobrerreacciones de los bancos al EMBI
A2: Paper trading: OW/UW de bancos vs Merval. Regla congelada el 2026-10-10. Se actualiza sola al cargar la hoja Datos.
A4: SEÑAL VIGENTE
A5: Última fila con señal | B5: =MAX(Calculo!$BI$5:$BI$352)
A6: Fecha de la señal (cierre de mes) | B6: =IF(B5>0,INDEX(Calculo!$A:$A,B5),"")
A7: Gap de 3 meses (residuo acumulado) | B7: =IF(B5>0,INDEX(Calculo!$AP:$AP,B5),"")
A8: Score (positivo = bancos cayeron de más) | B8: =IF(B5>0,INDEX(Calculo!$AW:$AW,B5),"")
A9: m del mes | B9: =IF(B5>0,INDEX(Calculo!$AX:$AX,B5),"")
A10: m A APLICAR el mes siguiente (promedio 3 meses) | B10: =IF(B5>0,INDEX(Calculo!$AY:$AY,B5),"")
A11: Lectura | B11: =IF(ISNUMBER(B10),IF(B10>=1,"Sobreponderar bancos ","Subponderar bancos ")&TEXT(ABS(B10-1),"0.0%")&" sobre su peso en el benchmark","")
A12: Ejemplo: peso de bancos si el benchmark pesa W_BANCOS | B12: =IF(ISNUMBER(B10),B10*W_BANCOS,"")
A14: SEGUIMIENTO EN VIVO
A15: Primer mes en vivo (retorno) | B15: =INICIO_VIVO
A16: Meses en vivo | B16: =SUM(Calculo!$BG$5:$BG$352)
A17: Activo neto acumulado en vivo (pb, con W_BANCOS) | B17: =IF(B16>0,SUM(Calculo!$BH$5:$BH$352)*10000,"")
A18: IR anualizado en vivo | B18: =IF(B16>=2,AVERAGE(Calculo!$BH$5:$BH$352)/STDEV(Calculo!$BH$5:$BH$352)*SQRT(12),"")
A19: Acierto (meses con activo > 0) | B19: =IF(B16>0,COUNTIF(Calculo!$BH$5:$BH$352,">0")/B16,"")
A20: ESTADO DE LA REGLA | B20: =IF(B16<MESES_EVAL,"EN EVALUACIÓN ("&B16&" de "&MESES_EVAL&" meses)",IF(B18<0,"DESCARTAR: IR en vivo negativo a los "&MESES_EVAL&" meses","MANTENER: IR en vivo ≥ 0"))
A22: CONTEXTO: BACKTEST (fuera de muestra, post hoc)
A23: IR era A (hasta 2016-05) | B23: =AVERAGE(Calculo!$BE$5:$BE$352)/STDEV(Calculo!$BE$5:$BE$352)*SQRT(12) | C23: Python: 0.56
A24: IR era B (desde 2016-06) | B24: =AVERAGE(Calculo!$BF$5:$BF$352)/STDEV(Calculo!$BF$5:$BF$352)*SQRT(12) | C24: Python: 0.19
A25: IR total | B25: =AVERAGE(Calculo!$BC$5:$BC$352)/STDEV(Calculo!$BC$5:$BC$352)*SQRT(12) | C25: Python: 0.33
A26: Activo promedio (pb/año, con W_BANCOS) | B26: =AVERAGE(Calculo!$BC$5:$BC$352)*12*10000 | C26: Python: 18.7
A28: Cuidado: la regla se eligió después de ver los datos (DSR 0.016 con 194 ensayos). El backtest es contexto, no evidencia. La decisión se toma sólo con los meses en vivo.
A30: ÚLTIMOS 12 MESES
A31: Fecha | B31: Score | C31: m del mes | D31: m a aplicar | E31: Spread T2 del mes | F31: Activo neto (pb) | G31: En vivo
A32: =IF($B$5-11>=5,INDEX(Calculo!$A:$A,$B$5-11),"") | B32: =IF($B$5-11>=5,IF(ISNUMBER(INDEX(Calculo!$AW:$AW,$B$5-11)),INDEX(Calculo!$AW:$AW,$B$5-11),""),"") | C32: =IF($B$5-11>=5,IF(ISNUMBER(INDEX(Calculo!$AX:$AX,$B$5-11)),INDEX(Calculo!$AX:$AX,$B$5-11),""),"") | D32: =IF($B$5-11>=5,IF(ISNUMBER(INDEX(Calculo!$AY:$AY,$B$5-11)),INDEX(Calculo!$AY:$AY,$B$5-11),""),"") | E32: =IF($B$5-11>=5,IF(ISNUMBER(INDEX(Calculo!$W:$W,$B$5-11)),INDEX(Calculo!$W:$W,$B$5-11),""),"") | F32: =IF($B$5-11>=5,IF(ISNUMBER(INDEX(Calculo!$BC:$BC,$B$5-11)),INDEX(Calculo!$BC:$BC,$B$5-11)*10000,""),"") | G32: =IF($B$5-11>=5,IF(ISNUMBER(INDEX(Calculo!$BG:$BG,$B$5-11)),INDEX(Calculo!$BG:$BG,$B$5-11),""),"")
A33: =IF($B$5-10>=5,INDEX(Calculo!$A:$A,$B$5-10),"") | B33: =IF($B$5-10>=5,IF(ISNUMBER(INDEX(Calculo!$AW:$AW,$B$5-10)),INDEX(Calculo!$AW:$AW,$B$5-10),""),"") | C33: =IF($B$5-10>=5,IF(ISNUMBER(INDEX(Calculo!$AX:$AX,$B$5-10)),INDEX(Calculo!$AX:$AX,$B$5-10),""),"") | D33: =IF($B$5-10>=5,IF(ISNUMBER(INDEX(Calculo!$AY:$AY,$B$5-10)),INDEX(Calculo!$AY:$AY,$B$5-10),""),"") | E33: =IF($B$5-10>=5,IF(ISNUMBER(INDEX(Calculo!$W:$W,$B$5-10)),INDEX(Calculo!$W:$W,$B$5-10),""),"") | F33: =IF($B$5-10>=5,IF(ISNUMBER(INDEX(Calculo!$BC:$BC,$B$5-10)),INDEX(Calculo!$BC:$BC,$B$5-10)*10000,""),"") | G33: =IF($B$5-10>=5,IF(ISNUMBER(INDEX(Calculo!$BG:$BG,$B$5-10)),INDEX(Calculo!$BG:$BG,$B$5-10),""),"")
A34: =IF($B$5-9>=5,INDEX(Calculo!$A:$A,$B$5-9),"") | B34: =IF($B$5-9>=5,IF(ISNUMBER(INDEX(Calculo!$AW:$AW,$B$5-9)),INDEX(Calculo!$AW:$AW,$B$5-9),""),"") | C34: =IF($B$5-9>=5,IF(ISNUMBER(INDEX(Calculo!$AX:$AX,$B$5-9)),INDEX(Calculo!$AX:$AX,$B$5-9),""),"") | D34: =IF($B$5-9>=5,IF(ISNUMBER(INDEX(Calculo!$AY:$AY,$B$5-9)),INDEX(Calculo!$AY:$AY,$B$5-9),""),"") | E34: =IF($B$5-9>=5,IF(ISNUMBER(INDEX(Calculo!$W:$W,$B$5-9)),INDEX(Calculo!$W:$W,$B$5-9),""),"") | F34: =IF($B$5-9>=5,IF(ISNUMBER(INDEX(Calculo!$BC:$BC,$B$5-9)),INDEX(Calculo!$BC:$BC,$B$5-9)*10000,""),"") | G34: =IF($B$5-9>=5,IF(ISNUMBER(INDEX(Calculo!$BG:$BG,$B$5-9)),INDEX(Calculo!$BG:$BG,$B$5-9),""),"")
A35: =IF($B$5-8>=5,INDEX(Calculo!$A:$A,$B$5-8),"") | B35: =IF($B$5-8>=5,IF(ISNUMBER(INDEX(Calculo!$AW:$AW,$B$5-8)),INDEX(Calculo!$AW:$AW,$B$5-8),""),"") | C35: =IF($B$5-8>=5,IF(ISNUMBER(INDEX(Calculo!$AX:$AX,$B$5-8)),INDEX(Calculo!$AX:$AX,$B$5-8),""),"") | D35: =IF($B$5-8>=5,IF(ISNUMBER(INDEX(Calculo!$AY:$AY,$B$5-8)),INDEX(Calculo!$AY:$AY,$B$5-8),""),"") | E35: =IF($B$5-8>=5,IF(ISNUMBER(INDEX(Calculo!$W:$W,$B$5-8)),INDEX(Calculo!$W:$W,$B$5-8),""),"") | F35: =IF($B$5-8>=5,IF(ISNUMBER(INDEX(Calculo!$BC:$BC,$B$5-8)),INDEX(Calculo!$BC:$BC,$B$5-8)*10000,""),"") | G35: =IF($B$5-8>=5,IF(ISNUMBER(INDEX(Calculo!$BG:$BG,$B$5-8)),INDEX(Calculo!$BG:$BG,$B$5-8),""),"")
A36: =IF($B$5-7>=5,INDEX(Calculo!$A:$A,$B$5-7),"") | B36: =IF($B$5-7>=5,IF(ISNUMBER(INDEX(Calculo!$AW:$AW,$B$5-7)),INDEX(Calculo!$AW:$AW,$B$5-7),""),"") | C36: =IF($B$5-7>=5,IF(ISNUMBER(INDEX(Calculo!$AX:$AX,$B$5-7)),INDEX(Calculo!$AX:$AX,$B$5-7),""),"") | D36: =IF($B$5-7>=5,IF(ISNUMBER(INDEX(Calculo!$AY:$AY,$B$5-7)),INDEX(Calculo!$AY:$AY,$B$5-7),""),"") | E36: =IF($B$5-7>=5,IF(ISNUMBER(INDEX(Calculo!$W:$W,$B$5-7)),INDEX(Calculo!$W:$W,$B$5-7),""),"") | F36: =IF($B$5-7>=5,IF(ISNUMBER(INDEX(Calculo!$BC:$BC,$B$5-7)),INDEX(Calculo!$BC:$BC,$B$5-7)*10000,""),"") | G36: =IF($B$5-7>=5,IF(ISNUMBER(INDEX(Calculo!$BG:$BG,$B$5-7)),INDEX(Calculo!$BG:$BG,$B$5-7),""),"")
A37: =IF($B$5-6>=5,INDEX(Calculo!$A:$A,$B$5-6),"") | B37: =IF($B$5-6>=5,IF(ISNUMBER(INDEX(Calculo!$AW:$AW,$B$5-6)),INDEX(Calculo!$AW:$AW,$B$5-6),""),"") | C37: =IF($B$5-6>=5,IF(ISNUMBER(INDEX(Calculo!$AX:$AX,$B$5-6)),INDEX(Calculo!$AX:$AX,$B$5-6),""),"") | D37: =IF($B$5-6>=5,IF(ISNUMBER(INDEX(Calculo!$AY:$AY,$B$5-6)),INDEX(Calculo!$AY:$AY,$B$5-6),""),"") | E37: =IF($B$5-6>=5,IF(ISNUMBER(INDEX(Calculo!$W:$W,$B$5-6)),INDEX(Calculo!$W:$W,$B$5-6),""),"") | F37: =IF($B$5-6>=5,IF(ISNUMBER(INDEX(Calculo!$BC:$BC,$B$5-6)),INDEX(Calculo!$BC:$BC,$B$5-6)*10000,""),"") | G37: =IF($B$5-6>=5,IF(ISNUMBER(INDEX(Calculo!$BG:$BG,$B$5-6)),INDEX(Calculo!$BG:$BG,$B$5-6),""),"")
A38: =IF($B$5-5>=5,INDEX(Calculo!$A:$A,$B$5-5),"") | B38: =IF($B$5-5>=5,IF(ISNUMBER(INDEX(Calculo!$AW:$AW,$B$5-5)),INDEX(Calculo!$AW:$AW,$B$5-5),""),"") | C38: =IF($B$5-5>=5,IF(ISNUMBER(INDEX(Calculo!$AX:$AX,$B$5-5)),INDEX(Calculo!$AX:$AX,$B$5-5),""),"") | D38: =IF($B$5-5>=5,IF(ISNUMBER(INDEX(Calculo!$AY:$AY,$B$5-5)),INDEX(Calculo!$AY:$AY,$B$5-5),""),"") | E38: =IF($B$5-5>=5,IF(ISNUMBER(INDEX(Calculo!$W:$W,$B$5-5)),INDEX(Calculo!$W:$W,$B$5-5),""),"") | F38: =IF($B$5-5>=5,IF(ISNUMBER(INDEX(Calculo!$BC:$BC,$B$5-5)),INDEX(Calculo!$BC:$BC,$B$5-5)*10000,""),"") | G38: =IF($B$5-5>=5,IF(ISNUMBER(INDEX(Calculo!$BG:$BG,$B$5-5)),INDEX(Calculo!$BG:$BG,$B$5-5),""),"")
A39: =IF($B$5-4>=5,INDEX(Calculo!$A:$A,$B$5-4),"") | B39: =IF($B$5-4>=5,IF(ISNUMBER(INDEX(Calculo!$AW:$AW,$B$5-4)),INDEX(Calculo!$AW:$AW,$B$5-4),""),"") | C39: =IF($B$5-4>=5,IF(ISNUMBER(INDEX(Calculo!$AX:$AX,$B$5-4)),INDEX(Calculo!$AX:$AX,$B$5-4),""),"") | D39: =IF($B$5-4>=5,IF(ISNUMBER(INDEX(Calculo!$AY:$AY,$B$5-4)),INDEX(Calculo!$AY:$AY,$B$5-4),""),"") | E39: =IF($B$5-4>=5,IF(ISNUMBER(INDEX(Calculo!$W:$W,$B$5-4)),INDEX(Calculo!$W:$W,$B$5-4),""),"") | F39: =IF($B$5-4>=5,IF(ISNUMBER(INDEX(Calculo!$BC:$BC,$B$5-4)),INDEX(Calculo!$BC:$BC,$B$5-4)*10000,""),"") | G39: =IF($B$5-4>=5,IF(ISNUMBER(INDEX(Calculo!$BG:$BG,$B$5-4)),INDEX(Calculo!$BG:$BG,$B$5-4),""),"")
A40: =IF($B$5-3>=5,INDEX(Calculo!$A:$A,$B$5-3),"") | B40: =IF($B$5-3>=5,IF(ISNUMBER(INDEX(Calculo!$AW:$AW,$B$5-3)),INDEX(Calculo!$AW:$AW,$B$5-3),""),"") | C40: =IF($B$5-3>=5,IF(ISNUMBER(INDEX(Calculo!$AX:$AX,$B$5-3)),INDEX(Calculo!$AX:$AX,$B$5-3),""),"") | D40: =IF($B$5-3>=5,IF(ISNUMBER(INDEX(Calculo!$AY:$AY,$B$5-3)),INDEX(Calculo!$AY:$AY,$B$5-3),""),"") | E40: =IF($B$5-3>=5,IF(ISNUMBER(INDEX(Calculo!$W:$W,$B$5-3)),INDEX(Calculo!$W:$W,$B$5-3),""),"") | F40: =IF($B$5-3>=5,IF(ISNUMBER(INDEX(Calculo!$BC:$BC,$B$5-3)),INDEX(Calculo!$BC:$BC,$B$5-3)*10000,""),"") | G40: =IF($B$5-3>=5,IF(ISNUMBER(INDEX(Calculo!$BG:$BG,$B$5-3)),INDEX(Calculo!$BG:$BG,$B$5-3),""),"")
A41: =IF($B$5-2>=5,INDEX(Calculo!$A:$A,$B$5-2),"") | B41: =IF($B$5-2>=5,IF(ISNUMBER(INDEX(Calculo!$AW:$AW,$B$5-2)),INDEX(Calculo!$AW:$AW,$B$5-2),""),"") | C41: =IF($B$5-2>=5,IF(ISNUMBER(INDEX(Calculo!$AX:$AX,$B$5-2)),INDEX(Calculo!$AX:$AX,$B$5-2),""),"") | D41: =IF($B$5-2>=5,IF(ISNUMBER(INDEX(Calculo!$AY:$AY,$B$5-2)),INDEX(Calculo!$AY:$AY,$B$5-2),""),"") | E41: =IF($B$5-2>=5,IF(ISNUMBER(INDEX(Calculo!$W:$W,$B$5-2)),INDEX(Calculo!$W:$W,$B$5-2),""),"") | F41: =IF($B$5-2>=5,IF(ISNUMBER(INDEX(Calculo!$BC:$BC,$B$5-2)),INDEX(Calculo!$BC:$BC,$B$5-2)*10000,""),"") | G41: =IF($B$5-2>=5,IF(ISNUMBER(INDEX(Calculo!$BG:$BG,$B$5-2)),INDEX(Calculo!$BG:$BG,$B$5-2),""),"")
A42: =IF($B$5-1>=5,INDEX(Calculo!$A:$A,$B$5-1),"") | B42: =IF($B$5-1>=5,IF(ISNUMBER(INDEX(Calculo!$AW:$AW,$B$5-1)),INDEX(Calculo!$AW:$AW,$B$5-1),""),"") | C42: =IF($B$5-1>=5,IF(ISNUMBER(INDEX(Calculo!$AX:$AX,$B$5-1)),INDEX(Calculo!$AX:$AX,$B$5-1),""),"") | D42: =IF($B$5-1>=5,IF(ISNUMBER(INDEX(Calculo!$AY:$AY,$B$5-1)),INDEX(Calculo!$AY:$AY,$B$5-1),""),"") | E42: =IF($B$5-1>=5,IF(ISNUMBER(INDEX(Calculo!$W:$W,$B$5-1)),INDEX(Calculo!$W:$W,$B$5-1),""),"") | F42: =IF($B$5-1>=5,IF(ISNUMBER(INDEX(Calculo!$BC:$BC,$B$5-1)),INDEX(Calculo!$BC:$BC,$B$5-1)*10000,""),"") | G42: =IF($B$5-1>=5,IF(ISNUMBER(INDEX(Calculo!$BG:$BG,$B$5-1)),INDEX(Calculo!$BG:$BG,$B$5-1),""),"")
A43: =IF($B$5-0>=5,INDEX(Calculo!$A:$A,$B$5-0),"") | B43: =IF($B$5-0>=5,IF(ISNUMBER(INDEX(Calculo!$AW:$AW,$B$5-0)),INDEX(Calculo!$AW:$AW,$B$5-0),""),"") | C43: =IF($B$5-0>=5,IF(ISNUMBER(INDEX(Calculo!$AX:$AX,$B$5-0)),INDEX(Calculo!$AX:$AX,$B$5-0),""),"") | D43: =IF($B$5-0>=5,IF(ISNUMBER(INDEX(Calculo!$AY:$AY,$B$5-0)),INDEX(Calculo!$AY:$AY,$B$5-0),""),"") | E43: =IF($B$5-0>=5,IF(ISNUMBER(INDEX(Calculo!$W:$W,$B$5-0)),INDEX(Calculo!$W:$W,$B$5-0),""),"") | F43: =IF($B$5-0>=5,IF(ISNUMBER(INDEX(Calculo!$BC:$BC,$B$5-0)),INDEX(Calculo!$BC:$BC,$B$5-0)*10000,""),"") | G43: =IF($B$5-0>=5,IF(ISNUMBER(INDEX(Calculo!$BG:$BG,$B$5-0)),INDEX(Calculo!$BG:$BG,$B$5-0),""),"")

Sheet Parametros
A1: Parámetros congelados de la regla H_OVR3 (no modificar)
A2: Fijados el 2026-10-10. Cambiar cualquiera invalida el seguimiento en vivo.
A4: Nombre | B4: Valor | C4: Descripción
A5: MIN_BANCOS | B5: 2 | C5: Mínimo de bancos con retorno para calcular el promedio del sector
A6: MIN_OBS_ROLL | B6: 24 | C6: Observaciones mínimas dentro de las ventanas móviles de 36 meses (β y regresión vs EMBI)
A7: MIN_OBS_Z | B7: 36 | C7: Observaciones mínimas del z-score expansivo del gap
A8: Z_CLIP | B8: 3 | C8: Recorte del z-score (±)
A9: AMPLITUD | B9: 0.2 | C9: m = 1 + AMPLITUD·tanh(score): multiplicador entre 0.8 y 1.2
A10: W_BANCOS | B10: 0.25 | C10: Peso ilustrativo de bancos en el benchmark (escala el activo; no afecta el IR)
A11: COSTO | B11: 0.01 | C11: Costo por unidad de cambio en (m − 1): 2 × 50 pb (dos patas)
A12: FECHA_ERA | B12: 42521 | C12: Corte de eras del backtest (A ≤ fecha < B)
A13: INICIO_VIVO | B13: 46356 | C13: Primer mes de retorno en vivo (usa la señal del cierre de oct-2026)
A14: MESES_EVAL | B14: 24 | C14: Meses en vivo para la decisión: si el IR acumulado es < 0, se descarta la regla
A16: Fijos en las fórmulas (no son celdas editables)
A17: Ventana de β (bancos vs Merval) | B17: 36 meses, datos hasta t−1
A18: Ventana de la regresión del spread contra ΔlogEMBI | B18: 36 meses, datos hasta t−1
A19: Gap de sobrerreacción | B19: suma de 3 meses de residuos (requiere los 3)
A20: Mantener la señal | B20: promedio de los multiplicadores de los últimos 3 meses (tramos superpuestos)

Sheet Datos
A1: Datos de entrada (único lugar para cargar información)
A2: Cada mes agregar UNA fila al final con el cierre del mes. Celdas amarillas = carga. No modificar filas anteriores. Fuente y unidades: ver encabezados y LEEME.
A4: Fecha (fin de mes) | B4: GGAL | C4: BBAR | D4: BMA | E4: SUPV | F4: MERVAL ARS | G4: Badlar (% TNA) | H4: EMBI Argentina (pb)
A5: 38017 | B5: 2.074 | C5: 6.855 | D5: 2.839 | F5: 1140.81 | G5: 1.5 | H5: 5764.38
A6: 38046 | B6: 2.322 | C6: 6.793 | D6: 3.034 | F6: 1183.14 | G6: 1.125 | H6: 5865.65
A7: 38077 | B7: 2.245 | C7: 6.628 | D7: 3.117 | F7: 1201.66 | G7: 1.6875 | H7: 4872.94
A8: 38107 | B8: 1.973 | C8: 5.232 | D8: 2.978 | F8: 1077.93 | G8: 1.8125 | H8: 4628.15
A9: 38138 | B9: 1.674 | C9: 4.236 | D9: 2.459 | F9: 952.62 | G9: 3.875 | H9: 4950
A10: 38168 | B10: 1.614 | C10: 4 | D10: 2.496 | F10: 945.45 | G10: 2.4375 | H10: 5188.06
A11: 38199 | B11: 1.535 | C11: 4.236 | D11: 2.829 | F11: 966.1 | G11: 4 | H11: 5036.41
A12: 38230 | B12: 1.505 | C12: 4.039 | D12: 2.944 | F12: 952.14 | G12: 4.4375 | H12: 5258.49
A13: 38260 | B13: 1.953 | C13: 5.122 | D13: 3.136 | F13: 1142.5 | G13: 5.1875 | H13: 5440.02
A14: 38291 | B14: 2.471 | C14: 4.959 | D14: 3.328 | F14: 1287.14 | G14: 4.375 | H14: 5440.1
A15: 38321 | B15: 2.142 | C15: 5.053 | D15: 3.223 | F15: 1213.09 | G15: 4.125 | H15: 5193.84
A16: 38352 | B16: 2.511 | C16: 6.042 | D16: 3.539 | F16: 1375.37 | G16: 4 | H16: 4702.63
... A152: 42490 | B152: 41.366 | C152: 134.159 | D152: 103.756 | F152: 13724.07 | G152: 30.5625 | H152: 544
A153: 42521 | B153: 40.522 | C153: 118.573 | D153: 100.006 | E153: 32.208 | F153: 12681.74 | G153: 31.25 | H153: 522
A154: 42551 | B154: 46.928 | C154: 137.382 | D154: 127.394 | E154: 37.792 | F154: 14683.49 | G154: 26.625 | H154: 518
A155: 42582 | B155: 45.606 | C155: 133.732 | D155: 128.417 | E155: 40.783 | F155: 15803.5 | G155: 25.625 | H155: 521
A156: 42613 | B156: 45.606 | C156: 135.537 | D156: 135.94 | E156: 41.631 | F156: 15649.47 | G156: 24 | H156: 454
A157: 42643 | B157: 47.792 | C157: 135.069 | D157: 136.513 | E157: 45.869 | F157: 16675.68 | G157: 22.1875 | H157: 439
A158: 42674 | B158: 47.894 | C158: 134.868 | D158: 131.98 | E158: 47.365 | F158: 17610.13 | G158: 21.75 | H158: 451
A159: 42704 | B159: 45.148 | C159: 130.388 | D159: 130.833 | E159: 45.32 | F159: 17442.4 | G159: 20.375 | H159: 515
A160: 42735 | B160: 43.42 | C160: 124.37 | D160: 117.864 | E160: 40.883 | F160: 16917.86 | G160: 19.875 | H160: 455
A161: 42766 | B161: 50.283 | C161: 130.254 | D161: 137.604 | E161: 46.168 | F161: 19062.59 | G161: 19.375 | H161: 469
A162: 42794 | B162: 51.554 | C162: 123.702 | D162: 142.596 | E162: 47.863 | F162: 19117.45 | G162: 20.1875 | H162: 466
A163: 42825 | B163: 59.893 | C163: 127.179 | D163: 153.212 | E163: 52.949 | F163: 20265.32 | G163: 19.0625 | H163: 452
A164: 42855 | B164: 61.723 | C164: 127.045 | D164: 154.073 | E164: 52.899 | F164: 21019.91 | G164: 20 | H164: 415
... A277: 46295 | B277: 8619.655 | C277: 14537.483 | D277: 18122.092 | E277: 2610.009 | F277: 2819323 | G277: 22.8125 | H277: 607

Sheet Calculo
A1: Cálculo de la regla H_OVR3 (fórmulas; no editar)
A2: Cada columna replica una línea del código Python. Columnas 'f' = 1 si el dato existe; columnas 'v' = valor numérico (0 si falta) para las ventanas móviles.
A3: Fecha | B3: Retornos locales | I3: Tasa libre de riesgo | K3: Spread ajustado por β (T2) | R3: β bancos vs Merval | X3: Regresión vs EMBI | AM3: Gap y señal | AX3: Posición | BA3: Resultado | BG3: Seguimiento | BJ3: Gráfico
A4: Fecha | B4: r GGAL | C4: r BBAR | D4: r BMA | E4: r SUPV | F4: N bancos | G4: r bancos (EW) | H4: r Merval | I4: Badlar (ffill) | J4: rf (log, mes) | K4: ln(1+r bancos) − rf | L4: ln(1+r Merval) − rf | M4: f XB | N4: v XB | O4: f XM | P4: v XM | Q4: f par | R4: n pares (36m, t−1) | S4: cov (36m, t−1) | T4: n Merval (36m, t−1) | U4: var Merval (36m, t−1) | V4: β | W4: T2 = XB − β·XM | X4: Δ ln EMBI | Y4: f T2 | Z4: v T2 | AA4: f ΔEMBI | AB4: v ΔEMBI | AC4: f par | AD4: n pares (36m, t−1) | AE4: cov(T2, ΔEMBI) | AF4: n ΔEMBI | AG4: var ΔEMBI | AH4: n T2 | AI4: media T2 | AJ4: media ΔEMBI | AK4: β_E | AL4: a_E | AM4: residuo e = T2 − (a + β_E·ΔEMBI) | AN4: f e | AO4: v e | AP4: gap 3m | AQ4: f gap | AR4: v gap | AS4: n gap (expansivo) | AT4: media gap (expansiva) | AU4: desvío gap (expansivo) | AV4: z gap (±Z_CLIP) | AW4: score = −z | AX4: m del mes = 1 + 0.2·tanh(score) | AY4: m a aplicar (prom. 3 meses) | AZ4: tilt = m − 1 | BA4: activo bruto | BB4: costo | BC4: activo neto | BD4: era | BE4: neto era A | BF4: neto era B | BG4: en vivo (1/0) | BH4: neto en vivo | BI4: fila con señal | BJ4: acumulado total (pb) (NA en meses sin dato) | BK4: acumulado en vivo (pb) (NA en meses sin dato) | BL4: m a aplicar (gráfico) (NA en meses sin dato)
A5: =IF(Datos!A5="","",Datos!A5) | B5: ="" | C5: ="" | D5: ="" | E5: ="" | F5: =IF($A5="","",COUNT(B5:E5)) | G5: =IF($A5="","",IF(F5>=MIN_BANCOS,AVERAGE(B5:E5),"")) | H5: ="" | I5: =IF($A5="","",IF(ISNUMBER(Datos!G5),Datos!G5,"")) | J5: =IF($A5="","",0) | K5: =IF(ISNUMBER(G5),LN(1+G5)-J5,"") | L5: =IF(ISNUMBER(H5),LN(1+H5)-J5,"") | M5: =IF(ISNUMBER(K5),1,0) | N5: =IF(M5=1,K5,0) | O5: =IF(ISNUMBER(L5),1,0) | P5: =IF(O5=1,L5,0) | Q5: =M5*O5 | R5: =0 | S5: ="" | T5: =0 | U5: ="" | V5: =IF(OR(S5="",U5=""),"",S5/U5) | W5: =IF(AND(ISNUMBER(K5),ISNUMBER(L5),ISNUMBER(V5)),K5-V5*L5,"") | X5: ="" | Y5: =IF(ISNUMBER(W5),1,0) | Z5: =IF(Y5=1,W5,0) | AA5: =IF(ISNUMBER(X5),1,0) | AB5: =IF(AA5=1,X5,0) | AC5: =Y5*AA5 | AD5: =0 | AE5: ="" | AF5: =0 | AG5: ="" | AH5: =0 | AI5: ="" | AJ5: ="" | AK5: =IF(OR(AE5="",AG5=""),"",AE5/AG5) | AL5: =IF(OR(AI5="",AK5="",AJ5=""),"",AI5-AK5*AJ5) | AM5: =IF(AND(ISNUMBER(W5),ISNUMBER(X5),ISNUMBER(AK5),ISNUMBER(AL5)),W5-(AL5+AK5*X5),"") | AN5: =IF(ISNUMBER(AM5),1,0) | AO5: =IF(AN5=1,AM5,0) | AP5: ="" | AQ5: =IF(ISNUMBER(AP5),1,0) | AR5: =IF(AQ5=1,AP5,0) | AS5: =SUM(AQ$5:AQ5) | AT5: =IF(AS5>=MIN_OBS_Z,SUMPRODUCT(AQ$5:AQ5,AR$5:AR5)/AS5,"") | AU5: =IF(AS5>=MIN_OBS_Z,SQRT(SUMPRODUCT(AQ$5:AQ5,(AR$5:AR5-AT5)^2)/(AS5-1)),"") | AV5: =IF(AND(AQ5=1,ISNUMBER(AT5)),MAX(-Z_CLIP,MIN(Z_CLIP,(AR5-AT5)/AU5)),"") | AW5: =IF(ISNUMBER(AV5),-AV5,"") | AX5: =IF(ISNUMBER(AW5),1+AMPLITUD*TANH(AW5),"") | AY5: =IF($A5="","",IF(COUNT(AX5:AX5)>0,AVERAGE(AX5:AX5),"")) | AZ5: =IF(ISNUMBER(AY5),AY5-1,"") | BA5: ="" | BB5: =0 | BC5: =IF(ISNUMBER(BA5),BA5-BB5,"") | BD5: =IF(ISNUMBER(BC5),IF(A5<=FECHA_ERA,"A","B"),"") | BE5: =IF(BD5="A",BC5,"") | BF5: =IF(BD5="B",BC5,"") | BG5: =IF(AND(ISNUMBER(BC5),ISNUMBER(A5)),IF(A5>=INICIO_VIVO,1,0),0) | BH5: =IF(BG5=1,BC5,"") | BI5: =IF(ISNUMBER(AY5),ROW(),0) | BJ5: =IF(ISNUMBER(BC5),SUM(BC$5:BC5)*10000,NA()) | BK5: =IF(BG5=1,SUM(BH$5:BH5)*10000,NA()) | BL5: =IF(ISNUMBER(AY5),AY5,NA())
A6: =IF(Datos!A6="","",Datos!A6) | B6: =IF(OR($A6="",NOT(ISNUMBER(Datos!B6)),NOT(ISNUMBER(Datos!B5))),"",Datos!B6/Datos!B5-1) | C6: =IF(OR($A6="",NOT(ISNUMBER(Datos!C6)),NOT(ISNUMBER(Datos!C5))),"",Datos!C6/Datos!C5-1) | D6: =IF(OR($A6="",NOT(ISNUMBER(Datos!D6)),NOT(ISNUMBER(Datos!D5))),"",Datos!D6/Datos!D5-1) | E6: =IF(OR($A6="",NOT(ISNUMBER(Datos!E6)),NOT(ISNUMBER(Datos!E5))),"",Datos!E6/Datos!E5-1) | F6: =IF($A6="","",COUNT(B6:E6)) | G6: =IF($A6="","",IF(F6>=MIN_BANCOS,AVERAGE(B6:E6),"")) | H6: =IF(OR($A6="",NOT(ISNUMBER(Datos!F6)),NOT(ISNUMBER(Datos!F5))),"",Datos!F6/Datos!F5-1) | I6: =IF($A6="","",IF(ISNUMBER(Datos!G6),Datos!G6,I5)) | J6: =IF($A6="","",IF(ISNUMBER(I5),LN(1+I5/100/12),0)) | K6: =IF(ISNUMBER(G6),LN(1+G6)-J6,"") | L6: =IF(ISNUMBER(H6),LN(1+H6)-J6,"") | M6: =IF(ISNUMBER(K6),1,0) | N6: =IF(M6=1,K6,0) | O6: =IF(ISNUMBER(L6),1,0) | P6: =IF(O6=1,L6,0) | Q6: =M6*O6 | R6: =SUM(Q5:Q5) | S6: =IF(OR($A6="",R6<MIN_OBS_ROLL),"",(SUMPRODUCT(Q5:Q5,N5:N5,P5:P5)/R6-SUMPRODUCT(Q5:Q5,N5:N5)/R6*SUMPRODUCT(Q5:Q5,P5:P5)/R6)*R6/(R6-1)) | T6: =SUM(O5:O5) | U6: =IF(OR($A6="",T6<MIN_OBS_ROLL),"",SUMPRODUCT(O5:O5,(P5:P5-SUMPRODUCT(O5:O5,P5:P5)/T6)^2)/(T6-1)) | V6: =IF(OR(S6="",U6=""),"",S6/U6) | W6: =IF(AND(ISNUMBER(K6),ISNUMBER(L6),ISNUMBER(V6)),K6-V6*L6,"") | X6: =IF(OR($A6="",NOT(ISNUMBER(Datos!H6)),NOT(ISNUMBER(Datos!H5))),"",LN(Datos!H6)-LN(Datos!H5)) | Y6: =IF(ISNUMBER(W6),1,0) | Z6: =IF(Y6=1,W6,0) | AA6: =IF(ISNUMBER(X6),1,0) | AB6: =IF(AA6=1,X6,0) | AC6: =Y6*AA6 | AD6: =SUM(AC5:AC5) | AE6: =IF(OR($A6="",AD6<MIN_OBS_ROLL),"",(SUMPRODUCT(AC5:AC5,Z5:Z5,AB5:AB5)/AD6-SUMPRODUCT(AC5:AC5,Z5:Z5)/AD6*SUMPRODUCT(AC5:AC5,AB5:AB5)/AD6)*AD6/(AD6-1)) | AF6: =SUM(AA5:AA5) | AG6: =IF(OR($A6="",AF6<MIN_OBS_ROLL),"",SUMPRODUCT(AA5:AA5,(AB5:AB5-SUMPRODUCT(AA5:AA5,AB5:AB5)/AF6)^2)/(AF6-1)) | AH6: =SUM(Y5:Y5) | AI6: =IF(OR($A6="",AH6<MIN_OBS_ROLL),"",SUMPRODUCT(Y5:Y5,Z5:Z5)/AH6) | AJ6: =IF(OR($A6="",AF6<MIN_OBS_ROLL),"",SUMPRODUCT(AA5:AA5,AB5:AB5)/AF6) | AK6: =IF(OR(AE6="",AG6=""),"",AE6/AG6) | AL6: =IF(OR(AI6="",AK6="",AJ6=""),"",AI6-AK6*AJ6) | AM6: =IF(AND(ISNUMBER(W6),ISNUMBER(X6),ISNUMBER(AK6),ISNUMBER(AL6)),W6-(AL6+AK6*X6),"") | AN6: =IF(ISNUMBER(AM6),1,0) | AO6: =IF(AN6=1,AM6,0) | AP6: ="" | AQ6: =IF(ISNUMBER(AP6),1,0) | AR6: =IF(AQ6=1,AP6,0) | AS6: =SUM(AQ$5:AQ6) | AT6: =IF(AS6>=MIN_OBS_Z,SUMPRODUCT(AQ$5:AQ6,AR$5:AR6)/AS6,"") | AU6: =IF(AS6>=MIN_OBS_Z,SQRT(SUMPRODUCT(AQ$5:AQ6,(AR$5:AR6-AT6)^2)/(AS6-1)),"") | AV6: =IF(AND(AQ6=1,ISNUMBER(AT6)),MAX(-Z_CLIP,MIN(Z_CLIP,(AR6-AT6)/AU6)),"") | AW6: =IF(ISNUMBER(AV6),-AV6,"") | AX6: =IF(ISNUMBER(AW6),1+AMPLITUD*TANH(AW6),"") | AY6: =IF($A6="","",IF(COUNT(AX5:AX6)>0,AVERAGE(AX5:AX6),"")) | AZ6: =IF(ISNUMBER(AY6),AY6-1,"") | BA6: =IF(AND(ISNUMBER(AZ5),ISNUMBER(W6)),AZ5*W_BANCOS*W6,"") | BB6: =0 | BC6: =IF(ISNUMBER(BA6),BA6-BB6,"") | BD6: =IF(ISNUMBER(BC6),IF(A6<=FECHA_ERA,"A","B"),"") | BE6: =IF(BD6="A",BC6,"") | BF6: =IF(BD6="B",BC6,"") | BG6: =IF(AND(ISNUMBER(BC6),ISNUMBER(A6)),IF(A6>=INICIO_VIVO,1,0),0) | BH6: =IF(BG6=1,BC6,"") | BI6: =IF(ISNUMBER(AY6),ROW(),0) | BJ6: =IF(ISNUMBER(BC6),SUM(BC$5:BC6)*10000,NA()) | BK6: =IF(BG6=1,SUM(BH$5:BH6)*10000,NA()) | BL6: =IF(ISNUMBER(AY6),AY6,NA())
A7: =IF(Datos!A7="","",Datos!A7) | B7: =IF(OR($A7="",NOT(ISNUMBER(Datos!B7)),NOT(ISNUMBER(Datos!B6))),"",Datos!B7/Datos!B6-1) | C7: =IF(OR($A7="",NOT(ISNUMBER(Datos!C7)),NOT(ISNUMBER(Datos!C6))),"",Datos!C7/Datos!C6-1) | D7: =IF(OR($A7="",NOT(ISNUMBER(Datos!D7)),NOT(ISNUMBER(Datos!D6))),"",Datos!D7/Datos!D6-1) | E7: =IF(OR($A7="",NOT(ISNUMBER(Datos!E7)),NOT(ISNUMBER(Datos!E6))),"",Datos!E7/Datos!E6-1) | F7: =IF($A7="","",COUNT(B7:E7)) | G7: =IF($A7="","",IF(F7>=MIN_BANCOS,AVERAGE(B7:E7),"")) | H7: =IF(OR($A7="",NOT(ISNUMBER(Datos!F7)),NOT(ISNUMBER(Datos!F6))),"",Datos!F7/Datos!F6-1) | I7: =IF($A7="","",IF(ISNUMBER(Datos!G7),Datos!G7,I6)) | J7: =IF($A7="","",IF(ISNUMBER(I6),LN(1+I6/100/12),0)) | K7: =IF(ISNUMBER(G7),LN(1+G7)-J7,"") | L7: =IF(ISNUMBER(H7),LN(1+H7)-J7,"") | M7: =IF(ISNUMBER(K7),1,0) | N7: =IF(M7=1,K7,0) | O7: =IF(ISNUMBER(L7),1,0) | P7: =IF(O7=1,L7,0) | Q7: =M7*O7 | R7: =SUM(Q5:Q6) | S7: =IF(OR($A7="",R7<MIN_OBS_ROLL),"",(SUMPRODUCT(Q5:Q6,N5:N6,P5:P6)/R7-SUMPRODUCT(Q5:Q6,N5:N6)/R7*SUMPRODUCT(Q5:Q6,P5:P6)/R7)*R7/(R7-1)) | T7: =SUM(O5:O6) | U7: =IF(OR($A7="",T7<MIN_OBS_ROLL),"",SUMPRODUCT(O5:O6,(P5:P6-SUMPRODUCT(O5:O6,P5:P6)/T7)^2)/(T7-1)) | V7: =IF(OR(S7="",U7=""),"",S7/U7) | W7: =IF(AND(ISNUMBER(K7),ISNUMBER(L7),ISNUMBER(V7)),K7-V7*L7,"") | X7: =IF(OR($A7="",NOT(ISNUMBER(Datos!H7)),NOT(ISNUMBER(Datos!H6))),"",LN(Datos!H7)-LN(Datos!H6)) | Y7: =IF(ISNUMBER(W7),1,0) | Z7: =IF(Y7=1,W7,0) | AA7: =IF(ISNUMBER(X7),1,0) | AB7: =IF(AA7=1,X7,0) | AC7: =Y7*AA7 | AD7: =SUM(AC5:AC6) | AE7: =IF(OR($A7="",AD7<MIN_OBS_ROLL),"",(SUMPRODUCT(AC5:AC6,Z5:Z6,AB5:AB6)/AD7-SUMPRODUCT(AC5:AC6,Z5:Z6)/AD7*SUMPRODUCT(AC5:AC6,AB5:AB6)/AD7)*AD7/(AD7-1)) | AF7: =SUM(AA5:AA6) | AG7: =IF(OR($A7="",AF7<MIN_OBS_ROLL),"",SUMPRODUCT(AA5:AA6,(AB5:AB6-SUMPRODUCT(AA5:AA6,AB5:AB6)/AF7)^2)/(AF7-1)) | AH7: =SUM(Y5:Y6) | AI7: =IF(OR($A7="",AH7<MIN_OBS_ROLL),"",SUMPRODUCT(Y5:Y6,Z5:Z6)/AH7) | AJ7: =IF(OR($A7="",AF7<MIN_OBS_ROLL),"",SUMPRODUCT(AA5:AA6,AB5:AB6)/AF7) | AK7: =IF(OR(AE7="",AG7=""),"",AE7/AG7) | AL7: =IF(OR(AI7="",AK7="",AJ7=""),"",AI7-AK7*AJ7) | AM7: =IF(AND(ISNUMBER(W7),ISNUMBER(X7),ISNUMBER(AK7),ISNUMBER(AL7)),W7-(AL7+AK7*X7),"") | AN7: =IF(ISNUMBER(AM7),1,0) | AO7: =IF(AN7=1,AM7,0) | AP7: =IF(SUM(AN5:AN7)=3,SUM(AO5:AO7),"") | AQ7: =IF(ISNUMBER(AP7),1,0) | AR7: =IF(AQ7=1,AP7,0) | AS7: =SUM(AQ$5:AQ7) | AT7: =IF(AS7>=MIN_OBS_Z,SUMPRODUCT(AQ$5:AQ7,AR$5:AR7)/AS7,"") | AU7: =IF(AS7>=MIN_OBS_Z,SQRT(SUMPRODUCT(AQ$5:AQ7,(AR$5:AR7-AT7)^2)/(AS7-1)),"") | AV7: =IF(AND(AQ7=1,ISNUMBER(AT7)),MAX(-Z_CLIP,MIN(Z_CLIP,(AR7-AT7)/AU7)),"") | AW7: =IF(ISNUMBER(AV7),-AV7,"") | AX7: =IF(ISNUMBER(AW7),1+AMPLITUD*TANH(AW7),"") | AY7: =IF($A7="","",IF(COUNT(AX5:AX7)>0,AVERAGE(AX5:AX7),"")) | AZ7: =IF(ISNUMBER(AY7),AY7-1,"") | BA7: =IF(AND(ISNUMBER(AZ6),ISNUMBER(W7)),AZ6*W_BANCOS*W7,"") | BB7: =IF(AND(ISNUMBER(AZ6),ISNUMBER(AZ5)),ABS(AZ6-AZ5)*W_BANCOS*COSTO,0) | BC7: =IF(ISNUMBER(BA7),BA7-BB7,"") | BD7: =IF(ISNUMBER(BC7),IF(A7<=FECHA_ERA,"A","B"),"") | BE7: =IF(BD7="A",BC7,"") | BF7: =IF(BD7="B",BC7,"") | BG7: =IF(AND(ISNUMBER(BC7),ISNUMBER(A7)),IF(A7>=INICIO_VIVO,1,0),0) | BH7: =IF(BG7=1,BC7,"") | BI7: =IF(ISNUMBER(AY7),ROW(),0) | BJ7: =IF(ISNUMBER(BC7),SUM(BC$5:BC7)*10000,NA()) | BK7: =IF(BG7=1,SUM(BH$5:BH7)*10000,NA()) | BL7: =IF(ISNUMBER(AY7),AY7,NA())
A8: =IF(Datos!A8="","",Datos!A8) | B8: =IF(OR($A8="",NOT(ISNUMBER(Datos!B8)),NOT(ISNUMBER(Datos!B7))),"",Datos!B8/Datos!B7-1) | C8: =IF(OR($A8="",NOT(ISNUMBER(Datos!C8)),NOT(ISNUMBER(Datos!C7))),"",Datos!C8/Datos!C7-1) | D8: =IF(OR($A8="",NOT(ISNUMBER(Datos!D8)),NOT(ISNUMBER(Datos!D7))),"",Datos!D8/Datos!D7-1) | E8: =IF(OR($A8="",NOT(ISNUMBER(Datos!E8)),NOT(ISNUMBER(Datos!E7))),"",Datos!E8/Datos!E7-1) | F8: =IF($A8="","",COUNT(B8:E8)) | G8: =IF($A8="","",IF(F8>=MIN_BANCOS,AVERAGE(B8:E8),"")) | H8: =IF(OR($A8="",NOT(ISNUMBER(Datos!F8)),NOT(ISNUMBER(Datos!F7))),"",Datos!F8/Datos!F7-1) | I8: =IF($A8="","",IF(ISNUMBER(Datos!G8),Datos!G8,I7)) | J8: =IF($A8="","",IF(ISNUMBER(I7),LN(1+I7/100/12),0)) | K8: =IF(ISNUMBER(G8),LN(1+G8)-J8,"") | L8: =IF(ISNUMBER(H8),LN(1+H8)-J8,"") | M8: =IF(ISNUMBER(K8),1,0) | N8: =IF(M8=1,K8,0) | O8: =IF(ISNUMBER(L8),1,0) | P8: =IF(O8=1,L8,0) | Q8: =M8*O8 | R8: =SUM(Q5:Q7) | S8: =IF(OR($A8="",R8<MIN_OBS_ROLL),"",(SUMPRODUCT(Q5:Q7,N5:N7,P5:P7)/R8-SUMPRODUCT(Q5:Q7,N5:N7)/R8*SUMPRODUCT(Q5:Q7,P5:P7)/R8)*R8/(R8-1)) | T8: =SUM(O5:O7) | U8: =IF(OR($A8="",T8<MIN_OBS_ROLL),"",SUMPRODUCT(O5:O7,(P5:P7-SUMPRODUCT(O5:O7,P5:P7)/T8)^2)/(T8-1)) | V8: =IF(OR(S8="",U8=""),"",S8/U8) | W8: =IF(AND(ISNUMBER(K8),ISNUMBER(L8),ISNUMBER(V8)),K8-V8*L8,"") | X8: =IF(OR($A8="",NOT(ISNUMBER(Datos!H8)),NOT(ISNUMBER(Datos!H7))),"",LN(Datos!H8)-LN(Datos!H7)) | Y8: =IF(ISNUMBER(W8),1,0) | Z8: =IF(Y8=1,W8,0) | AA8: =IF(ISNUMBER(X8),1,0) | AB8: =IF(AA8=1,X8,0) | AC8: =Y8*AA8 | AD8: =SUM(AC5:AC7) | AE8: =IF(OR($A8="",AD8<MIN_OBS_ROLL),"",(SUMPRODUCT(AC5:AC7,Z5:Z7,AB5:AB7)/AD8-SUMPRODUCT(AC5:AC7,Z5:Z7)/AD8*SUMPRODUCT(AC5:AC7,AB5:AB7)/AD8)*AD8/(AD8-1)) | AF8: =SUM(AA5:AA7) | AG8: =IF(OR($A8="",AF8<MIN_OBS_ROLL),"",SUMPRODUCT(AA5:AA7,(AB5:AB7-SUMPRODUCT(AA5:AA7,AB5:AB7)/AF8)^2)/(AF8-1)) | AH8: =SUM(Y5:Y7) | AI8: =IF(OR($A8="",AH8<MIN_OBS_ROLL),"",SUMPRODUCT(Y5:Y7,Z5:Z7)/AH8) | AJ8: =IF(OR($A8="",AF8<MIN_OBS_ROLL),"",SUMPRODUCT(AA5:AA7,AB5:AB7)/AF8) | AK8: =IF(OR(AE8="",AG8=""),"",AE8/AG8) | AL8: =IF(OR(AI8="",AK8="",AJ8=""),"",AI8-AK8*AJ8) | AM8: =IF(AND(ISNUMBER(W8),ISNUMBER(X8),ISNUMBER(AK8),ISNUMBER(AL8)),W8-(AL8+AK8*X8),"") | AN8: =IF(ISNUMBER(AM8),1,0) | AO8: =IF(AN8=1,AM8,0) | AP8: =IF(SUM(AN6:AN8)=3,SUM(AO6:AO8),"") | AQ8: =IF(ISNUMBER(AP8),1,0) | AR8: =IF(AQ8=1,AP8,0) | AS8: =SUM(AQ$5:AQ8) | AT8: =IF(AS8>=MIN_OBS_Z,SUMPRODUCT(AQ$5:AQ8,AR$5:AR8)/AS8,"") | AU8: =IF(AS8>=MIN_OBS_Z,SQRT(SUMPRODUCT(AQ$5:AQ8,(AR$5:AR8-AT8)^2)/(AS8-1)),"") | AV8: =IF(AND(AQ8=1,ISNUMBER(AT8)),MAX(-Z_CLIP,MIN(Z_CLIP,(AR8-AT8)/AU8)),"") | AW8: =IF(ISNUMBER(AV8),-AV8,"") | AX8: =IF(ISNUMBER(AW8),1+AMPLITUD*TANH(AW8),"") | AY8: =IF($A8="","",IF(COUNT(AX6:AX8)>0,AVERAGE(AX6:AX8),"")) | AZ8: =IF(ISNUMBER(AY8),AY8-1,"") | BA8: =IF(AND(ISNUMBER(AZ7),ISNUMBER(W8)),AZ7*W_BANCOS*W8,"") | BB8: =IF(AND(ISNUMBER(AZ7),ISNUMBER(AZ6)),ABS(AZ7-AZ6)*W_BANCOS*COSTO,0) | BC8: =IF(ISNUMBER(BA8),BA8-BB8,"") | BD8: =IF(ISNUMBER(BC8),IF(A8<=FECHA_ERA,"A","B"),"") | BE8: =IF(BD8="A",BC8,"") | BF8: =IF(BD8="B",BC8,"") | BG8: =IF(AND(ISNUMBER(BC8),ISNUMBER(A8)),IF(A8>=INICIO_VIVO,1,0),0) | BH8: =IF(BG8=1,BC8,"") | BI8: =IF(ISNUMBER(AY8),ROW(),0) | BJ8: =IF(ISNUMBER(BC8),SUM(BC$5:BC8)*10000,NA()) | BK8: =IF(BG8=1,SUM(BH$5:BH8)*10000,NA()) | BL8: =IF(ISNUMBER(AY8),AY8,NA())
A9: =IF(Datos!A9="","",Datos!A9) | B9: =IF(OR($A9="",NOT(ISNUMBER(Datos!B9)),NOT(ISNUMBER(Datos!B8))),"",Datos!B9/Datos!B8-1) | C9: =IF(OR($A9="",NOT(ISNUMBER(Datos!C9)),NOT(ISNUMBER(Datos!C8))),"",Datos!C9/Datos!C8-1) | D9: =IF(OR($A9="",NOT(ISNUMBER(Datos!D9)),NOT(ISNUMBER(Datos!D8))),"",Datos!D9/Datos!D8-1) | E9: =IF(OR($A9="",NOT(ISNUMBER(Datos!E9)),NOT(ISNUMBER(Datos!E8))),"",Datos!E9/Datos!E8-1) | F9: =IF($A9="","",COUNT(B9:E9)) | G9: =IF($A9="","",IF(F9>=MIN_BANCOS,AVERAGE(B9:E9),"")) | H9: =IF(OR($A9="",NOT(ISNUMBER(Datos!F9)),NOT(ISNUMBER(Datos!F8))),"",Datos!F9/Datos!F8-1) | I9: =IF($A9="","",IF(ISNUMBER(Datos!G9),Datos!G9,I8)) | J9: =IF($A9="","",IF(ISNUMBER(I8),LN(1+I8/100/12),0)) | K9: =IF(ISNUMBER(G9),LN(1+G9)-J9,"") | L9: =IF(ISNUMBER(H9),LN(1+H9)-J9,"") | M9: =IF(ISNUMBER(K9),1,0) | N9: =IF(M9=1,K9,0) | O9: =IF(ISNUMBER(L9),1,0) | P9: =IF(O9=1,L9,0) | Q9: =M9*O9 | R9: =SUM(Q5:Q8) | S9: =IF(OR($A9="",R9<MIN_OBS_ROLL),"",(SUMPRODUCT(Q5:Q8,N5:N8,P5:P8)/R9-SUMPRODUCT(Q5:Q8,N5:N8)/R9*SUMPRODUCT(Q5:Q8,P5:P8)/R9)*R9/(R9-1)) | T9: =SUM(O5:O8) | U9: =IF(OR($A9="",T9<MIN_OBS_ROLL),"",SUMPRODUCT(O5:O8,(P5:P8-SUMPRODUCT(O5:O8,P5:P8)/T9)^2)/(T9-1)) | V9: =IF(OR(S9="",U9=""),"",S9/U9) | W9: =IF(AND(ISNUMBER(K9),ISNUMBER(L9),ISNUMBER(V9)),K9-V9*L9,"") | X9: =IF(OR($A9="",NOT(ISNUMBER(Datos!H9)),NOT(ISNUMBER(Datos!H8))),"",LN(Datos!H9)-LN(Datos!H8)) | Y9: =IF(ISNUMBER(W9),1,0) | Z9: =IF(Y9=1,W9,0) | AA9: =IF(ISNUMBER(X9),1,0) | AB9: =IF(AA9=1,X9,0) | AC9: =Y9*AA9 | AD9: =SUM(AC5:AC8) | AE9: =IF(OR($A9="",AD9<MIN_OBS_ROLL),"",(SUMPRODUCT(AC5:AC8,Z5:Z8,AB5:AB8)/AD9-SUMPRODUCT(AC5:AC8,Z5:Z8)/AD9*SUMPRODUCT(AC5:AC8,AB5:AB8)/AD9)*AD9/(AD9-1)) | AF9: =SUM(AA5:AA8) | AG9: =IF(OR($A9="",AF9<MIN_OBS_ROLL),"",SUMPRODUCT(AA5:AA8,(AB5:AB8-SUMPRODUCT(AA5:AA8,AB5:AB8)/AF9)^2)/(AF9-1)) | AH9: =SUM(Y5:Y8) | AI9: =IF(OR($A9="",AH9<MIN_OBS_ROLL),"",SUMPRODUCT(Y5:Y8,Z5:Z8)/AH9) | AJ9: =IF(OR($A9="",AF9<MIN_OBS_ROLL),"",SUMPRODUCT(AA5:AA8,AB5:AB8)/AF9) | AK9: =IF(OR(AE9="",AG9=""),"",AE9/AG9) | AL9: =IF(OR(AI9="",AK9="",AJ9=""),"",AI9-AK9*AJ9) | AM9: =IF(AND(ISNUMBER(W9),ISNUMBER(X9),ISNUMBER(AK9),ISNUMBER(AL9)),W9-(AL9+AK9*X9),"") | AN9: =IF(ISNUMBER(AM9),1,0) | AO9: =IF(AN9=1,AM9,0) | AP9: =IF(SUM(AN7:AN9)=3,SUM(AO7:AO9),"") | AQ9: =IF(ISNUMBER(AP9),1,0) | AR9: =IF(AQ9=1,AP9,0) | AS9: =SUM(AQ$5:AQ9) | AT9: =IF(AS9>=MIN_OBS_Z,SUMPRODUCT(AQ$5:AQ9,AR$5:AR9)/AS9,"") | AU9: =IF(AS9>=MIN_OBS_Z,SQRT(SUMPRODUCT(AQ$5:AQ9,(AR$5:AR9-AT9)^2)/(AS9-1)),"") | AV9: =IF(AND(AQ9=1,ISNUMBER(AT9)),MAX(-Z_CLIP,MIN(Z_CLIP,(AR9-AT9)/AU9)),"") | AW9: =IF(ISNUMBER(AV9),-AV9,"") | AX9: =IF(ISNUMBER(AW9),1+AMPLITUD*TANH(AW9),"") | AY9: =IF($A9="","",IF(COUNT(AX7:AX9)>0,AVERAGE(AX7:AX9),"")) | AZ9: =IF(ISNUMBER(AY9),AY9-1,"") | BA9: =IF(AND(ISNUMBER(AZ8),ISNUMBER(W9)),AZ8*W_BANCOS*W9,"") | BB9: =IF(AND(ISNUMBER(AZ8),ISNUMBER(AZ7)),ABS(AZ8-AZ7)*W_BANCOS*COSTO,0) | BC9: =IF(ISNUMBER(BA9),BA9-BB9,"") | BD9: =IF(ISNUMBER(BC9),IF(A9<=FECHA_ERA,"A","B"),"") | BE9: =IF(BD9="A",BC9,"") | BF9: =IF(BD9="B",BC9,"") | BG9: =IF(AND(ISNUMBER(BC9),ISNUMBER(A9)),IF(A9>=INICIO_VIVO,1,0),0) | BH9: =IF(BG9=1,BC9,"") | BI9: =IF(ISNUMBER(AY9),ROW(),0) | BJ9: =IF(ISNUMBER(BC9),SUM(BC$5:BC9)*10000,NA()) | BK9: =IF(BG9=1,SUM(BH$5:BH9)*10000,NA()) | BL9: =IF(ISNUMBER(AY9),AY9,NA())
A10: =IF(Datos!A10="","",Datos!A10) | B10: =IF(OR($A10="",NOT(ISNUMBER(Datos!B10)),NOT(ISNUMBER(Datos!B9))),"",Datos!B10/Datos!B9-1) | C10: =IF(OR($A10="",NOT(ISNUMBER(Datos!C10)),NOT(ISNUMBER(Datos!C9))),"",Datos!C10/Datos!C9-1) | D10: =IF(OR($A10="",NOT(ISNUMBER(Datos!D10)),NOT(ISNUMBER(Datos!D9))),"",Datos!D10/Datos!D9-1) | E10: =IF(OR($A10="",NOT(ISNUMBER(Datos!E10)),NOT(ISNUMBER(Datos!E9))),"",Datos!E10/Datos!E9-1) | F10: =IF($A10="","",COUNT(B10:E10)) | G10: =IF($A10="","",IF(F10>=MIN_BANCOS,AVERAGE(B10:E10),"")) | H10: =IF(OR($A10="",NOT(ISNUMBER(Datos!F10)),NOT(ISNUMBER(Datos!F9))),"",Datos!F10/Datos!F9-1) | I10: =IF($A10="","",IF(ISNUMBER(Datos!G10),Datos!G10,I9)) | J10: =IF($A10="","",IF(ISNUMBER(I9),LN(1+I9/100/12),0)) | K10: =IF(ISNUMBER(G10),LN(1+G10)-J10,"") | L10: =IF(ISNUMBER(H10),LN(1+H10)-J10,"") | M10: =IF(ISNUMBER(K10),1,0) | N10: =IF(M10=1,K10,0) | O10: =IF(ISNUMBER(L10),1,0) | P10: =IF(O10=1,L10,0) | Q10: =M10*O10 | R10: =SUM(Q5:Q9) | S10: =IF(OR($A10="",R10<MIN_OBS_ROLL),"",(SUMPRODUCT(Q5:Q9,N5:N9,P5:P9)/R10-SUMPRODUCT(Q5:Q9,N5:N9)/R10*SUMPRODUCT(Q5:Q9,P5:P9)/R10)*R10/(R10-1)) | T10: =SUM(O5:O9) | U10: =IF(OR($A10="",T10<MIN_OBS_ROLL),"",SUMPRODUCT(O5:O9,(P5:P9-SUMPRODUCT(O5:O9,P5:P9)/T10)^2)/(T10-1)) | V10: =IF(OR(S10="",U10=""),"",S10/U10) | W10: =IF(AND(ISNUMBER(K10),ISNUMBER(L10),ISNUMBER(V10)),K10-V10*L10,"") | X10: =IF(OR($A10="",NOT(ISNUMBER(Datos!H10)),NOT(ISNUMBER(Datos!H9))),"",LN(Datos!H10)-LN(Datos!H9)) | Y10: =IF(ISNUMBER(W10),1,0) | Z10: =IF(Y10=1,W10,0) | AA10: =IF(ISNUMBER(X10),1,0) | AB10: =IF(AA10=1,X10,0) | AC10: =Y10*AA10 | AD10: =SUM(AC5:AC9) | AE10: =IF(OR($A10="",AD10<MIN_OBS_ROLL),"",(SUMPRODUCT(AC5:AC9,Z5:Z9,AB5:AB9)/AD10-SUMPRODUCT(AC5:AC9,Z5:Z9)/AD10*SUMPRODUCT(AC5:AC9,AB5:AB9)/AD10)*AD10/(AD10-1)) | AF10: =SUM(AA5:AA9) | AG10: =IF(OR($A10="",AF10<MIN_OBS_ROLL),"",SUMPRODUCT(AA5:AA9,(AB5:AB9-SUMPRODUCT(AA5:AA9,AB5:AB9)/AF10)^2)/(AF10-1)) | AH10: =SUM(Y5:Y9) | AI10: =IF(OR($A10="",AH10<MIN_OBS_ROLL),"",SUMPRODUCT(Y5:Y9,Z5:Z9)/AH10) | AJ10: =IF(OR($A10="",AF10<MIN_OBS_ROLL),"",SUMPRODUCT(AA5:AA9,AB5:AB9)/AF10) | AK10: =IF(OR(AE10="",AG10=""),"",AE10/AG10) | AL10: =IF(OR(AI10="",AK10="",AJ10=""),"",AI10-AK10*AJ10) | AM10: =IF(AND(ISNUMBER(W10),ISNUMBER(X10),ISNUMBER(AK10),ISNUMBER(AL10)),W10-(AL10+AK10*X10),"") | AN10: =IF(ISNUMBER(AM10),1,0) | AO10: =IF(AN10=1,AM10,0) | AP10: =IF(SUM(AN8:AN10)=3,SUM(AO8:AO10),"") | AQ10: =IF(ISNUMBER(AP10),1,0) | AR10: =IF(AQ10=1,AP10,0) | AS10: =SUM(AQ$5:AQ10) | AT10: =IF(AS10>=MIN_OBS_Z,SUMPRODUCT(AQ$5:AQ10,AR$5:AR10)/AS10,"") | AU10: =IF(AS10>=MIN_OBS_Z,SQRT(SUMPRODUCT(AQ$5:AQ10,(AR$5:AR10-AT10)^2)/(AS10-1)),"") | AV10: =IF(AND(AQ10=1,ISNUMBER(AT10)),MAX(-Z_CLIP,MIN(Z_CLIP,(AR10-AT10)/AU10)),"") | AW10: =IF(ISNUMBER(AV10),-AV10,"") | AX10: =IF(ISNUMBER(AW10),1+AMPLITUD*TANH(AW10),"") | AY10: =IF($A10="","",IF(COUNT(AX8:AX10)>0,AVERAGE(AX8:AX10),"")) | AZ10: =IF(ISNUMBER(AY10),AY10-1,"") | BA10: =IF(AND(ISNUMBER(AZ9),ISNUMBER(W10)),AZ9*W_BANCOS*W10,"") | BB10: =IF(AND(ISNUMBER(AZ9),ISNUMBER(AZ8)),ABS(AZ9-AZ8)*W_BANCOS*COSTO,0) | BC10: =IF(ISNUMBER(BA10),BA10-BB10,"") | BD10: =IF(ISNUMBER(BC10),IF(A10<=FECHA_ERA,"A","B"),"") | BE10: =IF(BD10="A",BC10,"") | BF10: =IF(BD10="B",BC10,"") | BG10: =IF(AND(ISNUMBER(BC10),ISNUMBER(A10)),IF(A10>=INICIO_VIVO,1,0),0) | BH10: =IF(BG10=1,BC10,"") | BI10: =IF(ISNUMBER(AY10),ROW(),0) | BJ10: =IF(ISNUMBER(BC10),SUM(BC$5:BC10)*10000,NA()) | BK10: =IF(BG10=1,SUM(BH$5:BH10)*10000,NA()) | BL10: =IF(ISNUMBER(AY10),AY10,NA())
A11: =IF(Datos!A11="","",Datos!A11) | B11: =IF(OR($A11="",NOT(ISNUMBER(Datos!B11)),NOT(ISNUMBER(Datos!B10))),"",Datos!B11/Datos!B10-1) | C11: =IF(OR($A11="",NOT(ISNUMBER(Datos!C11)),NOT(ISNUMBER(Datos!C10))),"",Datos!C11/Datos!C10-1) | D11: =IF(OR($A11="",NOT(ISNUMBER(Datos!D11)),NOT(ISNUMBER(Datos!D10))),"",Datos!D11/Datos!D10-1) | E11: =IF(OR($A11="",NOT(ISNUMBER(Datos!E11)),NOT(ISNUMBER(Datos!E10))),"",Datos!E11/Datos!E10-1) | F11: =IF($A11="","",COUNT(B11:E11)) | G11: =IF($A11="","",IF(F11>=MIN_BANCOS,AVERAGE(B11:E11),"")) | H11: =IF(OR($A11="",NOT(ISNUMBER(Datos!F11)),NOT(ISNUMBER(Datos!F10))),"",Datos!F11/Datos!F10-1) | I11: =IF($A11="","",IF(ISNUMBER(Datos!G11),Datos!G11,I10)) | J11: =IF($A11="","",IF(ISNUMBER(I10),LN(1+I10/100/12),0)) | K11: =IF(ISNUMBER(G11),LN(1+G11)-J11,"") | L11: =IF(ISNUMBER(H11),LN(1+H11)-J11,"") | M11: =IF(ISNUMBER(K11),1,0) | N11: =IF(M11=1,K11,0) | O11: =IF(ISNUMBER(L11),1,0) | P11: =IF(O11=1,L11,0) | Q11: =M11*O11 | R11: =SUM(Q5:Q10) | S11: =IF(OR($A11="",R11<MIN_OBS_ROLL),"",(SUMPRODUCT(Q5:Q10,N5:N10,P5:P10)/R11-SUMPRODUCT(Q5:Q10,N5:N10)/R11*SUMPRODUCT(Q5:Q10,P5:P10)/R11)*R11/(R11-1)) | T11: =SUM(O5:O10) | U11: =IF(OR($A11="",T11<MIN_OBS_ROLL),"",SUMPRODUCT(O5:O10,(P5:P10-SUMPRODUCT(O5:O10,P5:P10)/T11)^2)/(T11-1)) | V11: =IF(OR(S11="",U11=""),"",S11/U11) | W11: =IF(AND(ISNUMBER(K11),ISNUMBER(L11),ISNUMBER(V11)),K11-V11*L11,"") | X11: =IF(OR($A11="",NOT(ISNUMBER(Datos!H11)),NOT(ISNUMBER(Datos!H10))),"",LN(Datos!H11)-LN(Datos!H10)) | Y11: =IF(ISNUMBER(W11),1,0) | Z11: =IF(Y11=1,W11,0) | AA11: =IF(ISNUMBER(X11),1,0) | AB11: =IF(AA11=1,X11,0) | AC11: =Y11*AA11 | AD11: =SUM(AC5:AC10) | AE11: =IF(OR($A11="",AD11<MIN_OBS_ROLL),"",(SUMPRODUCT(AC5:AC10,Z5:Z10,AB5:AB10)/AD11-SUMPRODUCT(AC5:AC10,Z5:Z10)/AD11*SUMPRODUCT(AC5:AC10,AB5:AB10)/AD11)*AD11/(AD11-1)) | AF11: =SUM(AA5:AA10) | AG11: =IF(OR($A11="",AF11<MIN_OBS_ROLL),"",SUMPRODUCT(AA5:AA10,(AB5:AB10-SUMPRODUCT(AA5:AA10,AB5:AB10)/AF11)^2)/(AF11-1)) | AH11: =SUM(Y5:Y10) | AI11: =IF(OR($A11="",AH11<MIN_OBS_ROLL),"",SUMPRODUCT(Y5:Y10,Z5:Z10)/AH11) | AJ11: =IF(OR($A11="",AF11<MIN_OBS_ROLL),"",SUMPRODUCT(AA5:AA10,AB5:AB10)/AF11) | AK11: =IF(OR(AE11="",AG11=""),"",AE11/AG11) | AL11: =IF(OR(AI11="",AK11="",AJ11=""),"",AI11-AK11*AJ11) | AM11: =IF(AND(ISNUMBER(W11),ISNUMBER(X11),ISNUMBER(AK11),ISNUMBER(AL11)),W11-(AL11+AK11*X11),"") | AN11: =IF(ISNUMBER(AM11),1,0) | AO11: =IF(AN11=1,AM11,0) | AP11: =IF(SUM(AN9:AN11)=3,SUM(AO9:AO11),"") | AQ11: =IF(ISNUMBER(AP11),1,0) | AR11: =IF(AQ11=1,AP11,0) | AS11: =SUM(AQ$5:AQ11) | AT11: =IF(AS11>=MIN_OBS_Z,SUMPRODUCT(AQ$5:AQ11,AR$5:AR11)/AS11,"") | AU11: =IF(AS11>=MIN_OBS_Z,SQRT(SUMPRODUCT(AQ$5:AQ11,(AR$5:AR11-AT11)^2)/(AS11-1)),"") | AV11: =IF(AND(AQ11=1,ISNUMBER(AT11)),MAX(-Z_CLIP,MIN(Z_CLIP,(AR11-AT11)/AU11)),"") | AW11: =IF(ISNUMBER(AV11),-AV11,"") | AX11: =IF(ISNUMBER(AW11),1+AMPLITUD*TANH(AW11),"") | AY11: =IF($A11="","",IF(COUNT(AX9:AX11)>0,AVERAGE(AX9:AX11),"")) | AZ11: =IF(ISNUMBER(AY11),AY11-1,"") | BA11: =IF(AND(ISNUMBER(AZ10),ISNUMBER(W11)),AZ10*W_BANCOS*W11,"") | BB11: =IF(AND(ISNUMBER(AZ10),ISNUMBER(AZ9)),ABS(AZ10-AZ9)*W_BANCOS*COSTO,0) | BC11: =IF(ISNUMBER(BA11),BA11-BB11,"") | BD11: =IF(ISNUMBER(BC11),IF(A11<=FECHA_ERA,"A","B"),"") | BE11: =IF(BD11="A",BC11,"") | BF11: =IF(BD11="B",BC11,"") | BG11: =IF(AND(ISNUMBER(BC11),ISNUMBER(A11)),IF(A11>=INICIO_VIVO,1,0),0) | BH11: =IF(BG11=1,BC11,"") | BI11: =IF(ISNUMBER(AY11),ROW(),0) | BJ11: =IF(ISNUMBER(BC11),SUM(BC$5:BC11)*10000,NA()) | BK11: =IF(BG11=1,SUM(BH$5:BH11)*10000,NA()) | BL11: =IF(ISNUMBER(AY11),AY11,NA())
A12: =IF(Datos!A12="","",Datos!A12) | B12: =IF(OR($A12="",NOT(ISNUMBER(Datos!B12)),NOT(ISNUMBER(Datos!B11))),"",Datos!B12/Datos!B11-1) | C12: =IF(OR($A12="",NOT(ISNUMBER(Datos!C12)),NOT(ISNUMBER(Datos!C11))),"",Datos!C12/Datos!C11-1) | D12: =IF(OR($A12="",NOT(ISNUMBER(Datos!D12)),NOT(ISNUMBER(Datos!D11))),"",Datos!D12/Datos!D11-1) | E12: =IF(OR($A12="",NOT(ISNUMBER(Datos!E12)),NOT(ISNUMBER(Datos!E11))),"",Datos!E12/Datos!E11-1) | F12: =IF($A12="","",COUNT(B12:E12)) | G12: =IF($A12="","",IF(F12>=MIN_BANCOS,AVERAGE(B12:E12),"")) | H12: =IF(OR($A12="",NOT(ISNUMBER(Datos!F12)),NOT(ISNUMBER(Datos!F11))),"",Datos!F12/Datos!F11-1) | I12: =IF($A12="","",IF(ISNUMBER(Datos!G12),Datos!G12,I11)) | J12: =IF($A12="","",IF(ISNUMBER(I11),LN(1+I11/100/12),0)) | K12: =IF(ISNUMBER(G12),LN(1+G12)-J12,"") | L12: =IF(ISNUMBER(H12),LN(1+H12)-J12,"") | M12: =IF(ISNUMBER(K12),1,0) | N12: =IF(M12=1,K12,0) | O12: =IF(ISNUMBER(L12),1,0) | P12: =IF(O12=1,L12,0) | Q12: =M12*O12 | R12: =SUM(Q5:Q11) | S12: =IF(OR($A12="",R12<MIN_OBS_ROLL),"",(SUMPRODUCT(Q5:Q11,N5:N11,P5:P11)/R12-SUMPRODUCT(Q5:Q11,N5:N11)/R12*SUMPRODUCT(Q5:Q11,P5:P11)/R12)*R12/(R12-1)) | T12: =SUM(O5:O11) | U12: =IF(OR($A12="",T12<MIN_OBS_ROLL),"",SUMPRODUCT(O5:O11,(P5:P11-SUMPRODUCT(O5:O11,P5:P11)/T12)^2)/(T12-1)) | V12: =IF(OR(S12="",U12=""),"",S12/U12) | W12: =IF(AND(ISNUMBER(K12),ISNUMBER(L12),ISNUMBER(V12)),K12-V12*L12,"") | X12: =IF(OR($A12="",NOT(ISNUMBER(Datos!H12)),NOT(ISNUMBER(Datos!H11))),"",LN(Datos!H12)-LN(Datos!H11)) | Y12: =IF(ISNUMBER(W12),1,0) | Z12: =IF(Y12=1,W12,0) | AA12: =IF(ISNUMBER(X12),1,0) | AB12: =IF(AA12=1,X12,0) | AC12: =Y12*AA12 | AD12: =SUM(AC5:AC11) | AE12: =IF(OR($A12="",AD12<MIN_OBS_ROLL),"",(SUMPRODUCT(AC5:AC11,Z5:Z11,AB5:AB11)/AD12-SUMPRODUCT(AC5:AC11,Z5:Z11)/AD12*SUMPRODUCT(AC5:AC11,AB5:AB11)/AD12)*AD12/(AD12-1)) | AF12: =SUM(AA5:AA11) | AG12: =IF(OR($A12="",AF12<MIN_OBS_ROLL),"",SUMPRODUCT(AA5:AA11,(AB5:AB11-SUMPRODUCT(AA5:AA11,AB5:AB11)/AF12)^2)/(AF12-1)) | AH12: =SUM(Y5:Y11) | AI12: =IF(OR($A12="",AH12<MIN_OBS_ROLL),"",SUMPRODUCT(Y5:Y11,Z5:Z11)/AH12) | AJ12: =IF(OR($A12="",AF12<MIN_OBS_ROLL),"",SUMPRODUCT(AA5:AA11,AB5:AB11)/AF12) | AK12: =IF(OR(AE12="",AG12=""),"",AE12/AG12) | AL12: =IF(OR(AI12="",AK12="",AJ12=""),"",AI12-AK12*AJ12) | AM12: =IF(AND(ISNUMBER(W12),ISNUMBER(X12),ISNUMBER(AK12),ISNUMBER(AL12)),W12-(AL12+AK12*X12),"") | AN12: =IF(ISNUMBER(AM12),1,0) | AO12: =IF(AN12=1,AM12,0) | AP12: =IF(SUM(AN10:AN12)=3,SUM(AO10:AO12),"") | AQ12: =IF(ISNUMBER(AP12),1,0) | AR12: =IF(AQ12=1,AP12,0) | AS12: =SUM(AQ$5:AQ12) | AT12: =IF(AS12>=MIN_OBS_Z,SUMPRODUCT(AQ$5:AQ12,AR$5:AR12)/AS12,"") | AU12: =IF(AS12>=MIN_OBS_Z,SQRT(SUMPRODUCT(AQ$5:AQ12,(AR$5:AR12-AT12)^2)/(AS12-1)),"") | AV12: =IF(AND(AQ12=1,ISNUMBER(AT12)),MAX(-Z_CLIP,MIN(Z_CLIP,(AR12-AT12)/AU12)),"") | AW12: =IF(ISNUMBER(AV12),-AV12,"") | AX12: =IF(ISNUMBER(AW12),1+AMPLITUD*TANH(AW12),"") | AY12: =IF($A12="","",IF(COUNT(AX10:AX12)>0,AVERAGE(AX10:AX12),"")) | AZ12: =IF(ISNUMBER(AY12),AY12-1,"") | BA12: =IF(AND(ISNUMBER(AZ11),ISNUMBER(W12)),AZ11*W_BANCOS*W12,"") | BB12: =IF(AND(ISNUMBER(AZ11),ISNUMBER(AZ10)),ABS(AZ11-AZ10)*W_BANCOS*COSTO,0) | BC12: =IF(ISNUMBER(BA12),BA12-BB12,"") | BD12: =IF(ISNUMBER(BC12),IF(A12<=FECHA_ERA,"A","B"),"") | BE12: =IF(BD12="A",BC12,"") | BF12: =IF(BD12="B",BC12,"") | BG12: =IF(AND(ISNUMBER(BC12),ISNUMBER(A12)),IF(A12>=INICIO_VIVO,1,0),0) | BH12: =IF(BG12=1,BC12,"") | BI12: =IF(ISNUMBER(AY12),ROW(),0) | BJ12: =IF(ISNUMBER(BC12),SUM(BC$5:BC12)*10000,NA()) | BK12: =IF(BG12=1,SUM(BH$5:BH12)*10000,NA()) | BL12: =IF(ISNUMBER(AY12),AY12,NA())
A13: =IF(Datos!A13="","",Datos!A13) | B13: =IF(OR($A13="",NOT(ISNUMBER(Datos!B13)),NOT(ISNUMBER(Datos!B12))),"",Datos!B13/Datos!B12-1) | C13: =IF(OR($A13="",NOT(ISNUMBER(Datos!C13)),NOT(ISNUMBER(Datos!C12))),"",Datos!C13/Datos!C12-1) | D13: =IF(OR($A13="",NOT(ISNUMBER(Datos!D13)),NOT(ISNUMBER(Datos!D12))),"",Datos!D13/Datos!D12-1) | E13: =IF(OR($A13="",NOT(ISNUMBER(Datos!E13)),NOT(ISNUMBER(Datos!E12))),"",Datos!E13/Datos!E12-1) | F13: =IF($A13="","",COUNT(B13:E13)) | G13: =IF($A13="","",IF(F13>=MIN_BANCOS,AVERAGE(B13:E13),"")) | H13: =IF(OR($A13="",NOT(ISNUMBER(Datos!F13)),NOT(ISNUMBER(Datos!F12))),"",Datos!F13/Datos!F12-1) | I13: =IF($A13="","",IF(ISNUMBER(Datos!G13),Datos!G13,I12)) | J13: =IF($A13="","",IF(ISNUMBER(I12),LN(1+I12/100/12),0)) | K13: =IF(ISNUMBER(G13),LN(1+G13)-J13,"") | L13: =IF(ISNUMBER(H13),LN(1+H13)-J13,"") | M13: =IF(ISNUMBER(K13),1,0) | N13: =IF(M13=1,K13,0) | O13: =IF(ISNUMBER(L13),1,0) | P13: =IF(O13=1,L13,0) | Q13: =M13*O13 | R13: =SUM(Q5:Q12) | S13: =IF(OR($A13="",R13<MIN_OBS_ROLL),"",(SUMPRODUCT(Q5:Q12,N5:N12,P5:P12)/R13-SUMPRODUCT(Q5:Q12,N5:N12)/R13*SUMPRODUCT(Q5:Q12,P5:P12)/R13)*R13/(R13-1)) | T13: =SUM(O5:O12) | U13: =IF(OR($A13="",T13<MIN_OBS_ROLL),"",SUMPRODUCT(O5:O12,(P5:P12-SUMPRODUCT(O5:O12,P5:P12)/T13)^2)/(T13-1)) | V13: =IF(OR(S13="",U13=""),"",S13/U13) | W13: =IF(AND(ISNUMBER(K13),ISNUMBER(L13),ISNUMBER(V13)),K13-V13*L13,"") | X13: =IF(OR($A13="",NOT(ISNUMBER(Datos!H13)),NOT(ISNUMBER(Datos!H12))),"",LN(Datos!H13)-LN(Datos!H12)) | Y13: =IF(ISNUMBER(W13),1,0) | Z13: =IF(Y13=1,W13,0) | AA13: =IF(ISNUMBER(X13),1,0) | AB13: =IF(AA13=1,X13,0) | AC13: =Y13*AA13 | AD13: =SUM(AC5:AC12) | AE13: =IF(OR($A13="",AD13<MIN_OBS_ROLL),"",(SUMPRODUCT(AC5:AC12,Z5:Z12,AB5:AB12)/AD13-SUMPRODUCT(AC5:AC12,Z5:Z12)/AD13*SUMPRODUCT(AC5:AC12,AB5:AB12)/AD13)*AD13/(AD13-1)) | AF13: =SUM(AA5:AA12) | AG13: =IF(OR($A13="",AF13<MIN_OBS_ROLL),"",SUMPRODUCT(AA5:AA12,(AB5:AB12-SUMPRODUCT(AA5:AA12,AB5:AB12)/AF13)^2)/(AF13-1)) | AH13: =SUM(Y5:Y12) | AI13: =IF(OR($A13="",AH13<MIN_OBS_ROLL),"",SUMPRODUCT(Y5:Y12,Z5:Z12)/AH13) | AJ13: =IF(OR($A13="",AF13<MIN_OBS_ROLL),"",SUMPRODUCT(AA5:AA12,AB5:AB12)/AF13) | AK13: =IF(OR(AE13="",AG13=""),"",AE13/AG13) | AL13: =IF(OR(AI13="",AK13="",AJ13=""),"",AI13-AK13*AJ13) | AM13: =IF(AND(ISNUMBER(W13),ISNUMBER(X13),ISNUMBER(AK13),ISNUMBER(AL13)),W13-(AL13+AK13*X13),"") | AN13: =IF(ISNUMBER(AM13),1,0) | AO13: =IF(AN13=1,AM13,0) | AP13: =IF(SUM(AN11:AN13)=3,SUM(AO11:AO13),"") | AQ13: =IF(ISNUMBER(AP13),1,0) | AR13: =IF(AQ13=1,AP13,0) | AS13: =SUM(AQ$5:AQ13) | AT13: =IF(AS13>=MIN_OBS_Z,SUMPRODUCT(AQ$5:AQ13,AR$5:AR13)/AS13,"") | AU13: =IF(AS13>=MIN_OBS_Z,SQRT(SUMPRODUCT(AQ$5:AQ13,(AR$5:AR13-AT13)^2)/(AS13-1)),"") | AV13: =IF(AND(AQ13=1,ISNUMBER(AT13)),MAX(-Z_CLIP,MIN(Z_CLIP,(AR13-AT13)/AU13)),"") | AW13: =IF(ISNUMBER(AV13),-AV13,"") | AX13: =IF(ISNUMBER(AW13),1+AMPLITUD*TANH(AW13),"") | AY13: =IF($A13="","",IF(COUNT(AX11:AX13)>0,AVERAGE(AX11:AX13),"")) | AZ13: =IF(ISNUMBER(AY13),AY13-1,"") | BA13: =IF(AND(ISNUMBER(AZ12),ISNUMBER(W13)),AZ12*W_BANCOS*W13,"") | BB13: =IF(AND(ISNUMBER(AZ12),ISNUMBER(AZ11)),ABS(AZ12-AZ11)*W_BANCOS*COSTO,0) | BC13: =IF(ISNUMBER(BA13),BA13-BB13,"") | BD13: =IF(ISNUMBER(BC13),IF(A13<=FECHA_ERA,"A","B"),"") | BE13: =IF(BD13="A",BC13,"") | BF13: =IF(BD13="B",BC13,"") | BG13: =IF(AND(ISNUMBER(BC13),ISNUMBER(A13)),IF(A13>=INICIO_VIVO,1,0),0) | BH13: =IF(BG13=1,BC13,"") | BI13: =IF(ISNUMBER(AY13),ROW(),0) | BJ13: =IF(ISNUMBER(BC13),SUM(BC$5:BC13)*10000,NA()) | BK13: =IF(BG13=1,SUM(BH$5:BH13)*10000,NA()) | BL13: =IF(ISNUMBER(AY13),AY13,NA())
A14: =IF(Datos!A14="","",Datos!A14) | B14: =IF(OR($A14="",NOT(ISNUMBER(Datos!B14)),NOT(ISNUMBER(Datos!B13))),"",Datos!B14/Datos!B13-1) | C14: =IF(OR($A14="",NOT(ISNUMBER(Datos!C14)),NOT(ISNUMBER(Datos!C13))),"",Datos!C14/Datos!C13-1) | D14: =IF(OR($A14="",NOT(ISNUMBER(Datos!D14)),NOT(ISNUMBER(Datos!D13))),"",Datos!D14/Datos!D13-1) | E14: =IF(OR($A14="",NOT(ISNUMBER(Datos!E14)),NOT(ISNUMBER(Datos!E13))),"",Datos!E14/Datos!E13-1) | F14: =IF($A14="","",COUNT(B14:E14)) | G14: =IF($A14="","",IF(F14>=MIN_BANCOS,AVERAGE(B14:E14),"")) | H14: =IF(OR($A14="",NOT(ISNUMBER(Datos!F14)),NOT(ISNUMBER(Datos!F13))),"",Datos!F14/Datos!F13-1) | I14: =IF($A14="","",IF(ISNUMBER(Datos!G14),Datos!G14,I13)) | J14: =IF($A14="","",IF(ISNUMBER(I13),LN(1+I13/100/12),0)) | K14: =IF(ISNUMBER(G14),LN(1+G14)-J14,"") | L14: =IF(ISNUMBER(H14),LN(1+H14)-J14,"") | M14: =IF(ISNUMBER(K14),1,0) | N14: =IF(M14=1,K14,0) | O14: =IF(ISNUMBER(L14),1,0) | P14: =IF(O14=1,L14,0) | Q14: =M14*O14 | R14: =SUM(Q5:Q13) | S14: =IF(OR($A14="",R14<MIN_OBS_ROLL),"",(SUMPRODUCT(Q5:Q13,N5:N13,P5:P13)/R14-SUMPRODUCT(Q5:Q13,N5:N13)/R14*SUMPRODUCT(Q5:Q13,P5:P13)/R14)*R14/(R14-1)) | T14: =SUM(O5:O13) | U14: =IF(OR($A14="",T14<MIN_OBS_ROLL),"",SUMPRODUCT(O5:O13,(P5:P13-SUMPRODUCT(O5:O13,P5:P13)/T14)^2)/(T14-1)) | V14: =IF(OR(S14="",U14=""),"",S14/U14) | W14: =IF(AND(ISNUMBER(K14),ISNUMBER(L14),ISNUMBER(V14)),K14-V14*L14,"") | X14: =IF(OR($A14="",NOT(ISNUMBER(Datos!H14)),NOT(ISNUMBER(Datos!H13))),"",LN(Datos!H14)-LN(Datos!H13)) | Y14: =IF(ISNUMBER(W14),1,0) | Z14: =IF(Y14=1,W14,0) | AA14: =IF(ISNUMBER(X14),1,0) | AB14: =IF(AA14=1,X14,0) | AC14: =Y14*AA14 | AD14: =SUM(AC5:AC13) | AE14: =IF(OR($A14="",AD14<MIN_OBS_ROLL),"",(SUMPRODUCT(AC5:AC13,Z5:Z13,AB5:AB13)/AD14-SUMPRODUCT(AC5:AC13,Z5:Z13)/AD14*SUMPRODUCT(AC5:AC13,AB5:AB13)/AD14)*AD14/(AD14-1)) | AF14: =SUM(AA5:AA13) | AG14: =IF(OR($A14="",AF14<MIN_OBS_ROLL),"",SUMPRODUCT(AA5:AA13,(AB5:AB13-SUMPRODUCT(AA5:AA13,AB5:AB13)/AF14)^2)/(AF14-1)) | AH14: =SUM(Y5:Y13) | AI14: =IF(OR($A14="",AH14<MIN_OBS_ROLL),"",SUMPRODUCT(Y5:Y13,Z5:Z13)/AH14) | AJ14: =IF(OR($A14="",AF14<MIN_OBS_ROLL),"",SUMPRODUCT(AA5:AA13,AB5:AB13)/AF14) | AK14: =IF(OR(AE14="",AG14=""),"",AE14/AG14) | AL14: =IF(OR(AI14="",AK14="",AJ14=""),"",AI14-AK14*AJ14) | AM14: =IF(AND(ISNUMBER(W14),ISNUMBER(X14),ISNUMBER(AK14),ISNUMBER(AL14)),W14-(AL14+AK14*X14),"") | AN14: =IF(ISNUMBER(AM14),1,0) | AO14: =IF(AN14=1,AM14,0) | AP14: =IF(SUM(AN12:AN14)=3,SUM(AO12:AO14),"") | AQ14: =IF(ISNUMBER(AP14),1,0) | AR14: =IF(AQ14=1,AP14,0) | AS14: =SUM(AQ$5:AQ14) | AT14: =IF(AS14>=MIN_OBS_Z,SUMPRODUCT(AQ$5:AQ14,AR$5:AR14)/AS14,"") | AU14: =IF(AS14>=MIN_OBS_Z,SQRT(SUMPRODUCT(AQ$5:AQ14,(AR$5:AR14-AT14)^2)/(AS14-1)),"") | AV14: =IF(AND(AQ14=1,ISNUMBER(AT14)),MAX(-Z_CLIP,MIN(Z_CLIP,(AR14-AT14)/AU14)),"") | AW14: =IF(ISNUMBER(AV14),-AV14,"") | AX14: =IF(ISNUMBER(AW14),1+AMPLITUD*TANH(AW14),"") | AY14: =IF($A14="","",IF(COUNT(AX12:AX14)>0,AVERAGE(AX12:AX14),"")) | AZ14: =IF(ISNUMBER(AY14),AY14-1,"") | BA14: =IF(AND(ISNUMBER(AZ13),ISNUMBER(W14)),AZ13*W_BANCOS*W14,"") | BB14: =IF(AND(ISNUMBER(AZ13),ISNUMBER(AZ12)),ABS(AZ13-AZ12)*W_BANCOS*COSTO,0) | BC14: =IF(ISNUMBER(BA14),BA14-BB14,"") | BD14: =IF(ISNUMBER(BC14),IF(A14<=FECHA_ERA,"A","B"),"") | BE14: =IF(BD14="A",BC14,"") | BF14: =IF(BD14="B",BC14,"") | BG14: =IF(AND(ISNUMBER(BC14),ISNUMBER(A14)),IF(A14>=INICIO_VIVO,1,0),0) | BH14: =IF(BG14=1,BC14,"") | BI14: =IF(ISNUMBER(AY14),ROW(),0) | BJ14: =IF(ISNUMBER(BC14),SUM(BC$5:BC14)*10000,NA()) | BK14: =IF(BG14=1,SUM(BH$5:BH14)*10000,NA()) | BL14: =IF(ISNUMBER(AY14),AY14,NA())
A15: =IF(Datos!A15="","",Datos!A15) | B15: =IF(OR($A15="",NOT(ISNUMBER(Datos!B15)),NOT(ISNUMBER(Datos!B14))),"",Datos!B15/Datos!B14-1) | C15: =IF(OR($A15="",NOT(ISNUMBER(Datos!C15)),NOT(ISNUMBER(Datos!C14))),"",Datos!C15/Datos!C14-1) | D15: =IF(OR($A15="",NOT(ISNUMBER(Datos!D15)),NOT(ISNUMBER(Datos!D14))),"",Datos!D15/Datos!D14-1) | E15: =IF(OR($A15="",NOT(ISNUMBER(Datos!E15)),NOT(ISNUMBER(Datos!E14))),"",Datos!E15/Datos!E14-1) | F15: =IF($A15="","",COUNT(B15:E15)) | G15: =IF($A15="","",IF(F15>=MIN_BANCOS,AVERAGE(B15:E15),"")) | H15: =IF(OR($A15="",NOT(ISNUMBER(Datos!F15)),NOT(ISNUMBER(Datos!F14))),"",Datos!F15/Datos!F14-1) | I15: =IF($A15="","",IF(ISNUMBER(Datos!G15),Datos!G15,I14)) | J15: =IF($A15="","",IF(ISNUMBER(I14),LN(1+I14/100/12),0)) | K15: =IF(ISNUMBER(G15),LN(1+G15)-J15,"") | L15: =IF(ISNUMBER(H15),LN(1+H15)-J15,"") | M15: =IF(ISNUMBER(K15),1,0) | N15: =IF(M15=1,K15,0) | O15: =IF(ISNUMBER(L15),1,0) | P15: =IF(O15=1,L15,0) | Q15: =M15*O15 | R15: =SUM(Q5:Q14) | S15: =IF(OR($A15="",R15<MIN_OBS_ROLL),"",(SUMPRODUCT(Q5:Q14,N5:N14,P5:P14)/R15-SUMPRODUCT(Q5:Q14,N5:N14)/R15*SUMPRODUCT(Q5:Q14,P5:P14)/R15)*R15/(R15-1)) | T15: =SUM(O5:O14) | U15: =IF(OR($A15="",T15<MIN_OBS_ROLL),"",SUMPRODUCT(O5:O14,(P5:P14-SUMPRODUCT(O5:O14,P5:P14)/T15)^2)/(T15-1)) | V15: =IF(OR(S15="",U15=""),"",S15/U15) | W15: =IF(AND(ISNUMBER(K15),ISNUMBER(L15),ISNUMBER(V15)),K15-V15*L15,"") | X15: =IF(OR($A15="",NOT(ISNUMBER(Datos!H15)),NOT(ISNUMBER(Datos!H14))),"",LN(Datos!H15)-LN(Datos!H14)) | Y15: =IF(ISNUMBER(W15),1,0) | Z15: =IF(Y15=1,W15,0) | AA15: =IF(ISNUMBER(X15),1,0) | AB15: =IF(AA15=1,X15,0) | AC15: =Y15*AA15 | AD15: =SUM(AC5:AC14) | AE15: =IF(OR($A15="",AD15<MIN_OBS_ROLL),"",(SUMPRODUCT(AC5:AC14,Z5:Z14,AB5:AB14)/AD15-SUMPRODUCT(AC5:AC14,Z5:Z14)/AD15*SUMPRODUCT(AC5:AC14,AB5:AB14)/AD15)*AD15/(AD15-1)) | AF15: =SUM(AA5:AA14) | AG15: =IF(OR($A15="",AF15<MIN_OBS_ROLL),"",SUMPRODUCT(AA5:AA14,(AB5:AB14-SUMPRODUCT(AA5:AA14,AB5:AB14)/AF15)^2)/(AF15-1)) | AH15: =SUM(Y5:Y14) | AI15: =IF(OR($A15="",AH15<MIN_OBS_ROLL),"",SUMPRODUCT(Y5:Y14,Z5:Z14)/AH15) | AJ15: =IF(OR($A15="",AF15<MIN_OBS_ROLL),"",SUMPRODUCT(AA5:AA14,AB5:AB14)/AF15) | AK15: =IF(OR(AE15="",AG15=""),"",AE15/AG15) | AL15: =IF(OR(AI15="",AK15="",AJ15=""),"",AI15-AK15*AJ15) | AM15: =IF(AND(ISNUMBER(W15),ISNUMBER(X15),ISNUMBER(AK15),ISNUMBER(AL15)),W15-(AL15+AK15*X15),"") | AN15: =IF(ISNUMBER(AM15),1,0) | AO15: =IF(AN15=1,AM15,0) | AP15: =IF(SUM(AN13:AN15)=3,SUM(AO13:AO15),"") | AQ15: =IF(ISNUMBER(AP15),1,0) | AR15: =IF(AQ15=1,AP15,0) | AS15: =SUM(AQ$5:AQ15) | AT15: =IF(AS15>=MIN_OBS_Z,SUMPRODUCT(AQ$5:AQ15,AR$5:AR15)/AS15,"") | AU15: =IF(AS15>=MIN_OBS_Z,SQRT(SUMPRODUCT(AQ$5:AQ15,(AR$5:AR15-AT15)^2)/(AS15-1)),"") | AV15: =IF(AND(AQ15=1,ISNUMBER(AT15)),MAX(-Z_CLIP,MIN(Z_CLIP,(AR15-AT15)/AU15)),"") | AW15: =IF(ISNUMBER(AV15),-AV15,"") | AX15: =IF(ISNUMBER(AW15),1+AMPLITUD*TANH(AW15),"") | AY15: =IF($A15="","",IF(COUNT(AX13:AX15)>0,AVERAGE(AX13:AX15),"")) | AZ15: =IF(ISNUMBER(AY15),AY15-1,"") | BA15: =IF(AND(ISNUMBER(AZ14),ISNUMBER(W15)),AZ14*W_BANCOS*W15,"") | BB15: =IF(AND(ISNUMBER(AZ14),ISNUMBER(AZ13)),ABS(AZ14-AZ13)*W_BANCOS*COSTO,0) | BC15: =IF(ISNUMBER(BA15),BA15-BB15,"") | BD15: =IF(ISNUMBER(BC15),IF(A15<=FECHA_ERA,"A","B"),"") | BE15: =IF(BD15="A",BC15,"") | BF15: =IF(BD15="B",BC15,"") | BG15: =IF(AND(ISNUMBER(BC15),ISNUMBER(A15)),IF(A15>=INICIO_VIVO,1,0),0) | BH15: =IF(BG15=1,BC15,"") | BI15: =IF(ISNUMBER(AY15),ROW(),0) | BJ15: =IF(ISNUMBER(BC15),SUM(BC$5:BC15)*10000,NA()) | BK15: =IF(BG15=1,SUM(BH$5:BH15)*10000,NA()) | BL15: =IF(ISNUMBER(AY15),AY15,NA())
A16: =IF(Datos!A16="","",Datos!A16) | B16: =IF(OR($A16="",NOT(ISNUMBER(Datos!B16)),NOT(ISNUMBER(Datos!B15))),"",Datos!B16/Datos!B15-1) | C16: =IF(OR($A16="",NOT(ISNUMBER(Datos!C16)),NOT(ISNUMBER(Datos!C15))),"",Datos!C16/Datos!C15-1) | D16: =IF(OR($A16="",NOT(ISNUMBER(Datos!D16)),NOT(ISNUMBER(Datos!D15))),"",Datos!D16/Datos!D15-1) | E16: =IF(OR($A16="",NOT(ISNUMBER(Datos!E16)),NOT(ISNUMBER(Datos!E15))),"",Datos!E16/Datos!E15-1) | F16: =IF($A16="","",COUNT(B16:E16)) | G16: =IF($A16="","",IF(F16>=MIN_BANCOS,AVERAGE(B16:E16),"")) | H16: =IF(OR($A16="",NOT(ISNUMBER(Datos!F16)),NOT(ISNUMBER(Datos!F15))),"",Datos!F16/Datos!F15-1) | I16: =IF($A16="","",IF(ISNUMBER(Datos!G16),Datos!G16,I15)) | J16: =IF($A16="","",IF(ISNUMBER(I15),LN(1+I15/100/12),0)) | K16: =IF(ISNUMBER(G16),LN(1+G16)-J16,"") | L16: =IF(ISNUMBER(H16),LN(1+H16)-J16,"") | M16: =IF(ISNUMBER(K16),1,0) | N16: =IF(M16=1,K16,0) | O16: =IF(ISNUMBER(L16),1,0) | P16: =IF(O16=1,L16,0) | Q16: =M16*O16 | R16: =SUM(Q5:Q15) | S16: =IF(OR($A16="",R16<MIN_OBS_ROLL),"",(SUMPRODUCT(Q5:Q15,N5:N15,P5:P15)/R16-SUMPRODUCT(Q5:Q15,N5:N15)/R16*SUMPRODUCT(Q5:Q15,P5:P15)/R16)*R16/(R16-1)) | T16: =SUM(O5:O15) | U16: =IF(OR($A16="",T16<MIN_OBS_ROLL),"",SUMPRODUCT(O5:O15,(P5:P15-SUMPRODUCT(O5:O15,P5:P15)/T16)^2)/(T16-1)) | V16: =IF(OR(S16="",U16=""),"",S16/U16) | W16: =IF(AND(ISNUMBER(K16),ISNUMBER(L16),ISNUMBER(V16)),K16-V16*L16,"") | X16: =IF(OR($A16="",NOT(ISNUMBER(Datos!H16)),NOT(ISNUMBER(Datos!H15))),"",LN(Datos!H16)-LN(Datos!H15)) | Y16: =IF(ISNUMBER(W16),1,0) | Z16: =IF(Y16=1,W16,0) | AA16: =IF(ISNUMBER(X16),1,0) | AB16: =IF(AA16=1,X16,0) | AC16: =Y16*AA16 | AD16: =SUM(AC5:AC15) | AE16: =IF(OR($A16="",AD16<MIN_OBS_ROLL),"",(SUMPRODUCT(AC5:AC15,Z5:Z15,AB5:AB15)/AD16-SUMPRODUCT(AC5:AC15,Z5:Z15)/AD16*SUMPRODUCT(AC5:AC15,AB5:AB15)/AD16)*AD16/(AD16-1)) | AF16: =SUM(AA5:AA15) | AG16: =IF(OR($A16="",AF16<MIN_OBS_ROLL),"",SUMPRODUCT(AA5:AA15,(AB5:AB15-SUMPRODUCT(AA5:AA15,AB5:AB15)/AF16)^2)/(AF16-1)) | AH16: =SUM(Y5:Y15) | AI16: =IF(OR($A16="",AH16<MIN_OBS_ROLL),"",SUMPRODUCT(Y5:Y15,Z5:Z15)/AH16) | AJ16: =IF(OR($A16="",AF16<MIN_OBS_ROLL),"",SUMPRODUCT(AA5:AA15,AB5:AB15)/AF16) | AK16: =IF(OR(AE16="",AG16=""),"",AE16/AG16) | AL16: =IF(OR(AI16="",AK16="",AJ16=""),"",AI16-AK16*AJ16) | AM16: =IF(AND(ISNUMBER(W16),ISNUMBER(X16),ISNUMBER(AK16),ISNUMBER(AL16)),W16-(AL16+AK16*X16),"") | AN16: =IF(ISNUMBER(AM16),1,0) | AO16: =IF(AN16=1,AM16,0) | AP16: =IF(SUM(AN14:AN16)=3,SUM(AO14:AO16),"") | AQ16: =IF(ISNUMBER(AP16),1,0) | AR16: =IF(AQ16=1,AP16,0) | AS16: =SUM(AQ$5:AQ16) | AT16: =IF(AS16>=MIN_OBS_Z,SUMPRODUCT(AQ$5:AQ16,AR$5:AR16)/AS16,"") | AU16: =IF(AS16>=MIN_OBS_Z,SQRT(SUMPRODUCT(AQ$5:AQ16,(AR$5:AR16-AT16)^2)/(AS16-1)),"") | AV16: =IF(AND(AQ16=1,ISNUMBER(AT16)),MAX(-Z_CLIP,MIN(Z_CLIP,(AR16-AT16)/AU16)),"") | AW16: =IF(ISNUMBER(AV16),-AV16,"") | AX16: =IF(ISNUMBER(AW16),1+AMPLITUD*TANH(AW16),"") | AY16: =IF($A16="","",IF(COUNT(AX14:AX16)>0,AVERAGE(AX14:AX16),"")) | AZ16: =IF(ISNUMBER(AY16),AY16-1,"") | BA16: =IF(AND(ISNUMBER(AZ15),ISNUMBER(W16)),AZ15*W_BANCOS*W16,"") | BB16: =IF(AND(ISNUMBER(AZ15),ISNUMBER(AZ14)),ABS(AZ15-AZ14)*W_BANCOS*COSTO,0) | BC16: =IF(ISNUMBER(BA16),BA16-BB16,"") | BD16: =IF(ISNUMBER(BC16),IF(A16<=FECHA_ERA,"A","B"),"") | BE16: =IF(BD16="A",BC16,"") | BF16: =IF(BD16="B",BC16,"") | BG16: =IF(AND(ISNUMBER(BC16),ISNUMBER(A16)),IF(A16>=INICIO_VIVO,1,0),0) | BH16: =IF(BG16=1,BC16,"") | BI16: =IF(ISNUMBER(AY16),ROW(),0) | BJ16: =IF(ISNUMBER(BC16),SUM(BC$5:BC16)*10000,NA()) | BK16: =IF(BG16=1,SUM(BH$5:BH16)*10000,NA()) | BL16: =IF(ISNUMBER(AY16),AY16,NA())
A17: =IF(Datos!A17="","",Datos!A17) | B17: =IF(OR($A17="",NOT(ISNUMBER(Datos!B17)),NOT(ISNUMBER(Datos!B16))),"",Datos!B17/Datos!B16-1) | C17: =IF(OR($A17="",NOT(ISNUMBER(Datos!C17)),NOT(ISNUMBER(Datos!C16))),"",Datos!C17/Datos!C16-1) | D17: =IF(OR($A17="",NOT(ISNUMBER(Datos!D17)),NOT(ISNUMBER(Datos!D16))),"",Datos!D17/Datos!D16-1) | E17: =IF(OR($A17="",NOT(ISNUMBER(Datos!E17)),NOT(ISNUMBER(Datos!E16))),"",Datos!E17/Datos!E16-1) | F17: =IF($A17="","",COUNT(B17:E17)) | G17: =IF($A17="","",IF(F17>=MIN_BANCOS,AVERAGE(B17:E17),"")) | H17: =IF(OR($A17="",NOT(ISNUMBER(Datos!F17)),NOT(ISNUMBER(Datos!F16))),"",Datos!F17/Datos!F16-1) | I17: =IF($A17="","",IF(ISNUMBER(Datos!G17),Datos!G17,I16)) | J17: =IF($A17="","",IF(ISNUMBER(I16),LN(1+I16/100/12),0)) | K17: =IF(ISNUMBER(G17),LN(1+G17)-J17,"") | L17: =IF(ISNUMBER(H17),LN(1+H17)-J17,"") | M17: =IF(ISNUMBER(K17),1,0) | N17: =IF(M17=1,K17,0) | O17: =IF(ISNUMBER(L17),1,0) | P17: =IF(O17=1,L17,0) | Q17: =M17*O17 | R17: =SUM(Q5:Q16) | S17: =IF(OR($A17="",R17<MIN_OBS_ROLL),"",(SUMPRODUCT(Q5:Q16,N5:N16,P5:P16)/R17-SUMPRODUCT(Q5:Q16,N5:N16)/R17*SUMPRODUCT(Q5:Q16,P5:P16)/R17)*R17/(R17-1)) | T17: =SUM(O5:O16) | U17: =IF(OR($A17="",T17<MIN_OBS_ROLL),"",SUMPRODUCT(O5:O16,(P5:P16-SUMPRODUCT(O5:O16,P5:P16)/T17)^2)/(T17-1)) | V17: =IF(OR(S17="",U17=""),"",S17/U17) | W17: =IF(AND(ISNUMBER(K17),ISNUMBER(L17),ISNUMBER(V17)),K17-V17*L17,"") | X17: =IF(OR($A17="",NOT(ISNUMBER(Datos!H17)),NOT(ISNUMBER(Datos!H16))),"",LN(Datos!H17)-LN(Datos!H16)) | Y17: =IF(ISNUMBER(W17),1,0) | Z17: =IF(Y17=1,W17,0) | AA17: =IF(ISNUMBER(X17),1,0) | AB17: =IF(AA17=1,X17,0) | AC17: =Y17*AA17 | AD17: =SUM(AC5:AC16) | AE17: =IF(OR($A17="",AD17<MIN_OBS_ROLL),"",(SUMPRODUCT(AC5:AC16,Z5:Z16,AB5:AB16)/AD17-SUMPRODUCT(AC5:AC16,Z5:Z16)/AD17*SUMPRODUCT(AC5:AC16,AB5:AB16)/AD17)*AD17/(AD17-1)) | AF17: =SUM(AA5:AA16) | AG17: =IF(OR($A17="",AF17<MIN_OBS_ROLL),"",SUMPRODUCT(AA5:AA16,(AB5:AB16-SUMPRODUCT(AA5:AA16,AB5:AB16)/AF17)^2)/(AF17-1)) | AH17: =SUM(Y5:Y16) | AI17: =IF(OR($A17="",AH17<MIN_OBS_ROLL),"",SUMPRODUCT(Y5:Y16,Z5:Z16)/AH17) | AJ17: =IF(OR($A17="",AF17<MIN_OBS_ROLL),"",SUMPRODUCT(AA5:AA16,AB5:AB16)/AF17) | AK17: =IF(OR(AE17="",AG17=""),"",AE17/AG17) | AL17: =IF(OR(AI17="",AK17="",AJ17=""),"",AI17-AK17*AJ17) | AM17: =IF(AND(ISNUMBER(W17),ISNUMBER(X17),ISNUMBER(AK17),ISNUMBER(AL17)),W17-(AL17+AK17*X17),"") | AN17: =IF(ISNUMBER(AM17),1,0) | AO17: =IF(AN17=1,AM17,0) | AP17: =IF(SUM(AN15:AN17)=3,SUM(AO15:AO17),"") | AQ17: =IF(ISNUMBER(AP17),1,0) | AR17: =IF(AQ17=1,AP17,0) | AS17: =SUM(AQ$5:AQ17) | AT17: =IF(AS17>=MIN_OBS_Z,SUMPRODUCT(AQ$5:AQ17,AR$5:AR17)/AS17,"") | AU17: =IF(AS17>=MIN_OBS_Z,SQRT(SUMPRODUCT(AQ$5:AQ17,(AR$5:AR17-AT17)^2)/(AS17-1)),"") | AV17: =IF(AND(AQ17=1,ISNUMBER(AT17)),MAX(-Z_CLIP,MIN(Z_CLIP,(AR17-AT17)/AU17)),"") | AW17: =IF(ISNUMBER(AV17),-AV17,"") | AX17: =IF(ISNUMBER(AW17),1+AMPLITUD*TANH(AW17),"") | AY17: =IF($A17="","",IF(COUNT(AX15:AX17)>0,AVERAGE(AX15:AX17),"")) | AZ17: =IF(ISNUMBER(AY17),AY17-1,"") | BA17: =IF(AND(ISNUMBER(AZ16),ISNUMBER(W17)),AZ16*W_BANCOS*W17,"") | BB17: =IF(AND(ISNUMBER(AZ16),ISNUMBER(AZ15)),ABS(AZ16-AZ15)*W_BANCOS*COSTO,0) | BC17: =IF(ISNUMBER(BA17),BA17-BB17,"") | BD17: =IF(ISNUMBER(BC17),IF(A17<=FECHA_ERA,"A","B"),"") | BE17: =IF(BD17="A",BC17,"") | BF17: =IF(BD17="B",BC17,"") | BG17: =IF(AND(ISNUMBER(BC17),ISNUMBER(A17)),IF(A17>=INICIO_VIVO,1,0),0) | BH17: =IF(BG17=1,BC17,"") | BI17: =IF(ISNUMBER(AY17),ROW(),0) | BJ17: =IF(ISNUMBER(BC17),SUM(BC$5:BC17)*10000,NA()) | BK17: =IF(BG17=1,SUM(BH$5:BH17)*10000,NA()) | BL17: =IF(ISNUMBER(AY17),AY17,NA())
A18: =IF(Datos!A18="","",Datos!A18) | B18: =IF(OR($A18="",NOT(ISNUMBER(Datos!B18)),NOT(ISNUMBER(Datos!B17))),"",Datos!B18/Datos!B17-1) | C18: =IF(OR($A18="",NOT(ISNUMBER(Datos!C18)),NOT(ISNUMBER(Datos!C17))),"",Datos!C18/Datos!C17-1) | D18: =IF(OR($A18="",NOT(ISNUMBER(Datos!D18)),NOT(ISNUMBER(Datos!D17))),"",Datos!D18/Datos!D17-1) | E18: =IF(OR($A18="",NOT(ISNUMBER(Datos!E18)),NOT(ISNUMBER(Datos!E17))),"",Datos!E18/Datos!E17-1) | F18: =IF($A18="","",COUNT(B18:E18)) | G18: =IF($A18="","",IF(F18>=MIN_BANCOS,AVERAGE(B18:E18),"")) | H18: =IF(OR($A18="",NOT(ISNUMBER(Datos!F18)),NOT(ISNUMBER(Datos!F17))),"",Datos!F18/Datos!F17-1) | I18: =IF($A18="","",IF(ISNUMBER(Datos!G18),Datos!G18,I17)) | J18: =IF($A18="","",IF(ISNUMBER(I17),LN(1+I17/100/12),0)) | K18: =IF(ISNUMBER(G18),LN(1+G18)-J18,"") | L18: =IF(ISNUMBER(H18),LN(1+H18)-J18,"") | M18: =IF(ISNUMBER(K18),1,0) | N18: =IF(M18=1,K18,0) | O18: =IF(ISNUMBER(L18),1,0) | P18: =IF(O18=1,L18,0) | Q18: =M18*O18 | R18: =SUM(Q5:Q17) | S18: =IF(OR($A18="",R18<MIN_OBS_ROLL),"",(SUMPRODUCT(Q5:Q17,N5:N17,P5:P17)/R18-SUMPRODUCT(Q5:Q17,N5:N17)/R18*SUMPRODUCT(Q5:Q17,P5:P17)/R18)*R18/(R18-1)) | T18: =SUM(O5:O17) | U18: =IF(OR($A18="",T18<MIN_OBS_ROLL),"",SUMPRODUCT(O5:O17,(P5:P17-SUMPRODUCT(O5:O17,P5:P17)/T18)^2)/(T18-1)) | V18: =IF(OR(S18="",U18=""),"",S18/U18) | W18: =IF(AND(ISNUMBER(K18),ISNUMBER(L18),ISNUMBER(V18)),K18-V18*L18,"") | X18: =IF(OR($A18="",NOT(ISNUMBER(Datos!H18)),NOT(ISNUMBER(Datos!H17))),"",LN(Datos!H18)-LN(Datos!H17)) | Y18: =IF(ISNUMBER(W18),1,0) | Z18: =IF(Y18=1,W18,0) | AA18: =IF(ISNUMBER(X18),1,0) | AB18: =IF(AA18=1,X18,0) | AC18: =Y18*AA18 | AD18: =SUM(AC5:AC17) | AE18: =IF(OR($A18="",AD18<MIN_OBS_ROLL),"",(SUMPRODUCT(AC5:AC17,Z5:Z17,AB5:AB17)/AD18-SUMPRODUCT(AC5:AC17,Z5:Z17)/AD18*SUMPRODUCT(AC5:AC17,AB5:AB17)/AD18)*AD18/(AD18-1)) | AF18: =SUM(AA5:AA17) | AG18: =IF(OR($A18="",AF18<MIN_OBS_ROLL),"",SUMPRODUCT(AA5:AA17,(AB5:AB17-SUMPRODUCT(AA5:AA17,AB5:AB17)/AF18)^2)/(AF18-1)) | AH18: =SUM(Y5:Y17) | AI18: =IF(OR($A18="",AH18<MIN_OBS_ROLL),"",SUMPRODUCT(Y5:Y17,Z5:Z17)/AH18) | AJ18: =IF(OR($A18="",AF18<MIN_OBS_ROLL),"",SUMPRODUCT(AA5:AA17,AB5:AB17)/AF18) | AK18: =IF(OR(AE18="",AG18=""),"",AE18/AG18) | AL18: =IF(OR(AI18="",AK18="",AJ18=""),"",AI18-AK18*AJ18) | AM18: =IF(AND(ISNUMBER(W18),ISNUMBER(X18),ISNUMBER(AK18),ISNUMBER(AL18)),W18-(AL18+AK18*X18),"") | AN18: =IF(ISNUMBER(AM18),1,0) | AO18: =IF(AN18=1,AM18,0) | AP18: =IF(SUM(AN16:AN18)=3,SUM(AO16:AO18),"") | AQ18: =IF(ISNUMBER(AP18),1,0) | AR18: =IF(AQ18=1,AP18,0) | AS18: =SUM(AQ$5:AQ18) | AT18: =IF(AS18>=MIN_OBS_Z,SUMPRODUCT(AQ$5:AQ18,AR$5:AR18)/AS18,"") | AU18: =IF(AS18>=MIN_OBS_Z,SQRT(SUMPRODUCT(AQ$5:AQ18,(AR$5:AR18-AT18)^2)/(AS18-1)),"") | AV18: =IF(AND(AQ18=1,ISNUMBER(AT18)),MAX(-Z_CLIP,MIN(Z_CLIP,(AR18-AT18)/AU18)),"") | AW18: =IF(ISNUMBER(AV18),-AV18,"") | AX18: =IF(ISNUMBER(AW18),1+AMPLITUD*TANH(AW18),"") | AY18: =IF($A18="","",IF(COUNT(AX16:AX18)>0,AVERAGE(AX16:AX18),"")) | AZ18: =IF(ISNUMBER(AY18),AY18-1,"") | BA18: =IF(AND(ISNUMBER(AZ17),ISNUMBER(W18)),AZ17*W_BANCOS*W18,"") | BB18: =IF(AND(ISNUMBER(AZ17),ISNUMBER(AZ16)),ABS(AZ17-AZ16)*W_BANCOS*COSTO,0) | BC18: =IF(ISNUMBER(BA18),BA18-BB18,"") | BD18: =IF(ISNUMBER(BC18),IF(A18<=FECHA_ERA,"A","B"),"") | BE18: =IF(BD18="A",BC18,"") | BF18: =IF(BD18="B",BC18,"") | BG18: =IF(AND(ISNUMBER(BC18),ISNUMBER(A18)),IF(A18>=INICIO_VIVO,1,0),0) | BH18: =IF(BG18=1,BC18,"") | BI18: =IF(ISNUMBER(AY18),ROW(),0) | BJ18: =IF(ISNUMBER(BC18),SUM(BC$5:BC18)*10000,NA()) | BK18: =IF(BG18=1,SUM(BH$5:BH18)*10000,NA()) | BL18: =IF(ISNUMBER(AY18),AY18,NA())
A19: =IF(Datos!A19="","",Datos!A19) | B19: =IF(OR($A19="",NOT(ISNUMBER(Datos!B19)),NOT(ISNUMBER(Datos!B18))),"",Datos!B19/Datos!B18-1) | C19: =IF(OR($A19="",NOT(ISNUMBER(Datos!C19)),NOT(ISNUMBER(Datos!C18))),"",Datos!C19/Datos!C18-1) | D19: =IF(OR($A19="",NOT(ISNUMBER(Datos!D19)),NOT(ISNUMBER(Datos!D18))),"",Datos!D19/Datos!D18-1) | E19: =IF(OR($A19="",NOT(ISNUMBER(Datos!E19)),NOT(ISNUMBER(Datos!E18))),"",Datos!E19/Datos!E18-1) | F19: =IF($A19="","",COUNT(B19:E19)) | G19: =IF($A19="","",IF(F19>=MIN_BANCOS,AVERAGE(B19:E19),"")) | H19: =IF(OR($A19="",NOT(ISNUMBER(Datos!F19)),NOT(ISNUMBER(Datos!F18))),"",Datos!F19/Datos!F18-1) | I19: =IF($A19="","",IF(ISNUMBER(Datos!G19),Datos!G19,I18)) | J19: =IF($A19="","",IF(ISNUMBER(I18),LN(1+I18/100/12),0)) | K19: =IF(ISNUMBER(G19),LN(1+G19)-J19,"") | L19: =IF(ISNUMBER(H19),LN(1+H19)-J19,"") | M19: =IF(ISNUMBER(K19),1,0) | N19: =IF(M19=1,K19,0) | O19: =IF(ISNUMBER(L19),1,0) | P19: =IF(O19=1,L19,0) | Q19: =M19*O19 | R19: =SUM(Q5:Q18) | S19: =IF(OR($A19="",R19<MIN_OBS_ROLL),"",(SUMPRODUCT(Q5:Q18,N5:N18,P5:P18)/R19-SUMPRODUCT(Q5:Q18,N5:N18)/R19*SUMPRODUCT(Q5:Q18,P5:P18)/R19)*R19/(R19-1)) | T19: =SUM(O5:O18) | U19: =IF(OR($A19="",T19<MIN_OBS_ROLL),"",SUMPRODUCT(O5:O18,(P5:P18-SUMPRODUCT(O5:O18,P5:P18)/T19)^2)/(T19-1)) | V19: =IF(OR(S19="",U19=""),"",S19/U19) | W19: =IF(AND(ISNUMBER(K19),ISNUMBER(L19),ISNUMBER(V19)),K19-V19*L19,"") | X19: =IF(OR($A19="",NOT(ISNUMBER(Datos!H19)),NOT(ISNUMBER(Datos!H18))),"",LN(Datos!H19)-LN(Datos!H18)) | Y19: =IF(ISNUMBER(W19),1,0) | Z19: =IF(Y19=1,W19,0) | AA19: =IF(ISNUMBER(X19),1,0) | AB19: =IF(AA19=1,X19,0) | AC19: =Y19*AA19 | AD19: =SUM(AC5:AC18) | AE19: =IF(OR($A19="",AD19<MIN_OBS_ROLL),"",(SUMPRODUCT(AC5:AC18,Z5:Z18,AB5:AB18)/AD19-SUMPRODUCT(AC5:AC18,Z5:Z18)/AD19*SUMPRODUCT(AC5:AC18,AB5:AB18)/AD19)*AD19/(AD19-1)) | AF19: =SUM(AA5:AA18) | AG19: =IF(OR($A19="",AF19<MIN_OBS_ROLL),"",SUMPRODUCT(AA5:AA18,(AB5:AB18-SUMPRODUCT(AA5:AA18,AB5:AB18)/AF19)^2)/(AF19-1)) | AH19: =SUM(Y5:Y18) | AI19: =IF(OR($A19="",AH19<MIN_OBS_ROLL),"",SUMPRODUCT(Y5:Y18,Z5:Z18)/AH19) | AJ19: =IF(OR($A19="",AF19<MIN_OBS_ROLL),"",SUMPRODUCT(AA5:AA18,AB5:AB18)/AF19) | AK19: =IF(OR(AE19="",AG19=""),"",AE19/AG19) | AL19: =IF(OR(AI19="",AK19="",AJ19=""),"",AI19-AK19*AJ19) | AM19: =IF(AND(ISNUMBER(W19),ISNUMBER(X19),ISNUMBER(AK19),ISNUMBER(AL19)),W19-(AL19+AK19*X19),"") | AN19: =IF(ISNUMBER(AM19),1,0) | AO19: =IF(AN19=1,AM19,0) | AP19: =IF(SUM(AN17:AN19)=3,SUM(AO17:AO19),"") | AQ19: =IF(ISNUMBER(AP19),1,0) | AR19: =IF(AQ19=1,AP19,0) | AS19: =SUM(AQ$5:AQ19) | AT19: =IF(AS19>=MIN_OBS_Z,SUMPRODUCT(AQ$5:AQ19,AR$5:AR19)/AS19,"") | AU19: =IF(AS19>=MIN_OBS_Z,SQRT(SUMPRODUCT(AQ$5:AQ19,(AR$5:AR19-AT19)^2)/(AS19-1)),"") | AV19: =IF(AND(AQ19=1,ISNUMBER(AT19)),MAX(-Z_CLIP,MIN(Z_CLIP,(AR19-AT19)/AU19)),"") | AW19: =IF(ISNUMBER(AV19),-AV19,"") | AX19: =IF(ISNUMBER(AW19),1+AMPLITUD*TANH(AW19),"") | AY19: =IF($A19="","",IF(COUNT(AX17:AX19)>0,AVERAGE(AX17:AX19),"")) | AZ19: =IF(ISNUMBER(AY19),AY19-1,"") | BA19: =IF(AND(ISNUMBER(AZ18),ISNUMBER(W19)),AZ18*W_BANCOS*W19,"") | BB19: =IF(AND(ISNUMBER(AZ18),ISNUMBER(AZ17)),ABS(AZ18-AZ17)*W_BANCOS*COSTO,0) | BC19: =IF(ISNUMBER(BA19),BA19-BB19,"") | BD19: =IF(ISNUMBER(BC19),IF(A19<=FECHA_ERA,"A","B"),"") | BE19: =IF(BD19="A",BC19,"") | BF19: =IF(BD19="B",BC19,"") | BG19: =IF(AND(ISNUMBER(BC19),ISNUMBER(A19)),IF(A19>=INICIO_VIVO,1,0),0) | BH19: =IF(BG19=1,BC19,"") | BI19: =IF(ISNUMBER(AY19),ROW(),0) | BJ19: =IF(ISNUMBER(BC19),SUM(BC$5:BC19)*10000,NA()) | BK19: =IF(BG19=1,SUM(BH$5:BH19)*10000,NA()) | BL19: =IF(ISNUMBER(AY19),AY19,NA())
A20: =IF(Datos!A20="","",Datos!A20) | B20: =IF(OR($A20="",NOT(ISNUMBER(Datos!B20)),NOT(ISNUMBER(Datos!B19))),"",Datos!B20/Datos!B19-1) | C20: =IF(OR($A20="",NOT(ISNUMBER(Datos!C20)),NOT(ISNUMBER(Datos!C19))),"",Datos!C20/Datos!C19-1) | D20: =IF(OR($A20="",NOT(ISNUMBER(Datos!D20)),NOT(ISNUMBER(Datos!D19))),"",Datos!D20/Datos!D19-1) | E20: =IF(OR($A20="",NOT(ISNUMBER(Datos!E20)),NOT(ISNUMBER(Datos!E19))),"",Datos!E20/Datos!E19-1) | F20: =IF($A20="","",COUNT(B20:E20)) | G20: =IF($A20="","",IF(F20>=MIN_BANCOS,AVERAGE(B20:E20),"")) | H20: =IF(OR($A20="",NOT(ISNUMBER(Datos!F20)),NOT(ISNUMBER(Datos!F19))),"",Datos!F20/Datos!F19-1) | I20: =IF($A20="","",IF(ISNUMBER(Datos!G20),Datos!G20,I19)) | J20: =IF($A20="","",IF(ISNUMBER(I19),LN(1+I19/100/12),0)) | K20: =IF(ISNUMBER(G20),LN(1+G20)-J20,"") | L20: =IF(ISNUMBER(H20),LN(1+H20)-J20,"") | M20: =IF(ISNUMBER(K20),1,0) | N20: =IF(M20=1,K20,0) | O20: =IF(ISNUMBER(L20),1,0) | P20: =IF(O20=1,L20,0) | Q20: =M20*O20 | R20: =SUM(Q5:Q19) | S20: =IF(OR($A20="",R20<MIN_OBS_ROLL),"",(SUMPRODUCT(Q5:Q19,N5:N19,P5:P19)/R20-SUMPRODUCT(Q5:Q19,N5:N19)/R20*SUMPRODUCT(Q5:Q19,P5:P19)/R20)*R20/(R20-1)) | T20: =SUM(O5:O19) | U20: =IF(OR($A20="",T20<MIN_OBS_ROLL),"",SUMPRODUCT(O5:O19,(P5:P19-SUMPRODUCT(O5:O19,P5:P19)/T20)^2)/(T20-1)) | V20: =IF(OR(S20="",U20=""),"",S20/U20) | W20: =IF(AND(ISNUMBER(K20),ISNUMBER(L20),ISNUMBER(V20)),K20-V20*L20,"") | X20: =IF(OR($A20="",NOT(ISNUMBER(Datos!H20)),NOT(ISNUMBER(Datos!H19))),"",LN(Datos!H20)-LN(Datos!H19)) | Y20: =IF(ISNUMBER(W20),1,0) | Z20: =IF(Y20=1,W20,0) | AA20: =IF(ISNUMBER(X20),1,0) | AB20: =IF(AA20=1,X20,0) | AC20: =Y20*AA20 | AD20: =SUM(AC5:AC19) | AE20: =IF(OR($A20="",AD20<MIN_OBS_ROLL),"",(SUMPRODUCT(AC5:AC19,Z5:Z19,AB5:AB19)/AD20-SUMPRODUCT(AC5:AC19,Z5:Z19)/AD20*SUMPRODUCT(AC5:AC19,AB5:AB19)/AD20)*AD20/(AD20-1)) | AF20: =SUM(AA5:AA19) | AG20: =IF(OR($A20="",AF20<MIN_OBS_ROLL),"",SUMPRODUCT(AA5:AA19,(AB5:AB19-SUMPRODUCT(AA5:AA19,AB5:AB19)/AF20)^2)/(AF20-1)) | AH20: =SUM(Y5:Y19) | AI20: =IF(OR($A20="",AH20<MIN_OBS_ROLL),"",SUMPRODUCT(Y5:Y19,Z5:Z19)/AH20) | AJ20: =IF(OR($A20="",AF20<MIN_OBS_ROLL),"",SUMPRODUCT(AA5:AA19,AB5:AB19)/AF20) | AK20: =IF(OR(AE20="",AG20=""),"",AE20/AG20) | AL20: =IF(OR(AI20="",AK20="",AJ20=""),"",AI20-AK20*AJ20) | AM20: =IF(AND(ISNUMBER(W20),ISNUMBER(X20),ISNUMBER(AK20),ISNUMBER(AL20)),W20-(AL20+AK20*X20),"") | AN20: =IF(ISNUMBER(AM20),1,0) | AO20: =IF(AN20=1,AM20,0) | AP20: =IF(SUM(AN18:AN20)=3,SUM(AO18:AO20),"") | AQ20: =IF(ISNUMBER(AP20),1,0) | AR20: =IF(AQ20=1,AP20,0) | AS20: =SUM(AQ$5:AQ20) | AT20: =IF(AS20>=MIN_OBS_Z,SUMPRODUCT(AQ$5:AQ20,AR$5:AR20)/AS20,"") | AU20: =IF(AS20>=MIN_OBS_Z,SQRT(SUMPRODUCT(AQ$5:AQ20,(AR$5:AR20-AT20)^2)/(AS20-1)),"") | AV20: =IF(AND(AQ20=1,ISNUMBER(AT20)),MAX(-Z_CLIP,MIN(Z_CLIP,(AR20-AT20)/AU20)),"") | AW20: =IF(ISNUMBER(AV20),-AV20,"") | AX20: =IF(ISNUMBER(AW20),1+AMPLITUD*TANH(AW20),"") | AY20: =IF($A20="","",IF(COUNT(AX18:AX20)>0,AVERAGE(AX18:AX20),"")) | AZ20: =IF(ISNUMBER(AY20),AY20-1,"") | BA20: =IF(AND(ISNUMBER(AZ19),ISNUMBER(W20)),AZ19*W_BANCOS*W20,"") | BB20: =IF(AND(ISNUMBER(AZ19),ISNUMBER(AZ18)),ABS(AZ19-AZ18)*W_BANCOS*COSTO,0) | BC20: =IF(ISNUMBER(BA20),BA20-BB20,"") | BD20: =IF(ISNUMBER(BC20),IF(A20<=FECHA_ERA,"A","B"),"") | BE20: =IF(BD20="A",BC20,"") | BF20: =IF(BD20="B",BC20,"") | BG20: =IF(AND(ISNUMBER(BC20),ISNUMBER(A20)),IF(A20>=INICIO_VIVO,1,0),0) | BH20: =IF(BG20=1,BC20,"") | BI20: =IF(ISNUMBER(AY20),ROW(),0) | BJ20: =IF(ISNUMBER(BC20),SUM(BC$5:BC20)*10000,NA()) | BK20: =IF(BG20=1,SUM(BH$5:BH20)*10000,NA()) | BL20: =IF(ISNUMBER(AY20),AY20,NA())
A21: =IF(Datos!A21="","",Datos!A21) | B21: =IF(OR($A21="",NOT(ISNUMBER(Datos!B21)),NOT(ISNUMBER(Datos!B20))),"",Datos!B21/Datos!B20-1) | C21: =IF(OR($A21="",NOT(ISNUMBER(Datos!C21)),NOT(ISNUMBER(Datos!C20))),"",Datos!C21/Datos!C20-1) | D21: =IF(OR($A21="",NOT(ISNUMBER(Datos!D21)),NOT(ISNUMBER(Datos!D20))),"",Datos!D21/Datos!D20-1) | E21: =IF(OR($A21="",NOT(ISNUMBER(Datos!E21)),NOT(ISNUMBER(Datos!E20))),"",Datos!E21/Datos!E20-1) | F21: =IF($A21="","",COUNT(B21:E21)) | G21: =IF($A21="","",IF(F21>=MIN_BANCOS,AVERAGE(B21:E21),"")) | H21: =IF(OR($A21="",NOT(ISNUMBER(Datos!F21)),NOT(ISNUMBER(Datos!F20))),"",Datos!F21/Datos!F20-1) | I21: =IF($A21="","",IF(ISNUMBER(Datos!G21),Datos!G21,I20)) | J21: =IF($A21="","",IF(ISNUMBER(I20),LN(1+I20/100/12),0)) | K21: =IF(ISNUMBER(G21),LN(1+G21)-J21,"") | L21: =IF(ISNUMBER(H21),LN(1+H21)-J21,"") | M21: =IF(ISNUMBER(K21),1,0) | N21: =IF(M21=1,K21,0) | O21: =IF(ISNUMBER(L21),1,0) | P21: =IF(O21=1,L21,0) | Q21: =M21*O21 | R21: =SUM(Q5:Q20) | S21: =IF(OR($A21="",R21<MIN_OBS_ROLL),"",(SUMPRODUCT(Q5:Q20,N5:N20,P5:P20)/R21-SUMPRODUCT(Q5:Q20,N5:N20)/R21*SUMPRODUCT(Q5:Q20,P5:P20)/R21)*R21/(R21-1)) | T21: =SUM(O5:O20) | U21: =IF(OR($A21="",T21<MIN_OBS_ROLL),"",SUMPRODUCT(O5:O20,(P5:P20-SUMPRODUCT(O5:O20,P5:P20)/T21)^2)/(T21-1)) | V21: =IF(OR(S21="",U21=""),"",S21/U21) | W21: =IF(AND(ISNUMBER(K21),ISNUMBER(L21),ISNUMBER(V21)),K21-V21*L21,"") | X21: =IF(OR($A21="",NOT(ISNUMBER(Datos!H21)),NOT(ISNUMBER(Datos!H20))),"",LN(Datos!H21)-LN(Datos!H20)) | Y21: =IF(ISNUMBER(W21),1,0) | Z21: =IF(Y21=1,W21,0) | AA21: =IF(ISNUMBER(X21),1,0) | AB21: =IF(AA21=1,X21,0) | AC21: =Y21*AA21 | AD21: =SUM(AC5:AC20) | AE21: =IF(OR($A21="",AD21<MIN_OBS_ROLL),"",(SUMPRODUCT(AC5:AC20,Z5:Z20,AB5:AB20)/AD21-SUMPRODUCT(AC5:AC20,Z5:Z20)/AD21*SUMPRODUCT(AC5:AC20,AB5:AB20)/AD21)*AD21/(AD21-1)) | AF21: =SUM(AA5:AA20) | AG21: =IF(OR($A21="",AF21<MIN_OBS_ROLL),"",SUMPRODUCT(AA5:AA20,(AB5:AB20-SUMPRODUCT(AA5:AA20,AB5:AB20)/AF21)^2)/(AF21-1)) | AH21: =SUM(Y5:Y20) | AI21: =IF(OR($A21="",AH21<MIN_OBS_ROLL),"",SUMPRODUCT(Y5:Y20,Z5:Z20)/AH21) | AJ21: =IF(OR($A21="",AF21<MIN_OBS_ROLL),"",SUMPRODUCT(AA5:AA20,AB5:AB20)/AF21) | AK21: =IF(OR(AE21="",AG21=""),"",AE21/AG21) | AL21: =IF(OR(AI21="",AK21="",AJ21=""),"",AI21-AK21*AJ21) | AM21: =IF(AND(ISNUMBER(W21),ISNUMBER(X21),ISNUMBER(AK21),ISNUMBER(AL21)),W21-(AL21+AK21*X21),"") | AN21: =IF(ISNUMBER(AM21),1,0) | AO21: =IF(AN21=1,AM21,0) | AP21: =IF(SUM(AN19:AN21)=3,SUM(AO19:AO21),"") | AQ21: =IF(ISNUMBER(AP21),1,0) | AR21: =IF(AQ21=1,AP21,0) | AS21: =SUM(AQ$5:AQ21) | AT21: =IF(AS21>=MIN_OBS_Z,SUMPRODUCT(AQ$5:AQ21,AR$5:AR21)/AS21,"") | AU21: =IF(AS21>=MIN_OBS_Z,SQRT(SUMPRODUCT(AQ$5:AQ21,(AR$5:AR21-AT21)^2)/(AS21-1)),"") | AV21: =IF(AND(AQ21=1,ISNUMBER(AT21)),MAX(-Z_CLIP,MIN(Z_CLIP,(AR21-AT21)/AU21)),"") | AW21: =IF(ISNUMBER(AV21),-AV21,"") | AX21: =IF(ISNUMBER(AW21),1+AMPLITUD*TANH(AW21),"") | AY21: =IF($A21="","",IF(COUNT(AX19:AX21)>0,AVERAGE(AX19:AX21),"")) | AZ21: =IF(ISNUMBER(AY21),AY21-1,"") | BA21: =IF(AND(ISNUMBER(AZ20),ISNUMBER(W21)),AZ20*W_BANCOS*W21,"") | BB21: =IF(AND(ISNUMBER(AZ20),ISNUMBER(AZ19)),ABS(AZ20-AZ19)*W_BANCOS*COSTO,0) | BC21: =IF(ISNUMBER(BA21),BA21-BB21,"") | BD21: =IF(ISNUMBER(BC21),IF(A21<=FECHA_ERA,"A","B"),"") | BE21: =IF(BD21="A",BC21,"") | BF21: =IF(BD21="B",BC21,"") | BG21: =IF(AND(ISNUMBER(BC21),ISNUMBER(A21)),IF(A21>=INICIO_VIVO,1,0),0) | BH21: =IF(BG21=1,BC21,"") | BI21: =IF(ISNUMBER(AY21),ROW(),0) | BJ21: =IF(ISNUMBER(BC21),SUM(BC$5:BC21)*10000,NA()) | BK21: =IF(BG21=1,SUM(BH$5:BH21)*10000,NA()) | BL21: =IF(ISNUMBER(AY21),AY21,NA())
A22: =IF(Datos!A22="","",Datos!A22) | B22: =IF(OR($A22="",NOT(ISNUMBER(Datos!B22)),NOT(ISNUMBER(Datos!B21))),"",Datos!B22/Datos!B21-1) | C22: =IF(OR($A22="",NOT(ISNUMBER(Datos!C22)),NOT(ISNUMBER(Datos!C21))),"",Datos!C22/Datos!C21-1) | D22: =IF(OR($A22="",NOT(ISNUMBER(Datos!D22)),NOT(ISNUMBER(Datos!D21))),"",Datos!D22/Datos!D21-1) | E22: =IF(OR($A22="",NOT(ISNUMBER(Datos!E22)),NOT(ISNUMBER(Datos!E21))),"",Datos!E22/Datos!E21-1) | F22: =IF($A22="","",COUNT(B22:E22)) | G22: =IF($A22="","",IF(F22>=MIN_BANCOS,AVERAGE(B22:E22),"")) | H22: =IF(OR($A22="",NOT(ISNUMBER(Datos!F22)),NOT(ISNUMBER(Datos!F21))),"",Datos!F22/Datos!F21-1) | I22: =IF($A22="","",IF(ISNUMBER(Datos!G22),Datos!G22,I21)) | J22: =IF($A22="","",IF(ISNUMBER(I21),LN(1+I21/100/12),0)) | K22: =IF(ISNUMBER(G22),LN(1+G22)-J22,"") | L22: =IF(ISNUMBER(H22),LN(1+H22)-J22,"") | M22: =IF(ISNUMBER(K22),1,0) | N22: =IF(M22=1,K22,0) | O22: =IF(ISNUMBER(L22),1,0) | P22: =IF(O22=1,L22,0) | Q22: =M22*O22 | R22: =SUM(Q5:Q21) | S22: =IF(OR($A22="",R22<MIN_OBS_ROLL),"",(SUMPRODUCT(Q5:Q21,N5:N21,P5:P21)/R22-SUMPRODUCT(Q5:Q21,N5:N21)/R22*SUMPRODUCT(Q5:Q21,P5:P21)/R22)*R22/(R22-1)) | T22: =SUM(O5:O21) | U22: =IF(OR($A22="",T22<MIN_OBS_ROLL),"",SUMPRODUCT(O5:O21,(P5:P21-SUMPRODUCT(O5:O21,P5:P21)/T22)^2)/(T22-1)) | V22: =IF(OR(S22="",U22=""),"",S22/U22) | W22: =IF(AND(ISNUMBER(K22),ISNUMBER(L22),ISNUMBER(V22)),K22-V22*L22,"") | X22: =IF(OR($A22="",NOT(ISNUMBER(Datos!H22)),NOT(ISNUMBER(Datos!H21))),"",LN(Datos!H22)-LN(Datos!H21)) | Y22: =IF(ISNUMBER(W22),1,0) | Z22: =IF(Y22=1,W22,0) | AA22: =IF(ISNUMBER(X22),1,0) | AB22: =IF(AA22=1,X22,0) | AC22: =Y22*AA22 | AD22: =SUM(AC5:AC21) | AE22: =IF(OR($A22="",AD22<MIN_OBS_ROLL),"",(SUMPRODUCT(AC5:AC21,Z5:Z21,AB5:AB21)/AD22-SUMPRODUCT(AC5:AC21,Z5:Z21)/AD22*SUMPRODUCT(AC5:AC21,AB5:AB21)/AD22)*AD22/(AD22-1)) | AF22: =SUM(AA5:AA21) | AG22: =IF(OR($A22="",AF22<MIN_OBS_ROLL),"",SUMPRODUCT(AA5:AA21,(AB5:AB21-SUMPRODUCT(AA5:AA21,AB5:AB21)/AF22)^2)/(AF22-1)) | AH22: =SUM(Y5:Y21) | AI22: =IF(OR($A22="",AH22<MIN_OBS_ROLL),"",SUMPRODUCT(Y5:Y21,Z5:Z21)/AH22) | AJ22: =IF(OR($A22="",AF22<MIN_OBS_ROLL),"",SUMPRODUCT(AA5:AA21,AB5:AB21)/AF22) | AK22: =IF(OR(AE22="",AG22=""),"",AE22/AG22) | AL22: =IF(OR(AI22="",AK22="",AJ22=""),"",AI22-AK22*AJ22) | AM22: =IF(AND(ISNUMBER(W22),ISNUMBER(X22),ISNUMBER(AK22),ISNUMBER(AL22)),W22-(AL22+AK22*X22),"") | AN22: =IF(ISNUMBER(AM22),1,0) | AO22: =IF(AN22=1,AM22,0) | AP22: =IF(SUM(AN20:AN22)=3,SUM(AO20:AO22),"") | AQ22: =IF(ISNUMBER(AP22),1,0) | AR22: =IF(AQ22=1,AP22,0) | AS22: =SUM(AQ$5:AQ22) | AT22: =IF(AS22>=MIN_OBS_Z,SUMPRODUCT(AQ$5:AQ22,AR$5:AR22)/AS22,"") | AU22: =IF(AS22>=MIN_OBS_Z,SQRT(SUMPRODUCT(AQ$5:AQ22,(AR$5:AR22-AT22)^2)/(AS22-1)),"") | AV22: =IF(AND(AQ22=1,ISNUMBER(AT22)),MAX(-Z_CLIP,MIN(Z_CLIP,(AR22-AT22)/AU22)),"") | AW22: =IF(ISNUMBER(AV22),-AV22,"") | AX22: =IF(ISNUMBER(AW22),1+AMPLITUD*TANH(AW22),"") | AY22: =IF($A22="","",IF(COUNT(AX20:AX22)>0,AVERAGE(AX20:AX22),"")) | AZ22: =IF(ISNUMBER(AY22),AY22-1,"") | BA22: =IF(AND(ISNUMBER(AZ21),ISNUMBER(W22)),AZ21*W_BANCOS*W22,"") | BB22: =IF(AND(ISNUMBER(AZ21),ISNUMBER(AZ20)),ABS(AZ21-AZ20)*W_BANCOS*COSTO,0) | BC22: =IF(ISNUMBER(BA22),BA22-BB22,"") | BD22: =IF(ISNUMBER(BC22),IF(A22<=FECHA_ERA,"A","B"),"") | BE22: =IF(BD22="A",BC22,"") | BF22: =IF(BD22="B",BC22,"") | BG22: =IF(AND(ISNUMBER(BC22),ISNUMBER(A22)),IF(A22>=INICIO_VIVO,1,0),0) | BH22: =IF(BG22=1,BC22,"") | BI22: =IF(ISNUMBER(AY22),ROW(),0) | BJ22: =IF(ISNUMBER(BC22),SUM(BC$5:BC22)*10000,NA()) | BK22: =IF(BG22=1,SUM(BH$5:BH22)*10000,NA()) | BL22: =IF(ISNUMBER(AY22),AY22,NA())
A23: =IF(Datos!A23="","",Datos!A23) | B23: =IF(OR($A23="",NOT(ISNUMBER(Datos!B23)),NOT(ISNUMBER(Datos!B22))),"",Datos!B23/Datos!B22-1) | C23: =IF(OR($A23="",NOT(ISNUMBER(Datos!C23)),NOT(ISNUMBER(Datos!C22))),"",Datos!C23/Datos!C22-1) | D23: =IF(OR($A23="",NOT(ISNUMBER(Datos!D23)),NOT(ISNUMBER(Datos!D22))),"",Datos!D23/Datos!D22-1) | E23: =IF(OR($A23="",NOT(ISNUMBER(Datos!E23)),NOT(ISNUMBER(Datos!E22))),"",Datos!E23/Datos!E22-1) | F23: =IF($A23="","",COUNT(B23:E23)) | G23: =IF($A23="","",IF(F23>=MIN_BANCOS,AVERAGE(B23:E23),"")) | H23: =IF(OR($A23="",NOT(ISNUMBER(Datos!F23)),NOT(ISNUMBER(Datos!F22))),"",Datos!F23/Datos!F22-1) | I23: =IF($A23="","",IF(ISNUMBER(Datos!G23),Datos!G23,I22)) | J23: =IF($A23="","",IF(ISNUMBER(I22),LN(1+I22/100/12),0)) | K23: =IF(ISNUMBER(G23),LN(1+G23)-J23,"") | L23: =IF(ISNUMBER(H23),LN(1+H23)-J23,"") | M23: =IF(ISNUMBER(K23),1,0) | N23: =IF(M23=1,K23,0) | O23: =IF(ISNUMBER(L23),1,0) | P23: =IF(O23=1,L23,0) | Q23: =M23*O23 | R23: =SUM(Q5:Q22) | S23: =IF(OR($A23="",R23<MIN_OBS_ROLL),"",(SUMPRODUCT(Q5:Q22,N5:N22,P5:P22)/R23-SUMPRODUCT(Q5:Q22,N5:N22)/R23*SUMPRODUCT(Q5:Q22,P5:P22)/R23)*R23/(R23-1)) | T23: =SUM(O5:O22) | U23: =IF(OR($A23="",T23<MIN_OBS_ROLL),"",SUMPRODUCT(O5:O22,(P5:P22-SUMPRODUCT(O5:O22,P5:P22)/T23)^2)/(T23-1)) | V23: =IF(OR(S23="",U23=""),"",S23/U23) | W23: =IF(AND(ISNUMBER(K23),ISNUMBER(L23),ISNUMBER(V23)),K23-V23*L23,"") | X23: =IF(OR($A23="",NOT(ISNUMBER(Datos!H23)),NOT(ISNUMBER(Datos!H22))),"",LN(Datos!H23)-LN(Datos!H22)) | Y23: =IF(ISNUMBER(W23),1,0) | Z23: =IF(Y23=1,W23,0) | AA23: =IF(ISNUMBER(X23),1,0) | AB23: =IF(AA23=1,X23,0) | AC23: =Y23*AA23 | AD23: =SUM(AC5:AC22) | AE23: =IF(OR($A23="",AD23<MIN_OBS_ROLL),"",(SUMPRODUCT(AC5:AC22,Z5:Z22,AB5:AB22)/AD23-SUMPRODUCT(AC5:AC22,Z5:Z22)/AD23*SUMPRODUCT(AC5:AC22,AB5:AB22)/AD23)*AD23/(AD23-1)) | AF23: =SUM(AA5:AA22) | AG23: =IF(OR($A23="",AF23<MIN_OBS_ROLL),"",SUMPRODUCT(AA5:AA22,(AB5:AB22-SUMPRODUCT(AA5:AA22,AB5:AB22)/AF23)^2)/(AF23-1)) | AH23: =SUM(Y5:Y22) | AI23: =IF(OR($A23="",AH23<MIN_OBS_ROLL),"",SUMPRODUCT(Y5:Y22,Z5:Z22)/AH23) | AJ23: =IF(OR($A23="",AF23<MIN_OBS_ROLL),"",SUMPRODUCT(AA5:AA22,AB5:AB22)/AF23) | AK23: =IF(OR(AE23="",AG23=""),"",AE23/AG23) | AL23: =IF(OR(AI23="",AK23="",AJ23=""),"",AI23-AK23*AJ23) | AM23: =IF(AND(ISNUMBER(W23),ISNUMBER(X23),ISNUMBER(AK23),ISNUMBER(AL23)),W23-(AL23+AK23*X23),"") | AN23: =IF(ISNUMBER(AM23),1,0) | AO23: =IF(AN23=1,AM23,0) | AP23: =IF(SUM(AN21:AN23)=3,SUM(AO21:AO23),"") | AQ23: =IF(ISNUMBER(AP23),1,0) | AR23: =IF(AQ23=1,AP23,0) | AS23: =SUM(AQ$5:AQ23) | AT23: =IF(AS23>=MIN_OBS_Z,SUMPRODUCT(AQ$5:AQ23,AR$5:AR23)/AS23,"") | AU23: =IF(AS23>=MIN_OBS_Z,SQRT(SUMPRODUCT(AQ$5:AQ23,(AR$5:AR23-AT23)^2)/(AS23-1)),"") | AV23: =IF(AND(AQ23=1,ISNUMBER(AT23)),MAX(-Z_CLIP,MIN(Z_CLIP,(AR23-AT23)/AU23)),"") | AW23: =IF(ISNUMBER(AV23),-AV23,"") | AX23: =IF(ISNUMBER(AW23),1+AMPLITUD*TANH(AW23),"") | AY23: =IF($A23="","",IF(COUNT(AX21:AX23)>0,AVERAGE(AX21:AX23),"")) | AZ23: =IF(ISNUMBER(AY23),AY23-1,"") | BA23: =IF(AND(ISNUMBER(AZ22),ISNUMBER(W23)),AZ22*W_BANCOS*W23,"") | BB23: =IF(AND(ISNUMBER(AZ22),ISNUMBER(AZ21)),ABS(AZ22-AZ21)*W_BANCOS*COSTO,0) | BC23: =IF(ISNUMBER(BA23),BA23-BB23,"") | BD23: =IF(ISNUMBER(BC23),IF(A23<=FECHA_ERA,"A","B"),"") | BE23: =IF(BD23="A",BC23,"") | BF23: =IF(BD23="B",BC23,"") | BG23: =IF(AND(ISNUMBER(BC23),ISNUMBER(A23)),IF(A23>=INICIO_VIVO,1,0),0) | BH23: =IF(BG23=1,BC23,"") | BI23: =IF(ISNUMBER(AY23),ROW(),0) | BJ23: =IF(ISNUMBER(BC23),SUM(BC$5:BC23)*10000,NA()) | BK23: =IF(BG23=1,SUM(BH$5:BH23)*10000,NA()) | BL23: =IF(ISNUMBER(AY23),AY23,NA())
A24: =IF(Datos!A24="","",Datos!A24) | B24: =IF(OR($A24="",NOT(ISNUMBER(Datos!B24)),NOT(ISNUMBER(Datos!B23))),"",Datos!B24/Datos!B23-1) | C24: =IF(OR($A24="",NOT(ISNUMBER(Datos!C24)),NOT(ISNUMBER(Datos!C23))),"",Datos!C24/Datos!C23-1) | D24: =IF(OR($A24="",NOT(ISNUMBER(Datos!D24)),NOT(ISNUMBER(Datos!D23))),"",Datos!D24/Datos!D23-1) | E24: =IF(OR($A24="",NOT(ISNUMBER(Datos!E24)),NOT(ISNUMBER(Datos!E23))),"",Datos!E24/Datos!E23-1) | F24: =IF($A24="","",COUNT(B24:E24)) | G24: =IF($A24="","",IF(F24>=MIN_BANCOS,AVERAGE(B24:E24),"")) | H24: =IF(OR($A24="",NOT(ISNUMBER(Datos!F24)),NOT(ISNUMBER(Datos!F23))),"",Datos!F24/Datos!F23-1) | I24: =IF($A24="","",IF(ISNUMBER(Datos!G24),Datos!G24,I23)) | J24: =IF($A24="","",IF(ISNUMBER(I23),LN(1+I23/100/12),0)) | K24: =IF(ISNUMBER(G24),LN(1+G24)-J24,"") | L24: =IF(ISNUMBER(H24),LN(1+H24)-J24,"") | M24: =IF(ISNUMBER(K24),1,0) | N24: =IF(M24=1,K24,0) | O24: =IF(ISNUMBER(L24),1,0) | P24: =IF(O24=1,L24,0) | Q24: =M24*O24 | R24: =SUM(Q5:Q23) | S24: =IF(OR($A24="",R24<MIN_OBS_ROLL),"",(SUMPRODUCT(Q5:Q23,N5:N23,P5:P23)/R24-SUMPRODUCT(Q5:Q23,N5:N23)/R24*SUMPRODUCT(Q5:Q23,P5:P23)/R24)*R24/(R24-1)) | T24: =SUM(O5:O23) | U24: =IF(OR($A24="",T24<MIN_OBS_ROLL),"",SUMPRODUCT(O5:O23,(P5:P23-SUMPRODUCT(O5:O23,P5:P23)/T24)^2)/(T24-1)) | V24: =IF(OR(S24="",U24=""),"",S24/U24) | W24: =IF(AND(ISNUMBER(K24),ISNUMBER(L24),ISNUMBER(V24)),K24-V24*L24,"") | X24: =IF(OR($A24="",NOT(ISNUMBER(Datos!H24)),NOT(ISNUMBER(Datos!H23))),"",LN(Datos!H24)-LN(Datos!H23)) | Y24: =IF(ISNUMBER(W24),1,0) | Z24: =IF(Y24=1,W24,0) | AA24: =IF(ISNUMBER(X24),1,0) | AB24: =IF(AA24=1,X24,0) | AC24: =Y24*AA24 | AD24: =SUM(AC5:AC23) | AE24: =IF(OR($A24="",AD24<MIN_OBS_ROLL),"",(SUMPRODUCT(AC5:AC23,Z5:Z23,AB5:AB23)/AD24-SUMPRODUCT(AC5:AC23,Z5:Z23)/AD24*SUMPRODUCT(AC5:AC23,AB5:AB23)/AD24)*AD24/(AD24-1)) | AF24: =SUM(AA5:AA23) | AG24: =IF(OR($A24="",AF24<MIN_OBS_ROLL),"",SUMPRODUCT(AA5:AA23,(AB5:AB23-SUMPRODUCT(AA5:AA23,AB5:AB23)/AF24)^2)/(AF24-1)) | AH24: =SUM(Y5:Y23) | AI24: =IF(OR($A24="",AH24<MIN_OBS_ROLL),"",SUMPRODUCT(Y5:Y23,Z5:Z23)/AH24) | AJ24: =IF(OR($A24="",AF24<MIN_OBS_ROLL),"",SUMPRODUCT(AA5:AA23,AB5:AB23)/AF24) | AK24: =IF(OR(AE24="",AG24=""),"",AE24/AG24) | AL24: =IF(OR(AI24="",AK24="",AJ24=""),"",AI24-AK24*AJ24) | AM24: =IF(AND(ISNUMBER(W24),ISNUMBER(X24),ISNUMBER(AK24),ISNUMBER(AL24)),W24-(AL24+AK24*X24),"") | AN24: =IF(ISNUMBER(AM24),1,0) | AO24: =IF(AN24=1,AM24,0) | AP24: =IF(SUM(AN22:AN24)=3,SUM(AO22:AO24),"") | AQ24: =IF(ISNUMBER(AP24),1,0) | AR24: =IF(AQ24=1,AP24,0) | AS24: =SUM(AQ$5:AQ24) | AT24: =IF(AS24>=MIN_OBS_Z,SUMPRODUCT(AQ$5:AQ24,AR$5:AR24)/AS24,"") | AU24: =IF(AS24>=MIN_OBS_Z,SQRT(SUMPRODUCT(AQ$5:AQ24,(AR$5:AR24-AT24)^2)/(AS24-1)),"") | AV24: =IF(AND(AQ24=1,ISNUMBER(AT24)),MAX(-Z_CLIP,MIN(Z_CLIP,(AR24-AT24)/AU24)),"") | AW24: =IF(ISNUMBER(AV24),-AV24,"") | AX24: =IF(ISNUMBER(AW24),1+AMPLITUD*TANH(AW24),"") | AY24: =IF($A24="","",IF(COUNT(AX22:AX24)>0,AVERAGE(AX22:AX24),"")) | AZ24: =IF(ISNUMBER(AY24),AY24-1,"") | BA24: =IF(AND(ISNUMBER(AZ23),ISNUMBER(W24)),AZ23*W_BANCOS*W24,"") | BB24: =IF(AND(ISNUMBER(AZ23),ISNUMBER(AZ22)),ABS(AZ23-AZ22)*W_BANCOS*COSTO,0) | BC24: =IF(ISNUMBER(BA24),BA24-BB24,"") | BD24: =IF(ISNUMBER(BC24),IF(A24<=FECHA_ERA,"A","B"),"") | BE24: =IF(BD24="A",BC24,"") | BF24: =IF(BD24="B",BC24,"") | BG24: =IF(AND(ISNUMBER(BC24),ISNUMBER(A24)),IF(A24>=INICIO_VIVO,1,0),0) | BH24: =IF(BG24=1,BC24,"") | BI24: =IF(ISNUMBER(AY24),ROW(),0) | BJ24: =IF(ISNUMBER(BC24),SUM(BC$5:BC24)*10000,NA()) | BK24: =IF(BG24=1,SUM(BH$5:BH24)*10000,NA()) | BL24: =IF(ISNUMBER(AY24),AY24,NA())
A25: =IF(Datos!A25="","",Datos!A25) | B25: =IF(OR($A25="",NOT(ISNUMBER(Datos!B25)),NOT(ISNUMBER(Datos!B24))),"",Datos!B25/Datos!B24-1) | C25: =IF(OR($A25="",NOT(ISNUMBER(Datos!C25)),NOT(ISNUMBER(Datos!C24))),"",Datos!C25/Datos!C24-1) | D25: =IF(OR($A25="",NOT(ISNUMBER(Datos!D25)),NOT(ISNUMBER(Datos!D24))),"",Datos!D25/Datos!D24-1) | E25: =IF(OR($A25="",NOT(ISNUMBER(Datos!E25)),NOT(ISNUMBER(Datos!E24))),"",Datos!E25/Datos!E24-1) | F25: =IF($A25="","",COUNT(B25:E25)) | G25: =IF($A25="","",IF(F25>=MIN_BANCOS,AVERAGE(B25:E25),"")) | H25: =IF(OR($A25="",NOT(ISNUMBER(Datos!F25)),NOT(ISNUMBER(Datos!F24))),"",Datos!F25/Datos!F24-1) | I25: =IF($A25="","",IF(ISNUMBER(Datos!G25),Datos!G25,I24)) | J25: =IF($A25="","",IF(ISNUMBER(I24),LN(1+I24/100/12),0)) | K25: =IF(ISNUMBER(G25),LN(1+G25)-J25,"") | L25: =IF(ISNUMBER(H25),LN(1+H25)-J25,"") | M25: =IF(ISNUMBER(K25),1,0) | N25: =IF(M25=1,K25,0) | O25: =IF(ISNUMBER(L25),1,0) | P25: =IF(O25=1,L25,0) | Q25: =M25*O25 | R25: =SUM(Q5:Q24) | S25: =IF(OR($A25="",R25<MIN_OBS_ROLL),"",(SUMPRODUCT(Q5:Q24,N5:N24,P5:P24)/R25-SUMPRODUCT(Q5:Q24,N5:N24)/R25*SUMPRODUCT(Q5:Q24,P5:P24)/R25)*R25/(R25-1)) | T25: =SUM(O5:O24) | U25: =IF(OR($A25="",T25<MIN_OBS_ROLL),"",SUMPRODUCT(O5:O24,(P5:P24-SUMPRODUCT(O5:O24,P5:P24)/T25)^2)/(T25-1)) | V25: =IF(OR(S25="",U25=""),"",S25/U25) | W25: =IF(AND(ISNUMBER(K25),ISNUMBER(L25),ISNUMBER(V25)),K25-V25*L25,"") | X25: =IF(OR($A25="",NOT(ISNUMBER(Datos!H25)),NOT(ISNUMBER(Datos!H24))),"",LN(Datos!H25)-LN(Datos!H24)) | Y25: =IF(ISNUMBER(W25),1,0) | Z25: =IF(Y25=1,W25,0) | AA25: =IF(ISNUMBER(X25),1,0) | AB25: =IF(AA25=1,X25,0) | AC25: =Y25*AA25 | AD25: =SUM(AC5:AC24) | AE25: =IF(OR($A25="",AD25<MIN_OBS_ROLL),"",(SUMPRODUCT(AC5:AC24,Z5:Z24,AB5:AB24)/AD25-SUMPRODUCT(AC5:AC24,Z5:Z24)/AD25*SUMPRODUCT(AC5:AC24,AB5:AB24)/AD25)*AD25/(AD25-1)) | AF25: =SUM(AA5:AA24) | AG25: =IF(OR($A25="",AF25<MIN_OBS_ROLL),"",SUMPRODUCT(AA5:AA24,(AB5:AB24-SUMPRODUCT(AA5:AA24,AB5:AB24)/AF25)^2)/(AF25-1)) | AH25: =SUM(Y5:Y24) | AI25: =IF(OR($A25="",AH25<MIN_OBS_ROLL),"",SUMPRODUCT(Y5:Y24,Z5:Z24)/AH25) | AJ25: =IF(OR($A25="",AF25<MIN_OBS_ROLL),"",SUMPRODUCT(AA5:AA24,AB5:AB24)/AF25) | AK25: =IF(OR(AE25="",AG25=""),"",AE25/AG25) | AL25: =IF(OR(AI25="",AK25="",AJ25=""),"",AI25-AK25*AJ25) | AM25: =IF(AND(ISNUMBER(W25),ISNUMBER(X25),ISNUMBER(AK25),ISNUMBER(AL25)),W25-(AL25+AK25*X25),"") | AN25: =IF(ISNUMBER(AM25),1,0) | AO25: =IF(AN25=1,AM25,0) | AP25: =IF(SUM(AN23:AN25)=3,SUM(AO23:AO25),"") | AQ25: =IF(ISNUMBER(AP25),1,0) | AR25: =IF(AQ25=1,AP25,0) | AS25: =SUM(AQ$5:AQ25) | AT25: =IF(AS25>=MIN_OBS_Z,SUMPRODUCT(AQ$5:AQ25,AR$5:AR25)/AS25,"") | AU25: =IF(AS25>=MIN_OBS_Z,SQRT(SUMPRODUCT(AQ$5:AQ25,(AR$5:AR25-AT25)^2)/(AS25-1)),"") | AV25: =IF(AND(AQ25=1,ISNUMBER(AT25)),MAX(-Z_CLIP,MIN(Z_CLIP,(AR25-AT25)/AU25)),"") | AW25: =IF(ISNUMBER(AV25),-AV25,"") | AX25: =IF(ISNUMBER(AW25),1+AMPLITUD*TANH(AW25),"") | AY25: =IF($A25="","",IF(COUNT(AX23:AX25)>0,AVERAGE(AX23:AX25),"")) | AZ25: =IF(ISNUMBER(AY25),AY25-1,"") | BA25: =IF(AND(ISNUMBER(AZ24),ISNUMBER(W25)),AZ24*W_BANCOS*W25,"") | BB25: =IF(AND(ISNUMBER(AZ24),ISNUMBER(AZ23)),ABS(AZ24-AZ23)*W_BANCOS*COSTO,0) | BC25: =IF(ISNUMBER(BA25),BA25-BB25,"") | BD25: =IF(ISNUMBER(BC25),IF(A25<=FECHA_ERA,"A","B"),"") | BE25: =IF(BD25="A",BC25,"") | BF25: =IF(BD25="B",BC25,"") | BG25: =IF(AND(ISNUMBER(BC25),ISNUMBER(A25)),IF(A25>=INICIO_VIVO,1,0),0) | BH25: =IF(BG25=1,BC25,"") | BI25: =IF(ISNUMBER(AY25),ROW(),0) | BJ25: =IF(ISNUMBER(BC25),SUM(BC$5:BC25)*10000,NA()) | BK25: =IF(BG25=1,SUM(BH$5:BH25)*10000,NA()) | BL25: =IF(ISNUMBER(AY25),AY25,NA())
A26: =IF(Datos!A26="","",Datos!A26) | B26: =IF(OR($A26="",NOT(ISNUMBER(Datos!B26)),NOT(ISNUMBER(Datos!B25))),"",Datos!B26/Datos!B25-1) | C26: =IF(OR($A26="",NOT(ISNUMBER(Datos!C26)),NOT(ISNUMBER(Datos!C25))),"",Datos!C26/Datos!C25-1) | D26: =IF(OR($A26="",NOT(ISNUMBER(Datos!D26)),NOT(ISNUMBER(Datos!D25))),"",Datos!D26/Datos!D25-1) | E26: =IF(OR($A26="",NOT(ISNUMBER(Datos!E26)),NOT(ISNUMBER(Datos!E25))),"",Datos!E26/Datos!E25-1) | F26: =IF($A26="","",COUNT(B26:E26)) | G26: =IF($A26="","",IF(F26>=MIN_BANCOS,AVERAGE(B26:E26),"")) | H26: =IF(OR($A26="",NOT(ISNUMBER(Datos!F26)),NOT(ISNUMBER(Datos!F25))),"",Datos!F26/Datos!F25-1) | I26: =IF($A26="","",IF(ISNUMBER(Datos!G26),Datos!G26,I25)) | J26: =IF($A26="","",IF(ISNUMBER(I25),LN(1+I25/100/12),0)) | K26: =IF(ISNUMBER(G26),LN(1+G26)-J26,"") | L26: =IF(ISNUMBER(H26),LN(1+H26)-J26,"") | M26: =IF(ISNUMBER(K26),1,0) | N26: =IF(M26=1,K26,0) | O26: =IF(ISNUMBER(L26),1,0) | P26: =IF(O26=1,L26,0) | Q26: =M26*O26 | R26: =SUM(Q5:Q25) | S26: =IF(OR($A26="",R26<MIN_OBS_ROLL),"",(SUMPRODUCT(Q5:Q25,N5:N25,P5:P25)/R26-SUMPRODUCT(Q5:Q25,N5:N25)/R26*SUMPRODUCT(Q5:Q25,P5:P25)/R26)*R26/(R26-1)) | T26: =SUM(O5:O25) | U26: =IF(OR($A26="",T26<MIN_OBS_ROLL),"",SUMPRODUCT(O5:O25,(P5:P25-SUMPRODUCT(O5:O25,P5:P25)/T26)^2)/(T26-1)) | V26: =IF(OR(S26="",U26=""),"",S26/U26) | W26: =IF(AND(ISNUMBER(K26),ISNUMBER(L26),ISNUMBER(V26)),K26-V26*L26,"") | X26: =IF(OR($A26="",NOT(ISNUMBER(Datos!H26)),NOT(ISNUMBER(Datos!H25))),"",LN(Datos!H26)-LN(Datos!H25)) | Y26: =IF(ISNUMBER(W26),1,0) | Z26: =IF(Y26=1,W26,0) | AA26: =IF(ISNUMBER(X26),1,0) | AB26: =IF(AA26=1,X26,0) | AC26: =Y26*AA26 | AD26: =SUM(AC5:AC25) | AE26: =IF(OR($A26="",AD26<MIN_OBS_ROLL),"",(SUMPRODUCT(AC5:AC25,Z5:Z25,AB5:AB25)/AD26-SUMPRODUCT(AC5:AC25,Z5:Z25)/AD26*SUMPRODUCT(AC5:AC25,AB5:AB25)/AD26)*AD26/(AD26-1)) | AF26: =SUM(AA5:AA25) | AG26: =IF(OR($A26="",AF26<MIN_OBS_ROLL),"",SUMPRODUCT(AA5:AA25,(AB5:AB25-SUMPRODUCT(AA5:AA25,AB5:AB25)/AF26)^2)/(AF26-1)) | AH26: =SUM(Y5:Y25) | AI26: =IF(OR($A26="",AH26<MIN_OBS_ROLL),"",SUMPRODUCT(Y5:Y25,Z5:Z25)/AH26) | AJ26: =IF(OR($A26="",AF26<MIN_OBS_ROLL),"",SUMPRODUCT(AA5:AA25,AB5:AB25)/AF26) | AK26: =IF(OR(AE26="",AG26=""),"",AE26/AG26) | AL26: =IF(OR(AI26="",AK26="",AJ26=""),"",AI26-AK26*AJ26) | AM26: =IF(AND(ISNUMBER(W26),ISNUMBER(X26),ISNUMBER(AK26),ISNUMBER(AL26)),W26-(AL26+AK26*X26),"") | AN26: =IF(ISNUMBER(AM26),1,0) | AO26: =IF(AN26=1,AM26,0) | AP26: =IF(SUM(AN24:AN26)=3,SUM(AO24:AO26),"") | AQ26: =IF(ISNUMBER(AP26),1,0) | AR26: =IF(AQ26=1,AP26,0) | AS26: =SUM(AQ$5:AQ26) | AT26: =IF(AS26>=MIN_OBS_Z,SUMPRODUCT(AQ$5:AQ26,AR$5:AR26)/AS26,"") | AU26: =IF(AS26>=MIN_OBS_Z,SQRT(SUMPRODUCT(AQ$5:AQ26,(AR$5:AR26-AT26)^2)/(AS26-1)),"") | AV26: =IF(AND(AQ26=1,ISNUMBER(AT26)),MAX(-Z_CLIP,MIN(Z_CLIP,(AR26-AT26)/AU26)),"") | AW26: =IF(ISNUMBER(AV26),-AV26,"") | AX26: =IF(ISNUMBER(AW26),1+AMPLITUD*TANH(AW26),"") | AY26: =IF($A26="","",IF(COUNT(AX24:AX26)>0,AVERAGE(AX24:AX26),"")) | AZ26: =IF(ISNUMBER(AY26),AY26-1,"") | BA26: =IF(AND(ISNUMBER(AZ25),ISNUMBER(W26)),AZ25*W_BANCOS*W26,"") | BB26: =IF(AND(ISNUMBER(AZ25),ISNUMBER(AZ24)),ABS(AZ25-AZ24)*W_BANCOS*COSTO,0) | BC26: =IF(ISNUMBER(BA26),BA26-BB26,"") | BD26: =IF(ISNUMBER(BC26),IF(A26<=FECHA_ERA,"A","B"),"") | BE26: =IF(BD26="A",BC26,"") | BF26: =IF(BD26="B",BC26,"") | BG26: =IF(AND(ISNUMBER(BC26),ISNUMBER(A26)),IF(A26>=INICIO_VIVO,1,0),0) | BH26: =IF(BG26=1,BC26,"") | BI26: =IF(ISNUMBER(AY26),ROW(),0) | BJ26: =IF(ISNUMBER(BC26),SUM(BC$5:BC26)*10000,NA()) | BK26: =IF(BG26=1,SUM(BH$5:BH26)*10000,NA()) | BL26: =IF(ISNUMBER(AY26),AY26,NA())
A27: =IF(Datos!A27="","",Datos!A27) | B27: =IF(OR($A27="",NOT(ISNUMBER(Datos!B27)),NOT(ISNUMBER(Datos!B26))),"",Datos!B27/Datos!B26-1) | C27: =IF(OR($A27="",NOT(ISNUMBER(Datos!C27)),NOT(ISNUMBER(Datos!C26))),"",Datos!C27/Datos!C26-1) | D27: =IF(OR($A27="",NOT(ISNUMBER(Datos!D27)),NOT(ISNUMBER(Datos!D26))),"",Datos!D27/Datos!D26-1) | E27: =IF(OR($A27="",NOT(ISNUMBER(Datos!E27)),NOT(ISNUMBER(Datos!E26))),"",Datos!E27/Datos!E26-1) | F27: =IF($A27="","",COUNT(B27:E27)) | G27: =IF($A27="","",IF(F27>=MIN_BANCOS,AVERAGE(B27:E27),"")) | H27: =IF(OR($A27="",NOT(ISNUMBER(Datos!F27)),NOT(ISNUMBER(Datos!F26))),"",Datos!F27/Datos!F26-1) | I27: =IF($A27="","",IF(ISNUMBER(Datos!G27),Datos!G27,I26)) | J27: =IF($A27="","",IF(ISNUMBER(I26),LN(1+I26/100/12),0)) | K27: =IF(ISNUMBER(G27),LN(1+G27)-J27,"") | L27: =IF(ISNUMBER(H27),LN(1+H27)-J27,"") | M27: =IF(ISNUMBER(K27),1,0) | N27: =IF(M27=1,K27,0) | O27: =IF(ISNUMBER(L27),1,0) | P27: =IF(O27=1,L27,0) | Q27: =M27*O27 | R27: =SUM(Q5:Q26) | S27: =IF(OR($A27="",R27<MIN_OBS_ROLL),"",(SUMPRODUCT(Q5:Q26,N5:N26,P5:P26)/R27-SUMPRODUCT(Q5:Q26,N5:N26)/R27*SUMPRODUCT(Q5:Q26,P5:P26)/R27)*R27/(R27-1)) | T27: =SUM(O5:O26) | U27: =IF(OR($A27="",T27<MIN_OBS_ROLL),"",SUMPRODUCT(O5:O26,(P5:P26-SUMPRODUCT(O5:O26,P5:P26)/T27)^2)/(T27-1)) | V27: =IF(OR(S27="",U27=""),"",S27/U27) | W27: =IF(AND(ISNUMBER(K27),ISNUMBER(L27),ISNUMBER(V27)),K27-V27*L27,"") | X27: =IF(OR($A27="",NOT(ISNUMBER(Datos!H27)),NOT(ISNUMBER(Datos!H26))),"",LN(Datos!H27)-LN(Datos!H26)) | Y27: =IF(ISNUMBER(W27),1,0) | Z27: =IF(Y27=1,W27,0) | AA27: =IF(ISNUMBER(X27),1,0) | AB27: =IF(AA27=1,X27,0) | AC27: =Y27*AA27 | AD27: =SUM(AC5:AC26) | AE27: =IF(OR($A27="",AD27<MIN_OBS_ROLL),"",(SUMPRODUCT(AC5:AC26,Z5:Z26,AB5:AB26)/AD27-SUMPRODUCT(AC5:AC26,Z5:Z26)/AD27*SUMPRODUCT(AC5:AC26,AB5:AB26)/AD27)*AD27/(AD27-1)) | AF27: =SUM(AA5:AA26) | AG27: =IF(OR($A27="",AF27<MIN_OBS_ROLL),"",SUMPRODUCT(AA5:AA26,(AB5:AB26-SUMPRODUCT(AA5:AA26,AB5:AB26)/AF27)^2)/(AF27-1)) | AH27: =SUM(Y5:Y26) | AI27: =IF(OR($A27="",AH27<MIN_OBS_ROLL),"",SUMPRODUCT(Y5:Y26,Z5:Z26)/AH27) | AJ27: =IF(OR($A27="",AF27<MIN_OBS_ROLL),"",SUMPRODUCT(AA5:AA26,AB5:AB26)/AF27) | AK27: =IF(OR(AE27="",AG27=""),"",AE27/AG27) | AL27: =IF(OR(AI27="",AK27="",AJ27=""),"",AI27-AK27*AJ27) | AM27: =IF(AND(ISNUMBER(W27),ISNUMBER(X27),ISNUMBER(AK27),ISNUMBER(AL27)),W27-(AL27+AK27*X27),"") | AN27: =IF(ISNUMBER(AM27),1,0) | AO27: =IF(AN27=1,AM27,0) | AP27: =IF(SUM(AN25:AN27)=3,SUM(AO25:AO27),"") | AQ27: =IF(ISNUMBER(AP27),1,0) | AR27: =IF(AQ27=1,AP27,0) | AS27: =SUM(AQ$5:AQ27) | AT27: =IF(AS27>=MIN_OBS_Z,SUMPRODUCT(AQ$5:AQ27,AR$5:AR27)/AS27,"") | AU27: =IF(AS27>=MIN_OBS_Z,SQRT(SUMPRODUCT(AQ$5:AQ27,(AR$5:AR27-AT27)^2)/(AS27-1)),"") | AV27: =IF(AND(AQ27=1,ISNUMBER(AT27)),MAX(-Z_CLIP,MIN(Z_CLIP,(AR27-AT27)/AU27)),"") | AW27: =IF(ISNUMBER(AV27),-AV27,"") | AX27: =IF(ISNUMBER(AW27),1+AMPLITUD*TANH(AW27),"") | AY27: =IF($A27="","",IF(COUNT(AX25:AX27)>0,AVERAGE(AX25:AX27),"")) | AZ27: =IF(ISNUMBER(AY27),AY27-1,"") | BA27: =IF(AND(ISNUMBER(AZ26),ISNUMBER(W27)),AZ26*W_BANCOS*W27,"") | BB27: =IF(AND(ISNUMBER(AZ26),ISNUMBER(AZ25)),ABS(AZ26-AZ25)*W_BANCOS*COSTO,0) | BC27: =IF(ISNUMBER(BA27),BA27-BB27,"") | BD27: =IF(ISNUMBER(BC27),IF(A27<=FECHA_ERA,"A","B"),"") | BE27: =IF(BD27="A",BC27,"") | BF27: =IF(BD27="B",BC27,"") | BG27: =IF(AND(ISNUMBER(BC27),ISNUMBER(A27)),IF(A27>=INICIO_VIVO,1,0),0) | BH27: =IF(BG27=1,BC27,"") | BI27: =IF(ISNUMBER(AY27),ROW(),0) | BJ27: =IF(ISNUMBER(BC27),SUM(BC$5:BC27)*10000,NA()) | BK27: =IF(BG27=1,SUM(BH$5:BH27)*10000,NA()) | BL27: =IF(ISNUMBER(AY27),AY27,NA())
A28: =IF(Datos!A28="","",Datos!A28) | B28: =IF(OR($A28="",NOT(ISNUMBER(Datos!B28)),NOT(ISNUMBER(Datos!B27))),"",Datos!B28/Datos!B27-1) | C28: =IF(OR($A28="",NOT(ISNUMBER(Datos!C28)),NOT(ISNUMBER(Datos!C27))),"",Datos!C28/Datos!C27-1) | D28: =IF(OR($A28="",NOT(ISNUMBER(Datos!D28)),NOT(ISNUMBER(Datos!D27))),"",Datos!D28/Datos!D27-1) | E28: =IF(OR($A28="",NOT(ISNUMBER(Datos!E28)),NOT(ISNUMBER(Datos!E27))),"",Datos!E28/Datos!E27-1) | F28: =IF($A28="","",COUNT(B28:E28)) | G28: =IF($A28="","",IF(F28>=MIN_BANCOS,AVERAGE(B28:E28),"")) | H28: =IF(OR($A28="",NOT(ISNUMBER(Datos!F28)),NOT(ISNUMBER(Datos!F27))),"",Datos!F28/Datos!F27-1) | I28: =IF($A28="","",IF(ISNUMBER(Datos!G28),Datos!G28,I27)) | J28: =IF($A28="","",IF(ISNUMBER(I27),LN(1+I27/100/12),0)) | K28: =IF(ISNUMBER(G28),LN(1+G28)-J28,"") | L28: =IF(ISNUMBER(H28),LN(1+H28)-J28,"") | M28: =IF(ISNUMBER(K28),1,0) | N28: =IF(M28=1,K28,0) | O28: =IF(ISNUMBER(L28),1,0) | P28: =IF(O28=1,L28,0) | Q28: =M28*O28 | R28: =SUM(Q5:Q27) | S28: =IF(OR($A28="",R28<MIN_OBS_ROLL),"",(SUMPRODUCT(Q5:Q27,N5:N27,P5:P27)/R28-SUMPRODUCT(Q5:Q27,N5:N27)/R28*SUMPRODUCT(Q5:Q27,P5:P27)/R28)*R28/(R28-1)) | T28: =SUM(O5:O27) | U28: =IF(OR($A28="",T28<MIN_OBS_ROLL),"",SUMPRODUCT(O5:O27,(P5:P27-SUMPRODUCT(O5:O27,P5:P27)/T28)^2)/(T28-1)) | V28: =IF(OR(S28="",U28=""),"",S28/U28) | W28: =IF(AND(ISNUMBER(K28),ISNUMBER(L28),ISNUMBER(V28)),K28-V28*L28,"") | X28: =IF(OR($A28="",NOT(ISNUMBER(Datos!H28)),NOT(ISNUMBER(Datos!H27))),"",LN(Datos!H28)-LN(Datos!H27)) | Y28: =IF(ISNUMBER(W28),1,0) | Z28: =IF(Y28=1,W28,0) | AA28: =IF(ISNUMBER(X28),1,0) | AB28: =IF(AA28=1,X28,0) | AC28: =Y28*AA28 | AD28: =SUM(AC5:AC27) | AE28: =IF(OR($A28="",AD28<MIN_OBS_ROLL),"",(SUMPRODUCT(AC5:AC27,Z5:Z27,AB5:AB27)/AD28-SUMPRODUCT(AC5:AC27,Z5:Z27)/AD28*SUMPRODUCT(AC5:AC27,AB5:AB27)/AD28)*AD28/(AD28-1)) | AF28: =SUM(AA5:AA27) | AG28: =IF(OR($A28="",AF28<MIN_OBS_ROLL),"",SUMPRODUCT(AA5:AA27,(AB5:AB27-SUMPRODUCT(AA5:AA27,AB5:AB27)/AF28)^2)/(AF28-1)) | AH28: =SUM(Y5:Y27) | AI28: =IF(OR($A28="",AH28<MIN_OBS_ROLL),"",SUMPRODUCT(Y5:Y27,Z5:Z27)/AH28) | AJ28: =IF(OR($A28="",AF28<MIN_OBS_ROLL),"",SUMPRODUCT(AA5:AA27,AB5:AB27)/AF28) | AK28: =IF(OR(AE28="",AG28=""),"",AE28/AG28) | AL28: =IF(OR(AI28="",AK28="",AJ28=""),"",AI28-AK28*AJ28) | AM28: =IF(AND(ISNUMBER(W28),ISNUMBER(X28),ISNUMBER(AK28),ISNUMBER(AL28)),W28-(AL28+AK28*X28),"") | AN28: =IF(ISNUMBER(AM28),1,0) | AO28: =IF(AN28=1,AM28,0) | AP28: =IF(SUM(AN26:AN28)=3,SUM(AO26:AO28),"") | AQ28: =IF(ISNUMBER(AP28),1,0) | AR28: =IF(AQ28=1,AP28,0) | AS28: =SUM(AQ$5:AQ28) | AT28: =IF(AS28>=MIN_OBS_Z,SUMPRODUCT(AQ$5:AQ28,AR$5:AR28)/AS28,"") | AU28: =IF(AS28>=MIN_OBS_Z,SQRT(SUMPRODUCT(AQ$5:AQ28,(AR$5:AR28-AT28)^2)/(AS28-1)),"") | AV28: =IF(AND(AQ28=1,ISNUMBER(AT28)),MAX(-Z_CLIP,MIN(Z_CLIP,(AR28-AT28)/AU28)),"") | AW28: =IF(ISNUMBER(AV28),-AV28,"") | AX28: =IF(ISNUMBER(AW28),1+AMPLITUD*TANH(AW28),"") | AY28: =IF($A28="","",IF(COUNT(AX26:AX28)>0,AVERAGE(AX26:AX28),"")) | AZ28: =IF(ISNUMBER(AY28),AY28-1,"") | BA28: =IF(AND(ISNUMBER(AZ27),ISNUMBER(W28)),AZ27*W_BANCOS*W28,"") | BB28: =IF(AND(ISNUMBER(AZ27),ISNUMBER(AZ26)),ABS(AZ27-AZ26)*W_BANCOS*COSTO,0) | BC28: =IF(ISNUMBER(BA28),BA28-BB28,"") | BD28: =IF(ISNUMBER(BC28),IF(A28<=FECHA_ERA,"A","B"),"") | BE28: =IF(BD28="A",BC28,"") | BF28: =IF(BD28="B",BC28,"") | BG28: =IF(AND(ISNUMBER(BC28),ISNUMBER(A28)),IF(A28>=INICIO_VIVO,1,0),0) | BH28: =IF(BG28=1,BC28,"") | BI28: =IF(ISNUMBER(AY28),ROW(),0) | BJ28: =IF(ISNUMBER(BC28),SUM(BC$5:BC28)*10000,NA()) | BK28: =IF(BG28=1,SUM(BH$5:BH28)*10000,NA()) | BL28: =IF(ISNUMBER(AY28),AY28,NA())
A29: =IF(Datos!A29="","",Datos!A29) | B29: =IF(OR($A29="",NOT(ISNUMBER(Datos!B29)),NOT(ISNUMBER(Datos!B28))),"",Datos!B29/Datos!B28-1) | C29: =IF(OR($A29="",NOT(ISNUMBER(Datos!C29)),NOT(ISNUMBER(Datos!C28))),"",Datos!C29/Datos!C28-1) | D29: =IF(OR($A29="",NOT(ISNUMBER(Datos!D29)),NOT(ISNUMBER(Datos!D28))),"",Datos!D29/Datos!D28-1) | E29: =IF(OR($A29="",NOT(ISNUMBER(Datos!E29)),NOT(ISNUMBER(Datos!E28))),"",Datos!E29/Datos!E28-1) | F29: =IF($A29="","",COUNT(B29:E29)) | G29: =IF($A29="","",IF(F29>=MIN_BANCOS,AVERAGE(B29:E29),"")) | H29: =IF(OR($A29="",NOT(ISNUMBER(Datos!F29)),NOT(ISNUMBER(Datos!F28))),"",Datos!F29/Datos!F28-1) | I29: =IF($A29="","",IF(ISNUMBER(Datos!G29),Datos!G29,I28)) | J29: =IF($A29="","",IF(ISNUMBER(I28),LN(1+I28/100/12),0)) | K29: =IF(ISNUMBER(G29),LN(1+G29)-J29,"") | L29: =IF(ISNUMBER(H29),LN(1+H29)-J29,"") | M29: =IF(ISNUMBER(K29),1,0) | N29: =IF(M29=1,K29,0) | O29: =IF(ISNUMBER(L29),1,0) | P29: =IF(O29=1,L29,0) | Q29: =M29*O29 | R29: =SUM(Q5:Q28) | S29: =IF(OR($A29="",R29<MIN_OBS_ROLL),"",(SUMPRODUCT(Q5:Q28,N5:N28,P5:P28)/R29-SUMPRODUCT(Q5:Q28,N5:N28)/R29*SUMPRODUCT(Q5:Q28,P5:P28)/R29)*R29/(R29-1)) | T29: =SUM(O5:O28) | U29: =IF(OR($A29="",T29<MIN_OBS_ROLL),"",SUMPRODUCT(O5:O28,(P5:P28-SUMPRODUCT(O5:O28,P5:P28)/T29)^2)/(T29-1)) | V29: =IF(OR(S29="",U29=""),"",S29/U29) | W29: =IF(AND(ISNUMBER(K29),ISNUMBER(L29),ISNUMBER(V29)),K29-V29*L29,"") | X29: =IF(OR($A29="",NOT(ISNUMBER(Datos!H29)),NOT(ISNUMBER(Datos!H28))),"",LN(Datos!H29)-LN(Datos!H28)) | Y29: =IF(ISNUMBER(W29),1,0) | Z29: =IF(Y29=1,W29,0) | AA29: =IF(ISNUMBER(X29),1,0) | AB29: =IF(AA29=1,X29,0) | AC29: =Y29*AA29 | AD29: =SUM(AC5:AC28) | AE29: =IF(OR($A29="",AD29<MIN_OBS_ROLL),"",(SUMPRODUCT(AC5:AC28,Z5:Z28,AB5:AB28)/AD29-SUMPRODUCT(AC5:AC28,Z5:Z28)/AD29*SUMPRODUCT(AC5:AC28,AB5:AB28)/AD29)*AD29/(AD29-1)) | AF29: =SUM(AA5:AA28) | AG29: =IF(OR($A29="",AF29<MIN_OBS_ROLL),"",SUMPRODUCT(AA5:AA28,(AB5:AB28-SUMPRODUCT(AA5:AA28,AB5:AB28)/AF29)^2)/(AF29-1)) | AH29: =SUM(Y5:Y28) | AI29: =IF(OR($A29="",AH29<MIN_OBS_ROLL),"",SUMPRODUCT(Y5:Y28,Z5:Z28)/AH29) | AJ29: =IF(OR($A29="",AF29<MIN_OBS_ROLL),"",SUMPRODUCT(AA5:AA28,AB5:AB28)/AF29) | AK29: =IF(OR(AE29="",AG29=""),"",AE29/AG29) | AL29: =IF(OR(AI29="",AK29="",AJ29=""),"",AI29-AK29*AJ29) | AM29: =IF(AND(ISNUMBER(W29),ISNUMBER(X29),ISNUMBER(AK29),ISNUMBER(AL29)),W29-(AL29+AK29*X29),"") | AN29: =IF(ISNUMBER(AM29),1,0) | AO29: =IF(AN29=1,AM29,0) | AP29: =IF(SUM(AN27:AN29)=3,SUM(AO27:AO29),"") | AQ29: =IF(ISNUMBER(AP29),1,0) | AR29: =IF(AQ29=1,AP29,0) | AS29: =SUM(AQ$5:AQ29) | AT29: =IF(AS29>=MIN_OBS_Z,SUMPRODUCT(AQ$5:AQ29,AR$5:AR29)/AS29,"") | AU29: =IF(AS29>=MIN_OBS_Z,SQRT(SUMPRODUCT(AQ$5:AQ29,(AR$5:AR29-AT29)^2)/(AS29-1)),"") | AV29: =IF(AND(AQ29=1,ISNUMBER(AT29)),MAX(-Z_CLIP,MIN(Z_CLIP,(AR29-AT29)/AU29)),"") | AW29: =IF(ISNUMBER(AV29),-AV29,"") | AX29: =IF(ISNUMBER(AW29),1+AMPLITUD*TANH(AW29),"") | AY29: =IF($A29="","",IF(COUNT(AX27:AX29)>0,AVERAGE(AX27:AX29),"")) | AZ29: =IF(ISNUMBER(AY29),AY29-1,"") | BA29: =IF(AND(ISNUMBER(AZ28),ISNUMBER(W29)),AZ28*W_BANCOS*W29,"") | BB29: =IF(AND(ISNUMBER(AZ28),ISNUMBER(AZ27)),ABS(AZ28-AZ27)*W_BANCOS*COSTO,0) | BC29: =IF(ISNUMBER(BA29),BA29-BB29,"") | BD29: =IF(ISNUMBER(BC29),IF(A29<=FECHA_ERA,"A","B"),"") | BE29: =IF(BD29="A",BC29,"") | BF29: =IF(BD29="B",BC29,"") | BG29: =IF(AND(ISNUMBER(BC29),ISNUMBER(A29)),IF(A29>=INICIO_VIVO,1,0),0) | BH29: =IF(BG29=1,BC29,"") | BI29: =IF(ISNUMBER(AY29),ROW(),0) | BJ29: =IF(ISNUMBER(BC29),SUM(BC$5:BC29)*10000,NA()) | BK29: =IF(BG29=1,SUM(BH$5:BH29)*10000,NA()) | BL29: =IF(ISNUMBER(AY29),AY29,NA())
A30: =IF(Datos!A30="","",Datos!A30) | B30: =IF(OR($A30="",NOT(ISNUMBER(Datos!B30)),NOT(ISNUMBER(Datos!B29))),"",Datos!B30/Datos!B29-1) | C30: =IF(OR($A30="",NOT(ISNUMBER(Datos!C30)),NOT(ISNUMBER(Datos!C29))),"",Datos!C30/Datos!C29-1) | D30: =IF(OR($A30="",NOT(ISNUMBER(Datos!D30)),NOT(ISNUMBER(Datos!D29))),"",Datos!D30/Datos!D29-1) | E30: =IF(OR($A30="",NOT(ISNUMBER(Datos!E30)),NOT(ISNUMBER(Datos!E29))),"",Datos!E30/Datos!E29-1) | F30: =IF($A30="","",COUNT(B30:E30)) | G30: =IF($A30="","",IF(F30>=MIN_BANCOS,AVERAGE(B30:E30),"")) | H30: =IF(OR($A30="",NOT(ISNUMBER(Datos!F30)),NOT(ISNUMBER(Datos!F29))),"",Datos!F30/Datos!F29-1) | I30: =IF($A30="","",IF(ISNUMBER(Datos!G30),Datos!G30,I29)) | J30: =IF($A30="","",IF(ISNUMBER(I29),LN(1+I29/100/12),0)) | K30: =IF(ISNUMBER(G30),LN(1+G30)-J30,"") | L30: =IF(ISNUMBER(H30),LN(1+H30)-J30,"") | M30: =IF(ISNUMBER(K30),1,0) | N30: =IF(M30=1,K30,0) | O30: =IF(ISNUMBER(L30),1,0) | P30: =IF(O30=1,L30,0) | Q30: =M30*O30 | R30: =SUM(Q5:Q29) | S30: =IF(OR($A30="",R30<MIN_OBS_ROLL),"",(SUMPRODUCT(Q5:Q29,N5:N29,P5:P29)/R30-SUMPRODUCT(Q5:Q29,N5:N29)/R30*SUMPRODUCT(Q5:Q29,P5:P29)/R30)*R30/(R30-1)) | T30: =SUM(O5:O29) | U30: =IF(OR($A30="",T30<MIN_OBS_ROLL),"",SUMPRODUCT(O5:O29,(P5:P29-SUMPRODUCT(O5:O29,P5:P29)/T30)^2)/(T30-1)) | V30: =IF(OR(S30="",U30=""),"",S30/U30) | W30: =IF(AND(ISNUMBER(K30),ISNUMBER(L30),ISNUMBER(V30)),K30-V30*L30,"") | X30: =IF(OR($A30="",NOT(ISNUMBER(Datos!H30)),NOT(ISNUMBER(Datos!H29))),"",LN(Datos!H30)-LN(Datos!H29)) | Y30: =IF(ISNUMBER(W30),1,0) | Z30: =IF(Y30=1,W30,0) | AA30: =IF(ISNUMBER(X30),1,0) | AB30: =IF(AA30=1,X30,0) | AC30: =Y30*AA30 | AD30: =SUM(AC5:AC29) | AE30: =IF(OR($A30="",AD30<MIN_OBS_ROLL),"",(SUMPRODUCT(AC5:AC29,Z5:Z29,AB5:AB29)/AD30-SUMPRODUCT(AC5:AC29,Z5:Z29)/AD30*SUMPRODUCT(AC5:AC29,AB5:AB29)/AD30)*AD30/(AD30-1)) | AF30: =SUM(AA5:AA29) | AG30: =IF(OR($A30="",AF30<MIN_OBS_ROLL),"",SUMPRODUCT(AA5:AA29,(AB5:AB29-SUMPRODUCT(AA5:AA29,AB5:AB29)/AF30)^2)/(AF30-1)) | AH30: =SUM(Y5:Y29) | AI30: =IF(OR($A30="",AH30<MIN_OBS_ROLL),"",SUMPRODUCT(Y5:Y29,Z5:Z29)/AH30) | AJ30: =IF(OR($A30="",AF30<MIN_OBS_ROLL),"",SUMPRODUCT(AA5:AA29,AB5:AB29)/AF30) | AK30: =IF(OR(AE30="",AG30=""),"",AE30/AG30) | AL30: =IF(OR(AI30="",AK30="",AJ30=""),"",AI30-AK30*AJ30) | AM30: =IF(AND(ISNUMBER(W30),ISNUMBER(X30),ISNUMBER(AK30),ISNUMBER(AL30)),W30-(AL30+AK30*X30),"") | AN30: =IF(ISNUMBER(AM30),1,0) | AO30: =IF(AN30=1,AM30,0) | AP30: =IF(SUM(AN28:AN30)=3,SUM(AO28:AO30),"") | AQ30: =IF(ISNUMBER(AP30),1,0) | AR30: =IF(AQ30=1,AP30,0) | AS30: =SUM(AQ$5:AQ30) | AT30: =IF(AS30>=MIN_OBS_Z,SUMPRODUCT(AQ$5:AQ30,AR$5:AR30)/AS30,"") | AU30: =IF(AS30>=MIN_OBS_Z,SQRT(SUMPRODUCT(AQ$5:AQ30,(AR$5:AR30-AT30)^2)/(AS30-1)),"") | AV30: =IF(AND(AQ30=1,ISNUMBER(AT30)),MAX(-Z_CLIP,MIN(Z_CLIP,(AR30-AT30)/AU30)),"") | AW30: =IF(ISNUMBER(AV30),-AV30,"") | AX30: =IF(ISNUMBER(AW30),1+AMPLITUD*TANH(AW30),"") | AY30: =IF($A30="","",IF(COUNT(AX28:AX30)>0,AVERAGE(AX28:AX30),"")) | AZ30: =IF(ISNUMBER(AY30),AY30-1,"") | BA30: =IF(AND(ISNUMBER(AZ29),ISNUMBER(W30)),AZ29*W_BANCOS*W30,"") | BB30: =IF(AND(ISNUMBER(AZ29),ISNUMBER(AZ28)),ABS(AZ29-AZ28)*W_BANCOS*COSTO,0) | BC30: =IF(ISNUMBER(BA30),BA30-BB30,"") | BD30: =IF(ISNUMBER(BC30),IF(A30<=FECHA_ERA,"A","B"),"") | BE30: =IF(BD30="A",BC30,"") | BF30: =IF(BD30="B",BC30,"") | BG30: =IF(AND(ISNUMBER(BC30),ISNUMBER(A30)),IF(A30>=INICIO_VIVO,1,0),0) | BH30: =IF(BG30=1,BC30,"") | BI30: =IF(ISNUMBER(AY30),ROW(),0) | BJ30: =IF(ISNUMBER(BC30),SUM(BC$5:BC30)*10000,NA()) | BK30: =IF(BG30=1,SUM(BH$5:BH30)*10000,NA()) | BL30: =IF(ISNUMBER(AY30),AY30,NA())
A31: =IF(Datos!A31="","",Datos!A31) | B31: =IF(OR($A31="",NOT(ISNUMBER(Datos!B31)),NOT(ISNUMBER(Datos!B30))),"",Datos!B31/Datos!B30-1) | C31: =IF(OR($A31="",NOT(ISNUMBER(Datos!C31)),NOT(ISNUMBER(Datos!C30))),"",Datos!C31/Datos!C30-1) | D31: =IF(OR($A31="",NOT(ISNUMBER(Datos!D31)),NOT(ISNUMBER(Datos!D30))),"",Datos!D31/Datos!D30-1) | E31: =IF(OR($A31="",NOT(ISNUMBER(Datos!E31)),NOT(ISNUMBER(Datos!E30))),"",Datos!E31/Datos!E30-1) | F31: =IF($A31="","",COUNT(B31:E31)) | G31: =IF($A31="","",IF(F31>=MIN_BANCOS,AVERAGE(B31:E31),"")) | H31: =IF(OR($A31="",NOT(ISNUMBER(Datos!F31)),NOT(ISNUMBER(Datos!F30))),"",Datos!F31/Datos!F30-1) | I31: =IF($A31="","",IF(ISNUMBER(Datos!G31),Datos!G31,I30)) | J31: =IF($A31="","",IF(ISNUMBER(I30),LN(1+I30/100/12),0)) | K31: =IF(ISNUMBER(G31),LN(1+G31)-J31,"") | L31: =IF(ISNUMBER(H31),LN(1+H31)-J31,"") | M31: =IF(ISNUMBER(K31),1,0) | N31: =IF(M31=1,K31,0) | O31: =IF(ISNUMBER(L31),1,0) | P31: =IF(O31=1,L31,0) | Q31: =M31*O31 | R31: =SUM(Q5:Q30) | S31: =IF(OR($A31="",R31<MIN_OBS_ROLL),"",(SUMPRODUCT(Q5:Q30,N5:N30,P5:P30)/R31-SUMPRODUCT(Q5:Q30,N5:N30)/R31*SUMPRODUCT(Q5:Q30,P5:P30)/R31)*R31/(R31-1)) | T31: =SUM(O5:O30) | U31: =IF(OR($A31="",T31<MIN_OBS_ROLL),"",SUMPRODUCT(O5:O30,(P5:P30-SUMPRODUCT(O5:O30,P5:P30)/T31)^2)/(T31-1)) | V31: =IF(OR(S31="",U31=""),"",S31/U31) | W31: =IF(AND(ISNUMBER(K31),ISNUMBER(L31),ISNUMBER(V31)),K31-V31*L31,"") | X31: =IF(OR($A31="",NOT(ISNUMBER(Datos!H31)),NOT(ISNUMBER(Datos!H30))),"",LN(Datos!H31)-LN(Datos!H30)) | Y31: =IF(ISNUMBER(W31),1,0) | Z31: =IF(Y31=1,W31,0) | AA31: =IF(ISNUMBER(X31),1,0) | AB31: =IF(AA31=1,X31,0) | AC31: =Y31*AA31 | AD31: =SUM(AC5:AC30) | AE31: =IF(OR($A31="",AD31<MIN_OBS_ROLL),"",(SUMPRODUCT(AC5:AC30,Z5:Z30,AB5:AB30)/AD31-SUMPRODUCT(AC5:AC30,Z5:Z30)/AD31*SUMPRODUCT(AC5:AC30,AB5:AB30)/AD31)*AD31/(AD31-1)) | AF31: =SUM(AA5:AA30) | AG31: =IF(OR($A31="",AF31<MIN_OBS_ROLL),"",SUMPRODUCT(AA5:AA30,(AB5:AB30-SUMPRODUCT(AA5:AA30,AB5:AB30)/AF31)^2)/(AF31-1)) | AH31: =SUM(Y5:Y30) | AI31: =IF(OR($A31="",AH31<MIN_OBS_ROLL),"",SUMPRODUCT(Y5:Y30,Z5:Z30)/AH31) | AJ31: =IF(OR($A31="",AF31<MIN_OBS_ROLL),"",SUMPRODUCT(AA5:AA30,AB5:AB30)/AF31) | AK31: =IF(OR(AE31="",AG31=""),"",AE31/AG31) | AL31: =IF(OR(AI31="",AK31="",AJ31=""),"",AI31-AK31*AJ31) | AM31: =IF(AND(ISNUMBER(W31),ISNUMBER(X31),ISNUMBER(AK31),ISNUMBER(AL31)),W31-(AL31+AK31*X31),"") | AN31: =IF(ISNUMBER(AM31),1,0) | AO31: =IF(AN31=1,AM31,0) | AP31: =IF(SUM(AN29:AN31)=3,SUM(AO29:AO31),"") | AQ31: =IF(ISNUMBER(AP31),1,0) | AR31: =IF(AQ31=1,AP31,0) | AS31: =SUM(AQ$5:AQ31) | AT31: =IF(AS31>=MIN_OBS_Z,SUMPRODUCT(AQ$5:AQ31,AR$5:AR31)/AS31,"") | AU31: =IF(AS31>=MIN_OBS_Z,SQRT(SUMPRODUCT(AQ$5:AQ31,(AR$5:AR31-AT31)^2)/(AS31-1)),"") | AV31: =IF(AND(AQ31=1,ISNUMBER(AT31)),MAX(-Z_CLIP,MIN(Z_CLIP,(AR31-AT31)/AU31)),"") | AW31: =IF(ISNUMBER(AV31),-AV31,"") | AX31: =IF(ISNUMBER(AW31),1+AMPLITUD*TANH(AW31),"") | AY31: =IF($A31="","",IF(COUNT(AX29:AX31)>0,AVERAGE(AX29:AX31),"")) | AZ31: =IF(ISNUMBER(AY31),AY31-1,"") | BA31: =IF(AND(ISNUMBER(AZ30),ISNUMBER(W31)),AZ30*W_BANCOS*W31,"") | BB31: =IF(AND(ISNUMBER(AZ30),ISNUMBER(AZ29)),ABS(AZ30-AZ29)*W_BANCOS*COSTO,0) | BC31: =IF(ISNUMBER(BA31),BA31-BB31,"") | BD31: =IF(ISNUMBER(BC31),IF(A31<=FECHA_ERA,"A","B"),"") | BE31: =IF(BD31="A",BC31,"") | BF31: =IF(BD31="B",BC31,"") | BG31: =IF(AND(ISNUMBER(BC31),ISNUMBER(A31)),IF(A31>=INICIO_VIVO,1,0),0) | BH31: =IF(BG31=1,BC31,"") | BI31: =IF(ISNUMBER(AY31),ROW(),0) | BJ31: =IF(ISNUMBER(BC31),SUM(BC$5:BC31)*10000,NA()) | BK31: =IF(BG31=1,SUM(BH$5:BH31)*10000,NA()) | BL31: =IF(ISNUMBER(AY31),AY31,NA())
A32: =IF(Datos!A32="","",Datos!A32) | B32: =IF(OR($A32="",NOT(ISNUMBER(Datos!B32)),NOT(ISNUMBER(Datos!B31))),"",Datos!B32/Datos!B31-1) | C32: =IF(OR($A32="",NOT(ISNUMBER(Datos!C32)),NOT(ISNUMBER(Datos!C31))),"",Datos!C32/Datos!C31-1) | D32: =IF(OR($A32="",NOT(ISNUMBER(Datos!D32)),NOT(ISNUMBER(Datos!D31))),"",Datos!D32/Datos!D31-1) | E32: =IF(OR($A32="",NOT(ISNUMBER(Datos!E32)),NOT(ISNUMBER(Datos!E31))),"",Datos!E32/Datos!E31-1) | F32: =IF($A32="","",COUNT(B32:E32)) | G32: =IF($A32="","",IF(F32>=MIN_BANCOS,AVERAGE(B32:E32),"")) | H32: =IF(OR($A32="",NOT(ISNUMBER(Datos!F32)),NOT(ISNUMBER(Datos!F31))),"",Datos!F32/Datos!F31-1) | I32: =IF($A32="","",IF(ISNUMBER(Datos!G32),Datos!G32,I31)) | J32: =IF($A32="","",IF(ISNUMBER(I31),LN(1+I31/100/12),0)) | K32: =IF(ISNUMBER(G32),LN(1+G32)-J32,"") | L32: =IF(ISNUMBER(H32),LN(1+H32)-J32,"") | M32: =IF(ISNUMBER(K32),1,0) | N32: =IF(M32=1,K32,0) | O32: =IF(ISNUMBER(L32),1,0) | P32: =IF(O32=1,L32,0) | Q32: =M32*O32 | R32: =SUM(Q5:Q31) | S32: =IF(OR($A32="",R32<MIN_OBS_ROLL),"",(SUMPRODUCT(Q5:Q31,N5:N31,P5:P31)/R32-SUMPRODUCT(Q5:Q31,N5:N31)/R32*SUMPRODUCT(Q5:Q31,P5:P31)/R32)*R32/(R32-1)) | T32: =SUM(O5:O31) | U32: =IF(OR($A32="",T32<MIN_OBS_ROLL),"",SUMPRODUCT(O5:O31,(P5:P31-SUMPRODUCT(O5:O31,P5:P31)/T32)^2)/(T32-1)) | V32: =IF(OR(S32="",U32=""),"",S32/U32) | W32: =IF(AND(ISNUMBER(K32),ISNUMBER(L32),ISNUMBER(V32)),K32-V32*L32,"") | X32: =IF(OR($A32="",NOT(ISNUMBER(Datos!H32)),NOT(ISNUMBER(Datos!H31))),"",LN(Datos!H32)-LN(Datos!H31)) | Y32: =IF(ISNUMBER(W32),1,0) | Z32: =IF(Y32=1,W32,0) | AA32: =IF(ISNUMBER(X32),1,0) | AB32: =IF(AA32=1,X32,0) | AC32: =Y32*AA32 | AD32: =SUM(AC5:AC31) | AE32: =IF(OR($A32="",AD32<MIN_OBS_ROLL),"",(SUMPRODUCT(AC5:AC31,Z5:Z31,AB5:AB31)/AD32-SUMPRODUCT(AC5:AC31,Z5:Z31)/AD32*SUMPRODUCT(AC5:AC31,AB5:AB31)/AD32)*AD32/(AD32-1)) | AF32: =SUM(AA5:AA31) | AG32: =IF(OR($A32="",AF32<MIN_OBS_ROLL),"",SUMPRODUCT(AA5:AA31,(AB5:AB31-SUMPRODUCT(AA5:AA31,AB5:AB31)/AF32)^2)/(AF32-1)) | AH32: =SUM(Y5:Y31) | AI32: =IF(OR($A32="",AH32<MIN_OBS_ROLL),"",SUMPRODUCT(Y5:Y31,Z5:Z31)/AH32) | AJ32: =IF(OR($A32="",AF32<MIN_OBS_ROLL),"",SUMPRODUCT(AA5:AA31,AB5:AB31)/AF32) | AK32: =IF(OR(AE32="",AG32=""),"",AE32/AG32) | AL32: =IF(OR(AI32="",AK32="",AJ32=""),"",AI32-AK32*AJ32) | AM32: =IF(AND(ISNUMBER(W32),ISNUMBER(X32),ISNUMBER(AK32),ISNUMBER(AL32)),W32-(AL32+AK32*X32),"") | AN32: =IF(ISNUMBER(AM32),1,0) | AO32: =IF(AN32=1,AM32,0) | AP32: =IF(SUM(AN30:AN32)=3,SUM(AO30:AO32),"") | AQ32: =IF(ISNUMBER(AP32),1,0) | AR32: =IF(AQ32=1,AP32,0) | AS32: =SUM(AQ$5:AQ32) | AT32: =IF(AS32>=MIN_OBS_Z,SUMPRODUCT(AQ$5:AQ32,AR$5:AR32)/AS32,"") | AU32: =IF(AS32>=MIN_OBS_Z,SQRT(SUMPRODUCT(AQ$5:AQ32,(AR$5:AR32-AT32)^2)/(AS32-1)),"") | AV32: =IF(AND(AQ32=1,ISNUMBER(AT32)),MAX(-Z_CLIP,MIN(Z_CLIP,(AR32-AT32)/AU32)),"") | AW32: =IF(ISNUMBER(AV32),-AV32,"") | AX32: =IF(ISNUMBER(AW32),1+AMPLITUD*TANH(AW32),"") | AY32: =IF($A32="","",IF(COUNT(AX30:AX32)>0,AVERAGE(AX30:AX32),"")) | AZ32: =IF(ISNUMBER(AY32),AY32-1,"") | BA32: =IF(AND(ISNUMBER(AZ31),ISNUMBER(W32)),AZ31*W_BANCOS*W32,"") | BB32: =IF(AND(ISNUMBER(AZ31),ISNUMBER(AZ30)),ABS(AZ31-AZ30)*W_BANCOS*COSTO,0) | BC32: =IF(ISNUMBER(BA32),BA32-BB32,"") | BD32: =IF(ISNUMBER(BC32),IF(A32<=FECHA_ERA,"A","B"),"") | BE32: =IF(BD32="A",BC32,"") | BF32: =IF(BD32="B",BC32,"") | BG32: =IF(AND(ISNUMBER(BC32),ISNUMBER(A32)),IF(A32>=INICIO_VIVO,1,0),0) | BH32: =IF(BG32=1,BC32,"") | BI32: =IF(ISNUMBER(AY32),ROW(),0) | BJ32: =IF(ISNUMBER(BC32),SUM(BC$5:BC32)*10000,NA()) | BK32: =IF(BG32=1,SUM(BH$5:BH32)*10000,NA()) | BL32: =IF(ISNUMBER(AY32),AY32,NA())
A33: =IF(Datos!A33="","",Datos!A33) | B33: =IF(OR($A33="",NOT(ISNUMBER(Datos!B33)),NOT(ISNUMBER(Datos!B32))),"",Datos!B33/Datos!B32-1) | C33: =IF(OR($A33="",NOT(ISNUMBER(Datos!C33)),NOT(ISNUMBER(Datos!C32))),"",Datos!C33/Datos!C32-1) | D33: =IF(OR($A33="",NOT(ISNUMBER(Datos!D33)),NOT(ISNUMBER(Datos!D32))),"",Datos!D33/Datos!D32-1) | E33: =IF(OR($A33="",NOT(ISNUMBER(Datos!E33)),NOT(ISNUMBER(Datos!E32))),"",Datos!E33/Datos!E32-1) | F33: =IF($A33="","",COUNT(B33:E33)) | G33: =IF($A33="","",IF(F33>=MIN_BANCOS,AVERAGE(B33:E33),"")) | H33: =IF(OR($A33="",NOT(ISNUMBER(Datos!F33)),NOT(ISNUMBER(Datos!F32))),"",Datos!F33/Datos!F32-1) | I33: =IF($A33="","",IF(ISNUMBER(Datos!G33),Datos!G33,I32)) | J33: =IF($A33="","",IF(ISNUMBER(I32),LN(1+I32/100/12),0)) | K33: =IF(ISNUMBER(G33),LN(1+G33)-J33,"") | L33: =IF(ISNUMBER(H33),LN(1+H33)-J33,"") | M33: =IF(ISNUMBER(K33),1,0) | N33: =IF(M33=1,K33,0) | O33: =IF(ISNUMBER(L33),1,0) | P33: =IF(O33=1,L33,0) | Q33: =M33*O33 | R33: =SUM(Q5:Q32) | S33: =IF(OR($A33="",R33<MIN_OBS_ROLL),"",(SUMPRODUCT(Q5:Q32,N5:N32,P5:P32)/R33-SUMPRODUCT(Q5:Q32,N5:N32)/R33*SUMPRODUCT(Q5:Q32,P5:P32)/R33)*R33/(R33-1)) | T33: =SUM(O5:O32) | U33: =IF(OR($A33="",T33<MIN_OBS_ROLL),"",SUMPRODUCT(O5:O32,(P5:P32-SUMPRODUCT(O5:O32,P5:P32)/T33)^2)/(T33-1)) | V33: =IF(OR(S33="",U33=""),"",S33/U33) | W33: =IF(AND(ISNUMBER(K33),ISNUMBER(L33),ISNUMBER(V33)),K33-V33*L33,"") | X33: =IF(OR($A33="",NOT(ISNUMBER(Datos!H33)),NOT(ISNUMBER(Datos!H32))),"",LN(Datos!H33)-LN(Datos!H32)) | Y33: =IF(ISNUMBER(W33),1,0) | Z33: =IF(Y33=1,W33,0) | AA33: =IF(ISNUMBER(X33),1,0) | AB33: =IF(AA33=1,X33,0) | AC33: =Y33*AA33 | AD33: =SUM(AC5:AC32) | AE33: =IF(OR($A33="",AD33<MIN_OBS_ROLL),"",(SUMPRODUCT(AC5:AC32,Z5:Z32,AB5:AB32)/AD33-SUMPRODUCT(AC5:AC32,Z5:Z32)/AD33*SUMPRODUCT(AC5:AC32,AB5:AB32)/AD33)*AD33/(AD33-1)) | AF33: =SUM(AA5:AA32) | AG33: =IF(OR($A33="",AF33<MIN_OBS_ROLL),"",SUMPRODUCT(AA5:AA32,(AB5:AB32-SUMPRODUCT(AA5:AA32,AB5:AB32)/AF33)^2)/(AF33-1)) | AH33: =SUM(Y5:Y32) | AI33: =IF(OR($A33="",AH33<MIN_OBS_ROLL),"",SUMPRODUCT(Y5:Y32,Z5:Z32)/AH33) | AJ33: =IF(OR($A33="",AF33<MIN_OBS_ROLL),"",SUMPRODUCT(AA5:AA32,AB5:AB32)/AF33) | AK33: =IF(OR(AE33="",AG33=""),"",AE33/AG33) | AL33: =IF(OR(AI33="",AK33="",AJ33=""),"",AI33-AK33*AJ33) | AM33: =IF(AND(ISNUMBER(W33),ISNUMBER(X33),ISNUMBER(AK33),ISNUMBER(AL33)),W33-(AL33+AK33*X33),"") | AN33: =IF(ISNUMBER(AM33),1,0) | AO33: =IF(AN33=1,AM33,0) | AP33: =IF(SUM(AN31:AN33)=3,SUM(AO31:AO33),"") | AQ33: =IF(ISNUMBER(AP33),1,0) | AR33: =IF(AQ33=1,AP33,0) | AS33: =SUM(AQ$5:AQ33) | AT33: =IF(AS33>=MIN_OBS_Z,SUMPRODUCT(AQ$5:AQ33,AR$5:AR33)/AS33,"") | AU33: =IF(AS33>=MIN_OBS_Z,SQRT(SUMPRODUCT(AQ$5:AQ33,(AR$5:AR33-AT33)^2)/(AS33-1)),"") | AV33: =IF(AND(AQ33=1,ISNUMBER(AT33)),MAX(-Z_CLIP,MIN(Z_CLIP,(AR33-AT33)/AU33)),"") | AW33: =IF(ISNUMBER(AV33),-AV33,"") | AX33: =IF(ISNUMBER(AW33),1+AMPLITUD*TANH(AW33),"") | AY33: =IF($A33="","",IF(COUNT(AX31:AX33)>0,AVERAGE(AX31:AX33),"")) | AZ33: =IF(ISNUMBER(AY33),AY33-1,"") | BA33: =IF(AND(ISNUMBER(AZ32),ISNUMBER(W33)),AZ32*W_BANCOS*W33,"") | BB33: =IF(AND(ISNUMBER(AZ32),ISNUMBER(AZ31)),ABS(AZ32-AZ31)*W_BANCOS*COSTO,0) | BC33: =IF(ISNUMBER(BA33),BA33-BB33,"") | BD33: =IF(ISNUMBER(BC33),IF(A33<=FECHA_ERA,"A","B"),"") | BE33: =IF(BD33="A",BC33,"") | BF33: =IF(BD33="B",BC33,"") | BG33: =IF(AND(ISNUMBER(BC33),ISNUMBER(A33)),IF(A33>=INICIO_VIVO,1,0),0) | BH33: =IF(BG33=1,BC33,"") | BI33: =IF(ISNUMBER(AY33),ROW(),0) | BJ33: =IF(ISNUMBER(BC33),SUM(BC$5:BC33)*10000,NA()) | BK33: =IF(BG33=1,SUM(BH$5:BH33)*10000,NA()) | BL33: =IF(ISNUMBER(AY33),AY33,NA())
A34: =IF(Datos!A34="","",Datos!A34) | B34: =IF(OR($A34="",NOT(ISNUMBER(Datos!B34)),NOT(ISNUMBER(Datos!B33))),"",Datos!B34/Datos!B33-1) | C34: =IF(OR($A34="",NOT(ISNUMBER(Datos!C34)),NOT(ISNUMBER(Datos!C33))),"",Datos!C34/Datos!C33-1) | D34: =IF(OR($A34="",NOT(ISNUMBER(Datos!D34)),NOT(ISNUMBER(Datos!D33))),"",Datos!D34/Datos!D33-1) | E34: =IF(OR($A34="",NOT(ISNUMBER(Datos!E34)),NOT(ISNUMBER(Datos!E33))),"",Datos!E34/Datos!E33-1) | F34: =IF($A34="","",COUNT(B34:E34)) | G34: =IF($A34="","",IF(F34>=MIN_BANCOS,AVERAGE(B34:E34),"")) | H34: =IF(OR($A34="",NOT(ISNUMBER(Datos!F34)),NOT(ISNUMBER(Datos!F33))),"",Datos!F34/Datos!F33-1) | I34: =IF($A34="","",IF(ISNUMBER(Datos!G34),Datos!G34,I33)) | J34: =IF($A34="","",IF(ISNUMBER(I33),LN(1+I33/100/12),0)) | K34: =IF(ISNUMBER(G34),LN(1+G34)-J34,"") | L34: =IF(ISNUMBER(H34),LN(1+H34)-J34,"") | M34: =IF(ISNUMBER(K34),1,0) | N34: =IF(M34=1,K34,0) | O34: =IF(ISNUMBER(L34),1,0) | P34: =IF(O34=1,L34,0) | Q34: =M34*O34 | R34: =SUM(Q5:Q33) | S34: =IF(OR($A34="",R34<MIN_OBS_ROLL),"",(SUMPRODUCT(Q5:Q33,N5:N33,P5:P33)/R34-SUMPRODUCT(Q5:Q33,N5:N33)/R34*SUMPRODUCT(Q5:Q33,P5:P33)/R34)*R34/(R34-1)) | T34: =SUM(O5:O33) | U34: =IF(OR($A34="",T34<MIN_OBS_ROLL),"",SUMPRODUCT(O5:O33,(P5:P33-SUMPRODUCT(O5:O33,P5:P33)/T34)^2)/(T34-1)) | V34: =IF(OR(S34="",U34=""),"",S34/U34) | W34: =IF(AND(ISNUMBER(K34),ISNUMBER(L34),ISNUMBER(V34)),K34-V34*L34,"") | X34: =IF(OR($A34="",NOT(ISNUMBER(Datos!H34)),NOT(ISNUMBER(Datos!H33))),"",LN(Datos!H34)-LN(Datos!H33)) | Y34: =IF(ISNUMBER(W34),1,0) | Z34: =IF(Y34=1,W34,0) | AA34: =IF(ISNUMBER(X34),1,0) | AB34: =IF(AA34=1,X34,0) | AC34: =Y34*AA34 | AD34: =SUM(AC5:AC33) | AE34: =IF(OR($A34="",AD34<MIN_OBS_ROLL),"",(SUMPRODUCT(AC5:AC33,Z5:Z33,AB5:AB33)/AD34-SUMPRODUCT(AC5:AC33,Z5:Z33)/AD34*SUMPRODUCT(AC5:AC33,AB5:AB33)/AD34)*AD34/(AD34-1)) | AF34: =SUM(AA5:AA33) | AG34: =IF(OR($A34="",AF34<MIN_OBS_ROLL),"",SUMPRODUCT(AA5:AA33,(AB5:AB33-SUMPRODUCT(AA5:AA33,AB5:AB33)/AF34)^2)/(AF34-1)) | AH34: =SUM(Y5:Y33) | AI34: =IF(OR($A34="",AH34<MIN_OBS_ROLL),"",SUMPRODUCT(Y5:Y33,Z5:Z33)/AH34) | AJ34: =IF(OR($A34="",AF34<MIN_OBS_ROLL),"",SUMPRODUCT(AA5:AA33,AB5:AB33)/AF34) | AK34: =IF(OR(AE34="",AG34=""),"",AE34/AG34) | AL34: =IF(OR(AI34="",AK34="",AJ34=""),"",AI34-AK34*AJ34) | AM34: =IF(AND(ISNUMBER(W34),ISNUMBER(X34),ISNUMBER(AK34),ISNUMBER(AL34)),W34-(AL34+AK34*X34),"") | AN34: =IF(ISNUMBER(AM34),1,0) | AO34: =IF(AN34=1,AM34,0) | AP34: =IF(SUM(AN32:AN34)=3,SUM(AO32:AO34),"") | AQ34: =IF(ISNUMBER(AP34),1,0) | AR34: =IF(AQ34=1,AP34,0) | AS34: =SUM(AQ$5:AQ34) | AT34: =IF(AS34>=MIN_OBS_Z,SUMPRODUCT(AQ$5:AQ34,AR$5:AR34)/AS34,"") | AU34: =IF(AS34>=MIN_OBS_Z,SQRT(SUMPRODUCT(AQ$5:AQ34,(AR$5:AR34-AT34)^2)/(AS34-1)),"") | AV34: =IF(AND(AQ34=1,ISNUMBER(AT34)),MAX(-Z_CLIP,MIN(Z_CLIP,(AR34-AT34)/AU34)),"") | AW34: =IF(ISNUMBER(AV34),-AV34,"") | AX34: =IF(ISNUMBER(AW34),1+AMPLITUD*TANH(AW34),"") | AY34: =IF($A34="","",IF(COUNT(AX32:AX34)>0,AVERAGE(AX32:AX34),"")) | AZ34: =IF(ISNUMBER(AY34),AY34-1,"") | BA34: =IF(AND(ISNUMBER(AZ33),ISNUMBER(W34)),AZ33*W_BANCOS*W34,"") | BB34: =IF(AND(ISNUMBER(AZ33),ISNUMBER(AZ32)),ABS(AZ33-AZ32)*W_BANCOS*COSTO,0) | BC34: =IF(ISNUMBER(BA34),BA34-BB34,"") | BD34: =IF(ISNUMBER(BC34),IF(A34<=FECHA_ERA,"A","B"),"") | BE34: =IF(BD34="A",BC34,"") | BF34: =IF(BD34="B",BC34,"") | BG34: =IF(AND(ISNUMBER(BC34),ISNUMBER(A34)),IF(A34>=INICIO_VIVO,1,0),0) | BH34: =IF(BG34=1,BC34,"") | BI34: =IF(ISNUMBER(AY34),ROW(),0) | BJ34: =IF(ISNUMBER(BC34),SUM(BC$5:BC34)*10000,NA()) | BK34: =IF(BG34=1,SUM(BH$5:BH34)*10000,NA()) | BL34: =IF(ISNUMBER(AY34),AY34,NA())
A35: =IF(Datos!A35="","",Datos!A35) | B35: =IF(OR($A35="",NOT(ISNUMBER(Datos!B35)),NOT(ISNUMBER(Datos!B34))),"",Datos!B35/Datos!B34-1) | C35: =IF(OR($A35="",NOT(ISNUMBER(Datos!C35)),NOT(ISNUMBER(Datos!C34))),"",Datos!C35/Datos!C34-1) | D35: =IF(OR($A35="",NOT(ISNUMBER(Datos!D35)),NOT(ISNUMBER(Datos!D34))),"",Datos!D35/Datos!D34-1) | E35: =IF(OR($A35="",NOT(ISNUMBER(Datos!E35)),NOT(ISNUMBER(Datos!E34))),"",Datos!E35/Datos!E34-1) | F35: =IF($A35="","",COUNT(B35:E35)) | G35: =IF($A35="","",IF(F35>=MIN_BANCOS,AVERAGE(B35:E35),"")) | H35: =IF(OR($A35="",NOT(ISNUMBER(Datos!F35)),NOT(ISNUMBER(Datos!F34))),"",Datos!F35/Datos!F34-1) | I35: =IF($A35="","",IF(ISNUMBER(Datos!G35),Datos!G35,I34)) | J35: =IF($A35="","",IF(ISNUMBER(I34),LN(1+I34/100/12),0)) | K35: =IF(ISNUMBER(G35),LN(1+G35)-J35,"") | L35: =IF(ISNUMBER(H35),LN(1+H35)-J35,"") | M35: =IF(ISNUMBER(K35),1,0) | N35: =IF(M35=1,K35,0) | O35: =IF(ISNUMBER(L35),1,0) | P35: =IF(O35=1,L35,0) | Q35: =M35*O35 | R35: =SUM(Q5:Q34) | S35: =IF(OR($A35="",R35<MIN_OBS_ROLL),"",(SUMPRODUCT(Q5:Q34,N5:N34,P5:P34)/R35-SUMPRODUCT(Q5:Q34,N5:N34)/R35*SUMPRODUCT(Q5:Q34,P5:P34)/R35)*R35/(R35-1)) | T35: =SUM(O5:O34) | U35: =IF(OR($A35="",T35<MIN_OBS_ROLL),"",SUMPRODUCT(O5:O34,(P5:P34-SUMPRODUCT(O5:O34,P5:P34)/T35)^2)/(T35-1)) | V35: =IF(OR(S35="",U35=""),"",S35/U35) | W35: =IF(AND(ISNUMBER(K35),ISNUMBER(L35),ISNUMBER(V35)),K35-V35*L35,"") | X35: =IF(OR($A35="",NOT(ISNUMBER(Datos!H35)),NOT(ISNUMBER(Datos!H34))),"",LN(Datos!H35)-LN(Datos!H34)) | Y35: =IF(ISNUMBER(W35),1,0) | Z35: =IF(Y35=1,W35,0) | AA35: =IF(ISNUMBER(X35),1,0) | AB35: =IF(AA35=1,X35,0) | AC35: =Y35*AA35 | AD35: =SUM(AC5:AC34) | AE35: =IF(OR($A35="",AD35<MIN_OBS_ROLL),"",(SUMPRODUCT(AC5:AC34,Z5:Z34,AB5:AB34)/AD35-SUMPRODUCT(AC5:AC34,Z5:Z34)/AD35*SUMPRODUCT(AC5:AC34,AB5:AB34)/AD35)*AD35/(AD35-1)) | AF35: =SUM(AA5:AA34) | AG35: =IF(OR($A35="",AF35<MIN_OBS_ROLL),"",SUMPRODUCT(AA5:AA34,(AB5:AB34-SUMPRODUCT(AA5:AA34,AB5:AB34)/AF35)^2)/(AF35-1)) | AH35: =SUM(Y5:Y34) | AI35: =IF(OR($A35="",AH35<MIN_OBS_ROLL),"",SUMPRODUCT(Y5:Y34,Z5:Z34)/AH35) | AJ35: =IF(OR($A35="",AF35<MIN_OBS_ROLL),"",SUMPRODUCT(AA5:AA34,AB5:AB34)/AF35) | AK35: =IF(OR(AE35="",AG35=""),"",AE35/AG35) | AL35: =IF(OR(AI35="",AK35="",AJ35=""),"",AI35-AK35*AJ35) | AM35: =IF(AND(ISNUMBER(W35),ISNUMBER(X35),ISNUMBER(AK35),ISNUMBER(AL35)),W35-(AL35+AK35*X35),"") | AN35: =IF(ISNUMBER(AM35),1,0) | AO35: =IF(AN35=1,AM35,0) | AP35: =IF(SUM(AN33:AN35)=3,SUM(AO33:AO35),"") | AQ35: =IF(ISNUMBER(AP35),1,0) | AR35: =IF(AQ35=1,AP35,0) | AS35: =SUM(AQ$5:AQ35) | AT35: =IF(AS35>=MIN_OBS_Z,SUMPRODUCT(AQ$5:AQ35,AR$5:AR35)/AS35,"") | AU35: =IF(AS35>=MIN_OBS_Z,SQRT(SUMPRODUCT(AQ$5:AQ35,(AR$5:AR35-AT35)^2)/(AS35-1)),"") | AV35: =IF(AND(AQ35=1,ISNUMBER(AT35)),MAX(-Z_CLIP,MIN(Z_CLIP,(AR35-AT35)/AU35)),"") | AW35: =IF(ISNUMBER(AV35),-AV35,"") | AX35: =IF(ISNUMBER(AW35),1+AMPLITUD*TANH(AW35),"") | AY35: =IF($A35="","",IF(COUNT(AX33:AX35)>0,AVERAGE(AX33:AX35),"")) | AZ35: =IF(ISNUMBER(AY35),AY35-1,"") | BA35: =IF(AND(ISNUMBER(AZ34),ISNUMBER(W35)),AZ34*W_BANCOS*W35,"") | BB35: =IF(AND(ISNUMBER(AZ34),ISNUMBER(AZ33)),ABS(AZ34-AZ33)*W_BANCOS*COSTO,0) | BC35: =IF(ISNUMBER(BA35),BA35-BB35,"") | BD35: =IF(ISNUMBER(BC35),IF(A35<=FECHA_ERA,"A","B"),"") | BE35: =IF(BD35="A",BC35,"") | BF35: =IF(BD35="B",BC35,"") | BG35: =IF(AND(ISNUMBER(BC35),ISNUMBER(A35)),IF(A35>=INICIO_VIVO,1,0),0) | BH35: =IF(BG35=1,BC35,"") | BI35: =IF(ISNUMBER(AY35),ROW(),0) | BJ35: =IF(ISNUMBER(BC35),SUM(BC$5:BC35)*10000,NA()) | BK35: =IF(BG35=1,SUM(BH$5:BH35)*10000,NA()) | BL35: =IF(ISNUMBER(AY35),AY35,NA())
A36: =IF(Datos!A36="","",Datos!A36) | B36: =IF(OR($A36="",NOT(ISNUMBER(Datos!B36)),NOT(ISNUMBER(Datos!B35))),"",Datos!B36/Datos!B35-1) | C36: =IF(OR($A36="",NOT(ISNUMBER(Datos!C36)),NOT(ISNUMBER(Datos!C35))),"",Datos!C36/Datos!C35-1) | D36: =IF(OR($A36="",NOT(ISNUMBER(Datos!D36)),NOT(ISNUMBER(Datos!D35))),"",Datos!D36/Datos!D35-1) | E36: =IF(OR($A36="",NOT(ISNUMBER(Datos!E36)),NOT(ISNUMBER(Datos!E35))),"",Datos!E36/Datos!E35-1) | F36: =IF($A36="","",COUNT(B36:E36)) | G36: =IF($A36="","",IF(F36>=MIN_BANCOS,AVERAGE(B36:E36),"")) | H36: =IF(OR($A36="",NOT(ISNUMBER(Datos!F36)),NOT(ISNUMBER(Datos!F35))),"",Datos!F36/Datos!F35-1) | I36: =IF($A36="","",IF(ISNUMBER(Datos!G36),Datos!G36,I35)) | J36: =IF($A36="","",IF(ISNUMBER(I35),LN(1+I35/100/12),0)) | K36: =IF(ISNUMBER(G36),LN(1+G36)-J36,"") | L36: =IF(ISNUMBER(H36),LN(1+H36)-J36,"") | M36: =IF(ISNUMBER(K36),1,0) | N36: =IF(M36=1,K36,0) | O36: =IF(ISNUMBER(L36),1,0) | P36: =IF(O36=1,L36,0) | Q36: =M36*O36 | R36: =SUM(Q5:Q35) | S36: =IF(OR($A36="",R36<MIN_OBS_ROLL),"",(SUMPRODUCT(Q5:Q35,N5:N35,P5:P35)/R36-SUMPRODUCT(Q5:Q35,N5:N35)/R36*SUMPRODUCT(Q5:Q35,P5:P35)/R36)*R36/(R36-1)) | T36: =SUM(O5:O35) | U36: =IF(OR($A36="",T36<MIN_OBS_ROLL),"",SUMPRODUCT(O5:O35,(P5:P35-SUMPRODUCT(O5:O35,P5:P35)/T36)^2)/(T36-1)) | V36: =IF(OR(S36="",U36=""),"",S36/U36) | W36: =IF(AND(ISNUMBER(K36),ISNUMBER(L36),ISNUMBER(V36)),K36-V36*L36,"") | X36: =IF(OR($A36="",NOT(ISNUMBER(Datos!H36)),NOT(ISNUMBER(Datos!H35))),"",LN(Datos!H36)-LN(Datos!H35)) | Y36: =IF(ISNUMBER(W36),1,0) | Z36: =IF(Y36=1,W36,0) | AA36: =IF(ISNUMBER(X36),1,0) | AB36: =IF(AA36=1,X36,0) | AC36: =Y36*AA36 | AD36: =SUM(AC5:AC35) | AE36: =IF(OR($A36="",AD36<MIN_OBS_ROLL),"",(SUMPRODUCT(AC5:AC35,Z5:Z35,AB5:AB35)/AD36-SUMPRODUCT(AC5:AC35,Z5:Z35)/AD36*SUMPRODUCT(AC5:AC35,AB5:AB35)/AD36)*AD36/(AD36-1)) | AF36: =SUM(AA5:AA35) | AG36: =IF(OR($A36="",AF36<MIN_OBS_ROLL),"",SUMPRODUCT(AA5:AA35,(AB5:AB35-SUMPRODUCT(AA5:AA35,AB5:AB35)/AF36)^2)/(AF36-1)) | AH36: =SUM(Y5:Y35) | AI36: =IF(OR($A36="",AH36<MIN_OBS_ROLL),"",SUMPRODUCT(Y5:Y35,Z5:Z35)/AH36) | AJ36: =IF(OR($A36="",AF36<MIN_OBS_ROLL),"",SUMPRODUCT(AA5:AA35,AB5:AB35)/AF36) | AK36: =IF(OR(AE36="",AG36=""),"",AE36/AG36) | AL36: =IF(OR(AI36="",AK36="",AJ36=""),"",AI36-AK36*AJ36) | AM36: =IF(AND(ISNUMBER(W36),ISNUMBER(X36),ISNUMBER(AK36),ISNUMBER(AL36)),W36-(AL36+AK36*X36),"") | AN36: =IF(ISNUMBER(AM36),1,0) | AO36: =IF(AN36=1,AM36,0) | AP36: =IF(SUM(AN34:AN36)=3,SUM(AO34:AO36),"") | AQ36: =IF(ISNUMBER(AP36),1,0) | AR36: =IF(AQ36=1,AP36,0) | AS36: =SUM(AQ$5:AQ36) | AT36: =IF(AS36>=MIN_OBS_Z,SUMPRODUCT(AQ$5:AQ36,AR$5:AR36)/AS36,"") | AU36: =IF(AS36>=MIN_OBS_Z,SQRT(SUMPRODUCT(AQ$5:AQ36,(AR$5:AR36-AT36)^2)/(AS36-1)),"") | AV36: =IF(AND(AQ36=1,ISNUMBER(AT36)),MAX(-Z_CLIP,MIN(Z_CLIP,(AR36-AT36)/AU36)),"") | AW36: =IF(ISNUMBER(AV36),-AV36,"") | AX36: =IF(ISNUMBER(AW36),1+AMPLITUD*TANH(AW36),"") | AY36: =IF($A36="","",IF(COUNT(AX34:AX36)>0,AVERAGE(AX34:AX36),"")) | AZ36: =IF(ISNUMBER(AY36),AY36-1,"") | BA36: =IF(AND(ISNUMBER(AZ35),ISNUMBER(W36)),AZ35*W_BANCOS*W36,"") | BB36: =IF(AND(ISNUMBER(AZ35),ISNUMBER(AZ34)),ABS(AZ35-AZ34)*W_BANCOS*COSTO,0) | BC36: =IF(ISNUMBER(BA36),BA36-BB36,"") | BD36: =IF(ISNUMBER(BC36),IF(A36<=FECHA_ERA,"A","B"),"") | BE36: =IF(BD36="A",BC36,"") | BF36: =IF(BD36="B",BC36,"") | BG36: =IF(AND(ISNUMBER(BC36),ISNUMBER(A36)),IF(A36>=INICIO_VIVO,1,0),0) | BH36: =IF(BG36=1,BC36,"") | BI36: =IF(ISNUMBER(AY36),ROW(),0) | BJ36: =IF(ISNUMBER(BC36),SUM(BC$5:BC36)*10000,NA()) | BK36: =IF(BG36=1,SUM(BH$5:BH36)*10000,NA()) | BL36: =IF(ISNUMBER(AY36),AY36,NA())
A37: =IF(Datos!A37="","",Datos!A37) | B37: =IF(OR($A37="",NOT(ISNUMBER(Datos!B37)),NOT(ISNUMBER(Datos!B36))),"",Datos!B37/Datos!B36-1) | C37: =IF(OR($A37="",NOT(ISNUMBER(Datos!C37)),NOT(ISNUMBER(Datos!C36))),"",Datos!C37/Datos!C36-1) | D37: =IF(OR($A37="",NOT(ISNUMBER(Datos!D37)),NOT(ISNUMBER(Datos!D36))),"",Datos!D37/Datos!D36-1) | E37: =IF(OR($A37="",NOT(ISNUMBER(Datos!E37)),NOT(ISNUMBER(Datos!E36))),"",Datos!E37/Datos!E36-1) | F37: =IF($A37="","",COUNT(B37:E37)) | G37: =IF($A37="","",IF(F37>=MIN_BANCOS,AVERAGE(B37:E37),"")) | H37: =IF(OR($A37="",NOT(ISNUMBER(Datos!F37)),NOT(ISNUMBER(Datos!F36))),"",Datos!F37/Datos!F36-1) | I37: =IF($A37="","",IF(ISNUMBER(Datos!G37),Datos!G37,I36)) | J37: =IF($A37="","",IF(ISNUMBER(I36),LN(1+I36/100/12),0)) | K37: =IF(ISNUMBER(G37),LN(1+G37)-J37,"") | L37: =IF(ISNUMBER(H37),LN(1+H37)-J37,"") | M37: =IF(ISNUMBER(K37),1,0) | N37: =IF(M37=1,K37,0) | O37: =IF(ISNUMBER(L37),1,0) | P37: =IF(O37=1,L37,0) | Q37: =M37*O37 | R37: =SUM(Q5:Q36) | S37: =IF(OR($A37="",R37<MIN_OBS_ROLL),"",(SUMPRODUCT(Q5:Q36,N5:N36,P5:P36)/R37-SUMPRODUCT(Q5:Q36,N5:N36)/R37*SUMPRODUCT(Q5:Q36,P5:P36)/R37)*R37/(R37-1)) | T37: =SUM(O5:O36) | U37: =IF(OR($A37="",T37<MIN_OBS_ROLL),"",SUMPRODUCT(O5:O36,(P5:P36-SUMPRODUCT(O5:O36,P5:P36)/T37)^2)/(T37-1)) | V37: =IF(OR(S37="",U37=""),"",S37/U37) | W37: =IF(AND(ISNUMBER(K37),ISNUMBER(L37),ISNUMBER(V37)),K37-V37*L37,"") | X37: =IF(OR($A37="",NOT(ISNUMBER(Datos!H37)),NOT(ISNUMBER(Datos!H36))),"",LN(Datos!H37)-LN(Datos!H36)) | Y37: =IF(ISNUMBER(W37),1,0) | Z37: =IF(Y37=1,W37,0) | AA37: =IF(ISNUMBER(X37),1,0) | AB37: =IF(AA37=1,X37,0) | AC37: =Y37*AA37 | AD37: =SUM(AC5:AC36) | AE37: =IF(OR($A37="",AD37<MIN_OBS_ROLL),"",(SUMPRODUCT(AC5:AC36,Z5:Z36,AB5:AB36)/AD37-SUMPRODUCT(AC5:AC36,Z5:Z36)/AD37*SUMPRODUCT(AC5:AC36,AB5:AB36)/AD37)*AD37/(AD37-1)) | AF37: =SUM(AA5:AA36) | AG37: =IF(OR($A37="",AF37<MIN_OBS_ROLL),"",SUMPRODUCT(AA5:AA36,(AB5:AB36-SUMPRODUCT(AA5:AA36,AB5:AB36)/AF37)^2)/(AF37-1)) | AH37: =SUM(Y5:Y36) | AI37: =IF(OR($A37="",AH37<MIN_OBS_ROLL),"",SUMPRODUCT(Y5:Y36,Z5:Z36)/AH37) | AJ37: =IF(OR($A37="",AF37<MIN_OBS_ROLL),"",SUMPRODUCT(AA5:AA36,AB5:AB36)/AF37) | AK37: =IF(OR(AE37="",AG37=""),"",AE37/AG37) | AL37: =IF(OR(AI37="",AK37="",AJ37=""),"",AI37-AK37*AJ37) | AM37: =IF(AND(ISNUMBER(W37),ISNUMBER(X37),ISNUMBER(AK37),ISNUMBER(AL37)),W37-(AL37+AK37*X37),"") | AN37: =IF(ISNUMBER(AM37),1,0) | AO37: =IF(AN37=1,AM37,0) | AP37: =IF(SUM(AN35:AN37)=3,SUM(AO35:AO37),"") | AQ37: =IF(ISNUMBER(AP37),1,0) | AR37: =IF(AQ37=1,AP37,0) | AS37: =SUM(AQ$5:AQ37) | AT37: =IF(AS37>=MIN_OBS_Z,SUMPRODUCT(AQ$5:AQ37,AR$5:AR37)/AS37,"") | AU37: =IF(AS37>=MIN_OBS_Z,SQRT(SUMPRODUCT(AQ$5:AQ37,(AR$5:AR37-AT37)^2)/(AS37-1)),"") | AV37: =IF(AND(AQ37=1,ISNUMBER(AT37)),MAX(-Z_CLIP,MIN(Z_CLIP,(AR37-AT37)/AU37)),"") | AW37: =IF(ISNUMBER(AV37),-AV37,"") | AX37: =IF(ISNUMBER(AW37),1+AMPLITUD*TANH(AW37),"") | AY37: =IF($A37="","",IF(COUNT(AX35:AX37)>0,AVERAGE(AX35:AX37),"")) | AZ37: =IF(ISNUMBER(AY37),AY37-1,"") | BA37: =IF(AND(ISNUMBER(AZ36),ISNUMBER(W37)),AZ36*W_BANCOS*W37,"") | BB37: =IF(AND(ISNUMBER(AZ36),ISNUMBER(AZ35)),ABS(AZ36-AZ35)*W_BANCOS*COSTO,0) | BC37: =IF(ISNUMBER(BA37),BA37-BB37,"") | BD37: =IF(ISNUMBER(BC37),IF(A37<=FECHA_ERA,"A","B"),"") | BE37: =IF(BD37="A",BC37,"") | BF37: =IF(BD37="B",BC37,"") | BG37: =IF(AND(ISNUMBER(BC37),ISNUMBER(A37)),IF(A37>=INICIO_VIVO,1,0),0) | BH37: =IF(BG37=1,BC37,"") | BI37: =IF(ISNUMBER(AY37),ROW(),0) | BJ37: =IF(ISNUMBER(BC37),SUM(BC$5:BC37)*10000,NA()) | BK37: =IF(BG37=1,SUM(BH$5:BH37)*10000,NA()) | BL37: =IF(ISNUMBER(AY37),AY37,NA())
A38: =IF(Datos!A38="","",Datos!A38) | B38: =IF(OR($A38="",NOT(ISNUMBER(Datos!B38)),NOT(ISNUMBER(Datos!B37))),"",Datos!B38/Datos!B37-1) | C38: =IF(OR($A38="",NOT(ISNUMBER(Datos!C38)),NOT(ISNUMBER(Datos!C37))),"",Datos!C38/Datos!C37-1) | D38: =IF(OR($A38="",NOT(ISNUMBER(Datos!D38)),NOT(ISNUMBER(Datos!D37))),"",Datos!D38/Datos!D37-1) | E38: =IF(OR($A38="",NOT(ISNUMBER(Datos!E38)),NOT(ISNUMBER(Datos!E37))),"",Datos!E38/Datos!E37-1) | F38: =IF($A38="","",COUNT(B38:E38)) | G38: =IF($A38="","",IF(F38>=MIN_BANCOS,AVERAGE(B38:E38),"")) | H38: =IF(OR($A38="",NOT(ISNUMBER(Datos!F38)),NOT(ISNUMBER(Datos!F37))),"",Datos!F38/Datos!F37-1) | I38: =IF($A38="","",IF(ISNUMBER(Datos!G38),Datos!G38,I37)) | J38: =IF($A38="","",IF(ISNUMBER(I37),LN(1+I37/100/12),0)) | K38: =IF(ISNUMBER(G38),LN(1+G38)-J38,"") | L38: =IF(ISNUMBER(H38),LN(1+H38)-J38,"") | M38: =IF(ISNUMBER(K38),1,0) | N38: =IF(M38=1,K38,0) | O38: =IF(ISNUMBER(L38),1,0) | P38: =IF(O38=1,L38,0) | Q38: =M38*O38 | R38: =SUM(Q5:Q37) | S38: =IF(OR($A38="",R38<MIN_OBS_ROLL),"",(SUMPRODUCT(Q5:Q37,N5:N37,P5:P37)/R38-SUMPRODUCT(Q5:Q37,N5:N37)/R38*SUMPRODUCT(Q5:Q37,P5:P37)/R38)*R38/(R38-1)) | T38: =SUM(O5:O37) | U38: =IF(OR($A38="",T38<MIN_OBS_ROLL),"",SUMPRODUCT(O5:O37,(P5:P37-SUMPRODUCT(O5:O37,P5:P37)/T38)^2)/(T38-1)) | V38: =IF(OR(S38="",U38=""),"",S38/U38) | W38: =IF(AND(ISNUMBER(K38),ISNUMBER(L38),ISNUMBER(V38)),K38-V38*L38,"") | X38: =IF(OR($A38="",NOT(ISNUMBER(Datos!H38)),NOT(ISNUMBER(Datos!H37))),"",LN(Datos!H38)-LN(Datos!H37)) | Y38: =IF(ISNUMBER(W38),1,0) | Z38: =IF(Y38=1,W38,0) | AA38: =IF(ISNUMBER(X38),1,0) | AB38: =IF(AA38=1,X38,0) | AC38: =Y38*AA38 | AD38: =SUM(AC5:AC37) | AE38: =IF(OR($A38="",AD38<MIN_OBS_ROLL),"",(SUMPRODUCT(AC5:AC37,Z5:Z37,AB5:AB37)/AD38-SUMPRODUCT(AC5:AC37,Z5:Z37)/AD38*SUMPRODUCT(AC5:AC37,AB5:AB37)/AD38)*AD38/(AD38-1)) | AF38: =SUM(AA5:AA37) | AG38: =IF(OR($A38="",AF38<MIN_OBS_ROLL),"",SUMPRODUCT(AA5:AA37,(AB5:AB37-SUMPRODUCT(AA5:AA37,AB5:AB37)/AF38)^2)/(AF38-1)) | AH38: =SUM(Y5:Y37) | AI38: =IF(OR($A38="",AH38<MIN_OBS_ROLL),"",SUMPRODUCT(Y5:Y37,Z5:Z37)/AH38) | AJ38: =IF(OR($A38="",AF38<MIN_OBS_ROLL),"",SUMPRODUCT(AA5:AA37,AB5:AB37)/AF38) | AK38: =IF(OR(AE38="",AG38=""),"",AE38/AG38) | AL38: =IF(OR(AI38="",AK38="",AJ38=""),"",AI38-AK38*AJ38) | AM38: =IF(AND(ISNUMBER(W38),ISNUMBER(X38),ISNUMBER(AK38),ISNUMBER(AL38)),W38-(AL38+AK38*X38),"") | AN38: =IF(ISNUMBER(AM38),1,0) | AO38: =IF(AN38=1,AM38,0) | AP38: =IF(SUM(AN36:AN38)=3,SUM(AO36:AO38),"") | AQ38: =IF(ISNUMBER(AP38),1,0) | AR38: =IF(AQ38=1,AP38,0) | AS38: =SUM(AQ$5:AQ38) | AT38: =IF(AS38>=MIN_OBS_Z,SUMPRODUCT(AQ$5:AQ38,AR$5:AR38)/AS38,"") | AU38: =IF(AS38>=MIN_OBS_Z,SQRT(SUMPRODUCT(AQ$5:AQ38,(AR$5:AR38-AT38)^2)/(AS38-1)),"") | AV38: =IF(AND(AQ38=1,ISNUMBER(AT38)),MAX(-Z_CLIP,MIN(Z_CLIP,(AR38-AT38)/AU38)),"") | AW38: =IF(ISNUMBER(AV38),-AV38,"") | AX38: =IF(ISNUMBER(AW38),1+AMPLITUD*TANH(AW38),"") | AY38: =IF($A38="","",IF(COUNT(AX36:AX38)>0,AVERAGE(AX36:AX38),"")) | AZ38: =IF(ISNUMBER(AY38),AY38-1,"") | BA38: =IF(AND(ISNUMBER(AZ37),ISNUMBER(W38)),AZ37*W_BANCOS*W38,"") | BB38: =IF(AND(ISNUMBER(AZ37),ISNUMBER(AZ36)),ABS(AZ37-AZ36)*W_BANCOS*COSTO,0) | BC38: =IF(ISNUMBER(BA38),BA38-BB38,"") | BD38: =IF(ISNUMBER(BC38),IF(A38<=FECHA_ERA,"A","B"),"") | BE38: =IF(BD38="A",BC38,"") | BF38: =IF(BD38="B",BC38,"") | BG38: =IF(AND(ISNUMBER(BC38),ISNUMBER(A38)),IF(A38>=INICIO_VIVO,1,0),0) | BH38: =IF(BG38=1,BC38,"") | BI38: =IF(ISNUMBER(AY38),ROW(),0) | BJ38: =IF(ISNUMBER(BC38),SUM(BC$5:BC38)*10000,NA()) | BK38: =IF(BG38=1,SUM(BH$5:BH38)*10000,NA()) | BL38: =IF(ISNUMBER(AY38),AY38,NA())
A39: =IF(Datos!A39="","",Datos!A39) | B39: =IF(OR($A39="",NOT(ISNUMBER(Datos!B39)),NOT(ISNUMBER(Datos!B38))),"",Datos!B39/Datos!B38-1) | C39: =IF(OR($A39="",NOT(ISNUMBER(Datos!C39)),NOT(ISNUMBER(Datos!C38))),"",Datos!C39/Datos!C38-1) | D39: =IF(OR($A39="",NOT(ISNUMBER(Datos!D39)),NOT(ISNUMBER(Datos!D38))),"",Datos!D39/Datos!D38-1) | E39: =IF(OR($A39="",NOT(ISNUMBER(Datos!E39)),NOT(ISNUMBER(Datos!E38))),"",Datos!E39/Datos!E38-1) | F39: =IF($A39="","",COUNT(B39:E39)) | G39: =IF($A39="","",IF(F39>=MIN_BANCOS,AVERAGE(B39:E39),"")) | H39: =IF(OR($A39="",NOT(ISNUMBER(Datos!F39)),NOT(ISNUMBER(Datos!F38))),"",Datos!F39/Datos!F38-1) | I39: =IF($A39="","",IF(ISNUMBER(Datos!G39),Datos!G39,I38)) | J39: =IF($A39="","",IF(ISNUMBER(I38),LN(1+I38/100/12),0)) | K39: =IF(ISNUMBER(G39),LN(1+G39)-J39,"") | L39: =IF(ISNUMBER(H39),LN(1+H39)-J39,"") | M39: =IF(ISNUMBER(K39),1,0) | N39: =IF(M39=1,K39,0) | O39: =IF(ISNUMBER(L39),1,0) | P39: =IF(O39=1,L39,0) | Q39: =M39*O39 | R39: =SUM(Q5:Q38) | S39: =IF(OR($A39="",R39<MIN_OBS_ROLL),"",(SUMPRODUCT(Q5:Q38,N5:N38,P5:P38)/R39-SUMPRODUCT(Q5:Q38,N5:N38)/R39*SUMPRODUCT(Q5:Q38,P5:P38)/R39)*R39/(R39-1)) | T39: =SUM(O5:O38) | U39: =IF(OR($A39="",T39<MIN_OBS_ROLL),"",SUMPRODUCT(O5:O38,(P5:P38-SUMPRODUCT(O5:O38,P5:P38)/T39)^2)/(T39-1)) | V39: =IF(OR(S39="",U39=""),"",S39/U39) | W39: =IF(AND(ISNUMBER(K39),ISNUMBER(L39),ISNUMBER(V39)),K39-V39*L39,"") | X39: =IF(OR($A39="",NOT(ISNUMBER(Datos!H39)),NOT(ISNUMBER(Datos!H38))),"",LN(Datos!H39)-LN(Datos!H38)) | Y39: =IF(ISNUMBER(W39),1,0) | Z39: =IF(Y39=1,W39,0) | AA39: =IF(ISNUMBER(X39),1,0) | AB39: =IF(AA39=1,X39,0) | AC39: =Y39*AA39 | AD39: =SUM(AC5:AC38) | AE39: =IF(OR($A39="",AD39<MIN_OBS_ROLL),"",(SUMPRODUCT(AC5:AC38,Z5:Z38,AB5:AB38)/AD39-SUMPRODUCT(AC5:AC38,Z5:Z38)/AD39*SUMPRODUCT(AC5:AC38,AB5:AB38)/AD39)*AD39/(AD39-1)) | AF39: =SUM(AA5:AA38) | AG39: =IF(OR($A39="",AF39<MIN_OBS_ROLL),"",SUMPRODUCT(AA5:AA38,(AB5:AB38-SUMPRODUCT(AA5:AA38,AB5:AB38)/AF39)^2)/(AF39-1)) | AH39: =SUM(Y5:Y38) | AI39: =IF(OR($A39="",AH39<MIN_OBS_ROLL),"",SUMPRODUCT(Y5:Y38,Z5:Z38)/AH39) | AJ39: =IF(OR($A39="",AF39<MIN_OBS_ROLL),"",SUMPRODUCT(AA5:AA38,AB5:AB38)/AF39) | AK39: =IF(OR(AE39="",AG39=""),"",AE39/AG39) | AL39: =IF(OR(AI39="",AK39="",AJ39=""),"",AI39-AK39*AJ39) | AM39: =IF(AND(ISNUMBER(W39),ISNUMBER(X39),ISNUMBER(AK39),ISNUMBER(AL39)),W39-(AL39+AK39*X39),"") | AN39: =IF(ISNUMBER(AM39),1,0) | AO39: =IF(AN39=1,AM39,0) | AP39: =IF(SUM(AN37:AN39)=3,SUM(AO37:AO39),"") | AQ39: =IF(ISNUMBER(AP39),1,0) | AR39: =IF(AQ39=1,AP39,0) | AS39: =SUM(AQ$5:AQ39) | AT39: =IF(AS39>=MIN_OBS_Z,SUMPRODUCT(AQ$5:AQ39,AR$5:AR39)/AS39,"") | AU39: =IF(AS39>=MIN_OBS_Z,SQRT(SUMPRODUCT(AQ$5:AQ39,(AR$5:AR39-AT39)^2)/(AS39-1)),"") | AV39: =IF(AND(AQ39=1,ISNUMBER(AT39)),MAX(-Z_CLIP,MIN(Z_CLIP,(AR39-AT39)/AU39)),"") | AW39: =IF(ISNUMBER(AV39),-AV39,"") | AX39: =IF(ISNUMBER(AW39),1+AMPLITUD*TANH(AW39),"") | AY39: =IF($A39="","",IF(COUNT(AX37:AX39)>0,AVERAGE(AX37:AX39),"")) | AZ39: =IF(ISNUMBER(AY39),AY39-1,"") | BA39: =IF(AND(ISNUMBER(AZ38),ISNUMBER(W39)),AZ38*W_BANCOS*W39,"") | BB39: =IF(AND(ISNUMBER(AZ38),ISNUMBER(AZ37)),ABS(AZ38-AZ37)*W_BANCOS*COSTO,0) | BC39: =IF(ISNUMBER(BA39),BA39-BB39,"") | BD39: =IF(ISNUMBER(BC39),IF(A39<=FECHA_ERA,"A","B"),"") | BE39: =IF(BD39="A",BC39,"") | BF39: =IF(BD39="B",BC39,"") | BG39: =IF(AND(ISNUMBER(BC39),ISNUMBER(A39)),IF(A39>=INICIO_VIVO,1,0),0) | BH39: =IF(BG39=1,BC39,"") | BI39: =IF(ISNUMBER(AY39),ROW(),0) | BJ39: =IF(ISNUMBER(BC39),SUM(BC$5:BC39)*10000,NA()) | BK39: =IF(BG39=1,SUM(BH$5:BH39)*10000,NA()) | BL39: =IF(ISNUMBER(AY39),AY39,NA())
A40: =IF(Datos!A40="","",Datos!A40) | B40: =IF(OR($A40="",NOT(ISNUMBER(Datos!B40)),NOT(ISNUMBER(Datos!B39))),"",Datos!B40/Datos!B39-1) | C40: =IF(OR($A40="",NOT(ISNUMBER(Datos!C40)),NOT(ISNUMBER(Datos!C39))),"",Datos!C40/Datos!C39-1) | D40: =IF(OR($A40="",NOT(ISNUMBER(Datos!D40)),NOT(ISNUMBER(Datos!D39))),"",Datos!D40/Datos!D39-1) | E40: =IF(OR($A40="",NOT(ISNUMBER(Datos!E40)),NOT(ISNUMBER(Datos!E39))),"",Datos!E40/Datos!E39-1) | F40: =IF($A40="","",COUNT(B40:E40)) | G40: =IF($A40="","",IF(F40>=MIN_BANCOS,AVERAGE(B40:E40),"")) | H40: =IF(OR($A40="",NOT(ISNUMBER(Datos!F40)),NOT(ISNUMBER(Datos!F39))),"",Datos!F40/Datos!F39-1) | I40: =IF($A40="","",IF(ISNUMBER(Datos!G40),Datos!G40,I39)) | J40: =IF($A40="","",IF(ISNUMBER(I39),LN(1+I39/100/12),0)) | K40: =IF(ISNUMBER(G40),LN(1+G40)-J40,"") | L40: =IF(ISNUMBER(H40),LN(1+H40)-J40,"") | M40: =IF(ISNUMBER(K40),1,0) | N40: =IF(M40=1,K40,0) | O40: =IF(ISNUMBER(L40),1,0) | P40: =IF(O40=1,L40,0) | Q40: =M40*O40 | R40: =SUM(Q5:Q39) | S40: =IF(OR($A40="",R40<MIN_OBS_ROLL),"",(SUMPRODUCT(Q5:Q39,N5:N39,P5:P39)/R40-SUMPRODUCT(Q5:Q39,N5:N39)/R40*SUMPRODUCT(Q5:Q39,P5:P39)/R40)*R40/(R40-1)) | T40: =SUM(O5:O39) | U40: =IF(OR($A40="",T40<MIN_OBS_ROLL),"",SUMPRODUCT(O5:O39,(P5:P39-SUMPRODUCT(O5:O39,P5:P39)/T40)^2)/(T40-1)) | V40: =IF(OR(S40="",U40=""),"",S40/U40) | W40: =IF(AND(ISNUMBER(K40),ISNUMBER(L40),ISNUMBER(V40)),K40-V40*L40,"") | X40: =IF(OR($A40="",NOT(ISNUMBER(Datos!H40)),NOT(ISNUMBER(Datos!H39))),"",LN(Datos!H40)-LN(Datos!H39)) | Y40: =IF(ISNUMBER(W40),1,0) | Z40: =IF(Y40=1,W40,0) | AA40: =IF(ISNUMBER(X40),1,0) | AB40: =IF(AA40=1,X40,0) | AC40: =Y40*AA40 | AD40: =SUM(AC5:AC39) | AE40: =IF(OR($A40="",AD40<MIN_OBS_ROLL),"",(SUMPRODUCT(AC5:AC39,Z5:Z39,AB5:AB39)/AD40-SUMPRODUCT(AC5:AC39,Z5:Z39)/AD40*SUMPRODUCT(AC5:AC39,AB5:AB39)/AD40)*AD40/(AD40-1)) | AF40: =SUM(AA5:AA39) | AG40: =IF(OR($A40="",AF40<MIN_OBS_ROLL),"",SUMPRODUCT(AA5:AA39,(AB5:AB39-SUMPRODUCT(AA5:AA39,AB5:AB39)/AF40)^2)/(AF40-1)) | AH40: =SUM(Y5:Y39) | AI40: =IF(OR($A40="",AH40<MIN_OBS_ROLL),"",SUMPRODUCT(Y5:Y39,Z5:Z39)/AH40) | AJ40: =IF(OR($A40="",AF40<MIN_OBS_ROLL),"",SUMPRODUCT(AA5:AA39,AB5:AB39)/AF40) | AK40: =IF(OR(AE40="",AG40=""),"",AE40/AG40) | AL40: =IF(OR(AI40="",AK40="",AJ40=""),"",AI40-AK40*AJ40) | AM40: =IF(AND(ISNUMBER(W40),ISNUMBER(X40),ISNUMBER(AK40),ISNUMBER(AL40)),W40-(AL40+AK40*X40),"") | AN40: =IF(ISNUMBER(AM40),1,0) | AO40: =IF(AN40=1,AM40,0) | AP40: =IF(SUM(AN38:AN40)=3,SUM(AO38:AO40),"") | AQ40: =IF(ISNUMBER(AP40),1,0) | AR40: =IF(AQ40=1,AP40,0) | AS40: =SUM(AQ$5:AQ40) | AT40: =IF(AS40>=MIN_OBS_Z,SUMPRODUCT(AQ$5:AQ40,AR$5:AR40)/AS40,"") | AU40: =IF(AS40>=MIN_OBS_Z,SQRT(SUMPRODUCT(AQ$5:AQ40,(AR$5:AR40-AT40)^2)/(AS40-1)),"") | AV40: =IF(AND(AQ40=1,ISNUMBER(AT40)),MAX(-Z_CLIP,MIN(Z_CLIP,(AR40-AT40)/AU40)),"") | AW40: =IF(ISNUMBER(AV40),-AV40,"") | AX40: =IF(ISNUMBER(AW40),1+AMPLITUD*TANH(AW40),"") | AY40: =IF($A40="","",IF(COUNT(AX38:AX40)>0,AVERAGE(AX38:AX40),"")) | AZ40: =IF(ISNUMBER(AY40),AY40-1,"") | BA40: =IF(AND(ISNUMBER(AZ39),ISNUMBER(W40)),AZ39*W_BANCOS*W40,"") | BB40: =IF(AND(ISNUMBER(AZ39),ISNUMBER(AZ38)),ABS(AZ39-AZ38)*W_BANCOS*COSTO,0) | BC40: =IF(ISNUMBER(BA40),BA40-BB40,"") | BD40: =IF(ISNUMBER(BC40),IF(A40<=FECHA_ERA,"A","B"),"") | BE40: =IF(BD40="A",BC40,"") | BF40: =IF(BD40="B",BC40,"") | BG40: =IF(AND(ISNUMBER(BC40),ISNUMBER(A40)),IF(A40>=INICIO_VIVO,1,0),0) | BH40: =IF(BG40=1,BC40,"") | BI40: =IF(ISNUMBER(AY40),ROW(),0) | BJ40: =IF(ISNUMBER(BC40),SUM(BC$5:BC40)*10000,NA()) | BK40: =IF(BG40=1,SUM(BH$5:BH40)*10000,NA()) | BL40: =IF(ISNUMBER(AY40),AY40,NA())
A41: =IF(Datos!A41="","",Datos!A41) | B41: =IF(OR($A41="",NOT(ISNUMBER(Datos!B41)),NOT(ISNUMBER(Datos!B40))),"",Datos!B41/Datos!B40-1) | C41: =IF(OR($A41="",NOT(ISNUMBER(Datos!C41)),NOT(ISNUMBER(Datos!C40))),"",Datos!C41/Datos!C40-1) | D41: =IF(OR($A41="",NOT(ISNUMBER(Datos!D41)),NOT(ISNUMBER(Datos!D40))),"",Datos!D41/Datos!D40-1) | E41: =IF(OR($A41="",NOT(ISNUMBER(Datos!E41)),NOT(ISNUMBER(Datos!E40))),"",Datos!E41/Datos!E40-1) | F41: =IF($A41="","",COUNT(B41:E41)) | G41: =IF($A41="","",IF(F41>=MIN_BANCOS,AVERAGE(B41:E41),"")) | H41: =IF(OR($A41="",NOT(ISNUMBER(Datos!F41)),NOT(ISNUMBER(Datos!F40))),"",Datos!F41/Datos!F40-1) | I41: =IF($A41="","",IF(ISNUMBER(Datos!G41),Datos!G41,I40)) | J41: =IF($A41="","",IF(ISNUMBER(I40),LN(1+I40/100/12),0)) | K41: =IF(ISNUMBER(G41),LN(1+G41)-J41,"") | L41: =IF(ISNUMBER(H41),LN(1+H41)-J41,"") | M41: =IF(ISNUMBER(K41),1,0) | N41: =IF(M41=1,K41,0) | O41: =IF(ISNUMBER(L41),1,0) | P41: =IF(O41=1,L41,0) | Q41: =M41*O41 | R41: =SUM(Q5:Q40) | S41: =IF(OR($A41="",R41<MIN_OBS_ROLL),"",(SUMPRODUCT(Q5:Q40,N5:N40,P5:P40)/R41-SUMPRODUCT(Q5:Q40,N5:N40)/R41*SUMPRODUCT(Q5:Q40,P5:P40)/R41)*R41/(R41-1)) | T41: =SUM(O5:O40) | U41: =IF(OR($A41="",T41<MIN_OBS_ROLL),"",SUMPRODUCT(O5:O40,(P5:P40-SUMPRODUCT(O5:O40,P5:P40)/T41)^2)/(T41-1)) | V41: =IF(OR(S41="",U41=""),"",S41/U41) | W41: =IF(AND(ISNUMBER(K41),ISNUMBER(L41),ISNUMBER(V41)),K41-V41*L41,"") | X41: =IF(OR($A41="",NOT(ISNUMBER(Datos!H41)),NOT(ISNUMBER(Datos!H40))),"",LN(Datos!H41)-LN(Datos!H40)) | Y41: =IF(ISNUMBER(W41),1,0) | Z41: =IF(Y41=1,W41,0) | AA41: =IF(ISNUMBER(X41),1,0) | AB41: =IF(AA41=1,X41,0) | AC41: =Y41*AA41 | AD41: =SUM(AC5:AC40) | AE41: =IF(OR($A41="",AD41<MIN_OBS_ROLL),"",(SUMPRODUCT(AC5:AC40,Z5:Z40,AB5:AB40)/AD41-SUMPRODUCT(AC5:AC40,Z5:Z40)/AD41*SUMPRODUCT(AC5:AC40,AB5:AB40)/AD41)*AD41/(AD41-1)) | AF41: =SUM(AA5:AA40) | AG41: =IF(OR($A41="",AF41<MIN_OBS_ROLL),"",SUMPRODUCT(AA5:AA40,(AB5:AB40-SUMPRODUCT(AA5:AA40,AB5:AB40)/AF41)^2)/(AF41-1)) | AH41: =SUM(Y5:Y40) | AI41: =IF(OR($A41="",AH41<MIN_OBS_ROLL),"",SUMPRODUCT(Y5:Y40,Z5:Z40)/AH41) | AJ41: =IF(OR($A41="",AF41<MIN_OBS_ROLL),"",SUMPRODUCT(AA5:AA40,AB5:AB40)/AF41) | AK41: =IF(OR(AE41="",AG41=""),"",AE41/AG41) | AL41: =IF(OR(AI41="",AK41="",AJ41=""),"",AI41-AK41*AJ41) | AM41: =IF(AND(ISNUMBER(W41),ISNUMBER(X41),ISNUMBER(AK41),ISNUMBER(AL41)),W41-(AL41+AK41*X41),"") | AN41: =IF(ISNUMBER(AM41),1,0) | AO41: =IF(AN41=1,AM41,0) | AP41: =IF(SUM(AN39:AN41)=3,SUM(AO39:AO41),"") | AQ41: =IF(ISNUMBER(AP41),1,0) | AR41: =IF(AQ41=1,AP41,0) | AS41: =SUM(AQ$5:AQ41) | AT41: =IF(AS41>=MIN_OBS_Z,SUMPRODUCT(AQ$5:AQ41,AR$5:AR41)/AS41,"") | AU41: =IF(AS41>=MIN_OBS_Z,SQRT(SUMPRODUCT(AQ$5:AQ41,(AR$5:AR41-AT41)^2)/(AS41-1)),"") | AV41: =IF(AND(AQ41=1,ISNUMBER(AT41)),MAX(-Z_CLIP,MIN(Z_CLIP,(AR41-AT41)/AU41)),"") | AW41: =IF(ISNUMBER(AV41),-AV41,"") | AX41: =IF(ISNUMBER(AW41),1+AMPLITUD*TANH(AW41),"") | AY41: =IF($A41="","",IF(COUNT(AX39:AX41)>0,AVERAGE(AX39:AX41),"")) | AZ41: =IF(ISNUMBER(AY41),AY41-1,"") | BA41: =IF(AND(ISNUMBER(AZ40),ISNUMBER(W41)),AZ40*W_BANCOS*W41,"") | BB41: =IF(AND(ISNUMBER(AZ40),ISNUMBER(AZ39)),ABS(AZ40-AZ39)*W_BANCOS*COSTO,0) | BC41: =IF(ISNUMBER(BA41),BA41-BB41,"") | BD41: =IF(ISNUMBER(BC41),IF(A41<=FECHA_ERA,"A","B"),"") | BE41: =IF(BD41="A",BC41,"") | BF41: =IF(BD41="B",BC41,"") | BG41: =IF(AND(ISNUMBER(BC41),ISNUMBER(A41)),IF(A41>=INICIO_VIVO,1,0),0) | BH41: =IF(BG41=1,BC41,"") | BI41: =IF(ISNUMBER(AY41),ROW(),0) | BJ41: =IF(ISNUMBER(BC41),SUM(BC$5:BC41)*10000,NA()) | BK41: =IF(BG41=1,SUM(BH$5:BH41)*10000,NA()) | BL41: =IF(ISNUMBER(AY41),AY41,NA())
A42: =IF(Datos!A42="","",Datos!A42) | B42: =IF(OR($A42="",NOT(ISNUMBER(Datos!B42)),NOT(ISNUMBER(Datos!B41))),"",Datos!B42/Datos!B41-1) | C42: =IF(OR($A42="",NOT(ISNUMBER(Datos!C42)),NOT(ISNUMBER(Datos!C41))),"",Datos!C42/Datos!C41-1) | D42: =IF(OR($A42="",NOT(ISNUMBER(Datos!D42)),NOT(ISNUMBER(Datos!D41))),"",Datos!D42/Datos!D41-1) | E42: =IF(OR($A42="",NOT(ISNUMBER(Datos!E42)),NOT(ISNUMBER(Datos!E41))),"",Datos!E42/Datos!E41-1) | F42: =IF($A42="","",COUNT(B42:E42)) | G42: =IF($A42="","",IF(F42>=MIN_BANCOS,AVERAGE(B42:E42),"")) | H42: =IF(OR($A42="",NOT(ISNUMBER(Datos!F42)),NOT(ISNUMBER(Datos!F41))),"",Datos!F42/Datos!F41-1) | I42: =IF($A42="","",IF(ISNUMBER(Datos!G42),Datos!G42,I41)) | J42: =IF($A42="","",IF(ISNUMBER(I41),LN(1+I41/100/12),0)) | K42: =IF(ISNUMBER(G42),LN(1+G42)-J42,"") | L42: =IF(ISNUMBER(H42),LN(1+H42)-J42,"") | M42: =IF(ISNUMBER(K42),1,0) | N42: =IF(M42=1,K42,0) | O42: =IF(ISNUMBER(L42),1,0) | P42: =IF(O42=1,L42,0) | Q42: =M42*O42 | R42: =SUM(Q6:Q41) | S42: =IF(OR($A42="",R42<MIN_OBS_ROLL),"",(SUMPRODUCT(Q6:Q41,N6:N41,P6:P41)/R42-SUMPRODUCT(Q6:Q41,N6:N41)/R42*SUMPRODUCT(Q6:Q41,P6:P41)/R42)*R42/(R42-1)) | T42: =SUM(O6:O41) | U42: =IF(OR($A42="",T42<MIN_OBS_ROLL),"",SUMPRODUCT(O6:O41,(P6:P41-SUMPRODUCT(O6:O41,P6:P41)/T42)^2)/(T42-1)) | V42: =IF(OR(S42="",U42=""),"",S42/U42) | W42: =IF(AND(ISNUMBER(K42),ISNUMBER(L42),ISNUMBER(V42)),K42-V42*L42,"") | X42: =IF(OR($A42="",NOT(ISNUMBER(Datos!H42)),NOT(ISNUMBER(Datos!H41))),"",LN(Datos!H42)-LN(Datos!H41)) | Y42: =IF(ISNUMBER(W42),1,0) | Z42: =IF(Y42=1,W42,0) | AA42: =IF(ISNUMBER(X42),1,0) | AB42: =IF(AA42=1,X42,0) | AC42: =Y42*AA42 | AD42: =SUM(AC6:AC41) | AE42: =IF(OR($A42="",AD42<MIN_OBS_ROLL),"",(SUMPRODUCT(AC6:AC41,Z6:Z41,AB6:AB41)/AD42-SUMPRODUCT(AC6:AC41,Z6:Z41)/AD42*SUMPRODUCT(AC6:AC41,AB6:AB41)/AD42)*AD42/(AD42-1)) | AF42: =SUM(AA6:AA41) | AG42: =IF(OR($A42="",AF42<MIN_OBS_ROLL),"",SUMPRODUCT(AA6:AA41,(AB6:AB41-SUMPRODUCT(AA6:AA41,AB6:AB41)/AF42)^2)/(AF42-1)) | AH42: =SUM(Y6:Y41) | AI42: =IF(OR($A42="",AH42<MIN_OBS_ROLL),"",SUMPRODUCT(Y6:Y41,Z6:Z41)/AH42) | AJ42: =IF(OR($A42="",AF42<MIN_OBS_ROLL),"",SUMPRODUCT(AA6:AA41,AB6:AB41)/AF42) | AK42: =IF(OR(AE42="",AG42=""),"",AE42/AG42) | AL42: =IF(OR(AI42="",AK42="",AJ42=""),"",AI42-AK42*AJ42) | AM42: =IF(AND(ISNUMBER(W42),ISNUMBER(X42),ISNUMBER(AK42),ISNUMBER(AL42)),W42-(AL42+AK42*X42),"") | AN42: =IF(ISNUMBER(AM42),1,0) | AO42: =IF(AN42=1,AM42,0) | AP42: =IF(SUM(AN40:AN42)=3,SUM(AO40:AO42),"") | AQ42: =IF(ISNUMBER(AP42),1,0) | AR42: =IF(AQ42=1,AP42,0) | AS42: =SUM(AQ$5:AQ42) | AT42: =IF(AS42>=MIN_OBS_Z,SUMPRODUCT(AQ$5:AQ42,AR$5:AR42)/AS42,"") | AU42: =IF(AS42>=MIN_OBS_Z,SQRT(SUMPRODUCT(AQ$5:AQ42,(AR$5:AR42-AT42)^2)/(AS42-1)),"") | AV42: =IF(AND(AQ42=1,ISNUMBER(AT42)),MAX(-Z_CLIP,MIN(Z_CLIP,(AR42-AT42)/AU42)),"") | AW42: =IF(ISNUMBER(AV42),-AV42,"") | AX42: =IF(ISNUMBER(AW42),1+AMPLITUD*TANH(AW42),"") | AY42: =IF($A42="","",IF(COUNT(AX40:AX42)>0,AVERAGE(AX40:AX42),"")) | AZ42: =IF(ISNUMBER(AY42),AY42-1,"") | BA42: =IF(AND(ISNUMBER(AZ41),ISNUMBER(W42)),AZ41*W_BANCOS*W42,"") | BB42: =IF(AND(ISNUMBER(AZ41),ISNUMBER(AZ40)),ABS(AZ41-AZ40)*W_BANCOS*COSTO,0) | BC42: =IF(ISNUMBER(BA42),BA42-BB42,"") | BD42: =IF(ISNUMBER(BC42),IF(A42<=FECHA_ERA,"A","B"),"") | BE42: =IF(BD42="A",BC42,"") | BF42: =IF(BD42="B",BC42,"") | BG42: =IF(AND(ISNUMBER(BC42),ISNUMBER(A42)),IF(A42>=INICIO_VIVO,1,0),0) | BH42: =IF(BG42=1,BC42,"") | BI42: =IF(ISNUMBER(AY42),ROW(),0) | BJ42: =IF(ISNUMBER(BC42),SUM(BC$5:BC42)*10000,NA()) | BK42: =IF(BG42=1,SUM(BH$5:BH42)*10000,NA()) | BL42: =IF(ISNUMBER(AY42),AY42,NA())
A43: =IF(Datos!A43="","",Datos!A43) | B43: =IF(OR($A43="",NOT(ISNUMBER(Datos!B43)),NOT(ISNUMBER(Datos!B42))),"",Datos!B43/Datos!B42-1) | C43: =IF(OR($A43="",NOT(ISNUMBER(Datos!C43)),NOT(ISNUMBER(Datos!C42))),"",Datos!C43/Datos!C42-1) | D43: =IF(OR($A43="",NOT(ISNUMBER(Datos!D43)),NOT(ISNUMBER(Datos!D42))),"",Datos!D43/Datos!D42-1) | E43: =IF(OR($A43="",NOT(ISNUMBER(Datos!E43)),NOT(ISNUMBER(Datos!E42))),"",Datos!E43/Datos!E42-1) | F43: =IF($A43="","",COUNT(B43:E43)) | G43: =IF($A43="","",IF(F43>=MIN_BANCOS,AVERAGE(B43:E43),"")) | H43: =IF(OR($A43="",NOT(ISNUMBER(Datos!F43)),NOT(ISNUMBER(Datos!F42))),"",Datos!F43/Datos!F42-1) | I43: =IF($A43="","",IF(ISNUMBER(Datos!G43),Datos!G43,I42)) | J43: =IF($A43="","",IF(ISNUMBER(I42),LN(1+I42/100/12),0)) | K43: =IF(ISNUMBER(G43),LN(1+G43)-J43,"") | L43: =IF(ISNUMBER(H43),LN(1+H43)-J43,"") | M43: =IF(ISNUMBER(K43),1,0) | N43: =IF(M43=1,K43,0) | O43: =IF(ISNUMBER(L43),1,0) | P43: =IF(O43=1,L43,0) | Q43: =M43*O43 | R43: =SUM(Q7:Q42) | S43: =IF(OR($A43="",R43<MIN_OBS_ROLL),"",(SUMPRODUCT(Q7:Q42,N7:N42,P7:P42)/R43-SUMPRODUCT(Q7:Q42,N7:N42)/R43*SUMPRODUCT(Q7:Q42,P7:P42)/R43)*R43/(R43-1)) | T43: =SUM(O7:O42) | U43: =IF(OR($A43="",T43<MIN_OBS_ROLL),"",SUMPRODUCT(O7:O42,(P7:P42-SUMPRODUCT(O7:O42,P7:P42)/T43)^2)/(T43-1)) | V43: =IF(OR(S43="",U43=""),"",S43/U43) | W43: =IF(AND(ISNUMBER(K43),ISNUMBER(L43),ISNUMBER(V43)),K43-V43*L43,"") | X43: =IF(OR($A43="",NOT(ISNUMBER(Datos!H43)),NOT(ISNUMBER(Datos!H42))),"",LN(Datos!H43)-LN(Datos!H42)) | Y43: =IF(ISNUMBER(W43),1,0) | Z43: =IF(Y43=1,W43,0) | AA43: =IF(ISNUMBER(X43),1,0) | AB43: =IF(AA43=1,X43,0) | AC43: =Y43*AA43 | AD43: =SUM(AC7:AC42) | AE43: =IF(OR($A43="",AD43<MIN_OBS_ROLL),"",(SUMPRODUCT(AC7:AC42,Z7:Z42,AB7:AB42)/AD43-SUMPRODUCT(AC7:AC42,Z7:Z42)/AD43*SUMPRODUCT(AC7:AC42,AB7:AB42)/AD43)*AD43/(AD43-1)) | AF43: =SUM(AA7:AA42) | AG43: =IF(OR($A43="",AF43<MIN_OBS_ROLL),"",SUMPRODUCT(AA7:AA42,(AB7:AB42-SUMPRODUCT(AA7:AA42,AB7:AB42)/AF43)^2)/(AF43-1)) | AH43: =SUM(Y7:Y42) | AI43: =IF(OR($A43="",AH43<MIN_OBS_ROLL),"",SUMPRODUCT(Y7:Y42,Z7:Z42)/AH43) | AJ43: =IF(OR($A43="",AF43<MIN_OBS_ROLL),"",SUMPRODUCT(AA7:AA42,AB7:AB42)/AF43) | AK43: =IF(OR(AE43="",AG43=""),"",AE43/AG43) | AL43: =IF(OR(AI43="",AK43="",AJ43=""),"",AI43-AK43*AJ43) | AM43: =IF(AND(ISNUMBER(W43),ISNUMBER(X43),ISNUMBER(AK43),ISNUMBER(AL43)),W43-(AL43+AK43*X43),"") | AN43: =IF(ISNUMBER(AM43),1,0) | AO43: =IF(AN43=1,AM43,0) | AP43: =IF(SUM(AN41:AN43)=3,SUM(AO41:AO43),"") | AQ43: =IF(ISNUMBER(AP43),1,0) | AR43: =IF(AQ43=1,AP43,0) | AS43: =SUM(AQ$5:AQ43) | AT43: =IF(AS43>=MIN_OBS_Z,SUMPRODUCT(AQ$5:AQ43,AR$5:AR43)/AS43,"") | AU43: =IF(AS43>=MIN_OBS_Z,SQRT(SUMPRODUCT(AQ$5:AQ43,(AR$5:AR43-AT43)^2)/(AS43-1)),"") | AV43: =IF(AND(AQ43=1,ISNUMBER(AT43)),MAX(-Z_CLIP,MIN(Z_CLIP,(AR43-AT43)/AU43)),"") | AW43: =IF(ISNUMBER(AV43),-AV43,"") | AX43: =IF(ISNUMBER(AW43),1+AMPLITUD*TANH(AW43),"") | AY43: =IF($A43="","",IF(COUNT(AX41:AX43)>0,AVERAGE(AX41:AX43),"")) | AZ43: =IF(ISNUMBER(AY43),AY43-1,"") | BA43: =IF(AND(ISNUMBER(AZ42),ISNUMBER(W43)),AZ42*W_BANCOS*W43,"") | BB43: =IF(AND(ISNUMBER(AZ42),ISNUMBER(AZ41)),ABS(AZ42-AZ41)*W_BANCOS*COSTO,0) | BC43: =IF(ISNUMBER(BA43),BA43-BB43,"") | BD43: =IF(ISNUMBER(BC43),IF(A43<=FECHA_ERA,"A","B"),"") | BE43: =IF(BD43="A",BC43,"") | BF43: =IF(BD43="B",BC43,"") | BG43: =IF(AND(ISNUMBER(BC43),ISNUMBER(A43)),IF(A43>=INICIO_VIVO,1,0),0) | BH43: =IF(BG43=1,BC43,"") | BI43: =IF(ISNUMBER(AY43),ROW(),0) | BJ43: =IF(ISNUMBER(BC43),SUM(BC$5:BC43)*10000,NA()) | BK43: =IF(BG43=1,SUM(BH$5:BH43)*10000,NA()) | BL43: =IF(ISNUMBER(AY43),AY43,NA())
A44: =IF(Datos!A44="","",Datos!A44) | B44: =IF(OR($A44="",NOT(ISNUMBER(Datos!B44)),NOT(ISNUMBER(Datos!B43))),"",Datos!B44/Datos!B43-1) | C44: =IF(OR($A44="",NOT(ISNUMBER(Datos!C44)),NOT(ISNUMBER(Datos!C43))),"",Datos!C44/Datos!C43-1) | D44: =IF(OR($A44="",NOT(ISNUMBER(Datos!D44)),NOT(ISNUMBER(Datos!D43))),"",Datos!D44/Datos!D43-1) | E44: =IF(OR($A44="",NOT(ISNUMBER(Datos!E44)),NOT(ISNUMBER(Datos!E43))),"",Datos!E44/Datos!E43-1) | F44: =IF($A44="","",COUNT(B44:E44)) | G44: =IF($A44="","",IF(F44>=MIN_BANCOS,AVERAGE(B44:E44),"")) | H44: =IF(OR($A44="",NOT(ISNUMBER(Datos!F44)),NOT(ISNUMBER(Datos!F43))),"",Datos!F44/Datos!F43-1) | I44: =IF($A44="","",IF(ISNUMBER(Datos!G44),Datos!G44,I43)) | J44: =IF($A44="","",IF(ISNUMBER(I43),LN(1+I43/100/12),0)) | K44: =IF(ISNUMBER(G44),LN(1+G44)-J44,"") | L44: =IF(ISNUMBER(H44),LN(1+H44)-J44,"") | M44: =IF(ISNUMBER(K44),1,0) | N44: =IF(M44=1,K44,0) | O44: =IF(ISNUMBER(L44),1,0) | P44: =IF(O44=1,L44,0) | Q44: =M44*O44 | R44: =SUM(Q8:Q43) | S44: =IF(OR($A44="",R44<MIN_OBS_ROLL),"",(SUMPRODUCT(Q8:Q43,N8:N43,P8:P43)/R44-SUMPRODUCT(Q8:Q43,N8:N43)/R44*SUMPRODUCT(Q8:Q43,P8:P43)/R44)*R44/(R44-1)) | T44: =SUM(O8:O43) | U44: =IF(OR($A44="",T44<MIN_OBS_ROLL),"",SUMPRODUCT(O8:O43,(P8:P43-SUMPRODUCT(O8:O43,P8:P43)/T44)^2)/(T44-1)) | V44: =IF(OR(S44="",U44=""),"",S44/U44) | W44: =IF(AND(ISNUMBER(K44),ISNUMBER(L44),ISNUMBER(V44)),K44-V44*L44,"") | X44: =IF(OR($A44="",NOT(ISNUMBER(Datos!H44)),NOT(ISNUMBER(Datos!H43))),"",LN(Datos!H44)-LN(Datos!H43)) | Y44: =IF(ISNUMBER(W44),1,0) | Z44: =IF(Y44=1,W44,0) | AA44: =IF(ISNUMBER(X44),1,0) | AB44: =IF(AA44=1,X44,0) | AC44: =Y44*AA44 | AD44: =SUM(AC8:AC43) | AE44: =IF(OR($A44="",AD44<MIN_OBS_ROLL),"",(SUMPRODUCT(AC8:AC43,Z8:Z43,AB8:AB43)/AD44-SUMPRODUCT(AC8:AC43,Z8:Z43)/AD44*SUMPRODUCT(AC8:AC43,AB8:AB43)/AD44)*AD44/(AD44-1)) | AF44: =SUM(AA8:AA43) | AG44: =IF(OR($A44="",AF44<MIN_OBS_ROLL),"",SUMPRODUCT(AA8:AA43,(AB8:AB43-SUMPRODUCT(AA8:AA43,AB8:AB43)/AF44)^2)/(AF44-1)) | AH44: =SUM(Y8:Y43) | AI44: =IF(OR($A44="",AH44<MIN_OBS_ROLL),"",SUMPRODUCT(Y8:Y43,Z8:Z43)/AH44) | AJ44: =IF(OR($A44="",AF44<MIN_OBS_ROLL),"",SUMPRODUCT(AA8:AA43,AB8:AB43)/AF44) | AK44: =IF(OR(AE44="",AG44=""),"",AE44/AG44) | AL44: =IF(OR(AI44="",AK44="",AJ44=""),"",AI44-AK44*AJ44) | AM44: =IF(AND(ISNUMBER(W44),ISNUMBER(X44),ISNUMBER(AK44),ISNUMBER(AL44)),W44-(AL44+AK44*X44),"") | AN44: =IF(ISNUMBER(AM44),1,0) | AO44: =IF(AN44=1,AM44,0) | AP44: =IF(SUM(AN42:AN44)=3,SUM(AO42:AO44),"") | AQ44: =IF(ISNUMBER(AP44),1,0) | AR44: =IF(AQ44=1,AP44,0) | AS44: =SUM(AQ$5:AQ44) | AT44: =IF(AS44>=MIN_OBS_Z,SUMPRODUCT(AQ$5:AQ44,AR$5:AR44)/AS44,"") | AU44: =IF(AS44>=MIN_OBS_Z,SQRT(SUMPRODUCT(AQ$5:AQ44,(AR$5:AR44-AT44)^2)/(AS44-1)),"") | AV44: =IF(AND(AQ44=1,ISNUMBER(AT44)),MAX(-Z_CLIP,MIN(Z_CLIP,(AR44-AT44)/AU44)),"") | AW44: =IF(ISNUMBER(AV44),-AV44,"") | AX44: =IF(ISNUMBER(AW44),1+AMPLITUD*TANH(AW44),"") | AY44: =IF($A44="","",IF(COUNT(AX42:AX44)>0,AVERAGE(AX42:AX44),"")) | AZ44: =IF(ISNUMBER(AY44),AY44-1,"") | BA44: =IF(AND(ISNUMBER(AZ43),ISNUMBER(W44)),AZ43*W_BANCOS*W44,"") | BB44: =IF(AND(ISNUMBER(AZ43),ISNUMBER(AZ42)),ABS(AZ43-AZ42)*W_BANCOS*COSTO,0) | BC44: =IF(ISNUMBER(BA44),BA44-BB44,"") | BD44: =IF(ISNUMBER(BC44),IF(A44<=FECHA_ERA,"A","B"),"") | BE44: =IF(BD44="A",BC44,"") | BF44: =IF(BD44="B",BC44,"") | BG44: =IF(AND(ISNUMBER(BC44),ISNUMBER(A44)),IF(A44>=INICIO_VIVO,1,0),0) | BH44: =IF(BG44=1,BC44,"") | BI44: =IF(ISNUMBER(AY44),ROW(),0) | BJ44: =IF(ISNUMBER(BC44),SUM(BC$5:BC44)*10000,NA()) | BK44: =IF(BG44=1,SUM(BH$5:BH44)*10000,NA()) | BL44: =IF(ISNUMBER(AY44),AY44,NA())
A45: =IF(Datos!A45="","",Datos!A45) | B45: =IF(OR($A45="",NOT(ISNUMBER(Datos!B45)),NOT(ISNUMBER(Datos!B44))),"",Datos!B45/Datos!B44-1) | C45: =IF(OR($A45="",NOT(ISNUMBER(Datos!C45)),NOT(ISNUMBER(Datos!C44))),"",Datos!C45/Datos!C44-1) | D45: =IF(OR($A45="",NOT(ISNUMBER(Datos!D45)),NOT(ISNUMBER(Datos!D44))),"",Datos!D45/Datos!D44-1) | E45: =IF(OR($A45="",NOT(ISNUMBER(Datos!E45)),NOT(ISNUMBER(Datos!E44))),"",Datos!E45/Datos!E44-1) | F45: =IF($A45="","",COUNT(B45:E45)) | G45: =IF($A45="","",IF(F45>=MIN_BANCOS,AVERAGE(B45:E45),"")) | H45: =IF(OR($A45="",NOT(ISNUMBER(Datos!F45)),NOT(ISNUMBER(Datos!F44))),"",Datos!F45/Datos!F44-1) | I45: =IF($A45="","",IF(ISNUMBER(Datos!G45),Datos!G45,I44)) | J45: =IF($A45="","",IF(ISNUMBER(I44),LN(1+I44/100/12),0)) | K45: =IF(ISNUMBER(G45),LN(1+G45)-J45,"") | L45: =IF(ISNUMBER(H45),LN(1+H45)-J45,"") | M45: =IF(ISNUMBER(K45),1,0) | N45: =IF(M45=1,K45,0) | O45: =IF(ISNUMBER(L45),1,0) | P45: =IF(O45=1,L45,0) | Q45: =M45*O45 | R45: =SUM(Q9:Q44) | S45: =IF(OR($A45="",R45<MIN_OBS_ROLL),"",(SUMPRODUCT(Q9:Q44,N9:N44,P9:P44)/R45-SUMPRODUCT(Q9:Q44,N9:N44)/R45*SUMPRODUCT(Q9:Q44,P9:P44)/R45)*R45/(R45-1)) | T45: =SUM(O9:O44) | U45: =IF(OR($A45="",T45<MIN_OBS_ROLL),"",SUMPRODUCT(O9:O44,(P9:P44-SUMPRODUCT(O9:O44,P9:P44)/T45)^2)/(T45-1)) | V45: =IF(OR(S45="",U45=""),"",S45/U45) | W45: =IF(AND(ISNUMBER(K45),ISNUMBER(L45),ISNUMBER(V45)),K45-V45*L45,"") | X45: =IF(OR($A45="",NOT(ISNUMBER(Datos!H45)),NOT(ISNUMBER(Datos!H44))),"",LN(Datos!H45)-LN(Datos!H44)) | Y45: =IF(ISNUMBER(W45),1,0) | Z45: =IF(Y45=1,W45,0) | AA45: =IF(ISNUMBER(X45),1,0) | AB45: =IF(AA45=1,X45,0) | AC45: =Y45*AA45 | AD45: =SUM(AC9:AC44) | AE45: =IF(OR($A45="",AD45<MIN_OBS_ROLL),"",(SUMPRODUCT(AC9:AC44,Z9:Z44,AB9:AB44)/AD45-SUMPRODUCT(AC9:AC44,Z9:Z44)/AD45*SUMPRODUCT(AC9:AC44,AB9:AB44)/AD45)*AD45/(AD45-1)) | AF45: =SUM(AA9:AA44) | AG45: =IF(OR($A45="",AF45<MIN_OBS_ROLL),"",SUMPRODUCT(AA9:AA44,(AB9:AB44-SUMPRODUCT(AA9:AA44,AB9:AB44)/AF45)^2)/(AF45-1)) | AH45: =SUM(Y9:Y44) | AI45: =IF(OR($A45="",AH45<MIN_OBS_ROLL),"",SUMPRODUCT(Y9:Y44,Z9:Z44)/AH45) | AJ45: =IF(OR($A45="",AF45<MIN_OBS_ROLL),"",SUMPRODUCT(AA9:AA44,AB9:AB44)/AF45) | AK45: =IF(OR(AE45="",AG45=""),"",AE45/AG45) | AL45: =IF(OR(AI45="",AK45="",AJ45=""),"",AI45-AK45*AJ45) | AM45: =IF(AND(ISNUMBER(W45),ISNUMBER(X45),ISNUMBER(AK45),ISNUMBER(AL45)),W45-(AL45+AK45*X45),"") | AN45: =IF(ISNUMBER(AM45),1,0) | AO45: =IF(AN45=1,AM45,0) | AP45: =IF(SUM(AN43:AN45)=3,SUM(AO43:AO45),"") | AQ45: =IF(ISNUMBER(AP45),1,0) | AR45: =IF(AQ45=1,AP45,0) | AS45: =SUM(AQ$5:AQ45) | AT45: =IF(AS45>=MIN_OBS_Z,SUMPRODUCT(AQ$5:AQ45,AR$5:AR45)/AS45,"") | AU45: =IF(AS45>=MIN_OBS_Z,SQRT(SUMPRODUCT(AQ$5:AQ45,(AR$5:AR45-AT45)^2)/(AS45-1)),"") | AV45: =IF(AND(AQ45=1,ISNUMBER(AT45)),MAX(-Z_CLIP,MIN(Z_CLIP,(AR45-AT45)/AU45)),"") | AW45: =IF(ISNUMBER(AV45),-AV45,"") | AX45: =IF(ISNUMBER(AW45),1+AMPLITUD*TANH(AW45),"") | AY45: =IF($A45="","",IF(COUNT(AX43:AX45)>0,AVERAGE(AX43:AX45),"")) | AZ45: =IF(ISNUMBER(AY45),AY45-1,"") | BA45: =IF(AND(ISNUMBER(AZ44),ISNUMBER(W45)),AZ44*W_BANCOS*W45,"") | BB45: =IF(AND(ISNUMBER(AZ44),ISNUMBER(AZ43)),ABS(AZ44-AZ43)*W_BANCOS*COSTO,0) | BC45: =IF(ISNUMBER(BA45),BA45-BB45,"") | BD45: =IF(ISNUMBER(BC45),IF(A45<=FECHA_ERA,"A","B"),"") | BE45: =IF(BD45="A",BC45,"") | BF45: =IF(BD45="B",BC45,"") | BG45: =IF(AND(ISNUMBER(BC45),ISNUMBER(A45)),IF(A45>=INICIO_VIVO,1,0),0) | BH45: =IF(BG45=1,BC45,"") | BI45: =IF(ISNUMBER(AY45),ROW(),0) | BJ45: =IF(ISNUMBER(BC45),SUM(BC$5:BC45)*10000,NA()) | BK45: =IF(BG45=1,SUM(BH$5:BH45)*10000,NA()) | BL45: =IF(ISNUMBER(AY45),AY45,NA())
A46: =IF(Datos!A46="","",Datos!A46) | B46: =IF(OR($A46="",NOT(ISNUMBER(Datos!B46)),NOT(ISNUMBER(Datos!B45))),"",Datos!B46/Datos!B45-1) | C46: =IF(OR($A46="",NOT(ISNUMBER(Datos!C46)),NOT(ISNUMBER(Datos!C45))),"",Datos!C46/Datos!C45-1) | D46: =IF(OR($A46="",NOT(ISNUMBER(Datos!D46)),NOT(ISNUMBER(Datos!D45))),"",Datos!D46/Datos!D45-1) | E46: =IF(OR($A46="",NOT(ISNUMBER(Datos!E46)),NOT(ISNUMBER(Datos!E45))),"",Datos!E46/Datos!E45-1) | F46: =IF($A46="","",COUNT(B46:E46)) | G46: =IF($A46="","",IF(F46>=MIN_BANCOS,AVERAGE(B46:E46),"")) | H46: =IF(OR($A46="",NOT(ISNUMBER(Datos!F46)),NOT(ISNUMBER(Datos!F45))),"",Datos!F46/Datos!F45-1) | I46: =IF($A46="","",IF(ISNUMBER(Datos!G46),Datos!G46,I45)) | J46: =IF($A46="","",IF(ISNUMBER(I45),LN(1+I45/100/12),0)) | K46: =IF(ISNUMBER(G46),LN(1+G46)-J46,"") | L46: =IF(ISNUMBER(H46),LN(1+H46)-J46,"") | M46: =IF(ISNUMBER(K46),1,0) | N46: =IF(M46=1,K46,0) | O46: =IF(ISNUMBER(L46),1,0) | P46: =IF(O46=1,L46,0) | Q46: =M46*O46 | R46: =SUM(Q10:Q45) | S46: =IF(OR($A46="",R46<MIN_OBS_ROLL),"",(SUMPRODUCT(Q10:Q45,N10:N45,P10:P45)/R46-SUMPRODUCT(Q10:Q45,N10:N45)/R46*SUMPRODUCT(Q10:Q45,P10:P45)/R46)*R46/(R46-1)) | T46: =SUM(O10:O45) | U46: =IF(OR($A46="",T46<MIN_OBS_ROLL),"",SUMPRODUCT(O10:O45,(P10:P45-SUMPRODUCT(O10:O45,P10:P45)/T46)^2)/(T46-1)) | V46: =IF(OR(S46="",U46=""),"",S46/U46) | W46: =IF(AND(ISNUMBER(K46),ISNUMBER(L46),ISNUMBER(V46)),K46-V46*L46,"") | X46: =IF(OR($A46="",NOT(ISNUMBER(Datos!H46)),NOT(ISNUMBER(Datos!H45))),"",LN(Datos!H46)-LN(Datos!H45)) | Y46: =IF(ISNUMBER(W46),1,0) | Z46: =IF(Y46=1,W46,0) | AA46: =IF(ISNUMBER(X46),1,0) | AB46: =IF(AA46=1,X46,0) | AC46: =Y46*AA46 | AD46: =SUM(AC10:AC45) | AE46: =IF(OR($A46="",AD46<MIN_OBS_ROLL),"",(SUMPRODUCT(AC10:AC45,Z10:Z45,AB10:AB45)/AD46-SUMPRODUCT(AC10:AC45,Z10:Z45)/AD46*SUMPRODUCT(AC10:AC45,AB10:AB45)/AD46)*AD46/(AD46-1)) | AF46: =SUM(AA10:AA45) | AG46: =IF(OR($A46="",AF46<MIN_OBS_ROLL),"",SUMPRODUCT(AA10:AA45,(AB10:AB45-SUMPRODUCT(AA10:AA45,AB10:AB45)/AF46)^2)/(AF46-1)) | AH46: =SUM(Y10:Y45) | AI46: =IF(OR($A46="",AH46<MIN_OBS_ROLL),"",SUMPRODUCT(Y10:Y45,Z10:Z45)/AH46) | AJ46: =IF(OR($A46="",AF46<MIN_OBS_ROLL),"",SUMPRODUCT(AA10:AA45,AB10:AB45)/AF46) | AK46: =IF(OR(AE46="",AG46=""),"",AE46/AG46) | AL46: =IF(OR(AI46="",AK46="",AJ46=""),"",AI46-AK46*AJ46) | AM46: =IF(AND(ISNUMBER(W46),ISNUMBER(X46),ISNUMBER(AK46),ISNUMBER(AL46)),W46-(AL46+AK46*X46),"") | AN46: =IF(ISNUMBER(AM46),1,0) | AO46: =IF(AN46=1,AM46,0) | AP46: =IF(SUM(AN44:AN46)=3,SUM(AO44:AO46),"") | AQ46: =IF(ISNUMBER(AP46),1,0) | AR46: =IF(AQ46=1,AP46,0) | AS46: =SUM(AQ$5:AQ46) | AT46: =IF(AS46>=MIN_OBS_Z,SUMPRODUCT(AQ$5:AQ46,AR$5:AR46)/AS46,"") | AU46: =IF(AS46>=MIN_OBS_Z,SQRT(SUMPRODUCT(AQ$5:AQ46,(AR$5:AR46-AT46)^2)/(AS46-1)),"") | AV46: =IF(AND(AQ46=1,ISNUMBER(AT46)),MAX(-Z_CLIP,MIN(Z_CLIP,(AR46-AT46)/AU46)),"") | AW46: =IF(ISNUMBER(AV46),-AV46,"") | AX46: =IF(ISNUMBER(AW46),1+AMPLITUD*TANH(AW46),"") | AY46: =IF($A46="","",IF(COUNT(AX44:AX46)>0,AVERAGE(AX44:AX46),"")) | AZ46: =IF(ISNUMBER(AY46),AY46-1,"") | BA46: =IF(AND(ISNUMBER(AZ45),ISNUMBER(W46)),AZ45*W_BANCOS*W46,"") | BB46: =IF(AND(ISNUMBER(AZ45),ISNUMBER(AZ44)),ABS(AZ45-AZ44)*W_BANCOS*COSTO,0) | BC46: =IF(ISNUMBER(BA46),BA46-BB46,"") | BD46: =IF(ISNUMBER(BC46),IF(A46<=FECHA_ERA,"A","B"),"") | BE46: =IF(BD46="A",BC46,"") | BF46: =IF(BD46="B",BC46,"") | BG46: =IF(AND(ISNUMBER(BC46),ISNUMBER(A46)),IF(A46>=INICIO_VIVO,1,0),0) | BH46: =IF(BG46=1,BC46,"") | BI46: =IF(ISNUMBER(AY46),ROW(),0) | BJ46: =IF(ISNUMBER(BC46),SUM(BC$5:BC46)*10000,NA()) | BK46: =IF(BG46=1,SUM(BH$5:BH46)*10000,NA()) | BL46: =IF(ISNUMBER(AY46),AY46,NA())
A47: =IF(Datos!A47="","",Datos!A47) | B47: =IF(OR($A47="",NOT(ISNUMBER(Datos!B47)),NOT(ISNUMBER(Datos!B46))),"",Datos!B47/Datos!B46-1) | C47: =IF(OR($A47="",NOT(ISNUMBER(Datos!C47)),NOT(ISNUMBER(Datos!C46))),"",Datos!C47/Datos!C46-1) | D47: =IF(OR($A47="",NOT(ISNUMBER(Datos!D47)),NOT(ISNUMBER(Datos!D46))),"",Datos!D47/Datos!D46-1) | E47: =IF(OR($A47="",NOT(ISNUMBER(Datos!E47)),NOT(ISNUMBER(Datos!E46))),"",Datos!E47/Datos!E46-1) | F47: =IF($A47="","",COUNT(B47:E47)) | G47: =IF($A47="","",IF(F47>=MIN_BANCOS,AVERAGE(B47:E47),"")) | H47: =IF(OR($A47="",NOT(ISNUMBER(Datos!F47)),NOT(ISNUMBER(Datos!F46))),"",Datos!F47/Datos!F46-1) | I47: =IF($A47="","",IF(ISNUMBER(Datos!G47),Datos!G47,I46)) | J47: =IF($A47="","",IF(ISNUMBER(I46),LN(1+I46/100/12),0)) | K47: =IF(ISNUMBER(G47),LN(1+G47)-J47,"") | L47: =IF(ISNUMBER(H47),LN(1+H47)-J47,"") | M47: =IF(ISNUMBER(K47),1,0) | N47: =IF(M47=1,K47,0) | O47: =IF(ISNUMBER(L47),1,0) | P47: =IF(O47=1,L47,0) | Q47: =M47*O47 | R47: =SUM(Q11:Q46) | S47: =IF(OR($A47="",R47<MIN_OBS_ROLL),"",(SUMPRODUCT(Q11:Q46,N11:N46,P11:P46)/R47-SUMPRODUCT(Q11:Q46,N11:N46)/R47*SUMPRODUCT(Q11:Q46,P11:P46)/R47)*R47/(R47-1)) | T47: =SUM(O11:O46) | U47: =IF(OR($A47="",T47<MIN_OBS_ROLL),"",SUMPRODUCT(O11:O46,(P11:P46-SUMPRODUCT(O11:O46,P11:P46)/T47)^2)/(T47-1)) | V47: =IF(OR(S47="",U47=""),"",S47/U47) | W47: =IF(AND(ISNUMBER(K47),ISNUMBER(L47),ISNUMBER(V47)),K47-V47*L47,"") | X47: =IF(OR($A47="",NOT(ISNUMBER(Datos!H47)),NOT(ISNUMBER(Datos!H46))),"",LN(Datos!H47)-LN(Datos!H46)) | Y47: =IF(ISNUMBER(W47),1,0) | Z47: =IF(Y47=1,W47,0) | AA47: =IF(ISNUMBER(X47),1,0) | AB47: =IF(AA47=1,X47,0) | AC47: =Y47*AA47 | AD47: =SUM(AC11:AC46) | AE47: =IF(OR($A47="",AD47<MIN_OBS_ROLL),"",(SUMPRODUCT(AC11:AC46,Z11:Z46,AB11:AB46)/AD47-SUMPRODUCT(AC11:AC46,Z11:Z46)/AD47*SUMPRODUCT(AC11:AC46,AB11:AB46)/AD47)*AD47/(AD47-1)) | AF47: =SUM(AA11:AA46) | AG47: =IF(OR($A47="",AF47<MIN_OBS_ROLL),"",SUMPRODUCT(AA11:AA46,(AB11:AB46-SUMPRODUCT(AA11:AA46,AB11:AB46)/AF47)^2)/(AF47-1)) | AH47: =SUM(Y11:Y46) | AI47: =IF(OR($A47="",AH47<MIN_OBS_ROLL),"",SUMPRODUCT(Y11:Y46,Z11:Z46)/AH47) | AJ47: =IF(OR($A47="",AF47<MIN_OBS_ROLL),"",SUMPRODUCT(AA11:AA46,AB11:AB46)/AF47) | AK47: =IF(OR(AE47="",AG47=""),"",AE47/AG47) | AL47: =IF(OR(AI47="",AK47="",AJ47=""),"",AI47-AK47*AJ47) | AM47: =IF(AND(ISNUMBER(W47),ISNUMBER(X47),ISNUMBER(AK47),ISNUMBER(AL47)),W47-(AL47+AK47*X47),"") | AN47: =IF(ISNUMBER(AM47),1,0) | AO47: =IF(AN47=1,AM47,0) | AP47: =IF(SUM(AN45:AN47)=3,SUM(AO45:AO47),"") | AQ47: =IF(ISNUMBER(AP47),1,0) | AR47: =IF(AQ47=1,AP47,0) | AS47: =SUM(AQ$5:AQ47) | AT47: =IF(AS47>=MIN_OBS_Z,SUMPRODUCT(AQ$5:AQ47,AR$5:AR47)/AS47,"") | AU47: =IF(AS47>=MIN_OBS_Z,SQRT(SUMPRODUCT(AQ$5:AQ47,(AR$5:AR47-AT47)^2)/(AS47-1)),"") | AV47: =IF(AND(AQ47=1,ISNUMBER(AT47)),MAX(-Z_CLIP,MIN(Z_CLIP,(AR47-AT47)/AU47)),"") | AW47: =IF(ISNUMBER(AV47),-AV47,"") | AX47: =IF(ISNUMBER(AW47),1+AMPLITUD*TANH(AW47),"") | AY47: =IF($A47="","",IF(COUNT(AX45:AX47)>0,AVERAGE(AX45:AX47),"")) | AZ47: =IF(ISNUMBER(AY47),AY47-1,"") | BA47: =IF(AND(ISNUMBER(AZ46),ISNUMBER(W47)),AZ46*W_BANCOS*W47,"") | BB47: =IF(AND(ISNUMBER(AZ46),ISNUMBER(AZ45)),ABS(AZ46-AZ45)*W_BANCOS*COSTO,0) | BC47: =IF(ISNUMBER(BA47),BA47-BB47,"") | BD47: =IF(ISNUMBER(BC47),IF(A47<=FECHA_ERA,"A","B"),"") | BE47: =IF(BD47="A",BC47,"") | BF47: =IF(BD47="B",BC47,"") | BG47: =IF(AND(ISNUMBER(BC47),ISNUMBER(A47)),IF(A47>=INICIO_VIVO,1,0),0) | BH47: =IF(BG47=1,BC47,"") | BI47: =IF(ISNUMBER(AY47),ROW(),0) | BJ47: =IF(ISNUMBER(BC47),SUM(BC$5:BC47)*10000,NA()) | BK47: =IF(BG47=1,SUM(BH$5:BH47)*10000,NA()) | BL47: =IF(ISNUMBER(AY47),AY47,NA())
A48: =IF(Datos!A48="","",Datos!A48) | B48: =IF(OR($A48="",NOT(ISNUMBER(Datos!B48)),NOT(ISNUMBER(Datos!B47))),"",Datos!B48/Datos!B47-1) | C48: =IF(OR($A48="",NOT(ISNUMBER(Datos!C48)),NOT(ISNUMBER(Datos!C47))),"",Datos!C48/Datos!C47-1) | D48: =IF(OR($A48="",NOT(ISNUMBER(Datos!D48)),NOT(ISNUMBER(Datos!D47))),"",Datos!D48/Datos!D47-1) | E48: =IF(OR($A48="",NOT(ISNUMBER(Datos!E48)),NOT(ISNUMBER(Datos!E47))),"",Datos!E48/Datos!E47-1) | F48: =IF($A48="","",COUNT(B48:E48)) | G48: =IF($A48="","",IF(F48>=MIN_BANCOS,AVERAGE(B48:E48),"")) | H48: =IF(OR($A48="",NOT(ISNUMBER(Datos!F48)),NOT(ISNUMBER(Datos!F47))),"",Datos!F48/Datos!F47-1) | I48: =IF($A48="","",IF(ISNUMBER(Datos!G48),Datos!G48,I47)) | J48: =IF($A48="","",IF(ISNUMBER(I47),LN(1+I47/100/12),0)) | K48: =IF(ISNUMBER(G48),LN(1+G48)-J48,"") | L48: =IF(ISNUMBER(H48),LN(1+H48)-J48,"") | M48: =IF(ISNUMBER(K48),1,0) | N48: =IF(M48=1,K48,0) | O48: =IF(ISNUMBER(L48),1,0) | P48: =IF(O48=1,L48,0) | Q48: =M48*O48 | R48: =SUM(Q12:Q47) | S48: =IF(OR($A48="",R48<MIN_OBS_ROLL),"",(SUMPRODUCT(Q12:Q47,N12:N47,P12:P47)/R48-SUMPRODUCT(Q12:Q47,N12:N47)/R48*SUMPRODUCT(Q12:Q47,P12:P47)/R48)*R48/(R48-1)) | T48: =SUM(O12:O47) | U48: =IF(OR($A48="",T48<MIN_OBS_ROLL),"",SUMPRODUCT(O12:O47,(P12:P47-SUMPRODUCT(O12:O47,P12:P47)/T48)^2)/(T48-1)) | V48: =IF(OR(S48="",U48=""),"",S48/U48) | W48: =IF(AND(ISNUMBER(K48),ISNUMBER(L48),ISNUMBER(V48)),K48-V48*L48,"") | X48: =IF(OR($A48="",NOT(ISNUMBER(Datos!H48)),NOT(ISNUMBER(Datos!H47))),"",LN(Datos!H48)-LN(Datos!H47)) | Y48: =IF(ISNUMBER(W48),1,0) | Z48: =IF(Y48=1,W48,0) | AA48: =IF(ISNUMBER(X48),1,0) | AB48: =IF(AA48=1,X48,0) | AC48: =Y48*AA48 | AD48: =SUM(AC12:AC47) | AE48: =IF(OR($A48="",AD48<MIN_OBS_ROLL),"",(SUMPRODUCT(AC12:AC47,Z12:Z47,AB12:AB47)/AD48-SUMPRODUCT(AC12:AC47,Z12:Z47)/AD48*SUMPRODUCT(AC12:AC47,AB12:AB47)/AD48)*AD48/(AD48-1)) | AF48: =SUM(AA12:AA47) | AG48: =IF(OR($A48="",AF48<MIN_OBS_ROLL),"",SUMPRODUCT(AA12:AA47,(AB12:AB47-SUMPRODUCT(AA12:AA47,AB12:AB47)/AF48)^2)/(AF48-1)) | AH48: =SUM(Y12:Y47) | AI48: =IF(OR($A48="",AH48<MIN_OBS_ROLL),"",SUMPRODUCT(Y12:Y47,Z12:Z47)/AH48) | AJ48: =IF(OR($A48="",AF48<MIN_OBS_ROLL),"",SUMPRODUCT(AA12:AA47,AB12:AB47)/AF48) | AK48: =IF(OR(AE48="",AG48=""),"",AE48/AG48) | AL48: =IF(OR(AI48="",AK48="",AJ48=""),"",AI48-AK48*AJ48) | AM48: =IF(AND(ISNUMBER(W48),ISNUMBER(X48),ISNUMBER(AK48),ISNUMBER(AL48)),W48-(AL48+AK48*X48),"") | AN48: =IF(ISNUMBER(AM48),1,0) | AO48: =IF(AN48=1,AM48,0) | AP48: =IF(SUM(AN46:AN48)=3,SUM(AO46:AO48),"") | AQ48: =IF(ISNUMBER(AP48),1,0) | AR48: =IF(AQ48=1,AP48,0) | AS48: =SUM(AQ$5:AQ48) | AT48: =IF(AS48>=MIN_OBS_Z,SUMPRODUCT(AQ$5:AQ48,AR$5:AR48)/AS48,"") | AU48: =IF(AS48>=MIN_OBS_Z,SQRT(SUMPRODUCT(AQ$5:AQ48,(AR$5:AR48-AT48)^2)/(AS48-1)),"") | AV48: =IF(AND(AQ48=1,ISNUMBER(AT48)),MAX(-Z_CLIP,MIN(Z_CLIP,(AR48-AT48)/AU48)),"") | AW48: =IF(ISNUMBER(AV48),-AV48,"") | AX48: =IF(ISNUMBER(AW48),1+AMPLITUD*TANH(AW48),"") | AY48: =IF($A48="","",IF(COUNT(AX46:AX48)>0,AVERAGE(AX46:AX48),"")) | AZ48: =IF(ISNUMBER(AY48),AY48-1,"") | BA48: =IF(AND(ISNUMBER(AZ47),ISNUMBER(W48)),AZ47*W_BANCOS*W48,"") | BB48: =IF(AND(ISNUMBER(AZ47),ISNUMBER(AZ46)),ABS(AZ47-AZ46)*W_BANCOS*COSTO,0) | BC48: =IF(ISNUMBER(BA48),BA48-BB48,"") | BD48: =IF(ISNUMBER(BC48),IF(A48<=FECHA_ERA,"A","B"),"") | BE48: =IF(BD48="A",BC48,"") | BF48: =IF(BD48="B",BC48,"") | BG48: =IF(AND(ISNUMBER(BC48),ISNUMBER(A48)),IF(A48>=INICIO_VIVO,1,0),0) | BH48: =IF(BG48=1,BC48,"") | BI48: =IF(ISNUMBER(AY48),ROW(),0) | BJ48: =IF(ISNUMBER(BC48),SUM(BC$5:BC48)*10000,NA()) | BK48: =IF(BG48=1,SUM(BH$5:BH48)*10000,NA()) | BL48: =IF(ISNUMBER(AY48),AY48,NA())
A49: =IF(Datos!A49="","",Datos!A49) | B49: =IF(OR($A49="",NOT(ISNUMBER(Datos!B49)),NOT(ISNUMBER(Datos!B48))),"",Datos!B49/Datos!B48-1) | C49: =IF(OR($A49="",NOT(ISNUMBER(Datos!C49)),NOT(ISNUMBER(Datos!C48))),"",Datos!C49/Datos!C48-1) | D49: =IF(OR($A49="",NOT(ISNUMBER(Datos!D49)),NOT(ISNUMBER(Datos!D48))),"",Datos!D49/Datos!D48-1) | E49: =IF(OR($A49="",NOT(ISNUMBER(Datos!E49)),NOT(ISNUMBER(Datos!E48))),"",Datos!E49/Datos!E48-1) | F49: =IF($A49="","",COUNT(B49:E49)) | G49: =IF($A49="","",IF(F49>=MIN_BANCOS,AVERAGE(B49:E49),"")) | H49: =IF(OR($A49="",NOT(ISNUMBER(Datos!F49)),NOT(ISNUMBER(Datos!F48))),"",Datos!F49/Datos!F48-1) | I49: =IF($A49="","",IF(ISNUMBER(Datos!G49),Datos!G49,I48)) | J49: =IF($A49="","",IF(ISNUMBER(I48),LN(1+I48/100/12),0)) | K49: =IF(ISNUMBER(G49),LN(1+G49)-J49,"") | L49: =IF(ISNUMBER(H49),LN(1+H49)-J49,"") | M49: =IF(ISNUMBER(K49),1,0) | N49: =IF(M49=1,K49,0) | O49: =IF(ISNUMBER(L49),1,0) | P49: =IF(O49=1,L49,0) | Q49: =M49*O49 | R49: =SUM(Q13:Q48) | S49: =IF(OR($A49="",R49<MIN_OBS_ROLL),"",(SUMPRODUCT(Q13:Q48,N13:N48,P13:P48)/R49-SUMPRODUCT(Q13:Q48,N13:N48)/R49*SUMPRODUCT(Q13:Q48,P13:P48)/R49)*R49/(R49-1)) | T49: =SUM(O13:O48) | U49: =IF(OR($A49="",T49<MIN_OBS_ROLL),"",SUMPRODUCT(O13:O48,(P13:P48-SUMPRODUCT(O13:O48,P13:P48)/T49)^2)/(T49-1)) | V49: =IF(OR(S49="",U49=""),"",S49/U49) | W49: =IF(AND(ISNUMBER(K49),ISNUMBER(L49),ISNUMBER(V49)),K49-V49*L49,"") | X49: =IF(OR($A49="",NOT(ISNUMBER(Datos!H49)),NOT(ISNUMBER(Datos!H48))),"",LN(Datos!H49)-LN(Datos!H48)) | Y49: =IF(ISNUMBER(W49),1,0) | Z49: =IF(Y49=1,W49,0) | AA49: =IF(ISNUMBER(X49),1,0) | AB49: =IF(AA49=1,X49,0) | AC49: =Y49*AA49 | AD49: =SUM(AC13:AC48) | AE49: =IF(OR($A49="",AD49<MIN_OBS_ROLL),"",(SUMPRODUCT(AC13:AC48,Z13:Z48,AB13:AB48)/AD49-SUMPRODUCT(AC13:AC48,Z13:Z48)/AD49*SUMPRODUCT(AC13:AC48,AB13:AB48)/AD49)*AD49/(AD49-1)) | AF49: =SUM(AA13:AA48) | AG49: =IF(OR($A49="",AF49<MIN_OBS_ROLL),"",SUMPRODUCT(AA13:AA48,(AB13:AB48-SUMPRODUCT(AA13:AA48,AB13:AB48)/AF49)^2)/(AF49-1)) | AH49: =SUM(Y13:Y48) | AI49: =IF(OR($A49="",AH49<MIN_OBS_ROLL),"",SUMPRODUCT(Y13:Y48,Z13:Z48)/AH49) | AJ49: =IF(OR($A49="",AF49<MIN_OBS_ROLL),"",SUMPRODUCT(AA13:AA48,AB13:AB48)/AF49) | AK49: =IF(OR(AE49="",AG49=""),"",AE49/AG49) | AL49: =IF(OR(AI49="",AK49="",AJ49=""),"",AI49-AK49*AJ49) | AM49: =IF(AND(ISNUMBER(W49),ISNUMBER(X49),ISNUMBER(AK49),ISNUMBER(AL49)),W49-(AL49+AK49*X49),"") | AN49: =IF(ISNUMBER(AM49),1,0) | AO49: =IF(AN49=1,AM49,0) | AP49: =IF(SUM(AN47:AN49)=3,SUM(AO47:AO49),"") | AQ49: =IF(ISNUMBER(AP49),1,0) | AR49: =IF(AQ49=1,AP49,0) | AS49: =SUM(AQ$5:AQ49) | AT49: =IF(AS49>=MIN_OBS_Z,SUMPRODUCT(AQ$5:AQ49,AR$5:AR49)/AS49,"") | AU49: =IF(AS49>=MIN_OBS_Z,SQRT(SUMPRODUCT(AQ$5:AQ49,(AR$5:AR49-AT49)^2)/(AS49-1)),"") | AV49: =IF(AND(AQ49=1,ISNUMBER(AT49)),MAX(-Z_CLIP,MIN(Z_CLIP,(AR49-AT49)/AU49)),"") | AW49: =IF(ISNUMBER(AV49),-AV49,"") | AX49: =IF(ISNUMBER(AW49),1+AMPLITUD*TANH(AW49),"") | AY49: =IF($A49="","",IF(COUNT(AX47:AX49)>0,AVERAGE(AX47:AX49),"")) | AZ49: =IF(ISNUMBER(AY49),AY49-1,"") | BA49: =IF(AND(ISNUMBER(AZ48),ISNUMBER(W49)),AZ48*W_BANCOS*W49,"") | BB49: =IF(AND(ISNUMBER(AZ48),ISNUMBER(AZ47)),ABS(AZ48-AZ47)*W_BANCOS*COSTO,0) | BC49: =IF(ISNUMBER(BA49),BA49-BB49,"") | BD49: =IF(ISNUMBER(BC49),IF(A49<=FECHA_ERA,"A","B"),"") | BE49: =IF(BD49="A",BC49,"") | BF49: =IF(BD49="B",BC49,"") | BG49: =IF(AND(ISNUMBER(BC49),ISNUMBER(A49)),IF(A49>=INICIO_VIVO,1,0),0) | BH49: =IF(BG49=1,BC49,"") | BI49: =IF(ISNUMBER(AY49),ROW(),0) | BJ49: =IF(ISNUMBER(BC49),SUM(BC$5:BC49)*10000,NA()) | BK49: =IF(BG49=1,SUM(BH$5:BH49)*10000,NA()) | BL49: =IF(ISNUMBER(AY49),AY49,NA())
A50: =IF(Datos!A50="","",Datos!A50) | B50: =IF(OR($A50="",NOT(ISNUMBER(Datos!B50)),NOT(ISNUMBER(Datos!B49))),"",Datos!B50/Datos!B49-1) | C50: =IF(OR($A50="",NOT(ISNUMBER(Datos!C50)),NOT(ISNUMBER(Datos!C49))),"",Datos!C50/Datos!C49-1) | D50: =IF(OR($A50="",NOT(ISNUMBER(Datos!D50)),NOT(ISNUMBER(Datos!D49))),"",Datos!D50/Datos!D49-1) | E50: =IF(OR($A50="",NOT(ISNUMBER(Datos!E50)),NOT(ISNUMBER(Datos!E49))),"",Datos!E50/Datos!E49-1) | F50: =IF($A50="","",COUNT(B50:E50)) | G50: =IF($A50="","",IF(F50>=MIN_BANCOS,AVERAGE(B50:E50),"")) | H50: =IF(OR($A50="",NOT(ISNUMBER(Datos!F50)),NOT(ISNUMBER(Datos!F49))),"",Datos!F50/Datos!F49-1) | I50: =IF($A50="","",IF(ISNUMBER(Datos!G50),Datos!G50,I49)) | J50: =IF($A50="","",IF(ISNUMBER(I49),LN(1+I49/100/12),0)) | K50: =IF(ISNUMBER(G50),LN(1+G50)-J50,"") | L50: =IF(ISNUMBER(H50),LN(1+H50)-J50,"") | M50: =IF(ISNUMBER(K50),1,0) | N50: =IF(M50=1,K50,0) | O50: =IF(ISNUMBER(L50),1,0) | P50: =IF(O50=1,L50,0) | Q50: =M50*O50 | R50: =SUM(Q14:Q49) | S50: =IF(OR($A50="",R50<MIN_OBS_ROLL),"",(SUMPRODUCT(Q14:Q49,N14:N49,P14:P49)/R50-SUMPRODUCT(Q14:Q49,N14:N49)/R50*SUMPRODUCT(Q14:Q49,P14:P49)/R50)*R50/(R50-1)) | T50: =SUM(O14:O49) | U50: =IF(OR($A50="",T50<MIN_OBS_ROLL),"",SUMPRODUCT(O14:O49,(P14:P49-SUMPRODUCT(O14:O49,P14:P49)/T50)^2)/(T50-1)) | V50: =IF(OR(S50="",U50=""),"",S50/U50) | W50: =IF(AND(ISNUMBER(K50),ISNUMBER(L50),ISNUMBER(V50)),K50-V50*L50,"") | X50: =IF(OR($A50="",NOT(ISNUMBER(Datos!H50)),NOT(ISNUMBER(Datos!H49))),"",LN(Datos!H50)-LN(Datos!H49)) | Y50: =IF(ISNUMBER(W50),1,0) | Z50: =IF(Y50=1,W50,0) | AA50: =IF(ISNUMBER(X50),1,0) | AB50: =IF(AA50=1,X50,0) | AC50: =Y50*AA50 | AD50: =SUM(AC14:AC49) | AE50: =IF(OR($A50="",AD50<MIN_OBS_ROLL),"",(SUMPRODUCT(AC14:AC49,Z14:Z49,AB14:AB49)/AD50-SUMPRODUCT(AC14:AC49,Z14:Z49)/AD50*SUMPRODUCT(AC14:AC49,AB14:AB49)/AD50)*AD50/(AD50-1)) | AF50: =SUM(AA14:AA49) | AG50: =IF(OR($A50="",AF50<MIN_OBS_ROLL),"",SUMPRODUCT(AA14:AA49,(AB14:AB49-SUMPRODUCT(AA14:AA49,AB14:AB49)/AF50)^2)/(AF50-1)) | AH50: =SUM(Y14:Y49) | AI50: =IF(OR($A50="",AH50<MIN_OBS_ROLL),"",SUMPRODUCT(Y14:Y49,Z14:Z49)/AH50) | AJ50: =IF(OR($A50="",AF50<MIN_OBS_ROLL),"",SUMPRODUCT(AA14:AA49,AB14:AB49)/AF50) | AK50: =IF(OR(AE50="",AG50=""),"",AE50/AG50) | AL50: =IF(OR(AI50="",AK50="",AJ50=""),"",AI50-AK50*AJ50) | AM50: =IF(AND(ISNUMBER(W50),ISNUMBER(X50),ISNUMBER(AK50),ISNUMBER(AL50)),W50-(AL50+AK50*X50),"") | AN50: =IF(ISNUMBER(AM50),1,0) | AO50: =IF(AN50=1,AM50,0) | AP50: =IF(SUM(AN48:AN50)=3,SUM(AO48:AO50),"") | AQ50: =IF(ISNUMBER(AP50),1,0) | AR50: =IF(AQ50=1,AP50,0) | AS50: =SUM(AQ$5:AQ50) | AT50: =IF(AS50>=MIN_OBS_Z,SUMPRODUCT(AQ$5:AQ50,AR$5:AR50)/AS50,"") | AU50: =IF(AS50>=MIN_OBS_Z,SQRT(SUMPRODUCT(AQ$5:AQ50,(AR$5:AR50-AT50)^2)/(AS50-1)),"") | AV50: =IF(AND(AQ50=1,ISNUMBER(AT50)),MAX(-Z_CLIP,MIN(Z_CLIP,(AR50-AT50)/AU50)),"") | AW50: =IF(ISNUMBER(AV50),-AV50,"") | AX50: =IF(ISNUMBER(AW50),1+AMPLITUD*TANH(AW50),"") | AY50: =IF($A50="","",IF(COUNT(AX48:AX50)>0,AVERAGE(AX48:AX50),"")) | AZ50: =IF(ISNUMBER(AY50),AY50-1,"") | BA50: =IF(AND(ISNUMBER(AZ49),ISNUMBER(W50)),AZ49*W_BANCOS*W50,"") | BB50: =IF(AND(ISNUMBER(AZ49),ISNUMBER(AZ48)),ABS(AZ49-AZ48)*W_BANCOS*COSTO,0) | BC50: =IF(ISNUMBER(BA50),BA50-BB50,"") | BD50: =IF(ISNUMBER(BC50),IF(A50<=FECHA_ERA,"A","B"),"") | BE50: =IF(BD50="A",BC50,"") | BF50: =IF(BD50="B",BC50,"") | BG50: =IF(AND(ISNUMBER(BC50),ISNUMBER(A50)),IF(A50>=INICIO_VIVO,1,0),0) | BH50: =IF(BG50=1,BC50,"") | BI50: =IF(ISNUMBER(AY50),ROW(),0) | BJ50: =IF(ISNUMBER(BC50),SUM(BC$5:BC50)*10000,NA()) | BK50: =IF(BG50=1,SUM(BH$5:BH50)*10000,NA()) | BL50: =IF(ISNUMBER(AY50),AY50,NA())
A51: =IF(Datos!A51="","",Datos!A51) | B51: =IF(OR($A51="",NOT(ISNUMBER(Datos!B51)),NOT(ISNUMBER(Datos!B50))),"",Datos!B51/Datos!B50-1) | C51: =IF(OR($A51="",NOT(ISNUMBER(Datos!C51)),NOT(ISNUMBER(Datos!C50))),"",Datos!C51/Datos!C50-1) | D51: =IF(OR($A51="",NOT(ISNUMBER(Datos!D51)),NOT(ISNUMBER(Datos!D50))),"",Datos!D51/Datos!D50-1) | E51: =IF(OR($A51="",NOT(ISNUMBER(Datos!E51)),NOT(ISNUMBER(Datos!E50))),"",Datos!E51/Datos!E50-1) | F51: =IF($A51="","",COUNT(B51:E51)) | G51: =IF($A51="","",IF(F51>=MIN_BANCOS,AVERAGE(B51:E51),"")) | H51: =IF(OR($A51="",NOT(ISNUMBER(Datos!F51)),NOT(ISNUMBER(Datos!F50))),"",Datos!F51/Datos!F50-1) | I51: =IF($A51="","",IF(ISNUMBER(Datos!G51),Datos!G51,I50)) | J51: =IF($A51="","",IF(ISNUMBER(I50),LN(1+I50/100/12),0)) | K51: =IF(ISNUMBER(G51),LN(1+G51)-J51,"") | L51: =IF(ISNUMBER(H51),LN(1+H51)-J51,"") | M51: =IF(ISNUMBER(K51),1,0) | N51: =IF(M51=1,K51,0) | O51: =IF(ISNUMBER(L51),1,0) | P51: =IF(O51=1,L51,0) | Q51: =M51*O51 | R51: =SUM(Q15:Q50) | S51: =IF(OR($A51="",R51<MIN_OBS_ROLL),"",(SUMPRODUCT(Q15:Q50,N15:N50,P15:P50)/R51-SUMPRODUCT(Q15:Q50,N15:N50)/R51*SUMPRODUCT(Q15:Q50,P15:P50)/R51)*R51/(R51-1)) | T51: =SUM(O15:O50) | U51: =IF(OR($A51="",T51<MIN_OBS_ROLL),"",SUMPRODUCT(O15:O50,(P15:P50-SUMPRODUCT(O15:O50,P15:P50)/T51)^2)/(T51-1)) | V51: =IF(OR(S51="",U51=""),"",S51/U51) | W51: =IF(AND(ISNUMBER(K51),ISNUMBER(L51),ISNUMBER(V51)),K51-V51*L51,"") | X51: =IF(OR($A51="",NOT(ISNUMBER(Datos!H51)),NOT(ISNUMBER(Datos!H50))),"",LN(Datos!H51)-LN(Datos!H50)) | Y51: =IF(ISNUMBER(W51),1,0) | Z51: =IF(Y51=1,W51,0) | AA51: =IF(ISNUMBER(X51),1,0) | AB51: =IF(AA51=1,X51,0) | AC51: =Y51*AA51 | AD51: =SUM(AC15:AC50) | AE51: =IF(OR($A51="",AD51<MIN_OBS_ROLL),"",(SUMPRODUCT(AC15:AC50,Z15:Z50,AB15:AB50)/AD51-SUMPRODUCT(AC15:AC50,Z15:Z50)/AD51*SUMPRODUCT(AC15:AC50,AB15:AB50)/AD51)*AD51/(AD51-1)) | AF51: =SUM(AA15:AA50) | AG51: =IF(OR($A51="",AF51<MIN_OBS_ROLL),"",SUMPRODUCT(AA15:AA50,(AB15:AB50-SUMPRODUCT(AA15:AA50,AB15:AB50)/AF51)^2)/(AF51-1)) | AH51: =SUM(Y15:Y50) | AI51: =IF(OR($A51="",AH51<MIN_OBS_ROLL),"",SUMPRODUCT(Y15:Y50,Z15:Z50)/AH51) | AJ51: =IF(OR($A51="",AF51<MIN_OBS_ROLL),"",SUMPRODUCT(AA15:AA50,AB15:AB50)/AF51) | AK51: =IF(OR(AE51="",AG51=""),"",AE51/AG51) | AL51: =IF(OR(AI51="",AK51="",AJ51=""),"",AI51-AK51*AJ51) | AM51: =IF(AND(ISNUMBER(W51),ISNUMBER(X51),ISNUMBER(AK51),ISNUMBER(AL51)),W51-(AL51+AK51*X51),"") | AN51: =IF(ISNUMBER(AM51),1,0) | AO51: =IF(AN51=1,AM51,0) | AP51: =IF(SUM(AN49:AN51)=3,SUM(AO49:AO51),"") | AQ51: =IF(ISNUMBER(AP51),1,0) | AR51: =IF(AQ51=1,AP51,0) | AS51: =SUM(AQ$5:AQ51) | AT51: =IF(AS51>=MIN_OBS_Z,SUMPRODUCT(AQ$5:AQ51,AR$5:AR51)/AS51,"") | AU51: =IF(AS51>=MIN_OBS_Z,SQRT(SUMPRODUCT(AQ$5:AQ51,(AR$5:AR51-AT51)^2)/(AS51-1)),"") | AV51: =IF(AND(AQ51=1,ISNUMBER(AT51)),MAX(-Z_CLIP,MIN(Z_CLIP,(AR51-AT51)/AU51)),"") | AW51: =IF(ISNUMBER(AV51),-AV51,"") | AX51: =IF(ISNUMBER(AW51),1+AMPLITUD*TANH(AW51),"") | AY51: =IF($A51="","",IF(COUNT(AX49:AX51)>0,AVERAGE(AX49:AX51),"")) | AZ51: =IF(ISNUMBER(AY51),AY51-1,"") | BA51: =IF(AND(ISNUMBER(AZ50),ISNUMBER(W51)),AZ50*W_BANCOS*W51,"") | BB51: =IF(AND(ISNUMBER(AZ50),ISNUMBER(AZ49)),ABS(AZ50-AZ49)*W_BANCOS*COSTO,0) | BC51: =IF(ISNUMBER(BA51),BA51-BB51,"") | BD51: =IF(ISNUMBER(BC51),IF(A51<=FECHA_ERA,"A","B"),"") | BE51: =IF(BD51="A",BC51,"") | BF51: =IF(BD51="B",BC51,"") | BG51: =IF(AND(ISNUMBER(BC51),ISNUMBER(A51)),IF(A51>=INICIO_VIVO,1,0),0) | BH51: =IF(BG51=1,BC51,"") | BI51: =IF(ISNUMBER(AY51),ROW(),0) | BJ51: =IF(ISNUMBER(BC51),SUM(BC$5:BC51)*10000,NA()) | BK51: =IF(BG51=1,SUM(BH$5:BH51)*10000,NA()) | BL51: =IF(ISNUMBER(AY51),AY51,NA())
A52: =IF(Datos!A52="","",Datos!A52) | B52: =IF(OR($A52="",NOT(ISNUMBER(Datos!B52)),NOT(ISNUMBER(Datos!B51))),"",Datos!B52/Datos!B51-1) | C52: =IF(OR($A52="",NOT(ISNUMBER(Datos!C52)),NOT(ISNUMBER(Datos!C51))),"",Datos!C52/Datos!C51-1) | D52: =IF(OR($A52="",NOT(ISNUMBER(Datos!D52)),NOT(ISNUMBER(Datos!D51))),"",Datos!D52/Datos!D51-1) | E52: =IF(OR($A52="",NOT(ISNUMBER(Datos!E52)),NOT(ISNUMBER(Datos!E51))),"",Datos!E52/Datos!E51-1) | F52: =IF($A52="","",COUNT(B52:E52)) | G52: =IF($A52="","",IF(F52>=MIN_BANCOS,AVERAGE(B52:E52),"")) | H52: =IF(OR($A52="",NOT(ISNUMBER(Datos!F52)),NOT(ISNUMBER(Datos!F51))),"",Datos!F52/Datos!F51-1) | I52: =IF($A52="","",IF(ISNUMBER(Datos!G52),Datos!G52,I51)) | J52: =IF($A52="","",IF(ISNUMBER(I51),LN(1+I51/100/12),0)) | K52: =IF(ISNUMBER(G52),LN(1+G52)-J52,"") | L52: =IF(ISNUMBER(H52),LN(1+H52)-J52,"") | M52: =IF(ISNUMBER(K52),1,0) | N52: =IF(M52=1,K52,0) | O52: =IF(ISNUMBER(L52),1,0) | P52: =IF(O52=1,L52,0) | Q52: =M52*O52 | R52: =SUM(Q16:Q51) | S52: =IF(OR($A52="",R52<MIN_OBS_ROLL),"",(SUMPRODUCT(Q16:Q51,N16:N51,P16:P51)/R52-SUMPRODUCT(Q16:Q51,N16:N51)/R52*SUMPRODUCT(Q16:Q51,P16:P51)/R52)*R52/(R52-1)) | T52: =SUM(O16:O51) | U52: =IF(OR($A52="",T52<MIN_OBS_ROLL),"",SUMPRODUCT(O16:O51,(P16:P51-SUMPRODUCT(O16:O51,P16:P51)/T52)^2)/(T52-1)) | V52: =IF(OR(S52="",U52=""),"",S52/U52) | W52: =IF(AND(ISNUMBER(K52),ISNUMBER(L52),ISNUMBER(V52)),K52-V52*L52,"") | X52: =IF(OR($A52="",NOT(ISNUMBER(Datos!H52)),NOT(ISNUMBER(Datos!H51))),"",LN(Datos!H52)-LN(Datos!H51)) | Y52: =IF(ISNUMBER(W52),1,0) | Z52: =IF(Y52=1,W52,0) | AA52: =IF(ISNUMBER(X52),1,0) | AB52: =IF(AA52=1,X52,0) | AC52: =Y52*AA52 | AD52: =SUM(AC16:AC51) | AE52: =IF(OR($A52="",AD52<MIN_OBS_ROLL),"",(SUMPRODUCT(AC16:AC51,Z16:Z51,AB16:AB51)/AD52-SUMPRODUCT(AC16:AC51,Z16:Z51)/AD52*SUMPRODUCT(AC16:AC51,AB16:AB51)/AD52)*AD52/(AD52-1)) | AF52: =SUM(AA16:AA51) | AG52: =IF(OR($A52="",AF52<MIN_OBS_ROLL),"",SUMPRODUCT(AA16:AA51,(AB16:AB51-SUMPRODUCT(AA16:AA51,AB16:AB51)/AF52)^2)/(AF52-1)) | AH52: =SUM(Y16:Y51) | AI52: =IF(OR($A52="",AH52<MIN_OBS_ROLL),"",SUMPRODUCT(Y16:Y51,Z16:Z51)/AH52) | AJ52: =IF(OR($A52="",AF52<MIN_OBS_ROLL),"",SUMPRODUCT(AA16:AA51,AB16:AB51)/AF52) | AK52: =IF(OR(AE52="",AG52=""),"",AE52/AG52) | AL52: =IF(OR(AI52="",AK52="",AJ52=""),"",AI52-AK52*AJ52) | AM52: =IF(AND(ISNUMBER(W52),ISNUMBER(X52),ISNUMBER(AK52),ISNUMBER(AL52)),W52-(AL52+AK52*X52),"") | AN52: =IF(ISNUMBER(AM52),1,0) | AO52: =IF(AN52=1,AM52,0) | AP52: =IF(SUM(AN50:AN52)=3,SUM(AO50:AO52),"") | AQ52: =IF(ISNUMBER(AP52),1,0) | AR52: =IF(AQ52=1,AP52,0) | AS52: =SUM(AQ$5:AQ52) | AT52: =IF(AS52>=MIN_OBS_Z,SUMPRODUCT(AQ$5:AQ52,AR$5:AR52)/AS52,"") | AU52: =IF(AS52>=MIN_OBS_Z,SQRT(SUMPRODUCT(AQ$5:AQ52,(AR$5:AR52-AT52)^2)/(AS52-1)),"") | AV52: =IF(AND(AQ52=1,ISNUMBER(AT52)),MAX(-Z_CLIP,MIN(Z_CLIP,(AR52-AT52)/AU52)),"") | AW52: =IF(ISNUMBER(AV52),-AV52,"") | AX52: =IF(ISNUMBER(AW52),1+AMPLITUD*TANH(AW52),"") | AY52: =IF($A52="","",IF(COUNT(AX50:AX52)>0,AVERAGE(AX50:AX52),"")) | AZ52: =IF(ISNUMBER(AY52),AY52-1,"") | BA52: =IF(AND(ISNUMBER(AZ51),ISNUMBER(W52)),AZ51*W_BANCOS*W52,"") | BB52: =IF(AND(ISNUMBER(AZ51),ISNUMBER(AZ50)),ABS(AZ51-AZ50)*W_BANCOS*COSTO,0) | BC52: =IF(ISNUMBER(BA52),BA52-BB52,"") | BD52: =IF(ISNUMBER(BC52),IF(A52<=FECHA_ERA,"A","B"),"") | BE52: =IF(BD52="A",BC52,"") | BF52: =IF(BD52="B",BC52,"") | BG52: =IF(AND(ISNUMBER(BC52),ISNUMBER(A52)),IF(A52>=INICIO_VIVO,1,0),0) | BH52: =IF(BG52=1,BC52,"") | BI52: =IF(ISNUMBER(AY52),ROW(),0) | BJ52: =IF(ISNUMBER(BC52),SUM(BC$5:BC52)*10000,NA()) | BK52: =IF(BG52=1,SUM(BH$5:BH52)*10000,NA()) | BL52: =IF(ISNUMBER(AY52),AY52,NA())
... A352: =IF(Datos!A352="","",Datos!A352) | B352: =IF(OR($A352="",NOT(ISNUMBER(Datos!B352)),NOT(ISNUMBER(Datos!B351))),"",Datos!B352/Datos!B351-1) | C352: =IF(OR($A352="",NOT(ISNUMBER(Datos!C352)),NOT(ISNUMBER(Datos!C351))),"",Datos!C352/Datos!C351-1) | D352: =IF(OR($A352="",NOT(ISNUMBER(Datos!D352)),NOT(ISNUMBER(Datos!D351))),"",Datos!D352/Datos!D351-1) | E352: =IF(OR($A352="",NOT(ISNUMBER(Datos!E352)),NOT(ISNUMBER(Datos!E351))),"",Datos!E352/Datos!E351-1) | F352: =IF($A352="","",COUNT(B352:E352)) | G352: =IF($A352="","",IF(F352>=MIN_BANCOS,AVERAGE(B352:E352),"")) | H352: =IF(OR($A352="",NOT(ISNUMBER(Datos!F352)),NOT(ISNUMBER(Datos!F351))),"",Datos!F352/Datos!F351-1) | I352: =IF($A352="","",IF(ISNUMBER(Datos!G352),Datos!G352,I351)) | J352: =IF($A352="","",IF(ISNUMBER(I351),LN(1+I351/100/12),0)) | K352: =IF(ISNUMBER(G352),LN(1+G352)-J352,"") | L352: =IF(ISNUMBER(H352),LN(1+H352)-J352,"") | M352: =IF(ISNUMBER(K352),1,0) | N352: =IF(M352=1,K352,0) | O352: =IF(ISNUMBER(L352),1,0) | P352: =IF(O352=1,L352,0) | Q352: =M352*O352 | R352: =SUM(Q316:Q351) | S352: =IF(OR($A352="",R352<MIN_OBS_ROLL),"",(SUMPRODUCT(Q316:Q351,N316:N351,P316:P351)/R352-SUMPRODUCT(Q316:Q351,N316:N351)/R352*SUMPRODUCT(Q316:Q351,P316:P351)/R352)*R352/(R352-1)) | T352: =SUM(O316:O351) | U352: =IF(OR($A352="",T352<MIN_OBS_ROLL),"",SUMPRODUCT(O316:O351,(P316:P351-SUMPRODUCT(O316:O351,P316:P351)/T352)^2)/(T352-1)) | V352: =IF(OR(S352="",U352=""),"",S352/U352) | W352: =IF(AND(ISNUMBER(K352),ISNUMBER(L352),ISNUMBER(V352)),K352-V352*L352,"") | X352: =IF(OR($A352="",NOT(ISNUMBER(Datos!H352)),NOT(ISNUMBER(Datos!H351))),"",LN(Datos!H352)-LN(Datos!H351)) | Y352: =IF(ISNUMBER(W352),1,0) | Z352: =IF(Y352=1,W352,0) | AA352: =IF(ISNUMBER(X352),1,0) | AB352: =IF(AA352=1,X352,0) | AC352: =Y352*AA352 | AD352: =SUM(AC316:AC351) | AE352: =IF(OR($A352="",AD352<MIN_OBS_ROLL),"",(SUMPRODUCT(AC316:AC351,Z316:Z351,AB316:AB351)/AD352-SUMPRODUCT(AC316:AC351,Z316:Z351)/AD352*SUMPRODUCT(AC316:AC351,AB316:AB351)/AD352)*AD352/(AD352-1)) | AF352: =SUM(AA316:AA351) | AG352: =IF(OR($A352="",AF352<MIN_OBS_ROLL),"",SUMPRODUCT(AA316:AA351,(AB316:AB351-SUMPRODUCT(AA316:AA351,AB316:AB351)/AF352)^2)/(AF352-1)) | AH352: =SUM(Y316:Y351) | AI352: =IF(OR($A352="",AH352<MIN_OBS_ROLL),"",SUMPRODUCT(Y316:Y351,Z316:Z351)/AH352) | AJ352: =IF(OR($A352="",AF352<MIN_OBS_ROLL),"",SUMPRODUCT(AA316:AA351,AB316:AB351)/AF352) | AK352: =IF(OR(AE352="",AG352=""),"",AE352/AG352) | AL352: =IF(OR(AI352="",AK352="",AJ352=""),"",AI352-AK352*AJ352) | AM352: =IF(AND(ISNUMBER(W352),ISNUMBER(X352),ISNUMBER(AK352),ISNUMBER(AL352)),W352-(AL352+AK352*X352),"") | AN352: =IF(ISNUMBER(AM352),1,0) | AO352: =IF(AN352=1,AM352,0) | AP352: =IF(SUM(AN350:AN352)=3,SUM(AO350:AO352),"") | AQ352: =IF(ISNUMBER(AP352),1,0) | AR352: =IF(AQ352=1,AP352,0) | AS352: =SUM(AQ$5:AQ352) | AT352: =IF(AS352>=MIN_OBS_Z,SUMPRODUCT(AQ$5:AQ352,AR$5:AR352)/AS352,"") | AU352: =IF(AS352>=MIN_OBS_Z,SQRT(SUMPRODUCT(AQ$5:AQ352,(AR$5:AR352-AT352)^2)/(AS352-1)),"") | AV352: =IF(AND(AQ352=1,ISNUMBER(AT352)),MAX(-Z_CLIP,MIN(Z_CLIP,(AR352-AT352)/AU352)),"") | AW352: =IF(ISNUMBER(AV352),-AV352,"") | AX352: =IF(ISNUMBER(AW352),1+AMPLITUD*TANH(AW352),"") | AY352: =IF($A352="","",IF(COUNT(AX350:AX352)>0,AVERAGE(AX350:AX352),"")) | AZ352: =IF(ISNUMBER(AY352),AY352-1,"") | BA352: =IF(AND(ISNUMBER(AZ351),ISNUMBER(W352)),AZ351*W_BANCOS*W352,"") | BB352: =IF(AND(ISNUMBER(AZ351),ISNUMBER(AZ350)),ABS(AZ351-AZ350)*W_BANCOS*COSTO,0) | BC352: =IF(ISNUMBER(BA352),BA352-BB352,"") | BD352: =IF(ISNUMBER(BC352),IF(A352<=FECHA_ERA,"A","B"),"") | BE352: =IF(BD352="A",BC352,"") | BF352: =IF(BD352="B",BC352,"") | BG352: =IF(AND(ISNUMBER(BC352),ISNUMBER(A352)),IF(A352>=INICIO_VIVO,1,0),0) | BH352: =IF(BG352=1,BC352,"") | BI352: =IF(ISNUMBER(AY352),ROW(),0) | BJ352: =IF(ISNUMBER(BC352),SUM(BC$5:BC352)*10000,NA()) | BK352: =IF(BG352=1,SUM(BH$5:BH352)*10000,NA()) | BL352: =IF(ISNUMBER(AY352),AY352,NA())

Sheet Validacion
A1: Validación contra Python (pandas) — historia hasta 2026-09-30
A2: Valores de Python en azul (fijos). Diferencia = |Excel − Python|; 1 si uno existe y el otro no. Tolerancia: 1e-9.
B3: Máx |dif| T2 | E3: Máx |dif| BETA | H3: Máx |dif| B_E | K3: Máx |dif| A_E | N3: Máx |dif| GAP | Q3: Máx |dif| SCORE | T3: Máx |dif| M | W3: Máx |dif| M3 | Z3: Máx |dif| NETO
B4: =MAX(D7:D279) | C4: =IF(B4<=1E-9,"OK","REVISAR") | E4: =MAX(G7:G279) | F4: =IF(E4<=1E-9,"OK","REVISAR") | H4: =MAX(J7:J279) | I4: =IF(H4<=1E-9,"OK","REVISAR") | K4: =MAX(M7:M279) | L4: =IF(K4<=1E-9,"OK","REVISAR") | N4: =MAX(P7:P279) | O4: =IF(N4<=1E-9,"OK","REVISAR") | Q4: =MAX(S7:S279) | R4: =IF(Q4<=1E-9,"OK","REVISAR") | T4: =MAX(V7:V279) | U4: =IF(T4<=1E-9,"OK","REVISAR") | W4: =MAX(Y7:Y279) | X4: =IF(W4<=1E-9,"OK","REVISAR") | Z4: =MAX(AB7:AB279) | AA4: =IF(Z4<=1E-9,"OK","REVISAR")
A6: Fecha | B6: T2 Python | C6: T2 Excel | D6: T2 |dif| | E6: BETA Python | F6: BETA Excel | G6: BETA |dif| | H6: B_E Python | I6: B_E Excel | J6: B_E |dif| | K6: A_E Python | L6: A_E Excel | M6: A_E |dif| | N6: GAP Python | O6: GAP Excel | P6: GAP |dif| | Q6: SCORE Python | R6: SCORE Excel | S6: SCORE |dif| | T6: M Python | U6: M Excel | V6: M |dif| | W6: M3 Python | X6: M3 Excel | Y6: M3 |dif| | Z6: NETO Python | AA6: NETO Excel | AB6: NETO |dif|
A7: =Calculo!A5 | C7: =Calculo!W5 | D7: =IF(AND(ISNUMBER(B7),ISNUMBER(C7)),ABS(C7-B7),IF(ISNUMBER(B7)=ISNUMBER(C7),0,1)) | F7: =Calculo!V5 | G7: =IF(AND(ISNUMBER(E7),ISNUMBER(F7)),ABS(F7-E7),IF(ISNUMBER(E7)=ISNUMBER(F7),0,1)) | I7: =Calculo!AK5 | J7: =IF(AND(ISNUMBER(H7),ISNUMBER(I7)),ABS(I7-H7),IF(ISNUMBER(H7)=ISNUMBER(I7),0,1)) | L7: =Calculo!AL5 | M7: =IF(AND(ISNUMBER(K7),ISNUMBER(L7)),ABS(L7-K7),IF(ISNUMBER(K7)=ISNUMBER(L7),0,1)) | O7: =Calculo!AP5 | P7: =IF(AND(ISNUMBER(N7),ISNUMBER(O7)),ABS(O7-N7),IF(ISNUMBER(N7)=ISNUMBER(O7),0,1)) | R7: =Calculo!AW5 | S7: =IF(AND(ISNUMBER(Q7),ISNUMBER(R7)),ABS(R7-Q7),IF(ISNUMBER(Q7)=ISNUMBER(R7),0,1)) | U7: =Calculo!AX5 | V7: =IF(AND(ISNUMBER(T7),ISNUMBER(U7)),ABS(U7-T7),IF(ISNUMBER(T7)=ISNUMBER(U7),0,1)) | X7: =Calculo!AY5 | Y7: =IF(AND(ISNUMBER(W7),ISNUMBER(X7)),ABS(X7-W7),IF(ISNUMBER(W7)=ISNUMBER(X7),0,1)) | AA7: =Calculo!BC5 | AB7: =IF(AND(ISNUMBER(Z7),ISNUMBER(AA7)),ABS(AA7-Z7),IF(ISNUMBER(Z7)=ISNUMBER(AA7),0,1))
A8: =Calculo!A6 | C8: =Calculo!W6 | D8: =IF(AND(ISNUMBER(B8),ISNUMBER(C8)),ABS(C8-B8),IF(ISNUMBER(B8)=ISNUMBER(C8),0,1)) | F8: =Calculo!V6 | G8: =IF(AND(ISNUMBER(E8),ISNUMBER(F8)),ABS(F8-E8),IF(ISNUMBER(E8)=ISNUMBER(F8),0,1)) | I8: =Calculo!AK6 | J8: =IF(AND(ISNUMBER(H8),ISNUMBER(I8)),ABS(I8-H8),IF(ISNUMBER(H8)=ISNUMBER(I8),0,1)) | L8: =Calculo!AL6 | M8: =IF(AND(ISNUMBER(K8),ISNUMBER(L8)),ABS(L8-K8),IF(ISNUMBER(K8)=ISNUMBER(L8),0,1)) | O8: =Calculo!AP6 | P8: =IF(AND(ISNUMBER(N8),ISNUMBER(O8)),ABS(O8-N8),IF(ISNUMBER(N8)=ISNUMBER(O8),0,1)) | R8: =Calculo!AW6 | S8: =IF(AND(ISNUMBER(Q8),ISNUMBER(R8)),ABS(R8-Q8),IF(ISNUMBER(Q8)=ISNUMBER(R8),0,1)) | U8: =Calculo!AX6 | V8: =IF(AND(ISNUMBER(T8),ISNUMBER(U8)),ABS(U8-T8),IF(ISNUMBER(T8)=ISNUMBER(U8),0,1)) | X8: =Calculo!AY6 | Y8: =IF(AND(ISNUMBER(W8),ISNUMBER(X8)),ABS(X8-W8),IF(ISNUMBER(W8)=ISNUMBER(X8),0,1)) | AA8: =Calculo!BC6 | AB8: =IF(AND(ISNUMBER(Z8),ISNUMBER(AA8)),ABS(AA8-Z8),IF(ISNUMBER(Z8)=ISNUMBER(AA8),0,1))
A9: =Calculo!A7 | C9: =Calculo!W7 | D9: =IF(AND(ISNUMBER(B9),ISNUMBER(C9)),ABS(C9-B9),IF(ISNUMBER(B9)=ISNUMBER(C9),0,1)) | F9: =Calculo!V7 | G9: =IF(AND(ISNUMBER(E9),ISNUMBER(F9)),ABS(F9-E9),IF(ISNUMBER(E9)=ISNUMBER(F9),0,1)) | I9: =Calculo!AK7 | J9: =IF(AND(ISNUMBER(H9),ISNUMBER(I9)),ABS(I9-H9),IF(ISNUMBER(H9)=ISNUMBER(I9),0,1)) | L9: =Calculo!AL7 | M9: =IF(AND(ISNUMBER(K9),ISNUMBER(L9)),ABS(L9-K9),IF(ISNUMBER(K9)=ISNUMBER(L9),0,1)) | O9: =Calculo!AP7 | P9: =IF(AND(ISNUMBER(N9),ISNUMBER(O9)),ABS(O9-N9),IF(ISNUMBER(N9)=ISNUMBER(O9),0,1)) | R9: =Calculo!AW7 | S9: =IF(AND(ISNUMBER(Q9),ISNUMBER(R9)),ABS(R9-Q9),IF(ISNUMBER(Q9)=ISNUMBER(R9),0,1)) | U9: =Calculo!AX7 | V9: =IF(AND(ISNUMBER(T9),ISNUMBER(U9)),ABS(U9-T9),IF(ISNUMBER(T9)=ISNUMBER(U9),0,1)) | X9: =Calculo!AY7 | Y9: =IF(AND(ISNUMBER(W9),ISNUMBER(X9)),ABS(X9-W9),IF(ISNUMBER(W9)=ISNUMBER(X9),0,1)) | AA9: =Calculo!BC7 | AB9: =IF(AND(ISNUMBER(Z9),ISNUMBER(AA9)),ABS(AA9-Z9),IF(ISNUMBER(Z9)=ISNUMBER(AA9),0,1))
A10: =Calculo!A8 | C10: =Calculo!W8 | D10: =IF(AND(ISNUMBER(B10),ISNUMBER(C10)),ABS(C10-B10),IF(ISNUMBER(B10)=ISNUMBER(C10),0,1)) | F10: =Calculo!V8 | G10: =IF(AND(ISNUMBER(E10),ISNUMBER(F10)),ABS(F10-E10),IF(ISNUMBER(E10)=ISNUMBER(F10),0,1)) | I10: =Calculo!AK8 | J10: =IF(AND(ISNUMBER(H10),ISNUMBER(I10)),ABS(I10-H10),IF(ISNUMBER(H10)=ISNUMBER(I10),0,1)) | L10: =Calculo!AL8 | M10: =IF(AND(ISNUMBER(K10),ISNUMBER(L10)),ABS(L10-K10),IF(ISNUMBER(K10)=ISNUMBER(L10),0,1)) | O10: =Calculo!AP8 | P10: =IF(AND(ISNUMBER(N10),ISNUMBER(O10)),ABS(O10-N10),IF(ISNUMBER(N10)=ISNUMBER(O10),0,1)) | R10: =Calculo!AW8 | S10: =IF(AND(ISNUMBER(Q10),ISNUMBER(R10)),ABS(R10-Q10),IF(ISNUMBER(Q10)=ISNUMBER(R10),0,1)) | U10: =Calculo!AX8 | V10: =IF(AND(ISNUMBER(T10),ISNUMBER(U10)),ABS(U10-T10),IF(ISNUMBER(T10)=ISNUMBER(U10),0,1)) | X10: =Calculo!AY8 | Y10: =IF(AND(ISNUMBER(W10),ISNUMBER(X10)),ABS(X10-W10),IF(ISNUMBER(W10)=ISNUMBER(X10),0,1)) | AA10: =Calculo!BC8 | AB10: =IF(AND(ISNUMBER(Z10),ISNUMBER(AA10)),ABS(AA10-Z10),IF(ISNUMBER(Z10)=ISNUMBER(AA10),0,1))
A11: =Calculo!A9 | C11: =Calculo!W9 | D11: =IF(AND(ISNUMBER(B11),ISNUMBER(C11)),ABS(C11-B11),IF(ISNUMBER(B11)=ISNUMBER(C11),0,1)) | F11: =Calculo!V9 | G11: =IF(AND(ISNUMBER(E11),ISNUMBER(F11)),ABS(F11-E11),IF(ISNUMBER(E11)=ISNUMBER(F11),0,1)) | I11: =Calculo!AK9 | J11: =IF(AND(ISNUMBER(H11),ISNUMBER(I11)),ABS(I11-H11),IF(ISNUMBER(H11)=ISNUMBER(I11),0,1)) | L11: =Calculo!AL9 | M11: =IF(AND(ISNUMBER(K11),ISNUMBER(L11)),ABS(L11-K11),IF(ISNUMBER(K11)=ISNUMBER(L11),0,1)) | O11: =Calculo!AP9 | P11: =IF(AND(ISNUMBER(N11),ISNUMBER(O11)),ABS(O11-N11),IF(ISNUMBER(N11)=ISNUMBER(O11),0,1)) | R11: =Calculo!AW9 | S11: =IF(AND(ISNUMBER(Q11),ISNUMBER(R11)),ABS(R11-Q11),IF(ISNUMBER(Q11)=ISNUMBER(R11),0,1)) | U11: =Calculo!AX9 | V11: =IF(AND(ISNUMBER(T11),ISNUMBER(U11)),ABS(U11-T11),IF(ISNUMBER(T11)=ISNUMBER(U11),0,1)) | X11: =Calculo!AY9 | Y11: =IF(AND(ISNUMBER(W11),ISNUMBER(X11)),ABS(X11-W11),IF(ISNUMBER(W11)=ISNUMBER(X11),0,1)) | AA11: =Calculo!BC9 | AB11: =IF(AND(ISNUMBER(Z11),ISNUMBER(AA11)),ABS(AA11-Z11),IF(ISNUMBER(Z11)=ISNUMBER(AA11),0,1))
A12: =Calculo!A10 | C12: =Calculo!W10 | D12: =IF(AND(ISNUMBER(B12),ISNUMBER(C12)),ABS(C12-B12),IF(ISNUMBER(B12)=ISNUMBER(C12),0,1)) | F12: =Calculo!V10 | G12: =IF(AND(ISNUMBER(E12),ISNUMBER(F12)),ABS(F12-E12),IF(ISNUMBER(E12)=ISNUMBER(F12),0,1)) | I12: =Calculo!AK10 | J12: =IF(AND(ISNUMBER(H12),ISNUMBER(I12)),ABS(I12-H12),IF(ISNUMBER(H12)=ISNUMBER(I12),0,1)) | L12: =Calculo!AL10 | M12: =IF(AND(ISNUMBER(K12),ISNUMBER(L12)),ABS(L12-K12),IF(ISNUMBER(K12)=ISNUMBER(L12),0,1)) | O12: =Calculo!AP10 | P12: =IF(AND(ISNUMBER(N12),ISNUMBER(O12)),ABS(O12-N12),IF(ISNUMBER(N12)=ISNUMBER(O12),0,1)) | R12: =Calculo!AW10 | S12: =IF(AND(ISNUMBER(Q12),ISNUMBER(R12)),ABS(R12-Q12),IF(ISNUMBER(Q12)=ISNUMBER(R12),0,1)) | U12: =Calculo!AX10 | V12: =IF(AND(ISNUMBER(T12),ISNUMBER(U12)),ABS(U12-T12),IF(ISNUMBER(T12)=ISNUMBER(U12),0,1)) | X12: =Calculo!AY10 | Y12: =IF(AND(ISNUMBER(W12),ISNUMBER(X12)),ABS(X12-W12),IF(ISNUMBER(W12)=ISNUMBER(X12),0,1)) | AA12: =Calculo!BC10 | AB12: =IF(AND(ISNUMBER(Z12),ISNUMBER(AA12)),ABS(AA12-Z12),IF(ISNUMBER(Z12)=ISNUMBER(AA12),0,1))
A13: =Calculo!A11 | C13: =Calculo!W11 | D13: =IF(AND(ISNUMBER(B13),ISNUMBER(C13)),ABS(C13-B13),IF(ISNUMBER(B13)=ISNUMBER(C13),0,1)) | F13: =Calculo!V11 | G13: =IF(AND(ISNUMBER(E13),ISNUMBER(F13)),ABS(F13-E13),IF(ISNUMBER(E13)=ISNUMBER(F13),0,1)) | I13: =Calculo!AK11 | J13: =IF(AND(ISNUMBER(H13),ISNUMBER(I13)),ABS(I13-H13),IF(ISNUMBER(H13)=ISNUMBER(I13),0,1)) | L13: =Calculo!AL11 | M13: =IF(AND(ISNUMBER(K13),ISNUMBER(L13)),ABS(L13-K13),IF(ISNUMBER(K13)=ISNUMBER(L13),0,1)) | O13: =Calculo!AP11 | P13: =IF(AND(ISNUMBER(N13),ISNUMBER(O13)),ABS(O13-N13),IF(ISNUMBER(N13)=ISNUMBER(O13),0,1)) | R13: =Calculo!AW11 | S13: =IF(AND(ISNUMBER(Q13),ISNUMBER(R13)),ABS(R13-Q13),IF(ISNUMBER(Q13)=ISNUMBER(R13),0,1)) | U13: =Calculo!AX11 | V13: =IF(AND(ISNUMBER(T13),ISNUMBER(U13)),ABS(U13-T13),IF(ISNUMBER(T13)=ISNUMBER(U13),0,1)) | X13: =Calculo!AY11 | Y13: =IF(AND(ISNUMBER(W13),ISNUMBER(X13)),ABS(X13-W13),IF(ISNUMBER(W13)=ISNUMBER(X13),0,1)) | AA13: =Calculo!BC11 | AB13: =IF(AND(ISNUMBER(Z13),ISNUMBER(AA13)),ABS(AA13-Z13),IF(ISNUMBER(Z13)=ISNUMBER(AA13),0,1))
A14: =Calculo!A12 | C14: =Calculo!W12 | D14: =IF(AND(ISNUMBER(B14),ISNUMBER(C14)),ABS(C14-B14),IF(ISNUMBER(B14)=ISNUMBER(C14),0,1)) | F14: =Calculo!V12 | G14: =IF(AND(ISNUMBER(E14),ISNUMBER(F14)),ABS(F14-E14),IF(ISNUMBER(E14)=ISNUMBER(F14),0,1)) | I14: =Calculo!AK12 | J14: =IF(AND(ISNUMBER(H14),ISNUMBER(I14)),ABS(I14-H14),IF(ISNUMBER(H14)=ISNUMBER(I14),0,1)) | L14: =Calculo!AL12 | M14: =IF(AND(ISNUMBER(K14),ISNUMBER(L14)),ABS(L14-K14),IF(ISNUMBER(K14)=ISNUMBER(L14),0,1)) | O14: =Calculo!AP12 | P14: =IF(AND(ISNUMBER(N14),ISNUMBER(O14)),ABS(O14-N14),IF(ISNUMBER(N14)=ISNUMBER(O14),0,1)) | R14: =Calculo!AW12 | S14: =IF(AND(ISNUMBER(Q14),ISNUMBER(R14)),ABS(R14-Q14),IF(ISNUMBER(Q14)=ISNUMBER(R14),0,1)) | U14: =Calculo!AX12 | V14: =IF(AND(ISNUMBER(T14),ISNUMBER(U14)),ABS(U14-T14),IF(ISNUMBER(T14)=ISNUMBER(U14),0,1)) | X14: =Calculo!AY12 | Y14: =IF(AND(ISNUMBER(W14),ISNUMBER(X14)),ABS(X14-W14),IF(ISNUMBER(W14)=ISNUMBER(X14),0,1)) | AA14: =Calculo!BC12 | AB14: =IF(AND(ISNUMBER(Z14),ISNUMBER(AA14)),ABS(AA14-Z14),IF(ISNUMBER(Z14)=ISNUMBER(AA14),0,1))
